package yyds.sniarbtej;

public final class ʽ extends ˍɫ {
  private static int ˍ = 1;
  
  private static int ʹō = 2;
  
  private final int ᐝᵣ;
  
  private int ᔪ;
  
  public final ˌх ᐨẏ;
  
  private int ʿλ;
  
  private int ˉｓ;
  
  private int ʿপ;
  
  private int ʻล;
  
  private int[] ᴵʖ;
  
  private ˌ ᐨẏ;
  
  private ˌ ˊ;
  
  private ʿপ ᐨẏ;
  
  private ʿপ ˊ;
  
  private int ˈے;
  
  private ʿᵉ ˊ;
  
  private int ـﭔ;
  
  private int ʼᵖ;
  
  private int ﾞǰ;
  
  private int ˊᵃ;
  
  private ʿᵉ ᴵʖ;
  
  private ˊ ᴵʖ;
  
  private ˊ ﾞл;
  
  private ˊ ʿᵉ;
  
  private ˊ ʹﮃ;
  
  private ˈے ᐨẏ;
  
  private int ˌх;
  
  private int ιﾌ;
  
  private ʿᵉ ﾞл;
  
  private int ʻւ;
  
  private ʿᵉ ʿᵉ;
  
  private ﾞǰ ᐨẏ;
  
  private ﾞǰ ˊ;
  
  private ᴵʖ ˊ;
  
  private int ˑܘ;
  
  public ʽ(int paramInt) {
    this(null, 3);
  }
  
  private ʽ(ᐨم paramᐨم, int paramInt) {
    super(589824);
    this.ᐝᵣ = paramInt;
    this.ᐨẏ = (paramᐨم == null) ? (ﾞǰ)new ˌх(this) : (ﾞǰ)new ˌх(this, paramᐨم);
    if ((paramInt & 0x2) != 0) {
      this.ˑܘ = 4;
      return;
    } 
    if ((paramInt & 0x1) != 0) {
      this.ˑܘ = 1;
      return;
    } 
    this.ˑܘ = 0;
  }
  
  public final boolean ᐨẏ(int paramInt) {
    return ((this.ᐝᵣ & paramInt) == paramInt);
  }
  
  public final void ᐨẏ(int paramInt1, int paramInt2, String paramString1, String paramString2, String paramString3, String[] paramArrayOfString) {
    // Byte code:
    //   0: aload_0
    //   1: iload_1
    //   2: putfield ᔪ : I
    //   5: aload_0
    //   6: iload_2
    //   7: putfield ʿλ : I
    //   10: aload_0
    //   11: dup
    //   12: getfield ᐨẏ : Lyyds/sniarbtej/ˌх;
    //   15: iload_1
    //   16: ldc 65535
    //   18: iand
    //   19: aload_3
    //   20: astore #7
    //   22: istore_3
    //   23: dup
    //   24: astore_2
    //   25: iload_3
    //   26: putfield Ԇ : I
    //   29: aload_2
    //   30: aload #7
    //   32: putfield ˊ : Ljava/lang/String;
    //   35: aload_2
    //   36: aload #7
    //   38: astore #7
    //   40: dup
    //   41: astore_3
    //   42: bipush #7
    //   44: aload #7
    //   46: invokevirtual ᐨẏ : (ILjava/lang/String;)Lyyds/sniarbtej/ˊᵃ;
    //   49: getfield ͺᴲ : I
    //   52: putfield ˉｓ : I
    //   55: aload #4
    //   57: ifnull -> 73
    //   60: aload_0
    //   61: dup
    //   62: getfield ᐨẏ : Lyyds/sniarbtej/ˌх;
    //   65: aload #4
    //   67: invokevirtual ՙᗮ : (Ljava/lang/String;)I
    //   70: putfield ﾞǰ : I
    //   73: aload_0
    //   74: aload #5
    //   76: ifnonnull -> 83
    //   79: iconst_0
    //   80: goto -> 103
    //   83: aload_0
    //   84: getfield ᐨẏ : Lyyds/sniarbtej/ˌх;
    //   87: aload #5
    //   89: astore #7
    //   91: dup
    //   92: astore_3
    //   93: bipush #7
    //   95: aload #7
    //   97: invokevirtual ᐨẏ : (ILjava/lang/String;)Lyyds/sniarbtej/ˊᵃ;
    //   100: getfield ͺᴲ : I
    //   103: putfield ʿপ : I
    //   106: aload #6
    //   108: ifnull -> 178
    //   111: aload #6
    //   113: arraylength
    //   114: ifle -> 178
    //   117: aload_0
    //   118: aload #6
    //   120: arraylength
    //   121: putfield ʻล : I
    //   124: aload_0
    //   125: dup
    //   126: getfield ʻล : I
    //   129: newarray int
    //   131: putfield ᴵʖ : [I
    //   134: iconst_0
    //   135: istore_2
    //   136: iload_2
    //   137: aload_0
    //   138: getfield ʻล : I
    //   141: if_icmpge -> 178
    //   144: aload_0
    //   145: getfield ᴵʖ : [I
    //   148: iload_2
    //   149: aload_0
    //   150: getfield ᐨẏ : Lyyds/sniarbtej/ˌх;
    //   153: aload #6
    //   155: iload_2
    //   156: aaload
    //   157: astore #7
    //   159: dup
    //   160: astore_3
    //   161: bipush #7
    //   163: aload #7
    //   165: invokevirtual ᐨẏ : (ILjava/lang/String;)Lyyds/sniarbtej/ˊᵃ;
    //   168: getfield ͺᴲ : I
    //   171: iastore
    //   172: iinc #2, 1
    //   175: goto -> 136
    //   178: aload_0
    //   179: getfield ˑܘ : I
    //   182: iconst_1
    //   183: if_icmpne -> 200
    //   186: iload_1
    //   187: ldc 65535
    //   189: iand
    //   190: bipush #51
    //   192: if_icmplt -> 200
    //   195: aload_0
    //   196: iconst_2
    //   197: putfield ˑܘ : I
    //   200: return
  }
  
  public final void ᐨẏ(String paramString1, String paramString2) {
    if (paramString1 != null)
      this.ˊᵃ = this.ᐨẏ.ՙᗮ(paramString1); 
    if (paramString2 != null)
      this.ᴵʖ = (ˊ)(new ʿᵉ()).ᐨẏ(paramString2, 0, 2147483647); 
  }
  
  public final ʻล ᐨẏ(String paramString1, int paramInt, String paramString2) {
    return (ʻล)(this.ᐨẏ = (ﾞǰ)new ˈے((ˌх)this.ᐨẏ, (this.ᐨẏ.ﾞл(paramString1)).ͺᴲ, paramInt, (paramString2 == null) ? 0 : this.ᐨẏ.ՙᗮ(paramString2)));
  }
  
  public final void ᐨẏ(String paramString) {
    String str = paramString;
    ﾞǰ ﾞǰ1;
    this.ˌх = ((ﾞǰ1 = this.ᐨẏ).ᐨẏ(7, str)).ͺᴲ;
  }
  
  public final void ˊ(String paramString1, String paramString2, String paramString3) {
    String str = paramString1;
    ﾞǰ ﾞǰ1;
    this.ـﭔ = ((ﾞǰ1 = this.ᐨẏ).ᐨẏ(7, str)).ͺᴲ;
    if (paramString2 != null && paramString3 != null)
      this.ʼᵖ = this.ᐨẏ.ˊ(paramString2, paramString3); 
  }
  
  public final ᐨẏ ᐨẏ(String paramString, boolean paramBoolean) {
    return (ᐨẏ)(paramBoolean ? (this.ᴵʖ = ˊ.ᐨẏ((ˌх)this.ᐨẏ, paramString, this.ᴵʖ)) : (this.ﾞл = (ʿᵉ)ˊ.ᐨẏ((ˌх)this.ᐨẏ, paramString, (ˊ)this.ﾞл)));
  }
  
  public final ᐨẏ ᐨẏ(int paramInt, ˏɪ paramˏɪ, String paramString, boolean paramBoolean) {
    return (ᐨẏ)(paramBoolean ? (this.ʿᵉ = (ʿᵉ)ˊ.ᐨẏ((ˌх)this.ᐨẏ, paramInt, paramˏɪ, paramString, (ˊ)this.ʿᵉ)) : (this.ʹﮃ = ˊ.ᐨẏ((ˌх)this.ᐨẏ, paramInt, paramˏɪ, paramString, this.ʹﮃ)));
  }
  
  public final void ᴵʖ(ᴵʖ paramᴵʖ) {
    paramᴵʖ.ᐨẏ = this.ˊ;
    this.ˊ = paramᴵʖ;
  }
  
  public final void ˊ(String paramString) {
    if (this.ﾞл == null)
      this.ﾞл = new ʿᵉ(); 
    this.ιﾌ++;
    String str = paramString;
    ﾞǰ ﾞǰ1;
    this.ﾞл.ˊ(((ﾞǰ1 = this.ᐨẏ).ᐨẏ(7, str)).ͺᴲ);
  }
  
  public final void ᴵʖ(String paramString) {
    if (this.ʿᵉ == null)
      this.ʿᵉ = new ʿᵉ(); 
    this.ʻւ++;
    String str = paramString;
    ﾞǰ ﾞǰ1;
    this.ʿᵉ.ˊ(((ﾞǰ1 = this.ᐨẏ).ᐨẏ(7, str)).ͺᴲ);
  }
  
  public final void ᐨẏ(String paramString1, String paramString2, String paramString3, int paramInt) {
    if (this.ˊ == null)
      this.ˊ = (ᴵʖ)new ʿᵉ(); 
    String str = paramString1;
    ˊᵃ ˊᵃ;
    ﾞǰ ﾞǰ1;
    if ((ˊᵃ = (ﾞǰ1 = this.ᐨẏ).ᐨẏ(7, str)).ᐨḶ == 0) {
      this.ˈے++;
      this.ˊ.ˊ(ˊᵃ.ͺᴲ);
      str = paramString2;
      this.ˊ.ˊ((paramString2 == null) ? 0 : ((ﾞǰ1 = this.ᐨẏ).ᐨẏ(7, str)).ͺᴲ);
      this.ˊ.ˊ((paramString3 == null) ? 0 : this.ᐨẏ.ՙᗮ(paramString3));
      this.ˊ.ˊ(paramInt);
      ˊᵃ.ᐨḶ = this.ˈے;
    } 
  }
  
  public final ʼᵖ ᐨẏ(String paramString1, String paramString2, String paramString3) {
    ﾞǰ ﾞǰ1 = new ﾞǰ((ˌх)this.ᐨẏ, paramString1, paramString2, paramString3);
    if (this.ᐨẏ == null) {
      this.ᐨẏ = ﾞǰ1;
    } else {
      ((ﾞǰ)this.ˊ).ᐨẏ = (ˌх)ﾞǰ1;
    } 
    return (ʼᵖ)(this.ˊ = (ᴵʖ)ﾞǰ1);
  }
  
  public final ᴵƚ ᐨẏ(int paramInt, String paramString1, String paramString2, String paramString3, Object paramObject) {
    ˌ ˌ1 = new ˌ((ˌх)this.ᐨẏ, paramInt, paramString1, paramString2, paramString3, paramObject);
    if (this.ᐨẏ == null) {
      this.ᐨẏ = (ﾞǰ)ˌ1;
    } else {
      ((ˌ)this.ˊ).ᐨẏ = (ˌх)ˌ1;
    } 
    return (ᴵƚ)(this.ˊ = (ᴵʖ)ˌ1);
  }
  
  public final ˉｓ ᐨẏ(int paramInt, String paramString1, String paramString2, String paramString3, String[] paramArrayOfString) {
    ʿপ ʿপ1 = new ʿপ((ˌх)this.ᐨẏ, paramInt, paramString1, paramString2, paramString3, paramArrayOfString, this.ˑܘ);
    if (this.ᐨẏ == null) {
      this.ᐨẏ = (ﾞǰ)ʿপ1;
    } else {
      ((ʿপ)this.ˊ).ᐨẏ = (ˊ[])ʿপ1;
    } 
    return (ˉｓ)(this.ˊ = (ᴵʖ)ʿপ1);
  }
  
  public final void ᐨẏ() {}
  
  public final byte[] ᐨẏ() {
    // Byte code:
    //   0: bipush #24
    //   2: iconst_2
    //   3: aload_0
    //   4: getfield ʻล : I
    //   7: imul
    //   8: iadd
    //   9: istore_1
    //   10: iconst_0
    //   11: istore_2
    //   12: aload_0
    //   13: getfield ᐨẏ : Lyyds/sniarbtej/ˌ;
    //   16: astore_3
    //   17: aload_3
    //   18: ifnull -> 167
    //   21: iinc #2, 1
    //   24: iload_1
    //   25: aload_3
    //   26: astore #9
    //   28: bipush #8
    //   30: istore #10
    //   32: aload #9
    //   34: getfield ʿｱ : I
    //   37: ifeq -> 76
    //   40: aload #9
    //   42: getfield ᐨẏ : Lyyds/sniarbtej/ˌх;
    //   45: ldc '琓땲?﯏瓪释籛쩔ꥥ疵ᢊ퐜↋剼'
    //   47: invokevirtual toCharArray : ()[C
    //   50: dup
    //   51: dup
    //   52: iconst_3
    //   53: dup_x1
    //   54: caload
    //   55: sipush #12102
    //   58: ixor
    //   59: i2c
    //   60: castore
    //   61: sipush #22884
    //   64: iconst_0
    //   65: iconst_2
    //   66: invokestatic v : (Ljava/lang/Object;SIS)Ljava/lang/String;
    //   69: invokevirtual ՙᗮ : (Ljava/lang/String;)I
    //   72: pop
    //   73: iinc #10, 8
    //   76: iload #10
    //   78: aload #9
    //   80: getfield ᐨẏ : Lyyds/sniarbtej/ˌх;
    //   83: aload #9
    //   85: getfield ʿλ : I
    //   88: aload #9
    //   90: getfield ﾞǰ : I
    //   93: invokestatic ᐨẏ : (Lyyds/sniarbtej/ˌх;II)I
    //   96: iadd
    //   97: dup
    //   98: istore #10
    //   100: aload #9
    //   102: getfield ᴵʖ : Lyyds/sniarbtej/ˊ;
    //   105: aload #9
    //   107: getfield ﾞл : Lyyds/sniarbtej/ˊ;
    //   110: aload #9
    //   112: getfield ʿᵉ : Lyyds/sniarbtej/ˊ;
    //   115: aload #9
    //   117: getfield ʹﮃ : Lyyds/sniarbtej/ˊ;
    //   120: invokestatic ᐨẏ : (Lyyds/sniarbtej/ˊ;Lyyds/sniarbtej/ˊ;Lyyds/sniarbtej/ˊ;Lyyds/sniarbtej/ˊ;)I
    //   123: iadd
    //   124: istore #10
    //   126: aload #9
    //   128: getfield ˊ : Lyyds/sniarbtej/ᴵʖ;
    //   131: ifnull -> 152
    //   134: iload #10
    //   136: aload #9
    //   138: getfield ˊ : Lyyds/sniarbtej/ᴵʖ;
    //   141: aload #9
    //   143: getfield ᐨẏ : Lyyds/sniarbtej/ˌх;
    //   146: invokevirtual ᐨẏ : (Lyyds/sniarbtej/ˌх;)I
    //   149: iadd
    //   150: istore #10
    //   152: iload #10
    //   154: iadd
    //   155: istore_1
    //   156: aload_3
    //   157: getfield ᐨẏ : Lyyds/sniarbtej/ᴵƚ;
    //   160: checkcast yyds/sniarbtej/ˌ
    //   163: astore_3
    //   164: goto -> 17
    //   167: iconst_0
    //   168: istore #4
    //   170: aload_0
    //   171: getfield ᐨẏ : Lyyds/sniarbtej/ʿপ;
    //   174: astore_3
    //   175: aload_3
    //   176: ifnull -> 1169
    //   179: iinc #4, 1
    //   182: iload_1
    //   183: aload_3
    //   184: dup
    //   185: astore #9
    //   187: getfield ᴵ氵 : I
    //   190: ifeq -> 204
    //   193: bipush #6
    //   195: aload #9
    //   197: getfield ᵊ : I
    //   200: iadd
    //   201: goto -> 1156
    //   204: bipush #8
    //   206: istore #10
    //   208: aload #9
    //   210: getfield ʹﮃ : Lyyds/sniarbtej/ʿᵉ;
    //   213: getfield ʹﮃ : I
    //   216: ifle -> 766
    //   219: aload #9
    //   221: getfield ʹﮃ : Lyyds/sniarbtej/ʿᵉ;
    //   224: getfield ʹﮃ : I
    //   227: ldc 65535
    //   229: if_icmple -> 269
    //   232: new yyds/sniarbtej/ʿλ
    //   235: dup
    //   236: aload #9
    //   238: getfield ᐨẏ : Lyyds/sniarbtej/ˌх;
    //   241: dup
    //   242: astore #11
    //   244: getfield ˊ : Ljava/lang/String;
    //   247: aload #9
    //   249: getfield name : Ljava/lang/String;
    //   252: aload #9
    //   254: getfield ᴵʖ : Ljava/lang/String;
    //   257: aload #9
    //   259: getfield ʹﮃ : Lyyds/sniarbtej/ʿᵉ;
    //   262: getfield ʹﮃ : I
    //   265: invokespecial <init> : (Ljava/lang/String;Ljava/lang/String;Ljava/lang/String;I)V
    //   268: athrow
    //   269: aload #9
    //   271: getfield ᐨẏ : Lyyds/sniarbtej/ˌх;
    //   274: ldc_w '㓺竱䛇䤍ᱚ'
    //   277: invokevirtual toCharArray : ()[C
    //   280: dup
    //   281: dup
    //   282: iconst_2
    //   283: dup_x1
    //   284: caload
    //   285: sipush #21195
    //   288: ixor
    //   289: i2c
    //   290: castore
    //   291: sipush #24580
    //   294: iconst_3
    //   295: iconst_1
    //   296: invokestatic v : (Ljava/lang/Object;SIS)Ljava/lang/String;
    //   299: invokevirtual ՙᗮ : (Ljava/lang/String;)I
    //   302: pop
    //   303: bipush #8
    //   305: bipush #16
    //   307: aload #9
    //   309: getfield ʹﮃ : Lyyds/sniarbtej/ʿᵉ;
    //   312: getfield ʹﮃ : I
    //   315: iadd
    //   316: aload #9
    //   318: getfield ᐨẏ : Lyyds/sniarbtej/ˌᑦ;
    //   321: invokestatic ˊ : (Lyyds/sniarbtej/ˌᑦ;)I
    //   324: iadd
    //   325: iadd
    //   326: istore #10
    //   328: aload #9
    //   330: getfield ʾܪ : Lyyds/sniarbtej/ʿᵉ;
    //   333: ifnull -> 443
    //   336: aload #9
    //   338: getfield ᐨẏ : Lyyds/sniarbtej/ˌх;
    //   341: dup
    //   342: astore #11
    //   344: getfield Ԇ : I
    //   347: bipush #50
    //   349: if_icmplt -> 356
    //   352: iconst_1
    //   353: goto -> 357
    //   356: iconst_0
    //   357: istore #11
    //   359: aload #9
    //   361: getfield ᐨẏ : Lyyds/sniarbtej/ˌх;
    //   364: iload #11
    //   366: ifeq -> 398
    //   369: ldc_w '輫萭岐Ⴙ꣯副ῦ弈劍㸠骄㙃帺'
    //   372: invokevirtual toCharArray : ()[C
    //   375: dup
    //   376: dup
    //   377: bipush #6
    //   379: dup_x1
    //   380: caload
    //   381: sipush #2333
    //   384: ixor
    //   385: i2c
    //   386: castore
    //   387: sipush #11849
    //   390: iconst_4
    //   391: iconst_2
    //   392: invokestatic v : (Ljava/lang/Object;SIS)Ljava/lang/String;
    //   395: goto -> 423
    //   398: ldc_w '頵飽율?퉘㚰ቹ䃫'
    //   401: invokevirtual toCharArray : ()[C
    //   404: dup
    //   405: dup
    //   406: iconst_3
    //   407: dup_x1
    //   408: caload
    //   409: sipush #30939
    //   412: ixor
    //   413: i2c
    //   414: castore
    //   415: sipush #30040
    //   418: iconst_2
    //   419: iconst_2
    //   420: invokestatic v : (Ljava/lang/Object;SIS)Ljava/lang/String;
    //   423: invokevirtual ՙᗮ : (Ljava/lang/String;)I
    //   426: pop
    //   427: iload #10
    //   429: bipush #8
    //   431: aload #9
    //   433: getfield ʾܪ : Lyyds/sniarbtej/ʿᵉ;
    //   436: getfield ʹﮃ : I
    //   439: iadd
    //   440: iadd
    //   441: istore #10
    //   443: aload #9
    //   445: getfield ՙᗮ : Lyyds/sniarbtej/ʿᵉ;
    //   448: ifnull -> 502
    //   451: aload #9
    //   453: getfield ᐨẏ : Lyyds/sniarbtej/ˌх;
    //   456: ldc_w '㌄ᢚ篂斔蛬䥴ˏࢪ㝖ᐩᶱੵ䐐烲'
    //   459: invokevirtual toCharArray : ()[C
    //   462: dup
    //   463: dup
    //   464: bipush #12
    //   466: dup_x1
    //   467: caload
    //   468: sipush #13208
    //   471: ixor
    //   472: i2c
    //   473: castore
    //   474: sipush #10749
    //   477: iconst_2
    //   478: iconst_0
    //   479: invokestatic v : (Ljava/lang/Object;SIS)Ljava/lang/String;
    //   482: invokevirtual ՙᗮ : (Ljava/lang/String;)I
    //   485: pop
    //   486: iload #10
    //   488: bipush #8
    //   490: aload #9
    //   492: getfield ՙᗮ : Lyyds/sniarbtej/ʿᵉ;
    //   495: getfield ʹﮃ : I
    //   498: iadd
    //   499: iadd
    //   500: istore #10
    //   502: aload #9
    //   504: getfield ˍɫ : Lyyds/sniarbtej/ʿᵉ;
    //   507: ifnull -> 561
    //   510: aload #9
    //   512: getfield ᐨẏ : Lyyds/sniarbtej/ˌх;
    //   515: ldc_w '߻집愓㤾䅴▾﨔鋔ё켭嵆曰郘檞琚앳⫯'
    //   518: invokevirtual toCharArray : ()[C
    //   521: dup
    //   522: dup
    //   523: bipush #8
    //   525: dup_x1
    //   526: caload
    //   527: sipush #18226
    //   530: ixor
    //   531: i2c
    //   532: castore
    //   533: sipush #25852
    //   536: iconst_5
    //   537: iconst_3
    //   538: invokestatic v : (Ljava/lang/Object;SIS)Ljava/lang/String;
    //   541: invokevirtual ՙᗮ : (Ljava/lang/String;)I
    //   544: pop
    //   545: iload #10
    //   547: bipush #8
    //   549: aload #9
    //   551: getfield ˍɫ : Lyyds/sniarbtej/ʿᵉ;
    //   554: getfield ʹﮃ : I
    //   557: iadd
    //   558: iadd
    //   559: istore #10
    //   561: aload #9
    //   563: getfield ʽ : Lyyds/sniarbtej/ʿᵉ;
    //   566: ifnull -> 620
    //   569: aload #9
    //   571: getfield ᐨẏ : Lyyds/sniarbtej/ˌх;
    //   574: ldc_w 'ꋌ??矮冡꣬?豣襱帹ᙅ洫ޡ￾궨㰫윒뇰ᱷ'
    //   577: invokevirtual toCharArray : ()[C
    //   580: dup
    //   581: dup
    //   582: bipush #17
    //   584: dup_x1
    //   585: caload
    //   586: sipush #8611
    //   589: ixor
    //   590: i2c
    //   591: castore
    //   592: sipush #7186
    //   595: iconst_2
    //   596: iconst_4
    //   597: invokestatic v : (Ljava/lang/Object;SIS)Ljava/lang/String;
    //   600: invokevirtual ՙᗮ : (Ljava/lang/String;)I
    //   603: pop
    //   604: iload #10
    //   606: bipush #8
    //   608: aload #9
    //   610: getfield ʽ : Lyyds/sniarbtej/ʿᵉ;
    //   613: getfield ʹﮃ : I
    //   616: iadd
    //   617: iadd
    //   618: istore #10
    //   620: aload #9
    //   622: getfield ՙᗮ : Lyyds/sniarbtej/ˊ;
    //   625: ifnull -> 667
    //   628: iload #10
    //   630: aload #9
    //   632: getfield ՙᗮ : Lyyds/sniarbtej/ˊ;
    //   635: ldc_w '⤇ӛ堿梒鳝脛Ґ㢦︜벻ꁆ釫帿㏛攩?㯂暓횪퇜㺜䦭쇎ﱹ瑰㔐츚甔'
    //   638: invokevirtual toCharArray : ()[C
    //   641: dup
    //   642: dup
    //   643: bipush #9
    //   645: dup_x1
    //   646: caload
    //   647: sipush #2335
    //   650: ixor
    //   651: i2c
    //   652: castore
    //   653: sipush #12633
    //   656: iconst_0
    //   657: iconst_2
    //   658: invokestatic v : (Ljava/lang/Object;SIS)Ljava/lang/String;
    //   661: invokevirtual ᐨẏ : (Ljava/lang/String;)I
    //   664: iadd
    //   665: istore #10
    //   667: aload #9
    //   669: getfield ˍɫ : Lyyds/sniarbtej/ˊ;
    //   672: ifnull -> 714
    //   675: iload #10
    //   677: aload #9
    //   679: getfield ˍɫ : Lyyds/sniarbtej/ˊ;
    //   682: ldc_w '왢跦析㥜謄ᔅﲂ꟏ᕿ쥤핣﹅㨀﹄?쩣麛揱戌뻙쎀먼≽뿺㺄땃吰䒘骁ၘ㱵'
    //   685: invokevirtual toCharArray : ()[C
    //   688: dup
    //   689: dup
    //   690: bipush #12
    //   692: dup_x1
    //   693: caload
    //   694: sipush #1396
    //   697: ixor
    //   698: i2c
    //   699: castore
    //   700: sipush #21418
    //   703: iconst_4
    //   704: iconst_5
    //   705: invokestatic v : (Ljava/lang/Object;SIS)Ljava/lang/String;
    //   708: invokevirtual ᐨẏ : (Ljava/lang/String;)I
    //   711: iadd
    //   712: istore #10
    //   714: aload #9
    //   716: getfield ᴵʖ : Lyyds/sniarbtej/ᴵʖ;
    //   719: ifnull -> 766
    //   722: iload #10
    //   724: aload #9
    //   726: getfield ᴵʖ : Lyyds/sniarbtej/ᴵʖ;
    //   729: aload #9
    //   731: getfield ᐨẏ : Lyyds/sniarbtej/ˌх;
    //   734: aload #9
    //   736: getfield ʹﮃ : Lyyds/sniarbtej/ʿᵉ;
    //   739: getfield ˊ : [B
    //   742: aload #9
    //   744: getfield ʹﮃ : Lyyds/sniarbtej/ʿᵉ;
    //   747: getfield ʹﮃ : I
    //   750: aload #9
    //   752: getfield ˑỲ : I
    //   755: aload #9
    //   757: getfield ˌپ : I
    //   760: invokevirtual ᐨẏ : (Lyyds/sniarbtej/ˌх;[BIII)I
    //   763: iadd
    //   764: istore #10
    //   766: aload #9
    //   768: getfield ٴῪ : I
    //   771: ifle -> 823
    //   774: aload #9
    //   776: getfield ᐨẏ : Lyyds/sniarbtej/ˌх;
    //   779: ldc_w 'ا佐픊⛓翫띅胟왈╷'
    //   782: invokevirtual toCharArray : ()[C
    //   785: dup
    //   786: dup
    //   787: iconst_1
    //   788: dup_x1
    //   789: caload
    //   790: sipush #30971
    //   793: ixor
    //   794: i2c
    //   795: castore
    //   796: sipush #21432
    //   799: iconst_5
    //   800: iconst_3
    //   801: invokestatic v : (Ljava/lang/Object;SIS)Ljava/lang/String;
    //   804: invokevirtual ՙᗮ : (Ljava/lang/String;)I
    //   807: pop
    //   808: iload #10
    //   810: bipush #8
    //   812: iconst_2
    //   813: aload #9
    //   815: getfield ٴῪ : I
    //   818: imul
    //   819: iadd
    //   820: iadd
    //   821: istore #10
    //   823: iload #10
    //   825: aload #9
    //   827: getfield ᐨẏ : Lyyds/sniarbtej/ˌх;
    //   830: aload #9
    //   832: getfield ʿλ : I
    //   835: aload #9
    //   837: getfield ﾞǰ : I
    //   840: invokestatic ᐨẏ : (Lyyds/sniarbtej/ˌх;II)I
    //   843: iadd
    //   844: dup
    //   845: istore #10
    //   847: aload #9
    //   849: getfield ᴵʖ : Lyyds/sniarbtej/ˊ;
    //   852: aload #9
    //   854: getfield ﾞл : Lyyds/sniarbtej/ˊ;
    //   857: aload #9
    //   859: getfield ʿᵉ : Lyyds/sniarbtej/ˊ;
    //   862: aload #9
    //   864: getfield ʹﮃ : Lyyds/sniarbtej/ˊ;
    //   867: invokestatic ᐨẏ : (Lyyds/sniarbtej/ˊ;Lyyds/sniarbtej/ˊ;Lyyds/sniarbtej/ˊ;Lyyds/sniarbtej/ˊ;)I
    //   870: iadd
    //   871: istore #10
    //   873: aload #9
    //   875: getfield ᐨẏ : [Lyyds/sniarbtej/ˊ;
    //   878: ifnull -> 942
    //   881: iload #10
    //   883: ldc_w '⬒쯽艁䋵漶絝納亊쉧䃥ⅿ䴣қỌ꣘杔ａ乙額登ึ쾨韛?鐅艓䨐'
    //   886: invokevirtual toCharArray : ()[C
    //   889: dup
    //   890: dup
    //   891: bipush #25
    //   893: dup_x1
    //   894: caload
    //   895: sipush #4119
    //   898: ixor
    //   899: i2c
    //   900: castore
    //   901: sipush #22254
    //   904: iconst_3
    //   905: iconst_1
    //   906: invokestatic v : (Ljava/lang/Object;SIS)Ljava/lang/String;
    //   909: aload #9
    //   911: getfield ᐨẏ : [Lyyds/sniarbtej/ˊ;
    //   914: aload #9
    //   916: getfield শ : I
    //   919: ifne -> 931
    //   922: aload #9
    //   924: getfield ᐨẏ : [Lyyds/sniarbtej/ˊ;
    //   927: arraylength
    //   928: goto -> 936
    //   931: aload #9
    //   933: getfield শ : I
    //   936: invokestatic ᐨẏ : (Ljava/lang/String;[Lyyds/sniarbtej/ˊ;I)I
    //   939: iadd
    //   940: istore #10
    //   942: aload #9
    //   944: getfield ˊ : [Lyyds/sniarbtej/ˊ;
    //   947: ifnull -> 1011
    //   950: iload #10
    //   952: ldc_w '蘯◎릐?ᗝ쌖콃䕐ゥᇭँ뢭隌ት阋⩓ܫ酠ﯸ䠼锞孌趏?팮앪擙糙펃짚蓓䮹쏵࿰'
    //   955: invokevirtual toCharArray : ()[C
    //   958: dup
    //   959: dup
    //   960: bipush #23
    //   962: dup_x1
    //   963: caload
    //   964: sipush #17704
    //   967: ixor
    //   968: i2c
    //   969: castore
    //   970: sipush #31083
    //   973: iconst_0
    //   974: iconst_4
    //   975: invokestatic v : (Ljava/lang/Object;SIS)Ljava/lang/String;
    //   978: aload #9
    //   980: getfield ˊ : [Lyyds/sniarbtej/ˊ;
    //   983: aload #9
    //   985: getfield ˋᴷ : I
    //   988: ifne -> 1000
    //   991: aload #9
    //   993: getfield ˊ : [Lyyds/sniarbtej/ˊ;
    //   996: arraylength
    //   997: goto -> 1005
    //   1000: aload #9
    //   1002: getfield ˋᴷ : I
    //   1005: invokestatic ᐨẏ : (Ljava/lang/String;[Lyyds/sniarbtej/ˊ;I)I
    //   1008: iadd
    //   1009: istore #10
    //   1011: aload #9
    //   1013: getfield ᐨم : Lyyds/sniarbtej/ʿᵉ;
    //   1016: ifnull -> 1069
    //   1019: aload #9
    //   1021: getfield ᐨẏ : Lyyds/sniarbtej/ˌх;
    //   1024: ldc_w '≋䢶⡞໨䖩紳ⲝ沠޻瓹ﴸ泎▬䛞᣺⾼炔'
    //   1027: invokevirtual toCharArray : ()[C
    //   1030: dup
    //   1031: dup
    //   1032: iconst_5
    //   1033: dup_x1
    //   1034: caload
    //   1035: sipush #1206
    //   1038: ixor
    //   1039: i2c
    //   1040: castore
    //   1041: sipush #718
    //   1044: iconst_0
    //   1045: iconst_2
    //   1046: invokestatic v : (Ljava/lang/Object;SIS)Ljava/lang/String;
    //   1049: invokevirtual ՙᗮ : (Ljava/lang/String;)I
    //   1052: pop
    //   1053: iload #10
    //   1055: bipush #6
    //   1057: aload #9
    //   1059: getfield ᐨم : Lyyds/sniarbtej/ʿᵉ;
    //   1062: getfield ʹﮃ : I
    //   1065: iadd
    //   1066: iadd
    //   1067: istore #10
    //   1069: aload #9
    //   1071: getfield ʾ : Lyyds/sniarbtej/ʿᵉ;
    //   1074: ifnull -> 1128
    //   1077: aload #9
    //   1079: getfield ᐨẏ : Lyyds/sniarbtej/ˌх;
    //   1082: ldc_w '빊檑봾ࡱ莲.ධ増랟慗ᮽ壣⫭'
    //   1085: invokevirtual toCharArray : ()[C
    //   1088: dup
    //   1089: dup
    //   1090: bipush #6
    //   1092: dup_x1
    //   1093: caload
    //   1094: sipush #277
    //   1097: ixor
    //   1098: i2c
    //   1099: castore
    //   1100: sipush #9704
    //   1103: iconst_1
    //   1104: iconst_4
    //   1105: invokestatic v : (Ljava/lang/Object;SIS)Ljava/lang/String;
    //   1108: invokevirtual ՙᗮ : (Ljava/lang/String;)I
    //   1111: pop
    //   1112: iload #10
    //   1114: bipush #7
    //   1116: aload #9
    //   1118: getfield ʾ : Lyyds/sniarbtej/ʿᵉ;
    //   1121: getfield ʹﮃ : I
    //   1124: iadd
    //   1125: iadd
    //   1126: istore #10
    //   1128: aload #9
    //   1130: getfield ˊ : Lyyds/sniarbtej/ᴵʖ;
    //   1133: ifnull -> 1154
    //   1136: iload #10
    //   1138: aload #9
    //   1140: getfield ˊ : Lyyds/sniarbtej/ᴵʖ;
    //   1143: aload #9
    //   1145: getfield ᐨẏ : Lyyds/sniarbtej/ˌх;
    //   1148: invokevirtual ᐨẏ : (Lyyds/sniarbtej/ˌх;)I
    //   1151: iadd
    //   1152: istore #10
    //   1154: iload #10
    //   1156: iadd
    //   1157: istore_1
    //   1158: aload_3
    //   1159: getfield ᐨẏ : Lyyds/sniarbtej/ˉｓ;
    //   1162: checkcast yyds/sniarbtej/ʿপ
    //   1165: astore_3
    //   1166: goto -> 175
    //   1169: iconst_0
    //   1170: istore #5
    //   1172: aload_0
    //   1173: getfield ˊ : Lyyds/sniarbtej/ʿᵉ;
    //   1176: ifnull -> 1228
    //   1179: iinc #5, 1
    //   1182: iload_1
    //   1183: bipush #8
    //   1185: aload_0
    //   1186: getfield ˊ : Lyyds/sniarbtej/ʿᵉ;
    //   1189: getfield ʹﮃ : I
    //   1192: iadd
    //   1193: iadd
    //   1194: istore_1
    //   1195: aload_0
    //   1196: getfield ᐨẏ : Lyyds/sniarbtej/ˌх;
    //   1199: ldc_w '虿᪤ƽ䟚䨯ᙑ㘲誾劵ﾐ倘ꟺ䃇'
    //   1202: invokevirtual toCharArray : ()[C
    //   1205: dup
    //   1206: dup
    //   1207: iconst_5
    //   1208: dup_x1
    //   1209: caload
    //   1210: sipush #12930
    //   1213: ixor
    //   1214: i2c
    //   1215: castore
    //   1216: sipush #20353
    //   1219: iconst_0
    //   1220: iconst_2
    //   1221: invokestatic v : (Ljava/lang/Object;SIS)Ljava/lang/String;
    //   1224: invokevirtual ՙᗮ : (Ljava/lang/String;)I
    //   1227: pop
    //   1228: aload_0
    //   1229: getfield ـﭔ : I
    //   1232: ifeq -> 1274
    //   1235: iinc #5, 1
    //   1238: iinc #1, 10
    //   1241: aload_0
    //   1242: getfield ᐨẏ : Lyyds/sniarbtej/ˌх;
    //   1245: ldc_w '嶟쎼䜲籭汧髖?ݧ变᎓믒㓾욋㸵䀶່'
    //   1248: invokevirtual toCharArray : ()[C
    //   1251: dup
    //   1252: dup
    //   1253: iconst_1
    //   1254: dup_x1
    //   1255: caload
    //   1256: sipush #16044
    //   1259: ixor
    //   1260: i2c
    //   1261: castore
    //   1262: sipush #24728
    //   1265: iconst_2
    //   1266: iconst_3
    //   1267: invokestatic v : (Ljava/lang/Object;SIS)Ljava/lang/String;
    //   1270: invokevirtual ՙᗮ : (Ljava/lang/String;)I
    //   1273: pop
    //   1274: aload_0
    //   1275: getfield ʿλ : I
    //   1278: sipush #4096
    //   1281: iand
    //   1282: ifeq -> 1337
    //   1285: aload_0
    //   1286: getfield ᔪ : I
    //   1289: ldc 65535
    //   1291: iand
    //   1292: bipush #49
    //   1294: if_icmpge -> 1337
    //   1297: iinc #5, 1
    //   1300: iinc #1, 6
    //   1303: aload_0
    //   1304: getfield ᐨẏ : Lyyds/sniarbtej/ˌх;
    //   1307: ldc_w '鐩猆ꦢ텻鉶茊ၤ뙡곷⯣'
    //   1310: invokevirtual toCharArray : ()[C
    //   1313: dup
    //   1314: dup
    //   1315: bipush #7
    //   1317: dup_x1
    //   1318: caload
    //   1319: sipush #18818
    //   1322: ixor
    //   1323: i2c
    //   1324: castore
    //   1325: sipush #6475
    //   1328: iconst_1
    //   1329: iconst_4
    //   1330: invokestatic v : (Ljava/lang/Object;SIS)Ljava/lang/String;
    //   1333: invokevirtual ՙᗮ : (Ljava/lang/String;)I
    //   1336: pop
    //   1337: aload_0
    //   1338: getfield ﾞǰ : I
    //   1341: ifeq -> 1383
    //   1344: iinc #5, 1
    //   1347: iinc #1, 8
    //   1350: aload_0
    //   1351: getfield ᐨẏ : Lyyds/sniarbtej/ˌх;
    //   1354: ldc_w '㯛黽䶷绂ꈕꏅ坯䩱ᔆ'
    //   1357: invokevirtual toCharArray : ()[C
    //   1360: dup
    //   1361: dup
    //   1362: iconst_0
    //   1363: dup_x1
    //   1364: caload
    //   1365: sipush #2855
    //   1368: ixor
    //   1369: i2c
    //   1370: castore
    //   1371: sipush #8269
    //   1374: iconst_3
    //   1375: iconst_4
    //   1376: invokestatic v : (Ljava/lang/Object;SIS)Ljava/lang/String;
    //   1379: invokevirtual ՙᗮ : (Ljava/lang/String;)I
    //   1382: pop
    //   1383: aload_0
    //   1384: getfield ˊᵃ : I
    //   1387: ifeq -> 1429
    //   1390: iinc #5, 1
    //   1393: iinc #1, 8
    //   1396: aload_0
    //   1397: getfield ᐨẏ : Lyyds/sniarbtej/ˌх;
    //   1400: ldc_w '잿顪泿䅹卦儭、粺'
    //   1403: invokevirtual toCharArray : ()[C
    //   1406: dup
    //   1407: dup
    //   1408: iconst_3
    //   1409: dup_x1
    //   1410: caload
    //   1411: sipush #26806
    //   1414: ixor
    //   1415: i2c
    //   1416: castore
    //   1417: sipush #5435
    //   1420: iconst_4
    //   1421: iconst_1
    //   1422: invokestatic v : (Ljava/lang/Object;SIS)Ljava/lang/String;
    //   1425: invokevirtual ՙᗮ : (Ljava/lang/String;)I
    //   1428: pop
    //   1429: aload_0
    //   1430: getfield ᴵʖ : Lyyds/sniarbtej/ʿᵉ;
    //   1433: ifnull -> 1485
    //   1436: iinc #5, 1
    //   1439: iload_1
    //   1440: bipush #6
    //   1442: aload_0
    //   1443: getfield ᴵʖ : Lyyds/sniarbtej/ʿᵉ;
    //   1446: getfield ʹﮃ : I
    //   1449: iadd
    //   1450: iadd
    //   1451: istore_1
    //   1452: aload_0
    //   1453: getfield ᐨẏ : Lyyds/sniarbtej/ˌх;
    //   1456: ldc_w '䊮㳪鉔਱즓麧ᆸ睬硊쉏毩ᛓⷺị㇖⽀䘮'
    //   1459: invokevirtual toCharArray : ()[C
    //   1462: dup
    //   1463: dup
    //   1464: iconst_5
    //   1465: dup_x1
    //   1466: caload
    //   1467: sipush #11237
    //   1470: ixor
    //   1471: i2c
    //   1472: castore
    //   1473: sipush #140
    //   1476: iconst_0
    //   1477: iconst_2
    //   1478: invokestatic v : (Ljava/lang/Object;SIS)Ljava/lang/String;
    //   1481: invokevirtual ՙᗮ : (Ljava/lang/String;)I
    //   1484: pop
    //   1485: aload_0
    //   1486: getfield ʿλ : I
    //   1489: ldc_w 131072
    //   1492: iand
    //   1493: ifeq -> 1535
    //   1496: iinc #5, 1
    //   1499: iinc #1, 6
    //   1502: aload_0
    //   1503: getfield ᐨẏ : Lyyds/sniarbtej/ˌх;
    //   1506: ldc_w '∮⏉폓㺭獜閿噡䞪픶挅'
    //   1509: invokevirtual toCharArray : ()[C
    //   1512: dup
    //   1513: dup
    //   1514: iconst_2
    //   1515: dup_x1
    //   1516: caload
    //   1517: sipush #1817
    //   1520: ixor
    //   1521: i2c
    //   1522: castore
    //   1523: sipush #20940
    //   1526: iconst_3
    //   1527: iconst_1
    //   1528: invokestatic v : (Ljava/lang/Object;SIS)Ljava/lang/String;
    //   1531: invokevirtual ՙᗮ : (Ljava/lang/String;)I
    //   1534: pop
    //   1535: aload_0
    //   1536: getfield ᴵʖ : Lyyds/sniarbtej/ˊ;
    //   1539: ifnull -> 1581
    //   1542: iinc #5, 1
    //   1545: iload_1
    //   1546: aload_0
    //   1547: getfield ᴵʖ : Lyyds/sniarbtej/ˊ;
    //   1550: ldc_w 'ꛙ庀綔圹ꮙ륄Ἠ愬敔鹭韑鍢䄎웩ꤖ睉?㟸꯱㊠揼쐓䊅'
    //   1553: invokevirtual toCharArray : ()[C
    //   1556: dup
    //   1557: dup
    //   1558: bipush #10
    //   1560: dup_x1
    //   1561: caload
    //   1562: sipush #17454
    //   1565: ixor
    //   1566: i2c
    //   1567: castore
    //   1568: sipush #31733
    //   1571: iconst_3
    //   1572: iconst_5
    //   1573: invokestatic v : (Ljava/lang/Object;SIS)Ljava/lang/String;
    //   1576: invokevirtual ᐨẏ : (Ljava/lang/String;)I
    //   1579: iadd
    //   1580: istore_1
    //   1581: aload_0
    //   1582: getfield ﾞл : Lyyds/sniarbtej/ˊ;
    //   1585: ifnull -> 1627
    //   1588: iinc #5, 1
    //   1591: iload_1
    //   1592: aload_0
    //   1593: getfield ﾞл : Lyyds/sniarbtej/ˊ;
    //   1596: ldc_w '뫆皕䨠搑襁጖콂燋ی赓㞬쟹ಹ莲傤㋣ꋸツ俥뿩㍛ኌ뻌壇'
    //   1599: invokevirtual toCharArray : ()[C
    //   1602: dup
    //   1603: dup
    //   1604: bipush #16
    //   1606: dup_x1
    //   1607: caload
    //   1608: sipush #1376
    //   1611: ixor
    //   1612: i2c
    //   1613: castore
    //   1614: sipush #19025
    //   1617: iconst_1
    //   1618: iconst_0
    //   1619: invokestatic v : (Ljava/lang/Object;SIS)Ljava/lang/String;
    //   1622: invokevirtual ᐨẏ : (Ljava/lang/String;)I
    //   1625: iadd
    //   1626: istore_1
    //   1627: aload_0
    //   1628: getfield ʿᵉ : Lyyds/sniarbtej/ˊ;
    //   1631: ifnull -> 1672
    //   1634: iinc #5, 1
    //   1637: iload_1
    //   1638: aload_0
    //   1639: getfield ʿᵉ : Lyyds/sniarbtej/ˊ;
    //   1642: ldc_w 'ᵔ嚔쎖絆暘෸荲ᄞ힫䀋?躝葲彌毆諙⛾鼘༳뮠斵䎛妵먿⯪驒敖콌唣䙺'
    //   1645: invokevirtual toCharArray : ()[C
    //   1648: dup
    //   1649: dup
    //   1650: iconst_2
    //   1651: dup_x1
    //   1652: caload
    //   1653: sipush #30911
    //   1656: ixor
    //   1657: i2c
    //   1658: castore
    //   1659: sipush #24608
    //   1662: iconst_0
    //   1663: iconst_4
    //   1664: invokestatic v : (Ljava/lang/Object;SIS)Ljava/lang/String;
    //   1667: invokevirtual ᐨẏ : (Ljava/lang/String;)I
    //   1670: iadd
    //   1671: istore_1
    //   1672: aload_0
    //   1673: getfield ʹﮃ : Lyyds/sniarbtej/ˊ;
    //   1676: ifnull -> 1718
    //   1679: iinc #5, 1
    //   1682: iload_1
    //   1683: aload_0
    //   1684: getfield ʹﮃ : Lyyds/sniarbtej/ˊ;
    //   1687: ldc_w '玠簕⽮᜜ꚇ殐ꂚ쌆㲏렶?ᑔ㶔촏㳡夛࠻箣⩪?쇪ᇴ嬬㣠詂苾祻泍棻'
    //   1690: invokevirtual toCharArray : ()[C
    //   1693: dup
    //   1694: dup
    //   1695: bipush #14
    //   1697: dup_x1
    //   1698: caload
    //   1699: sipush #25485
    //   1702: ixor
    //   1703: i2c
    //   1704: castore
    //   1705: sipush #2956
    //   1708: iconst_2
    //   1709: iconst_5
    //   1710: invokestatic v : (Ljava/lang/Object;SIS)Ljava/lang/String;
    //   1713: invokevirtual ᐨẏ : (Ljava/lang/String;)I
    //   1716: iadd
    //   1717: istore_1
    //   1718: aload_0
    //   1719: getfield ᐨẏ : Lyyds/sniarbtej/ˌх;
    //   1722: invokevirtual ʿλ : ()I
    //   1725: ifle -> 1741
    //   1728: iinc #5, 1
    //   1731: iload_1
    //   1732: aload_0
    //   1733: getfield ᐨẏ : Lyyds/sniarbtej/ˌх;
    //   1736: invokevirtual ʿλ : ()I
    //   1739: iadd
    //   1740: istore_1
    //   1741: aload_0
    //   1742: getfield ᐨẏ : Lyyds/sniarbtej/ˈے;
    //   1745: ifnull -> 1985
    //   1748: iload #5
    //   1750: aload_0
    //   1751: getfield ᐨẏ : Lyyds/sniarbtej/ˈے;
    //   1754: astore #9
    //   1756: iconst_1
    //   1757: aload #9
    //   1759: getfield ˎᒩ : I
    //   1762: ifle -> 1769
    //   1765: iconst_1
    //   1766: goto -> 1770
    //   1769: iconst_0
    //   1770: iadd
    //   1771: aload #9
    //   1773: getfield ـō : I
    //   1776: ifle -> 1783
    //   1779: iconst_1
    //   1780: goto -> 1784
    //   1783: iconst_0
    //   1784: iadd
    //   1785: iadd
    //   1786: istore #5
    //   1788: iload_1
    //   1789: aload_0
    //   1790: getfield ᐨẏ : Lyyds/sniarbtej/ˈے;
    //   1793: dup
    //   1794: astore #9
    //   1796: getfield ᐨẏ : Lyyds/sniarbtej/ˌх;
    //   1799: ldc_w '迶쁓癠?繏冬'
    //   1802: invokevirtual toCharArray : ()[C
    //   1805: dup
    //   1806: dup
    //   1807: iconst_0
    //   1808: dup_x1
    //   1809: caload
    //   1810: sipush #14193
    //   1813: ixor
    //   1814: i2c
    //   1815: castore
    //   1816: sipush #29558
    //   1819: iconst_5
    //   1820: iconst_1
    //   1821: invokestatic v : (Ljava/lang/Object;SIS)Ljava/lang/String;
    //   1824: invokevirtual ՙᗮ : (Ljava/lang/String;)I
    //   1827: pop
    //   1828: bipush #22
    //   1830: aload #9
    //   1832: getfield ͺо : Lyyds/sniarbtej/ʿᵉ;
    //   1835: getfield ʹﮃ : I
    //   1838: iadd
    //   1839: aload #9
    //   1841: getfield ٴӵ : Lyyds/sniarbtej/ʿᵉ;
    //   1844: getfield ʹﮃ : I
    //   1847: iadd
    //   1848: aload #9
    //   1850: getfield ᴵƚ : Lyyds/sniarbtej/ʿᵉ;
    //   1853: getfield ʹﮃ : I
    //   1856: iadd
    //   1857: aload #9
    //   1859: getfield ˌ : Lyyds/sniarbtej/ʿᵉ;
    //   1862: getfield ʹﮃ : I
    //   1865: iadd
    //   1866: aload #9
    //   1868: getfield ˍ : Lyyds/sniarbtej/ʿᵉ;
    //   1871: getfield ʹﮃ : I
    //   1874: iadd
    //   1875: istore #10
    //   1877: aload #9
    //   1879: getfield ˎᒩ : I
    //   1882: ifle -> 1935
    //   1885: aload #9
    //   1887: getfield ᐨẏ : Lyyds/sniarbtej/ˌх;
    //   1890: ldc_w '㼫耗ᒮ⠼뇈蹰빹䦨褀軀?萃慊'
    //   1893: invokevirtual toCharArray : ()[C
    //   1896: dup
    //   1897: dup
    //   1898: iconst_4
    //   1899: dup_x1
    //   1900: caload
    //   1901: sipush #5353
    //   1904: ixor
    //   1905: i2c
    //   1906: castore
    //   1907: sipush #8021
    //   1910: iconst_3
    //   1911: iconst_1
    //   1912: invokestatic v : (Ljava/lang/Object;SIS)Ljava/lang/String;
    //   1915: invokevirtual ՙᗮ : (Ljava/lang/String;)I
    //   1918: pop
    //   1919: iload #10
    //   1921: bipush #8
    //   1923: aload #9
    //   1925: getfield ʹō : Lyyds/sniarbtej/ʿᵉ;
    //   1928: getfield ʹﮃ : I
    //   1931: iadd
    //   1932: iadd
    //   1933: istore #10
    //   1935: aload #9
    //   1937: getfield ـō : I
    //   1940: ifle -> 1981
    //   1943: aload #9
    //   1945: getfield ᐨẏ : Lyyds/sniarbtej/ˌх;
    //   1948: ldc_w 'ﲌꀹ?곿僇쫠＂軑Ⴐ褅퀤럠⊓'
    //   1951: invokevirtual toCharArray : ()[C
    //   1954: dup
    //   1955: dup
    //   1956: bipush #7
    //   1958: dup_x1
    //   1959: caload
    //   1960: sipush #8631
    //   1963: ixor
    //   1964: i2c
    //   1965: castore
    //   1966: sipush #15262
    //   1969: iconst_4
    //   1970: iconst_0
    //   1971: invokestatic v : (Ljava/lang/Object;SIS)Ljava/lang/String;
    //   1974: invokevirtual ՙᗮ : (Ljava/lang/String;)I
    //   1977: pop
    //   1978: iinc #10, 8
    //   1981: iload #10
    //   1983: iadd
    //   1984: istore_1
    //   1985: aload_0
    //   1986: getfield ˌх : I
    //   1989: ifeq -> 2031
    //   1992: iinc #5, 1
    //   1995: iinc #1, 8
    //   1998: aload_0
    //   1999: getfield ᐨẏ : Lyyds/sniarbtej/ˌх;
    //   2002: ldc_w 'Ìא炄ꇪ菵呂〴'
    //   2005: invokevirtual toCharArray : ()[C
    //   2008: dup
    //   2009: dup
    //   2010: iconst_4
    //   2011: dup_x1
    //   2012: caload
    //   2013: sipush #8134
    //   2016: ixor
    //   2017: i2c
    //   2018: castore
    //   2019: sipush #16095
    //   2022: iconst_0
    //   2023: iconst_4
    //   2024: invokestatic v : (Ljava/lang/Object;SIS)Ljava/lang/String;
    //   2027: invokevirtual ՙᗮ : (Ljava/lang/String;)I
    //   2030: pop
    //   2031: aload_0
    //   2032: getfield ﾞл : Lyyds/sniarbtej/ʿᵉ;
    //   2035: ifnull -> 2088
    //   2038: iinc #5, 1
    //   2041: iload_1
    //   2042: bipush #8
    //   2044: aload_0
    //   2045: getfield ﾞл : Lyyds/sniarbtej/ʿᵉ;
    //   2048: getfield ʹﮃ : I
    //   2051: iadd
    //   2052: iadd
    //   2053: istore_1
    //   2054: aload_0
    //   2055: getfield ᐨẏ : Lyyds/sniarbtej/ˌх;
    //   2058: ldc_w '㸻ད쩜驩綤끴뵂ߠ❈縮懫'
    //   2061: invokevirtual toCharArray : ()[C
    //   2064: dup
    //   2065: dup
    //   2066: bipush #7
    //   2068: dup_x1
    //   2069: caload
    //   2070: sipush #9778
    //   2073: ixor
    //   2074: i2c
    //   2075: castore
    //   2076: sipush #24355
    //   2079: iconst_2
    //   2080: iconst_1
    //   2081: invokestatic v : (Ljava/lang/Object;SIS)Ljava/lang/String;
    //   2084: invokevirtual ՙᗮ : (Ljava/lang/String;)I
    //   2087: pop
    //   2088: aload_0
    //   2089: getfield ʿᵉ : Lyyds/sniarbtej/ʿᵉ;
    //   2092: ifnull -> 2144
    //   2095: iinc #5, 1
    //   2098: iload_1
    //   2099: bipush #8
    //   2101: aload_0
    //   2102: getfield ʿᵉ : Lyyds/sniarbtej/ʿᵉ;
    //   2105: getfield ʹﮃ : I
    //   2108: iadd
    //   2109: iadd
    //   2110: istore_1
    //   2111: aload_0
    //   2112: getfield ᐨẏ : Lyyds/sniarbtej/ˌх;
    //   2115: ldc_w '삍䆇턔㾏藴⻂郚뭵ꛠ?௬늤㳪܍䢄沰粯'
    //   2118: invokevirtual toCharArray : ()[C
    //   2121: dup
    //   2122: dup
    //   2123: iconst_2
    //   2124: dup_x1
    //   2125: caload
    //   2126: sipush #21832
    //   2129: ixor
    //   2130: i2c
    //   2131: castore
    //   2132: sipush #6289
    //   2135: iconst_2
    //   2136: iconst_5
    //   2137: invokestatic v : (Ljava/lang/Object;SIS)Ljava/lang/String;
    //   2140: invokevirtual ՙᗮ : (Ljava/lang/String;)I
    //   2143: pop
    //   2144: iconst_0
    //   2145: istore #6
    //   2147: iconst_0
    //   2148: istore #7
    //   2150: aload_0
    //   2151: getfield ʿλ : I
    //   2154: ldc_w 65536
    //   2157: iand
    //   2158: ifne -> 2168
    //   2161: aload_0
    //   2162: getfield ᐨẏ : Lyyds/sniarbtej/ﾞǰ;
    //   2165: ifnull -> 2317
    //   2168: aload_0
    //   2169: getfield ᐨẏ : Lyyds/sniarbtej/ﾞǰ;
    //   2172: astore_3
    //   2173: aload_3
    //   2174: ifnull -> 2273
    //   2177: iinc #6, 1
    //   2180: iload #7
    //   2182: aload_3
    //   2183: astore #9
    //   2185: bipush #6
    //   2187: aload #9
    //   2189: getfield ᐨẏ : Lyyds/sniarbtej/ˌх;
    //   2192: iconst_0
    //   2193: aload #9
    //   2195: getfield ﾞǰ : I
    //   2198: invokestatic ᐨẏ : (Lyyds/sniarbtej/ˌх;II)I
    //   2201: iadd
    //   2202: dup
    //   2203: istore #10
    //   2205: aload #9
    //   2207: getfield ᴵʖ : Lyyds/sniarbtej/ˊ;
    //   2210: aload #9
    //   2212: getfield ﾞл : Lyyds/sniarbtej/ˊ;
    //   2215: aload #9
    //   2217: getfield ʿᵉ : Lyyds/sniarbtej/ˊ;
    //   2220: aload #9
    //   2222: getfield ʹﮃ : Lyyds/sniarbtej/ˊ;
    //   2225: invokestatic ᐨẏ : (Lyyds/sniarbtej/ˊ;Lyyds/sniarbtej/ˊ;Lyyds/sniarbtej/ˊ;Lyyds/sniarbtej/ˊ;)I
    //   2228: iadd
    //   2229: istore #10
    //   2231: aload #9
    //   2233: getfield ˊ : Lyyds/sniarbtej/ᴵʖ;
    //   2236: ifnull -> 2257
    //   2239: iload #10
    //   2241: aload #9
    //   2243: getfield ˊ : Lyyds/sniarbtej/ᴵʖ;
    //   2246: aload #9
    //   2248: getfield ᐨẏ : Lyyds/sniarbtej/ˌх;
    //   2251: invokevirtual ᐨẏ : (Lyyds/sniarbtej/ˌх;)I
    //   2254: iadd
    //   2255: istore #10
    //   2257: iload #10
    //   2259: iadd
    //   2260: istore #7
    //   2262: aload_3
    //   2263: getfield ᐨẏ : Lyyds/sniarbtej/ʼᵖ;
    //   2266: checkcast yyds/sniarbtej/ﾞǰ
    //   2269: astore_3
    //   2270: goto -> 2173
    //   2273: iinc #5, 1
    //   2276: iload_1
    //   2277: iload #7
    //   2279: bipush #8
    //   2281: iadd
    //   2282: iadd
    //   2283: istore_1
    //   2284: aload_0
    //   2285: getfield ᐨẏ : Lyyds/sniarbtej/ˌх;
    //   2288: ldc_w '닓緦ﺍ酶ꪑ⸃瞵'
    //   2291: invokevirtual toCharArray : ()[C
    //   2294: dup
    //   2295: dup
    //   2296: iconst_4
    //   2297: dup_x1
    //   2298: caload
    //   2299: sipush #19443
    //   2302: ixor
    //   2303: i2c
    //   2304: castore
    //   2305: sipush #2950
    //   2308: iconst_0
    //   2309: iconst_2
    //   2310: invokestatic v : (Ljava/lang/Object;SIS)Ljava/lang/String;
    //   2313: invokevirtual ՙᗮ : (Ljava/lang/String;)I
    //   2316: pop
    //   2317: aload_0
    //   2318: getfield ˊ : Lyyds/sniarbtej/ᴵʖ;
    //   2321: ifnull -> 2350
    //   2324: iload #5
    //   2326: aload_0
    //   2327: getfield ˊ : Lyyds/sniarbtej/ᴵʖ;
    //   2330: invokevirtual ᐨẏ : ()I
    //   2333: iadd
    //   2334: istore #5
    //   2336: iload_1
    //   2337: aload_0
    //   2338: getfield ˊ : Lyyds/sniarbtej/ᴵʖ;
    //   2341: aload_0
    //   2342: getfield ᐨẏ : Lyyds/sniarbtej/ˌх;
    //   2345: invokevirtual ᐨẏ : (Lyyds/sniarbtej/ˌх;)I
    //   2348: iadd
    //   2349: istore_1
    //   2350: iload_1
    //   2351: aload_0
    //   2352: getfield ᐨẏ : Lyyds/sniarbtej/ˌх;
    //   2355: dup
    //   2356: astore #9
    //   2358: getfield ᐝᵣ : Lyyds/sniarbtej/ʿᵉ;
    //   2361: getfield ʹﮃ : I
    //   2364: iadd
    //   2365: istore_1
    //   2366: aload_0
    //   2367: getfield ᐨẏ : Lyyds/sniarbtej/ˌх;
    //   2370: dup
    //   2371: astore #9
    //   2373: getfield ˌ : I
    //   2376: dup
    //   2377: istore_3
    //   2378: ldc 65535
    //   2380: if_icmple -> 2402
    //   2383: new yyds/sniarbtej/ՙᗮ
    //   2386: dup
    //   2387: aload_0
    //   2388: getfield ᐨẏ : Lyyds/sniarbtej/ˌх;
    //   2391: dup
    //   2392: astore #11
    //   2394: getfield ˊ : Ljava/lang/String;
    //   2397: iload_3
    //   2398: invokespecial <init> : (Ljava/lang/String;I)V
    //   2401: athrow
    //   2402: new yyds/sniarbtej/ʿᵉ
    //   2405: dup
    //   2406: iload_1
    //   2407: invokespecial <init> : (I)V
    //   2410: dup
    //   2411: astore_1
    //   2412: ldc_w -889275714
    //   2415: invokevirtual ᴵʖ : (I)Lyyds/sniarbtej/ʿᵉ;
    //   2418: aload_0
    //   2419: getfield ᔪ : I
    //   2422: invokevirtual ᴵʖ : (I)Lyyds/sniarbtej/ʿᵉ;
    //   2425: pop
    //   2426: aload_0
    //   2427: getfield ᐨẏ : Lyyds/sniarbtej/ˌх;
    //   2430: aload_1
    //   2431: astore #10
    //   2433: astore #9
    //   2435: aload #10
    //   2437: aload #9
    //   2439: getfield ˌ : I
    //   2442: invokevirtual ˊ : (I)Lyyds/sniarbtej/ʿᵉ;
    //   2445: aload #9
    //   2447: getfield ᐝᵣ : Lyyds/sniarbtej/ʿᵉ;
    //   2450: getfield ˊ : [B
    //   2453: iconst_0
    //   2454: aload #9
    //   2456: getfield ᐝᵣ : Lyyds/sniarbtej/ʿᵉ;
    //   2459: getfield ʹﮃ : I
    //   2462: invokevirtual ᐨẏ : ([BII)Lyyds/sniarbtej/ʿᵉ;
    //   2465: pop
    //   2466: aload_0
    //   2467: getfield ᔪ : I
    //   2470: ldc 65535
    //   2472: iand
    //   2473: bipush #49
    //   2475: if_icmpge -> 2484
    //   2478: sipush #4096
    //   2481: goto -> 2485
    //   2484: iconst_0
    //   2485: istore_3
    //   2486: aload_1
    //   2487: aload_0
    //   2488: getfield ʿλ : I
    //   2491: iload_3
    //   2492: iconst_m1
    //   2493: ixor
    //   2494: iand
    //   2495: invokevirtual ˊ : (I)Lyyds/sniarbtej/ʿᵉ;
    //   2498: aload_0
    //   2499: getfield ˉｓ : I
    //   2502: invokevirtual ˊ : (I)Lyyds/sniarbtej/ʿᵉ;
    //   2505: aload_0
    //   2506: getfield ʿপ : I
    //   2509: invokevirtual ˊ : (I)Lyyds/sniarbtej/ʿᵉ;
    //   2512: pop
    //   2513: aload_1
    //   2514: aload_0
    //   2515: getfield ʻล : I
    //   2518: invokevirtual ˊ : (I)Lyyds/sniarbtej/ʿᵉ;
    //   2521: pop
    //   2522: iconst_0
    //   2523: istore #8
    //   2525: iload #8
    //   2527: aload_0
    //   2528: getfield ʻล : I
    //   2531: if_icmpge -> 2552
    //   2534: aload_1
    //   2535: aload_0
    //   2536: getfield ᴵʖ : [I
    //   2539: iload #8
    //   2541: iaload
    //   2542: invokevirtual ˊ : (I)Lyyds/sniarbtej/ʿᵉ;
    //   2545: pop
    //   2546: iinc #8, 1
    //   2549: goto -> 2525
    //   2552: aload_1
    //   2553: iload_2
    //   2554: invokevirtual ˊ : (I)Lyyds/sniarbtej/ʿᵉ;
    //   2557: pop
    //   2558: aload_0
    //   2559: getfield ᐨẏ : Lyyds/sniarbtej/ˌ;
    //   2562: astore_3
    //   2563: aload_3
    //   2564: ifnull -> 2916
    //   2567: aload_3
    //   2568: aload_1
    //   2569: astore #10
    //   2571: dup
    //   2572: astore #9
    //   2574: getfield ᐨẏ : Lyyds/sniarbtej/ˌх;
    //   2577: dup
    //   2578: astore #11
    //   2580: getfield Ԇ : I
    //   2583: bipush #49
    //   2585: if_icmpge -> 2592
    //   2588: iconst_1
    //   2589: goto -> 2593
    //   2592: iconst_0
    //   2593: dup
    //   2594: istore #11
    //   2596: ifeq -> 2605
    //   2599: sipush #4096
    //   2602: goto -> 2606
    //   2605: iconst_0
    //   2606: istore #12
    //   2608: aload #10
    //   2610: aload #9
    //   2612: getfield ʿλ : I
    //   2615: iload #12
    //   2617: iconst_m1
    //   2618: ixor
    //   2619: iand
    //   2620: invokevirtual ˊ : (I)Lyyds/sniarbtej/ʿᵉ;
    //   2623: aload #9
    //   2625: getfield ᐝт : I
    //   2628: invokevirtual ˊ : (I)Lyyds/sniarbtej/ʿᵉ;
    //   2631: aload #9
    //   2633: getfield ɟ : I
    //   2636: invokevirtual ˊ : (I)Lyyds/sniarbtej/ʿᵉ;
    //   2639: pop
    //   2640: iconst_0
    //   2641: istore #12
    //   2643: aload #9
    //   2645: getfield ʿｱ : I
    //   2648: ifeq -> 2654
    //   2651: iinc #12, 1
    //   2654: aload #9
    //   2656: getfield ʿλ : I
    //   2659: sipush #4096
    //   2662: iand
    //   2663: ifeq -> 2674
    //   2666: iload #11
    //   2668: ifeq -> 2674
    //   2671: iinc #12, 1
    //   2674: aload #9
    //   2676: getfield ﾞǰ : I
    //   2679: ifeq -> 2685
    //   2682: iinc #12, 1
    //   2685: aload #9
    //   2687: getfield ʿλ : I
    //   2690: ldc_w 131072
    //   2693: iand
    //   2694: ifeq -> 2700
    //   2697: iinc #12, 1
    //   2700: aload #9
    //   2702: getfield ᴵʖ : Lyyds/sniarbtej/ˊ;
    //   2705: ifnull -> 2711
    //   2708: iinc #12, 1
    //   2711: aload #9
    //   2713: getfield ﾞл : Lyyds/sniarbtej/ˊ;
    //   2716: ifnull -> 2722
    //   2719: iinc #12, 1
    //   2722: aload #9
    //   2724: getfield ʿᵉ : Lyyds/sniarbtej/ˊ;
    //   2727: ifnull -> 2733
    //   2730: iinc #12, 1
    //   2733: aload #9
    //   2735: getfield ʹﮃ : Lyyds/sniarbtej/ˊ;
    //   2738: ifnull -> 2744
    //   2741: iinc #12, 1
    //   2744: aload #9
    //   2746: getfield ˊ : Lyyds/sniarbtej/ᴵʖ;
    //   2749: ifnull -> 2765
    //   2752: iload #12
    //   2754: aload #9
    //   2756: getfield ˊ : Lyyds/sniarbtej/ᴵʖ;
    //   2759: invokevirtual ᐨẏ : ()I
    //   2762: iadd
    //   2763: istore #12
    //   2765: aload #10
    //   2767: iload #12
    //   2769: invokevirtual ˊ : (I)Lyyds/sniarbtej/ʿᵉ;
    //   2772: pop
    //   2773: aload #9
    //   2775: getfield ʿｱ : I
    //   2778: ifeq -> 2832
    //   2781: aload #10
    //   2783: aload #9
    //   2785: getfield ᐨẏ : Lyyds/sniarbtej/ˌх;
    //   2788: ldc_w 'ꮀ壆뭣銠䎶沞་箰ĥ羀暃'
    //   2791: invokevirtual toCharArray : ()[C
    //   2794: dup
    //   2795: dup
    //   2796: iconst_1
    //   2797: dup_x1
    //   2798: caload
    //   2799: sipush #28483
    //   2802: ixor
    //   2803: i2c
    //   2804: castore
    //   2805: sipush #7096
    //   2808: iconst_4
    //   2809: iconst_3
    //   2810: invokestatic v : (Ljava/lang/Object;SIS)Ljava/lang/String;
    //   2813: invokevirtual ՙᗮ : (Ljava/lang/String;)I
    //   2816: invokevirtual ˊ : (I)Lyyds/sniarbtej/ʿᵉ;
    //   2819: iconst_2
    //   2820: invokevirtual ᴵʖ : (I)Lyyds/sniarbtej/ʿᵉ;
    //   2823: aload #9
    //   2825: getfield ʿｱ : I
    //   2828: invokevirtual ˊ : (I)Lyyds/sniarbtej/ʿᵉ;
    //   2831: pop
    //   2832: aload #9
    //   2834: getfield ᐨẏ : Lyyds/sniarbtej/ˌх;
    //   2837: aload #9
    //   2839: getfield ʿλ : I
    //   2842: aload #9
    //   2844: getfield ﾞǰ : I
    //   2847: aload #10
    //   2849: invokestatic ᐨẏ : (Lyyds/sniarbtej/ˌх;IILyyds/sniarbtej/ʿᵉ;)V
    //   2852: aload #9
    //   2854: getfield ᐨẏ : Lyyds/sniarbtej/ˌх;
    //   2857: aload #9
    //   2859: getfield ᴵʖ : Lyyds/sniarbtej/ˊ;
    //   2862: aload #9
    //   2864: getfield ﾞл : Lyyds/sniarbtej/ˊ;
    //   2867: aload #9
    //   2869: getfield ʿᵉ : Lyyds/sniarbtej/ˊ;
    //   2872: aload #9
    //   2874: getfield ʹﮃ : Lyyds/sniarbtej/ˊ;
    //   2877: aload #10
    //   2879: invokestatic ᐨẏ : (Lyyds/sniarbtej/ˌх;Lyyds/sniarbtej/ˊ;Lyyds/sniarbtej/ˊ;Lyyds/sniarbtej/ˊ;Lyyds/sniarbtej/ˊ;Lyyds/sniarbtej/ʿᵉ;)V
    //   2882: aload #9
    //   2884: getfield ˊ : Lyyds/sniarbtej/ᴵʖ;
    //   2887: ifnull -> 2905
    //   2890: aload #9
    //   2892: getfield ˊ : Lyyds/sniarbtej/ᴵʖ;
    //   2895: aload #9
    //   2897: getfield ᐨẏ : Lyyds/sniarbtej/ˌх;
    //   2900: aload #10
    //   2902: invokevirtual ᐨẏ : (Lyyds/sniarbtej/ˌх;Lyyds/sniarbtej/ʿᵉ;)V
    //   2905: aload_3
    //   2906: getfield ᐨẏ : Lyyds/sniarbtej/ᴵƚ;
    //   2909: checkcast yyds/sniarbtej/ˌ
    //   2912: astore_3
    //   2913: goto -> 2563
    //   2916: aload_1
    //   2917: iload #4
    //   2919: invokevirtual ˊ : (I)Lyyds/sniarbtej/ʿᵉ;
    //   2922: pop
    //   2923: iconst_0
    //   2924: istore #8
    //   2926: iconst_0
    //   2927: istore_2
    //   2928: aload_0
    //   2929: getfield ᐨẏ : Lyyds/sniarbtej/ʿপ;
    //   2932: astore_3
    //   2933: aload_3
    //   2934: ifnull -> 4836
    //   2937: iload #8
    //   2939: aload_3
    //   2940: dup
    //   2941: astore #9
    //   2943: getfield ᓑ : I
    //   2946: ifle -> 2953
    //   2949: iconst_1
    //   2950: goto -> 2954
    //   2953: iconst_0
    //   2954: ior
    //   2955: istore #8
    //   2957: iload_2
    //   2958: aload_3
    //   2959: dup
    //   2960: astore #9
    //   2962: getfield ﾞл : Z
    //   2965: ior
    //   2966: istore_2
    //   2967: aload_3
    //   2968: aload_1
    //   2969: astore #10
    //   2971: dup
    //   2972: astore #9
    //   2974: getfield ᐨẏ : Lyyds/sniarbtej/ˌх;
    //   2977: dup
    //   2978: astore #11
    //   2980: getfield Ԇ : I
    //   2983: bipush #49
    //   2985: if_icmpge -> 2992
    //   2988: iconst_1
    //   2989: goto -> 2993
    //   2992: iconst_0
    //   2993: dup
    //   2994: istore #11
    //   2996: ifeq -> 3005
    //   2999: sipush #4096
    //   3002: goto -> 3006
    //   3005: iconst_0
    //   3006: istore #12
    //   3008: aload #10
    //   3010: aload #9
    //   3012: getfield ʿλ : I
    //   3015: iload #12
    //   3017: iconst_m1
    //   3018: ixor
    //   3019: iand
    //   3020: invokevirtual ˊ : (I)Lyyds/sniarbtej/ʿᵉ;
    //   3023: aload #9
    //   3025: getfield ᐝт : I
    //   3028: invokevirtual ˊ : (I)Lyyds/sniarbtej/ʿᵉ;
    //   3031: aload #9
    //   3033: getfield ɟ : I
    //   3036: invokevirtual ˊ : (I)Lyyds/sniarbtej/ʿᵉ;
    //   3039: pop
    //   3040: aload #9
    //   3042: getfield ᴵ氵 : I
    //   3045: ifeq -> 3081
    //   3048: aload #10
    //   3050: aload #9
    //   3052: getfield ᐨẏ : Lyyds/sniarbtej/ˌх;
    //   3055: dup
    //   3056: astore #11
    //   3058: getfield ᐨẏ : Lyyds/sniarbtej/ᐨم;
    //   3061: getfield ﾞл : [B
    //   3064: aload #9
    //   3066: getfield ᴵ氵 : I
    //   3069: aload #9
    //   3071: getfield ᵊ : I
    //   3074: invokevirtual ᐨẏ : ([BII)Lyyds/sniarbtej/ʿᵉ;
    //   3077: pop
    //   3078: goto -> 4825
    //   3081: iconst_0
    //   3082: istore #12
    //   3084: aload #9
    //   3086: getfield ʹﮃ : Lyyds/sniarbtej/ʿᵉ;
    //   3089: getfield ʹﮃ : I
    //   3092: ifle -> 3098
    //   3095: iinc #12, 1
    //   3098: aload #9
    //   3100: getfield ٴῪ : I
    //   3103: ifle -> 3109
    //   3106: iinc #12, 1
    //   3109: aload #9
    //   3111: getfield ʿλ : I
    //   3114: sipush #4096
    //   3117: iand
    //   3118: ifeq -> 3129
    //   3121: iload #11
    //   3123: ifeq -> 3129
    //   3126: iinc #12, 1
    //   3129: aload #9
    //   3131: getfield ﾞǰ : I
    //   3134: ifeq -> 3140
    //   3137: iinc #12, 1
    //   3140: aload #9
    //   3142: getfield ʿλ : I
    //   3145: ldc_w 131072
    //   3148: iand
    //   3149: ifeq -> 3155
    //   3152: iinc #12, 1
    //   3155: aload #9
    //   3157: getfield ᴵʖ : Lyyds/sniarbtej/ˊ;
    //   3160: ifnull -> 3166
    //   3163: iinc #12, 1
    //   3166: aload #9
    //   3168: getfield ﾞл : Lyyds/sniarbtej/ˊ;
    //   3171: ifnull -> 3177
    //   3174: iinc #12, 1
    //   3177: aload #9
    //   3179: getfield ᐨẏ : [Lyyds/sniarbtej/ˊ;
    //   3182: ifnull -> 3188
    //   3185: iinc #12, 1
    //   3188: aload #9
    //   3190: getfield ˊ : [Lyyds/sniarbtej/ˊ;
    //   3193: ifnull -> 3199
    //   3196: iinc #12, 1
    //   3199: aload #9
    //   3201: getfield ʿᵉ : Lyyds/sniarbtej/ˊ;
    //   3204: ifnull -> 3210
    //   3207: iinc #12, 1
    //   3210: aload #9
    //   3212: getfield ʹﮃ : Lyyds/sniarbtej/ˊ;
    //   3215: ifnull -> 3221
    //   3218: iinc #12, 1
    //   3221: aload #9
    //   3223: getfield ᐨم : Lyyds/sniarbtej/ʿᵉ;
    //   3226: ifnull -> 3232
    //   3229: iinc #12, 1
    //   3232: aload #9
    //   3234: getfield ʾ : Lyyds/sniarbtej/ʿᵉ;
    //   3237: ifnull -> 3243
    //   3240: iinc #12, 1
    //   3243: aload #9
    //   3245: getfield ˊ : Lyyds/sniarbtej/ᴵʖ;
    //   3248: ifnull -> 3264
    //   3251: iload #12
    //   3253: aload #9
    //   3255: getfield ˊ : Lyyds/sniarbtej/ᴵʖ;
    //   3258: invokevirtual ᐨẏ : ()I
    //   3261: iadd
    //   3262: istore #12
    //   3264: aload #10
    //   3266: iload #12
    //   3268: invokevirtual ˊ : (I)Lyyds/sniarbtej/ʿᵉ;
    //   3271: pop
    //   3272: aload #9
    //   3274: getfield ʹﮃ : Lyyds/sniarbtej/ʿᵉ;
    //   3277: getfield ʹﮃ : I
    //   3280: ifle -> 4329
    //   3283: bipush #10
    //   3285: aload #9
    //   3287: getfield ʹﮃ : Lyyds/sniarbtej/ʿᵉ;
    //   3290: getfield ʹﮃ : I
    //   3293: iadd
    //   3294: aload #9
    //   3296: getfield ᐨẏ : Lyyds/sniarbtej/ˌᑦ;
    //   3299: invokestatic ˊ : (Lyyds/sniarbtej/ˌᑦ;)I
    //   3302: iadd
    //   3303: istore #4
    //   3305: iconst_0
    //   3306: istore #13
    //   3308: aload #9
    //   3310: getfield ʾܪ : Lyyds/sniarbtej/ʿᵉ;
    //   3313: ifnull -> 3335
    //   3316: iload #4
    //   3318: bipush #8
    //   3320: aload #9
    //   3322: getfield ʾܪ : Lyyds/sniarbtej/ʿᵉ;
    //   3325: getfield ʹﮃ : I
    //   3328: iadd
    //   3329: iadd
    //   3330: istore #4
    //   3332: iinc #13, 1
    //   3335: aload #9
    //   3337: getfield ՙᗮ : Lyyds/sniarbtej/ʿᵉ;
    //   3340: ifnull -> 3362
    //   3343: iload #4
    //   3345: bipush #8
    //   3347: aload #9
    //   3349: getfield ՙᗮ : Lyyds/sniarbtej/ʿᵉ;
    //   3352: getfield ʹﮃ : I
    //   3355: iadd
    //   3356: iadd
    //   3357: istore #4
    //   3359: iinc #13, 1
    //   3362: aload #9
    //   3364: getfield ˍɫ : Lyyds/sniarbtej/ʿᵉ;
    //   3367: ifnull -> 3389
    //   3370: iload #4
    //   3372: bipush #8
    //   3374: aload #9
    //   3376: getfield ˍɫ : Lyyds/sniarbtej/ʿᵉ;
    //   3379: getfield ʹﮃ : I
    //   3382: iadd
    //   3383: iadd
    //   3384: istore #4
    //   3386: iinc #13, 1
    //   3389: aload #9
    //   3391: getfield ʽ : Lyyds/sniarbtej/ʿᵉ;
    //   3394: ifnull -> 3416
    //   3397: iload #4
    //   3399: bipush #8
    //   3401: aload #9
    //   3403: getfield ʽ : Lyyds/sniarbtej/ʿᵉ;
    //   3406: getfield ʹﮃ : I
    //   3409: iadd
    //   3410: iadd
    //   3411: istore #4
    //   3413: iinc #13, 1
    //   3416: aload #9
    //   3418: getfield ՙᗮ : Lyyds/sniarbtej/ˊ;
    //   3421: ifnull -> 3466
    //   3424: iload #4
    //   3426: aload #9
    //   3428: getfield ՙᗮ : Lyyds/sniarbtej/ˊ;
    //   3431: ldc_w '▮ﺒ⃪৤蠴㬽ǟ⯴㍛㹏꓆䅹壧燭࢜࿤ꦼ퉍㥺㌴쨆꒼ꬫ韐䃜伧✊ѳᖘ'
    //   3434: invokevirtual toCharArray : ()[C
    //   3437: dup
    //   3438: dup
    //   3439: bipush #18
    //   3441: dup_x1
    //   3442: caload
    //   3443: sipush #21465
    //   3446: ixor
    //   3447: i2c
    //   3448: castore
    //   3449: sipush #6342
    //   3452: iconst_2
    //   3453: iconst_4
    //   3454: invokestatic v : (Ljava/lang/Object;SIS)Ljava/lang/String;
    //   3457: invokevirtual ᐨẏ : (Ljava/lang/String;)I
    //   3460: iadd
    //   3461: istore #4
    //   3463: iinc #13, 1
    //   3466: aload #9
    //   3468: getfield ˍɫ : Lyyds/sniarbtej/ˊ;
    //   3471: ifnull -> 3516
    //   3474: iload #4
    //   3476: aload #9
    //   3478: getfield ˍɫ : Lyyds/sniarbtej/ˊ;
    //   3481: ldc_w '꾦裯⅏국쮚풱ꗟ㷓ی㪡롂㽠秚㼧귌᪍⎌蔖ﷇ梏㟢亨䧐缷겄စ㓟㜜ڴ'
    //   3484: invokevirtual toCharArray : ()[C
    //   3487: dup
    //   3488: dup
    //   3489: bipush #30
    //   3491: dup_x1
    //   3492: caload
    //   3493: sipush #32708
    //   3496: ixor
    //   3497: i2c
    //   3498: castore
    //   3499: sipush #27541
    //   3502: iconst_4
    //   3503: iconst_0
    //   3504: invokestatic v : (Ljava/lang/Object;SIS)Ljava/lang/String;
    //   3507: invokevirtual ᐨẏ : (Ljava/lang/String;)I
    //   3510: iadd
    //   3511: istore #4
    //   3513: iinc #13, 1
    //   3516: aload #9
    //   3518: getfield ᴵʖ : Lyyds/sniarbtej/ᴵʖ;
    //   3521: ifnull -> 3581
    //   3524: iload #4
    //   3526: aload #9
    //   3528: getfield ᴵʖ : Lyyds/sniarbtej/ᴵʖ;
    //   3531: aload #9
    //   3533: getfield ᐨẏ : Lyyds/sniarbtej/ˌх;
    //   3536: aload #9
    //   3538: getfield ʹﮃ : Lyyds/sniarbtej/ʿᵉ;
    //   3541: getfield ˊ : [B
    //   3544: aload #9
    //   3546: getfield ʹﮃ : Lyyds/sniarbtej/ʿᵉ;
    //   3549: getfield ʹﮃ : I
    //   3552: aload #9
    //   3554: getfield ˑỲ : I
    //   3557: aload #9
    //   3559: getfield ˌپ : I
    //   3562: invokevirtual ᐨẏ : (Lyyds/sniarbtej/ˌх;[BIII)I
    //   3565: iadd
    //   3566: istore #4
    //   3568: iload #13
    //   3570: aload #9
    //   3572: getfield ᴵʖ : Lyyds/sniarbtej/ᴵʖ;
    //   3575: invokevirtual ᐨẏ : ()I
    //   3578: iadd
    //   3579: istore #13
    //   3581: aload #10
    //   3583: aload #9
    //   3585: getfield ᐨẏ : Lyyds/sniarbtej/ˌх;
    //   3588: ldc_w '洌숙兤?⃫'
    //   3591: invokevirtual toCharArray : ()[C
    //   3594: dup
    //   3595: dup
    //   3596: iconst_0
    //   3597: dup_x1
    //   3598: caload
    //   3599: sipush #8634
    //   3602: ixor
    //   3603: i2c
    //   3604: castore
    //   3605: sipush #31131
    //   3608: iconst_5
    //   3609: iconst_4
    //   3610: invokestatic v : (Ljava/lang/Object;SIS)Ljava/lang/String;
    //   3613: invokevirtual ՙᗮ : (Ljava/lang/String;)I
    //   3616: invokevirtual ˊ : (I)Lyyds/sniarbtej/ʿᵉ;
    //   3619: iload #4
    //   3621: invokevirtual ᴵʖ : (I)Lyyds/sniarbtej/ʿᵉ;
    //   3624: aload #9
    //   3626: getfield ˑỲ : I
    //   3629: invokevirtual ˊ : (I)Lyyds/sniarbtej/ʿᵉ;
    //   3632: aload #9
    //   3634: getfield ˌپ : I
    //   3637: invokevirtual ˊ : (I)Lyyds/sniarbtej/ʿᵉ;
    //   3640: aload #9
    //   3642: getfield ʹﮃ : Lyyds/sniarbtej/ʿᵉ;
    //   3645: getfield ʹﮃ : I
    //   3648: invokevirtual ᴵʖ : (I)Lyyds/sniarbtej/ʿᵉ;
    //   3651: aload #9
    //   3653: getfield ʹﮃ : Lyyds/sniarbtej/ʿᵉ;
    //   3656: getfield ˊ : [B
    //   3659: iconst_0
    //   3660: aload #9
    //   3662: getfield ʹﮃ : Lyyds/sniarbtej/ʿᵉ;
    //   3665: getfield ʹﮃ : I
    //   3668: invokevirtual ᐨẏ : ([BII)Lyyds/sniarbtej/ʿᵉ;
    //   3671: pop
    //   3672: aload #9
    //   3674: getfield ᐨẏ : Lyyds/sniarbtej/ˌᑦ;
    //   3677: aload #10
    //   3679: astore #16
    //   3681: astore #15
    //   3683: aload #16
    //   3685: aload #15
    //   3687: invokestatic ᐨẏ : (Lyyds/sniarbtej/ˌᑦ;)I
    //   3690: invokevirtual ˊ : (I)Lyyds/sniarbtej/ʿᵉ;
    //   3693: pop
    //   3694: aload #15
    //   3696: astore #4
    //   3698: aload #4
    //   3700: ifnull -> 3757
    //   3703: aload #16
    //   3705: aload #4
    //   3707: getfield ᴵʖ : Lyyds/sniarbtej/ᔪ;
    //   3710: getfield ʻบ : I
    //   3713: invokevirtual ˊ : (I)Lyyds/sniarbtej/ʿᵉ;
    //   3716: aload #4
    //   3718: getfield ﾞл : Lyyds/sniarbtej/ᔪ;
    //   3721: getfield ʻบ : I
    //   3724: invokevirtual ˊ : (I)Lyyds/sniarbtej/ʿᵉ;
    //   3727: aload #4
    //   3729: getfield ʿᵉ : Lyyds/sniarbtej/ᔪ;
    //   3732: getfield ʻบ : I
    //   3735: invokevirtual ˊ : (I)Lyyds/sniarbtej/ʿᵉ;
    //   3738: aload #4
    //   3740: getfield ڊ : I
    //   3743: invokevirtual ˊ : (I)Lyyds/sniarbtej/ʿᵉ;
    //   3746: pop
    //   3747: aload #4
    //   3749: getfield ᴵʖ : Lyyds/sniarbtej/ˌᑦ;
    //   3752: astore #4
    //   3754: goto -> 3698
    //   3757: aload #10
    //   3759: iload #13
    //   3761: invokevirtual ˊ : (I)Lyyds/sniarbtej/ʿᵉ;
    //   3764: pop
    //   3765: aload #9
    //   3767: getfield ʾܪ : Lyyds/sniarbtej/ʿᵉ;
    //   3770: ifnull -> 3910
    //   3773: aload #9
    //   3775: getfield ᐨẏ : Lyyds/sniarbtej/ˌх;
    //   3778: dup
    //   3779: astore #11
    //   3781: getfield Ԇ : I
    //   3784: bipush #50
    //   3786: if_icmplt -> 3793
    //   3789: iconst_1
    //   3790: goto -> 3794
    //   3793: iconst_0
    //   3794: istore #14
    //   3796: aload #10
    //   3798: aload #9
    //   3800: getfield ᐨẏ : Lyyds/sniarbtej/ˌх;
    //   3803: iload #14
    //   3805: ifeq -> 3837
    //   3808: ldc_w 'ꌂ僉庎ཇὄ㫎푸?∁ꚣ㫐虌潚'
    //   3811: invokevirtual toCharArray : ()[C
    //   3814: dup
    //   3815: dup
    //   3816: bipush #10
    //   3818: dup_x1
    //   3819: caload
    //   3820: sipush #20409
    //   3823: ixor
    //   3824: i2c
    //   3825: castore
    //   3826: sipush #22519
    //   3829: iconst_3
    //   3830: iconst_5
    //   3831: invokestatic v : (Ljava/lang/Object;SIS)Ljava/lang/String;
    //   3834: goto -> 3862
    //   3837: ldc_w '駛ꘟᭁꙉ䧱蚣⥶꫱䫀'
    //   3840: invokevirtual toCharArray : ()[C
    //   3843: dup
    //   3844: dup
    //   3845: iconst_5
    //   3846: dup_x1
    //   3847: caload
    //   3848: sipush #31458
    //   3851: ixor
    //   3852: i2c
    //   3853: castore
    //   3854: sipush #10689
    //   3857: iconst_0
    //   3858: iconst_4
    //   3859: invokestatic v : (Ljava/lang/Object;SIS)Ljava/lang/String;
    //   3862: invokevirtual ՙᗮ : (Ljava/lang/String;)I
    //   3865: invokevirtual ˊ : (I)Lyyds/sniarbtej/ʿᵉ;
    //   3868: iconst_2
    //   3869: aload #9
    //   3871: getfield ʾܪ : Lyyds/sniarbtej/ʿᵉ;
    //   3874: getfield ʹﮃ : I
    //   3877: iadd
    //   3878: invokevirtual ᴵʖ : (I)Lyyds/sniarbtej/ʿᵉ;
    //   3881: aload #9
    //   3883: getfield ᓑ : I
    //   3886: invokevirtual ˊ : (I)Lyyds/sniarbtej/ʿᵉ;
    //   3889: aload #9
    //   3891: getfield ʾܪ : Lyyds/sniarbtej/ʿᵉ;
    //   3894: getfield ˊ : [B
    //   3897: iconst_0
    //   3898: aload #9
    //   3900: getfield ʾܪ : Lyyds/sniarbtej/ʿᵉ;
    //   3903: getfield ʹﮃ : I
    //   3906: invokevirtual ᐨẏ : ([BII)Lyyds/sniarbtej/ʿᵉ;
    //   3909: pop
    //   3910: aload #9
    //   3912: getfield ՙᗮ : Lyyds/sniarbtej/ʿᵉ;
    //   3915: ifnull -> 3999
    //   3918: aload #10
    //   3920: aload #9
    //   3922: getfield ᐨẏ : Lyyds/sniarbtej/ˌх;
    //   3925: ldc_w '꜕蒿떁鸒祼놠晘澭૭肰䲡熚僖३呠發'
    //   3928: invokevirtual toCharArray : ()[C
    //   3931: dup
    //   3932: dup
    //   3933: bipush #13
    //   3935: dup_x1
    //   3936: caload
    //   3937: sipush #22142
    //   3940: ixor
    //   3941: i2c
    //   3942: castore
    //   3943: sipush #15192
    //   3946: iconst_3
    //   3947: iconst_2
    //   3948: invokestatic v : (Ljava/lang/Object;SIS)Ljava/lang/String;
    //   3951: invokevirtual ՙᗮ : (Ljava/lang/String;)I
    //   3954: invokevirtual ˊ : (I)Lyyds/sniarbtej/ʿᵉ;
    //   3957: iconst_2
    //   3958: aload #9
    //   3960: getfield ՙᗮ : Lyyds/sniarbtej/ʿᵉ;
    //   3963: getfield ʹﮃ : I
    //   3966: iadd
    //   3967: invokevirtual ᴵʖ : (I)Lyyds/sniarbtej/ʿᵉ;
    //   3970: aload #9
    //   3972: getfield ﾞﮢ : I
    //   3975: invokevirtual ˊ : (I)Lyyds/sniarbtej/ʿᵉ;
    //   3978: aload #9
    //   3980: getfield ՙᗮ : Lyyds/sniarbtej/ʿᵉ;
    //   3983: getfield ˊ : [B
    //   3986: iconst_0
    //   3987: aload #9
    //   3989: getfield ՙᗮ : Lyyds/sniarbtej/ʿᵉ;
    //   3992: getfield ʹﮃ : I
    //   3995: invokevirtual ᐨẏ : ([BII)Lyyds/sniarbtej/ʿᵉ;
    //   3998: pop
    //   3999: aload #9
    //   4001: getfield ˍɫ : Lyyds/sniarbtej/ʿᵉ;
    //   4004: ifnull -> 4088
    //   4007: aload #10
    //   4009: aload #9
    //   4011: getfield ᐨẏ : Lyyds/sniarbtej/ˌх;
    //   4014: ldc_w '端砙騫齐˵⡿魏蹊䥸㣻䑨ꮾ뽨⍙嚄'
    //   4017: invokevirtual toCharArray : ()[C
    //   4020: dup
    //   4021: dup
    //   4022: bipush #7
    //   4024: dup_x1
    //   4025: caload
    //   4026: sipush #16912
    //   4029: ixor
    //   4030: i2c
    //   4031: castore
    //   4032: sipush #22602
    //   4035: iconst_2
    //   4036: iconst_4
    //   4037: invokestatic v : (Ljava/lang/Object;SIS)Ljava/lang/String;
    //   4040: invokevirtual ՙᗮ : (Ljava/lang/String;)I
    //   4043: invokevirtual ˊ : (I)Lyyds/sniarbtej/ʿᵉ;
    //   4046: iconst_2
    //   4047: aload #9
    //   4049: getfield ˍɫ : Lyyds/sniarbtej/ʿᵉ;
    //   4052: getfield ʹﮃ : I
    //   4055: iadd
    //   4056: invokevirtual ᴵʖ : (I)Lyyds/sniarbtej/ʿᵉ;
    //   4059: aload #9
    //   4061: getfield ﾞﾇ : I
    //   4064: invokevirtual ˊ : (I)Lyyds/sniarbtej/ʿᵉ;
    //   4067: aload #9
    //   4069: getfield ˍɫ : Lyyds/sniarbtej/ʿᵉ;
    //   4072: getfield ˊ : [B
    //   4075: iconst_0
    //   4076: aload #9
    //   4078: getfield ˍɫ : Lyyds/sniarbtej/ʿᵉ;
    //   4081: getfield ʹﮃ : I
    //   4084: invokevirtual ᐨẏ : ([BII)Lyyds/sniarbtej/ʿᵉ;
    //   4087: pop
    //   4088: aload #9
    //   4090: getfield ʽ : Lyyds/sniarbtej/ʿᵉ;
    //   4093: ifnull -> 4177
    //   4096: aload #10
    //   4098: aload #9
    //   4100: getfield ᐨẏ : Lyyds/sniarbtej/ˌх;
    //   4103: ldc_w '嬘퐠埶쩣ᬹ㴺ዖ雦?๕롻䢂⤔䘛짳敇這슪멃훗ᅁ⴨'
    //   4106: invokevirtual toCharArray : ()[C
    //   4109: dup
    //   4110: dup
    //   4111: bipush #16
    //   4113: dup_x1
    //   4114: caload
    //   4115: sipush #20170
    //   4118: ixor
    //   4119: i2c
    //   4120: castore
    //   4121: sipush #4140
    //   4124: iconst_1
    //   4125: iconst_5
    //   4126: invokestatic v : (Ljava/lang/Object;SIS)Ljava/lang/String;
    //   4129: invokevirtual ՙᗮ : (Ljava/lang/String;)I
    //   4132: invokevirtual ˊ : (I)Lyyds/sniarbtej/ʿᵉ;
    //   4135: iconst_2
    //   4136: aload #9
    //   4138: getfield ʽ : Lyyds/sniarbtej/ʿᵉ;
    //   4141: getfield ʹﮃ : I
    //   4144: iadd
    //   4145: invokevirtual ᴵʖ : (I)Lyyds/sniarbtej/ʿᵉ;
    //   4148: aload #9
    //   4150: getfield ˍʶ : I
    //   4153: invokevirtual ˊ : (I)Lyyds/sniarbtej/ʿᵉ;
    //   4156: aload #9
    //   4158: getfield ʽ : Lyyds/sniarbtej/ʿᵉ;
    //   4161: getfield ˊ : [B
    //   4164: iconst_0
    //   4165: aload #9
    //   4167: getfield ʽ : Lyyds/sniarbtej/ʿᵉ;
    //   4170: getfield ʹﮃ : I
    //   4173: invokevirtual ᐨẏ : ([BII)Lyyds/sniarbtej/ʿᵉ;
    //   4176: pop
    //   4177: aload #9
    //   4179: getfield ՙᗮ : Lyyds/sniarbtej/ˊ;
    //   4182: ifnull -> 4229
    //   4185: aload #9
    //   4187: getfield ՙᗮ : Lyyds/sniarbtej/ˊ;
    //   4190: aload #9
    //   4192: getfield ᐨẏ : Lyyds/sniarbtej/ˌх;
    //   4195: ldc_w '簘岋񄫻豇㘚㧛ಋŻ늽ꖼ뾚ⅉᗡ좳܁铠폔镥᧘ꫭ㸍ᙲ䑐♂'
    //   4198: invokevirtual toCharArray : ()[C
    //   4201: dup
    //   4202: dup
    //   4203: bipush #25
    //   4205: dup_x1
    //   4206: caload
    //   4207: sipush #9032
    //   4210: ixor
    //   4211: i2c
    //   4212: castore
    //   4213: sipush #5153
    //   4216: iconst_1
    //   4217: iconst_3
    //   4218: invokestatic v : (Ljava/lang/Object;SIS)Ljava/lang/String;
    //   4221: invokevirtual ՙᗮ : (Ljava/lang/String;)I
    //   4224: aload #10
    //   4226: invokevirtual ᐨẏ : (ILyyds/sniarbtej/ʿᵉ;)V
    //   4229: aload #9
    //   4231: getfield ˍɫ : Lyyds/sniarbtej/ˊ;
    //   4234: ifnull -> 4280
    //   4237: aload #9
    //   4239: getfield ˍɫ : Lyyds/sniarbtej/ˊ;
    //   4242: aload #9
    //   4244: getfield ᐨẏ : Lyyds/sniarbtej/ˌх;
    //   4247: ldc_w 'ⓗ쎶胄櫞麋᰹燨⺙ȱ᫗盛葵㝅⫢洅棘ዀﻈ厨뵫ᣔ튭ⱌ勆炝癘ࣄ൰쇳崉'
    //   4250: invokevirtual toCharArray : ()[C
    //   4253: dup
    //   4254: dup
    //   4255: iconst_5
    //   4256: dup_x1
    //   4257: caload
    //   4258: sipush #2196
    //   4261: ixor
    //   4262: i2c
    //   4263: castore
    //   4264: sipush #24297
    //   4267: iconst_4
    //   4268: iconst_4
    //   4269: invokestatic v : (Ljava/lang/Object;SIS)Ljava/lang/String;
    //   4272: invokevirtual ՙᗮ : (Ljava/lang/String;)I
    //   4275: aload #10
    //   4277: invokevirtual ᐨẏ : (ILyyds/sniarbtej/ʿᵉ;)V
    //   4280: aload #9
    //   4282: getfield ᴵʖ : Lyyds/sniarbtej/ᴵʖ;
    //   4285: ifnull -> 4329
    //   4288: aload #9
    //   4290: getfield ᴵʖ : Lyyds/sniarbtej/ᴵʖ;
    //   4293: aload #9
    //   4295: getfield ᐨẏ : Lyyds/sniarbtej/ˌх;
    //   4298: aload #9
    //   4300: getfield ʹﮃ : Lyyds/sniarbtej/ʿᵉ;
    //   4303: getfield ˊ : [B
    //   4306: aload #9
    //   4308: getfield ʹﮃ : Lyyds/sniarbtej/ʿᵉ;
    //   4311: getfield ʹﮃ : I
    //   4314: aload #9
    //   4316: getfield ˑỲ : I
    //   4319: aload #9
    //   4321: getfield ˌپ : I
    //   4324: aload #10
    //   4326: invokevirtual ᐨẏ : (Lyyds/sniarbtej/ˌх;[BIIILyyds/sniarbtej/ʿᵉ;)V
    //   4329: aload #9
    //   4331: getfield ٴῪ : I
    //   4334: ifle -> 4438
    //   4337: aload #10
    //   4339: aload #9
    //   4341: getfield ᐨẏ : Lyyds/sniarbtej/ˌх;
    //   4344: ldc_w '濣ለ遁얹짳㙠柭뷁옟ൂ'
    //   4347: invokevirtual toCharArray : ()[C
    //   4350: dup
    //   4351: dup
    //   4352: iconst_5
    //   4353: dup_x1
    //   4354: caload
    //   4355: sipush #7556
    //   4358: ixor
    //   4359: i2c
    //   4360: castore
    //   4361: sipush #4778
    //   4364: iconst_0
    //   4365: iconst_1
    //   4366: invokestatic v : (Ljava/lang/Object;SIS)Ljava/lang/String;
    //   4369: invokevirtual ՙᗮ : (Ljava/lang/String;)I
    //   4372: invokevirtual ˊ : (I)Lyyds/sniarbtej/ʿᵉ;
    //   4375: iconst_2
    //   4376: iconst_2
    //   4377: aload #9
    //   4379: getfield ٴῪ : I
    //   4382: imul
    //   4383: iadd
    //   4384: invokevirtual ᴵʖ : (I)Lyyds/sniarbtej/ʿᵉ;
    //   4387: aload #9
    //   4389: getfield ٴῪ : I
    //   4392: invokevirtual ˊ : (I)Lyyds/sniarbtej/ʿᵉ;
    //   4395: pop
    //   4396: aload #9
    //   4398: getfield ͺо : [I
    //   4401: dup
    //   4402: astore #4
    //   4404: arraylength
    //   4405: istore #13
    //   4407: iconst_0
    //   4408: istore #14
    //   4410: iload #14
    //   4412: iload #13
    //   4414: if_icmpge -> 4438
    //   4417: aload #4
    //   4419: iload #14
    //   4421: iaload
    //   4422: istore #12
    //   4424: aload #10
    //   4426: iload #12
    //   4428: invokevirtual ˊ : (I)Lyyds/sniarbtej/ʿᵉ;
    //   4431: pop
    //   4432: iinc #14, 1
    //   4435: goto -> 4410
    //   4438: aload #9
    //   4440: getfield ᐨẏ : Lyyds/sniarbtej/ˌх;
    //   4443: aload #9
    //   4445: getfield ʿλ : I
    //   4448: aload #9
    //   4450: getfield ﾞǰ : I
    //   4453: aload #10
    //   4455: invokestatic ᐨẏ : (Lyyds/sniarbtej/ˌх;IILyyds/sniarbtej/ʿᵉ;)V
    //   4458: aload #9
    //   4460: getfield ᐨẏ : Lyyds/sniarbtej/ˌх;
    //   4463: aload #9
    //   4465: getfield ᴵʖ : Lyyds/sniarbtej/ˊ;
    //   4468: aload #9
    //   4470: getfield ﾞл : Lyyds/sniarbtej/ˊ;
    //   4473: aload #9
    //   4475: getfield ʿᵉ : Lyyds/sniarbtej/ˊ;
    //   4478: aload #9
    //   4480: getfield ʹﮃ : Lyyds/sniarbtej/ˊ;
    //   4483: aload #10
    //   4485: invokestatic ᐨẏ : (Lyyds/sniarbtej/ˌх;Lyyds/sniarbtej/ˊ;Lyyds/sniarbtej/ˊ;Lyyds/sniarbtej/ˊ;Lyyds/sniarbtej/ˊ;Lyyds/sniarbtej/ʿᵉ;)V
    //   4488: aload #9
    //   4490: getfield ᐨẏ : [Lyyds/sniarbtej/ˊ;
    //   4493: ifnull -> 4562
    //   4496: aload #9
    //   4498: getfield ᐨẏ : Lyyds/sniarbtej/ˌх;
    //   4501: ldc_w '䆤헞雦踜ᅼ㮋痪撵ꑎᫍ꫈ꬸ൏愐ힺ挀ꑰ〃ꩃ㋹돇⎤狴䇼?剔꭪᧍礆跁ʧￆᾜ'
    //   4504: invokevirtual toCharArray : ()[C
    //   4507: dup
    //   4508: dup
    //   4509: bipush #6
    //   4511: dup_x1
    //   4512: caload
    //   4513: sipush #27389
    //   4516: ixor
    //   4517: i2c
    //   4518: castore
    //   4519: sipush #19800
    //   4522: iconst_1
    //   4523: iconst_3
    //   4524: invokestatic v : (Ljava/lang/Object;SIS)Ljava/lang/String;
    //   4527: invokevirtual ՙᗮ : (Ljava/lang/String;)I
    //   4530: aload #9
    //   4532: getfield ᐨẏ : [Lyyds/sniarbtej/ˊ;
    //   4535: aload #9
    //   4537: getfield শ : I
    //   4540: ifne -> 4552
    //   4543: aload #9
    //   4545: getfield ᐨẏ : [Lyyds/sniarbtej/ˊ;
    //   4548: arraylength
    //   4549: goto -> 4557
    //   4552: aload #9
    //   4554: getfield শ : I
    //   4557: aload #10
    //   4559: invokestatic ᐨẏ : (I[Lyyds/sniarbtej/ˊ;ILyyds/sniarbtej/ʿᵉ;)V
    //   4562: aload #9
    //   4564: getfield ˊ : [Lyyds/sniarbtej/ˊ;
    //   4567: ifnull -> 4636
    //   4570: aload #9
    //   4572: getfield ᐨẏ : Lyyds/sniarbtej/ˌх;
    //   4575: ldc_w '㨗출嬭騕蟊帘秤ᦖ㱾邡宻᥸閑바⣻㴾﫣?Ꙏ핰䗳薧멫ֆಮ㡦ꅻᶟ샯밀켵纲䥭'
    //   4578: invokevirtual toCharArray : ()[C
    //   4581: dup
    //   4582: dup
    //   4583: bipush #30
    //   4585: dup_x1
    //   4586: caload
    //   4587: sipush #23496
    //   4590: ixor
    //   4591: i2c
    //   4592: castore
    //   4593: sipush #26236
    //   4596: iconst_3
    //   4597: iconst_2
    //   4598: invokestatic v : (Ljava/lang/Object;SIS)Ljava/lang/String;
    //   4601: invokevirtual ՙᗮ : (Ljava/lang/String;)I
    //   4604: aload #9
    //   4606: getfield ˊ : [Lyyds/sniarbtej/ˊ;
    //   4609: aload #9
    //   4611: getfield ˋᴷ : I
    //   4614: ifne -> 4626
    //   4617: aload #9
    //   4619: getfield ˊ : [Lyyds/sniarbtej/ˊ;
    //   4622: arraylength
    //   4623: goto -> 4631
    //   4626: aload #9
    //   4628: getfield ˋᴷ : I
    //   4631: aload #10
    //   4633: invokestatic ᐨẏ : (I[Lyyds/sniarbtej/ˊ;ILyyds/sniarbtej/ʿᵉ;)V
    //   4636: aload #9
    //   4638: getfield ᐨم : Lyyds/sniarbtej/ʿᵉ;
    //   4641: ifnull -> 4714
    //   4644: aload #10
    //   4646: aload #9
    //   4648: getfield ᐨẏ : Lyyds/sniarbtej/ˌх;
    //   4651: ldc_w '᮱㼯?鵲㬜턶れ喣뚊曛ব쉥ꝓ碘髆疙摯'
    //   4654: invokevirtual toCharArray : ()[C
    //   4657: dup
    //   4658: dup
    //   4659: iconst_4
    //   4660: dup_x1
    //   4661: caload
    //   4662: sipush #10199
    //   4665: ixor
    //   4666: i2c
    //   4667: castore
    //   4668: sipush #14655
    //   4671: iconst_3
    //   4672: iconst_5
    //   4673: invokestatic v : (Ljava/lang/Object;SIS)Ljava/lang/String;
    //   4676: invokevirtual ՙᗮ : (Ljava/lang/String;)I
    //   4679: invokevirtual ˊ : (I)Lyyds/sniarbtej/ʿᵉ;
    //   4682: aload #9
    //   4684: getfield ᐨم : Lyyds/sniarbtej/ʿᵉ;
    //   4687: getfield ʹﮃ : I
    //   4690: invokevirtual ᴵʖ : (I)Lyyds/sniarbtej/ʿᵉ;
    //   4693: aload #9
    //   4695: getfield ᐨم : Lyyds/sniarbtej/ʿᵉ;
    //   4698: getfield ˊ : [B
    //   4701: iconst_0
    //   4702: aload #9
    //   4704: getfield ᐨم : Lyyds/sniarbtej/ʿᵉ;
    //   4707: getfield ʹﮃ : I
    //   4710: invokevirtual ᐨẏ : ([BII)Lyyds/sniarbtej/ʿᵉ;
    //   4713: pop
    //   4714: aload #9
    //   4716: getfield ʾ : Lyyds/sniarbtej/ʿᵉ;
    //   4719: ifnull -> 4802
    //   4722: aload #10
    //   4724: aload #9
    //   4726: getfield ᐨẏ : Lyyds/sniarbtej/ˌх;
    //   4729: ldc_w '밉⩜饝䥑띢啁缹㫠뒱⠦呛ꯤ勍㫿'
    //   4732: invokevirtual toCharArray : ()[C
    //   4735: dup
    //   4736: dup
    //   4737: iconst_4
    //   4738: dup_x1
    //   4739: caload
    //   4740: sipush #8043
    //   4743: ixor
    //   4744: i2c
    //   4745: castore
    //   4746: sipush #8698
    //   4749: iconst_2
    //   4750: iconst_4
    //   4751: invokestatic v : (Ljava/lang/Object;SIS)Ljava/lang/String;
    //   4754: invokevirtual ՙᗮ : (Ljava/lang/String;)I
    //   4757: invokevirtual ˊ : (I)Lyyds/sniarbtej/ʿᵉ;
    //   4760: iconst_1
    //   4761: aload #9
    //   4763: getfield ʾ : Lyyds/sniarbtej/ʿᵉ;
    //   4766: getfield ʹﮃ : I
    //   4769: iadd
    //   4770: invokevirtual ᴵʖ : (I)Lyyds/sniarbtej/ʿᵉ;
    //   4773: aload #9
    //   4775: getfield ﹼ : I
    //   4778: invokevirtual ᐨẏ : (I)Lyyds/sniarbtej/ʿᵉ;
    //   4781: aload #9
    //   4783: getfield ʾ : Lyyds/sniarbtej/ʿᵉ;
    //   4786: getfield ˊ : [B
    //   4789: iconst_0
    //   4790: aload #9
    //   4792: getfield ʾ : Lyyds/sniarbtej/ʿᵉ;
    //   4795: getfield ʹﮃ : I
    //   4798: invokevirtual ᐨẏ : ([BII)Lyyds/sniarbtej/ʿᵉ;
    //   4801: pop
    //   4802: aload #9
    //   4804: getfield ˊ : Lyyds/sniarbtej/ᴵʖ;
    //   4807: ifnull -> 4825
    //   4810: aload #9
    //   4812: getfield ˊ : Lyyds/sniarbtej/ᴵʖ;
    //   4815: aload #9
    //   4817: getfield ᐨẏ : Lyyds/sniarbtej/ˌх;
    //   4820: aload #10
    //   4822: invokevirtual ᐨẏ : (Lyyds/sniarbtej/ˌх;Lyyds/sniarbtej/ʿᵉ;)V
    //   4825: aload_3
    //   4826: getfield ᐨẏ : Lyyds/sniarbtej/ˉｓ;
    //   4829: checkcast yyds/sniarbtej/ʿপ
    //   4832: astore_3
    //   4833: goto -> 2933
    //   4836: aload_1
    //   4837: iload #5
    //   4839: invokevirtual ˊ : (I)Lyyds/sniarbtej/ʿᵉ;
    //   4842: pop
    //   4843: aload_0
    //   4844: getfield ˊ : Lyyds/sniarbtej/ʿᵉ;
    //   4847: ifnull -> 4924
    //   4850: aload_1
    //   4851: aload_0
    //   4852: getfield ᐨẏ : Lyyds/sniarbtej/ˌх;
    //   4855: ldc_w '拌ꭲ笎栣呫咭鋼且셏់֯劑'
    //   4858: invokevirtual toCharArray : ()[C
    //   4861: dup
    //   4862: dup
    //   4863: iconst_2
    //   4864: dup_x1
    //   4865: caload
    //   4866: sipush #6707
    //   4869: ixor
    //   4870: i2c
    //   4871: castore
    //   4872: sipush #29138
    //   4875: iconst_3
    //   4876: iconst_4
    //   4877: invokestatic v : (Ljava/lang/Object;SIS)Ljava/lang/String;
    //   4880: invokevirtual ՙᗮ : (Ljava/lang/String;)I
    //   4883: invokevirtual ˊ : (I)Lyyds/sniarbtej/ʿᵉ;
    //   4886: aload_0
    //   4887: getfield ˊ : Lyyds/sniarbtej/ʿᵉ;
    //   4890: getfield ʹﮃ : I
    //   4893: iconst_2
    //   4894: iadd
    //   4895: invokevirtual ᴵʖ : (I)Lyyds/sniarbtej/ʿᵉ;
    //   4898: aload_0
    //   4899: getfield ˈے : I
    //   4902: invokevirtual ˊ : (I)Lyyds/sniarbtej/ʿᵉ;
    //   4905: aload_0
    //   4906: getfield ˊ : Lyyds/sniarbtej/ʿᵉ;
    //   4909: getfield ˊ : [B
    //   4912: iconst_0
    //   4913: aload_0
    //   4914: getfield ˊ : Lyyds/sniarbtej/ʿᵉ;
    //   4917: getfield ʹﮃ : I
    //   4920: invokevirtual ᐨẏ : ([BII)Lyyds/sniarbtej/ʿᵉ;
    //   4923: pop
    //   4924: aload_0
    //   4925: getfield ـﭔ : I
    //   4928: ifeq -> 4987
    //   4931: aload_1
    //   4932: aload_0
    //   4933: getfield ᐨẏ : Lyyds/sniarbtej/ˌх;
    //   4936: ldc_w '㣈쉐餒읲玗僘賵ﴆ鰋?䍿崓叶'
    //   4939: invokevirtual toCharArray : ()[C
    //   4942: dup
    //   4943: dup
    //   4944: bipush #11
    //   4946: dup_x1
    //   4947: caload
    //   4948: sipush #27475
    //   4951: ixor
    //   4952: i2c
    //   4953: castore
    //   4954: sipush #20847
    //   4957: iconst_3
    //   4958: iconst_4
    //   4959: invokestatic v : (Ljava/lang/Object;SIS)Ljava/lang/String;
    //   4962: invokevirtual ՙᗮ : (Ljava/lang/String;)I
    //   4965: invokevirtual ˊ : (I)Lyyds/sniarbtej/ʿᵉ;
    //   4968: iconst_4
    //   4969: invokevirtual ᴵʖ : (I)Lyyds/sniarbtej/ʿᵉ;
    //   4972: aload_0
    //   4973: getfield ـﭔ : I
    //   4976: invokevirtual ˊ : (I)Lyyds/sniarbtej/ʿᵉ;
    //   4979: aload_0
    //   4980: getfield ʼᵖ : I
    //   4983: invokevirtual ˊ : (I)Lyyds/sniarbtej/ʿᵉ;
    //   4986: pop
    //   4987: aload_0
    //   4988: getfield ʿλ : I
    //   4991: sipush #4096
    //   4994: iand
    //   4995: ifeq -> 5052
    //   4998: aload_0
    //   4999: getfield ᔪ : I
    //   5002: ldc 65535
    //   5004: iand
    //   5005: bipush #49
    //   5007: if_icmpge -> 5052
    //   5010: aload_1
    //   5011: aload_0
    //   5012: getfield ᐨẏ : Lyyds/sniarbtej/ˌх;
    //   5015: ldc_w '諈㰑漾ഀ⧵苩싛冶'
    //   5018: invokevirtual toCharArray : ()[C
    //   5021: dup
    //   5022: dup
    //   5023: bipush #6
    //   5025: dup_x1
    //   5026: caload
    //   5027: sipush #27709
    //   5030: ixor
    //   5031: i2c
    //   5032: castore
    //   5033: sipush #24945
    //   5036: iconst_4
    //   5037: iconst_3
    //   5038: invokestatic v : (Ljava/lang/Object;SIS)Ljava/lang/String;
    //   5041: invokevirtual ՙᗮ : (Ljava/lang/String;)I
    //   5044: invokevirtual ˊ : (I)Lyyds/sniarbtej/ʿᵉ;
    //   5047: iconst_0
    //   5048: invokevirtual ᴵʖ : (I)Lyyds/sniarbtej/ʿᵉ;
    //   5051: pop
    //   5052: aload_0
    //   5053: getfield ﾞǰ : I
    //   5056: ifeq -> 5107
    //   5059: aload_1
    //   5060: aload_0
    //   5061: getfield ᐨẏ : Lyyds/sniarbtej/ˌх;
    //   5064: ldc_w '⨚坃櫖঩ຐ巏﯆ཐ뾢Ḭ'
    //   5067: invokevirtual toCharArray : ()[C
    //   5070: dup
    //   5071: dup
    //   5072: iconst_2
    //   5073: dup_x1
    //   5074: caload
    //   5075: sipush #19022
    //   5078: ixor
    //   5079: i2c
    //   5080: castore
    //   5081: sipush #1730
    //   5084: iconst_2
    //   5085: iconst_0
    //   5086: invokestatic v : (Ljava/lang/Object;SIS)Ljava/lang/String;
    //   5089: invokevirtual ՙᗮ : (Ljava/lang/String;)I
    //   5092: invokevirtual ˊ : (I)Lyyds/sniarbtej/ʿᵉ;
    //   5095: iconst_2
    //   5096: invokevirtual ᴵʖ : (I)Lyyds/sniarbtej/ʿᵉ;
    //   5099: aload_0
    //   5100: getfield ﾞǰ : I
    //   5103: invokevirtual ˊ : (I)Lyyds/sniarbtej/ʿᵉ;
    //   5106: pop
    //   5107: aload_0
    //   5108: getfield ˊᵃ : I
    //   5111: ifeq -> 5162
    //   5114: aload_1
    //   5115: aload_0
    //   5116: getfield ᐨẏ : Lyyds/sniarbtej/ˌх;
    //   5119: ldc_w '㱒ᦿ땴온佄ꃽ琘沕䦱'
    //   5122: invokevirtual toCharArray : ()[C
    //   5125: dup
    //   5126: dup
    //   5127: iconst_2
    //   5128: dup_x1
    //   5129: caload
    //   5130: sipush #28507
    //   5133: ixor
    //   5134: i2c
    //   5135: castore
    //   5136: sipush #29864
    //   5139: iconst_4
    //   5140: iconst_0
    //   5141: invokestatic v : (Ljava/lang/Object;SIS)Ljava/lang/String;
    //   5144: invokevirtual ՙᗮ : (Ljava/lang/String;)I
    //   5147: invokevirtual ˊ : (I)Lyyds/sniarbtej/ʿᵉ;
    //   5150: iconst_2
    //   5151: invokevirtual ᴵʖ : (I)Lyyds/sniarbtej/ʿᵉ;
    //   5154: aload_0
    //   5155: getfield ˊᵃ : I
    //   5158: invokevirtual ˊ : (I)Lyyds/sniarbtej/ʿᵉ;
    //   5161: pop
    //   5162: aload_0
    //   5163: getfield ᴵʖ : Lyyds/sniarbtej/ʿᵉ;
    //   5166: ifnull -> 5231
    //   5169: aload_0
    //   5170: getfield ᴵʖ : Lyyds/sniarbtej/ʿᵉ;
    //   5173: getfield ʹﮃ : I
    //   5176: istore_3
    //   5177: aload_1
    //   5178: aload_0
    //   5179: getfield ᐨẏ : Lyyds/sniarbtej/ˌх;
    //   5182: ldc_w '轲?ᥨ뙴覮집唟䅨ꉋ숉둥㢙颶皵⅙旑⭈⋑'
    //   5185: invokevirtual toCharArray : ()[C
    //   5188: dup
    //   5189: dup
    //   5190: bipush #7
    //   5192: dup_x1
    //   5193: caload
    //   5194: sipush #16489
    //   5197: ixor
    //   5198: i2c
    //   5199: castore
    //   5200: sipush #32249
    //   5203: iconst_0
    //   5204: iconst_2
    //   5205: invokestatic v : (Ljava/lang/Object;SIS)Ljava/lang/String;
    //   5208: invokevirtual ՙᗮ : (Ljava/lang/String;)I
    //   5211: invokevirtual ˊ : (I)Lyyds/sniarbtej/ʿᵉ;
    //   5214: iload_3
    //   5215: invokevirtual ᴵʖ : (I)Lyyds/sniarbtej/ʿᵉ;
    //   5218: aload_0
    //   5219: getfield ᴵʖ : Lyyds/sniarbtej/ʿᵉ;
    //   5222: getfield ˊ : [B
    //   5225: iconst_0
    //   5226: iload_3
    //   5227: invokevirtual ᐨẏ : ([BII)Lyyds/sniarbtej/ʿᵉ;
    //   5230: pop
    //   5231: aload_0
    //   5232: getfield ʿλ : I
    //   5235: ldc_w 131072
    //   5238: iand
    //   5239: ifeq -> 5284
    //   5242: aload_1
    //   5243: aload_0
    //   5244: getfield ᐨẏ : Lyyds/sniarbtej/ˌх;
    //   5247: ldc_w '곛៟錏ݬڡ琡忛⨪黸棇㢜'
    //   5250: invokevirtual toCharArray : ()[C
    //   5253: dup
    //   5254: dup
    //   5255: bipush #6
    //   5257: dup_x1
    //   5258: caload
    //   5259: sipush #23239
    //   5262: ixor
    //   5263: i2c
    //   5264: castore
    //   5265: sipush #29463
    //   5268: iconst_1
    //   5269: iconst_2
    //   5270: invokestatic v : (Ljava/lang/Object;SIS)Ljava/lang/String;
    //   5273: invokevirtual ՙᗮ : (Ljava/lang/String;)I
    //   5276: invokevirtual ˊ : (I)Lyyds/sniarbtej/ʿᵉ;
    //   5279: iconst_0
    //   5280: invokevirtual ᴵʖ : (I)Lyyds/sniarbtej/ʿᵉ;
    //   5283: pop
    //   5284: aload_0
    //   5285: getfield ᐨẏ : Lyyds/sniarbtej/ˌх;
    //   5288: aload_0
    //   5289: getfield ᴵʖ : Lyyds/sniarbtej/ˊ;
    //   5292: aload_0
    //   5293: getfield ﾞл : Lyyds/sniarbtej/ˊ;
    //   5296: aload_0
    //   5297: getfield ʿᵉ : Lyyds/sniarbtej/ˊ;
    //   5300: aload_0
    //   5301: getfield ʹﮃ : Lyyds/sniarbtej/ˊ;
    //   5304: aload_1
    //   5305: invokestatic ᐨẏ : (Lyyds/sniarbtej/ˌх;Lyyds/sniarbtej/ˊ;Lyyds/sniarbtej/ˊ;Lyyds/sniarbtej/ˊ;Lyyds/sniarbtej/ˊ;Lyyds/sniarbtej/ʿᵉ;)V
    //   5308: aload_0
    //   5309: getfield ᐨẏ : Lyyds/sniarbtej/ˌх;
    //   5312: aload_1
    //   5313: astore #10
    //   5315: dup
    //   5316: astore #9
    //   5318: getfield ᔪ : Lyyds/sniarbtej/ʿᵉ;
    //   5321: ifnull -> 5401
    //   5324: aload #10
    //   5326: aload #9
    //   5328: ldc_w 'ꎙ郰ᐷߔ鲉鶺ࢲ煸刺ㄨ肻놂峤굛㱌榖'
    //   5331: invokevirtual toCharArray : ()[C
    //   5334: dup
    //   5335: dup
    //   5336: iconst_3
    //   5337: dup_x1
    //   5338: caload
    //   5339: sipush #4158
    //   5342: ixor
    //   5343: i2c
    //   5344: castore
    //   5345: sipush #26263
    //   5348: iconst_1
    //   5349: iconst_0
    //   5350: invokestatic v : (Ljava/lang/Object;SIS)Ljava/lang/String;
    //   5353: invokevirtual ՙᗮ : (Ljava/lang/String;)I
    //   5356: invokevirtual ˊ : (I)Lyyds/sniarbtej/ʿᵉ;
    //   5359: aload #9
    //   5361: getfield ᔪ : Lyyds/sniarbtej/ʿᵉ;
    //   5364: getfield ʹﮃ : I
    //   5367: iconst_2
    //   5368: iadd
    //   5369: invokevirtual ᴵʖ : (I)Lyyds/sniarbtej/ʿᵉ;
    //   5372: aload #9
    //   5374: getfield ՙῑ : I
    //   5377: invokevirtual ˊ : (I)Lyyds/sniarbtej/ʿᵉ;
    //   5380: aload #9
    //   5382: getfield ᔪ : Lyyds/sniarbtej/ʿᵉ;
    //   5385: getfield ˊ : [B
    //   5388: iconst_0
    //   5389: aload #9
    //   5391: getfield ᔪ : Lyyds/sniarbtej/ʿᵉ;
    //   5394: getfield ʹﮃ : I
    //   5397: invokevirtual ᐨẏ : ([BII)Lyyds/sniarbtej/ʿᵉ;
    //   5400: pop
    //   5401: aload_0
    //   5402: getfield ᐨẏ : Lyyds/sniarbtej/ˈے;
    //   5405: ifnull -> 5823
    //   5408: aload_0
    //   5409: getfield ᐨẏ : Lyyds/sniarbtej/ˈے;
    //   5412: aload_1
    //   5413: astore #10
    //   5415: astore #9
    //   5417: bipush #16
    //   5419: aload #9
    //   5421: getfield ͺо : Lyyds/sniarbtej/ʿᵉ;
    //   5424: getfield ʹﮃ : I
    //   5427: iadd
    //   5428: aload #9
    //   5430: getfield ٴӵ : Lyyds/sniarbtej/ʿᵉ;
    //   5433: getfield ʹﮃ : I
    //   5436: iadd
    //   5437: aload #9
    //   5439: getfield ᴵƚ : Lyyds/sniarbtej/ʿᵉ;
    //   5442: getfield ʹﮃ : I
    //   5445: iadd
    //   5446: aload #9
    //   5448: getfield ˌ : Lyyds/sniarbtej/ʿᵉ;
    //   5451: getfield ʹﮃ : I
    //   5454: iadd
    //   5455: aload #9
    //   5457: getfield ˍ : Lyyds/sniarbtej/ʿᵉ;
    //   5460: getfield ʹﮃ : I
    //   5463: iadd
    //   5464: istore #11
    //   5466: aload #10
    //   5468: aload #9
    //   5470: getfield ᐨẏ : Lyyds/sniarbtej/ˌх;
    //   5473: ldc_w '屲ᆙ三ู낟죟Ṕ'
    //   5476: invokevirtual toCharArray : ()[C
    //   5479: dup
    //   5480: dup
    //   5481: iconst_4
    //   5482: dup_x1
    //   5483: caload
    //   5484: sipush #18961
    //   5487: ixor
    //   5488: i2c
    //   5489: castore
    //   5490: sipush #24095
    //   5493: iconst_1
    //   5494: iconst_3
    //   5495: invokestatic v : (Ljava/lang/Object;SIS)Ljava/lang/String;
    //   5498: invokevirtual ՙᗮ : (Ljava/lang/String;)I
    //   5501: invokevirtual ˊ : (I)Lyyds/sniarbtej/ʿᵉ;
    //   5504: iload #11
    //   5506: invokevirtual ᴵʖ : (I)Lyyds/sniarbtej/ʿᵉ;
    //   5509: aload #9
    //   5511: getfield ʿʹ : I
    //   5514: invokevirtual ˊ : (I)Lyyds/sniarbtej/ʿᵉ;
    //   5517: aload #9
    //   5519: getfield ᵪ : I
    //   5522: invokevirtual ˊ : (I)Lyyds/sniarbtej/ʿᵉ;
    //   5525: aload #9
    //   5527: getfield ˎე : I
    //   5530: invokevirtual ˊ : (I)Lyyds/sniarbtej/ʿᵉ;
    //   5533: aload #9
    //   5535: getfield ᐝᴾ : I
    //   5538: invokevirtual ˊ : (I)Lyyds/sniarbtej/ʿᵉ;
    //   5541: aload #9
    //   5543: getfield ͺо : Lyyds/sniarbtej/ʿᵉ;
    //   5546: getfield ˊ : [B
    //   5549: iconst_0
    //   5550: aload #9
    //   5552: getfield ͺо : Lyyds/sniarbtej/ʿᵉ;
    //   5555: getfield ʹﮃ : I
    //   5558: invokevirtual ᐨẏ : ([BII)Lyyds/sniarbtej/ʿᵉ;
    //   5561: aload #9
    //   5563: getfield ˋᕁ : I
    //   5566: invokevirtual ˊ : (I)Lyyds/sniarbtej/ʿᵉ;
    //   5569: aload #9
    //   5571: getfield ٴӵ : Lyyds/sniarbtej/ʿᵉ;
    //   5574: getfield ˊ : [B
    //   5577: iconst_0
    //   5578: aload #9
    //   5580: getfield ٴӵ : Lyyds/sniarbtej/ʿᵉ;
    //   5583: getfield ʹﮃ : I
    //   5586: invokevirtual ᐨẏ : ([BII)Lyyds/sniarbtej/ʿᵉ;
    //   5589: aload #9
    //   5591: getfield ˌﺙ : I
    //   5594: invokevirtual ˊ : (I)Lyyds/sniarbtej/ʿᵉ;
    //   5597: aload #9
    //   5599: getfield ᴵƚ : Lyyds/sniarbtej/ʿᵉ;
    //   5602: getfield ˊ : [B
    //   5605: iconst_0
    //   5606: aload #9
    //   5608: getfield ᴵƚ : Lyyds/sniarbtej/ʿᵉ;
    //   5611: getfield ʹﮃ : I
    //   5614: invokevirtual ᐨẏ : ([BII)Lyyds/sniarbtej/ʿᵉ;
    //   5617: aload #9
    //   5619: getfield ᐝᎫ : I
    //   5622: invokevirtual ˊ : (I)Lyyds/sniarbtej/ʿᵉ;
    //   5625: aload #9
    //   5627: getfield ˌ : Lyyds/sniarbtej/ʿᵉ;
    //   5630: getfield ˊ : [B
    //   5633: iconst_0
    //   5634: aload #9
    //   5636: getfield ˌ : Lyyds/sniarbtej/ʿᵉ;
    //   5639: getfield ʹﮃ : I
    //   5642: invokevirtual ᐨẏ : ([BII)Lyyds/sniarbtej/ʿᵉ;
    //   5645: aload #9
    //   5647: getfield ͺᴘ : I
    //   5650: invokevirtual ˊ : (I)Lyyds/sniarbtej/ʿᵉ;
    //   5653: aload #9
    //   5655: getfield ˍ : Lyyds/sniarbtej/ʿᵉ;
    //   5658: getfield ˊ : [B
    //   5661: iconst_0
    //   5662: aload #9
    //   5664: getfield ˍ : Lyyds/sniarbtej/ʿᵉ;
    //   5667: getfield ʹﮃ : I
    //   5670: invokevirtual ᐨẏ : ([BII)Lyyds/sniarbtej/ʿᵉ;
    //   5673: pop
    //   5674: aload #9
    //   5676: getfield ˎᒩ : I
    //   5679: ifle -> 5763
    //   5682: aload #10
    //   5684: aload #9
    //   5686: getfield ᐨẏ : Lyyds/sniarbtej/ˌх;
    //   5689: ldc_w '뜿뒧楱ㆣ徽䯈숼迸슲筑놿ꛘ㞮ᮤऴ'
    //   5692: invokevirtual toCharArray : ()[C
    //   5695: dup
    //   5696: dup
    //   5697: bipush #9
    //   5699: dup_x1
    //   5700: caload
    //   5701: sipush #1731
    //   5704: ixor
    //   5705: i2c
    //   5706: castore
    //   5707: sipush #25915
    //   5710: iconst_2
    //   5711: iconst_0
    //   5712: invokestatic v : (Ljava/lang/Object;SIS)Ljava/lang/String;
    //   5715: invokevirtual ՙᗮ : (Ljava/lang/String;)I
    //   5718: invokevirtual ˊ : (I)Lyyds/sniarbtej/ʿᵉ;
    //   5721: iconst_2
    //   5722: aload #9
    //   5724: getfield ʹō : Lyyds/sniarbtej/ʿᵉ;
    //   5727: getfield ʹﮃ : I
    //   5730: iadd
    //   5731: invokevirtual ᴵʖ : (I)Lyyds/sniarbtej/ʿᵉ;
    //   5734: aload #9
    //   5736: getfield ˎᒩ : I
    //   5739: invokevirtual ˊ : (I)Lyyds/sniarbtej/ʿᵉ;
    //   5742: aload #9
    //   5744: getfield ʹō : Lyyds/sniarbtej/ʿᵉ;
    //   5747: getfield ˊ : [B
    //   5750: iconst_0
    //   5751: aload #9
    //   5753: getfield ʹō : Lyyds/sniarbtej/ʿᵉ;
    //   5756: getfield ʹﮃ : I
    //   5759: invokevirtual ᐨẏ : ([BII)Lyyds/sniarbtej/ʿᵉ;
    //   5762: pop
    //   5763: aload #9
    //   5765: getfield ـō : I
    //   5768: ifle -> 5823
    //   5771: aload #10
    //   5773: aload #9
    //   5775: getfield ᐨẏ : Lyyds/sniarbtej/ˌх;
    //   5778: ldc_w '閛鍲袘皉萦絨ޭ꜄鯑錇ш섅娱า耎嬙'
    //   5781: invokevirtual toCharArray : ()[C
    //   5784: dup
    //   5785: dup
    //   5786: bipush #7
    //   5788: dup_x1
    //   5789: caload
    //   5790: sipush #20683
    //   5793: ixor
    //   5794: i2c
    //   5795: castore
    //   5796: sipush #18813
    //   5799: iconst_2
    //   5800: iconst_5
    //   5801: invokestatic v : (Ljava/lang/Object;SIS)Ljava/lang/String;
    //   5804: invokevirtual ՙᗮ : (Ljava/lang/String;)I
    //   5807: invokevirtual ˊ : (I)Lyyds/sniarbtej/ʿᵉ;
    //   5810: iconst_2
    //   5811: invokevirtual ᴵʖ : (I)Lyyds/sniarbtej/ʿᵉ;
    //   5814: aload #9
    //   5816: getfield ـō : I
    //   5819: invokevirtual ˊ : (I)Lyyds/sniarbtej/ʿᵉ;
    //   5822: pop
    //   5823: aload_0
    //   5824: getfield ˌх : I
    //   5827: ifeq -> 5878
    //   5830: aload_1
    //   5831: aload_0
    //   5832: getfield ᐨẏ : Lyyds/sniarbtej/ˌх;
    //   5835: ldc_w '쵚喭娾⤲峁ᛋ㶝'
    //   5838: invokevirtual toCharArray : ()[C
    //   5841: dup
    //   5842: dup
    //   5843: iconst_2
    //   5844: dup_x1
    //   5845: caload
    //   5846: sipush #21333
    //   5849: ixor
    //   5850: i2c
    //   5851: castore
    //   5852: sipush #9903
    //   5855: iconst_4
    //   5856: iconst_5
    //   5857: invokestatic v : (Ljava/lang/Object;SIS)Ljava/lang/String;
    //   5860: invokevirtual ՙᗮ : (Ljava/lang/String;)I
    //   5863: invokevirtual ˊ : (I)Lyyds/sniarbtej/ʿᵉ;
    //   5866: iconst_2
    //   5867: invokevirtual ᴵʖ : (I)Lyyds/sniarbtej/ʿᵉ;
    //   5870: aload_0
    //   5871: getfield ˌх : I
    //   5874: invokevirtual ˊ : (I)Lyyds/sniarbtej/ʿᵉ;
    //   5877: pop
    //   5878: aload_0
    //   5879: getfield ﾞл : Lyyds/sniarbtej/ʿᵉ;
    //   5882: ifnull -> 5959
    //   5885: aload_1
    //   5886: aload_0
    //   5887: getfield ᐨẏ : Lyyds/sniarbtej/ˌх;
    //   5890: ldc_w '蝷참苳蛣漗齤ꔗ諸멲熑έ'
    //   5893: invokevirtual toCharArray : ()[C
    //   5896: dup
    //   5897: dup
    //   5898: iconst_3
    //   5899: dup_x1
    //   5900: caload
    //   5901: sipush #1932
    //   5904: ixor
    //   5905: i2c
    //   5906: castore
    //   5907: sipush #3178
    //   5910: iconst_0
    //   5911: iconst_5
    //   5912: invokestatic v : (Ljava/lang/Object;SIS)Ljava/lang/String;
    //   5915: invokevirtual ՙᗮ : (Ljava/lang/String;)I
    //   5918: invokevirtual ˊ : (I)Lyyds/sniarbtej/ʿᵉ;
    //   5921: aload_0
    //   5922: getfield ﾞл : Lyyds/sniarbtej/ʿᵉ;
    //   5925: getfield ʹﮃ : I
    //   5928: iconst_2
    //   5929: iadd
    //   5930: invokevirtual ᴵʖ : (I)Lyyds/sniarbtej/ʿᵉ;
    //   5933: aload_0
    //   5934: getfield ιﾌ : I
    //   5937: invokevirtual ˊ : (I)Lyyds/sniarbtej/ʿᵉ;
    //   5940: aload_0
    //   5941: getfield ﾞл : Lyyds/sniarbtej/ʿᵉ;
    //   5944: getfield ˊ : [B
    //   5947: iconst_0
    //   5948: aload_0
    //   5949: getfield ﾞл : Lyyds/sniarbtej/ʿᵉ;
    //   5952: getfield ʹﮃ : I
    //   5955: invokevirtual ᐨẏ : ([BII)Lyyds/sniarbtej/ʿᵉ;
    //   5958: pop
    //   5959: aload_0
    //   5960: getfield ʿᵉ : Lyyds/sniarbtej/ʿᵉ;
    //   5963: ifnull -> 6040
    //   5966: aload_1
    //   5967: aload_0
    //   5968: getfield ᐨẏ : Lyyds/sniarbtej/ˌх;
    //   5971: ldc_w 'ᎋ橭ᔡ퉣膳窐Ⅴ諌䋜Ἑ侬年렧ꆚ♺♱瞳Ώꭏ忤'
    //   5974: invokevirtual toCharArray : ()[C
    //   5977: dup
    //   5978: dup
    //   5979: iconst_3
    //   5980: dup_x1
    //   5981: caload
    //   5982: sipush #17923
    //   5985: ixor
    //   5986: i2c
    //   5987: castore
    //   5988: sipush #16909
    //   5991: iconst_3
    //   5992: iconst_2
    //   5993: invokestatic v : (Ljava/lang/Object;SIS)Ljava/lang/String;
    //   5996: invokevirtual ՙᗮ : (Ljava/lang/String;)I
    //   5999: invokevirtual ˊ : (I)Lyyds/sniarbtej/ʿᵉ;
    //   6002: aload_0
    //   6003: getfield ʿᵉ : Lyyds/sniarbtej/ʿᵉ;
    //   6006: getfield ʹﮃ : I
    //   6009: iconst_2
    //   6010: iadd
    //   6011: invokevirtual ᴵʖ : (I)Lyyds/sniarbtej/ʿᵉ;
    //   6014: aload_0
    //   6015: getfield ʻւ : I
    //   6018: invokevirtual ˊ : (I)Lyyds/sniarbtej/ʿᵉ;
    //   6021: aload_0
    //   6022: getfield ʿᵉ : Lyyds/sniarbtej/ʿᵉ;
    //   6025: getfield ˊ : [B
    //   6028: iconst_0
    //   6029: aload_0
    //   6030: getfield ʿᵉ : Lyyds/sniarbtej/ʿᵉ;
    //   6033: getfield ʹﮃ : I
    //   6036: invokevirtual ᐨẏ : ([BII)Lyyds/sniarbtej/ʿᵉ;
    //   6039: pop
    //   6040: aload_0
    //   6041: getfield ʿλ : I
    //   6044: ldc_w 65536
    //   6047: iand
    //   6048: ifne -> 6058
    //   6051: aload_0
    //   6052: getfield ᐨẏ : Lyyds/sniarbtej/ﾞǰ;
    //   6055: ifnull -> 6308
    //   6058: aload_1
    //   6059: aload_0
    //   6060: getfield ᐨẏ : Lyyds/sniarbtej/ˌх;
    //   6063: ldc_w '膿䨭Ὲ౞糦'
    //   6066: invokevirtual toCharArray : ()[C
    //   6069: dup
    //   6070: dup
    //   6071: iconst_4
    //   6072: dup_x1
    //   6073: caload
    //   6074: sipush #31561
    //   6077: ixor
    //   6078: i2c
    //   6079: castore
    //   6080: sipush #29562
    //   6083: iconst_3
    //   6084: iconst_4
    //   6085: invokestatic v : (Ljava/lang/Object;SIS)Ljava/lang/String;
    //   6088: invokevirtual ՙᗮ : (Ljava/lang/String;)I
    //   6091: invokevirtual ˊ : (I)Lyyds/sniarbtej/ʿᵉ;
    //   6094: iload #7
    //   6096: iconst_2
    //   6097: iadd
    //   6098: invokevirtual ᴵʖ : (I)Lyyds/sniarbtej/ʿᵉ;
    //   6101: iload #6
    //   6103: invokevirtual ˊ : (I)Lyyds/sniarbtej/ʿᵉ;
    //   6106: pop
    //   6107: aload_0
    //   6108: getfield ᐨẏ : Lyyds/sniarbtej/ﾞǰ;
    //   6111: astore_3
    //   6112: aload_3
    //   6113: ifnull -> 6308
    //   6116: aload_3
    //   6117: aload_1
    //   6118: astore #10
    //   6120: astore #9
    //   6122: aload #10
    //   6124: aload #9
    //   6126: getfield ᐝт : I
    //   6129: invokevirtual ˊ : (I)Lyyds/sniarbtej/ʿᵉ;
    //   6132: aload #9
    //   6134: getfield ɟ : I
    //   6137: invokevirtual ˊ : (I)Lyyds/sniarbtej/ʿᵉ;
    //   6140: pop
    //   6141: iconst_0
    //   6142: istore #11
    //   6144: aload #9
    //   6146: getfield ﾞǰ : I
    //   6149: ifeq -> 6155
    //   6152: iinc #11, 1
    //   6155: aload #9
    //   6157: getfield ᴵʖ : Lyyds/sniarbtej/ˊ;
    //   6160: ifnull -> 6166
    //   6163: iinc #11, 1
    //   6166: aload #9
    //   6168: getfield ﾞл : Lyyds/sniarbtej/ˊ;
    //   6171: ifnull -> 6177
    //   6174: iinc #11, 1
    //   6177: aload #9
    //   6179: getfield ʿᵉ : Lyyds/sniarbtej/ˊ;
    //   6182: ifnull -> 6188
    //   6185: iinc #11, 1
    //   6188: aload #9
    //   6190: getfield ʹﮃ : Lyyds/sniarbtej/ˊ;
    //   6193: ifnull -> 6199
    //   6196: iinc #11, 1
    //   6199: aload #9
    //   6201: getfield ˊ : Lyyds/sniarbtej/ᴵʖ;
    //   6204: ifnull -> 6220
    //   6207: iload #11
    //   6209: aload #9
    //   6211: getfield ˊ : Lyyds/sniarbtej/ᴵʖ;
    //   6214: invokevirtual ᐨẏ : ()I
    //   6217: iadd
    //   6218: istore #11
    //   6220: aload #10
    //   6222: iload #11
    //   6224: invokevirtual ˊ : (I)Lyyds/sniarbtej/ʿᵉ;
    //   6227: pop
    //   6228: aload #9
    //   6230: getfield ᐨẏ : Lyyds/sniarbtej/ˌх;
    //   6233: iconst_0
    //   6234: aload #9
    //   6236: getfield ﾞǰ : I
    //   6239: aload #10
    //   6241: invokestatic ᐨẏ : (Lyyds/sniarbtej/ˌх;IILyyds/sniarbtej/ʿᵉ;)V
    //   6244: aload #9
    //   6246: getfield ᐨẏ : Lyyds/sniarbtej/ˌх;
    //   6249: aload #9
    //   6251: getfield ᴵʖ : Lyyds/sniarbtej/ˊ;
    //   6254: aload #9
    //   6256: getfield ﾞл : Lyyds/sniarbtej/ˊ;
    //   6259: aload #9
    //   6261: getfield ʿᵉ : Lyyds/sniarbtej/ˊ;
    //   6264: aload #9
    //   6266: getfield ʹﮃ : Lyyds/sniarbtej/ˊ;
    //   6269: aload #10
    //   6271: invokestatic ᐨẏ : (Lyyds/sniarbtej/ˌх;Lyyds/sniarbtej/ˊ;Lyyds/sniarbtej/ˊ;Lyyds/sniarbtej/ˊ;Lyyds/sniarbtej/ˊ;Lyyds/sniarbtej/ʿᵉ;)V
    //   6274: aload #9
    //   6276: getfield ˊ : Lyyds/sniarbtej/ᴵʖ;
    //   6279: ifnull -> 6297
    //   6282: aload #9
    //   6284: getfield ˊ : Lyyds/sniarbtej/ᴵʖ;
    //   6287: aload #9
    //   6289: getfield ᐨẏ : Lyyds/sniarbtej/ˌх;
    //   6292: aload #10
    //   6294: invokevirtual ᐨẏ : (Lyyds/sniarbtej/ˌх;Lyyds/sniarbtej/ʿᵉ;)V
    //   6297: aload_3
    //   6298: getfield ᐨẏ : Lyyds/sniarbtej/ʼᵖ;
    //   6301: checkcast yyds/sniarbtej/ﾞǰ
    //   6304: astore_3
    //   6305: goto -> 6112
    //   6308: aload_0
    //   6309: getfield ˊ : Lyyds/sniarbtej/ᴵʖ;
    //   6312: ifnull -> 6327
    //   6315: aload_0
    //   6316: getfield ˊ : Lyyds/sniarbtej/ᴵʖ;
    //   6319: aload_0
    //   6320: getfield ᐨẏ : Lyyds/sniarbtej/ˌх;
    //   6323: aload_1
    //   6324: invokevirtual ᐨẏ : (Lyyds/sniarbtej/ˌх;Lyyds/sniarbtej/ʿᵉ;)V
    //   6327: iload_2
    //   6328: ifeq -> 6694
    //   6331: aload_0
    //   6332: aload_1
    //   6333: getfield ˊ : [B
    //   6336: iload #8
    //   6338: istore #11
    //   6340: astore #10
    //   6342: dup
    //   6343: astore #9
    //   6345: astore #12
    //   6347: new yyds/sniarbtej/ﾞл
    //   6350: dup
    //   6351: invokespecial <init> : ()V
    //   6354: dup
    //   6355: astore #4
    //   6357: aload #12
    //   6359: getfield ˊ : Lyyds/sniarbtej/ᴵʖ;
    //   6362: invokevirtual ᐨẏ : (Lyyds/sniarbtej/ᴵʖ;)V
    //   6365: aload #12
    //   6367: getfield ᐨẏ : Lyyds/sniarbtej/ˌ;
    //   6370: astore #13
    //   6372: aload #13
    //   6374: ifnull -> 6408
    //   6377: aload #13
    //   6379: aload #4
    //   6381: astore #16
    //   6383: astore #15
    //   6385: aload #16
    //   6387: aload #15
    //   6389: getfield ˊ : Lyyds/sniarbtej/ᴵʖ;
    //   6392: invokevirtual ᐨẏ : (Lyyds/sniarbtej/ᴵʖ;)V
    //   6395: aload #13
    //   6397: getfield ᐨẏ : Lyyds/sniarbtej/ᴵƚ;
    //   6400: checkcast yyds/sniarbtej/ˌ
    //   6403: astore #13
    //   6405: goto -> 6372
    //   6408: aload #12
    //   6410: getfield ᐨẏ : Lyyds/sniarbtej/ʿপ;
    //   6413: astore #14
    //   6415: aload #14
    //   6417: ifnull -> 6461
    //   6420: aload #14
    //   6422: aload #4
    //   6424: astore #16
    //   6426: astore #15
    //   6428: aload #16
    //   6430: aload #15
    //   6432: getfield ˊ : Lyyds/sniarbtej/ᴵʖ;
    //   6435: invokevirtual ᐨẏ : (Lyyds/sniarbtej/ᴵʖ;)V
    //   6438: aload #16
    //   6440: aload #15
    //   6442: getfield ᴵʖ : Lyyds/sniarbtej/ᴵʖ;
    //   6445: invokevirtual ᐨẏ : (Lyyds/sniarbtej/ᴵʖ;)V
    //   6448: aload #14
    //   6450: getfield ᐨẏ : Lyyds/sniarbtej/ˉｓ;
    //   6453: checkcast yyds/sniarbtej/ʿপ
    //   6456: astore #14
    //   6458: goto -> 6415
    //   6461: aload #12
    //   6463: getfield ᐨẏ : Lyyds/sniarbtej/ﾞǰ;
    //   6466: astore #12
    //   6468: aload #12
    //   6470: ifnull -> 6504
    //   6473: aload #12
    //   6475: aload #4
    //   6477: astore #16
    //   6479: astore #15
    //   6481: aload #16
    //   6483: aload #15
    //   6485: getfield ˊ : Lyyds/sniarbtej/ᴵʖ;
    //   6488: invokevirtual ᐨẏ : (Lyyds/sniarbtej/ᴵʖ;)V
    //   6491: aload #12
    //   6493: getfield ᐨẏ : Lyyds/sniarbtej/ʼᵖ;
    //   6496: checkcast yyds/sniarbtej/ﾞǰ
    //   6499: astore #12
    //   6501: goto -> 6468
    //   6504: aload #4
    //   6506: dup
    //   6507: astore #15
    //   6509: getfield ʿᵉ : I
    //   6512: anewarray yyds/sniarbtej/ᴵʖ
    //   6515: astore #16
    //   6517: aload #15
    //   6519: getfield ᐨẏ : [Lyyds/sniarbtej/ᴵʖ;
    //   6522: iconst_0
    //   6523: aload #16
    //   6525: iconst_0
    //   6526: aload #15
    //   6528: getfield ʿᵉ : I
    //   6531: invokestatic arraycopy : (Ljava/lang/Object;ILjava/lang/Object;II)V
    //   6534: aload #16
    //   6536: astore #12
    //   6538: aload #9
    //   6540: aconst_null
    //   6541: putfield ᐨẏ : Lyyds/sniarbtej/ˌ;
    //   6544: aload #9
    //   6546: aconst_null
    //   6547: putfield ˊ : Lyyds/sniarbtej/ˌ;
    //   6550: aload #9
    //   6552: aconst_null
    //   6553: putfield ᐨẏ : Lyyds/sniarbtej/ʿপ;
    //   6556: aload #9
    //   6558: aconst_null
    //   6559: putfield ˊ : Lyyds/sniarbtej/ʿপ;
    //   6562: aload #9
    //   6564: aconst_null
    //   6565: putfield ᴵʖ : Lyyds/sniarbtej/ˊ;
    //   6568: aload #9
    //   6570: aconst_null
    //   6571: putfield ﾞл : Lyyds/sniarbtej/ˊ;
    //   6574: aload #9
    //   6576: aconst_null
    //   6577: putfield ʿᵉ : Lyyds/sniarbtej/ˊ;
    //   6580: aload #9
    //   6582: aconst_null
    //   6583: putfield ʹﮃ : Lyyds/sniarbtej/ˊ;
    //   6586: aload #9
    //   6588: aconst_null
    //   6589: putfield ᐨẏ : Lyyds/sniarbtej/ˈے;
    //   6592: aload #9
    //   6594: iconst_0
    //   6595: putfield ˌх : I
    //   6598: aload #9
    //   6600: iconst_0
    //   6601: putfield ιﾌ : I
    //   6604: aload #9
    //   6606: aconst_null
    //   6607: putfield ﾞл : Lyyds/sniarbtej/ʿᵉ;
    //   6610: aload #9
    //   6612: iconst_0
    //   6613: putfield ʻւ : I
    //   6616: aload #9
    //   6618: aconst_null
    //   6619: putfield ʿᵉ : Lyyds/sniarbtej/ʿᵉ;
    //   6622: aload #9
    //   6624: aconst_null
    //   6625: putfield ᐨẏ : Lyyds/sniarbtej/ﾞǰ;
    //   6628: aload #9
    //   6630: aconst_null
    //   6631: putfield ˊ : Lyyds/sniarbtej/ﾞǰ;
    //   6634: aload #9
    //   6636: aconst_null
    //   6637: putfield ˊ : Lyyds/sniarbtej/ᴵʖ;
    //   6640: aload #9
    //   6642: iload #11
    //   6644: ifeq -> 6651
    //   6647: iconst_3
    //   6648: goto -> 6652
    //   6651: iconst_0
    //   6652: putfield ˑܘ : I
    //   6655: new yyds/sniarbtej/ᐨم
    //   6658: dup
    //   6659: aload #10
    //   6661: iconst_0
    //   6662: iconst_0
    //   6663: invokespecial <init> : ([BIZ)V
    //   6666: aload #9
    //   6668: aload #12
    //   6670: iload #11
    //   6672: ifeq -> 6680
    //   6675: bipush #8
    //   6677: goto -> 6681
    //   6680: iconst_0
    //   6681: sipush #256
    //   6684: ior
    //   6685: invokevirtual ᐨẏ : (Lyyds/sniarbtej/ˍɫ;[Lyyds/sniarbtej/ᴵʖ;I)V
    //   6688: aload #9
    //   6690: astore_0
    //   6691: goto -> 0
    //   6694: aload_1
    //   6695: getfield ˊ : [B
    //   6698: areturn
  }
  
  private byte[] ᐨẏ(byte[] paramArrayOfbyte, boolean paramBoolean) {
    ᴵʖ[] arrayOfᴵʖ = ˊ();
    this.ᐨẏ = null;
    this.ˊ = null;
    this.ᐨẏ = null;
    this.ˊ = null;
    this.ᴵʖ = null;
    this.ﾞл = null;
    this.ʿᵉ = null;
    this.ʹﮃ = null;
    this.ᐨẏ = null;
    this.ˌх = 0;
    this.ιﾌ = 0;
    this.ﾞл = null;
    this.ʻւ = 0;
    this.ʿᵉ = null;
    this.ᐨẏ = null;
    this.ˊ = null;
    this.ˊ = null;
    this.ˑܘ = paramBoolean ? 3 : 0;
    (new ᐨم(paramArrayOfbyte, 0, false)).ᐨẏ(this, arrayOfᴵʖ, (paramBoolean ? 8 : 0) | 0x100);
    return ᐨẏ();
  }
  
  private ᴵʖ[] ˊ() {
    ﾞл ﾞл;
    (ﾞл = new ﾞл()).ᐨẏ(this.ˊ);
    ﾞǰ ﾞǰ1 = this.ᐨẏ;
    while (ﾞǰ1 != null) {
      ﾞǰ1.ᐨẏ(ﾞл);
      ˌ ˌ1 = (ˌ)((ˌ)ﾞǰ1).ᐨẏ;
    } 
    ﾞǰ1 = this.ᐨẏ;
    while (ﾞǰ1 != null) {
      ﾞǰ1.ᐨẏ(ﾞл);
      ʿপ ʿপ1 = (ʿপ)((ʿপ)ﾞǰ1).ᐨẏ;
    } 
    for (ﾞǰ1 = this.ᐨẏ; ﾞǰ1 != null; ﾞǰ1 = (ﾞǰ)ﾞǰ1.ᐨẏ)
      ﾞǰ1.ᐨẏ(ﾞл); 
    return ﾞл.ᐨẏ();
  }
  
  private int ᐨẏ(Object paramObject) {
    return (this.ᐨẏ.ᐨẏ(paramObject)).ͺᴲ;
  }
  
  public final int ˊ(String paramString) {
    return this.ᐨẏ.ՙᗮ(paramString);
  }
  
  private int ᴵʖ(String paramString) {
    String str = paramString;
    ﾞǰ ﾞǰ1;
    return ((ﾞǰ1 = this.ᐨẏ).ᐨẏ(7, str)).ͺᴲ;
  }
  
  private int ﾞл(String paramString) {
    String str = paramString;
    ﾞǰ ﾞǰ1;
    return ((ﾞǰ1 = this.ᐨẏ).ᐨẏ(16, str)).ͺᴲ;
  }
  
  public final int ʿᵉ(String paramString) {
    String str = paramString;
    ﾞǰ ﾞǰ1;
    return ((ﾞǰ1 = this.ᐨẏ).ᐨẏ(19, str)).ͺᴲ;
  }
  
  private int ʹﮃ(String paramString) {
    String str = paramString;
    ﾞǰ ﾞǰ1;
    return ((ﾞǰ1 = this.ᐨẏ).ᐨẏ(20, str)).ͺᴲ;
  }
  
  @Deprecated
  private int ᐨẏ(int paramInt, String paramString1, String paramString2, String paramString3) {
    boolean bool = (paramInt == 9) ? true : false;
    String str = paramString3;
    paramString3 = paramString2;
    paramString2 = paramString1;
    int i = paramInt;
    ʽ ʽ1;
    return ((ʽ1 = this).ᐨẏ.ᐨẏ(i, paramString2, paramString3, str, bool)).ͺᴲ;
  }
  
  private int ᐨẏ(int paramInt, String paramString1, String paramString2, String paramString3, boolean paramBoolean) {
    return (this.ᐨẏ.ᐨẏ(paramInt, paramString1, paramString2, paramString3, paramBoolean)).ͺᴲ;
  }
  
  private int ᐨẏ(String paramString1, String paramString2, ʹō paramʹō, Object... paramVarArgs) {
    return (this.ᐨẏ.ᐨẏ(paramString1, paramString2, paramʹō, paramVarArgs)).ͺᴲ;
  }
  
  private int ˊ(String paramString1, String paramString2, ʹō paramʹō, Object... paramVarArgs) {
    return (this.ᐨẏ.ˊ(paramString1, paramString2, paramʹō, paramVarArgs)).ͺᴲ;
  }
  
  private int ᐨẏ(String paramString1, String paramString2, String paramString3) {
    return (this.ᐨẏ.ᐨẏ(paramString1, paramString2, paramString3)).ͺᴲ;
  }
  
  private int ᐨẏ(String paramString1, String paramString2, String paramString3, boolean paramBoolean) {
    return (this.ᐨẏ.ᐨẏ(paramString1, paramString2, paramString3, paramBoolean)).ͺᴲ;
  }
  
  private int ᐨẏ(String paramString1, String paramString2) {
    return this.ᐨẏ.ˊ(paramString1, paramString2);
  }
  
  protected final String ᐨẏ(String paramString1, String paramString2) {
    Class<?> clazz1;
    ʽ ʽ1;
    ClassLoader classLoader = (ʽ1 = this).getClass().getClassLoader();
    try {
      clazz2 = Class.forName(paramString1.replace('/', '.'), false, classLoader);
    } catch (ClassNotFoundException classNotFoundException2) {
      throw new TypeNotPresentException(paramString1, classNotFoundException2);
    } 
    try {
      clazz1 = Class.forName(paramString2.replace('/', '.'), false, (ClassLoader)classNotFoundException2);
    } catch (ClassNotFoundException classNotFoundException1) {
      throw new TypeNotPresentException(paramString2, classNotFoundException1);
    } 
    if (clazz2.isAssignableFrom(clazz1))
      return (String)classNotFoundException1; 
    if (clazz1.isAssignableFrom(clazz2))
      return paramString2; 
    if (clazz2.isInterface() || clazz1.isInterface()) {
      "筇ὑ⩢猊阪ၴ톢糧伩劈歎继ᆠ廒뷅ゴ".toCharArray()[11] = (char)("筇ὑ⩢猊阪ၴ톢糧伩劈歎继ᆠ廒뷅ゴ".toCharArray()[11] ^ 0x96E);
      return ᐨẏ$ᐝт.W("筇ὑ⩢猊阪ၴ톢糧伩劈歎继ᆠ廒뷅ゴ".toCharArray(), (short)26633, (byte)0, (short)3);
    } 
    Class<?> clazz2;
    do {
    
    } while (!(clazz2 = clazz2.getSuperclass()).isAssignableFrom(clazz1));
    return clazz2.getName().replace('.', '/');
  }
  
  private ClassLoader ᐨẏ() {
    return getClass().getClassLoader();
  }
}


/* Location:              C:\Users\kb\Downloads\ja-netfilter.jar!\yyds\sniarbtej\ʽ.class
 * Java compiler version: 8 (52.0)
 * JD-Core Version:       1.1.3
 */