package yyds.sniarbtej;

import ylt.pmn.zubdqvgt;

public final class ʿপ extends ˉｓ {
  private static int ʻṿ = 0;
  
  private static int ﹳﺫ = 1;
  
  private static int ˍᔨ = 2;
  
  private static int ˌদ = 3;
  
  private static int ʻⅬ = 4;
  
  private static final int ˌᑦ = 0;
  
  private static final int[] ʾ = new int[] { 
      0, 1, 1, 1, 1, 1, 1, 1, 1, 2, 
      2, 1, 1, 1, 2, 2, 1, 1, 1, 0, 
      0, 1, 2, 1, 2, 1, 0, 0, 0, 0, 
      0, 0, 0, 0, 0, 0, 0, 0, 0, 0, 
      0, 0, 0, 0, 0, 0, -1, 0, -1, 0, 
      -1, -1, -1, -1, -1, -2, -1, -2, -1, 0, 
      0, 0, 0, 0, 0, 0, 0, 0, 0, 0, 
      0, 0, 0, 0, 0, 0, 0, 0, 0, -3, 
      -4, -3, -4, -3, -3, -3, -3, -1, -2, 1, 
      1, 1, 2, 2, 2, 0, -1, -2, -1, -2, 
      -1, -2, -1, -2, -1, -2, -1, -2, -1, -2, 
      -1, -2, -1, -2, -1, -2, 0, 0, 0, 0, 
      -1, -1, -1, -1, -1, -1, -1, -2, -1, -2, 
      -1, -2, 0, 1, 0, 1, -1, -1, 0, 0, 
      1, 1, -1, 0, -1, 0, 0, 0, -3, -1, 
      -1, -3, -3, -1, -1, -1, -1, -1, -1, -2, 
      -2, -2, -2, -2, -2, -2, -2, 0, 1, 0, 
      -1, -1, -1, -2, -1, -2, -1, 0, 0, 0, 
      0, 0, 0, 0, 0, 0, 0, 1, 0, 0, 
      0, 0, 0, 0, -1, -1, 0, 0, -1, -1, 
      0, 0 };
  
  final ˌх ᐨẏ;
  
  final int ʿλ;
  
  final int ᐝт;
  
  final String name;
  
  final int ɟ;
  
  final String ᴵʖ;
  
  int ˑỲ;
  
  int ˌپ;
  
  final ʿᵉ ʹﮃ;
  
  ˌᑦ ᐨẏ;
  
  private ˌᑦ ˊ;
  
  int ﾞﮢ;
  
  ʿᵉ ՙᗮ;
  
  int ﾞﾇ;
  
  ʿᵉ ˍɫ;
  
  int ˍʶ;
  
  ʿᵉ ʽ;
  
  int ᓑ;
  
  ʿᵉ ʾܪ;
  
  ˊ ՙᗮ;
  
  ˊ ˍɫ;
  
  ᴵʖ ᴵʖ;
  
  final int ٴῪ;
  
  final int[] ͺо;
  
  final int ﾞǰ;
  
  ˊ ᴵʖ;
  
  ˊ ﾞл;
  
  int শ;
  
  ˊ[] ᐨẏ;
  
  int ˋᴷ;
  
  ˊ[] ˊ;
  
  ˊ ʿᵉ;
  
  ˊ ʹﮃ = (ˊ)new ʿᵉ();
  
  ʿᵉ ᐨم;
  
  int ﹼ;
  
  ʿᵉ ʾ;
  
  ᴵʖ ˊ;
  
  private final int ˑܘ;
  
  private ᔪ ʽ;
  
  private ᔪ ʾܪ;
  
  private ᔪ ᐨم;
  
  private int ˑײַ;
  
  private int ᴾ;
  
  private int ʼᓓ;
  
  private int ᐝᵛ;
  
  private int[] ٴӵ;
  
  public int[] ᴵƚ;
  
  private boolean ᴵʖ;
  
  boolean ﾞл;
  
  private int ՙぃ;
  
  int ᴵ氵;
  
  int ᵊ;
  
  ʿপ(ˌх paramˌх, int paramInt1, String paramString1, String paramString2, String paramString3, String[] paramArrayOfString, int paramInt2) {
    super(589824);
    this.ᐨẏ = (ˊ[])paramˌх;
    "ࠉ㘄鿞ⰵԊ".toCharArray()[1] = (char)("ࠉ㘄鿞ⰵԊ".toCharArray()[1] ^ 0x62B1);
    this.ʿλ = ᐨẏ$ᐝт.W("ࠉ㘄鿞ⰵԊ".toCharArray(), (short)15892, (byte)0, (short)5).equals(paramString1) ? (paramInt1 | 0x40000) : paramInt1;
    this.ᐝт = paramˌх.ՙᗮ(paramString1);
    this.name = paramString1;
    this.ɟ = paramˌх.ՙᗮ(paramString2);
    this.ᴵʖ = paramString2;
    this.ﾞǰ = (paramString3 == null) ? 0 : paramˌх.ՙᗮ(paramString3);
    if (paramArrayOfString != null && paramArrayOfString.length > 0) {
      this.ٴῪ = paramArrayOfString.length;
      this.ͺо = new int[this.ٴῪ];
      for (byte b = 0; b < this.ٴῪ; b++) {
        String str = paramArrayOfString[b];
        ˌх ˌх1;
        this.ͺо[b] = ((ˌх1 = paramˌх).ᐨẏ(7, str)).ͺᴲ;
      } 
    } else {
      this.ٴῪ = 0;
      this.ͺо = null;
    } 
    this.ˑܘ = paramInt2;
    if (paramInt2 != 0) {
      int i = ˑܘ.ᐨم(paramString2) >> 2;
      if ((paramInt1 & 0x8) != 0)
        i--; 
      this.ˌپ = i;
      this.ʼᓓ = i;
      this.ʽ = new ᔪ();
      ˊ(this.ʽ);
    } 
  }
  
  final boolean ﾞл() {
    return (this.ᓑ > 0);
  }
  
  final boolean ʿᵉ() {
    return this.ﾞл;
  }
  
  public final void ᐨẏ(String paramString, int paramInt) {
    if (this.ʾ == null)
      this.ʾ = new ʿᵉ(); 
    this.ﹼ++;
    this.ʾ.ˊ((paramString == null) ? 0 : this.ᐨẏ.ՙᗮ(paramString)).ˊ(paramInt);
  }
  
  public final ᐨẏ ˊ() {
    this.ᐨم = (ᔪ)new ʿᵉ();
    return new ˊ((ˌх)this.ᐨẏ, false, (ʿᵉ)this.ᐨم, null);
  }
  
  public final ᐨẏ ᐨẏ(String paramString, boolean paramBoolean) {
    return paramBoolean ? (this.ᴵʖ = ˊ.ᐨẏ((ˌх)this.ᐨẏ, paramString, this.ᴵʖ)) : (this.ﾞл = ˊ.ᐨẏ((ˌх)this.ᐨẏ, paramString, this.ﾞл));
  }
  
  public final ᐨẏ ᐨẏ(int paramInt, ˏɪ paramˏɪ, String paramString, boolean paramBoolean) {
    return paramBoolean ? (this.ʿᵉ = ˊ.ᐨẏ((ˌх)this.ᐨẏ, paramInt, paramˏɪ, paramString, this.ʿᵉ)) : (this.ʹﮃ = ˊ.ᐨẏ((ˌх)this.ᐨẏ, paramInt, paramˏɪ, paramString, this.ʹﮃ));
  }
  
  public final void ᐨẏ(int paramInt, boolean paramBoolean) {
    if (paramBoolean) {
      this.শ = paramInt;
      return;
    } 
    this.ˋᴷ = paramInt;
  }
  
  public final ᐨẏ ᐨẏ(int paramInt, String paramString, boolean paramBoolean) {
    if (paramBoolean) {
      if (this.ᐨẏ == null)
        this.ᐨẏ = new ˊ[ˑܘ.ʾܪ(this.ᴵʖ)]; 
      this.ᐨẏ[paramInt] = ˊ.ᐨẏ((ˌх)this.ᐨẏ, paramString, this.ᐨẏ[paramInt]);
      return ˊ.ᐨẏ((ˌх)this.ᐨẏ, paramString, this.ᐨẏ[paramInt]);
    } 
    if (this.ˊ == null)
      this.ˊ = (ᴵʖ)new ˊ[ˑܘ.ʾܪ(this.ᴵʖ)]; 
    this.ˊ[paramInt] = (ᴵʖ)ˊ.ᐨẏ((ˌх)this.ᐨẏ, paramString, (ˊ)this.ˊ[paramInt]);
    return ˊ.ᐨẏ((ˌх)this.ᐨẏ, paramString, (ˊ)this.ˊ[paramInt]);
  }
  
  public final void ᴵʖ(ᴵʖ paramᴵʖ) {
    paramᴵʖ.ᐨẏ = this.ˊ;
    this.ˊ = paramᴵʖ;
  }
  
  public final void ᴵʖ() {}
  
  public final void ᐨẏ(int paramInt1, int paramInt2, Object[] paramArrayOfObject1, int paramInt3, Object[] paramArrayOfObject2) {
    if (this.ˑܘ == 4)
      return; 
    if (this.ˑܘ == 3) {
      if (this.ᐨم.ᐨẏ == null) {
        this.ᐨم.ᐨẏ = (ٴᐤ)new ͺо(this.ᐨم);
        this.ᐨم.ᐨẏ.ᐨẏ((ˌх)this.ᐨẏ, this.ʿλ, this.ᴵʖ, paramInt2);
        this.ᐨم.ᐨẏ.ᐨẏ(this);
      } else {
        if (paramInt1 == -1)
          this.ᐨم.ᐨẏ.ᐨẏ((ˌх)this.ᐨẏ, paramInt2, paramArrayOfObject1, paramInt3, paramArrayOfObject2); 
        this.ᐨم.ᐨẏ.ᐨẏ(this);
      } 
    } else if (paramInt1 == -1) {
      if (this.ٴӵ == null) {
        int j = ˑܘ.ᐨم(this.ᴵʖ) >> 2;
        ՙ⁔ ՙ⁔;
        (ՙ⁔ = new ՙ⁔(new ᔪ())).ᐨẏ((ˌх)this.ᐨẏ, this.ʿλ, this.ᴵʖ, j);
        ՙ⁔.ᐨẏ(this);
      } 
      this.ʼᓓ = paramInt2;
      int i = ᐨẏ(((ʿᵉ)this.ʹﮃ).ʹﮃ, paramInt2, paramInt3);
      for (paramInt1 = 0; paramInt1 < paramInt2; paramInt1++)
        this.ᴵƚ[i++] = ՙ⁔.ᐨẏ((ˌх)this.ᐨẏ, paramArrayOfObject1[paramInt1]); 
      for (paramInt1 = 0; paramInt1 < paramInt3; paramInt1++)
        this.ᴵƚ[i++] = ՙ⁔.ᐨẏ((ˌх)this.ᐨẏ, paramArrayOfObject2[paramInt1]); 
      ՙᗮ();
    } else {
      int i;
      ˊ[] arrayOfˊ;
      if (((ˌх)(arrayOfˊ = this.ᐨẏ)).Ԇ < 50) {
        "쬷ⰻຑ羭ບ죦뛐⛟랶Ც๳₤醙憗ᾲ큟嶬飅蕅ᦓ袷씭ṳ얖ẙ덕㤪溃Ȑ扵絫䔗郟﹨寈痷묀䎶굃죬嘋᷇主Ƥ".toCharArray()[22] = (char)("쬷ⰻຑ羭ບ죦뛐⛟랶Ც๳₤醙憗ᾲ큟嶬飅蕅ᦓ袷씭ṳ얖ẙ덕㤪溃Ȑ扵絫䔗郟﹨寈痷묀䎶굃죬嘋᷇主Ƥ".toCharArray()[22] ^ 0x75F4);
        throw new IllegalArgumentException(ˏȓ$ᴵЃ.E("쬷ⰻຑ羭ບ죦뛐⛟랶Ც๳₤醙憗ᾲ큟嶬飅蕅ᦓ袷씭ṳ얖ẙ덕㤪溃Ȑ扵絫䔗郟﹨寈痷묀䎶굃죬嘋᷇主Ƥ".toCharArray(), (short)1043, (short)3, (short)2));
      } 
      if (this.ʾܪ == null) {
        this.ʾܪ = (ᔪ)new ʿᵉ();
        i = ((ʿᵉ)this.ʹﮃ).ʹﮃ;
      } else if ((i = ((ʿᵉ)this.ʹﮃ).ʹﮃ - this.ᐝᵛ - 1) < 0) {
        if (paramInt1 == 3)
          return; 
        throw new IllegalStateException();
      } 
      switch (paramInt1) {
        case 0:
          this.ʼᓓ = paramInt2;
          this.ʾܪ.ᐨẏ(255).ˊ(i).ˊ(paramInt2);
          for (paramInt1 = 0; paramInt1 < paramInt2; paramInt1++)
            ᴵʖ(paramArrayOfObject1[paramInt1]); 
          this.ʾܪ.ˊ(paramInt3);
          for (paramInt1 = 0; paramInt1 < paramInt3; paramInt1++)
            ᴵʖ(paramArrayOfObject2[paramInt1]); 
          break;
        case 1:
          this.ʼᓓ += paramInt2;
          this.ʾܪ.ᐨẏ(paramInt2 + 251).ˊ(i);
          for (paramInt1 = 0; paramInt1 < paramInt2; paramInt1++)
            ᴵʖ(paramArrayOfObject1[paramInt1]); 
          break;
        case 2:
          this.ʼᓓ -= paramInt2;
          this.ʾܪ.ᐨẏ(251 - paramInt2).ˊ(i);
          break;
        case 3:
          if (i < 64) {
            this.ʾܪ.ᐨẏ(i);
            break;
          } 
          this.ʾܪ.ᐨẏ(251).ˊ(i);
          break;
        case 4:
          if (i < 64) {
            this.ʾܪ.ᐨẏ(i + 64);
          } else {
            this.ʾܪ.ᐨẏ(247).ˊ(i);
          } 
          ᴵʖ(paramArrayOfObject2[0]);
          break;
        default:
          throw new IllegalArgumentException();
      } 
      this.ᐝᵛ = ((ʿᵉ)this.ʹﮃ).ʹﮃ;
      this.ᓑ++;
    } 
    if (this.ˑܘ == 2) {
      this.ˑײַ = paramInt3;
      for (byte b = 0; b < paramInt3; b++) {
        if (zubdqvgt.G(paramArrayOfObject2[b], ـﭔ.ʿᵉ) || zubdqvgt.G(paramArrayOfObject2[b], ـﭔ.ﾞл))
          this.ˑײַ++; 
      } 
      if (this.ˑײַ > this.ᴾ)
        this.ᴾ = this.ˑײַ; 
    } 
    this.ˑỲ = Math.max(this.ˑỲ, paramInt3);
    this.ˌپ = Math.max(this.ˌپ, this.ʼᓓ);
  }
  
  public final void ʹﮃ(int paramInt) {
    this.ՙぃ = ((ʿᵉ)this.ʹﮃ).ʹﮃ;
    this.ʹﮃ.ᐨẏ(paramInt);
    if (this.ᐨم != null) {
      if (this.ˑܘ == 4 || this.ˑܘ == 3) {
        this.ᐨم.ᐨẏ.ᐨẏ(paramInt, 0, (ˊᵃ)null, (ˌх)null);
      } else {
        int i;
        if ((i = this.ˑײַ + ʾ[paramInt]) > this.ᴾ)
          this.ᴾ = i; 
        this.ˑײַ = i;
      } 
      if ((paramInt >= 172 && paramInt <= 177) || paramInt == 191)
        ʹﮃ(); 
    } 
  }
  
  public final void ˊ(int paramInt1, int paramInt2) {
    this.ՙぃ = ((ʿᵉ)this.ʹﮃ).ʹﮃ;
    if (paramInt1 == 17) {
      this.ʹﮃ.ˊ(paramInt1, paramInt2);
    } else {
      this.ʹﮃ.ᐨẏ(paramInt1, paramInt2);
    } 
    if (this.ᐨم != null) {
      if (this.ˑܘ == 4 || this.ˑܘ == 3) {
        this.ᐨم.ᐨẏ.ᐨẏ(paramInt1, paramInt2, (ˊᵃ)null, (ˌх)null);
        return;
      } 
      if (paramInt1 != 188) {
        if ((paramInt1 = this.ˑײַ + 1) > this.ᴾ)
          this.ᴾ = paramInt1; 
        this.ˑײַ = paramInt1;
      } 
    } 
  }
  
  public final void ᴵʖ(int paramInt1, int paramInt2) {
    this.ՙぃ = ((ʿᵉ)this.ʹﮃ).ʹﮃ;
    if (paramInt2 < 4 && paramInt1 != 169) {
      int i;
      if (paramInt1 < 54) {
        i = 26 + (paramInt1 - 21 << 2) + paramInt2;
      } else {
        i = 59 + (paramInt1 - 54 << 2) + paramInt2;
      } 
      this.ʹﮃ.ᐨẏ(i);
    } else if (paramInt2 >= 256) {
      this.ʹﮃ.ᐨẏ(196).ˊ(paramInt1, paramInt2);
    } else {
      this.ʹﮃ.ᐨẏ(paramInt1, paramInt2);
    } 
    if (this.ᐨم != null)
      if (this.ˑܘ == 4 || this.ˑܘ == 3) {
        this.ᐨم.ᐨẏ.ᐨẏ(paramInt1, paramInt2, (ˊᵃ)null, (ˌх)null);
      } else if (paramInt1 == 169) {
        this.ᐨم.ᴵʖ = (short)(this.ᐨم.ᴵʖ | 0x40);
        this.ᐨم.ʹﮃ = (short)this.ˑײַ;
        ʹﮃ();
      } else {
        int i;
        if ((i = this.ˑײַ + ʾ[paramInt1]) > this.ᴾ)
          this.ᴾ = i; 
        this.ˑײַ = i;
      }  
    if (this.ˑܘ != 0) {
      int i;
      if (paramInt1 == 22 || paramInt1 == 24 || paramInt1 == 55 || paramInt1 == 57) {
        i = paramInt2 + 2;
      } else {
        i = paramInt2 + 1;
      } 
      if (i > this.ˌپ)
        this.ˌپ = i; 
    } 
    if (paramInt1 >= 54 && this.ˑܘ == 4 && this.ᐨẏ != null)
      ˊ(new ᔪ()); 
  }
  
  public final void ᐨẏ(int paramInt, String paramString) {
    this.ՙぃ = ((ʿᵉ)this.ʹﮃ).ʹﮃ;
    String str = paramString;
    ˊ[] arrayOfˊ;
    ˊᵃ ˊᵃ = (arrayOfˊ = this.ᐨẏ).ᐨẏ(7, str);
    this.ʹﮃ.ˊ(paramInt, ˊᵃ.ͺᴲ);
    if (this.ᐨم != null) {
      if (this.ˑܘ == 4 || this.ˑܘ == 3) {
        this.ᐨم.ᐨẏ.ᐨẏ(paramInt, this.ՙぃ, ˊᵃ, (ˌх)this.ᐨẏ);
        return;
      } 
      if (paramInt == 187) {
        if ((paramInt = this.ˑײַ + 1) > this.ᴾ)
          this.ᴾ = paramInt; 
        this.ˑײַ = paramInt;
      } 
    } 
  }
  
  public final void ᐨẏ(int paramInt, String paramString1, String paramString2, String paramString3) {
    this.ՙぃ = ((ʿᵉ)this.ʹﮃ).ʹﮃ;
    ˊᵃ ˊᵃ = this.ᐨẏ.ᐨẏ(paramString1, paramString2, paramString3);
    this.ʹﮃ.ˊ(paramInt, ˊᵃ.ͺᴲ);
    if (this.ᐨم != null) {
      if (this.ˑܘ == 4 || this.ˑܘ == 3) {
        this.ᐨم.ᐨẏ.ᐨẏ(paramInt, 0, ˊᵃ, (ˌх)this.ᐨẏ);
        return;
      } 
      char c = paramString3.charAt(0);
      switch (paramInt) {
        case 178:
          paramInt = this.ˑײַ + ((c == 'D' || c == 'J') ? 2 : 1);
          break;
        case 179:
          paramInt = this.ˑײַ + ((c == 'D' || c == 'J') ? -2 : -1);
          break;
        case 180:
          paramInt = this.ˑײַ + ((c == 'D' || c == 'J') ? 1 : 0);
          break;
        default:
          paramInt = this.ˑײַ + ((c == 'D' || c == 'J') ? -3 : -2);
          break;
      } 
      if (paramInt > this.ᴾ)
        this.ᴾ = paramInt; 
      this.ˑײַ = paramInt;
    } 
  }
  
  public final void ᐨẏ(int paramInt, String paramString1, String paramString2, String paramString3, boolean paramBoolean) {
    this.ՙぃ = ((ʿᵉ)this.ʹﮃ).ʹﮃ;
    ˊᵃ ˊᵃ = this.ᐨẏ.ᐨẏ(paramString1, paramString2, paramString3, paramBoolean);
    if (paramInt == 185) {
      this.ʹﮃ.ˊ(185, ˊᵃ.ͺᴲ).ᐨẏ(ˊᵃ.ʹō() >> 2, 0);
    } else {
      this.ʹﮃ.ˊ(paramInt, ˊᵃ.ͺᴲ);
    } 
    if (this.ᐨم != null) {
      if (this.ˑܘ == 4 || this.ˑܘ == 3) {
        this.ᐨم.ᐨẏ.ᐨẏ(paramInt, 0, ˊᵃ, (ˌх)this.ᐨẏ);
        return;
      } 
      int i = ((i = ˊᵃ.ʹō()) & 0x3) - (i >> 2);
      if (paramInt == 184) {
        paramInt = this.ˑײַ + i + 1;
      } else {
        paramInt = this.ˑײַ + i;
      } 
      if (paramInt > this.ᴾ)
        this.ᴾ = paramInt; 
      this.ˑײַ = paramInt;
    } 
  }
  
  public final void ᐨẏ(String paramString1, String paramString2, ʹō paramʹō, Object... paramVarArgs) {
    this.ՙぃ = ((ʿᵉ)this.ʹﮃ).ʹﮃ;
    ˊᵃ ˊᵃ = this.ᐨẏ.ˊ(paramString1, paramString2, paramʹō, paramVarArgs);
    this.ʹﮃ.ˊ(186, ˊᵃ.ͺᴲ);
    this.ʹﮃ.ˊ(0);
    if (this.ᐨم != null) {
      if (this.ˑܘ == 4 || this.ˑܘ == 3) {
        this.ᐨم.ᐨẏ.ᐨẏ(186, 0, ˊᵃ, (ˌх)this.ᐨẏ);
        return;
      } 
      int i = ((i = ˊᵃ.ʹō()) & 0x3) - (i >> 2) + 1;
      if ((i = this.ˑײַ + i) > this.ᴾ)
        this.ᴾ = i; 
      this.ˑײַ = i;
    } 
  }
  
  public final void ᐨẏ(int paramInt, ᔪ paramᔪ) {
    this.ՙぃ = ((ʿᵉ)this.ʹﮃ).ʹﮃ;
    int i = (paramInt >= 200) ? (paramInt - 33) : paramInt;
    boolean bool = false;
    if ((paramᔪ.ᴵʖ & 0x4) != 0 && paramᔪ.ʻบ - ((ʿᵉ)this.ʹﮃ).ʹﮃ < -32768) {
      if (i == 167) {
        this.ʹﮃ.ᐨẏ(200);
      } else if (i == 168) {
        this.ʹﮃ.ᐨẏ(201);
      } else {
        this.ʹﮃ.ᐨẏ((i >= 198) ? (i ^ 0x1) : ((i + 1 ^ 0x1) - 1));
        this.ʹﮃ.ˊ(8);
        this.ʹﮃ.ᐨẏ(220);
        this.ﾞл = true;
        bool = true;
      } 
      paramᔪ.ᐨẏ((ʿᵉ)this.ʹﮃ, ((ʿᵉ)this.ʹﮃ).ʹﮃ - 1, true);
    } else if (i != paramInt) {
      this.ʹﮃ.ᐨẏ(paramInt);
      paramᔪ.ᐨẏ((ʿᵉ)this.ʹﮃ, ((ʿᵉ)this.ʹﮃ).ʹﮃ - 1, true);
    } else {
      this.ʹﮃ.ᐨẏ(i);
      paramᔪ.ᐨẏ((ʿᵉ)this.ʹﮃ, ((ʿᵉ)this.ʹﮃ).ʹﮃ - 1, false);
    } 
    if (this.ᐨم != null) {
      ᔪ ᔪ1 = null;
      if (this.ˑܘ == 4) {
        this.ᐨم.ᐨẏ.ᐨẏ(i, 0, (ˊᵃ)null, (ˌх)null);
        (paramᔪ.ᐨẏ()).ᴵʖ = (short)((paramᔪ.ᐨẏ()).ᴵʖ | 0x2);
        ᴵʖ(0, paramᔪ);
        if (i != 167)
          ᔪ1 = new ᔪ(); 
      } else if (this.ˑܘ == 3) {
        this.ᐨم.ᐨẏ.ᐨẏ(i, 0, (ˊᵃ)null, (ˌх)null);
      } else if (this.ˑܘ == 2) {
        this.ˑײַ += ʾ[i];
      } else if (i == 168) {
        if ((paramᔪ.ᴵʖ & 0x20) == 0) {
          paramᔪ.ᴵʖ = (short)(paramᔪ.ᴵʖ | 0x20);
          this.ᴵʖ = true;
        } 
        this.ᐨم.ᴵʖ = (short)(this.ᐨم.ᴵʖ | 0x10);
        ᴵʖ(this.ˑײַ + 1, paramᔪ);
        ᔪ1 = new ᔪ();
      } else {
        this.ˑײַ += ʾ[i];
        ᴵʖ(this.ˑײַ, paramᔪ);
      } 
      if (ᔪ1 != null) {
        if (bool)
          ᔪ1.ᴵʖ = (short)(ᔪ1.ᴵʖ | 0x2); 
        ˊ(ᔪ1);
      } 
      if (i == 167)
        ʹﮃ(); 
    } 
  }
  
  public final void ˊ(ᔪ paramᔪ) {
    this.ﾞл |= paramᔪ.ᐨẏ(((ʿᵉ)this.ʹﮃ).ˊ, (ʿᵉ)this.ʾܪ, ((ʿᵉ)this.ʹﮃ).ʹﮃ);
    if ((paramᔪ.ᴵʖ & 0x1) != 0)
      return; 
    if (this.ˑܘ == 4) {
      if (this.ᐨم != null) {
        if (paramᔪ.ʻบ == this.ᐨم.ʻบ) {
          this.ᐨم.ᴵʖ = (short)(this.ᐨم.ᴵʖ | paramᔪ.ᴵʖ & 0x2);
          paramᔪ.ᐨẏ = this.ᐨم.ᐨẏ;
          return;
        } 
        ᴵʖ(0, paramᔪ);
      } 
      if (this.ʾܪ != null) {
        if (paramᔪ.ʻบ == this.ʾܪ.ʻบ) {
          this.ʾܪ.ᴵʖ = (short)(this.ʾܪ.ᴵʖ | paramᔪ.ᴵʖ & 0x2);
          paramᔪ.ᐨẏ = this.ʾܪ.ᐨẏ;
          this.ᐨم = this.ʾܪ;
          return;
        } 
        this.ʾܪ.ՙᗮ = paramᔪ;
      } 
      this.ʾܪ = paramᔪ;
      this.ᐨم = paramᔪ;
      paramᔪ.ᐨẏ = (ٴᐤ)new ՙ⁔(paramᔪ);
      return;
    } 
    if (this.ˑܘ == 3) {
      if (this.ᐨم == null) {
        this.ᐨم = paramᔪ;
        return;
      } 
      ((ՙ⁔)this.ᐨم.ᐨẏ).ˊ = paramᔪ;
      return;
    } 
    if (this.ˑܘ == 1) {
      if (this.ᐨم != null) {
        this.ᐨم.ՙᗮ = (short)this.ᴾ;
        ᴵʖ(this.ˑײַ, paramᔪ);
      } 
      this.ᐨم = paramᔪ;
      this.ˑײַ = 0;
      this.ᴾ = 0;
      if (this.ʾܪ != null)
        this.ʾܪ.ՙᗮ = paramᔪ; 
      this.ʾܪ = paramᔪ;
      return;
    } 
    if (this.ˑܘ == 2 && this.ᐨم == null)
      this.ᐨم = paramᔪ; 
  }
  
  public final void ˊ(Object paramObject) {
    this.ՙぃ = ((ʿᵉ)this.ʹﮃ).ʹﮃ;
    int i = ((ˊᵃ)(paramObject = this.ᐨẏ.ᐨẏ(paramObject))).ͺᴲ;
    char c;
    if ((c = (((ˊᵃ)paramObject).ᙆ == 5 || ((ˊᵃ)paramObject).ᙆ == 6 || (((ˊᵃ)paramObject).ᙆ == 17 && ((c = ((ˊᵃ)paramObject).ʹл.charAt(0)) == 'J' || c == 'D'))) ? '\001' : Character.MIN_VALUE) != '\000') {
      this.ʹﮃ.ˊ(20, i);
    } else if (i >= 256) {
      this.ʹﮃ.ˊ(19, i);
    } else {
      this.ʹﮃ.ᐨẏ(18, i);
    } 
    if (this.ᐨم != null) {
      if (this.ˑܘ == 4 || this.ˑܘ == 3) {
        this.ᐨم.ᐨẏ.ᐨẏ(18, 0, (ˊᵃ)paramObject, (ˌх)this.ᐨẏ);
        return;
      } 
      int j;
      if ((j = this.ˑײַ + ((c != '\000') ? 2 : 1)) > this.ᴾ)
        this.ᴾ = j; 
      this.ˑײַ = j;
    } 
  }
  
  public final void ﾞл(int paramInt1, int paramInt2) {
    this.ՙぃ = ((ʿᵉ)this.ʹﮃ).ʹﮃ;
    if (paramInt1 > 255 || paramInt2 > 127 || paramInt2 < -128) {
      this.ʹﮃ.ᐨẏ(196).ˊ(132, paramInt1).ˊ(paramInt2);
    } else {
      this.ʹﮃ.ᐨẏ(132).ᐨẏ(paramInt1, paramInt2);
    } 
    if (this.ᐨم != null && (this.ˑܘ == 4 || this.ˑܘ == 3))
      this.ᐨم.ᐨẏ.ᐨẏ(132, paramInt1, (ˊᵃ)null, (ˌх)null); 
    if (this.ˑܘ != 0 && ++paramInt1 > this.ˌپ)
      this.ˌپ = paramInt1; 
  }
  
  public final void ᐨẏ(int paramInt1, int paramInt2, ᔪ paramᔪ, ᔪ... paramVarArgs) {
    this.ՙぃ = ((ʿᵉ)this.ʹﮃ).ʹﮃ;
    this.ʹﮃ.ᐨẏ(170).ᐨẏ((byte[])null, 0, (4 - ((ʿᵉ)this.ʹﮃ).ʹﮃ % 4) % 4);
    paramᔪ.ᐨẏ((ʿᵉ)this.ʹﮃ, this.ՙぃ, true);
    this.ʹﮃ.ᴵʖ(paramInt1).ᴵʖ(paramInt2);
    ᔪ[] arrayOfᔪ;
    paramInt2 = (arrayOfᔪ = paramVarArgs).length;
    for (byte b = 0; b < paramInt2; b++) {
      ᔪ ᔪ1;
      (ᔪ1 = arrayOfᔪ[b]).ᐨẏ((ʿᵉ)this.ʹﮃ, this.ՙぃ, true);
    } 
    ᐨẏ(paramᔪ, paramVarArgs);
  }
  
  public final void ᐨẏ(ᔪ paramᔪ, int[] paramArrayOfint, ᔪ[] paramArrayOfᔪ) {
    this.ՙぃ = ((ʿᵉ)this.ʹﮃ).ʹﮃ;
    this.ʹﮃ.ᐨẏ(171).ᐨẏ((byte[])null, 0, (4 - ((ʿᵉ)this.ʹﮃ).ʹﮃ % 4) % 4);
    paramᔪ.ᐨẏ((ʿᵉ)this.ʹﮃ, this.ՙぃ, true);
    this.ʹﮃ.ᴵʖ(paramArrayOfᔪ.length);
    for (byte b = 0; b < paramArrayOfᔪ.length; b++) {
      this.ʹﮃ.ᴵʖ(paramArrayOfint[b]);
      paramArrayOfᔪ[b].ᐨẏ((ʿᵉ)this.ʹﮃ, this.ՙぃ, true);
    } 
    ᐨẏ(paramᔪ, paramArrayOfᔪ);
  }
  
  private void ᐨẏ(ᔪ paramᔪ, ᔪ[] paramArrayOfᔪ) {
    if (this.ᐨم != null) {
      ᔪ[] arrayOfᔪ;
      int i;
      if (this.ˑܘ == 4) {
        this.ᐨم.ᐨẏ.ᐨẏ(171, 0, (ˊᵃ)null, (ˌх)null);
        ᴵʖ(0, paramᔪ);
        (paramᔪ.ᐨẏ()).ᴵʖ = (short)((paramᔪ.ᐨẏ()).ᴵʖ | 0x2);
        i = (arrayOfᔪ = paramArrayOfᔪ).length;
        for (byte b = 0; b < i; b++) {
          ᔪ ᔪ1 = arrayOfᔪ[b];
          ᴵʖ(0, ᔪ1);
          (ᔪ1.ᐨẏ()).ᴵʖ = (short)((ᔪ1.ᐨẏ()).ᴵʖ | 0x2);
        } 
      } else if (this.ˑܘ == 1) {
        this.ˑײַ--;
        ᴵʖ(this.ˑײַ, (ᔪ)arrayOfᔪ);
        int j;
        i = (j = i).length;
        for (byte b = 0; b < i; b++) {
          int k = j[b];
          ᴵʖ(this.ˑײַ, k);
        } 
      } 
      ʹﮃ();
    } 
  }
  
  public final void ˊ(String paramString, int paramInt) {
    this.ՙぃ = ((ʿᵉ)this.ʹﮃ).ʹﮃ;
    String str = paramString;
    ˊ[] arrayOfˊ;
    ˊᵃ ˊᵃ = (arrayOfˊ = this.ᐨẏ).ᐨẏ(7, str);
    this.ʹﮃ.ˊ(197, ˊᵃ.ͺᴲ).ᐨẏ(paramInt);
    if (this.ᐨم != null) {
      if (this.ˑܘ == 4 || this.ˑܘ == 3) {
        this.ᐨم.ᐨẏ.ᐨẏ(197, paramInt, ˊᵃ, (ˌх)this.ᐨẏ);
        return;
      } 
      this.ˑײַ += 1 - paramInt;
    } 
  }
  
  public final ᐨẏ ˊ(int paramInt, ˏɪ paramˏɪ, String paramString, boolean paramBoolean) {
    return paramBoolean ? (this.ՙᗮ = ˊ.ᐨẏ((ˌх)this.ᐨẏ, paramInt & 0xFF0000FF | this.ՙぃ << 8, paramˏɪ, paramString, this.ՙᗮ)) : (this.ˍɫ = ˊ.ᐨẏ((ˌх)this.ᐨẏ, paramInt & 0xFF0000FF | this.ՙぃ << 8, paramˏɪ, paramString, this.ˍɫ));
  }
  
  public final void ᐨẏ(ᔪ paramᔪ1, ᔪ paramᔪ2, ᔪ paramᔪ3, String paramString) {
    ˌᑦ ˌᑦ1 = new ˌᑦ(paramᔪ1, paramᔪ2, paramᔪ3, (paramString != null) ? (this.ᐨẏ.ᐨẏ(paramString)).ͺᴲ : 0, paramString);
    if (this.ᐨẏ == null) {
      this.ᐨẏ = (ˊ[])ˌᑦ1;
    } else {
      ((ˌᑦ)this.ˊ).ᴵʖ = ˌᑦ1;
    } 
    this.ˊ = (ᴵʖ)ˌᑦ1;
  }
  
  public final ᐨẏ ᴵʖ(int paramInt, ˏɪ paramˏɪ, String paramString, boolean paramBoolean) {
    return paramBoolean ? (this.ՙᗮ = ˊ.ᐨẏ((ˌх)this.ᐨẏ, paramInt, paramˏɪ, paramString, this.ՙᗮ)) : (this.ˍɫ = ˊ.ᐨẏ((ˌх)this.ᐨẏ, paramInt, paramˏɪ, paramString, this.ˍɫ));
  }
  
  public final void ᐨẏ(String paramString1, String paramString2, String paramString3, ᔪ paramᔪ1, ᔪ paramᔪ2, int paramInt) {
    if (paramString3 != null) {
      if (this.ʽ == null)
        this.ʽ = (ᔪ)new ʿᵉ(); 
      this.ˍʶ++;
      this.ʽ.ˊ(paramᔪ1.ʻบ).ˊ(paramᔪ2.ʻบ - paramᔪ1.ʻบ).ˊ(this.ᐨẏ.ՙᗮ(paramString1)).ˊ(this.ᐨẏ.ՙᗮ(paramString3)).ˊ(paramInt);
    } 
    if (this.ˍɫ == null)
      this.ˍɫ = (ˊ)new ʿᵉ(); 
    this.ﾞﾇ++;
    this.ˍɫ.ˊ(paramᔪ1.ʻบ).ˊ(paramᔪ2.ʻบ - paramᔪ1.ʻบ).ˊ(this.ᐨẏ.ՙᗮ(paramString1)).ˊ(this.ᐨẏ.ՙᗮ(paramString2)).ˊ(paramInt);
    if (this.ˑܘ != 0) {
      char c = paramString2.charAt(0);
      int i;
      if ((i = paramInt + ((c == 'J' || c == 'D') ? 2 : 1)) > this.ˌپ)
        this.ˌپ = i; 
    } 
  }
  
  public final ᐨẏ ᐨẏ(int paramInt, ˏɪ paramˏɪ, ᔪ[] paramArrayOfᔪ1, ᔪ[] paramArrayOfᔪ2, int[] paramArrayOfint, String paramString, boolean paramBoolean) {
    ʿᵉ ʿᵉ1;
    (ʿᵉ1 = new ʿᵉ()).ᐨẏ(paramInt >>> 24).ˊ(paramArrayOfᔪ1.length);
    for (paramInt = 0; paramInt < paramArrayOfᔪ1.length; paramInt++)
      ʿᵉ1.ˊ((paramArrayOfᔪ1[paramInt]).ʻบ).ˊ((paramArrayOfᔪ2[paramInt]).ʻบ - (paramArrayOfᔪ1[paramInt]).ʻบ).ˊ(paramArrayOfint[paramInt]); 
    ˏɪ.ᐨẏ(paramˏɪ, ʿᵉ1);
    ʿᵉ1.ˊ(this.ᐨẏ.ՙᗮ(paramString)).ˊ(0);
    return paramBoolean ? (this.ՙᗮ = new ˊ((ˌх)this.ᐨẏ, true, ʿᵉ1, this.ՙᗮ)) : (this.ˍɫ = new ˊ((ˌх)this.ᐨẏ, true, ʿᵉ1, this.ˍɫ));
  }
  
  public final void ˊ(int paramInt, ᔪ paramᔪ) {
    if (this.ՙᗮ == null)
      this.ՙᗮ = (ˊ)new ʿᵉ(); 
    this.ﾞﮢ++;
    this.ՙᗮ.ˊ(paramᔪ.ʻบ);
    this.ՙᗮ.ˊ(paramInt);
  }
  
  public final void ʿᵉ(int paramInt1, int paramInt2) {
    ʿপ ʿপ1;
    ٴᐤ ٴᐤ;
    if (this.ˑܘ == 4) {
      ˊ[] arrayOfˊ = (ʿপ1 = this).ᐨẏ;
      while (arrayOfˊ != null) {
        "폌毬睙鴫묋鶸瓄얓Ŵꮯ예蚔핁筃瘗ᴯࣈ䒉".toCharArray()[15] = (char)("폌毬睙鴫묋鶸瓄얓Ŵꮯ예蚔핁筃瘗ᴯࣈ䒉".toCharArray()[15] ^ 0x6E10);
        String str = (((ˌᑦ)arrayOfˊ).ﹳיִ == null) ? ˏȓ$ᴵЃ.E("폌毬睙鴫묋鶸瓄얓Ŵꮯ예蚔핁筃瘗ᴯࣈ䒉".toCharArray(), (short)21431, (short)1, (short)4) : ((ˌᑦ)arrayOfˊ).ﹳיִ;
        int j = ՙ⁔.ᐨẏ((ˌх)ʿপ1.ᐨẏ, str);
        ᔪ ᔪ3;
        (ᔪ3 = ((ˌᑦ)arrayOfˊ).ʿᵉ.ᐨẏ()).ᴵʖ = (short)((ᔪ3 = ((ˌᑦ)arrayOfˊ).ʿᵉ.ᐨẏ()).ᴵʖ | 0x2);
        ᔪ ᔪ4 = ((ˌᑦ)arrayOfˊ).ᴵʖ.ᐨẏ();
        ᔪ ᔪ5 = ((ˌᑦ)arrayOfˊ).ﾞл.ᐨẏ();
        while (!zubdqvgt.G(ᔪ4, ᔪ5)) {
          ᔪ4.ᐨẏ = new ٴᐤ(j, ᔪ3, ᔪ4.ᐨẏ);
          ᔪ4 = ᔪ4.ՙᗮ;
        } 
        ˌᑦ ˌᑦ1 = ((ˌᑦ)arrayOfˊ).ᴵʖ;
      } 
      ٴᐤ ٴᐤ1;
      (ٴᐤ1 = ʿপ1.ʽ.ᐨẏ).ᐨẏ((ˌх)ʿপ1.ᐨẏ, ʿপ1.ʿλ, ʿপ1.ᴵʖ, ʿপ1.ˌپ);
      ٴᐤ1.ᐨẏ(ʿপ1);
      ᔪ ᔪ1;
      (ᔪ1 = ʿপ1.ʽ).ˍɫ = ᔪ.ʹﮃ;
      int i = 0;
      while (!zubdqvgt.G(ᔪ1, ᔪ.ʹﮃ)) {
        ᔪ ᔪ3 = ᔪ1;
        ᔪ1 = ᔪ1.ˍɫ;
        ᔪ3.ˍɫ = null;
        ᔪ3.ᴵʖ = (short)(ᔪ3.ᴵʖ | 0x8);
        int j;
        if ((j = ᔪ3.ᐨẏ.ʾܪ() + ᔪ3.ՙᗮ) > i)
          i = j; 
        for (ٴᐤ = ᔪ3.ᐨẏ; ٴᐤ != null; ٴᐤ = ٴᐤ.ˊ) {
          ᔪ ᔪ4 = ٴᐤ.ᐨẏ.ᐨẏ();
          boolean bool;
          if ((bool = ᔪ3.ᐨẏ.ᐨẏ((ˌх)ʿপ1.ᐨẏ, (ՙ⁔)ᔪ4.ᐨẏ, ٴᐤ.ᐨḶ)) && ᔪ4.ˍɫ == null) {
            ᔪ4.ˍɫ = ᔪ1;
            ᔪ1 = ᔪ4;
          } 
        } 
      } 
      for (ᔪ ᔪ2 = ʿপ1.ʽ; ᔪ2 != null; ᔪ2 = ᔪ2.ՙᗮ) {
        if ((ᔪ2.ᴵʖ & 0xA) == 10)
          ᔪ2.ᐨẏ.ᐨẏ(ʿপ1); 
        if ((ᔪ2.ᴵʖ & 0x8) == 0) {
          ᔪ ᔪ3 = ᔪ2.ՙᗮ;
          int j = ᔪ2.ʻบ;
          int k;
          if ((k = ((ᔪ3 == null) ? ((ʿᵉ)ʿপ1.ʹﮃ).ʹﮃ : ᔪ3.ʻบ) - 1) >= j) {
            for (int m = j; m < k; m++)
              ((ʿᵉ)ʿপ1.ʹﮃ).ˊ[m] = 0; 
            ((ʿᵉ)ʿপ1.ʹﮃ).ˊ[k] = -65;
            ʿপ1.ᐨẏ(j, 0, 1);
            "ࢹã鴭旍?ﵧųۼ楃鑊搿亖罪בֿ璘幐ٵ쯛䁞".toCharArray()[14] = (char)("ࢹã鴭旍?ﵧųۼ楃鑊搿亖罪בֿ璘幐ٵ쯛䁞".toCharArray()[14] ^ 0x7C5);
            ʿপ1.ᴵƚ[3] = ՙ⁔.ᐨẏ((ˌх)ʿপ1.ᐨẏ, ˏȓ$ᴵЃ.E("ࢹã鴭旍?ﵧųۼ楃鑊搿亖罪בֿ璘幐ٵ쯛䁞".toCharArray(), (short)12733, (short)1, (short)4));
            ʿপ1.ՙᗮ();
            ʿপ1.ᐨẏ = (ˊ[])ˌᑦ.ᐨẏ((ˌᑦ)ʿপ1.ᐨẏ, ᔪ2, ᔪ3);
            i = Math.max(i, 1);
          } 
        } 
      } 
      ʿপ1.ˑỲ = i;
      return;
    } 
    if (this.ˑܘ == 1) {
      ˊ[] arrayOfˊ = (ʿপ1 = this).ᐨẏ;
      while (arrayOfˊ != null) {
        ᔪ ᔪ2 = ((ˌᑦ)arrayOfˊ).ʿᵉ;
        ˌᑦ ˌᑦ2 = ((ˌᑦ)arrayOfˊ).ᴵʖ;
        ᔪ ᔪ3 = ((ˌᑦ)arrayOfˊ).ﾞл;
        while (!zubdqvgt.G(ˌᑦ2, ᔪ3)) {
          if ((((ᔪ)ˌᑦ2).ᴵʖ & 0x10) == 0) {
            ((ᔪ)ˌᑦ2).ᐨẏ = new ٴᐤ(2147483647, ᔪ2, ((ᔪ)ˌᑦ2).ᐨẏ);
          } else {
            ((ᔪ)ˌᑦ2).ᐨẏ.ˊ.ˊ = new ٴᐤ(2147483647, ᔪ2, ((ᔪ)ˌᑦ2).ᐨẏ.ˊ.ˊ);
          } 
          ᔪ ᔪ4 = ((ᔪ)ˌᑦ2).ՙᗮ;
        } 
        ˌᑦ ˌᑦ1 = ((ˌᑦ)arrayOfˊ).ᴵʖ;
      } 
      if (ʿপ1.ᴵʖ) {
        short s1 = 1;
        ʿপ1.ʽ.ᐨẏ((short)1);
        short s2;
        for (s2 = 1; s2 <= s1; s2 = (short)(s2 + 1)) {
          for (ᔪ ᔪ3 = ʿপ1.ʽ; ᔪ3 != null; ᔪ3 = ᔪ3.ՙᗮ) {
            ᔪ ᔪ4;
            if ((ᔪ3.ᴵʖ & 0x10) != 0 && ᔪ3.ˍɫ == s2 && (ᔪ4 = ᔪ3.ᐨẏ.ˊ.ᐨẏ).ˍɫ == null)
              ᔪ4.ᐨẏ(s1 = (short)(s1 + 1)); 
          } 
        } 
        for (ᔪ ᔪ2 = ʿপ1.ʽ; ᔪ2 != null; ᔪ2 = ᔪ2.ՙᗮ) {
          if ((ᔪ2.ᴵʖ & 0x10) != 0) {
            ᔪ ᔪ5;
            ᔪ ᔪ3 = ᔪ2;
            ᔪ ᔪ6 = ᔪ2.ᐨẏ.ˊ.ᐨẏ;
            ᔪ ᔪ4 = ᔪ6;
            short s = ᔪ.ʹﮃ;
            (ᔪ4 = ᔪ4).ˍɫ = ᔪ.ʹﮃ;
            while (!zubdqvgt.G(ᔪ4, ᔪ.ʹﮃ)) {
              ᔪ ᔪ7;
              ᔪ4 = (ᔪ7 = ᔪ4).ˍɫ;
              ᔪ7.ˍɫ = s;
              ᔪ5 = ᔪ7;
              if ((ᔪ7.ᴵʖ & 0x40) != 0 && ᔪ7.ˍɫ != ᔪ3.ˍɫ)
                ᔪ7.ᐨẏ = new ٴᐤ(ᔪ7.ʹﮃ, ᔪ3.ᐨẏ.ᐨẏ, ᔪ7.ᐨẏ); 
              ᔪ4 = ᔪ7.ᐨẏ(ᔪ4);
            } 
            while (!zubdqvgt.G(ᔪ5, ᔪ.ʹﮃ)) {
              ᔪ ᔪ7 = ᔪ5.ˍɫ;
              ᔪ5.ˍɫ = null;
              ᔪ5 = ᔪ7;
            } 
          } 
        } 
      } 
      ᔪ ᔪ1;
      (ᔪ1 = ʿপ1.ʽ).ˍɫ = ᔪ.ʹﮃ;
      int i = ʿপ1.ˑỲ;
      while (!zubdqvgt.G(ᔪ1, ᔪ.ʹﮃ)) {
        ᔪ ᔪ2 = ᔪ1;
        ᔪ1 = ᔪ1.ˍɫ;
        short s;
        int j;
        if ((j = (s = ᔪ2.ʿᵉ) + ᔪ2.ՙᗮ) > i)
          i = j; 
        ٴᐤ = ᔪ2.ᐨẏ;
        if ((ᔪ2.ᴵʖ & 0x10) != 0)
          ٴᐤ = ٴᐤ.ˊ; 
        while (ٴᐤ != null) {
          ᔪ ᔪ3;
          if ((ᔪ3 = ٴᐤ.ᐨẏ).ˍɫ == null) {
            ᔪ3.ʿᵉ = (short)((ٴᐤ.ᐨḶ == Integer.MAX_VALUE) ? 1 : (s + ٴᐤ.ᐨḶ));
            ᔪ3.ˍɫ = ᔪ1;
            ᔪ1 = ᔪ3;
          } 
          ٴᐤ = ٴᐤ.ˊ;
        } 
      } 
      ʿপ1.ˑỲ = i;
      return;
    } 
    if (this.ˑܘ == 2) {
      this.ˑỲ = this.ᴾ;
      return;
    } 
    this.ˑỲ = ʿপ1;
    this.ˌپ = ٴᐤ;
  }
  
  private void ﾞл() {
    ˊ[] arrayOfˊ = this.ᐨẏ;
    while (arrayOfˊ != null) {
      "轛퇕軫쌅閊썙矣㞵䳤挐麛腯ᣢ✦紒鮥羄".toCharArray()[12] = (char)("轛퇕軫쌅閊썙矣㞵䳤挐麛腯ᣢ✦紒鮥羄".toCharArray()[12] ^ 0x65A);
      String str = (((ˌᑦ)arrayOfˊ).ﹳיִ == null) ? ˉﻤ$ͺſ.v("轛퇕軫쌅閊썙矣㞵䳤挐麛腯ᣢ✦紒鮥羄".toCharArray(), (short)16173, 0, (short)4) : ((ˌᑦ)arrayOfˊ).ﹳיִ;
      int j = ՙ⁔.ᐨẏ((ˌх)this.ᐨẏ, str);
      ᔪ ᔪ3;
      (ᔪ3 = ((ˌᑦ)arrayOfˊ).ʿᵉ.ᐨẏ()).ᴵʖ = (short)((ᔪ3 = ((ˌᑦ)arrayOfˊ).ʿᵉ.ᐨẏ()).ᴵʖ | 0x2);
      ᔪ ᔪ4 = ((ˌᑦ)arrayOfˊ).ᴵʖ.ᐨẏ();
      ᔪ ᔪ5 = ((ˌᑦ)arrayOfˊ).ﾞл.ᐨẏ();
      while (!zubdqvgt.G(ᔪ4, ᔪ5)) {
        ᔪ4.ᐨẏ = new ٴᐤ(j, ᔪ3, ᔪ4.ᐨẏ);
        ᔪ4 = ᔪ4.ՙᗮ;
      } 
      ˌᑦ ˌᑦ1 = ((ˌᑦ)arrayOfˊ).ᴵʖ;
    } 
    ٴᐤ ٴᐤ;
    (ٴᐤ = this.ʽ.ᐨẏ).ᐨẏ((ˌх)this.ᐨẏ, this.ʿλ, this.ᴵʖ, this.ˌپ);
    ٴᐤ.ᐨẏ(this);
    ᔪ ᔪ1;
    (ᔪ1 = this.ʽ).ˍɫ = ᔪ.ʹﮃ;
    int i = 0;
    while (!zubdqvgt.G(ᔪ1, ᔪ.ʹﮃ)) {
      ᔪ ᔪ3 = ᔪ1;
      ᔪ1 = ᔪ1.ˍɫ;
      ᔪ3.ˍɫ = null;
      ᔪ3.ᴵʖ = (short)(ᔪ3.ᴵʖ | 0x8);
      int j;
      if ((j = ᔪ3.ᐨẏ.ʾܪ() + ᔪ3.ՙᗮ) > i)
        i = j; 
      for (ٴᐤ ٴᐤ1 = ᔪ3.ᐨẏ; ٴᐤ1 != null; ٴᐤ1 = ٴᐤ1.ˊ) {
        ᔪ ᔪ4 = ٴᐤ1.ᐨẏ.ᐨẏ();
        boolean bool;
        if ((bool = ᔪ3.ᐨẏ.ᐨẏ((ˌх)this.ᐨẏ, (ՙ⁔)ᔪ4.ᐨẏ, ٴᐤ1.ᐨḶ)) && ᔪ4.ˍɫ == null) {
          ᔪ4.ˍɫ = ᔪ1;
          ᔪ1 = ᔪ4;
        } 
      } 
    } 
    for (ᔪ ᔪ2 = this.ʽ; ᔪ2 != null; ᔪ2 = ᔪ2.ՙᗮ) {
      if ((ᔪ2.ᴵʖ & 0xA) == 10)
        ᔪ2.ᐨẏ.ᐨẏ(this); 
      if ((ᔪ2.ᴵʖ & 0x8) == 0) {
        ᔪ ᔪ3 = ᔪ2.ՙᗮ;
        int j = ᔪ2.ʻบ;
        int k;
        if ((k = ((ᔪ3 == null) ? ((ʿᵉ)this.ʹﮃ).ʹﮃ : ᔪ3.ʻบ) - 1) >= j) {
          for (int m = j; m < k; m++)
            ((ʿᵉ)this.ʹﮃ).ˊ[m] = 0; 
          ((ʿᵉ)this.ʹﮃ).ˊ[k] = -65;
          ᐨẏ(j, 0, 1);
          "㵭贼ᯀ㝒㘤鸺裎㱤㳰⒟읿硆砗?뛕숂ꇟ佺拽ѹ".toCharArray()[14] = (char)("㵭贼ᯀ㝒㘤鸺裎㱤㳰⒟읿硆砗?뛕숂ꇟ佺拽ѹ".toCharArray()[14] ^ 0x7847);
          this.ᴵƚ[3] = ՙ⁔.ᐨẏ((ˌх)this.ᐨẏ, ˉﻤ$ͺſ.v("㵭贼ᯀ㝒㘤鸺裎㱤㳰⒟읿硆砗?뛕숂ꇟ佺拽ѹ".toCharArray(), (short)30960, 3, (short)1));
          ՙᗮ();
          this.ᐨẏ = (ˊ[])ˌᑦ.ᐨẏ((ˌᑦ)this.ᐨẏ, ᔪ2, ᔪ3);
          i = Math.max(i, 1);
        } 
      } 
    } 
    this.ˑỲ = i;
  }
  
  private void ʿᵉ() {
    ˊ[] arrayOfˊ = this.ᐨẏ;
    while (arrayOfˊ != null) {
      ᔪ ᔪ2 = ((ˌᑦ)arrayOfˊ).ʿᵉ;
      ˌᑦ ˌᑦ2 = ((ˌᑦ)arrayOfˊ).ᴵʖ;
      ᔪ ᔪ3 = ((ˌᑦ)arrayOfˊ).ﾞл;
      while (!zubdqvgt.G(ˌᑦ2, ᔪ3)) {
        if ((((ᔪ)ˌᑦ2).ᴵʖ & 0x10) == 0) {
          ((ᔪ)ˌᑦ2).ᐨẏ = new ٴᐤ(2147483647, ᔪ2, ((ᔪ)ˌᑦ2).ᐨẏ);
        } else {
          ((ᔪ)ˌᑦ2).ᐨẏ.ˊ.ˊ = new ٴᐤ(2147483647, ᔪ2, ((ᔪ)ˌᑦ2).ᐨẏ.ˊ.ˊ);
        } 
        ᔪ ᔪ4 = ((ᔪ)ˌᑦ2).ՙᗮ;
      } 
      ˌᑦ ˌᑦ1 = ((ˌᑦ)arrayOfˊ).ᴵʖ;
    } 
    if (this.ᴵʖ) {
      short s1 = 1;
      this.ʽ.ᐨẏ((short)1);
      for (short s2 = 1; s2 <= s1; s2 = (short)(s2 + 1)) {
        for (ᔪ ᔪ3 = this.ʽ; ᔪ3 != null; ᔪ3 = ᔪ3.ՙᗮ) {
          ᔪ ᔪ4;
          if ((ᔪ3.ᴵʖ & 0x10) != 0 && ᔪ3.ˍɫ == s2 && (ᔪ4 = ᔪ3.ᐨẏ.ˊ.ᐨẏ).ˍɫ == null)
            ᔪ4.ᐨẏ(s1 = (short)(s1 + 1)); 
        } 
      } 
      for (ᔪ ᔪ2 = this.ʽ; ᔪ2 != null; ᔪ2 = ᔪ2.ՙᗮ) {
        if ((ᔪ2.ᴵʖ & 0x10) != 0) {
          ᔪ ᔪ3;
          (ᔪ3 = ᔪ2.ᐨẏ.ˊ.ᐨẏ).ᐨẏ(ᔪ2);
        } 
      } 
    } 
    ᔪ ᔪ1;
    (ᔪ1 = this.ʽ).ˍɫ = ᔪ.ʹﮃ;
    int i = this.ˑỲ;
    while (!zubdqvgt.G(ᔪ1, ᔪ.ʹﮃ)) {
      ᔪ ᔪ2 = ᔪ1;
      ᔪ1 = ᔪ1.ˍɫ;
      short s;
      int j;
      if ((j = (s = ᔪ2.ʿᵉ) + ᔪ2.ՙᗮ) > i)
        i = j; 
      ٴᐤ ٴᐤ = ᔪ2.ᐨẏ;
      if ((ᔪ2.ᴵʖ & 0x10) != 0)
        ٴᐤ = ٴᐤ.ˊ; 
      while (ٴᐤ != null) {
        if ((ᔪ2 = ٴᐤ.ᐨẏ).ˍɫ == null) {
          ᔪ2.ʿᵉ = (short)((ٴᐤ.ᐨḶ == Integer.MAX_VALUE) ? 1 : (s + ٴᐤ.ᐨḶ));
          ᔪ2.ˍɫ = ᔪ1;
          ᔪ1 = ᔪ2;
        } 
        ٴᐤ = ٴᐤ.ˊ;
      } 
    } 
    this.ˑỲ = i;
  }
  
  public final void ᐨẏ() {}
  
  private void ᴵʖ(int paramInt, ᔪ paramᔪ) {
    this.ᐨم.ᐨẏ = new ٴᐤ(paramInt, paramᔪ, this.ᐨم.ᐨẏ);
  }
  
  private void ʹﮃ() {
    if (this.ˑܘ == 4) {
      ᔪ ᔪ1;
      (ᔪ1 = new ᔪ()).ᐨẏ = (ٴᐤ)new ՙ⁔(ᔪ1);
      ᔪ1.ᐨẏ(((ʿᵉ)this.ʹﮃ).ˊ, (ʿᵉ)this.ʾܪ, ((ʿᵉ)this.ʹﮃ).ʹﮃ);
      this.ʾܪ.ՙᗮ = ᔪ1;
      this.ʾܪ = ᔪ1;
      this.ᐨم = null;
      return;
    } 
    if (this.ˑܘ == 1) {
      this.ᐨم.ՙᗮ = (short)this.ᴾ;
      this.ᐨم = null;
    } 
  }
  
  public final int ᐨẏ(int paramInt1, int paramInt2, int paramInt3) {
    int i = paramInt2 + 3 + paramInt3;
    if (this.ᴵƚ == null || this.ᴵƚ.length < i)
      this.ᴵƚ = new int[i]; 
    this.ᴵƚ[0] = paramInt1;
    this.ᴵƚ[1] = paramInt2;
    this.ᴵƚ[2] = paramInt3;
    return 3;
  }
  
  public final void ʹﮃ(int paramInt1, int paramInt2) {
    this.ᴵƚ[paramInt1] = paramInt2;
  }
  
  public final void ՙᗮ() {
    if (this.ٴӵ != null) {
      if (this.ʾܪ == null)
        this.ʾܪ = (ᔪ)new ʿᵉ(); 
      ˍɫ();
      this.ᓑ++;
    } 
    this.ٴӵ = this.ᴵƚ;
    this.ᴵƚ = null;
  }
  
  private void ˍɫ() {
    // Byte code:
    //   0: aload_0
    //   1: getfield ᴵƚ : [I
    //   4: iconst_1
    //   5: iaload
    //   6: istore_1
    //   7: aload_0
    //   8: getfield ᴵƚ : [I
    //   11: iconst_2
    //   12: iaload
    //   13: istore_2
    //   14: aload_0
    //   15: getfield ᐨẏ : Lyyds/sniarbtej/ˌх;
    //   18: dup
    //   19: astore_3
    //   20: getfield Ԇ : I
    //   23: bipush #50
    //   25: if_icmpge -> 76
    //   28: aload_0
    //   29: getfield ʾܪ : Lyyds/sniarbtej/ʿᵉ;
    //   32: aload_0
    //   33: getfield ᴵƚ : [I
    //   36: iconst_0
    //   37: iaload
    //   38: invokevirtual ˊ : (I)Lyyds/sniarbtej/ʿᵉ;
    //   41: iload_1
    //   42: invokevirtual ˊ : (I)Lyyds/sniarbtej/ʿᵉ;
    //   45: pop
    //   46: aload_0
    //   47: iconst_3
    //   48: iload_1
    //   49: iconst_3
    //   50: iadd
    //   51: invokespecial ՙᗮ : (II)V
    //   54: aload_0
    //   55: getfield ʾܪ : Lyyds/sniarbtej/ʿᵉ;
    //   58: iload_2
    //   59: invokevirtual ˊ : (I)Lyyds/sniarbtej/ʿᵉ;
    //   62: pop
    //   63: aload_0
    //   64: iload_1
    //   65: iconst_3
    //   66: iadd
    //   67: iload_1
    //   68: iconst_3
    //   69: iadd
    //   70: iload_2
    //   71: iadd
    //   72: invokespecial ՙᗮ : (II)V
    //   75: return
    //   76: aload_0
    //   77: getfield ᓑ : I
    //   80: ifne -> 92
    //   83: aload_0
    //   84: getfield ᴵƚ : [I
    //   87: iconst_0
    //   88: iaload
    //   89: goto -> 107
    //   92: aload_0
    //   93: getfield ᴵƚ : [I
    //   96: iconst_0
    //   97: iaload
    //   98: aload_0
    //   99: getfield ٴӵ : [I
    //   102: iconst_0
    //   103: iaload
    //   104: isub
    //   105: iconst_1
    //   106: isub
    //   107: istore_3
    //   108: aload_0
    //   109: getfield ٴӵ : [I
    //   112: iconst_1
    //   113: iaload
    //   114: istore #4
    //   116: iload_1
    //   117: iload #4
    //   119: isub
    //   120: istore #5
    //   122: sipush #255
    //   125: istore #6
    //   127: iload_2
    //   128: ifne -> 209
    //   131: iload #5
    //   133: tableswitch default -> 206, -3 -> 176, -2 -> 176, -1 -> 176, 0 -> 182, 1 -> 200, 2 -> 200, 3 -> 200
    //   176: sipush #248
    //   179: goto -> 233
    //   182: iload_3
    //   183: bipush #64
    //   185: if_icmpge -> 192
    //   188: iconst_0
    //   189: goto -> 195
    //   192: sipush #251
    //   195: istore #6
    //   197: goto -> 235
    //   200: sipush #252
    //   203: goto -> 233
    //   206: goto -> 235
    //   209: iload #5
    //   211: ifne -> 235
    //   214: iload_2
    //   215: iconst_1
    //   216: if_icmpne -> 235
    //   219: iload_3
    //   220: bipush #63
    //   222: if_icmpge -> 230
    //   225: bipush #64
    //   227: goto -> 233
    //   230: sipush #247
    //   233: istore #6
    //   235: iload #6
    //   237: sipush #255
    //   240: if_icmpeq -> 296
    //   243: iconst_3
    //   244: istore #7
    //   246: iconst_0
    //   247: istore #8
    //   249: iload #8
    //   251: iload #4
    //   253: if_icmpge -> 296
    //   256: iload #8
    //   258: iload_1
    //   259: if_icmpge -> 296
    //   262: aload_0
    //   263: getfield ᴵƚ : [I
    //   266: iload #7
    //   268: iaload
    //   269: aload_0
    //   270: getfield ٴӵ : [I
    //   273: iload #7
    //   275: iaload
    //   276: if_icmpeq -> 287
    //   279: sipush #255
    //   282: istore #6
    //   284: goto -> 296
    //   287: iinc #7, 1
    //   290: iinc #8, 1
    //   293: goto -> 249
    //   296: iload #6
    //   298: lookupswitch default -> 480, 0 -> 356, 64 -> 366, 247 -> 389, 248 -> 431, 251 -> 415, 252 -> 450
    //   356: aload_0
    //   357: getfield ʾܪ : Lyyds/sniarbtej/ʿᵉ;
    //   360: iload_3
    //   361: invokevirtual ᐨẏ : (I)Lyyds/sniarbtej/ʿᵉ;
    //   364: pop
    //   365: return
    //   366: aload_0
    //   367: getfield ʾܪ : Lyyds/sniarbtej/ʿᵉ;
    //   370: iload_3
    //   371: bipush #64
    //   373: iadd
    //   374: invokevirtual ᐨẏ : (I)Lyyds/sniarbtej/ʿᵉ;
    //   377: pop
    //   378: aload_0
    //   379: iload_1
    //   380: iconst_3
    //   381: iadd
    //   382: iload_1
    //   383: iconst_4
    //   384: iadd
    //   385: invokespecial ՙᗮ : (II)V
    //   388: return
    //   389: aload_0
    //   390: getfield ʾܪ : Lyyds/sniarbtej/ʿᵉ;
    //   393: sipush #247
    //   396: invokevirtual ᐨẏ : (I)Lyyds/sniarbtej/ʿᵉ;
    //   399: iload_3
    //   400: invokevirtual ˊ : (I)Lyyds/sniarbtej/ʿᵉ;
    //   403: pop
    //   404: aload_0
    //   405: iload_1
    //   406: iconst_3
    //   407: iadd
    //   408: iload_1
    //   409: iconst_4
    //   410: iadd
    //   411: invokespecial ՙᗮ : (II)V
    //   414: return
    //   415: aload_0
    //   416: getfield ʾܪ : Lyyds/sniarbtej/ʿᵉ;
    //   419: sipush #251
    //   422: invokevirtual ᐨẏ : (I)Lyyds/sniarbtej/ʿᵉ;
    //   425: iload_3
    //   426: invokevirtual ˊ : (I)Lyyds/sniarbtej/ʿᵉ;
    //   429: pop
    //   430: return
    //   431: aload_0
    //   432: getfield ʾܪ : Lyyds/sniarbtej/ʿᵉ;
    //   435: iload #5
    //   437: sipush #251
    //   440: iadd
    //   441: invokevirtual ᐨẏ : (I)Lyyds/sniarbtej/ʿᵉ;
    //   444: iload_3
    //   445: invokevirtual ˊ : (I)Lyyds/sniarbtej/ʿᵉ;
    //   448: pop
    //   449: return
    //   450: aload_0
    //   451: getfield ʾܪ : Lyyds/sniarbtej/ʿᵉ;
    //   454: iload #5
    //   456: sipush #251
    //   459: iadd
    //   460: invokevirtual ᐨẏ : (I)Lyyds/sniarbtej/ʿᵉ;
    //   463: iload_3
    //   464: invokevirtual ˊ : (I)Lyyds/sniarbtej/ʿᵉ;
    //   467: pop
    //   468: aload_0
    //   469: iload #4
    //   471: iconst_3
    //   472: iadd
    //   473: iload_1
    //   474: iconst_3
    //   475: iadd
    //   476: invokespecial ՙᗮ : (II)V
    //   479: return
    //   480: aload_0
    //   481: getfield ʾܪ : Lyyds/sniarbtej/ʿᵉ;
    //   484: sipush #255
    //   487: invokevirtual ᐨẏ : (I)Lyyds/sniarbtej/ʿᵉ;
    //   490: iload_3
    //   491: invokevirtual ˊ : (I)Lyyds/sniarbtej/ʿᵉ;
    //   494: iload_1
    //   495: invokevirtual ˊ : (I)Lyyds/sniarbtej/ʿᵉ;
    //   498: pop
    //   499: aload_0
    //   500: iconst_3
    //   501: iload_1
    //   502: iconst_3
    //   503: iadd
    //   504: invokespecial ՙᗮ : (II)V
    //   507: aload_0
    //   508: getfield ʾܪ : Lyyds/sniarbtej/ʿᵉ;
    //   511: iload_2
    //   512: invokevirtual ˊ : (I)Lyyds/sniarbtej/ʿᵉ;
    //   515: pop
    //   516: aload_0
    //   517: iload_1
    //   518: iconst_3
    //   519: iadd
    //   520: iload_1
    //   521: iconst_3
    //   522: iadd
    //   523: iload_2
    //   524: iadd
    //   525: invokespecial ՙᗮ : (II)V
    //   528: return
  }
  
  private void ՙᗮ(int paramInt1, int paramInt2) {
    for (paramInt1 = paramInt1; paramInt1 < paramInt2; paramInt1++)
      ՙ⁔.ᐨẏ((ˌх)this.ᐨẏ, this.ᴵƚ[paramInt1], (ʿᵉ)this.ʾܪ); 
  }
  
  private void ᴵʖ(Object paramObject) {
    if (paramObject instanceof Integer) {
      this.ʾܪ.ᐨẏ(((Integer)paramObject).intValue());
      return;
    } 
    if (paramObject instanceof String) {
      String str = (String)paramObject;
      this.ʾܪ.ᐨẏ(7).ˊ(((paramObject = this.ᐨẏ).ᐨẏ(7, str)).ͺᴲ);
      return;
    } 
    this.ʾܪ.ᐨẏ(8);
    ((ᔪ)paramObject).ˊ((ʿᵉ)this.ʾܪ);
  }
  
  final boolean ᐨẏ(ᐨم paramᐨم, boolean paramBoolean1, boolean paramBoolean2, int paramInt1, int paramInt2, int paramInt3) {
    ˊ[] arrayOfˊ;
    if (!zubdqvgt.G(paramᐨم, ((ˌх)(arrayOfˊ = this.ᐨẏ)).ᐨẏ) || paramInt1 != this.ɟ || paramInt2 != this.ﾞǰ || paramBoolean2 != (((this.ʿλ & 0x20000) != 0)))
      return false; 
    paramBoolean2 = (((ˌх)(arrayOfˊ = this.ᐨẏ)).Ԇ < 49 && (this.ʿλ & 0x1000) != 0);
    if (paramBoolean1 != paramBoolean2)
      return false; 
    if (paramInt3 == 0) {
      if (this.ٴῪ != 0)
        return false; 
    } else if (paramᐨم.ᴵʖ(paramInt3) == this.ٴῪ) {
      int i = paramInt3 + 2;
      for (paramBoolean2 = false; paramBoolean2 < this.ٴῪ; paramBoolean2++) {
        if (paramᐨم.ᴵʖ(i) != this.ͺо[paramBoolean2])
          return false; 
        i += 2;
      } 
    } 
    return true;
  }
  
  final void ˍɫ(int paramInt1, int paramInt2) {
    this.ᴵ氵 = paramInt1 + 6;
    this.ᵊ = paramInt2 - 6;
  }
  
  final int ᴵƚ() {
    // Byte code:
    //   0: aload_0
    //   1: getfield ᴵ氵 : I
    //   4: ifeq -> 15
    //   7: bipush #6
    //   9: aload_0
    //   10: getfield ᵊ : I
    //   13: iadd
    //   14: ireturn
    //   15: bipush #8
    //   17: istore_1
    //   18: aload_0
    //   19: getfield ʹﮃ : Lyyds/sniarbtej/ʿᵉ;
    //   22: getfield ʹﮃ : I
    //   25: ifle -> 523
    //   28: aload_0
    //   29: getfield ʹﮃ : Lyyds/sniarbtej/ʿᵉ;
    //   32: getfield ʹﮃ : I
    //   35: ldc_w 65535
    //   38: if_icmple -> 73
    //   41: new yyds/sniarbtej/ʿλ
    //   44: dup
    //   45: aload_0
    //   46: getfield ᐨẏ : Lyyds/sniarbtej/ˌх;
    //   49: dup
    //   50: astore_2
    //   51: getfield ˊ : Ljava/lang/String;
    //   54: aload_0
    //   55: getfield name : Ljava/lang/String;
    //   58: aload_0
    //   59: getfield ᴵʖ : Ljava/lang/String;
    //   62: aload_0
    //   63: getfield ʹﮃ : Lyyds/sniarbtej/ʿᵉ;
    //   66: getfield ʹﮃ : I
    //   69: invokespecial <init> : (Ljava/lang/String;Ljava/lang/String;Ljava/lang/String;I)V
    //   72: athrow
    //   73: aload_0
    //   74: getfield ᐨẏ : Lyyds/sniarbtej/ˌх;
    //   77: ldc_w 'Υｅ陔࢏'
    //   80: invokevirtual toCharArray : ()[C
    //   83: dup
    //   84: dup
    //   85: iconst_2
    //   86: dup_x1
    //   87: caload
    //   88: sipush #2614
    //   91: ixor
    //   92: i2c
    //   93: castore
    //   94: sipush #27648
    //   97: iconst_0
    //   98: iconst_1
    //   99: invokestatic J : (Ljava/lang/Object;SSB)Ljava/lang/String;
    //   102: invokevirtual ՙᗮ : (Ljava/lang/String;)I
    //   105: pop
    //   106: bipush #8
    //   108: bipush #16
    //   110: aload_0
    //   111: getfield ʹﮃ : Lyyds/sniarbtej/ʿᵉ;
    //   114: getfield ʹﮃ : I
    //   117: iadd
    //   118: aload_0
    //   119: getfield ᐨẏ : Lyyds/sniarbtej/ˌᑦ;
    //   122: invokestatic ˊ : (Lyyds/sniarbtej/ˌᑦ;)I
    //   125: iadd
    //   126: iadd
    //   127: istore_1
    //   128: aload_0
    //   129: getfield ʾܪ : Lyyds/sniarbtej/ʿᵉ;
    //   132: ifnull -> 233
    //   135: aload_0
    //   136: getfield ᐨẏ : Lyyds/sniarbtej/ˌх;
    //   139: dup
    //   140: astore_2
    //   141: getfield Ԇ : I
    //   144: bipush #50
    //   146: if_icmplt -> 153
    //   149: iconst_1
    //   150: goto -> 154
    //   153: iconst_0
    //   154: istore_2
    //   155: aload_0
    //   156: getfield ᐨẏ : Lyyds/sniarbtej/ˌх;
    //   159: iload_2
    //   160: ifeq -> 191
    //   163: ldc_w '幩㺂侈ﴜ䄕튵㚗鑉䑦笍'
    //   166: invokevirtual toCharArray : ()[C
    //   169: dup
    //   170: dup
    //   171: iconst_0
    //   172: dup_x1
    //   173: caload
    //   174: sipush #32551
    //   177: ixor
    //   178: i2c
    //   179: castore
    //   180: sipush #18617
    //   183: iconst_3
    //   184: iconst_3
    //   185: invokestatic J : (Ljava/lang/Object;SSB)Ljava/lang/String;
    //   188: goto -> 216
    //   191: ldc_w '벆洯滥뷐?樵ᩔ⯫'
    //   194: invokevirtual toCharArray : ()[C
    //   197: dup
    //   198: dup
    //   199: iconst_2
    //   200: dup_x1
    //   201: caload
    //   202: sipush #32705
    //   205: ixor
    //   206: i2c
    //   207: castore
    //   208: sipush #7639
    //   211: iconst_3
    //   212: iconst_3
    //   213: invokestatic J : (Ljava/lang/Object;SSB)Ljava/lang/String;
    //   216: invokevirtual ՙᗮ : (Ljava/lang/String;)I
    //   219: pop
    //   220: iload_1
    //   221: bipush #8
    //   223: aload_0
    //   224: getfield ʾܪ : Lyyds/sniarbtej/ʿᵉ;
    //   227: getfield ʹﮃ : I
    //   230: iadd
    //   231: iadd
    //   232: istore_1
    //   233: aload_0
    //   234: getfield ՙᗮ : Lyyds/sniarbtej/ʿᵉ;
    //   237: ifnull -> 286
    //   240: aload_0
    //   241: getfield ᐨẏ : Lyyds/sniarbtej/ˌх;
    //   244: ldc_w '왤鰄?맆Ⳓ䓖띁틚䯣聇⌒﷾䤩댞㏥ღ'
    //   247: invokevirtual toCharArray : ()[C
    //   250: dup
    //   251: dup
    //   252: iconst_4
    //   253: dup_x1
    //   254: caload
    //   255: sipush #20198
    //   258: ixor
    //   259: i2c
    //   260: castore
    //   261: sipush #1096
    //   264: iconst_2
    //   265: iconst_2
    //   266: invokestatic J : (Ljava/lang/Object;SSB)Ljava/lang/String;
    //   269: invokevirtual ՙᗮ : (Ljava/lang/String;)I
    //   272: pop
    //   273: iload_1
    //   274: bipush #8
    //   276: aload_0
    //   277: getfield ՙᗮ : Lyyds/sniarbtej/ʿᵉ;
    //   280: getfield ʹﮃ : I
    //   283: iadd
    //   284: iadd
    //   285: istore_1
    //   286: aload_0
    //   287: getfield ˍɫ : Lyyds/sniarbtej/ʿᵉ;
    //   290: ifnull -> 340
    //   293: aload_0
    //   294: getfield ᐨẏ : Lyyds/sniarbtej/ˌх;
    //   297: ldc_w '諟翦Ή㋓㫾휜珥꼲ꌘ⃓⋪땏午?應ꏗ☖㺄曖'
    //   300: invokevirtual toCharArray : ()[C
    //   303: dup
    //   304: dup
    //   305: bipush #8
    //   307: dup_x1
    //   308: caload
    //   309: sipush #4922
    //   312: ixor
    //   313: i2c
    //   314: castore
    //   315: sipush #17210
    //   318: iconst_2
    //   319: iconst_2
    //   320: invokestatic J : (Ljava/lang/Object;SSB)Ljava/lang/String;
    //   323: invokevirtual ՙᗮ : (Ljava/lang/String;)I
    //   326: pop
    //   327: iload_1
    //   328: bipush #8
    //   330: aload_0
    //   331: getfield ˍɫ : Lyyds/sniarbtej/ʿᵉ;
    //   334: getfield ʹﮃ : I
    //   337: iadd
    //   338: iadd
    //   339: istore_1
    //   340: aload_0
    //   341: getfield ʽ : Lyyds/sniarbtej/ʿᵉ;
    //   344: ifnull -> 394
    //   347: aload_0
    //   348: getfield ᐨẏ : Lyyds/sniarbtej/ˌх;
    //   351: ldc_w 'ŗ힧珫럅꤅䳣飄땠͍䡃ⲿ腳孬୨쎵酡⶝ⵠ쾁䙬೑䔆'
    //   354: invokevirtual toCharArray : ()[C
    //   357: dup
    //   358: dup
    //   359: bipush #10
    //   361: dup_x1
    //   362: caload
    //   363: sipush #3225
    //   366: ixor
    //   367: i2c
    //   368: castore
    //   369: sipush #22598
    //   372: iconst_4
    //   373: iconst_5
    //   374: invokestatic J : (Ljava/lang/Object;SSB)Ljava/lang/String;
    //   377: invokevirtual ՙᗮ : (Ljava/lang/String;)I
    //   380: pop
    //   381: iload_1
    //   382: bipush #8
    //   384: aload_0
    //   385: getfield ʽ : Lyyds/sniarbtej/ʿᵉ;
    //   388: getfield ʹﮃ : I
    //   391: iadd
    //   392: iadd
    //   393: istore_1
    //   394: aload_0
    //   395: getfield ՙᗮ : Lyyds/sniarbtej/ˊ;
    //   398: ifnull -> 437
    //   401: iload_1
    //   402: aload_0
    //   403: getfield ՙᗮ : Lyyds/sniarbtej/ˊ;
    //   406: ldc_w 'ȏᇧꦆ㼽췳䀋ㆌⓞꢐ᛼㷬簾௧඿吞臶ഏꣴ꫉蠩ڟꤌ㦓롓ੈ㨑?ꔣ昚'
    //   409: invokevirtual toCharArray : ()[C
    //   412: dup
    //   413: dup
    //   414: bipush #12
    //   416: dup_x1
    //   417: caload
    //   418: sipush #14087
    //   421: ixor
    //   422: i2c
    //   423: castore
    //   424: sipush #20143
    //   427: iconst_1
    //   428: iconst_2
    //   429: invokestatic J : (Ljava/lang/Object;SSB)Ljava/lang/String;
    //   432: invokevirtual ᐨẏ : (Ljava/lang/String;)I
    //   435: iadd
    //   436: istore_1
    //   437: aload_0
    //   438: getfield ˍɫ : Lyyds/sniarbtej/ˊ;
    //   441: ifnull -> 480
    //   444: iload_1
    //   445: aload_0
    //   446: getfield ˍɫ : Lyyds/sniarbtej/ˊ;
    //   449: ldc_w 'ෂ襑値࿝蓤੭꧹錂걓指틹嘺僟踊俘⸧镣桞힀౜Ᾱ愥컨䦖倜洃∆녊৹㢬䂏'
    //   452: invokevirtual toCharArray : ()[C
    //   455: dup
    //   456: dup
    //   457: bipush #14
    //   459: dup_x1
    //   460: caload
    //   461: sipush #9918
    //   464: ixor
    //   465: i2c
    //   466: castore
    //   467: sipush #31954
    //   470: iconst_2
    //   471: iconst_5
    //   472: invokestatic J : (Ljava/lang/Object;SSB)Ljava/lang/String;
    //   475: invokevirtual ᐨẏ : (Ljava/lang/String;)I
    //   478: iadd
    //   479: istore_1
    //   480: aload_0
    //   481: getfield ᴵʖ : Lyyds/sniarbtej/ᴵʖ;
    //   484: ifnull -> 523
    //   487: iload_1
    //   488: aload_0
    //   489: getfield ᴵʖ : Lyyds/sniarbtej/ᴵʖ;
    //   492: aload_0
    //   493: getfield ᐨẏ : Lyyds/sniarbtej/ˌх;
    //   496: aload_0
    //   497: getfield ʹﮃ : Lyyds/sniarbtej/ʿᵉ;
    //   500: getfield ˊ : [B
    //   503: aload_0
    //   504: getfield ʹﮃ : Lyyds/sniarbtej/ʿᵉ;
    //   507: getfield ʹﮃ : I
    //   510: aload_0
    //   511: getfield ˑỲ : I
    //   514: aload_0
    //   515: getfield ˌپ : I
    //   518: invokevirtual ᐨẏ : (Lyyds/sniarbtej/ˌх;[BIII)I
    //   521: iadd
    //   522: istore_1
    //   523: aload_0
    //   524: getfield ٴῪ : I
    //   527: ifle -> 576
    //   530: aload_0
    //   531: getfield ᐨẏ : Lyyds/sniarbtej/ˌх;
    //   534: ldc_w 'ܓꨙ᦯ữ婯粬퇿蠠穡'
    //   537: invokevirtual toCharArray : ()[C
    //   540: dup
    //   541: dup
    //   542: bipush #8
    //   544: dup_x1
    //   545: caload
    //   546: sipush #1806
    //   549: ixor
    //   550: i2c
    //   551: castore
    //   552: sipush #27954
    //   555: iconst_0
    //   556: iconst_0
    //   557: invokestatic J : (Ljava/lang/Object;SSB)Ljava/lang/String;
    //   560: invokevirtual ՙᗮ : (Ljava/lang/String;)I
    //   563: pop
    //   564: iload_1
    //   565: bipush #8
    //   567: iconst_2
    //   568: aload_0
    //   569: getfield ٴῪ : I
    //   572: imul
    //   573: iadd
    //   574: iadd
    //   575: istore_1
    //   576: iload_1
    //   577: aload_0
    //   578: getfield ᐨẏ : Lyyds/sniarbtej/ˌх;
    //   581: aload_0
    //   582: getfield ʿλ : I
    //   585: aload_0
    //   586: getfield ﾞǰ : I
    //   589: invokestatic ᐨẏ : (Lyyds/sniarbtej/ˌх;II)I
    //   592: iadd
    //   593: dup
    //   594: istore_1
    //   595: aload_0
    //   596: getfield ᴵʖ : Lyyds/sniarbtej/ˊ;
    //   599: aload_0
    //   600: getfield ﾞл : Lyyds/sniarbtej/ˊ;
    //   603: aload_0
    //   604: getfield ʿᵉ : Lyyds/sniarbtej/ˊ;
    //   607: aload_0
    //   608: getfield ʹﮃ : Lyyds/sniarbtej/ˊ;
    //   611: invokestatic ᐨẏ : (Lyyds/sniarbtej/ˊ;Lyyds/sniarbtej/ˊ;Lyyds/sniarbtej/ˊ;Lyyds/sniarbtej/ˊ;)I
    //   614: iadd
    //   615: istore_1
    //   616: aload_0
    //   617: getfield ᐨẏ : [Lyyds/sniarbtej/ˊ;
    //   620: ifnull -> 678
    //   623: iload_1
    //   624: ldc_w '㷼葿肮疄㥝⸤ⲕ곽쬏椽㖺ⅽ䲘脹쾋┼૙肐ꋒ꜑?搷큇͟慠圯쇤뒢ᵁ趌?墔'
    //   627: invokevirtual toCharArray : ()[C
    //   630: dup
    //   631: dup
    //   632: bipush #31
    //   634: dup_x1
    //   635: caload
    //   636: sipush #3804
    //   639: ixor
    //   640: i2c
    //   641: castore
    //   642: sipush #25225
    //   645: iconst_1
    //   646: iconst_1
    //   647: invokestatic J : (Ljava/lang/Object;SSB)Ljava/lang/String;
    //   650: aload_0
    //   651: getfield ᐨẏ : [Lyyds/sniarbtej/ˊ;
    //   654: aload_0
    //   655: getfield শ : I
    //   658: ifne -> 669
    //   661: aload_0
    //   662: getfield ᐨẏ : [Lyyds/sniarbtej/ˊ;
    //   665: arraylength
    //   666: goto -> 673
    //   669: aload_0
    //   670: getfield শ : I
    //   673: invokestatic ᐨẏ : (Ljava/lang/String;[Lyyds/sniarbtej/ˊ;I)I
    //   676: iadd
    //   677: istore_1
    //   678: aload_0
    //   679: getfield ˊ : [Lyyds/sniarbtej/ˊ;
    //   682: ifnull -> 740
    //   685: iload_1
    //   686: ldc_w '睗嬠鈡圽偶➅鄉㰨㕏级?䑃ꑏẘ힋膐㬱虲ﱝ討씵韛蕭職븀藯祖㙓暡訰漒㏳션品'
    //   689: invokevirtual toCharArray : ()[C
    //   692: dup
    //   693: dup
    //   694: bipush #28
    //   696: dup_x1
    //   697: caload
    //   698: sipush #21174
    //   701: ixor
    //   702: i2c
    //   703: castore
    //   704: sipush #16507
    //   707: iconst_5
    //   708: iconst_5
    //   709: invokestatic J : (Ljava/lang/Object;SSB)Ljava/lang/String;
    //   712: aload_0
    //   713: getfield ˊ : [Lyyds/sniarbtej/ˊ;
    //   716: aload_0
    //   717: getfield ˋᴷ : I
    //   720: ifne -> 731
    //   723: aload_0
    //   724: getfield ˊ : [Lyyds/sniarbtej/ˊ;
    //   727: arraylength
    //   728: goto -> 735
    //   731: aload_0
    //   732: getfield ˋᴷ : I
    //   735: invokestatic ᐨẏ : (Ljava/lang/String;[Lyyds/sniarbtej/ˊ;I)I
    //   738: iadd
    //   739: istore_1
    //   740: aload_0
    //   741: getfield ᐨم : Lyyds/sniarbtej/ʿᵉ;
    //   744: ifnull -> 794
    //   747: aload_0
    //   748: getfield ᐨẏ : Lyyds/sniarbtej/ˌх;
    //   751: ldc_w '缽孹记䔁㲕꞊쯴鞼닋黛ꏠꠖ짮㔌ව'
    //   754: invokevirtual toCharArray : ()[C
    //   757: dup
    //   758: dup
    //   759: bipush #9
    //   761: dup_x1
    //   762: caload
    //   763: sipush #20750
    //   766: ixor
    //   767: i2c
    //   768: castore
    //   769: sipush #7794
    //   772: iconst_2
    //   773: iconst_0
    //   774: invokestatic J : (Ljava/lang/Object;SSB)Ljava/lang/String;
    //   777: invokevirtual ՙᗮ : (Ljava/lang/String;)I
    //   780: pop
    //   781: iload_1
    //   782: bipush #6
    //   784: aload_0
    //   785: getfield ᐨم : Lyyds/sniarbtej/ʿᵉ;
    //   788: getfield ʹﮃ : I
    //   791: iadd
    //   792: iadd
    //   793: istore_1
    //   794: aload_0
    //   795: getfield ʾ : Lyyds/sniarbtej/ʿᵉ;
    //   798: ifnull -> 848
    //   801: aload_0
    //   802: getfield ᐨẏ : Lyyds/sniarbtej/ˌх;
    //   805: ldc_w '鋔ꘜ宎庄暾엙욦席漣䤢䩙뫝穛઻濁'
    //   808: invokevirtual toCharArray : ()[C
    //   811: dup
    //   812: dup
    //   813: bipush #9
    //   815: dup_x1
    //   816: caload
    //   817: sipush #30331
    //   820: ixor
    //   821: i2c
    //   822: castore
    //   823: sipush #16253
    //   826: iconst_5
    //   827: iconst_0
    //   828: invokestatic J : (Ljava/lang/Object;SSB)Ljava/lang/String;
    //   831: invokevirtual ՙᗮ : (Ljava/lang/String;)I
    //   834: pop
    //   835: iload_1
    //   836: bipush #7
    //   838: aload_0
    //   839: getfield ʾ : Lyyds/sniarbtej/ʿᵉ;
    //   842: getfield ʹﮃ : I
    //   845: iadd
    //   846: iadd
    //   847: istore_1
    //   848: aload_0
    //   849: getfield ˊ : Lyyds/sniarbtej/ᴵʖ;
    //   852: ifnull -> 869
    //   855: iload_1
    //   856: aload_0
    //   857: getfield ˊ : Lyyds/sniarbtej/ᴵʖ;
    //   860: aload_0
    //   861: getfield ᐨẏ : Lyyds/sniarbtej/ˌх;
    //   864: invokevirtual ᐨẏ : (Lyyds/sniarbtej/ˌх;)I
    //   867: iadd
    //   868: istore_1
    //   869: iload_1
    //   870: ireturn
  }
  
  final void ᴵʖ(ʿᵉ paramʿᵉ) {
    // Byte code:
    //   0: aload_0
    //   1: getfield ᐨẏ : Lyyds/sniarbtej/ˌх;
    //   4: dup
    //   5: astore_2
    //   6: getfield Ԇ : I
    //   9: bipush #49
    //   11: if_icmpge -> 18
    //   14: iconst_1
    //   15: goto -> 19
    //   18: iconst_0
    //   19: dup
    //   20: istore_2
    //   21: ifeq -> 30
    //   24: sipush #4096
    //   27: goto -> 31
    //   30: iconst_0
    //   31: istore_3
    //   32: aload_1
    //   33: aload_0
    //   34: getfield ʿλ : I
    //   37: iload_3
    //   38: iconst_m1
    //   39: ixor
    //   40: iand
    //   41: invokevirtual ˊ : (I)Lyyds/sniarbtej/ʿᵉ;
    //   44: aload_0
    //   45: getfield ᐝт : I
    //   48: invokevirtual ˊ : (I)Lyyds/sniarbtej/ʿᵉ;
    //   51: aload_0
    //   52: getfield ɟ : I
    //   55: invokevirtual ˊ : (I)Lyyds/sniarbtej/ʿᵉ;
    //   58: pop
    //   59: aload_0
    //   60: getfield ᴵ氵 : I
    //   63: ifeq -> 92
    //   66: aload_1
    //   67: aload_0
    //   68: getfield ᐨẏ : Lyyds/sniarbtej/ˌх;
    //   71: dup
    //   72: astore_2
    //   73: getfield ᐨẏ : Lyyds/sniarbtej/ᐨم;
    //   76: getfield ﾞл : [B
    //   79: aload_0
    //   80: getfield ᴵ氵 : I
    //   83: aload_0
    //   84: getfield ᵊ : I
    //   87: invokevirtual ᐨẏ : ([BII)Lyyds/sniarbtej/ʿᵉ;
    //   90: pop
    //   91: return
    //   92: iconst_0
    //   93: istore_3
    //   94: aload_0
    //   95: getfield ʹﮃ : Lyyds/sniarbtej/ʿᵉ;
    //   98: getfield ʹﮃ : I
    //   101: ifle -> 107
    //   104: iinc #3, 1
    //   107: aload_0
    //   108: getfield ٴῪ : I
    //   111: ifle -> 117
    //   114: iinc #3, 1
    //   117: aload_0
    //   118: getfield ʿλ : I
    //   121: sipush #4096
    //   124: iand
    //   125: ifeq -> 135
    //   128: iload_2
    //   129: ifeq -> 135
    //   132: iinc #3, 1
    //   135: aload_0
    //   136: getfield ﾞǰ : I
    //   139: ifeq -> 145
    //   142: iinc #3, 1
    //   145: aload_0
    //   146: getfield ʿλ : I
    //   149: ldc_w 131072
    //   152: iand
    //   153: ifeq -> 159
    //   156: iinc #3, 1
    //   159: aload_0
    //   160: getfield ᴵʖ : Lyyds/sniarbtej/ˊ;
    //   163: ifnull -> 169
    //   166: iinc #3, 1
    //   169: aload_0
    //   170: getfield ﾞл : Lyyds/sniarbtej/ˊ;
    //   173: ifnull -> 179
    //   176: iinc #3, 1
    //   179: aload_0
    //   180: getfield ᐨẏ : [Lyyds/sniarbtej/ˊ;
    //   183: ifnull -> 189
    //   186: iinc #3, 1
    //   189: aload_0
    //   190: getfield ˊ : [Lyyds/sniarbtej/ˊ;
    //   193: ifnull -> 199
    //   196: iinc #3, 1
    //   199: aload_0
    //   200: getfield ʿᵉ : Lyyds/sniarbtej/ˊ;
    //   203: ifnull -> 209
    //   206: iinc #3, 1
    //   209: aload_0
    //   210: getfield ʹﮃ : Lyyds/sniarbtej/ˊ;
    //   213: ifnull -> 219
    //   216: iinc #3, 1
    //   219: aload_0
    //   220: getfield ᐨم : Lyyds/sniarbtej/ʿᵉ;
    //   223: ifnull -> 229
    //   226: iinc #3, 1
    //   229: aload_0
    //   230: getfield ʾ : Lyyds/sniarbtej/ʿᵉ;
    //   233: ifnull -> 239
    //   236: iinc #3, 1
    //   239: aload_0
    //   240: getfield ˊ : Lyyds/sniarbtej/ᴵʖ;
    //   243: ifnull -> 256
    //   246: iload_3
    //   247: aload_0
    //   248: getfield ˊ : Lyyds/sniarbtej/ᴵʖ;
    //   251: invokevirtual ᐨẏ : ()I
    //   254: iadd
    //   255: istore_3
    //   256: aload_1
    //   257: iload_3
    //   258: invokevirtual ˊ : (I)Lyyds/sniarbtej/ʿᵉ;
    //   261: pop
    //   262: aload_0
    //   263: getfield ʹﮃ : Lyyds/sniarbtej/ʿᵉ;
    //   266: getfield ʹﮃ : I
    //   269: ifle -> 1142
    //   272: bipush #10
    //   274: aload_0
    //   275: getfield ʹﮃ : Lyyds/sniarbtej/ʿᵉ;
    //   278: getfield ʹﮃ : I
    //   281: iadd
    //   282: aload_0
    //   283: getfield ᐨẏ : Lyyds/sniarbtej/ˌᑦ;
    //   286: invokestatic ˊ : (Lyyds/sniarbtej/ˌᑦ;)I
    //   289: iadd
    //   290: istore_2
    //   291: iconst_0
    //   292: istore_3
    //   293: aload_0
    //   294: getfield ʾܪ : Lyyds/sniarbtej/ʿᵉ;
    //   297: ifnull -> 316
    //   300: iload_2
    //   301: bipush #8
    //   303: aload_0
    //   304: getfield ʾܪ : Lyyds/sniarbtej/ʿᵉ;
    //   307: getfield ʹﮃ : I
    //   310: iadd
    //   311: iadd
    //   312: istore_2
    //   313: iinc #3, 1
    //   316: aload_0
    //   317: getfield ՙᗮ : Lyyds/sniarbtej/ʿᵉ;
    //   320: ifnull -> 339
    //   323: iload_2
    //   324: bipush #8
    //   326: aload_0
    //   327: getfield ՙᗮ : Lyyds/sniarbtej/ʿᵉ;
    //   330: getfield ʹﮃ : I
    //   333: iadd
    //   334: iadd
    //   335: istore_2
    //   336: iinc #3, 1
    //   339: aload_0
    //   340: getfield ˍɫ : Lyyds/sniarbtej/ʿᵉ;
    //   343: ifnull -> 362
    //   346: iload_2
    //   347: bipush #8
    //   349: aload_0
    //   350: getfield ˍɫ : Lyyds/sniarbtej/ʿᵉ;
    //   353: getfield ʹﮃ : I
    //   356: iadd
    //   357: iadd
    //   358: istore_2
    //   359: iinc #3, 1
    //   362: aload_0
    //   363: getfield ʽ : Lyyds/sniarbtej/ʿᵉ;
    //   366: ifnull -> 385
    //   369: iload_2
    //   370: bipush #8
    //   372: aload_0
    //   373: getfield ʽ : Lyyds/sniarbtej/ʿᵉ;
    //   376: getfield ʹﮃ : I
    //   379: iadd
    //   380: iadd
    //   381: istore_2
    //   382: iinc #3, 1
    //   385: aload_0
    //   386: getfield ՙᗮ : Lyyds/sniarbtej/ˊ;
    //   389: ifnull -> 431
    //   392: iload_2
    //   393: aload_0
    //   394: getfield ՙᗮ : Lyyds/sniarbtej/ˊ;
    //   397: ldc_w '淙⇵ꔰ뗦嘢黦❑ҶB徂ꎓꥊ?雠⣪嬵쎭ᴦ縊핔碆圌苉摴ꍈ顿ıଂ啚'
    //   400: invokevirtual toCharArray : ()[C
    //   403: dup
    //   404: dup
    //   405: bipush #21
    //   407: dup_x1
    //   408: caload
    //   409: sipush #25337
    //   412: ixor
    //   413: i2c
    //   414: castore
    //   415: sipush #3989
    //   418: iconst_1
    //   419: iconst_4
    //   420: invokestatic W : (Ljava/lang/Object;SBS)Ljava/lang/String;
    //   423: invokevirtual ᐨẏ : (Ljava/lang/String;)I
    //   426: iadd
    //   427: istore_2
    //   428: iinc #3, 1
    //   431: aload_0
    //   432: getfield ˍɫ : Lyyds/sniarbtej/ˊ;
    //   435: ifnull -> 477
    //   438: iload_2
    //   439: aload_0
    //   440: getfield ˍɫ : Lyyds/sniarbtej/ˊ;
    //   443: ldc_w '匨殛뺮챀딘㇬Ą岘ퟑṀ輛哒ඦㄶ?腂욫ꯑΈ뛋跏埋잵ﶞ瘤犭䵊苬髒扎㻭'
    //   446: invokevirtual toCharArray : ()[C
    //   449: dup
    //   450: dup
    //   451: bipush #20
    //   453: dup_x1
    //   454: caload
    //   455: sipush #10241
    //   458: ixor
    //   459: i2c
    //   460: castore
    //   461: sipush #17633
    //   464: iconst_1
    //   465: iconst_2
    //   466: invokestatic W : (Ljava/lang/Object;SBS)Ljava/lang/String;
    //   469: invokevirtual ᐨẏ : (Ljava/lang/String;)I
    //   472: iadd
    //   473: istore_2
    //   474: iinc #3, 1
    //   477: aload_0
    //   478: getfield ᴵʖ : Lyyds/sniarbtej/ᴵʖ;
    //   481: ifnull -> 530
    //   484: iload_2
    //   485: aload_0
    //   486: getfield ᴵʖ : Lyyds/sniarbtej/ᴵʖ;
    //   489: aload_0
    //   490: getfield ᐨẏ : Lyyds/sniarbtej/ˌх;
    //   493: aload_0
    //   494: getfield ʹﮃ : Lyyds/sniarbtej/ʿᵉ;
    //   497: getfield ˊ : [B
    //   500: aload_0
    //   501: getfield ʹﮃ : Lyyds/sniarbtej/ʿᵉ;
    //   504: getfield ʹﮃ : I
    //   507: aload_0
    //   508: getfield ˑỲ : I
    //   511: aload_0
    //   512: getfield ˌپ : I
    //   515: invokevirtual ᐨẏ : (Lyyds/sniarbtej/ˌх;[BIII)I
    //   518: iadd
    //   519: istore_2
    //   520: iload_3
    //   521: aload_0
    //   522: getfield ᴵʖ : Lyyds/sniarbtej/ᴵʖ;
    //   525: invokevirtual ᐨẏ : ()I
    //   528: iadd
    //   529: istore_3
    //   530: aload_1
    //   531: aload_0
    //   532: getfield ᐨẏ : Lyyds/sniarbtej/ˌх;
    //   535: ldc_w 'ꦻ䛡㰶测竽'
    //   538: invokevirtual toCharArray : ()[C
    //   541: dup
    //   542: dup
    //   543: iconst_3
    //   544: dup_x1
    //   545: caload
    //   546: sipush #31103
    //   549: ixor
    //   550: i2c
    //   551: castore
    //   552: sipush #14169
    //   555: iconst_5
    //   556: iconst_3
    //   557: invokestatic W : (Ljava/lang/Object;SBS)Ljava/lang/String;
    //   560: invokevirtual ՙᗮ : (Ljava/lang/String;)I
    //   563: invokevirtual ˊ : (I)Lyyds/sniarbtej/ʿᵉ;
    //   566: iload_2
    //   567: invokevirtual ᴵʖ : (I)Lyyds/sniarbtej/ʿᵉ;
    //   570: aload_0
    //   571: getfield ˑỲ : I
    //   574: invokevirtual ˊ : (I)Lyyds/sniarbtej/ʿᵉ;
    //   577: aload_0
    //   578: getfield ˌپ : I
    //   581: invokevirtual ˊ : (I)Lyyds/sniarbtej/ʿᵉ;
    //   584: aload_0
    //   585: getfield ʹﮃ : Lyyds/sniarbtej/ʿᵉ;
    //   588: getfield ʹﮃ : I
    //   591: invokevirtual ᴵʖ : (I)Lyyds/sniarbtej/ʿᵉ;
    //   594: aload_0
    //   595: getfield ʹﮃ : Lyyds/sniarbtej/ʿᵉ;
    //   598: getfield ˊ : [B
    //   601: iconst_0
    //   602: aload_0
    //   603: getfield ʹﮃ : Lyyds/sniarbtej/ʿᵉ;
    //   606: getfield ʹﮃ : I
    //   609: invokevirtual ᐨẏ : ([BII)Lyyds/sniarbtej/ʿᵉ;
    //   612: pop
    //   613: aload_0
    //   614: getfield ᐨẏ : Lyyds/sniarbtej/ˌᑦ;
    //   617: aload_1
    //   618: invokestatic ᐨẏ : (Lyyds/sniarbtej/ˌᑦ;Lyyds/sniarbtej/ʿᵉ;)V
    //   621: aload_1
    //   622: iload_3
    //   623: invokevirtual ˊ : (I)Lyyds/sniarbtej/ʿᵉ;
    //   626: pop
    //   627: aload_0
    //   628: getfield ʾܪ : Lyyds/sniarbtej/ʿᵉ;
    //   631: ifnull -> 762
    //   634: aload_0
    //   635: getfield ᐨẏ : Lyyds/sniarbtej/ˌх;
    //   638: dup
    //   639: astore_2
    //   640: getfield Ԇ : I
    //   643: bipush #50
    //   645: if_icmplt -> 652
    //   648: iconst_1
    //   649: goto -> 653
    //   652: iconst_0
    //   653: istore #4
    //   655: aload_1
    //   656: aload_0
    //   657: getfield ᐨẏ : Lyyds/sniarbtej/ˌх;
    //   660: iload #4
    //   662: ifeq -> 693
    //   665: ldc_w '폀ਅ∗뭱╞ឺﲐ땍ﱭ롫㻢ꈒ꠾氟'
    //   668: invokevirtual toCharArray : ()[C
    //   671: dup
    //   672: dup
    //   673: iconst_1
    //   674: dup_x1
    //   675: caload
    //   676: sipush #3944
    //   679: ixor
    //   680: i2c
    //   681: castore
    //   682: sipush #29635
    //   685: iconst_0
    //   686: iconst_4
    //   687: invokestatic W : (Ljava/lang/Object;SBS)Ljava/lang/String;
    //   690: goto -> 718
    //   693: ldc_w '䊎쥅皌╋십?袀꥗冞'
    //   696: invokevirtual toCharArray : ()[C
    //   699: dup
    //   700: dup
    //   701: iconst_5
    //   702: dup_x1
    //   703: caload
    //   704: sipush #19775
    //   707: ixor
    //   708: i2c
    //   709: castore
    //   710: sipush #27131
    //   713: iconst_0
    //   714: iconst_1
    //   715: invokestatic W : (Ljava/lang/Object;SBS)Ljava/lang/String;
    //   718: invokevirtual ՙᗮ : (Ljava/lang/String;)I
    //   721: invokevirtual ˊ : (I)Lyyds/sniarbtej/ʿᵉ;
    //   724: iconst_2
    //   725: aload_0
    //   726: getfield ʾܪ : Lyyds/sniarbtej/ʿᵉ;
    //   729: getfield ʹﮃ : I
    //   732: iadd
    //   733: invokevirtual ᴵʖ : (I)Lyyds/sniarbtej/ʿᵉ;
    //   736: aload_0
    //   737: getfield ᓑ : I
    //   740: invokevirtual ˊ : (I)Lyyds/sniarbtej/ʿᵉ;
    //   743: aload_0
    //   744: getfield ʾܪ : Lyyds/sniarbtej/ʿᵉ;
    //   747: getfield ˊ : [B
    //   750: iconst_0
    //   751: aload_0
    //   752: getfield ʾܪ : Lyyds/sniarbtej/ʿᵉ;
    //   755: getfield ʹﮃ : I
    //   758: invokevirtual ᐨẏ : ([BII)Lyyds/sniarbtej/ʿᵉ;
    //   761: pop
    //   762: aload_0
    //   763: getfield ՙᗮ : Lyyds/sniarbtej/ʿᵉ;
    //   766: ifnull -> 843
    //   769: aload_1
    //   770: aload_0
    //   771: getfield ᐨẏ : Lyyds/sniarbtej/ˌх;
    //   774: ldc_w '쥿茺̳䬅ਗ鹵徺ủး捋ꉮ⌞쎊ฎ⇸'
    //   777: invokevirtual toCharArray : ()[C
    //   780: dup
    //   781: dup
    //   782: iconst_4
    //   783: dup_x1
    //   784: caload
    //   785: sipush #23425
    //   788: ixor
    //   789: i2c
    //   790: castore
    //   791: sipush #28451
    //   794: iconst_3
    //   795: iconst_0
    //   796: invokestatic W : (Ljava/lang/Object;SBS)Ljava/lang/String;
    //   799: invokevirtual ՙᗮ : (Ljava/lang/String;)I
    //   802: invokevirtual ˊ : (I)Lyyds/sniarbtej/ʿᵉ;
    //   805: iconst_2
    //   806: aload_0
    //   807: getfield ՙᗮ : Lyyds/sniarbtej/ʿᵉ;
    //   810: getfield ʹﮃ : I
    //   813: iadd
    //   814: invokevirtual ᴵʖ : (I)Lyyds/sniarbtej/ʿᵉ;
    //   817: aload_0
    //   818: getfield ﾞﮢ : I
    //   821: invokevirtual ˊ : (I)Lyyds/sniarbtej/ʿᵉ;
    //   824: aload_0
    //   825: getfield ՙᗮ : Lyyds/sniarbtej/ʿᵉ;
    //   828: getfield ˊ : [B
    //   831: iconst_0
    //   832: aload_0
    //   833: getfield ՙᗮ : Lyyds/sniarbtej/ʿᵉ;
    //   836: getfield ʹﮃ : I
    //   839: invokevirtual ᐨẏ : ([BII)Lyyds/sniarbtej/ʿᵉ;
    //   842: pop
    //   843: aload_0
    //   844: getfield ˍɫ : Lyyds/sniarbtej/ʿᵉ;
    //   847: ifnull -> 925
    //   850: aload_1
    //   851: aload_0
    //   852: getfield ᐨẏ : Lyyds/sniarbtej/ˌх;
    //   855: ldc_w '砀潓Ꮥ詊鰩系╷ಥ鬥ﯖ髰ꮱ൐瞜ꫨ鮤ࣝ'
    //   858: invokevirtual toCharArray : ()[C
    //   861: dup
    //   862: dup
    //   863: bipush #14
    //   865: dup_x1
    //   866: caload
    //   867: sipush #9280
    //   870: ixor
    //   871: i2c
    //   872: castore
    //   873: sipush #1198
    //   876: iconst_5
    //   877: iconst_1
    //   878: invokestatic W : (Ljava/lang/Object;SBS)Ljava/lang/String;
    //   881: invokevirtual ՙᗮ : (Ljava/lang/String;)I
    //   884: invokevirtual ˊ : (I)Lyyds/sniarbtej/ʿᵉ;
    //   887: iconst_2
    //   888: aload_0
    //   889: getfield ˍɫ : Lyyds/sniarbtej/ʿᵉ;
    //   892: getfield ʹﮃ : I
    //   895: iadd
    //   896: invokevirtual ᴵʖ : (I)Lyyds/sniarbtej/ʿᵉ;
    //   899: aload_0
    //   900: getfield ﾞﾇ : I
    //   903: invokevirtual ˊ : (I)Lyyds/sniarbtej/ʿᵉ;
    //   906: aload_0
    //   907: getfield ˍɫ : Lyyds/sniarbtej/ʿᵉ;
    //   910: getfield ˊ : [B
    //   913: iconst_0
    //   914: aload_0
    //   915: getfield ˍɫ : Lyyds/sniarbtej/ʿᵉ;
    //   918: getfield ʹﮃ : I
    //   921: invokevirtual ᐨẏ : ([BII)Lyyds/sniarbtej/ʿᵉ;
    //   924: pop
    //   925: aload_0
    //   926: getfield ʽ : Lyyds/sniarbtej/ʿᵉ;
    //   929: ifnull -> 1007
    //   932: aload_1
    //   933: aload_0
    //   934: getfield ᐨẏ : Lyyds/sniarbtej/ˌх;
    //   937: ldc_w '煚Ṓ涫궄轍향șꇸ绰籍㪄㸸㲮竏＇⦤⺲븸鹼缾臁⦲'
    //   940: invokevirtual toCharArray : ()[C
    //   943: dup
    //   944: dup
    //   945: bipush #15
    //   947: dup_x1
    //   948: caload
    //   949: sipush #11434
    //   952: ixor
    //   953: i2c
    //   954: castore
    //   955: sipush #26212
    //   958: iconst_0
    //   959: iconst_5
    //   960: invokestatic W : (Ljava/lang/Object;SBS)Ljava/lang/String;
    //   963: invokevirtual ՙᗮ : (Ljava/lang/String;)I
    //   966: invokevirtual ˊ : (I)Lyyds/sniarbtej/ʿᵉ;
    //   969: iconst_2
    //   970: aload_0
    //   971: getfield ʽ : Lyyds/sniarbtej/ʿᵉ;
    //   974: getfield ʹﮃ : I
    //   977: iadd
    //   978: invokevirtual ᴵʖ : (I)Lyyds/sniarbtej/ʿᵉ;
    //   981: aload_0
    //   982: getfield ˍʶ : I
    //   985: invokevirtual ˊ : (I)Lyyds/sniarbtej/ʿᵉ;
    //   988: aload_0
    //   989: getfield ʽ : Lyyds/sniarbtej/ʿᵉ;
    //   992: getfield ˊ : [B
    //   995: iconst_0
    //   996: aload_0
    //   997: getfield ʽ : Lyyds/sniarbtej/ʿᵉ;
    //   1000: getfield ʹﮃ : I
    //   1003: invokevirtual ᐨẏ : ([BII)Lyyds/sniarbtej/ʿᵉ;
    //   1006: pop
    //   1007: aload_0
    //   1008: getfield ՙᗮ : Lyyds/sniarbtej/ˊ;
    //   1011: ifnull -> 1055
    //   1014: aload_0
    //   1015: getfield ՙᗮ : Lyyds/sniarbtej/ˊ;
    //   1018: aload_0
    //   1019: getfield ᐨẏ : Lyyds/sniarbtej/ˌх;
    //   1022: ldc_w '吝酭醾?ⵔı娩示ቈ─◳渻ڥ赮灴饷鉽驿놼핼뽂䝭{诀禹࣡ꫭ馒终'
    //   1025: invokevirtual toCharArray : ()[C
    //   1028: dup
    //   1029: dup
    //   1030: bipush #13
    //   1032: dup_x1
    //   1033: caload
    //   1034: sipush #21104
    //   1037: ixor
    //   1038: i2c
    //   1039: castore
    //   1040: sipush #17324
    //   1043: iconst_4
    //   1044: iconst_5
    //   1045: invokestatic W : (Ljava/lang/Object;SBS)Ljava/lang/String;
    //   1048: invokevirtual ՙᗮ : (Ljava/lang/String;)I
    //   1051: aload_1
    //   1052: invokevirtual ᐨẏ : (ILyyds/sniarbtej/ʿᵉ;)V
    //   1055: aload_0
    //   1056: getfield ˍɫ : Lyyds/sniarbtej/ˊ;
    //   1059: ifnull -> 1101
    //   1062: aload_0
    //   1063: getfield ˍɫ : Lyyds/sniarbtej/ˊ;
    //   1066: aload_0
    //   1067: getfield ᐨẏ : Lyyds/sniarbtej/ˌх;
    //   1070: ldc_w '俪媊범탘洟뻯?떓Ɤ䄼整楠⹴芒苑릳ꌔ琞⒂ᎂ쎅뗑ࣧ鬎䙫䂝㶁동ِ籠'
    //   1073: invokevirtual toCharArray : ()[C
    //   1076: dup
    //   1077: dup
    //   1078: iconst_4
    //   1079: dup_x1
    //   1080: caload
    //   1081: sipush #3276
    //   1084: ixor
    //   1085: i2c
    //   1086: castore
    //   1087: bipush #29
    //   1089: iconst_2
    //   1090: iconst_3
    //   1091: invokestatic W : (Ljava/lang/Object;SBS)Ljava/lang/String;
    //   1094: invokevirtual ՙᗮ : (Ljava/lang/String;)I
    //   1097: aload_1
    //   1098: invokevirtual ᐨẏ : (ILyyds/sniarbtej/ʿᵉ;)V
    //   1101: aload_0
    //   1102: getfield ᴵʖ : Lyyds/sniarbtej/ᴵʖ;
    //   1105: ifnull -> 1142
    //   1108: aload_0
    //   1109: getfield ᴵʖ : Lyyds/sniarbtej/ᴵʖ;
    //   1112: aload_0
    //   1113: getfield ᐨẏ : Lyyds/sniarbtej/ˌх;
    //   1116: aload_0
    //   1117: getfield ʹﮃ : Lyyds/sniarbtej/ʿᵉ;
    //   1120: getfield ˊ : [B
    //   1123: aload_0
    //   1124: getfield ʹﮃ : Lyyds/sniarbtej/ʿᵉ;
    //   1127: getfield ʹﮃ : I
    //   1130: aload_0
    //   1131: getfield ˑỲ : I
    //   1134: aload_0
    //   1135: getfield ˌپ : I
    //   1138: aload_1
    //   1139: invokevirtual ᐨẏ : (Lyyds/sniarbtej/ˌх;[BIIILyyds/sniarbtej/ʿᵉ;)V
    //   1142: aload_0
    //   1143: getfield ٴῪ : I
    //   1146: ifle -> 1240
    //   1149: aload_1
    //   1150: aload_0
    //   1151: getfield ᐨẏ : Lyyds/sniarbtej/ˌх;
    //   1154: ldc_w '䔄甦챳㒵໩?㝻ꤽ턏㥎੣'
    //   1157: invokevirtual toCharArray : ()[C
    //   1160: dup
    //   1161: dup
    //   1162: iconst_5
    //   1163: dup_x1
    //   1164: caload
    //   1165: sipush #8546
    //   1168: ixor
    //   1169: i2c
    //   1170: castore
    //   1171: sipush #6489
    //   1174: iconst_3
    //   1175: iconst_3
    //   1176: invokestatic W : (Ljava/lang/Object;SBS)Ljava/lang/String;
    //   1179: invokevirtual ՙᗮ : (Ljava/lang/String;)I
    //   1182: invokevirtual ˊ : (I)Lyyds/sniarbtej/ʿᵉ;
    //   1185: iconst_2
    //   1186: iconst_2
    //   1187: aload_0
    //   1188: getfield ٴῪ : I
    //   1191: imul
    //   1192: iadd
    //   1193: invokevirtual ᴵʖ : (I)Lyyds/sniarbtej/ʿᵉ;
    //   1196: aload_0
    //   1197: getfield ٴῪ : I
    //   1200: invokevirtual ˊ : (I)Lyyds/sniarbtej/ʿᵉ;
    //   1203: pop
    //   1204: aload_0
    //   1205: getfield ͺо : [I
    //   1208: dup
    //   1209: astore_2
    //   1210: arraylength
    //   1211: istore_3
    //   1212: iconst_0
    //   1213: istore #4
    //   1215: iload #4
    //   1217: iload_3
    //   1218: if_icmpge -> 1240
    //   1221: aload_2
    //   1222: iload #4
    //   1224: iaload
    //   1225: istore #5
    //   1227: aload_1
    //   1228: iload #5
    //   1230: invokevirtual ˊ : (I)Lyyds/sniarbtej/ʿᵉ;
    //   1233: pop
    //   1234: iinc #4, 1
    //   1237: goto -> 1215
    //   1240: aload_0
    //   1241: getfield ᐨẏ : Lyyds/sniarbtej/ˌх;
    //   1244: aload_0
    //   1245: getfield ʿλ : I
    //   1248: aload_0
    //   1249: getfield ﾞǰ : I
    //   1252: aload_1
    //   1253: invokestatic ᐨẏ : (Lyyds/sniarbtej/ˌх;IILyyds/sniarbtej/ʿᵉ;)V
    //   1256: aload_0
    //   1257: getfield ᐨẏ : Lyyds/sniarbtej/ˌх;
    //   1260: aload_0
    //   1261: getfield ᴵʖ : Lyyds/sniarbtej/ˊ;
    //   1264: aload_0
    //   1265: getfield ﾞл : Lyyds/sniarbtej/ˊ;
    //   1268: aload_0
    //   1269: getfield ʿᵉ : Lyyds/sniarbtej/ˊ;
    //   1272: aload_0
    //   1273: getfield ʹﮃ : Lyyds/sniarbtej/ˊ;
    //   1276: aload_1
    //   1277: invokestatic ᐨẏ : (Lyyds/sniarbtej/ˌх;Lyyds/sniarbtej/ˊ;Lyyds/sniarbtej/ˊ;Lyyds/sniarbtej/ˊ;Lyyds/sniarbtej/ˊ;Lyyds/sniarbtej/ʿᵉ;)V
    //   1280: aload_0
    //   1281: getfield ᐨẏ : [Lyyds/sniarbtej/ˊ;
    //   1284: ifnull -> 1347
    //   1287: aload_0
    //   1288: getfield ᐨẏ : Lyyds/sniarbtej/ˌх;
    //   1291: ldc_w '騐즑㩊㸒辢?튕蝹ㆾݣ㒉֊յ橞拯躖ࠠ䆬뉗㽝綪虘灎撈ᚢ䂖䕾?ᬵ炌'
    //   1294: invokevirtual toCharArray : ()[C
    //   1297: dup
    //   1298: dup
    //   1299: bipush #15
    //   1301: dup_x1
    //   1302: caload
    //   1303: sipush #14927
    //   1306: ixor
    //   1307: i2c
    //   1308: castore
    //   1309: sipush #19177
    //   1312: iconst_5
    //   1313: iconst_1
    //   1314: invokestatic W : (Ljava/lang/Object;SBS)Ljava/lang/String;
    //   1317: invokevirtual ՙᗮ : (Ljava/lang/String;)I
    //   1320: aload_0
    //   1321: getfield ᐨẏ : [Lyyds/sniarbtej/ˊ;
    //   1324: aload_0
    //   1325: getfield শ : I
    //   1328: ifne -> 1339
    //   1331: aload_0
    //   1332: getfield ᐨẏ : [Lyyds/sniarbtej/ˊ;
    //   1335: arraylength
    //   1336: goto -> 1343
    //   1339: aload_0
    //   1340: getfield শ : I
    //   1343: aload_1
    //   1344: invokestatic ᐨẏ : (I[Lyyds/sniarbtej/ˊ;ILyyds/sniarbtej/ʿᵉ;)V
    //   1347: aload_0
    //   1348: getfield ˊ : [Lyyds/sniarbtej/ˊ;
    //   1351: ifnull -> 1414
    //   1354: aload_0
    //   1355: getfield ᐨẏ : Lyyds/sniarbtej/ˌх;
    //   1358: ldc_w '袇믢逸?鉾븖׆ާ齀螕긯쩻뵼砐㻆橈괽ꉼ㑀註晴フ嶼䁰ﶯ짲㽴텒촀滯遴룔屭'
    //   1361: invokevirtual toCharArray : ()[C
    //   1364: dup
    //   1365: dup
    //   1366: bipush #10
    //   1368: dup_x1
    //   1369: caload
    //   1370: sipush #28753
    //   1373: ixor
    //   1374: i2c
    //   1375: castore
    //   1376: sipush #8367
    //   1379: iconst_5
    //   1380: iconst_4
    //   1381: invokestatic W : (Ljava/lang/Object;SBS)Ljava/lang/String;
    //   1384: invokevirtual ՙᗮ : (Ljava/lang/String;)I
    //   1387: aload_0
    //   1388: getfield ˊ : [Lyyds/sniarbtej/ˊ;
    //   1391: aload_0
    //   1392: getfield ˋᴷ : I
    //   1395: ifne -> 1406
    //   1398: aload_0
    //   1399: getfield ˊ : [Lyyds/sniarbtej/ˊ;
    //   1402: arraylength
    //   1403: goto -> 1410
    //   1406: aload_0
    //   1407: getfield ˋᴷ : I
    //   1410: aload_1
    //   1411: invokestatic ᐨẏ : (I[Lyyds/sniarbtej/ˊ;ILyyds/sniarbtej/ʿᵉ;)V
    //   1414: aload_0
    //   1415: getfield ᐨم : Lyyds/sniarbtej/ʿᵉ;
    //   1418: ifnull -> 1486
    //   1421: aload_1
    //   1422: aload_0
    //   1423: getfield ᐨẏ : Lyyds/sniarbtej/ˌх;
    //   1426: ldc_w '㐐ꭀꞙ匥痛ល齌뮭恚⨌ṋ흪㼫귐コ潞瀌'
    //   1429: invokevirtual toCharArray : ()[C
    //   1432: dup
    //   1433: dup
    //   1434: iconst_4
    //   1435: dup_x1
    //   1436: caload
    //   1437: sipush #8613
    //   1440: ixor
    //   1441: i2c
    //   1442: castore
    //   1443: sipush #32766
    //   1446: iconst_2
    //   1447: iconst_3
    //   1448: invokestatic W : (Ljava/lang/Object;SBS)Ljava/lang/String;
    //   1451: invokevirtual ՙᗮ : (Ljava/lang/String;)I
    //   1454: invokevirtual ˊ : (I)Lyyds/sniarbtej/ʿᵉ;
    //   1457: aload_0
    //   1458: getfield ᐨم : Lyyds/sniarbtej/ʿᵉ;
    //   1461: getfield ʹﮃ : I
    //   1464: invokevirtual ᴵʖ : (I)Lyyds/sniarbtej/ʿᵉ;
    //   1467: aload_0
    //   1468: getfield ᐨم : Lyyds/sniarbtej/ʿᵉ;
    //   1471: getfield ˊ : [B
    //   1474: iconst_0
    //   1475: aload_0
    //   1476: getfield ᐨم : Lyyds/sniarbtej/ʿᵉ;
    //   1479: getfield ʹﮃ : I
    //   1482: invokevirtual ᐨẏ : ([BII)Lyyds/sniarbtej/ʿᵉ;
    //   1485: pop
    //   1486: aload_0
    //   1487: getfield ʾ : Lyyds/sniarbtej/ʿᵉ;
    //   1490: ifnull -> 1568
    //   1493: aload_1
    //   1494: aload_0
    //   1495: getfield ᐨẏ : Lyyds/sniarbtej/ˌх;
    //   1498: ldc_w '褅퓈ꉂ싹?⌊ﴇꫝ睓ᑼଧᑓ꒶黙஍'
    //   1501: invokevirtual toCharArray : ()[C
    //   1504: dup
    //   1505: dup
    //   1506: bipush #13
    //   1508: dup_x1
    //   1509: caload
    //   1510: sipush #3584
    //   1513: ixor
    //   1514: i2c
    //   1515: castore
    //   1516: sipush #12592
    //   1519: iconst_4
    //   1520: iconst_2
    //   1521: invokestatic W : (Ljava/lang/Object;SBS)Ljava/lang/String;
    //   1524: invokevirtual ՙᗮ : (Ljava/lang/String;)I
    //   1527: invokevirtual ˊ : (I)Lyyds/sniarbtej/ʿᵉ;
    //   1530: iconst_1
    //   1531: aload_0
    //   1532: getfield ʾ : Lyyds/sniarbtej/ʿᵉ;
    //   1535: getfield ʹﮃ : I
    //   1538: iadd
    //   1539: invokevirtual ᴵʖ : (I)Lyyds/sniarbtej/ʿᵉ;
    //   1542: aload_0
    //   1543: getfield ﹼ : I
    //   1546: invokevirtual ᐨẏ : (I)Lyyds/sniarbtej/ʿᵉ;
    //   1549: aload_0
    //   1550: getfield ʾ : Lyyds/sniarbtej/ʿᵉ;
    //   1553: getfield ˊ : [B
    //   1556: iconst_0
    //   1557: aload_0
    //   1558: getfield ʾ : Lyyds/sniarbtej/ʿᵉ;
    //   1561: getfield ʹﮃ : I
    //   1564: invokevirtual ᐨẏ : ([BII)Lyyds/sniarbtej/ʿᵉ;
    //   1567: pop
    //   1568: aload_0
    //   1569: getfield ˊ : Lyyds/sniarbtej/ᴵʖ;
    //   1572: ifnull -> 1587
    //   1575: aload_0
    //   1576: getfield ˊ : Lyyds/sniarbtej/ᴵʖ;
    //   1579: aload_0
    //   1580: getfield ᐨẏ : Lyyds/sniarbtej/ˌх;
    //   1583: aload_1
    //   1584: invokevirtual ᐨẏ : (Lyyds/sniarbtej/ˌх;Lyyds/sniarbtej/ʿᵉ;)V
    //   1587: return
  }
  
  final void ᐨẏ(ﾞл paramﾞл) {
    paramﾞл.ᐨẏ(this.ˊ);
    paramﾞл.ᐨẏ(this.ᴵʖ);
  }
}


/* Location:              C:\Users\kb\Downloads\ja-netfilter.jar!\yyds\sniarbtej\ʿপ.class
 * Java compiler version: 8 (52.0)
 * JD-Core Version:       1.1.3
 */