package yyds.sniarbtej;

import java.io.FileInputStream;
import java.io.PrintWriter;
import java.util.ArrayList;
import java.util.HashMap;
import java.util.List;
import java.util.Map;
import ylt.pmn.zubdqvgt;

public class ˉʭ extends ˍɫ {
  private static final String ʾא = ˏȓ$ᴵЃ.E("㔽깓諤?๺㔘囇簗쒟䖍寱獘댫솲ᚴ?ȭ篡㤴摮峝ẽ페௜࿣咹끔께⇩麬귉ᙄ鷫꧶献\007䞾?雭䤓꾒樨癭⌆틝떆㉗ꩴ悒戊刽鳊↹鿆ᠴ첓?ꎹ㹊䂙旸₪Ⓘ詸埏葏Ö⋬陞㯑⋞氰៨峛?喴㋏讚ᯑⲐ㻓늉婐巼䦃掲㣎੸䀖".toCharArray(), (short)10678, (short)0, (short)2).intern();
  
  private static final String יς = ˏȓ$ᴵЃ.E("좞來ꇠᵏꈅ㾉誙ᶢ뫙멏個䃚秶䰮⤵핟⟥".toCharArray(), (short)18043, (short)5, (short)1).intern();
  
  private boolean ˌ;
  
  private int ᔪ;
  
  private boolean ˍ;
  
  private boolean ʹō;
  
  private boolean ᐝᵣ;
  
  private boolean ᔪ;
  
  private boolean ʿλ;
  
  private String ˏﾚ;
  
  private boolean ᴵƚ;
  
  private Map<ᔪ, Integer> ʽ = new HashMap<>();
  
  private ˉʭ(ˍɫ paramˍɫ) {
    this(paramˍɫ, true);
  }
  
  private ˉʭ(ˍɫ paramˍɫ, boolean paramBoolean) {
    this(589824, paramˍɫ, true);
    if (!zubdqvgt.G(getClass(), ˉʭ.class))
      throw new IllegalStateException(); 
  }
  
  protected ˉʭ(int paramInt, ˍɫ paramˍɫ, boolean paramBoolean) {
    super(paramInt, paramˍɫ);
    this.ˌ = paramBoolean;
  }
  
  public final void ᐨẏ(int paramInt1, int paramInt2, String paramString1, String paramString2, String paramString3, String[] paramArrayOfString) {
    if (this.ˍ) {
      "۟돈꟔̋ꀎ꺈?싈︐也若쑻叡ቿ黼Ჴఢ톘㕱죬᭻苒闰븹齓풟㑏".toCharArray()[7] = (char)("۟돈꟔̋ꀎ꺈?싈︐也若쑻叡ቿ黼Ჴఢ톘㕱죬᭻苒闰븹齓풟㑏".toCharArray()[7] ^ 0x6BFA);
      throw new IllegalStateException(ᐨẏ$ᐝт.W("۟돈꟔̋ꀎ꺈?싈︐也若쑻叡ቿ黼Ჴఢ톘㕱죬᭻苒闰븹齓풟㑏".toCharArray(), (short)8812, (byte)2, (short)0));
    } 
    this.ˍ = true;
    গ();
    ᐨم(paramInt2, 259633);
    if (paramString1 == null) {
      "鼶㲄싂ᨵ뱿ఉ닷ꤴꗶ멨楝浢Ώ攛站觃趠禫郧⋴䵜ⵦ囯齬᥽".toCharArray()[15] = (char)("鼶㲄싂ᨵ뱿ఉ닷ꤴꗶ멨楝浢Ώ攛站觃趠禫郧⋴䵜ⵦ囯齬᥽".toCharArray()[15] ^ 0x571);
      throw new IllegalArgumentException(ᐨẏ$ᐝт.W("鼶㲄싂ᨵ뱿ఉ닷ꤴꗶ멨楝浢Ώ攛站觃趠禫郧⋴䵜ⵦ囯齬᥽".toCharArray(), (short)5034, (byte)3, (short)4));
    } 
    "蓔頬਺珿䥤鮕?뱚ႃ㏐".toCharArray()[0] = (char)("蓔頬਺珿䥤鮕?뱚ႃ㏐".toCharArray()[0] ^ 0x5689);
    "䘊텯受羌驹⨨랍䄑枖릃獛⡁".toCharArray()[3] = (char)("䘊텯受羌驹⨨랍䄑枖릃獛⡁".toCharArray()[3] ^ 0x71BA);
    if (!paramString1.endsWith(ᐨẏ$ᐝт.W("蓔頬਺珿䥤鮕?뱚ႃ㏐".toCharArray(), (short)27059, (byte)2, (short)5)) && !paramString1.endsWith(ᐨẏ$ᐝт.W("䘊텯受羌驹⨨랍䄑枖릃獛⡁".toCharArray(), (short)31073, (byte)1, (short)2))) {
      "㉖뻜ꣾ鸿쐷톐璍୰歰骾糺".toCharArray()[0] = (char)("㉖뻜ꣾ鸿쐷톐璍୰歰骾糺".toCharArray()[0] ^ 0x5AE6);
      ـｊ.ʹﮃ(paramInt1, paramString1, ᐨẏ$ᐝт.W("㉖뻜ꣾ鸿쐷톐璍୰歰骾糺".toCharArray(), (short)19406, (byte)0, (short)0));
    } 
    "쥳㪄遒롣糠෼⑁Ն鳯១༙귨骭鯷䍮䛆".toCharArray()[9] = (char)("쥳㪄遒롣糠෼⑁Ն鳯១༙귨骭鯷䍮䛆".toCharArray()[9] ^ 0x68F6);
    if (ᐨẏ$ᐝт.W("쥳㪄遒롣糠෼⑁Ն鳯១༙귨骭鯷䍮䛆".toCharArray(), (short)25566, (byte)0, (short)0).equals(paramString1)) {
      if (paramString3 != null) {
        "괠錡浫즻気뮕?䑬꒺說띵佗嫔⚢觿酅ｘ덳笳꾄ႆ쮁霌힝椱ᷡ뀹ፖ㩡േ튂狭ꛡ䉩酰黄캬稘矃닛飳쬌똎쐻驪㪷".toCharArray()[50] = (char)("괠錡浫즻気뮕?䑬꒺說띵佗嫔⚢觿酅ｘ덳笳꾄ႆ쮁霌힝椱ᷡ뀹ፖ㩡േ튂狭ꛡ䉩酰黄캬稘矃닛飳쬌똎쐻驪㪷".toCharArray()[50] ^ 0x5906);
        throw new IllegalArgumentException(ᐨẏ$ᐝт.W("괠錡浫즻気뮕?䑬꒺說띵佗嫔⚢觿酅ｘ덳笳꾄ႆ쮁霌힝椱ᷡ뀹ፖ㩡േ튂狭ꛡ䉩酰黄캬稘矃닛飳쬌똎쐻驪㪷".toCharArray(), (short)12918, (byte)1, (short)4));
      } 
    } else {
      "嗻뾫Ⴄ྘輓轘ᆫ橽વ褾㰃".toCharArray()[3] = (char)("嗻뾫Ⴄ྘輓轘ᆫ橽વ褾㰃".toCharArray()[3] ^ 0x145);
      if (paramString1.endsWith(ᐨẏ$ᐝт.W("嗻뾫Ⴄ྘輓轘ᆫ橽વ褾㰃".toCharArray(), (short)4787, (byte)4, (short)5))) {
        if (paramString3 != null) {
          "텊Թ꟧ꀋ밁帗?桎튝脋䜖㸲䧖녲ྐྵ⍂讜틡똡玽ᘛ嗴迉牒뤧䱶﹪闧鯦ꡱ牒ﴻ컿牀̝䭙밉ᇵ替㰚㍕悛ᢒ沿폃䆩⅘ࠨ塍옾ᄻ?ژ".toCharArray()[16] = (char)("텊Թ꟧ꀋ밁帗?桎튝脋䜖㸲䧖녲ྐྵ⍂讜틡똡玽ᘛ嗴迉牒뤧䱶﹪闧鯦ꡱ牒ﴻ컿牀̝䭙밉ᇵ替㰚㍕悛ᢒ沿폃䆩⅘ࠨ塍옾ᄻ?ژ".toCharArray()[16] ^ 0x5AF5);
          throw new IllegalArgumentException(ᐨẏ$ᐝт.W("텊Թ꟧ꀋ밁帗?桎튝脋䜖㸲䧖녲ྐྵ⍂讜틡똡玽ᘛ嗴迉牒뤧䱶﹪闧鯦ꡱ牒ﴻ컿牀̝䭙밉ᇵ替㰚㍕悛ᢒ沿폃䆩⅘ࠨ塍옾ᄻ?ژ".toCharArray(), (short)28042, (byte)1, (short)1));
        } 
      } else {
        "ⷲ͡㟥륂豱⻮姫퐫䓉ﲡ묵ᾯᚒ◉ꖖ摭".toCharArray()[15] = (char)("ⷲ͡㟥륂豱⻮姫퐫䓉ﲡ묵ᾯᚒ◉ꖖ摭".toCharArray()[15] ^ 0x3DD6);
        ـｊ.ʹﮃ(paramInt1, paramString3, ᐨẏ$ᐝт.W("ⷲ͡㟥륂豱⻮姫퐫䓉ﲡ묵ᾯᚒ◉ꖖ摭".toCharArray(), (short)26669, (byte)1, (short)0));
      } 
    } 
    if (paramString2 != null)
      ᴵƚ(paramString2); 
    "ቯ祪ﶓⲖ쮰멭崎챂ᦗ盆ǹ塊땣㱆".toCharArray()[13] = (char)("ቯ祪ﶓⲖ쮰멭崎챂ᦗ盆ǹ塊땣㱆".toCharArray()[13] ^ 0xCE);
    if ((paramInt2 & 0x200) != 0 && !ᐨẏ$ᐝт.W("ቯ祪ﶓⲖ쮰멭崎챂ᦗ盆ǹ塊땣㱆".toCharArray(), (short)11728, (byte)3, (short)1).equals(paramString3)) {
      "暶羧酨鳇燣襄ᱜ瑬穛␼膂녮㿰㟞맃㖗簀䕏ꮀ녔侴빛﬎ꙧ鳳㒝ứɭ౟⑞묙ఉ뮕쮣魏䠻ἐ뵅릆飫Ꞣﾒひ瞾Ꝏꌈㆪ?䫜阞쳸︳緲䯴".toCharArray()[3] = (char)("暶羧酨鳇燣襄ᱜ瑬穛␼膂녮㿰㟞맃㖗簀䕏ꮀ녔侴빛﬎ꙧ鳳㒝ứɭ౟⑞묙ఉ뮕쮣魏䠻ἐ뵅릆飫Ꞣﾒひ瞾Ꝏꌈㆪ?䫜阞쳸︳緲䯴".toCharArray()[3] ^ 0x2042);
      throw new IllegalArgumentException(ᐨẏ$ᐝт.W("暶羧酨鳇燣襄ᱜ瑬穛␼膂녮㿰㟞맃㖗簀䕏ꮀ녔侴빛﬎ꙧ鳳㒝ứɭ౟⑞묙ఉ뮕쮣魏䠻ἐ뵅릆飫Ꞣﾒひ瞾Ꝏꌈㆪ?䫜阞쳸︳緲䯴".toCharArray(), (short)9547, (byte)4, (short)5));
    } 
    if (paramArrayOfString != null)
      for (byte b = 0; b < paramArrayOfString.length; b++) {
        "ꦮ族兾畘?炤笠蚢⹱巄욨ⶶ茪髄쑩로땔?⦍震ᗁ".toCharArray()[18] = (char)("ꦮ族兾畘?炤笠蚢⹱巄욨ⶶ茪髄쑩로땔?⦍震ᗁ".toCharArray()[18] ^ 0x638);
        ـｊ.ʹﮃ(paramInt1, paramArrayOfString[b], ᐨẏ$ᐝт.W("ꦮ族兾畘?炤笠蚢⹱巄욨ⶶ茪髄쑩로땔?⦍震ᗁ".toCharArray(), (short)5374, (byte)3, (short)0) + b);
      }  
    this.ᔪ = paramInt1;
    super.ᐨẏ(paramInt1, paramInt2, paramString1, paramString2, paramString3, paramArrayOfString);
  }
  
  public final void ᐨẏ(String paramString1, String paramString2) {
    গ();
    if (this.ᐝᵣ) {
      "孼ꕉ远ꚜ觪鹧?귮闱蔍鹻㓆愘潿힎੫㬒烌⛺ύ໢䩍㚘秦间为犱櫭僟苛くƽ?俋캩咳".toCharArray()[14] = (char)("孼ꕉ远ꚜ觪鹧?귮闱蔍鹻㓆愘潿힎੫㬒烌⛺ύ໢䩍㚘秦间为犱櫭僟苛くƽ?俋캩咳".toCharArray()[14] ^ 0x231C);
      throw new IllegalStateException(ᐝᵣ$ﾞﾇ.j("孼ꕉ远ꚜ觪鹧?귮闱蔍鹻㓆愘潿힎੫㬒烌⛺ύ໢䩍㚘秦间为犱櫭僟苛くƽ?俋캩咳".toCharArray(), (short)4100, 0, (short)4));
    } 
    this.ᐝᵣ = true;
    super.ᐨẏ(paramString1, paramString2);
  }
  
  public final ʻล ᐨẏ(String paramString1, int paramInt, String paramString2) {
    গ();
    if (this.ʹō) {
      "㟸䴸ò칪뗓鄩轏帰ꦏ琗斃ᥪ늹砸쨴ᡎ聎냏邉?䟮빡퍎䕏恍嬮៓઎읈鞽쿅ሥ᦬".toCharArray()[34] = (char)("㟸䴸ò칪뗓鄩轏帰ꦏ琗斃ᥪ늹砸쨴ᡎ聎냏邉?䟮빡퍎䕏恍嬮៓઎읈鞽쿅ሥ᦬".toCharArray()[34] ^ 0x15C6);
      throw new IllegalStateException(ˏȓ$ᴵЃ.E("㟸䴸ò칪뗓鄩轏帰ꦏ琗斃ᥪ늹砸쨴ᡎ聎냏邉?䟮빡퍎䕏恍嬮៓઎읈鞽쿅ሥ᦬".toCharArray(), (short)30140, (short)4, (short)1));
    } 
    this.ʹō = true;
    "⵰婢?휙ሧṪ蟚ꬼ걖㺗娆દ".toCharArray()[4] = (char)("⵰婢?휙ሧṪ蟚ꬼ걖㺗娆દ".toCharArray()[4] ^ 0x743C);
    ᴵʖ(this.ᔪ, paramString1, ˏȓ$ᴵЃ.E("⵰婢?휙ሧṪ蟚ꬼ걖㺗娆દ".toCharArray(), (short)18741, (short)1, (short)0));
    ᐨم(paramInt, 36896);
    ʋ ʋ;
    (ʋ = new ʋ(this.ᐨẏ, super.ᐨẏ(paramString1, paramInt, paramString2), ((paramInt & 0x20) != 0))).ᓕ = this.ᔪ;
    return ʋ;
  }
  
  public final void ᐨẏ(String paramString) {
    গ();
    "肩蓱쐆䧴贝吉綅뇂拴".toCharArray()[1] = (char)("肩蓱쐆䧴贝吉綅뇂拴".toCharArray()[1] ^ 0x7AA9);
    ـｊ.ʹﮃ(this.ᔪ, paramString, ˉﻤ$ͺſ.v("肩蓱쐆䧴贝吉綅뇂拴".toCharArray(), (short)9234, 0, (short)2));
    if (this.ʿλ) {
      "ळ퓩늁돠ⳓॣ꦳몏岭⡣Კ಍Ꮮជ큎㞆떟줌鱓褘寅噒밁褿ৌᙀ⣐蜹⿆⢥㒿䎿䂽殗脨娊賕䕿".toCharArray()[7] = (char)("ळ퓩늁돠ⳓॣ꦳몏岭⡣Კ಍Ꮮជ큎㞆떟줌鱓褘寅噒밁褿ৌᙀ⣐蜹⿆⢥㒿䎿䂽殗脨娊賕䕿".toCharArray()[7] ^ 0x3D9D);
      throw new IllegalStateException(ˉﻤ$ͺſ.v("ळ퓩늁돠ⳓॣ꦳몏岭⡣Კ಍Ꮮជ큎㞆떟줌鱓褘寅噒밁褿ৌᙀ⣐蜹⿆⢥㒿䎿䂽殗脨娊賕䕿".toCharArray(), (short)28707, 3, (short)0));
    } 
    if (this.ˏﾚ != null) {
      "搐敭䢍?飚㗐虏欔鵃ẫ廱࡝촋攻ẵ쀓靇䲿짿췁တ傿䁨铹诓迊鳪唉픇ퟹ❄▥?槏杦늣ᝰ闽푛퍔氺꓏頭跏ᬎ睸듊砌".toCharArray()[16] = (char)("搐敭䢍?飚㗐虏欔鵃ẫ廱࡝촋攻ẵ쀓靇䲿짿췁တ傿䁨铹诓迊鳪唉픇ퟹ❄▥?槏杦늣ᝰ闽푛퍔氺꓏頭跏ᬎ睸듊砌".toCharArray()[16] ^ 0x5554);
      throw new IllegalStateException(ˉﻤ$ͺſ.v("搐敭䢍?飚㗐虏欔鵃ẫ廱࡝촋攻ẵ쀓靇䲿짿췁တ傿䁨铹诓迊鳪唉픇ퟹ❄▥?槏杦늣ᝰ闽푛퍔氺꓏頭跏ᬎ睸듊砌".toCharArray(), (short)17039, 2, (short)5));
    } 
    this.ʿλ = true;
    super.ᐨẏ(paramString);
  }
  
  public final void ˊ(String paramString) {
    গ();
    "䶯좺촥큺륢ﲰ鲝ᶗᱮ芒໿".toCharArray()[0] = (char)("䶯좺촥큺륢ﲰ鲝ᶗᱮ芒໿".toCharArray()[0] ^ 0x508);
    ـｊ.ʹﮃ(this.ᔪ, paramString, ᐝᵣ$ﾞﾇ.j("䶯좺촥큺륢ﲰ鲝ᶗᱮ芒໿".toCharArray(), (short)31502, 5, (short)0));
    if (this.ʿλ) {
      "䗽澱醱ⲙ汮㧭➶碳푔ꉭऋ艞㯓⁶ⲉᇩ谛扛骻ࡺ겊临쥸Ὦ㎏볛㩈혡⯺쪨蠅綧㴞賰ﮀ璢㇮閑釜쾂࿏镭〬뽍緢찄룻하俘於硎〫䤍䓍?⟷䕘".toCharArray()[28] = (char)("䗽澱醱ⲙ汮㧭➶碳푔ꉭऋ艞㯓⁶ⲉᇩ谛扛骻ࡺ겊临쥸Ὦ㎏볛㩈혡⯺쪨蠅綧㴞賰ﮀ璢㇮閑釜쾂࿏镭〬뽍緢찄룻하俘於硎〫䤍䓍?⟷䕘".toCharArray()[28] ^ 0x5D1A);
      throw new IllegalStateException(ᐝᵣ$ﾞﾇ.j("䗽澱醱ⲙ汮㧭➶碳푔ꉭऋ艞㯓⁶ⲉᇩ谛扛骻ࡺ겊临쥸Ὦ㎏볛㩈혡⯺쪨蠅綧㴞賰ﮀ璢㇮閑釜쾂࿏镭〬뽍緢찄룻하俘於硎〫䤍䓍?⟷䕘".toCharArray(), (short)1801, 3, (short)5));
    } 
    int i;
    String str = ((i = (str = paramString).lastIndexOf('/')) == -1) ? "" : str.substring(0, i);
    if (this.ˏﾚ == null) {
      this.ˏﾚ = str;
    } else if (!this.ˏﾚ.equals(str)) {
      "錚㟤ѹ液춂睷䖠榱⥔趃엣ૃ".toCharArray()[8] = (char)("錚㟤ѹ液춂睷䖠榱⥔趃엣ૃ".toCharArray()[8] ^ 0x4250);
      "亘勞쭿桼釥✘뙔쵥梹㷷ꪹˑ偘鰭ၫ艬뫊⃔఺伾ﹱ㒍੶".toCharArray()[14] = (char)("亘勞쭿桼釥✘뙔쵥梹㷷ꪹˑ偘鰭ၫ艬뫊⃔఺伾ﹱ㒍੶".toCharArray()[14] ^ 0x49C9);
      throw new IllegalStateException(ᐝᵣ$ﾞﾇ.j("錚㟤ѹ液춂睷䖠榱⥔趃엣ૃ".toCharArray(), (short)10043, 4, (short)2) + paramString + ᐝᵣ$ﾞﾇ.j("亘勞쭿桼釥✘뙔쵥梹㷷ꪹˑ偘鰭ၫ艬뫊⃔఺伾ﹱ㒍੶".toCharArray(), (short)26771, 1, (short)0) + this.ˏﾚ);
    } 
    super.ˊ(paramString);
  }
  
  public final void ᴵʖ(String paramString) {
    গ();
    "濞記ⵈꕵ惘௽᪓휝簇祻㫈쿳㜣撠녨饺⻠".toCharArray()[3] = (char)("濞記ⵈꕵ惘௽᪓휝簇祻㫈쿳㜣撠녨饺⻠".toCharArray()[3] ^ 0x7BC7);
    ـｊ.ʹﮃ(this.ᔪ, paramString, ᐝᵣ$ﾞﾇ.j("濞記ⵈꕵ惘௽᪓휝簇祻㫈쿳㜣撠녨饺⻠".toCharArray(), (short)3528, 0, (short)1));
    super.ᴵʖ(paramString);
  }
  
  public final void ˊ(String paramString1, String paramString2, String paramString3) {
    গ();
    if (this.ᔪ) {
      "짞聠카珤ꡲ륟᳿ܼ摌铷ꍳꦊ秜ｪⓒ盓￻㿸ꦊ桃脯葺揀Ꮣ頢娤?ᨽ銌屧?꼕䕉죋姍︻劐⚗䶓勨滍".toCharArray()[12] = (char)("짞聠카珤ꡲ륟᳿ܼ摌铷ꍳꦊ秜ｪⓒ盓￻㿸ꦊ桃脯葺揀Ꮣ頢娤?ᨽ銌屧?꼕䕉죋姍︻劐⚗䶓勨滍".toCharArray()[12] ^ 0x3ABB);
      throw new IllegalStateException(ˏȓ$ᴵЃ.E("짞聠카珤ꡲ륟᳿ܼ摌铷ꍳꦊ秜ｪⓒ盓￻㿸ꦊ桃脯葺揀Ꮣ頢娤?ᨽ銌屧?꼕䕉죋姍︻劐⚗䶓勨滍".toCharArray(), (short)29393, (short)2, (short)1));
    } 
    this.ᔪ = true;
    if (paramString1 == null) {
      "숁誂铹〱莌ꀏ뺷ﷶᣑॠ鞈ᎁ⪭뢜ն뢐⍼ᡋЮ눠ﱽ뒒撬ퟓ悗".toCharArray()[11] = (char)("숁誂铹〱莌ꀏ뺷ﷶᣑॠ鞈ᎁ⪭뢜ն뢐⍼ᡋЮ눠ﱽ뒒撬ퟓ悗".toCharArray()[11] ^ 0x10BC);
      throw new IllegalArgumentException(ˏȓ$ᴵЃ.E("숁誂铹〱莌ꀏ뺷ﷶᣑॠ鞈ᎁ⪭뢜ն뢐⍼ᡋЮ눠ﱽ뒒撬ퟓ悗".toCharArray(), (short)25087, (short)3, (short)1));
    } 
    if (paramString3 != null)
      ـｊ.ʹﮃ(this.ᔪ, paramString3); 
    super.ˊ(paramString1, paramString2, paramString3);
  }
  
  public final void ᐨẏ(String paramString1, String paramString2, String paramString3, int paramInt) {
    গ();
    "?ﮗ䖧㖶六㰵봁둧ꅢ࣑".toCharArray()[5] = (char)("?ﮗ䖧㖶六㰵봁둧ꅢ࣑".toCharArray()[5] ^ 0xABA);
    ـｊ.ʹﮃ(this.ᔪ, paramString1, ˉﻤ$ͺſ.v("?ﮗ䖧㖶六㰵봁둧ꅢ࣑".toCharArray(), (short)24408, 0, (short)5));
    if (paramString2 != null) {
      "힑뼐얄䡩괫⾸눶糧퐥헴ஈ?Ꝫ깈♅".toCharArray()[9] = (char)("힑뼐얄䡩괫⾸눶糧퐥헴ஈ?Ꝫ깈♅".toCharArray()[9] ^ 0x7);
      ـｊ.ʹﮃ(this.ᔪ, paramString2, ˉﻤ$ͺſ.v("힑뼐얄䡩괫⾸눶糧퐥헴ஈ?Ꝫ깈♅".toCharArray(), (short)17337, 5, (short)1));
    } 
    if (paramString3 != null) {
      byte b;
      for (b = 0; b < paramString3.length() && Character.isDigit(paramString3.charAt(b)); b++);
      if (b == 0 || b < paramString3.length()) {
        "泼沫᠐ࣼ炸뱧ꋣ䜂螑萂컇抌?䉭썽愅Ɵ".toCharArray()[8] = (char)("泼沫᠐ࣼ炸뱧ꋣ䜂螑萂컇抌?䉭썽愅Ɵ".toCharArray()[8] ^ 0x2C34);
        ـｊ.ᐨẏ(this.ᔪ, paramString3, b, -1, ˉﻤ$ͺſ.v("泼沫᠐ࣼ炸뱧ꋣ䜂螑萂컇抌?䉭썽愅Ɵ".toCharArray(), (short)21152, 2, (short)2));
      } 
    } 
    ᐨم(paramInt, 30239);
    super.ᐨẏ(paramString1, paramString2, paramString3, paramInt);
  }
  
  public final ʼᵖ ᐨẏ(String paramString1, String paramString2, String paramString3) {
    গ();
    "ᩨ햋ႀ줡轟詆糽㫠象⇥蘬衴㷼䜐쐶릈㊋ꗳ䁹?㈡".toCharArray()[15] = (char)("ᩨ햋ႀ줡轟詆糽㫠象⇥蘬衴㷼䜐쐶릈㊋ꗳ䁹?㈡".toCharArray()[15] ^ 0x423);
    ـｊ.ﾞл(this.ᔪ, paramString1, ˉﻤ$ͺſ.v("ᩨ햋ႀ줡轟詆糽㫠象⇥蘬衴㷼䜐쐶릈㊋ꗳ䁹?㈡".toCharArray(), (short)22236, 2, (short)2));
    ـｊ.ᐨẏ(this.ᔪ, paramString2, false);
    if (paramString3 != null)
      ˍ(paramString3); 
    return new ʾˤ(this.ᐨẏ, super.ᐨẏ(paramString1, paramString2, paramString3));
  }
  
  public final ᴵƚ ᐨẏ(int paramInt, String paramString1, String paramString2, String paramString3, Object paramObject) {
    গ();
    ᐨم(paramInt, 184543);
    "﷋Ⲧꠌ刓伴皞䡦浣曡".toCharArray()[9] = (char)("﷋Ⲧꠌ刓伴皞䡦浣曡".toCharArray()[9] ^ 0x4CA2);
    ـｊ.ﾞл(this.ᔪ, paramString1, ˏȓ$ᴵЃ.E("﷋Ⲧꠌ刓伴皞䡦浣曡".toCharArray(), (short)10378, (short)0, (short)0));
    ـｊ.ᐨẏ(this.ᔪ, paramString2, false);
    if (paramString3 != null)
      ˍ(paramString3); 
    if (paramObject != null)
      ـｊ.ʽ(paramObject); 
    return new ٴǐ(this.ᐨẏ, super.ᐨẏ(paramInt, paramString1, paramString2, paramString3, paramObject));
  }
  
  public final ˉｓ ᐨẏ(int paramInt, String paramString1, String paramString2, String paramString3, String[] paramArrayOfString) {
    ـｊ ـｊ;
    গ();
    int i = 171519;
    int j = paramInt;
    boolean bool = this.ᔪ;
    ᐨم(j, 171519);
    if ((bool & 0xFFFF) < 61 && Integer.bitCount(j & 0xC00) > 1) {
      "疠阤ᄠ垄큁?璓涁饑繘ԣ땚뤛峅捐圳㰃棂䩜핞䀚㦗炡桚㉮웡쟡ᛃଘ䑉哩㧽ᩨ䩼㯉磂?㼡쀎낅畊".toCharArray()[26] = (char)("疠阤ᄠ垄큁?璓涁饑繘ԣ땚뤛峅捐圳㰃棂䩜핞䀚㦗炡桚㉮웡쟡ᛃଘ䑉哩㧽ᩨ䩼㯉磂?㼡쀎낅畊".toCharArray()[26] ^ 0x4A64);
      throw new IllegalArgumentException(ˍɫ$יς.J("疠阤ᄠ垄큁?璓涁饑繘ԣ땚뤛峅捐圳㰃棂䩜핞䀚㦗炡桚㉮웡쟡ᛃଘ䑉哩㧽ᩨ䩼㯉磂?㼡쀎낅畊".toCharArray(), (short)12180, (short)0, (byte)5) + j);
    } 
    "ᄏㄏ鎝Ꮁㆴ匯ᘼ".toCharArray()[0] = (char)("ᄏㄏ鎝Ꮁㆴ匯ᘼ".toCharArray()[0] ^ 0x347F);
    "剗﮴稏ೃ跗鞉ᙧᷥઘ".toCharArray()[2] = (char)("剗﮴稏ೃ跗鞉ᙧᷥઘ".toCharArray()[2] ^ 0x3CE0);
    if (!ˍɫ$יς.J("ᄏㄏ鎝Ꮁㆴ匯ᘼ".toCharArray(), (short)13884, (short)0, (byte)1).equals(paramString1) && !ˍɫ$יς.J("剗﮴稏ೃ跗鞉ᙧᷥઘ".toCharArray(), (short)31672, (short)5, (byte)5).equals(paramString1)) {
      "⢈徦繥⇤闿妹ꑓ뽉᣺૱".toCharArray()[8] = (char)("⢈徦繥⇤闿妹ꑓ뽉᣺૱".toCharArray()[8] ^ 0x3CE4);
      ـｊ.ʿᵉ(this.ᔪ, paramString1, ˍɫ$יς.J("⢈徦繥⇤闿妹ꑓ뽉᣺૱".toCharArray(), (short)17586, (short)4, (byte)1));
    } 
    ـｊ.ʹﮃ(this.ᔪ, paramString2);
    if (paramString3 != null)
      ˌ(paramString3); 
    if (paramArrayOfString != null)
      for (bool = false; bool < paramArrayOfString.length; bool++) {
        "?胇䍬瓂ౙ떪ᛱ㺊蟟涥圂茟᫦ꃲꌾ⯈㒠擄ۈ︨訕벾쳁ꐻ⋿".toCharArray()[20] = (char)("?胇䍬瓂ౙ떪ᛱ㺊蟟涥圂茟᫦ꃲꌾ⯈㒠擄ۈ︨訕벾쳁ꐻ⋿".toCharArray()[20] ^ 0x25EF);
        ـｊ.ʹﮃ(this.ᔪ, paramArrayOfString[bool], ˍɫ$יς.J("?胇䍬瓂ౙ떪ᛱ㺊蟟涥圂茟᫦ꃲꌾ⯈㒠擄ۈ︨訕벾쳁ꐻ⋿".toCharArray(), (short)7822, (short)2, (byte)0) + bool);
      }  
    ˉｓ ˉｓ = super.ᐨẏ(paramInt, paramString1, paramString2, paramString3, paramArrayOfString);
    if (this.ˌ) {
      if (this.ᐨẏ instanceof ʽ)
        ˉｓ = new ـﾚ(this.ᐨẏ, this.ᔪ, (ʽ)this.ᐨẏ, ˉｓ); 
      ـｊ = new ـｊ(this.ᐨẏ, paramInt, paramString1, paramString2, ˉｓ, this.ʽ);
    } else {
      ـｊ = new ـｊ(this.ᐨẏ, ˉｓ, this.ʽ);
    } 
    ـｊ.ᔪ = this.ᔪ;
    return ـｊ;
  }
  
  public final ᐨẏ ᐨẏ(String paramString, boolean paramBoolean) {
    গ();
    ـｊ.ᐨẏ(this.ᔪ, paramString, false);
    return new ͺᖽ(super.ᐨẏ(paramString, paramBoolean));
  }
  
  public final ᐨẏ ᐨẏ(int paramInt, ˏɪ paramˏɪ, String paramString, boolean paramBoolean) {
    গ();
    int i;
    if ((i = (new ʾเ(paramInt)).ˉｓ()) != 0 && i != 17 && i != 16) {
      "袳ﳛ♣獶씶髁廦ﮤᄞﴀ㡕￷짫䴭刵拮褥㌐у臬䳻矜怏☢ৃ웳᱿곹脎맇ԃ".toCharArray()[22] = (char)("袳ﳛ♣獶씶髁廦ﮤᄞﴀ㡕￷짫䴭刵拮褥㌐у臬䳻矜怏☢ৃ웳᱿곹脎맇ԃ".toCharArray()[22] ^ 0x4575);
      throw new IllegalArgumentException(ᐨẏ$ᐝт.W("袳ﳛ♣獶씶髁廦ﮤᄞﴀ㡕￷짫䴭刵拮褥㌐у臬䳻矜怏☢ৃ웳᱿곹脎맇ԃ".toCharArray(), (short)31775, (byte)4, (short)3) + Integer.toHexString(i));
    } 
    ʹō(paramInt);
    ـｊ.ᐨẏ(this.ᔪ, paramString, false);
    return new ͺᖽ(super.ᐨẏ(paramInt, paramˏɪ, paramString, paramBoolean));
  }
  
  public final void ᴵʖ(ᴵʖ paramᴵʖ) {
    গ();
    if (paramᴵʖ == null) {
      "텑硐㽤꓆Ჩ뭱⢞관麓諌䖋춝䮳㄃봧̵໤읪ᅢ䃱췤놪돧珚睘粥졆캅齹䳑れ棩".toCharArray()[32] = (char)("텑硐㽤꓆Ჩ뭱⢞관麓諌䖋춝䮳㄃봧̵໤읪ᅢ䃱췤놪돧珚睘粥졆캅齹䳑れ棩".toCharArray()[32] ^ 0x3AC7);
      throw new IllegalArgumentException(ˉﻤ$ͺſ.v("텑硐㽤꓆Ჩ뭱⢞관麓諌䖋춝䮳㄃봧̵໤읪ᅢ䃱췤놪돧珚睘粥졆캅齹䳑れ棩".toCharArray(), (short)13594, 4, (short)3));
    } 
    super.ᴵʖ(paramᴵʖ);
  }
  
  public final void ᐨẏ() {
    গ();
    this.ᴵƚ = true;
    super.ᐨẏ();
  }
  
  private void গ() {
    if (!this.ˍ) {
      "난ᕮ䰮튒빌㝴眍Ӊࣟ?ꡕ펱䢻᷾섽䯈ᔞ埓曹⚛穲竵餯钹鑚系쇈̬皬㤽帉烚몱窛√鉂䱮ꏮ㩸ᰵ愂郂ꃖҀ?稒".toCharArray()[1] = (char)("난ᕮ䰮튒빌㝴眍Ӊࣟ?ꡕ펱䢻᷾섽䯈ᔞ埓曹⚛穲竵餯钹鑚系쇈̬皬㤽帉烚몱窛√鉂䱮ꏮ㩸ᰵ愂郂ꃖҀ?稒".toCharArray()[1] ^ 0x364C);
      throw new IllegalStateException(ᐝᵣ$ﾞﾇ.j("난ᕮ䰮튒빌㝴眍Ӊࣟ?ꡕ펱䢻᷾섽䯈ᔞ埓曹⚛穲竵餯钹鑚系쇈̬皬㤽帉烚몱窛√鉂䱮ꏮ㩸ᰵ愂郂ꃖҀ?稒".toCharArray(), (short)7475, 3, (short)1));
    } 
    if (this.ᴵƚ) {
      "萢滇㮞ᢡ䵵榻줌髣넄녎ﶷࣥƳ쳭࿌䡷媮ꭟ뀽渂௏䖷䣿䒒ᇹ율ֻ?椟텉ڍ꤀쯍型叡ѭহ芯ꖙṬ䶝莵倘湍ꇘᙑ㑟".toCharArray()[14] = (char)("萢滇㮞ᢡ䵵榻줌髣넄녎ﶷࣥƳ쳭࿌䡷媮ꭟ뀽渂௏䖷䣿䒒ᇹ율ֻ?椟텉ڍ꤀쯍型叡ѭহ芯ꖙṬ䶝莵倘湍ꇘᙑ㑟".toCharArray()[14] ^ 0x6D79);
      throw new IllegalStateException(ᐝᵣ$ﾞﾇ.j("萢滇㮞ᢡ䵵榻줌髣넄녎ﶷࣥƳ쳭࿌䡷媮ꭟ뀽渂௏䖷䣿䒒ᇹ율ֻ?椟텉ڍ꤀쯍型叡ѭহ芯ꖙṬ䶝莵倘湍ꇘᙑ㑟".toCharArray(), (short)22163, 5, (short)2));
    } 
  }
  
  static void ᐨم(int paramInt1, int paramInt2) {
    if ((paramInt1 & (paramInt2 ^ 0xFFFFFFFF)) != 0) {
      "㦝汀鉔缡垹줵盁ૌ捥洙ტҢⱍꁁ赪걻ኃ釠劫휊녷㷿".toCharArray()[2] = (char)("㦝汀鉔缡垹줵盁ૌ捥洙ტҢⱍꁁ赪걻ኃ釠劫휊녷㷿".toCharArray()[2] ^ 0x3F93);
      throw new IllegalArgumentException(ˏȓ$ᴵЃ.E("㦝汀鉔缡垹줵盁ૌ捥洙ტҢⱍꁁ赪걻ኃ釠劫휊녷㷿".toCharArray(), (short)9093, (short)1, (short)2) + paramInt1);
    } 
    if (Integer.bitCount(paramInt1 & 0x7) > 1) {
      "铟ᠫ얈痱㼰䋍?矋⃏ꕙ랢䥂煉窞鮀䳺ࣙ⛻ﶜ잤ᬆ炴뽵胲蘿惉鳄렕ꆷ즨⣂䊚?䈜歹??挩ꂞฌ?䔗淎墪㺍ﵝʿᬡ畿ᓈ".toCharArray()[34] = (char)("铟ᠫ얈痱㼰䋍?矋⃏ꕙ랢䥂煉窞鮀䳺ࣙ⛻ﶜ잤ᬆ炴뽵胲蘿惉鳄렕ꆷ즨⣂䊚?䈜歹??挩ꂞฌ?䔗淎墪㺍ﵝʿᬡ畿ᓈ".toCharArray()[34] ^ 0x5010);
      throw new IllegalArgumentException(ˏȓ$ᴵЃ.E("铟ᠫ얈痱㼰䋍?矋⃏ꕙ랢䥂煉窞鮀䳺ࣙ⛻ﶜ잤ᬆ炴뽵胲蘿惉鳄렕ꆷ즨⣂䊚?䈜歹??挩ꂞฌ?䔗淎墪㺍ﵝʿᬡ畿ᓈ".toCharArray(), (short)4468, (short)2, (short)4) + paramInt1);
    } 
    if (Integer.bitCount(paramInt1 & 0x410) > 1) {
      "媁晁쫷鎐猖뇌馤澅浸㲆쌼犡醅੤ᶠФퟨ낞꜈⏳㐡ᯍ肈먍멎骽朗ʖ窱쁩ហꏆౕ꾧薰ꞇ藽照⴬".toCharArray()[11] = (char)("媁晁쫷鎐猖뇌馤澅浸㲆쌼犡醅੤ᶠФퟨ낞꜈⏳㐡ᯍ肈먍멎骽朗ʖ窱쁩ហꏆౕ꾧薰ꞇ藽照⴬".toCharArray()[11] ^ 0x7427);
      throw new IllegalArgumentException(ˏȓ$ᴵЃ.E("媁晁쫷鎐猖뇌馤澅浸㲆쌼犡醅੤ᶠФퟨ낞꜈⏳㐡ᯍ肈먍멎骽朗ʖ窱쁩ហꏆౕ꾧薰ꞇ藽照⴬".toCharArray(), (short)21906, (short)5, (short)3) + paramInt1);
    } 
  }
  
  private static void ᴵʖ(int paramInt1, int paramInt2, int paramInt3) {
    ᐨم(paramInt2, 171519);
    if ((paramInt1 & 0xFFFF) < 61 && Integer.bitCount(paramInt2 & 0xC00) > 1) {
      "ꑺ鎢岛쫌唑얂ᙔ浢勱ꊦ켯?䖴㙼莱켿毜ﭖ蘶셴슚諐ᇙ叢䝹ꑇ輑鮛朮₷삠種嘸瘣㸢䢼땢鈲魺輴䝅".toCharArray()[10] = (char)("ꑺ鎢岛쫌唑얂ᙔ浢勱ꊦ켯?䖴㙼莱켿毜ﭖ蘶셴슚諐ᇙ叢䝹ꑇ輑鮛朮₷삠種嘸瘣㸢䢼땢鈲魺輴䝅".toCharArray()[10] ^ 0x5EA);
      throw new IllegalArgumentException(ˉﻤ$ͺſ.v("ꑺ鎢岛쫌唑얂ᙔ浢勱ꊦ켯?䖴㙼莱켿毜ﭖ蘶셴슚諐ᇙ叢䝹ꑇ輑鮛朮₷삠種嘸瘣㸢䢼땢鈲魺輴䝅".toCharArray(), (short)30437, 2, (short)0) + paramInt2);
    } 
  }
  
  static void ᴵʖ(int paramInt, String paramString1, String paramString2) {
    try {
      int i;
      int j;
      for (i = 0; (j = paramString1.indexOf('.', i + 1)) != -1; i = j + 1)
        ـｊ.ᐨẏ(paramInt, paramString1, i, j, (String)null); 
      ـｊ.ᐨẏ(paramInt, paramString1, i, paramString1.length(), (String)null);
      return;
    } catch (IllegalArgumentException illegalArgumentException) {
      "嬉⤹ᑠ돸໷࿆圞䦵".toCharArray()[7] = (char)("嬉⤹ᑠ돸໷࿆圞䦵".toCharArray()[7] ^ 0x4505);
      "굌?綨﷒壅皗鋓Û뙉寙뽛㓭뱾Ṕ該매땙㒸䗢ㅲ鄚⋸??ۣ䈋锰尒₡ᐆ?ꣷη".toCharArray()[5] = (char)("굌?綨﷒壅皗鋓Û뙉寙뽛㓭뱾Ṕ該매땙㒸䗢ㅲ鄚⋸??ۣ䈋锰尒₡ᐆ?ꣷη".toCharArray()[5] ^ 0x34CC);
      throw new IllegalArgumentException(ˉﻤ$ͺſ.v("嬉⤹ᑠ돸໷࿆圞䦵".toCharArray(), (short)6899, 1, (short)3) + paramString2 + ˉﻤ$ͺſ.v("굌?綨﷒壅皗鋓Û뙉寙뽛㓭뱾Ṕ該매땙㒸䗢ㅲ鄚⋸??ۣ䈋锰尒₡ᐆ?ꣷη".toCharArray(), (short)4834, 4, (short)0) + paramString1, illegalArgumentException);
    } 
  }
  
  private static void ᴵƚ(String paramString) {
    int i = 0;
    if (ᐨẏ(paramString, 0) == '<')
      i = ˊ(paramString, 0); 
    while (true) {
      i = ʿᵉ(paramString, i);
      if (ᐨẏ(paramString, i) != 'L') {
        if (i != paramString.length()) {
          "蝯✝論?䖄匰◳嚉黓견⛎࣠福ꃄ酷⯠".toCharArray()[3] = (char)("蝯✝論?䖄匰◳嚉黓견⛎࣠福ꃄ酷⯠".toCharArray()[3] ^ 0x1FAB);
          throw new IllegalArgumentException(paramString + ˉﻤ$ͺſ.v("蝯✝論?䖄匰◳嚉黓견⛎࣠福ꃄ酷⯠".toCharArray(), (short)16356, 2, (short)2).intern() + i);
        } 
        return;
      } 
    } 
  }
  
  private static void ˌ(String paramString) {
    int i = 0;
    if (ᐨẏ(paramString, 0) == '<')
      i = ˊ(paramString, 0); 
    i = ᐨẏ('(', paramString, i);
    "荹센⠉┛ꤺ捳戡㲋淳貨^".toCharArray()[2] = (char)("荹센⠉┛ꤺ捳戡㲋淳貨^".toCharArray()[2] ^ 0x18A6);
    while (ˉﻤ$ͺſ.v("荹센⠉┛ꤺ捳戡㲋淳貨^".toCharArray(), (short)27608, 0, (short)4).indexOf(ᐨẏ(paramString, i)) != -1)
      i = ʽ(paramString, i); 
    i = ᐨẏ(')', paramString, i);
    if (ᐨẏ(paramString, i) == 'V') {
      i++;
    } else {
      i = ʽ(paramString, i);
    } 
    while (ᐨẏ(paramString, i) == '^') {
      if (ᐨẏ(paramString, ++i) == 'L') {
        i = ʿᵉ(paramString, i);
        continue;
      } 
      i = ˍɫ(paramString, i);
    } 
    if (i != paramString.length()) {
      "⠑骊䷾?됂輡ⱖ儇䎃浖訑鹗촂䌈එႉ峼".toCharArray()[15] = (char)("⠑骊䷾?됂輡ⱖ儇䎃浖訑鹗촂䌈එႉ峼".toCharArray()[15] ^ 0x5E21);
      throw new IllegalArgumentException(paramString + ˉﻤ$ͺſ.v("⠑骊䷾?됂輡ⱖ儇䎃浖訑鹗촂䌈එႉ峼".toCharArray(), (short)27555, 4, (short)1).intern() + i);
    } 
  }
  
  public static void ˍ(String paramString) {
    int i;
    if ((i = ﾞл(paramString, 0)) != paramString.length()) {
      "㮗돞僬技ꓢ켆?斋츛蛮ꝗ¼".toCharArray()[1] = (char)("㮗돞僬技ꓢ켆?斋츛蛮ꝗ¼".toCharArray()[1] ^ 0x43A5);
      throw new IllegalArgumentException(paramString + ˍɫ$יς.J("㮗돞僬技ꓢ켆?斋츛蛮ꝗ¼".toCharArray(), (short)13161, (short)1, (byte)4).intern() + i);
    } 
  }
  
  private static int ˊ(String paramString, int paramInt) {
    paramInt = ᐨẏ('<', paramString, 0);
    for (paramInt = ᴵʖ(paramString, paramInt); ᐨẏ(paramString, paramInt) != '>'; paramInt = ᴵʖ(paramString, paramInt));
    return paramInt + 1;
  }
  
  private static int ᴵʖ(String paramString, int paramInt) {
    paramInt = paramInt;
    paramInt = ʾܪ(paramString, paramInt);
    paramInt = ᐨẏ(':', paramString, paramInt);
    "눤㋧ᚳᮻ".toCharArray()[2] = (char)("눤㋧ᚳᮻ".toCharArray()[2] ^ 0xFD8);
    if (ᐨẏ$ᐝт.W("눤㋧ᚳᮻ".toCharArray(), (short)4973, (byte)5, (short)2).indexOf(ᐨẏ(paramString, paramInt)) != -1)
      paramInt = ﾞл(paramString, paramInt); 
    while (ᐨẏ(paramString, paramInt) == ':')
      paramInt = ﾞл(paramString, paramInt + 1); 
    return paramInt;
  }
  
  private static int ﾞл(String paramString, int paramInt) {
    switch (ᐨẏ(paramString, paramInt)) {
      case 'L':
        return ʿᵉ(paramString, paramInt);
      case '[':
        return ʽ(paramString, paramInt + 1);
    } 
    return ˍɫ(paramString, paramInt);
  }
  
  private static int ʿᵉ(String paramString, int paramInt) {
    paramInt = paramInt;
    paramInt = ᐨẏ('L', paramString, paramInt);
    for (paramInt = ʾܪ(paramString, paramInt); ᐨẏ(paramString, paramInt) == '/'; paramInt = ʾܪ(paramString, paramInt + 1));
    if (ᐨẏ(paramString, paramInt) == '<')
      paramInt = ʹﮃ(paramString, paramInt); 
    while (ᐨẏ(paramString, paramInt) == '.') {
      paramInt = ʾܪ(paramString, paramInt + 1);
      if (ᐨẏ(paramString, paramInt) == '<')
        paramInt = ʹﮃ(paramString, paramInt); 
    } 
    return ᐨẏ(';', paramString, paramInt);
  }
  
  private static int ʹﮃ(String paramString, int paramInt) {
    paramInt = paramInt;
    paramInt = ᐨẏ('<', paramString, paramInt);
    for (paramInt = ՙᗮ(paramString, paramInt); ᐨẏ(paramString, paramInt) != '>'; paramInt = ՙᗮ(paramString, paramInt));
    return paramInt + 1;
  }
  
  private static int ՙᗮ(String paramString, int paramInt) {
    paramInt = paramInt;
    char c;
    if ((c = ᐨẏ(paramString, paramInt)) == '*')
      return paramInt + 1; 
    if (c == '+' || c == '-')
      paramInt++; 
    return ﾞл(paramString, paramInt);
  }
  
  private static int ˍɫ(String paramString, int paramInt) {
    paramInt = paramInt;
    paramInt = ᐨẏ('T', paramString, paramInt);
    paramInt = ʾܪ(paramString, paramInt);
    return ᐨẏ(';', paramString, paramInt);
  }
  
  private static int ʽ(String paramString, int paramInt) {
    paramInt = paramInt;
    switch (ᐨẏ(paramString, paramInt)) {
      case 'B':
      case 'C':
      case 'D':
      case 'F':
      case 'I':
      case 'J':
      case 'S':
      case 'Z':
        return paramInt + 1;
    } 
    return ﾞл(paramString, paramInt);
  }
  
  private static int ʾܪ(String paramString, int paramInt) {
    int i = paramInt;
    "葒籟ኈ፴岰ꐶ嚅㸋".toCharArray()[0] = (char)("葒籟ኈ፴岰ꐶ嚅㸋".toCharArray()[0] ^ 0x2A82);
    while (i < paramString.length() && ˉﻤ$ͺſ.v("葒籟ኈ፴岰ꐶ嚅㸋".toCharArray(), (short)22262, 4, (short)2).indexOf(paramString.codePointAt(i)) == -1)
      i = paramString.offsetByCodePoints(i, 1); 
    if (i == paramInt) {
      "⢇ᢼ⤾皸榘囐眭??鶅缻ଛܫ㱁䣉ൔ麁⹦ᓗ䑯귅跱茐﷓몥敏亨".toCharArray()[27] = (char)("⢇ᢼ⤾皸榘囐眭??鶅缻ଛܫ㱁䣉ൔ麁⹦ᓗ䑯귅跱茐﷓몥敏亨".toCharArray()[27] ^ 0x6572);
      throw new IllegalArgumentException(paramString + ˉﻤ$ͺſ.v("⢇ᢼ⤾皸榘囐眭??鶅缻ଛܫ㱁䣉ൔ麁⹦ᓗ䑯귅跱茐﷓몥敏亨".toCharArray(), (short)30862, 1, (short)4) + paramInt);
    } 
    return i;
  }
  
  private static int ᐨẏ(char paramChar, String paramString, int paramInt) {
    if (ᐨẏ(paramString, paramInt) == paramChar)
      return paramInt + 1; 
    "⬦?揙".toCharArray()[1] = (char)("⬦?揙".toCharArray()[1] ^ 0x4427);
    "굞㠮࿑㒪⥧鴑아ၨ⎽颲陴ᷭ］犗메땻ﾞ岽".toCharArray()[7] = (char)("굞㠮࿑㒪⥧鴑아ၨ⎽颲陴ᷭ］犗메땻ﾞ岽".toCharArray()[7] ^ 0x467B);
    throw new IllegalArgumentException(paramString + ˏȓ$ᴵЃ.E("⬦?揙".toCharArray(), (short)13896, (short)2, (short)2) + paramChar + ˏȓ$ᴵЃ.E("굞㠮࿑㒪⥧鴑아ၨ⎽颲陴ᷭ］犗메땻ﾞ岽".toCharArray(), (short)22717, (short)3, (short)5) + paramInt);
  }
  
  private static char ᐨẏ(String paramString, int paramInt) {
    return (paramInt < paramString.length()) ? paramString.charAt(paramInt) : Character.MIN_VALUE;
  }
  
  static void ʹō(int paramInt) {
    int i = 0;
    switch (paramInt >>> 24) {
      case 0:
      case 1:
      case 22:
        i = -65536;
        break;
      case 19:
      case 20:
      case 21:
      case 64:
      case 65:
      case 67:
      case 68:
      case 69:
      case 70:
        i = -16777216;
        break;
      case 16:
      case 17:
      case 18:
      case 23:
      case 66:
        i = -256;
        break;
      case 71:
      case 72:
      case 73:
      case 74:
      case 75:
        i = -16776961;
        break;
    } 
    if (i == 0 || (paramInt & (i ^ 0xFFFFFFFF)) != 0) {
      "Ǜ戀泋鶜쓩訾㴡ꃳ椛횙䪂♭᧌ઃ飢龄覐㭹?芆̱ꅥ萡偟".toCharArray()[21] = (char)("Ǜ戀泋鶜쓩訾㴡ꃳ椛횙䪂♭᧌ઃ飢龄覐㭹?芆̱ꅥ萡偟".toCharArray()[21] ^ 0x1FB8);
      throw new IllegalArgumentException(ˍɫ$יς.J("Ǜ戀泋鶜쓩訾㴡ꃳ椛횙䪂♭᧌ઃ飢龄覐㭹?芆̱ꅥ萡偟".toCharArray(), (short)14967, (short)2, (byte)5) + Integer.toHexString(paramInt));
    } 
  }
  
  private static String ʽ(String paramString) {
    int i;
    return ((i = paramString.lastIndexOf('/')) == -1) ? "" : paramString.substring(0, i);
  }
  
  private static void main(String[] paramArrayOfString) {
    ᐨم ᐨم2;
    PrintWriter printWriter = new PrintWriter(System.err, true);
    if ((paramArrayOfString = paramArrayOfString).length != 1) {
      "娥⦨악䒿磨襡뿌齷⸞㉲⬄빘髙?翺ᾼ蹹뻆?屯ꁴ䌳栾ꉣ콎蔀竘慂㉽᷶斦닪㿘酢䱙⇰탋㡇臯謉欖磰鵞Ꞙ?彍?舢혔⃺ᰍ쏸祵ꇥ午晴縺㸶䩃ⳕ醊ଳ㞆?ᚶ䶬⦂䬡⃤㸨驜⦚ၳ葲⎟揆涑厱銅줚釅﹠쓰䱌泂苡㴟".toCharArray()[75] = (char)("娥⦨악䒿磨襡뿌齷⸞㉲⬄빘髙?翺ᾼ蹹뻆?屯ꁴ䌳栾ꉣ콎蔀竘慂㉽᷶斦닪㿘酢䱙⇰탋㡇臯謉欖磰鵞Ꞙ?彍?舢혔⃺ᰍ쏸祵ꇥ午晴縺㸶䩃ⳕ醊ଳ㞆?ᚶ䶬⦂䬡⃤㸨驜⦚ၳ葲⎟揆涑厱銅줚釅﹠쓰䱌泂苡㴟".toCharArray()[75] ^ 0x2D8F);
      printWriter.println(ᐝᵣ$ﾞﾇ.j("娥⦨악䒿磨襡뿌齷⸞㉲⬄빘髙?翺ᾼ蹹뻆?屯ꁴ䌳栾ꉣ콎蔀竘慂㉽᷶斦닪㿘酢䱙⇰탋㡇臯謉欖磰鵞Ꞙ?彍?舢혔⃺ᰍ쏸祵ꇥ午晴縺㸶䩃ⳕ醊ଳ㞆?ᚶ䶬⦂䬡⃤㸨驜⦚ၳ葲⎟揆涑厱銅줚釅﹠쓰䱌泂苡㴟".toCharArray(), (short)5781, 5, (short)5).intern());
      return;
    } 
    "⢝ꈯ?젚﷭䵝㎧".toCharArray()[2] = (char)("⢝ꈯ?젚﷭䵝㎧".toCharArray()[2] ^ 0x6AE8);
    if (paramArrayOfString[0].endsWith(ᐝᵣ$ﾞﾇ.j("⢝ꈯ?젚﷭䵝㎧".toCharArray(), (short)17676, 4, (short)5))) {
      FileInputStream fileInputStream = new FileInputStream(paramArrayOfString[0]);
      try {
        ᐨم2 = new ᐨم(fileInputStream);
        fileInputStream.close();
      } catch (Throwable throwable1) {
        try {
          fileInputStream.close();
        } catch (Throwable throwable2) {
          throwable1.addSuppressed(throwable2);
        } 
        throw throwable1;
      } 
    } else {
      ᐨم2 = new ᐨم((String)throwable1[0]);
    } 
    throwable2 = throwable2;
    boolean bool = false;
    ᐨم ᐨم1;
    ᐨẏ(ᐨم1 = ᐨم2, (ClassLoader)null, false, (PrintWriter)throwable2);
  }
  
  private static void ᐨẏ(String[] paramArrayOfString, PrintWriter paramPrintWriter) {
    ᐨم ᐨم;
    if (paramArrayOfString.length != 1) {
      "톏夽戽ᨗњ葍ಬᖼ鞏伒夼䆐岦휲웟?岆븱钆趯ẗ?＝?அﲒ　ꃴ㣇ሶᡫ톔臜ᖘℰ⒀ね㽤⊗畔?ᦡ㗝蒚ꮎ喧成滆䰉✎鏳?ታ牲䆠祼裠㊿捈袅ႊ佧빓۸켸᪯㥔㩇?뱶Ꜭਥ뛝ꨩ阤麭畮㾵鬣㓔蕽䥮䱸긗쟧뼘돇춚ᕁ".toCharArray()[79] = (char)("톏夽戽ᨗњ葍ಬᖼ鞏伒夼䆐岦휲웟?岆븱钆趯ẗ?＝?அﲒ　ꃴ㣇ሶᡫ톔臜ᖘℰ⒀ね㽤⊗畔?ᦡ㗝蒚ꮎ喧成滆䰉✎鏳?ታ牲䆠祼裠㊿捈袅ႊ佧빓۸켸᪯㥔㩇?뱶Ꜭਥ뛝ꨩ阤麭畮㾵鬣㓔蕽䥮䱸긗쟧뼘돇춚ᕁ".toCharArray()[79] ^ 0x62A2);
      paramPrintWriter.println(ᐨẏ$ᐝт.W("톏夽戽ᨗњ葍ಬᖼ鞏伒夼䆐岦휲웟?岆븱钆趯ẗ?＝?அﲒ　ꃴ㣇ሶᡫ톔臜ᖘℰ⒀ね㽤⊗畔?ᦡ㗝蒚ꮎ喧成滆䰉✎鏳?ታ牲䆠祼裠㊿捈袅ႊ佧빓۸켸᪯㥔㩇?뱶Ꜭਥ뛝ꨩ阤麭畮㾵鬣㓔蕽䥮䱸긗쟧뼘돇춚ᕁ".toCharArray(), (short)26918, (byte)2, (short)2).intern());
      return;
    } 
    "䲤ꨵ꣥颡엜ರ".toCharArray()[4] = (char)("䲤ꨵ꣥颡엜ರ".toCharArray()[4] ^ 0x755E);
    if (paramArrayOfString[0].endsWith(ᐨẏ$ᐝт.W("䲤ꨵ꣥颡엜ರ".toCharArray(), (short)22226, (byte)1, (short)5))) {
      FileInputStream fileInputStream = new FileInputStream(paramArrayOfString[0]);
      try {
        ᐨم = new ᐨم(fileInputStream);
        fileInputStream.close();
      } catch (Throwable throwable1) {
        try {
          fileInputStream.close();
        } catch (Throwable throwable2) {
          throwable1.addSuppressed(throwable2);
        } 
        throw throwable1;
      } 
    } else {
      ᐨم = new ᐨم((String)throwable1[0]);
    } 
    ᐨẏ(ᐨم, false, (PrintWriter)throwable2);
  }
  
  private static void ᐨẏ(ᐨم paramᐨم, boolean paramBoolean, PrintWriter paramPrintWriter) {
    ᐨẏ(paramᐨم, (ClassLoader)null, false, paramPrintWriter);
  }
  
  private static void ᐨẏ(ᐨم paramᐨم, ClassLoader paramClassLoader, boolean paramBoolean, PrintWriter paramPrintWriter) {
    ᵘ ᵘ = new ᵘ();
    paramᐨم.ᐨẏ(new ˊں(17432576, ᵘ, false), 2);
    ˑܘ ˑܘ = (ᵘ.ʼᐡ == null) ? null : ˑܘ.ˊ(ᵘ.ʼᐡ);
    List<ᐧє> list = ᵘ.ᔪ;
    ArrayList<ˑܘ> arrayList = new ArrayList();
    for (String str : ᵘ.ᐨم)
      arrayList.add(ˑܘ.ˊ(str)); 
    for (ᐧє ᐧє : list) {
      ﻥ ﻥ = new ﻥ(ˑܘ.ˊ(ᵘ.name), ˑܘ, arrayList, ((ᵘ.ᒬ & 0x200) != 0));
      ιᒶ<ן> ιᒶ = new ιᒶ<>(ﻥ);
      if (paramClassLoader != null) {
        ClassLoader classLoader = paramClassLoader;
        (ﻥ = ﻥ).ᐨẏ = classLoader;
      } 
      try {
        ιᒶ.ᐨẏ(ᵘ.name, ᐧє);
      } catch (ιƚ ιƚ) {
        (ﻥ = null).printStackTrace(paramPrintWriter);
      } 
      if (paramBoolean)
        ᐨẏ(ᐧє, (ιᒶ)ιᒶ, paramPrintWriter); 
    } 
    paramPrintWriter.flush();
  }
  
  static void ᐨẏ(ᐧє paramᐧє, ιᒶ<ﹳه> paramιᒶ, PrintWriter paramPrintWriter) {
    // Byte code:
    //   0: new yyds/sniarbtej/ძ
    //   3: dup
    //   4: invokespecial <init> : ()V
    //   7: astore_3
    //   8: new yyds/sniarbtej/丶
    //   11: dup
    //   12: aload_3
    //   13: invokespecial <init> : (Lyyds/sniarbtej/ᐨᘂ;)V
    //   16: astore #4
    //   18: aload_2
    //   19: new java/lang/StringBuilder
    //   22: dup
    //   23: invokespecial <init> : ()V
    //   26: aload_0
    //   27: getfield name : Ljava/lang/String;
    //   30: invokevirtual append : (Ljava/lang/String;)Ljava/lang/StringBuilder;
    //   33: aload_0
    //   34: getfield ˎᴗ : Ljava/lang/String;
    //   37: invokevirtual append : (Ljava/lang/String;)Ljava/lang/StringBuilder;
    //   40: invokevirtual toString : ()Ljava/lang/String;
    //   43: invokevirtual println : (Ljava/lang/String;)V
    //   46: iconst_0
    //   47: istore #5
    //   49: iload #5
    //   51: aload_0
    //   52: getfield ˊ : Lyyds/sniarbtej/ـс;
    //   55: dup
    //   56: astore #9
    //   58: getfield ʿᵉ : I
    //   61: if_icmpge -> 391
    //   64: aload_0
    //   65: getfield ˊ : Lyyds/sniarbtej/ـс;
    //   68: iload #5
    //   70: invokevirtual ᐨẏ : (I)Lyyds/sniarbtej/Ӏ;
    //   73: aload #4
    //   75: invokevirtual ᐨẏ : (Lyyds/sniarbtej/ˉｓ;)V
    //   78: new java/lang/StringBuilder
    //   81: dup
    //   82: invokespecial <init> : ()V
    //   85: astore #6
    //   87: aload_1
    //   88: dup
    //   89: astore #9
    //   91: getfield ᐨẏ : [Lyyds/sniarbtej/ιՆ;
    //   94: iload #5
    //   96: aaload
    //   97: dup
    //   98: astore #7
    //   100: ifnonnull -> 114
    //   103: aload #6
    //   105: bipush #63
    //   107: invokevirtual append : (C)Ljava/lang/StringBuilder;
    //   110: pop
    //   111: goto -> 243
    //   114: iconst_0
    //   115: istore #8
    //   117: iload #8
    //   119: aload #7
    //   121: dup
    //   122: astore #9
    //   124: getfield ﹳᖦ : I
    //   127: if_icmpge -> 163
    //   130: aload #6
    //   132: aload #7
    //   134: iload #8
    //   136: invokevirtual ᐨẏ : (I)Lyyds/sniarbtej/ן;
    //   139: checkcast yyds/sniarbtej/ﹳه
    //   142: invokevirtual toString : ()Ljava/lang/String;
    //   145: invokestatic ʾܪ : (Ljava/lang/String;)Ljava/lang/String;
    //   148: invokevirtual append : (Ljava/lang/String;)Ljava/lang/StringBuilder;
    //   151: bipush #32
    //   153: invokevirtual append : (C)Ljava/lang/StringBuilder;
    //   156: pop
    //   157: iinc #8, 1
    //   160: goto -> 117
    //   163: aload #6
    //   165: ldc_w '敒꺊俚'
    //   168: invokevirtual toCharArray : ()[C
    //   171: dup
    //   172: dup
    //   173: iconst_0
    //   174: dup_x1
    //   175: caload
    //   176: sipush #16714
    //   179: ixor
    //   180: i2c
    //   181: castore
    //   182: sipush #27839
    //   185: iconst_2
    //   186: iconst_2
    //   187: invokestatic v : (Ljava/lang/Object;SIS)Ljava/lang/String;
    //   190: invokevirtual append : (Ljava/lang/String;)Ljava/lang/StringBuilder;
    //   193: pop
    //   194: iconst_0
    //   195: istore #8
    //   197: iload #8
    //   199: aload #7
    //   201: dup
    //   202: astore #9
    //   204: getfield ᐝᒰ : I
    //   207: if_icmpge -> 243
    //   210: aload #6
    //   212: aload #7
    //   214: iload #8
    //   216: invokevirtual ˊ : (I)Lyyds/sniarbtej/ן;
    //   219: checkcast yyds/sniarbtej/ﹳه
    //   222: invokevirtual toString : ()Ljava/lang/String;
    //   225: invokestatic ʾܪ : (Ljava/lang/String;)Ljava/lang/String;
    //   228: invokevirtual append : (Ljava/lang/String;)Ljava/lang/StringBuilder;
    //   231: bipush #32
    //   233: invokevirtual append : (C)Ljava/lang/StringBuilder;
    //   236: pop
    //   237: iinc #8, 1
    //   240: goto -> 197
    //   243: aload #6
    //   245: invokevirtual length : ()I
    //   248: aload_0
    //   249: getfield ˑỲ : I
    //   252: aload_0
    //   253: getfield ˌپ : I
    //   256: iadd
    //   257: iconst_1
    //   258: iadd
    //   259: if_icmpge -> 273
    //   262: aload #6
    //   264: bipush #32
    //   266: invokevirtual append : (C)Ljava/lang/StringBuilder;
    //   269: pop
    //   270: goto -> 243
    //   273: aload_2
    //   274: iload #5
    //   276: ldc_w 100000
    //   279: iadd
    //   280: invokestatic toString : (I)Ljava/lang/String;
    //   283: iconst_1
    //   284: invokevirtual substring : (I)Ljava/lang/String;
    //   287: invokevirtual print : (Ljava/lang/String;)V
    //   290: aload_2
    //   291: new java/lang/StringBuilder
    //   294: dup
    //   295: ldc_w '빓囯'
    //   298: invokevirtual toCharArray : ()[C
    //   301: dup
    //   302: dup
    //   303: iconst_0
    //   304: dup_x1
    //   305: caload
    //   306: sipush #20000
    //   309: ixor
    //   310: i2c
    //   311: castore
    //   312: sipush #3633
    //   315: iconst_4
    //   316: iconst_4
    //   317: invokestatic v : (Ljava/lang/Object;SIS)Ljava/lang/String;
    //   320: invokespecial <init> : (Ljava/lang/String;)V
    //   323: aload #6
    //   325: invokevirtual append : (Ljava/lang/Object;)Ljava/lang/StringBuilder;
    //   328: ldc_w '횡΂뭤篘'
    //   331: invokevirtual toCharArray : ()[C
    //   334: dup
    //   335: dup
    //   336: iconst_2
    //   337: dup_x1
    //   338: caload
    //   339: sipush #14570
    //   342: ixor
    //   343: i2c
    //   344: castore
    //   345: sipush #17768
    //   348: iconst_5
    //   349: iconst_4
    //   350: invokestatic v : (Ljava/lang/Object;SIS)Ljava/lang/String;
    //   353: invokevirtual append : (Ljava/lang/String;)Ljava/lang/StringBuilder;
    //   356: aload_3
    //   357: getfield ۥ : Ljava/util/List;
    //   360: aload_3
    //   361: getfield ۥ : Ljava/util/List;
    //   364: invokeinterface size : ()I
    //   369: iconst_1
    //   370: isub
    //   371: invokeinterface get : (I)Ljava/lang/Object;
    //   376: invokevirtual append : (Ljava/lang/Object;)Ljava/lang/StringBuilder;
    //   379: invokevirtual toString : ()Ljava/lang/String;
    //   382: invokevirtual print : (Ljava/lang/String;)V
    //   385: iinc #5, 1
    //   388: goto -> 49
    //   391: aload_0
    //   392: getfield ﾞǰ : Ljava/util/List;
    //   395: invokeinterface iterator : ()Ljava/util/Iterator;
    //   400: astore #5
    //   402: aload #5
    //   404: invokeinterface hasNext : ()Z
    //   409: ifeq -> 495
    //   412: aload #5
    //   414: invokeinterface next : ()Ljava/lang/Object;
    //   419: checkcast yyds/sniarbtej/ˌț
    //   422: dup
    //   423: astore #6
    //   425: aload #4
    //   427: invokevirtual ᐨẏ : (Lyyds/sniarbtej/ˉｓ;)V
    //   430: aload_2
    //   431: new java/lang/StringBuilder
    //   434: dup
    //   435: ldc_w '滈'
    //   438: invokevirtual toCharArray : ()[C
    //   441: dup
    //   442: dup
    //   443: iconst_0
    //   444: dup_x1
    //   445: caload
    //   446: sipush #21956
    //   449: ixor
    //   450: i2c
    //   451: castore
    //   452: sipush #31431
    //   455: iconst_0
    //   456: iconst_3
    //   457: invokestatic v : (Ljava/lang/Object;SIS)Ljava/lang/String;
    //   460: invokespecial <init> : (Ljava/lang/String;)V
    //   463: aload_3
    //   464: getfield ۥ : Ljava/util/List;
    //   467: aload_3
    //   468: getfield ۥ : Ljava/util/List;
    //   471: invokeinterface size : ()I
    //   476: iconst_1
    //   477: isub
    //   478: invokeinterface get : (I)Ljava/lang/Object;
    //   483: invokevirtual append : (Ljava/lang/Object;)Ljava/lang/StringBuilder;
    //   486: invokevirtual toString : ()Ljava/lang/String;
    //   489: invokevirtual print : (Ljava/lang/String;)V
    //   492: goto -> 402
    //   495: aload_2
    //   496: invokevirtual println : ()V
    //   499: return
  }
  
  private static String ʾܪ(String paramString) {
    int i;
    if ((i = paramString.lastIndexOf('/')) == -1)
      return paramString; 
    int j = paramString.length();
    if (paramString.charAt(j - 1) == ';')
      j--; 
    int k;
    return ((k = paramString.lastIndexOf('[')) == -1) ? paramString.substring(i + 1, j) : (paramString.substring(0, k + 1) + paramString.substring(i + 1, j));
  }
  
  static {
    "㔽깓諤?๺㔘囇簗쒟䖍寱獘댫솲ᚴ?ȭ篡㤴摮峝ẽ페௜࿣咹끔께⇩麬귉ᙄ鷫꧶献\007䞾?雭䤓꾒樨癭⌆틝떆㉗ꩴ悒戊刽鳊↹鿆ᠴ첓?ꎹ㹊䂙旸₪Ⓘ詸埏葏Ö⋬陞㯑⋞氰៨峛?喴㋏讚ᯑⲐ㻓늉婐巼䦃掲㣎੸䀖".toCharArray()[24] = (char)("㔽깓諤?๺㔘囇簗쒟䖍寱獘댫솲ᚴ?ȭ篡㤴摮峝ẽ페௜࿣咹끔께⇩麬귉ᙄ鷫꧶献\007䞾?雭䤓꾒樨癭⌆틝떆㉗ꩴ悒戊刽鳊↹鿆ᠴ첓?ꎹ㹊䂙旸₪Ⓘ詸埏葏Ö⋬陞㯑⋞氰៨峛?喴㋏讚ᯑⲐ㻓늉婐巼䦃掲㣎੸䀖".toCharArray()[24] ^ 0x208F);
  }
  
  static {
    "좞來ꇠᵏꈅ㾉誙ᶢ뫙멏個䃚秶䰮⤵핟⟥".toCharArray()[4] = (char)("좞來ꇠᵏꈅ㾉誙ᶢ뫙멏個䃚秶䰮⤵핟⟥".toCharArray()[4] ^ 0x2160);
  }
}


/* Location:              C:\Users\kb\Downloads\ja-netfilter.jar!\yyds\sniarbtej\ˉʭ.class
 * Java compiler version: 8 (52.0)
 * JD-Core Version:       1.1.3
 */