package yyds.sniarbtej;

import java.util.Collections;
import java.util.Iterator;
import java.util.List;
import java.util.ListIterator;
import ylt.pmn.zubdqvgt;

final class ˋن<V extends ן> extends ιᒶ<V> {
  private final וּ<V> ᐨẏ;
  
  private ـс ᴵʖ;
  
  private int ʼᓓ;
  
  ˋن(וּ<V> paramוּ) {
    super(paramוּ);
    this.ᐨẏ = paramוּ;
  }
  
  public final void ᐨẏ(String paramString, ᐧє paramᐧє) {
    this.ᴵʖ = paramᐧє.ˊ;
    this.ʼᓓ = ˑܘ.ᐨم(paramᐧє.ˎᴗ) >> 2;
    if ((paramᐧє.ᒬ & 0x8) != 0)
      this.ʼᓓ--; 
    ιՆ[] arrayOfΙՆ;
    ιՆ<? extends V> ιՆ1 = (arrayOfΙՆ = (ιՆ[])ᐨẏ())[0];
    ιՆ<? extends V> ιՆ2 = ιՆ1;
    ᐧє ᐧє1 = paramᐧє;
    String str = paramString;
    ˋن<Object> ˋن1 = this;
    int i = -1;
    ιՆ2 = ιՆ2;
    int j = 0;
    ListIterator<Ӏ> listIterator = ᐧє1.ˊ.ᐨẏ();
    while (listIterator.hasNext()) {
      Ӏ ӏ;
      if (ӏ = listIterator.next() instanceof ﾞঽ) {
        ιՆ<? extends V> ιՆ;
        try {
          Iterator iterator;
          ﾞঽ ﾞঽ = (ﾞঽ)ӏ;
          ιՆ<? extends V> ιՆ3 = ιՆ2;
          String str1 = str;
          ˋن<Object> ˋن2 = ˋن1;
          ιՆ3 = ᐨẏ(ιՆ3);
          List list2 = (ﾞঽ.ʿλ == null) ? Collections.emptyList() : ﾞঽ.ʿλ;
          int m = ˋن2.ʼᓓ;
          switch (ﾞঽ.ᓱ) {
            case -1:
            case 0:
              m = 0;
            case 1:
              for (ιՆ<? extends V> ιՆ5 : (Iterable<ιՆ<? extends V>>)list2) {
                ן ן = (ן)ˋن2.ᐨẏ(str1, ﾞঽ, ιՆ5);
                if (m + ן.ˍɫ() > (ιՆ5 = ιՆ3).ﹳᖦ) {
                  "멜愈棈㎒鷰쑙蛰ⱝ尢쁿க飧↓敻豝ᑓӾ엲?읒Ⅿ餢風?頀⾛㏩㷞㧁拟鳗淝룰㭂蠩旹".toCharArray()[0] = (char)("멜愈棈㎒鷰쑙蛰ⱝ尢쁿க飧↓敻豝ᑓӾ엲?읒Ⅿ餢風?頀⾛㏩㷞㧁拟鳗淝룰㭂蠩旹".toCharArray()[0] ^ 0x56BB);
                  throw new ιƚ(ﾞঽ, ᐨẏ$ᐝт.W("멜愈棈㎒鷰쑙蛰ⱝ尢쁿க飧↓敻豝ᑓӾ엲?읒Ⅿ餢風?頀⾛㏩㷞㧁拟鳗淝룰㭂蠩旹".toCharArray(), (short)12656, (byte)4, (short)2));
                } 
                ιՆ3.ᐨẏ(m++, (V)ן);
                if (ן.ˍɫ() == 2)
                  ιՆ3.ᐨẏ(m++, ˋن2.ᐨẏ.ᐨẏ((ˑܘ)null)); 
              } 
              break;
            case 2:
              iterator = list2.iterator();
              while (iterator.hasNext()) {
                iterator.next();
                if (m <= 0) {
                  "?蠂쭐??ᬜ釧ﲻ➃왳肋཮፥榎螸瓨初ֳ퐴䄾ԥ魎쁩띲뭩頲惟赘룂ⴐᛪ쯎Ǝ".toCharArray()[4] = (char)("?蠂쭐??ᬜ釧ﲻ➃왳肋཮፥榎螸瓨初ֳ퐴䄾ԥ魎쁩띲뭩頲惟赘룂ⴐᛪ쯎Ǝ".toCharArray()[4] ^ 0x4B4B);
                  throw new ιƚ(ﾞঽ, ᐨẏ$ᐝт.W("?蠂쭐??ᬜ釧ﲻ➃왳肋཮፥榎螸瓨初ֳ퐴䄾ԥ魎쁩띲뭩頲惟赘룂ⴐᛪ쯎Ǝ".toCharArray(), (short)7163, (byte)5, (short)5));
                } 
                if (m > 1 && ιՆ3.ᐨẏ(m - 2).ˍɫ() == 2) {
                  m -= 2;
                  continue;
                } 
                m--;
              } 
              break;
            case 3:
            case 4:
              break;
            default:
              "鲁嘀驾싫諞τ漺笏ோɍ帅锊蟃౱⠙㼂彔".toCharArray()[14] = (char)("鲁嘀驾싫諞τ漺笏ோɍ帅锊蟃౱⠙㼂彔".toCharArray()[14] ^ 0x6957);
              throw new ιƚ(ﾞঽ, ᐨẏ$ᐝт.W("鲁嘀驾싫諞τ漺笏ோɍ帅锊蟃౱⠙㼂彔".toCharArray(), (short)27807, (byte)5, (short)4) + ﾞঽ.ᓱ);
          } 
          ˋن2.ʼᓓ = m;
          ιՆ<? extends V> ιՆ4;
          while (m < (ιՆ4 = ιՆ3).ﹳᖦ)
            ιՆ3.ᐨẏ(m++, ˋن2.ᐨẏ.ᐨẏ((ˑܘ)null)); 
          List list1 = (ﾞঽ.ᴵʖ == null) ? Collections.emptyList() : ﾞঽ.ᴵʖ;
          (ιՆ4 = ιՆ3).ᐝᒰ = 0;
          for (Object object : list1)
            ιՆ3.ˊ((V)ˋن2.ᐨẏ(str1, ﾞঽ, object)); 
          ιՆ = ιՆ3;
        } catch (ιƚ ιƚ) {
          "剚阩諗鎖鍺扎ቌ峪⸬䔚㺘䞰伃屎ᤷ蜵楛ꣾ鑶澥嘶".toCharArray()[13] = (char)("剚阩諗鎖鍺扎ቌ峪⸬䔚㺘䞰伃屎ᤷ蜵楛ꣾ鑶澥嘶".toCharArray()[13] ^ 0x1AC1);
          "쵉忮ᆻ".toCharArray()[0] = (char)("쵉忮ᆻ".toCharArray()[0] ^ 0x1CD0);
          throw new ιƚ(ιƚ.ʹﮃ, ᐨẏ$ᐝт.W("剚阩諗鎖鍺扎ቌ峪⸬䔚㺘䞰伃屎ᤷ蜵楛ꣾ鑶澥嘶".toCharArray(), (short)11566, (byte)3, (short)4) + j + ᐨẏ$ᐝт.W("쵉忮ᆻ".toCharArray(), (short)20226, (byte)2, (short)5) + ιƚ.getMessage(), ιƚ);
        } 
        for (int k = i + 1; k <= j; k++)
          ˋن1.ᐨẏ()[k] = (ιՆ)ιՆ; 
      } 
      if (ˊ(ӏ) || ӏ instanceof ﾞঽ)
        i = j; 
      j++;
    } 
    ـс ـс1;
    for (byte b = 0; b < (ـс1 = this.ᴵʖ).ʿᵉ; b++) {
      Ӏ ӏ;
      ιՆ<V> ιՆ = arrayOfΙՆ[b];
      listIterator = null;
      try {
        int k = (ӏ = paramᐧє.ˊ.ᐨẏ(b)).ˈהּ();
        if ((i = ӏ.ﹳיִ()) == 8 || i == 15 || i == 14) {
          ᐨẏ(b + 1, ιՆ, false);
        } else {
          ιՆ1.ˊ(ιՆ).ᐨẏ(ӏ, this.ᐨẏ);
          if (ӏ instanceof ʿশ) {
            if (k == 168) {
              "䒌ⶕ麷蓱ၼ默苩异淋并難?엁ﱆ鶁籘븜餔喍魋䚈뷬簨駺ᜱ沰琢⾝Κ".toCharArray()[12] = (char)("䒌ⶕ麷蓱ၼ默苩异淋并難?엁ﱆ鶁籘븜餔喍魋䚈뷬簨駺ᜱ沰琢⾝Κ".toCharArray()[12] ^ 0x7C4);
              throw new ιƚ(ӏ, ᐨẏ$ᐝт.W("䒌ⶕ麷蓱ၼ默苩异淋并難?엁ﱆ鶁籘븜餔喍魋䚈뷬簨駺ᜱ沰琢⾝Κ".toCharArray(), (short)26332, (byte)1, (short)0));
            } 
            ʿশ ʿশ = (ʿশ)ӏ;
            j = this.ᴵʖ.ᐨẏ(ʿশ.ˊ);
            ᐨẏ(j, (ιՆ)ιՆ1, true);
            if (k == 167) {
              ᐝᵣ(b);
            } else {
              ᐨẏ(b + 1, (ιՆ)ιՆ1, false);
            } 
          } else if (ӏ instanceof ﹳڐ) {
            ﹳڐ ﹳڐ = (ﹳڐ)ӏ;
            j = this.ᴵʖ.ᐨẏ(ﹳڐ.ʿᵉ);
            ᐨẏ(j, (ιՆ)ιՆ1, true);
            for (k = 0; k < ﹳڐ.ﾞл.size(); k++) {
              λ λ = ﹳڐ.ﾞл.get(k);
              j = this.ᴵʖ.ᐨẏ(λ);
              ᐨẏ(j, (ιՆ)ιՆ1, true);
            } 
            ᐝᵣ(b);
          } else if (ӏ instanceof יᔭ) {
            יᔭ יᔭ = (יᔭ)ӏ;
            j = this.ᴵʖ.ᐨẏ(יᔭ.ʿᵉ);
            ᐨẏ(j, (ιՆ)ιՆ1, true);
            for (k = 0; k < יᔭ.ﾞл.size(); k++) {
              λ λ = יᔭ.ﾞл.get(k);
              j = this.ᴵʖ.ᐨẏ(λ);
              ᐨẏ(j, (ιՆ)ιՆ1, true);
            } 
            ᐝᵣ(b);
          } else {
            if (k == 169) {
              "沢騣赴䒀틻칩瑃඙膂ᾪꔣ⨟ⷈ㟅뼖胒觭鸨שּׂ㈋䶎䤾ꑀ䃱봄ⵇଁ?㸈间⋶".toCharArray()[21] = (char)("沢騣赴䒀틻칩瑃඙膂ᾪꔣ⨟ⷈ㟅뼖胒觭鸨שּׂ㈋䶎䤾ꑀ䃱봄ⵇଁ?㸈间⋶".toCharArray()[21] ^ 0x46E3);
              throw new ιƚ(ӏ, ᐨẏ$ᐝт.W("沢騣赴䒀틻칩瑃඙膂ᾪꔣ⨟ⷈ㟅뼖胒觭鸨שּׂ㈋䶎䤾ꑀ䃱봄ⵇଁ?㸈间⋶".toCharArray(), (short)19985, (byte)2, (short)0));
            } 
            if (k != 191 && (k < 172 || k > 177)) {
              ᐨẏ(b + 1, (ιՆ)ιՆ1, false);
            } else {
              ᐝᵣ(b);
            } 
          } 
        } 
        List<ˌț> list;
        if ((list = ˊ(b)) != null) {
          Iterator<ˌț> iterator = list.iterator();
          while (iterator.hasNext()) {
            ˌț ˌț;
            if ((ˌț = iterator.next()).ᐨẏ == null) {
              "崔䠎얜ᔗ測擜돟珋␞糆瞷䳹෭᷇閧쑦槼녨劸".toCharArray()[10] = (char)("崔䠎얜ᔗ測擜돟珋␞糆瞷䳹෭᷇閧쑦槼녨劸".toCharArray()[10] ^ 0x38F6);
              ˑܘ = ˑܘ.ˊ(ᐨẏ$ᐝт.W("崔䠎얜ᔗ測擜돟珋␞糆瞷䳹෭᷇閧쑦槼녨劸".toCharArray(), (short)24924, (byte)5, (short)3));
            } else {
              ˑܘ = ˑܘ.ˊ(ˌț.ᐨẏ);
            } 
            ιՆ<V> ιՆ3;
            ιՆ<V> ιՆ4;
            (ιՆ4 = ιՆ3 = ᐨẏ(ιՆ)).ᐝᒰ = 0;
            ˑܘ ˑܘ = ˑܘ;
            וּ<V> וּ1;
            ιՆ3.ˊ((וּ1 = this.ᐨẏ).ᐨẏ(ˑܘ));
            ᐨẏ(this.ᴵʖ.ᐨẏ(ˌț.ʹﮃ), ιՆ3, true);
          } 
        } 
        if (!ˊ(b))
          return; 
      } catch (ιƚ ιƚ) {
        "ﮡ姑띴俼뷈လ憂腨᳋뇊叱ෛ戇룅䣮↦꾾噻燼".toCharArray()[5] = (char)("ﮡ姑띴俼뷈လ憂腨᳋뇊叱ෛ戇룅䣮↦꾾噻燼".toCharArray()[5] ^ 0x40FF);
        "ၬ节ⳓ".toCharArray()[0] = (char)("ၬ节ⳓ".toCharArray()[0] ^ 0x6D67);
        throw new ιƚ(ιƚ.ʹﮃ, ᐨẏ$ᐝт.W("ﮡ姑띴俼뷈လ憂腨᳋뇊叱ෛ戇룅䣮↦꾾噻燼".toCharArray(), (short)9407, (byte)1, (short)5) + b + ᐨẏ$ᐝт.W("ၬ节ⳓ".toCharArray(), (short)24299, (byte)1, (short)4) + ιƚ.getMessage(), ιƚ);
      } catch (RuntimeException runtimeException) {
        "⨫柑મ䤎ꕉမ疇䦠太赏⟫綞귒羋㲝ⴟ躄ක㩝뮜宙".toCharArray()[4] = (char)("⨫柑મ䤎ꕉမ疇䦠太赏⟫綞귒羋㲝ⴟ躄ක㩝뮜宙".toCharArray()[4] ^ 0x741E);
        "ʦ쨍ࣚ".toCharArray()[0] = (char)("ʦ쨍ࣚ".toCharArray()[0] ^ 0xA2C);
        throw new ιƚ(ӏ, ᐨẏ$ᐝт.W("⨫柑મ䤎ꕉမ疇䦠太赏⟫綞귒羋㲝ⴟ躄ක㩝뮜宙".toCharArray(), (short)6832, (byte)1, (short)1) + b + ᐨẏ$ᐝт.W("ʦ쨍ࣚ".toCharArray(), (short)30109, (byte)0, (short)3) + runtimeException.getMessage(), runtimeException);
      } 
    } 
  }
  
  private void ᐨẏ(String paramString, ᐧє paramᐧє, ιՆ<V> paramιՆ) {
    byte b = -1;
    paramιՆ = paramιՆ;
    byte b1 = 0;
    ListIterator<Ӏ> listIterator = paramᐧє.ˊ.ᐨẏ();
    while (listIterator.hasNext()) {
      Ӏ ӏ;
      if (ӏ = listIterator.next() instanceof ﾞঽ) {
        try {
          paramιՆ = ᐨẏ(paramString, paramιՆ, (ﾞঽ)ӏ);
        } catch (ιƚ ιƚ) {
          "壨褲鿌埖㊦ဒ㾏തꃎ蠪攇㐢蠄앿ꯟ璶⯪藱蜑౔".toCharArray()[10] = (char)("壨褲鿌埖㊦ဒ㾏തꃎ蠪攇㐢蠄앿ꯟ璶⯪藱蜑౔".toCharArray()[10] ^ 0x7CFD);
          "嘃᧡".toCharArray()[0] = (char)("嘃᧡".toCharArray()[0] ^ 0x2A33);
          throw new ιƚ(ιƚ.ʹﮃ, ˍɫ$יς.J("壨褲鿌埖㊦ဒ㾏തꃎ蠪攇㐢蠄앿ꯟ璶⯪藱蜑౔".toCharArray(), (short)18811, (short)5, (byte)1) + b1 + ˍɫ$יς.J("嘃᧡".toCharArray(), (short)8699, (short)2, (byte)2) + ιƚ.getMessage(), ιƚ);
        } 
        for (int i = b + 1; i <= b1; i++)
          ᐨẏ()[i] = paramιՆ; 
      } 
      if (ˊ(ӏ) || ӏ instanceof ﾞঽ)
        b = b1; 
      b1++;
    } 
  }
  
  private ιՆ<V> ᐨẏ(String paramString, ιՆ<V> paramιՆ, ﾞঽ paramﾞঽ) {
    Iterator iterator;
    paramιՆ = ᐨẏ(paramιՆ);
    List list2 = (paramﾞঽ.ʿλ == null) ? Collections.emptyList() : paramﾞঽ.ʿλ;
    int i = this.ʼᓓ;
    switch (paramﾞঽ.ᓱ) {
      case -1:
      case 0:
        i = 0;
      case 1:
        for (ιՆ<V> ιՆ2 : (Iterable<ιՆ<V>>)list2) {
          V v = ᐨẏ(paramString, paramﾞঽ, ιՆ2);
          if (i + v.ˍɫ() > (ιՆ2 = paramιՆ).ﹳᖦ) {
            "鏡鐒澕뇬퐑㤌ኙ批푨ဂ괳㊿ᦵ鵈淄虋鈔ঁ腿詥ł⍽☄똝닱ᔺᤙ帳뇯খ퉡멃鹉貲㰿".toCharArray()[30] = (char)("鏡鐒澕뇬퐑㤌ኙ批푨ဂ괳㊿ᦵ鵈淄虋鈔ঁ腿詥ł⍽☄똝닱ᔺᤙ帳뇯খ퉡멃鹉貲㰿".toCharArray()[30] ^ 0x2709);
            throw new ιƚ(paramﾞঽ, ˍɫ$יς.J("鏡鐒澕뇬퐑㤌ኙ批푨ဂ괳㊿ᦵ鵈淄虋鈔ঁ腿詥ł⍽☄똝닱ᔺᤙ帳뇯খ퉡멃鹉貲㰿".toCharArray(), (short)9847, (short)5, (byte)5));
          } 
          paramιՆ.ᐨẏ(i++, v);
          if (v.ˍɫ() == 2)
            paramιՆ.ᐨẏ(i++, this.ᐨẏ.ᐨẏ((ˑܘ)null)); 
        } 
        break;
      case 2:
        iterator = list2.iterator();
        while (iterator.hasNext()) {
          iterator.next();
          if (i <= 0) {
            "웋ꤞ꣤ꮟꖇ죿돭⮿ꂉ蛨믧跎刘옧಴踂邯혪ⓞ냸뤰櫭᛽䇙혰✞祐轙瘎댨牪‮מּ杒屩".toCharArray()[3] = (char)("웋ꤞ꣤ꮟꖇ죿돭⮿ꂉ蛨믧跎刘옧಴踂邯혪ⓞ냸뤰櫭᛽䇙혰✞祐轙瘎댨牪‮מּ杒屩".toCharArray()[3] ^ 0x7B7E);
            throw new ιƚ(paramﾞঽ, ˍɫ$יς.J("웋ꤞ꣤ꮟꖇ죿돭⮿ꂉ蛨믧跎刘옧಴踂邯혪ⓞ냸뤰櫭᛽䇙혰✞祐轙瘎댨牪‮מּ杒屩".toCharArray(), (short)31037, (short)5, (byte)2));
          } 
          if (i > 1 && paramιՆ.ᐨẏ(i - 2).ˍɫ() == 2) {
            i -= 2;
            continue;
          } 
          i--;
        } 
        break;
      case 3:
      case 4:
        break;
      default:
        "ແ迄舲㴁᥊勺?罳铳瑶䋝鯴ࣃ䫣肳林롟࿄".toCharArray()[2] = (char)("ແ迄舲㴁᥊勺?罳铳瑶䋝鯴ࣃ䫣肳林롟࿄".toCharArray()[2] ^ 0x636);
        throw new ιƚ(paramﾞঽ, ˍɫ$יς.J("ແ迄舲㴁᥊勺?罳铳瑶䋝鯴ࣃ䫣肳林롟࿄".toCharArray(), (short)32413, (short)1, (byte)3) + paramﾞঽ.ᓱ);
    } 
    this.ʼᓓ = i;
    ιՆ<V> ιՆ1;
    while (i < (ιՆ1 = paramιՆ).ﹳᖦ)
      paramιՆ.ᐨẏ(i++, this.ᐨẏ.ᐨẏ((ˑܘ)null)); 
    List list1 = (paramﾞঽ.ᴵʖ == null) ? Collections.emptyList() : paramﾞঽ.ᴵʖ;
    (ιՆ1 = paramιՆ).ᐝᒰ = 0;
    for (Object object : list1)
      paramιՆ.ˊ(ᐨẏ(paramString, paramﾞঽ, object)); 
    return paramιՆ;
  }
  
  private V ᐨẏ(String paramString, ﾞঽ paramﾞঽ, Object paramObject) {
    if (zubdqvgt.G(paramObject, ـﭔ.ᐨẏ))
      return this.ᐨẏ.ᐨẏ((ˑܘ)null); 
    if (zubdqvgt.G(paramObject, ـﭔ.ˊ))
      return this.ᐨẏ.ᐨẏ(ˑܘ.ʹﮃ); 
    if (zubdqvgt.G(paramObject, ـﭔ.ᴵʖ))
      return this.ᐨẏ.ᐨẏ(ˑܘ.ՙᗮ); 
    if (zubdqvgt.G(paramObject, ـﭔ.ʿᵉ))
      return this.ᐨẏ.ᐨẏ(ˑܘ.ˍɫ); 
    if (zubdqvgt.G(paramObject, ـﭔ.ﾞл))
      return this.ᐨẏ.ᐨẏ(ˑܘ.ʽ); 
    if (zubdqvgt.G(paramObject, ـﭔ.ʹﮃ))
      return this.ᐨẏ.ᐨẏ(new ˏﾚ(1)); 
    if (zubdqvgt.G(paramObject, ـﭔ.ՙᗮ))
      return this.ᐨẏ.ᐨẏ(ˑܘ.ˊ(paramString)); 
    if (paramObject instanceof String)
      return this.ᐨẏ.ᐨẏ(ˑܘ.ˊ((String)paramObject)); 
    if (paramObject instanceof λ) {
      Ӏ ӏ = (λ)paramObject;
      while (ӏ != null && !ˊ(ӏ))
        ӏ = (ӏ = ӏ).ˊ; 
      if (ӏ == null || ӏ.ˈהּ() != 187) {
        "녮ໝﮭζሑ멼໱딜튇᜛嘙䏪풩삗릟㓒࠸掏锧ᘯ䌙￑ྮ낰烘雞收◌⩴枣䖣칇쭿ᔁ裢葮䂳⪖顖먌恛".toCharArray()[24] = (char)("녮ໝﮭζሑ멼໱딜튇᜛嘙䏪풩삗릟㓒࠸掏锧ᘯ䌙￑ྮ낰烘雞收◌⩴枣䖣칇쭿ᔁ裢葮䂳⪖顖먌恛".toCharArray()[24] ^ 0x14C);
        throw new ιƚ(paramﾞঽ, ˍɫ$יς.J("녮ໝﮭζሑ멼໱딜튇᜛嘙䏪풩삗릟㓒࠸掏锧ᘯ䌙￑ྮ낰烘雞收◌⩴枣䖣칇쭿ᔁ裢葮䂳⪖顖먌恛".toCharArray(), (short)19961, (short)1, (byte)4));
      } 
      return this.ᐨẏ.ᐨẏ(ˑܘ.ˊ(((ᔉ)ӏ).ˎᴗ));
    } 
    "?肥笩뀭㻳蘱注෶渫㝉즪ནꓟ㰓꽒\025꺅먞娶ｮ쬶⛇勰衏࠱፷幵".toCharArray()[14] = (char)("?肥笩뀭㻳蘱注෶渫㝉즪ནꓟ㰓꽒\025꺅먞娶ｮ쬶⛇勰衏࠱፷幵".toCharArray()[14] ^ 0x1FCB);
    throw new ιƚ(paramﾞঽ, ˍɫ$יς.J("?肥笩뀭㻳蘱注෶渫㝉즪ནꓟ㰓꽒\025꺅먞娶ｮ쬶⛇勰衏࠱፷幵".toCharArray(), (short)19626, (short)1, (byte)1) + paramObject);
  }
  
  private void ᐨẏ(int paramInt, ιՆ<V> paramιՆ, boolean paramBoolean) {
    ιՆ<V> ιՆ1;
    if ((ιՆ1 = ᐨẏ()[paramInt]) == null) {
      if (paramBoolean) {
        "䋒儉椵밥豸쾁鄑?쪷哆䵭Ꞔ⒁᳽徔Ŷ㝸눤렄သ끢女骴ၰ쮝궚谄鲫㈶썳ꎢ׃ꖲ崎蛺ት퀇塊挓".toCharArray()[4] = (char)("䋒儉椵밥豸쾁鄑?쪷哆䵭Ꞔ⒁᳽徔Ŷ㝸눤렄သ끢女骴ၰ쮝궚谄鲫㈶썳ꎢ׃ꖲ崎蛺ት퀇塊挓".toCharArray()[4] ^ 0x39FE);
        throw new ιƚ(null, ᐝᵣ$ﾞﾇ.j("䋒儉椵밥豸쾁鄑?쪷哆䵭Ꞔ⒁᳽徔Ŷ㝸눤렄သ끢女骴ၰ쮝궚谄鲫㈶썳ꎢ׃ꖲ崎蛺ት퀇塊挓".toCharArray(), (short)27566, 4, (short)0) + paramInt);
      } 
      ᐨẏ()[paramInt] = ᐨẏ(paramιՆ);
      return;
    } 
    String str;
    if ((str = ᐨẏ(paramιՆ, ιՆ1)) != null) {
      "繈颇ᨶ鴿붝茅꼺쁣쓙蚂⤥哪䇻闳숡ɤ⍩Ὁ酊斊ᶆ?籣땓끼鬡㋌䛵輢燂?괥ᾈ냊禎㯀隹Ꚉ駠㯆췩⎤䂣⍼祙ᑦ䁸냏洵㮇䗣䬝捿堎".toCharArray()[2] = (char)("繈颇ᨶ鴿붝茅꼺쁣쓙蚂⤥哪䇻闳숡ɤ⍩Ὁ酊斊ᶆ?籣땓끼鬡㋌䛵輢燂?괥ᾈ냊禎㯀隹Ꚉ駠㯆췩⎤䂣⍼祙ᑦ䁸냏洵㮇䗣䬝捿堎".toCharArray()[2] ^ 0x60B5);
      "쪉쁮器".toCharArray()[0] = (char)("쪉쁮器".toCharArray()[0] ^ 0x468E);
      "氼朩".toCharArray()[0] = (char)("氼朩".toCharArray()[0] ^ 0x27C1);
      throw new ιƚ(null, ᐝᵣ$ﾞﾇ.j("繈颇ᨶ鴿붝茅꼺쁣쓙蚂⤥哪䇻闳숡ɤ⍩Ὁ酊斊ᶆ?籣땓끼鬡㋌䛵輢燂?괥ᾈ냊禎㯀隹Ꚉ駠㯆췩⎤䂣⍼祙ᑦ䁸냏洵㮇䗣䬝捿堎".toCharArray(), (short)21837, 2, (short)2) + paramInt + ᐝᵣ$ﾞﾇ.j("쪉쁮器".toCharArray(), (short)9919, 3, (short)0) + str + ᐝᵣ$ﾞﾇ.j("氼朩".toCharArray(), (short)23731, 3, (short)3));
    } 
  }
  
  private String ᐨẏ(ιՆ<V> paramιՆ1, ιՆ<V> paramιՆ2) {
    // Byte code:
    //   0: aload_1
    //   1: dup
    //   2: astore #5
    //   4: getfield ﹳᖦ : I
    //   7: dup
    //   8: istore_3
    //   9: aload_2
    //   10: dup
    //   11: astore #5
    //   13: getfield ﹳᖦ : I
    //   16: if_icmpeq -> 27
    //   19: new java/lang/AssertionError
    //   22: dup
    //   23: invokespecial <init> : ()V
    //   26: athrow
    //   27: iconst_0
    //   28: istore #4
    //   30: iload #4
    //   32: iload_3
    //   33: if_icmpge -> 192
    //   36: aload_0
    //   37: getfield ᐨẏ : Lyyds/sniarbtej/וּ;
    //   40: aload_1
    //   41: iload #4
    //   43: invokevirtual ᐨẏ : (I)Lyyds/sniarbtej/ן;
    //   46: aload_2
    //   47: iload #4
    //   49: invokevirtual ᐨẏ : (I)Lyyds/sniarbtej/ן;
    //   52: invokevirtual ᐨẏ : (Lyyds/sniarbtej/ן;Lyyds/sniarbtej/ן;)Lyyds/sniarbtej/ן;
    //   55: dup
    //   56: astore #5
    //   58: aload_2
    //   59: iload #4
    //   61: invokevirtual ᐨẏ : (I)Lyyds/sniarbtej/ן;
    //   64: invokevirtual equals : (Ljava/lang/Object;)Z
    //   67: ifne -> 186
    //   70: new java/lang/StringBuilder
    //   73: dup
    //   74: ldc_w '寓ᱏꑶ?㈀艀Ṉ肖㗯䅀ꏫ껪䑫왱᫯ꎖ쇿䄨ﵖŖ⎔佉曉㟪磍'
    //   77: invokevirtual toCharArray : ()[C
    //   80: dup
    //   81: dup
    //   82: bipush #15
    //   84: dup_x1
    //   85: caload
    //   86: sipush #32060
    //   89: ixor
    //   90: i2c
    //   91: castore
    //   92: sipush #24450
    //   95: iconst_4
    //   96: iconst_5
    //   97: invokestatic j : (Ljava/lang/Object;SIS)Ljava/lang/String;
    //   100: invokespecial <init> : (Ljava/lang/String;)V
    //   103: iload #4
    //   105: invokevirtual append : (I)Ljava/lang/StringBuilder;
    //   108: ldc_w '晧烊'
    //   111: invokevirtual toCharArray : ()[C
    //   114: dup
    //   115: dup
    //   116: iconst_1
    //   117: dup_x1
    //   118: caload
    //   119: sipush #14663
    //   122: ixor
    //   123: i2c
    //   124: castore
    //   125: sipush #16420
    //   128: iconst_5
    //   129: iconst_3
    //   130: invokestatic j : (Ljava/lang/Object;SIS)Ljava/lang/String;
    //   133: invokevirtual append : (Ljava/lang/String;)Ljava/lang/StringBuilder;
    //   136: aload_1
    //   137: iload #4
    //   139: invokevirtual ᐨẏ : (I)Lyyds/sniarbtej/ן;
    //   142: invokevirtual append : (Ljava/lang/Object;)Ljava/lang/StringBuilder;
    //   145: ldc_w '輊푙穙ݹ'
    //   148: invokevirtual toCharArray : ()[C
    //   151: dup
    //   152: dup
    //   153: iconst_1
    //   154: dup_x1
    //   155: caload
    //   156: sipush #26677
    //   159: ixor
    //   160: i2c
    //   161: castore
    //   162: sipush #8688
    //   165: iconst_4
    //   166: iconst_0
    //   167: invokestatic j : (Ljava/lang/Object;SIS)Ljava/lang/String;
    //   170: invokevirtual append : (Ljava/lang/String;)Ljava/lang/StringBuilder;
    //   173: aload_2
    //   174: iload #4
    //   176: invokevirtual ᐨẏ : (I)Lyyds/sniarbtej/ן;
    //   179: invokevirtual append : (Ljava/lang/Object;)Ljava/lang/StringBuilder;
    //   182: invokevirtual toString : ()Ljava/lang/String;
    //   185: areturn
    //   186: iinc #4, 1
    //   189: goto -> 30
    //   192: aload_1
    //   193: dup
    //   194: astore #5
    //   196: getfield ᐝᒰ : I
    //   199: dup
    //   200: istore #4
    //   202: aload_2
    //   203: dup
    //   204: astore #5
    //   206: getfield ᐝᒰ : I
    //   209: if_icmpeq -> 239
    //   212: ldc_w '届ત?뒐垸裦ᶈ⒥姱븪?뵗ꃈᔱ坐蝋骿ꎁ뚼㌾鄭랡̜﬌轜屧'
    //   215: invokevirtual toCharArray : ()[C
    //   218: dup
    //   219: dup
    //   220: bipush #24
    //   222: dup_x1
    //   223: caload
    //   224: sipush #15073
    //   227: ixor
    //   228: i2c
    //   229: castore
    //   230: sipush #151
    //   233: iconst_1
    //   234: iconst_4
    //   235: invokestatic j : (Ljava/lang/Object;SIS)Ljava/lang/String;
    //   238: areturn
    //   239: iconst_0
    //   240: istore #5
    //   242: iload #5
    //   244: iload #4
    //   246: if_icmpge -> 403
    //   249: aload_0
    //   250: getfield ᐨẏ : Lyyds/sniarbtej/וּ;
    //   253: aload_1
    //   254: iload #5
    //   256: invokevirtual ˊ : (I)Lyyds/sniarbtej/ן;
    //   259: aload_2
    //   260: iload #5
    //   262: invokevirtual ˊ : (I)Lyyds/sniarbtej/ן;
    //   265: invokevirtual ᐨẏ : (Lyyds/sniarbtej/ן;Lyyds/sniarbtej/ן;)Lyyds/sniarbtej/ן;
    //   268: dup
    //   269: astore_3
    //   270: aload_2
    //   271: iload #5
    //   273: invokevirtual ˊ : (I)Lyyds/sniarbtej/ן;
    //   276: invokevirtual equals : (Ljava/lang/Object;)Z
    //   279: ifne -> 397
    //   282: new java/lang/StringBuilder
    //   285: dup
    //   286: ldc_w '効涻板ꯩ㖗ᮢ䤿앀滿礪傃咬轖户王䋤슐ᦆᄃ찎ᱯ킮ࡁỞ寷逘ͨ㮧߂豝䍖'
    //   289: invokevirtual toCharArray : ()[C
    //   292: dup
    //   293: dup
    //   294: iconst_1
    //   295: dup_x1
    //   296: caload
    //   297: sipush #27236
    //   300: ixor
    //   301: i2c
    //   302: castore
    //   303: sipush #9816
    //   306: iconst_4
    //   307: iconst_3
    //   308: invokestatic j : (Ljava/lang/Object;SIS)Ljava/lang/String;
    //   311: invokespecial <init> : (Ljava/lang/String;)V
    //   314: iload #5
    //   316: invokevirtual append : (I)Ljava/lang/StringBuilder;
    //   319: ldc_w '茳ㅡ㉭'
    //   322: invokevirtual toCharArray : ()[C
    //   325: dup
    //   326: dup
    //   327: iconst_0
    //   328: dup_x1
    //   329: caload
    //   330: sipush #24580
    //   333: ixor
    //   334: i2c
    //   335: castore
    //   336: sipush #17416
    //   339: iconst_4
    //   340: iconst_3
    //   341: invokestatic j : (Ljava/lang/Object;SIS)Ljava/lang/String;
    //   344: invokevirtual append : (Ljava/lang/String;)Ljava/lang/StringBuilder;
    //   347: aload_1
    //   348: iload #5
    //   350: invokevirtual ˊ : (I)Lyyds/sniarbtej/ן;
    //   353: invokevirtual append : (Ljava/lang/Object;)Ljava/lang/StringBuilder;
    //   356: ldc_w '퇣봃ꡧ䯧溦⼜'
    //   359: invokevirtual toCharArray : ()[C
    //   362: dup
    //   363: dup
    //   364: iconst_0
    //   365: dup_x1
    //   366: caload
    //   367: sipush #14541
    //   370: ixor
    //   371: i2c
    //   372: castore
    //   373: sipush #23111
    //   376: iconst_2
    //   377: iconst_5
    //   378: invokestatic j : (Ljava/lang/Object;SIS)Ljava/lang/String;
    //   381: invokevirtual append : (Ljava/lang/String;)Ljava/lang/StringBuilder;
    //   384: aload_2
    //   385: iload #5
    //   387: invokevirtual ˊ : (I)Lyyds/sniarbtej/ן;
    //   390: invokevirtual append : (Ljava/lang/Object;)Ljava/lang/StringBuilder;
    //   393: invokevirtual toString : ()Ljava/lang/String;
    //   396: areturn
    //   397: iinc #5, 1
    //   400: goto -> 242
    //   403: aconst_null
    //   404: areturn
  }
  
  private void ᐝᵣ(int paramInt) {
    if (ˊ(paramInt) && ᐨẏ()[paramInt + 1] == null) {
      "曹┽턈枠쌑ᶉ氕츗섀鿹梤奇ﴆ륹㖒嘌ᷗ赙驇Ė䔽셢᧋뚏浥멶䟍䆔晆॒辩︮㚾꒯낗섲䐯뉟ﰵ铣䨪".toCharArray()[19] = (char)("曹┽턈枠쌑ᶉ氕츗섀鿹梤奇ﴆ륹㖒嘌ᷗ赙驇Ė䔽셢᧋뚏浥멶䟍䆔晆॒辩︮㚾꒯낗섲䐯뉟ﰵ铣䨪".toCharArray()[19] ^ 0x76E7);
      throw new ιƚ(null, ˉﻤ$ͺſ.v("曹┽턈枠쌑ᶉ氕츗섀鿹梤奇ﴆ륹㖒嘌ᷗ赙驇Ė䔽셢᧋뚏浥멶䟍䆔晆॒辩︮㚾꒯낗섲䐯뉟ﰵ铣䨪".toCharArray(), (short)22493, 0, (short)5) + (paramInt + 1));
    } 
  }
  
  private boolean ˊ(int paramInt) {
    for (Ӏ ӏ = (ӏ = this.ᴵʖ.ᐨẏ(paramInt)).ˊ; ӏ != null; ӏ = (ӏ = ӏ).ˊ) {
      if (ˊ(ӏ) || ӏ instanceof ﾞঽ)
        return true; 
    } 
    return false;
  }
  
  private static boolean ˊ(Ӏ paramӀ) {
    return (paramӀ.ˈהּ() >= 0);
  }
}


/* Location:              C:\Users\kb\Downloads\ja-netfilter.jar!\yyds\sniarbtej\ˋن.class
 * Java compiler version: 8 (52.0)
 * JD-Core Version:       1.1.3
 */