package yyds.sniarbtej;

import ylt.pmn.zubdqvgt;

public class ۥ extends ˉｓ {
  private static ˑܘ ͺо = ˑܘ.ᐨẏ(ˏȓ$ᴵЃ.E("羪昐桟佲򓸛弣퐭娉ꗜ擷㧦ﮉ묉禚䘛".toCharArray(), (short)26687, (short)5, (short)2));
  
  private ۥ(ˉｓ paramˉｓ) {
    this(589824, paramˉｓ);
    if (!zubdqvgt.G(getClass(), ۥ.class))
      throw new IllegalStateException(); 
  }
  
  private ۥ(int paramInt, ˉｓ paramˉｓ) {
    super(589824, paramˉｓ);
  }
  
  public final void ʹﮃ(int paramInt) {
    ۥ ۥ1;
    switch (paramInt) {
      case 0:
        (ۥ1 = this).ᐨẏ.ʹﮃ(0);
        return;
      case 1:
        ʹﮃ((Object)null);
        return;
      case 2:
      case 3:
      case 4:
      case 5:
      case 6:
      case 7:
      case 8:
        ʾ(ۥ1 - 3);
        return;
      case 9:
      case 10:
        ˊ((ۥ1 - 9));
        return;
      case 11:
      case 12:
      case 13:
        ˊ((ۥ1 - 11));
        return;
      case 14:
      case 15:
        ˊ((ۥ1 - 14));
        return;
      case 46:
        ʾ(ˑܘ.ʹﮃ);
        return;
      case 47:
        ʾ(ˑܘ.ˍɫ);
        return;
      case 48:
        ʾ(ˑܘ.ՙᗮ);
        return;
      case 49:
        ʾ(ˑܘ.ʽ);
        return;
      case 50:
        ʾ(ͺо);
        return;
      case 51:
        ʾ(ˑܘ.ﾞл);
        return;
      case 52:
        ʾ(ˑܘ.ᴵʖ);
        return;
      case 53:
        ʾ(ˑܘ.ʿᵉ);
        return;
      case 79:
        ͺо(ˑܘ.ʹﮃ);
        return;
      case 80:
        ͺо(ˑܘ.ˍɫ);
        return;
      case 81:
        ͺо(ˑܘ.ՙᗮ);
        return;
      case 82:
        ͺо(ˑܘ.ʽ);
        return;
      case 83:
        ͺо(ͺо);
        return;
      case 84:
        ͺо(ˑܘ.ﾞл);
        return;
      case 85:
        ͺо(ˑܘ.ᴵʖ);
        return;
      case 86:
        ͺо(ˑܘ.ʿᵉ);
        return;
      case 87:
        (ۥ1 = this).ᐨẏ.ʹﮃ(87);
        return;
      case 88:
        (ۥ1 = this).ᐨẏ.ʹﮃ(88);
        return;
      case 89:
        (ۥ1 = this).ᐨẏ.ʹﮃ(89);
        return;
      case 90:
        (ۥ1 = this).ᐨẏ.ʹﮃ(90);
        return;
      case 91:
        (ۥ1 = this).ᐨẏ.ʹﮃ(91);
        return;
      case 92:
        (ۥ1 = this).ᐨẏ.ʹﮃ(92);
        return;
      case 93:
        (ۥ1 = this).ᐨẏ.ʹﮃ(93);
        return;
      case 94:
        (ۥ1 = this).ᐨẏ.ʹﮃ(94);
        return;
      case 95:
        (ۥ1 = this).ᐨẏ.ʹﮃ(95);
        return;
      case 96:
        ٴӵ(ˑܘ.ʹﮃ);
        return;
      case 97:
        ٴӵ(ˑܘ.ˍɫ);
        return;
      case 98:
        ٴӵ(ˑܘ.ՙᗮ);
        return;
      case 99:
        ٴӵ(ˑܘ.ʽ);
        return;
      case 100:
        ᴵƚ(ˑܘ.ʹﮃ);
        return;
      case 101:
        ᴵƚ(ˑܘ.ˍɫ);
        return;
      case 102:
        ᴵƚ(ˑܘ.ՙᗮ);
        return;
      case 103:
        ᴵƚ(ˑܘ.ʽ);
        return;
      case 104:
        ˌ(ˑܘ.ʹﮃ);
        return;
      case 105:
        ˌ(ˑܘ.ˍɫ);
        return;
      case 106:
        ˌ(ˑܘ.ՙᗮ);
        return;
      case 107:
        ˌ(ˑܘ.ʽ);
        return;
      case 108:
        ˍ(ˑܘ.ʹﮃ);
        return;
      case 109:
        ˍ(ˑܘ.ˍɫ);
        return;
      case 110:
        ˍ(ˑܘ.ՙᗮ);
        return;
      case 111:
        ˍ(ˑܘ.ʽ);
        return;
      case 112:
        ʹō(ˑܘ.ʹﮃ);
        return;
      case 113:
        ʹō(ˑܘ.ˍɫ);
        return;
      case 114:
        ʹō(ˑܘ.ՙᗮ);
        return;
      case 115:
        ʹō(ˑܘ.ʽ);
        return;
      case 116:
        ᐝᵣ(ˑܘ.ʹﮃ);
        return;
      case 117:
        ᐝᵣ(ˑܘ.ˍɫ);
        return;
      case 118:
        ᐝᵣ(ˑܘ.ՙᗮ);
        return;
      case 119:
        ᐝᵣ(ˑܘ.ʽ);
        return;
      case 120:
        ᔪ(ˑܘ.ʹﮃ);
        return;
      case 121:
        ᔪ(ˑܘ.ˍɫ);
        return;
      case 122:
        ʿλ(ˑܘ.ʹﮃ);
        return;
      case 123:
        ʿλ(ˑܘ.ˍɫ);
        return;
      case 124:
        ˉｓ(ˑܘ.ʹﮃ);
        return;
      case 125:
        ˉｓ(ˑܘ.ˍɫ);
        return;
      case 126:
        ʿপ(ˑܘ.ʹﮃ);
        return;
      case 127:
        ʿপ(ˑܘ.ˍɫ);
        return;
      case 128:
        ʻล(ˑܘ.ʹﮃ);
        return;
      case 129:
        ʻล(ˑܘ.ˍɫ);
        return;
      case 130:
        ˈے(ˑܘ.ʹﮃ);
        return;
      case 131:
        ˈے(ˑܘ.ˍɫ);
        return;
      case 133:
        ˊ(ˑܘ.ʹﮃ, ˑܘ.ˍɫ);
        return;
      case 134:
        ˊ(ˑܘ.ʹﮃ, ˑܘ.ՙᗮ);
        return;
      case 135:
        ˊ(ˑܘ.ʹﮃ, ˑܘ.ʽ);
        return;
      case 136:
        ˊ(ˑܘ.ˍɫ, ˑܘ.ʹﮃ);
        return;
      case 137:
        ˊ(ˑܘ.ˍɫ, ˑܘ.ՙᗮ);
        return;
      case 138:
        ˊ(ˑܘ.ˍɫ, ˑܘ.ʽ);
        return;
      case 139:
        ˊ(ˑܘ.ՙᗮ, ˑܘ.ʹﮃ);
        return;
      case 140:
        ˊ(ˑܘ.ՙᗮ, ˑܘ.ˍɫ);
        return;
      case 141:
        ˊ(ˑܘ.ՙᗮ, ˑܘ.ʽ);
        return;
      case 142:
        ˊ(ˑܘ.ʽ, ˑܘ.ʹﮃ);
        return;
      case 143:
        ˊ(ˑܘ.ʽ, ˑܘ.ˍɫ);
        return;
      case 144:
        ˊ(ˑܘ.ʽ, ˑܘ.ՙᗮ);
        return;
      case 145:
        ˊ(ˑܘ.ʹﮃ, ˑܘ.ﾞл);
        return;
      case 146:
        ˊ(ˑܘ.ʹﮃ, ˑܘ.ᴵʖ);
        return;
      case 147:
        ˊ(ˑܘ.ʹﮃ, ˑܘ.ʿᵉ);
        return;
      case 148:
        (ۥ1 = this).ᐨẏ.ʹﮃ(148);
        return;
      case 149:
        ـﭔ(ˑܘ.ՙᗮ);
        return;
      case 150:
        ʼᵖ(ˑܘ.ՙᗮ);
        return;
      case 151:
        ـﭔ(ˑܘ.ʽ);
        return;
      case 152:
        ʼᵖ(ˑܘ.ʽ);
        return;
      case 172:
        ﾞǰ(ˑܘ.ʹﮃ);
        return;
      case 173:
        ﾞǰ(ˑܘ.ˍɫ);
        return;
      case 174:
        ﾞǰ(ˑܘ.ՙᗮ);
        return;
      case 175:
        ﾞǰ(ˑܘ.ʽ);
        return;
      case 176:
        ﾞǰ(ͺо);
        return;
      case 177:
        ﾞǰ(ˑܘ.ᐨẏ);
        return;
      case 190:
        (ۥ1 = this).ᐨẏ.ʹﮃ(190);
        return;
      case 191:
        (ۥ1 = this).ᐨẏ.ʹﮃ(191);
        return;
      case 194:
        (ۥ1 = this).ᐨẏ.ʹﮃ(194);
        return;
      case 195:
        (ۥ1 = this).ᐨẏ.ʹﮃ(195);
        return;
    } 
    throw new IllegalArgumentException();
  }
  
  public final void ˊ(int paramInt1, int paramInt2) {
    switch (paramInt1) {
      case 16:
        ʾ(paramInt2);
        return;
      case 17:
        ʾ(paramInt2);
        return;
      case 188:
        switch (paramInt2) {
          case 4:
            ˌх(ˑܘ.ˊ);
            return;
          case 5:
            ˌх(ˑܘ.ᴵʖ);
            return;
          case 8:
            ˌх(ˑܘ.ﾞл);
            return;
          case 9:
            ˌх(ˑܘ.ʿᵉ);
            return;
          case 10:
            ˌх(ˑܘ.ʹﮃ);
            return;
          case 6:
            ˌх(ˑܘ.ՙᗮ);
            return;
          case 11:
            ˌх(ˑܘ.ˍɫ);
            return;
          case 7:
            ˌх(ˑܘ.ʽ);
            return;
        } 
        throw new IllegalArgumentException();
    } 
    throw new IllegalArgumentException();
  }
  
  public final void ᴵʖ(int paramInt1, int paramInt2) {
    ۥ ۥ1;
    switch (paramInt1) {
      case 21:
        ʹﮃ(paramInt2, ˑܘ.ʹﮃ);
        return;
      case 22:
        ʹﮃ(paramInt2, ˑܘ.ˍɫ);
        return;
      case 23:
        ʹﮃ(paramInt2, ˑܘ.ՙᗮ);
        return;
      case 24:
        ʹﮃ(paramInt2, ˑܘ.ʽ);
        return;
      case 25:
        ʹﮃ(paramInt2, ͺо);
        return;
      case 54:
        ՙᗮ(paramInt2, ˑܘ.ʹﮃ);
        return;
      case 55:
        ՙᗮ(paramInt2, ˑܘ.ˍɫ);
        return;
      case 56:
        ՙᗮ(paramInt2, ˑܘ.ՙᗮ);
        return;
      case 57:
        ՙᗮ(paramInt2, ˑܘ.ʽ);
        return;
      case 58:
        ՙᗮ(paramInt2, ͺо);
        return;
      case 169:
        paramInt2 = paramInt2;
        (ۥ1 = this).ᐨẏ.ᴵʖ(169, paramInt2);
        return;
    } 
    throw new IllegalArgumentException();
  }
  
  public final void ᐨẏ(int paramInt, String paramString) {
    ۥ ۥ1;
    ˑܘ ˑܘ1 = ˑܘ.ˊ(paramString);
    switch (paramInt) {
      case 187:
        ˑܘ1 = ˑܘ1;
        (ۥ1 = this).ᐨẏ.ᐨẏ(187, ˑܘ1.ՙᗮ());
        return;
      case 189:
        ˌх(ˑܘ1);
        return;
      case 192:
        ˑܘ1 = ˑܘ1;
        (ۥ1 = this).ᐨẏ.ᐨẏ(192, ˑܘ1.ՙᗮ());
        return;
      case 193:
        ˑܘ1 = ˑܘ1;
        (ۥ1 = this).ᐨẏ.ᐨẏ(193, ˑܘ1.ՙᗮ());
        return;
    } 
    throw new IllegalArgumentException();
  }
  
  public final void ᐨẏ(int paramInt, String paramString1, String paramString2, String paramString3) {
    ۥ ۥ1;
    switch (paramInt) {
      case 178:
        paramString3 = paramString3;
        paramString2 = paramString2;
        paramString1 = paramString1;
        (ۥ1 = this).ᐨẏ.ᐨẏ(178, paramString1, paramString2, paramString3);
        return;
      case 179:
        paramString3 = paramString3;
        paramString2 = paramString2;
        paramString1 = paramString1;
        (ۥ1 = this).ᐨẏ.ᐨẏ(179, paramString1, paramString2, paramString3);
        return;
      case 180:
        paramString3 = paramString3;
        paramString2 = paramString2;
        paramString1 = paramString1;
        (ۥ1 = this).ᐨẏ.ᐨẏ(180, paramString1, paramString2, paramString3);
        return;
      case 181:
        paramString3 = paramString3;
        paramString2 = paramString2;
        paramString1 = paramString1;
        (ۥ1 = this).ᐨẏ.ᐨẏ(181, paramString1, paramString2, paramString3);
        return;
    } 
    throw new IllegalArgumentException();
  }
  
  public final void ᐨẏ(int paramInt, String paramString1, String paramString2, String paramString3, boolean paramBoolean) {
    ۥ ۥ1;
    if (this.ᐨẏ < 327680 && (paramInt & 0x100) == 0) {
      super.ᐨẏ(paramInt, paramString1, paramString2, paramString3, paramBoolean);
      return;
    } 
    switch (paramInt &= 0xFFFFFEFF) {
      case 183:
        ˊ(paramString1, paramString2, paramString3, paramBoolean);
        return;
      case 182:
        ᐨẏ(paramString1, paramString2, paramString3, paramBoolean);
        return;
      case 184:
        ᴵʖ(paramString1, paramString2, paramString3, paramBoolean);
        return;
      case 185:
        paramString3 = paramString3;
        paramString2 = paramString2;
        paramString1 = paramString1;
        (ۥ1 = this).ᐨẏ.ᐨẏ(185, paramString1, paramString2, paramString3, true);
        return;
    } 
    throw new IllegalArgumentException();
  }
  
  public final void ᐨẏ(String paramString1, String paramString2, ʹō paramʹō, Object... paramVarArgs) {
    Object[] arrayOfObject = paramVarArgs;
    ʹō ʹō1 = paramʹō;
    String str = paramString2;
    paramString2 = paramString1;
    ۥ ۥ1;
    (ۥ1 = this).ᐨẏ.ᐨẏ(paramString2, str, ʹō1, arrayOfObject);
  }
  
  public final void ᐨẏ(int paramInt, ᔪ paramᔪ) {
    ۥ ۥ1;
    switch (paramInt) {
      case 153:
        paramᔪ = paramᔪ;
        (ۥ1 = this).ᐨẏ.ᐨẏ(153, paramᔪ);
        return;
      case 154:
        paramᔪ = paramᔪ;
        (ۥ1 = this).ᐨẏ.ᐨẏ(154, paramᔪ);
        return;
      case 155:
        paramᔪ = paramᔪ;
        (ۥ1 = this).ᐨẏ.ᐨẏ(155, paramᔪ);
        return;
      case 156:
        paramᔪ = paramᔪ;
        (ۥ1 = this).ᐨẏ.ᐨẏ(156, paramᔪ);
        return;
      case 157:
        paramᔪ = paramᔪ;
        (ۥ1 = this).ᐨẏ.ᐨẏ(157, paramᔪ);
        return;
      case 158:
        paramᔪ = paramᔪ;
        (ۥ1 = this).ᐨẏ.ᐨẏ(158, paramᔪ);
        return;
      case 159:
        paramᔪ = paramᔪ;
        (ۥ1 = this).ᐨẏ.ᐨẏ(159, paramᔪ);
        return;
      case 160:
        paramᔪ = paramᔪ;
        (ۥ1 = this).ᐨẏ.ᐨẏ(160, paramᔪ);
        return;
      case 161:
        paramᔪ = paramᔪ;
        (ۥ1 = this).ᐨẏ.ᐨẏ(161, paramᔪ);
        return;
      case 162:
        paramᔪ = paramᔪ;
        (ۥ1 = this).ᐨẏ.ᐨẏ(162, paramᔪ);
        return;
      case 163:
        paramᔪ = paramᔪ;
        (ۥ1 = this).ᐨẏ.ᐨẏ(163, paramᔪ);
        return;
      case 164:
        paramᔪ = paramᔪ;
        (ۥ1 = this).ᐨẏ.ᐨẏ(164, paramᔪ);
        return;
      case 165:
        paramᔪ = paramᔪ;
        (ۥ1 = this).ᐨẏ.ᐨẏ(165, paramᔪ);
        return;
      case 166:
        paramᔪ = paramᔪ;
        (ۥ1 = this).ᐨẏ.ᐨẏ(166, paramᔪ);
        return;
      case 167:
        paramᔪ = paramᔪ;
        (ۥ1 = this).ᐨẏ.ᐨẏ(167, paramᔪ);
        return;
      case 168:
        paramᔪ = paramᔪ;
        (ۥ1 = this).ᐨẏ.ᐨẏ(168, paramᔪ);
        return;
      case 198:
        paramᔪ = paramᔪ;
        (ۥ1 = this).ᐨẏ.ᐨẏ(198, paramᔪ);
        return;
      case 199:
        paramᔪ = paramᔪ;
        (ۥ1 = this).ᐨẏ.ᐨẏ(199, paramᔪ);
        return;
    } 
    throw new IllegalArgumentException();
  }
  
  public final void ˊ(ᔪ paramᔪ) {
    ᔪ ᔪ1 = paramᔪ;
    ۥ ۥ1;
    (ۥ1 = this).ᐨẏ.ˊ(ᔪ1);
  }
  
  public final void ˊ(Object paramObject) {
    if (this.ᐨẏ < 327680 && (paramObject instanceof ʹō || (paramObject instanceof ˑܘ && ((ˑܘ)paramObject).ˉｓ() == 11))) {
      "愄뗪᪮㝺鎻숮뮼띊؟‒샫친먑쬔瀙밴ㅽ셠엺苻샄㽽꾳ඬ".toCharArray()[0] = (char)("愄뗪᪮㝺鎻숮뮼띊؟‒샫친먑쬔瀙밴ㅽ셠엺苻샄㽽꾳ඬ".toCharArray()[0] ^ 0x2221);
      throw new UnsupportedOperationException(ᐨẏ$ᐝт.W("愄뗪᪮㝺鎻숮뮼띊؟‒샫친먑쬔瀙밴ㅽ셠엺苻샄㽽꾳ඬ".toCharArray(), (short)12598, (byte)3, (short)2));
    } 
    if (this.ᐨẏ < 458752 && paramObject instanceof ʾܪ) {
      "孖榄뒚Ԍ兢൧ꑿ䳳㻈钩∜띀㵡隱譊啯?ᘭꎡ쇧뺉䷨ꜜ揠⺼".toCharArray()[10] = (char)("孖榄뒚Ԍ兢൧ꑿ䳳㻈钩∜띀㵡隱譊啯?ᘭꎡ쇧뺉䷨ꜜ揠⺼".toCharArray()[10] ^ 0x65AE);
      throw new UnsupportedOperationException(ᐨẏ$ᐝт.W("孖榄뒚Ԍ兢൧ꑿ䳳㻈钩∜띀㵡隱譊啯?ᘭꎡ쇧뺉䷨ꜜ揠⺼".toCharArray(), (short)10559, (byte)3, (short)3));
    } 
    if (paramObject instanceof Integer) {
      ʾ(((Integer)paramObject).intValue());
      return;
    } 
    if (paramObject instanceof Byte) {
      ʾ(((Byte)paramObject).intValue());
      return;
    } 
    if (paramObject instanceof Character) {
      ʾ(((Character)paramObject).charValue());
      return;
    } 
    if (paramObject instanceof Short) {
      ʾ(((Short)paramObject).intValue());
      return;
    } 
    if (paramObject instanceof Boolean) {
      ʾ(((Boolean)paramObject).booleanValue() ? 1 : 0);
      return;
    } 
    if (paramObject instanceof Float) {
      ˊ(((Float)paramObject).floatValue());
      return;
    } 
    if (paramObject instanceof Long) {
      ˊ(((Long)paramObject).longValue());
      return;
    } 
    if (paramObject instanceof Double) {
      ˊ(((Double)paramObject).doubleValue());
      return;
    } 
    if (paramObject instanceof String) {
      ʹﮃ(paramObject);
      return;
    } 
    if (paramObject instanceof ˑܘ) {
      ˑܘ ˑܘ1 = (ˑܘ)paramObject;
      ((ۥ)(paramObject = this)).ᐨẏ.ˊ(ˑܘ1);
      return;
    } 
    if (paramObject instanceof ʹō) {
      ʹō ʹō = (ʹō)paramObject;
      ((ۥ)(paramObject = this)).ᐨẏ.ˊ(ʹō);
      return;
    } 
    if (paramObject instanceof ʾܪ) {
      ʾܪ ʾܪ = (ʾܪ)paramObject;
      ((ۥ)(paramObject = this)).ᐨẏ.ˊ(ʾܪ);
      return;
    } 
    throw new IllegalArgumentException();
  }
  
  public final void ﾞл(int paramInt1, int paramInt2) {
    int i = paramInt2;
    paramInt2 = paramInt1;
    ۥ ۥ1;
    (ۥ1 = this).ᐨẏ.ﾞл(paramInt2, i);
  }
  
  public final void ᐨẏ(int paramInt1, int paramInt2, ᔪ paramᔪ, ᔪ... paramVarArgs) {
    ᔪ[] arrayOfᔪ = paramVarArgs;
    ᔪ ᔪ1 = paramᔪ;
    int i = paramInt2;
    paramInt2 = paramInt1;
    ۥ ۥ1;
    (ۥ1 = this).ᐨẏ.ᐨẏ(paramInt2, i, ᔪ1, arrayOfᔪ);
  }
  
  public final void ᐨẏ(ᔪ paramᔪ, int[] paramArrayOfint, ᔪ[] paramArrayOfᔪ) {
    ᔪ[] arrayOfᔪ = paramArrayOfᔪ;
    int[] arrayOfInt = paramArrayOfint;
    ᔪ ᔪ1 = paramᔪ;
    ۥ ۥ1;
    (ۥ1 = this).ᐨẏ.ᐨẏ(ᔪ1, arrayOfInt, arrayOfᔪ);
  }
  
  public final void ˊ(String paramString, int paramInt) {
    int i = paramInt;
    String str = paramString;
    ۥ ۥ1;
    (ۥ1 = this).ᐨẏ.ˊ(str, i);
  }
  
  private void ιﾌ() {
    this.ᐨẏ.ʹﮃ(0);
  }
  
  private void ʹﮃ(Object paramObject) {
    if (paramObject == null) {
      this.ᐨẏ.ʹﮃ(1);
      return;
    } 
    this.ᐨẏ.ˊ(paramObject);
  }
  
  private void ʾ(int paramInt) {
    if (paramInt >= -1 && paramInt <= 5) {
      this.ᐨẏ.ʹﮃ(paramInt + 3);
      return;
    } 
    if (paramInt >= -128 && paramInt <= 127) {
      this.ᐨẏ.ˊ(16, paramInt);
      return;
    } 
    if (paramInt >= -32768 && paramInt <= 32767) {
      this.ᐨẏ.ˊ(17, paramInt);
      return;
    } 
    this.ᐨẏ.ˊ(Integer.valueOf(paramInt));
  }
  
  private void ˊ(long paramLong) {
    if (paramLong == 0L || paramLong == 1L) {
      this.ᐨẏ.ʹﮃ(9 + (int)paramLong);
      return;
    } 
    this.ᐨẏ.ˊ(Long.valueOf(paramLong));
  }
  
  private void ˊ(float paramFloat) {
    int i;
    if ((i = Float.floatToIntBits(paramFloat)) == 0L || i == 1065353216 || i == 1073741824) {
      this.ᐨẏ.ʹﮃ(11 + (int)paramFloat);
      return;
    } 
    this.ᐨẏ.ˊ(Float.valueOf(paramFloat));
  }
  
  private void ˊ(double paramDouble) {
    long l;
    if ((l = Double.doubleToLongBits(paramDouble)) == 0L || l == 4607182418800017408L) {
      this.ᐨẏ.ʹﮃ(14 + (int)paramDouble);
      return;
    } 
    this.ᐨẏ.ˊ(Double.valueOf(paramDouble));
  }
  
  private void ᐨم(ˑܘ paramˑܘ) {
    this.ᐨẏ.ˊ(paramˑܘ);
  }
  
  private void ˊ(ʹō paramʹō) {
    this.ᐨẏ.ˊ(paramʹō);
  }
  
  private void ˊ(ʾܪ paramʾܪ) {
    this.ᐨẏ.ˊ(paramʾܪ);
  }
  
  private void ʹﮃ(int paramInt, ˑܘ paramˑܘ) {
    this.ᐨẏ.ᴵʖ(paramˑܘ.ʹﮃ(21), paramInt);
  }
  
  private void ʾ(ˑܘ paramˑܘ) {
    this.ᐨẏ.ʹﮃ(paramˑܘ.ʹﮃ(46));
  }
  
  private void ՙᗮ(int paramInt, ˑܘ paramˑܘ) {
    this.ᐨẏ.ᴵʖ(paramˑܘ.ʹﮃ(54), paramInt);
  }
  
  private void ͺо(ˑܘ paramˑܘ) {
    this.ᐨẏ.ʹﮃ(paramˑܘ.ʹﮃ(79));
  }
  
  private void ᴵƚ() {
    this.ᐨẏ.ʹﮃ(87);
  }
  
  private void ˌ() {
    this.ᐨẏ.ʹﮃ(88);
  }
  
  private void ˍ() {
    this.ᐨẏ.ʹﮃ(89);
  }
  
  private void ʹō() {
    this.ᐨẏ.ʹﮃ(92);
  }
  
  private void ᐝᵣ() {
    this.ᐨẏ.ʹﮃ(90);
  }
  
  private void ᔪ() {
    this.ᐨẏ.ʹﮃ(91);
  }
  
  private void ʿλ() {
    this.ᐨẏ.ʹﮃ(93);
  }
  
  private void ˉｓ() {
    this.ᐨẏ.ʹﮃ(94);
  }
  
  private void ʿপ() {
    this.ᐨẏ.ʹﮃ(95);
  }
  
  private void ٴӵ(ˑܘ paramˑܘ) {
    this.ᐨẏ.ʹﮃ(paramˑܘ.ʹﮃ(96));
  }
  
  private void ᴵƚ(ˑܘ paramˑܘ) {
    this.ᐨẏ.ʹﮃ(paramˑܘ.ʹﮃ(100));
  }
  
  private void ˌ(ˑܘ paramˑܘ) {
    this.ᐨẏ.ʹﮃ(paramˑܘ.ʹﮃ(104));
  }
  
  private void ˍ(ˑܘ paramˑܘ) {
    this.ᐨẏ.ʹﮃ(paramˑܘ.ʹﮃ(108));
  }
  
  private void ʹō(ˑܘ paramˑܘ) {
    this.ᐨẏ.ʹﮃ(paramˑܘ.ʹﮃ(112));
  }
  
  private void ᐝᵣ(ˑܘ paramˑܘ) {
    this.ᐨẏ.ʹﮃ(paramˑܘ.ʹﮃ(116));
  }
  
  private void ᔪ(ˑܘ paramˑܘ) {
    this.ᐨẏ.ʹﮃ(paramˑܘ.ʹﮃ(120));
  }
  
  private void ʿλ(ˑܘ paramˑܘ) {
    this.ᐨẏ.ʹﮃ(paramˑܘ.ʹﮃ(122));
  }
  
  private void ˉｓ(ˑܘ paramˑܘ) {
    this.ᐨẏ.ʹﮃ(paramˑܘ.ʹﮃ(124));
  }
  
  private void ʿপ(ˑܘ paramˑܘ) {
    this.ᐨẏ.ʹﮃ(paramˑܘ.ʹﮃ(126));
  }
  
  private void ʻล(ˑܘ paramˑܘ) {
    this.ᐨẏ.ʹﮃ(paramˑܘ.ʹﮃ(128));
  }
  
  private void ˈے(ˑܘ paramˑܘ) {
    this.ᐨẏ.ʹﮃ(paramˑܘ.ʹﮃ(130));
  }
  
  private void ʾܪ(int paramInt1, int paramInt2) {
    this.ᐨẏ.ﾞл(paramInt1, paramInt2);
  }
  
  private void ˊ(ˑܘ paramˑܘ1, ˑܘ paramˑܘ2) {
    ᐨẏ(this.ᐨẏ, paramˑܘ1, paramˑܘ2);
  }
  
  static void ᐨẏ(ˉｓ paramˉｓ, ˑܘ paramˑܘ1, ˑܘ paramˑܘ2) {
    if (!zubdqvgt.G(paramˑܘ1, paramˑܘ2)) {
      if (zubdqvgt.G(paramˑܘ1, ˑܘ.ʽ)) {
        if (zubdqvgt.G(paramˑܘ2, ˑܘ.ՙᗮ)) {
          paramˉｓ.ʹﮃ(144);
          return;
        } 
        if (zubdqvgt.G(paramˑܘ2, ˑܘ.ˍɫ)) {
          paramˉｓ.ʹﮃ(143);
          return;
        } 
        paramˉｓ.ʹﮃ(142);
        ᐨẏ(paramˉｓ, ˑܘ.ʹﮃ, paramˑܘ2);
        return;
      } 
      if (zubdqvgt.G(paramˑܘ1, ˑܘ.ՙᗮ)) {
        if (zubdqvgt.G(paramˑܘ2, ˑܘ.ʽ)) {
          paramˉｓ.ʹﮃ(141);
          return;
        } 
        if (zubdqvgt.G(paramˑܘ2, ˑܘ.ˍɫ)) {
          paramˉｓ.ʹﮃ(140);
          return;
        } 
        paramˉｓ.ʹﮃ(139);
        ᐨẏ(paramˉｓ, ˑܘ.ʹﮃ, paramˑܘ2);
        return;
      } 
      if (zubdqvgt.G(paramˑܘ1, ˑܘ.ˍɫ)) {
        if (zubdqvgt.G(paramˑܘ2, ˑܘ.ʽ)) {
          paramˉｓ.ʹﮃ(138);
          return;
        } 
        if (zubdqvgt.G(paramˑܘ2, ˑܘ.ՙᗮ)) {
          paramˉｓ.ʹﮃ(137);
          return;
        } 
        paramˉｓ.ʹﮃ(136);
        ᐨẏ(paramˉｓ, ˑܘ.ʹﮃ, paramˑܘ2);
        return;
      } 
      if (zubdqvgt.G(paramˑܘ2, ˑܘ.ﾞл)) {
        paramˉｓ.ʹﮃ(145);
        return;
      } 
      if (zubdqvgt.G(paramˑܘ2, ˑܘ.ᴵʖ)) {
        paramˉｓ.ʹﮃ(146);
        return;
      } 
      if (zubdqvgt.G(paramˑܘ2, ˑܘ.ʽ)) {
        paramˉｓ.ʹﮃ(135);
        return;
      } 
      if (zubdqvgt.G(paramˑܘ2, ˑܘ.ՙᗮ)) {
        paramˉｓ.ʹﮃ(134);
        return;
      } 
      if (zubdqvgt.G(paramˑܘ2, ˑܘ.ˍɫ)) {
        paramˉｓ.ʹﮃ(133);
        return;
      } 
      if (zubdqvgt.G(paramˑܘ2, ˑܘ.ʿᵉ))
        paramˉｓ.ʹﮃ(147); 
    } 
  }
  
  private void ʻւ() {
    this.ᐨẏ.ʹﮃ(148);
  }
  
  private void ـﭔ(ˑܘ paramˑܘ) {
    this.ᐨẏ.ʹﮃ(zubdqvgt.G(paramˑܘ, ˑܘ.ՙᗮ) ? 149 : 151);
  }
  
  private void ʼᵖ(ˑܘ paramˑܘ) {
    this.ᐨẏ.ʹﮃ(zubdqvgt.G(paramˑܘ, ˑܘ.ՙᗮ) ? 150 : 152);
  }
  
  private void ˍɫ(ᔪ paramᔪ) {
    this.ᐨẏ.ᐨẏ(153, paramᔪ);
  }
  
  private void ʽ(ᔪ paramᔪ) {
    this.ᐨẏ.ᐨẏ(154, paramᔪ);
  }
  
  private void ʾܪ(ᔪ paramᔪ) {
    this.ᐨẏ.ᐨẏ(155, paramᔪ);
  }
  
  private void ᐨم(ᔪ paramᔪ) {
    this.ᐨẏ.ᐨẏ(156, paramᔪ);
  }
  
  private void ʾ(ᔪ paramᔪ) {
    this.ᐨẏ.ᐨẏ(157, paramᔪ);
  }
  
  private void ͺо(ᔪ paramᔪ) {
    this.ᐨẏ.ᐨẏ(158, paramᔪ);
  }
  
  private void ٴӵ(ᔪ paramᔪ) {
    this.ᐨẏ.ᐨẏ(159, paramᔪ);
  }
  
  private void ᴵƚ(ᔪ paramᔪ) {
    this.ᐨẏ.ᐨẏ(160, paramᔪ);
  }
  
  private void ˌ(ᔪ paramᔪ) {
    this.ᐨẏ.ᐨẏ(161, paramᔪ);
  }
  
  private void ˍ(ᔪ paramᔪ) {
    this.ᐨẏ.ᐨẏ(162, paramᔪ);
  }
  
  private void ʹō(ᔪ paramᔪ) {
    this.ᐨẏ.ᐨẏ(163, paramᔪ);
  }
  
  private void ᐝᵣ(ᔪ paramᔪ) {
    this.ᐨẏ.ᐨẏ(164, paramᔪ);
  }
  
  private void ᔪ(ᔪ paramᔪ) {
    this.ᐨẏ.ᐨẏ(165, paramᔪ);
  }
  
  private void ʿλ(ᔪ paramᔪ) {
    this.ᐨẏ.ᐨẏ(166, paramᔪ);
  }
  
  private void ՙᗮ(ᔪ paramᔪ) {
    this.ᐨẏ.ᐨẏ(167, paramᔪ);
  }
  
  private void ˉｓ(ᔪ paramᔪ) {
    this.ᐨẏ.ᐨẏ(168, paramᔪ);
  }
  
  private void ᐨم(int paramInt) {
    this.ᐨẏ.ᴵʖ(169, paramInt);
  }
  
  private void ˊ(int paramInt1, int paramInt2, ᔪ paramᔪ, ᔪ... paramVarArgs) {
    this.ᐨẏ.ᐨẏ(paramInt1, paramInt2, paramᔪ, paramVarArgs);
  }
  
  private void ˊ(ᔪ paramᔪ, int[] paramArrayOfint, ᔪ[] paramArrayOfᔪ) {
    this.ᐨẏ.ᐨẏ(paramᔪ, paramArrayOfint, paramArrayOfᔪ);
  }
  
  private void ﾞǰ(ˑܘ paramˑܘ) {
    this.ᐨẏ.ʹﮃ(paramˑܘ.ʹﮃ(172));
  }
  
  private void ᴵʖ(String paramString1, String paramString2, String paramString3) {
    this.ᐨẏ.ᐨẏ(178, paramString1, paramString2, paramString3);
  }
  
  private void ﾞл(String paramString1, String paramString2, String paramString3) {
    this.ᐨẏ.ᐨẏ(179, paramString1, paramString2, paramString3);
  }
  
  private void ʿᵉ(String paramString1, String paramString2, String paramString3) {
    this.ᐨẏ.ᐨẏ(180, paramString1, paramString2, paramString3);
  }
  
  private void ʹﮃ(String paramString1, String paramString2, String paramString3) {
    this.ᐨẏ.ᐨẏ(181, paramString1, paramString2, paramString3);
  }
  
  @Deprecated
  private void ՙᗮ(String paramString1, String paramString2, String paramString3) {
    if (this.ᐨẏ >= 327680) {
      ᐨẏ(paramString1, paramString2, paramString3, false);
      return;
    } 
    this.ᐨẏ.ˊ(182, paramString1, paramString2, paramString3);
  }
  
  private void ᐨẏ(String paramString1, String paramString2, String paramString3, boolean paramBoolean) {
    if (this.ᐨẏ < 327680) {
      if (paramBoolean) {
        "硫᫬閚⎱ꢻ⍛靼䓥둸囓潤ꮁ윚ㆶꠥ塞᯴⸓笝짺㠏拏같䙷Ꚍ酫ⅿᥠ鹻돉髉鶌ｻ갱ꛓ灢翋".toCharArray()[22] = (char)("硫᫬閚⎱ꢻ⍛靼䓥둸囓潤ꮁ윚ㆶꠥ塞᯴⸓笝짺㠏拏같䙷Ꚍ酫ⅿᥠ鹻돉髉鶌ｻ갱ꛓ灢翋".toCharArray()[22] ^ 0x5D5);
        throw new UnsupportedOperationException(ˍɫ$יς.J("硫᫬閚⎱ꢻ⍛靼䓥둸囓潤ꮁ윚ㆶꠥ塞᯴⸓笝짺㠏拏같䙷Ꚍ酫ⅿᥠ鹻돉髉鶌ｻ갱ꛓ灢翋".toCharArray(), (short)30582, (short)5, (byte)5));
      } 
      ՙᗮ(paramString1, paramString2, paramString3);
      return;
    } 
    this.ᐨẏ.ᐨẏ(182, paramString1, paramString2, paramString3, paramBoolean);
  }
  
  @Deprecated
  private void ˍɫ(String paramString1, String paramString2, String paramString3) {
    if (this.ᐨẏ >= 327680) {
      ˊ(paramString1, paramString2, paramString3, false);
      return;
    } 
    this.ᐨẏ.ᐨẏ(183, paramString1, paramString2, paramString3, false);
  }
  
  private void ˊ(String paramString1, String paramString2, String paramString3, boolean paramBoolean) {
    if (this.ᐨẏ < 327680) {
      if (paramBoolean) {
        "猪晽뮶혚ꅄ놊㠠贒Ⳓ公ణ푷採妷䩖㕅ਲ਼笡?笼㕬Ԩ畃緱崙꼰ެ碽♧琈ౖ렘啀섚쌱씷杻웢잳㔸".toCharArray()[37] = (char)("猪晽뮶혚ꅄ놊㠠贒Ⳓ公ణ푷採妷䩖㕅ਲ਼笡?笼㕬Ԩ畃緱崙꼰ެ碽♧琈ౖ렘啀섚쌱씷杻웢잳㔸".toCharArray()[37] ^ 0x2049);
        throw new UnsupportedOperationException(ˍɫ$יς.J("猪晽뮶혚ꅄ놊㠠贒Ⳓ公ణ푷採妷䩖㕅ਲ਼笡?笼㕬Ԩ畃緱崙꼰ެ碽♧琈ౖ렘啀섚쌱씷杻웢잳㔸".toCharArray(), (short)31946, (short)1, (byte)1));
      } 
      ˍɫ(paramString1, paramString2, paramString3);
      return;
    } 
    this.ᐨẏ.ᐨẏ(183, paramString1, paramString2, paramString3, paramBoolean);
  }
  
  @Deprecated
  private void ʽ(String paramString1, String paramString2, String paramString3) {
    if (this.ᐨẏ >= 327680) {
      ᴵʖ(paramString1, paramString2, paramString3, false);
      return;
    } 
    this.ᐨẏ.ᐨẏ(184, paramString1, paramString2, paramString3, false);
  }
  
  private void ᴵʖ(String paramString1, String paramString2, String paramString3, boolean paramBoolean) {
    if (this.ᐨẏ < 327680) {
      if (paramBoolean) {
        "犒Ꙉ䭎謢ᅶ굸쯟撺렸䦬絃̥즏㯡첱ꀬ晩徜䵓裵ࡖ⵿夳囿盃獒蚼鱞䞘磄⁪䈥駁콀徺㠻".toCharArray()[37] = (char)("犒Ꙉ䭎謢ᅶ굸쯟撺렸䦬絃̥즏㯡첱ꀬ晩徜䵓裵ࡖ⵿夳囿盃獒蚼鱞䞘磄⁪䈥駁콀徺㠻".toCharArray()[37] ^ 0x6E07);
        throw new UnsupportedOperationException(ˍɫ$יς.J("犒Ꙉ䭎謢ᅶ굸쯟撺렸䦬絃̥즏㯡첱ꀬ晩徜䵓裵ࡖ⵿夳囿盃獒蚼鱞䞘磄⁪䈥駁콀徺㠻".toCharArray(), (short)23048, (short)0, (byte)2));
      } 
      ʽ(paramString1, paramString2, paramString3);
      return;
    } 
    this.ᐨẏ.ᐨẏ(184, paramString1, paramString2, paramString3, paramBoolean);
  }
  
  private void ʾܪ(String paramString1, String paramString2, String paramString3) {
    this.ᐨẏ.ᐨẏ(185, paramString1, paramString2, paramString3, true);
  }
  
  private void ᴵʖ(String paramString1, String paramString2, ʹō paramʹō, Object[] paramArrayOfObject) {
    this.ᐨẏ.ᐨẏ(paramString1, paramString2, paramʹō, paramArrayOfObject);
  }
  
  private void ˊᵃ(ˑܘ paramˑܘ) {
    this.ᐨẏ.ᐨẏ(187, paramˑܘ.ՙᗮ());
  }
  
  private void ˌх(ˑܘ paramˑܘ) {
    ᐨẏ(this.ᐨẏ, paramˑܘ);
  }
  
  static void ᐨẏ(ˉｓ paramˉｓ, ˑܘ paramˑܘ) {
    // Byte code:
    //   0: aload_1
    //   1: invokevirtual ˉｓ : ()I
    //   4: tableswitch default -> 98, 1 -> 52, 2 -> 57, 3 -> 62, 4 -> 68, 5 -> 74, 6 -> 80, 7 -> 86, 8 -> 92
    //   52: iconst_4
    //   53: istore_1
    //   54: goto -> 110
    //   57: iconst_5
    //   58: istore_1
    //   59: goto -> 110
    //   62: bipush #8
    //   64: istore_1
    //   65: goto -> 110
    //   68: bipush #9
    //   70: istore_1
    //   71: goto -> 110
    //   74: bipush #10
    //   76: istore_1
    //   77: goto -> 110
    //   80: bipush #6
    //   82: istore_1
    //   83: goto -> 110
    //   86: bipush #11
    //   88: istore_1
    //   89: goto -> 110
    //   92: bipush #7
    //   94: istore_1
    //   95: goto -> 110
    //   98: aload_0
    //   99: sipush #189
    //   102: aload_1
    //   103: invokevirtual ՙᗮ : ()Ljava/lang/String;
    //   106: invokevirtual ᐨẏ : (ILjava/lang/String;)V
    //   109: return
    //   110: aload_0
    //   111: sipush #188
    //   114: iload_1
    //   115: invokevirtual ˊ : (II)V
    //   118: return
  }
  
  private void ˑܘ() {
    this.ᐨẏ.ʹﮃ(190);
  }
  
  private void ᐧפ() {
    this.ᐨẏ.ʹﮃ(191);
  }
  
  private void ιﾌ(ˑܘ paramˑܘ) {
    this.ᐨẏ.ᐨẏ(192, paramˑܘ.ՙᗮ());
  }
  
  private void ʾܪ(ˑܘ paramˑܘ) {
    this.ᐨẏ.ᐨẏ(193, paramˑܘ.ՙᗮ());
  }
  
  private void ιˠ() {
    this.ᐨẏ.ʹﮃ(194);
  }
  
  private void ˈהּ() {
    this.ᐨẏ.ʹﮃ(195);
  }
  
  private void ᴵʖ(String paramString, int paramInt) {
    this.ᐨẏ.ˊ(paramString, paramInt);
  }
  
  private void ʿপ(ᔪ paramᔪ) {
    this.ᐨẏ.ᐨẏ(198, paramᔪ);
  }
  
  private void ʻล(ᔪ paramᔪ) {
    this.ᐨẏ.ᐨẏ(199, paramᔪ);
  }
  
  private void ﾞл(ᔪ paramᔪ) {
    this.ᐨẏ.ˊ(paramᔪ);
  }
  
  static {
    "羪昐桟佲򓸛弣퐭娉ꗜ擷㧦ﮉ묉禚䘛".toCharArray()[5] = (char)("羪昐桟佲򓸛弣퐭娉ꗜ擷㧦ﮉ묉禚䘛".toCharArray()[5] ^ 0x6334);
  }
}


/* Location:              C:\Users\kb\Downloads\ja-netfilter.jar!\yyds\sniarbtej\ۥ.class
 * Java compiler version: 8 (52.0)
 * JD-Core Version:       1.1.3
 */