package yyds.sniarbtej;

import java.util.ArrayList;
import java.util.List;
import ylt.pmn.zubdqvgt;

public class ᐧє extends ˉｓ {
  public int ᒬ;
  
  public String name;
  
  public String ˎᴗ;
  
  public String ˊﮈ;
  
  public List<String> ـﭔ;
  
  private List<ᐨп> ʼᵖ;
  
  private List<ʾא> ʾ;
  
  private List<ʾא> ͺо;
  
  private List<ʽ冫> ˍɫ;
  
  private List<ʽ冫> ʽ;
  
  private List<ᴵʖ> ٴӵ;
  
  public Object ʹﮃ;
  
  private int শ;
  
  private List<ʾא>[] ᐨẏ;
  
  private int ˋᴷ;
  
  private List<ʾא>[] ˊ;
  
  public ـс ˊ;
  
  public List<ˌț> ﾞǰ;
  
  public int ˑỲ;
  
  public int ˌپ;
  
  public List<ᕻ> ˊᵃ;
  
  private List<ˉḽ> ˌх;
  
  private List<ˉḽ> ιﾌ;
  
  private boolean ͺо;
  
  public ᐧє() {
    this(589824);
    if (!zubdqvgt.G(getClass(), ᐧє.class))
      throw new IllegalStateException(); 
  }
  
  private ᐧє(int paramInt) {
    super(589824);
    this.ˊ = new ـс();
  }
  
  public ᐧє(int paramInt, String paramString1, String paramString2, String paramString3, String[] paramArrayOfString) {
    this(589824, paramInt, paramString1, paramString2, paramString3, paramArrayOfString);
    if (!zubdqvgt.G(getClass(), ᐧє.class))
      throw new IllegalStateException(); 
  }
  
  public ᐧє(int paramInt1, int paramInt2, String paramString1, String paramString2, String paramString3, String[] paramArrayOfString) {
    super(paramInt1);
    this.ᒬ = paramInt2;
    this.name = paramString1;
    this.ˎᴗ = paramString2;
    this.ˊﮈ = paramString3;
    this.ـﭔ = ٴᐤ.ᐨẏ(paramArrayOfString);
    if ((paramInt2 & 0x400) == 0)
      this.ˊᵃ = new ArrayList<>(5); 
    this.ﾞǰ = new ArrayList<>();
    this.ˊ = new ـс();
  }
  
  public final void ᐨẏ(String paramString, int paramInt) {
    if (this.ʼᵖ == null)
      this.ʼᵖ = new ArrayList<>(5); 
    this.ʼᵖ.add(new ᐨп(paramString, paramInt));
  }
  
  public final ᐨẏ ˊ() {
    return new ʾא(new ʹˉ(this, 0));
  }
  
  public final ᐨẏ ᐨẏ(String paramString, boolean paramBoolean) {
    ʾא ʾא = new ʾא(paramString);
    if (paramBoolean) {
      this.ʾ = ٴᐤ.ᐨẏ(this.ʾ, ʾא);
    } else {
      this.ͺо = ٴᐤ.ᐨẏ(this.ͺо, ʾא);
    } 
    return ʾא;
  }
  
  public final ᐨẏ ᐨẏ(int paramInt, ˏɪ paramˏɪ, String paramString, boolean paramBoolean) {
    ʽ冫 ʽ冫 = new ʽ冫(paramInt, paramˏɪ, paramString);
    if (paramBoolean) {
      this.ˍɫ = ٴᐤ.ᐨẏ(this.ˍɫ, ʽ冫);
    } else {
      this.ʽ = ٴᐤ.ᐨẏ(this.ʽ, ʽ冫);
    } 
    return ʽ冫;
  }
  
  public final void ᐨẏ(int paramInt, boolean paramBoolean) {
    if (paramBoolean) {
      this.শ = paramInt;
      return;
    } 
    this.ˋᴷ = paramInt;
  }
  
  public final ᐨẏ ᐨẏ(int paramInt, String paramString, boolean paramBoolean) {
    ʾא ʾא = new ʾא(paramString);
    if (paramBoolean) {
      if (this.ᐨẏ == null) {
        int i = ˑܘ.ʾܪ(this.ˎᴗ);
        this.ᐨẏ = (List<ʾא>[])new List[i];
      } 
      this.ᐨẏ[paramInt] = ٴᐤ.ᐨẏ(this.ᐨẏ[paramInt], ʾא);
    } else {
      if (this.ˊ == null) {
        int i = ˑܘ.ʾܪ(this.ˎᴗ);
        this.ˊ = (ـс)new List[i];
      } 
      this.ˊ[paramInt] = ٴᐤ.ᐨẏ((List<ʾא>)this.ˊ[paramInt], ʾא);
    } 
    return ʾא;
  }
  
  public final void ᴵʖ(ᴵʖ paramᴵʖ) {
    this.ٴӵ = ٴᐤ.ᐨẏ(this.ٴӵ, paramᴵʖ);
  }
  
  public final void ᴵʖ() {}
  
  public final void ᐨẏ(int paramInt1, int paramInt2, Object[] paramArrayOfObject1, int paramInt3, Object[] paramArrayOfObject2) {
    this.ˊ.ᐨẏ(new ﾞঽ(paramInt1, paramInt2, (paramArrayOfObject1 == null) ? null : ᐨẏ(paramArrayOfObject1), paramInt3, (paramArrayOfObject2 == null) ? null : ᐨẏ(paramArrayOfObject2)));
  }
  
  public final void ʹﮃ(int paramInt) {
    this.ˊ.ᐨẏ(new ˏﾚ(paramInt));
  }
  
  public final void ˊ(int paramInt1, int paramInt2) {
    this.ˊ.ᐨẏ(new ʿḶ(paramInt1, paramInt2));
  }
  
  public final void ᴵʖ(int paramInt1, int paramInt2) {
    this.ˊ.ᐨẏ(new ᕁ(paramInt1, paramInt2));
  }
  
  public final void ᐨẏ(int paramInt, String paramString) {
    this.ˊ.ᐨẏ(new ᔉ(paramInt, paramString));
  }
  
  public final void ᐨẏ(int paramInt, String paramString1, String paramString2, String paramString3) {
    this.ˊ.ᐨẏ(new ˑܥ(paramInt, paramString1, paramString2, paramString3));
  }
  
  public final void ᐨẏ(int paramInt, String paramString1, String paramString2, String paramString3, boolean paramBoolean) {
    if (this.ᐨẏ < 327680 && (paramInt & 0x100) == 0) {
      super.ᐨẏ(paramInt, paramString1, paramString2, paramString3, paramBoolean);
      return;
    } 
    paramInt &= 0xFFFFFEFF;
    this.ˊ.ᐨẏ(new ʾᔂ(paramInt, paramString1, paramString2, paramString3, paramBoolean));
  }
  
  public final void ᐨẏ(String paramString1, String paramString2, ʹō paramʹō, Object... paramVarArgs) {
    this.ˊ.ᐨẏ(new ʻᴷ(paramString1, paramString2, paramʹō, paramVarArgs));
  }
  
  public void ᐨẏ(int paramInt, ᔪ paramᔪ) {
    this.ˊ.ᐨẏ(new ʿশ(paramInt, ᐨẏ(paramᔪ)));
  }
  
  public final void ˊ(ᔪ paramᔪ) {
    this.ˊ.ᐨẏ(ᐨẏ(paramᔪ));
  }
  
  public final void ˊ(Object paramObject) {
    this.ˊ.ᐨẏ(new ˏἴ(paramObject));
  }
  
  public final void ﾞл(int paramInt1, int paramInt2) {
    this.ˊ.ᐨẏ(new ۦ(paramInt1, paramInt2));
  }
  
  public final void ᐨẏ(int paramInt1, int paramInt2, ᔪ paramᔪ, ᔪ... paramVarArgs) {
    this.ˊ.ᐨẏ(new יᔭ(paramInt1, paramInt2, ᐨẏ(paramᔪ), ᐨẏ(paramVarArgs)));
  }
  
  public final void ᐨẏ(ᔪ paramᔪ, int[] paramArrayOfint, ᔪ[] paramArrayOfᔪ) {
    this.ˊ.ᐨẏ(new ﹳڐ(ᐨẏ(paramᔪ), paramArrayOfint, ᐨẏ(paramArrayOfᔪ)));
  }
  
  public final void ˊ(String paramString, int paramInt) {
    this.ˊ.ᐨẏ(new ˍᒄ(paramString, paramInt));
  }
  
  public final ᐨẏ ˊ(int paramInt, ˏɪ paramˏɪ, String paramString, boolean paramBoolean) {
    ـс ـс1;
    Ӏ ӏ;
    for (ӏ = (ـс1 = this.ˊ).ﾞл; ӏ.ˈהּ() == -1; ӏ = (ӏ = ӏ).ᐨẏ);
    ʽ冫 ʽ冫 = new ʽ冫(paramInt, paramˏɪ, paramString);
    if (paramBoolean) {
      ӏ.ˍɫ = ٴᐤ.ᐨẏ(ӏ.ˍɫ, ʽ冫);
    } else {
      ӏ.ʽ = ٴᐤ.ᐨẏ(ӏ.ʽ, ʽ冫);
    } 
    return ʽ冫;
  }
  
  public final void ᐨẏ(ᔪ paramᔪ1, ᔪ paramᔪ2, ᔪ paramᔪ3, String paramString) {
    ˌț ˌț = new ˌț(ᐨẏ(paramᔪ1), ᐨẏ(paramᔪ2), ᐨẏ(paramᔪ3), paramString);
    this.ﾞǰ = ٴᐤ.ᐨẏ(this.ﾞǰ, ˌț);
  }
  
  public final ᐨẏ ᴵʖ(int paramInt, ˏɪ paramˏɪ, String paramString, boolean paramBoolean) {
    ˌț ˌț = this.ﾞǰ.get((paramInt & 0xFFFF00) >> 8);
    ʽ冫 ʽ冫 = new ʽ冫(paramInt, paramˏɪ, paramString);
    if (paramBoolean) {
      ˌț.ˍɫ = ٴᐤ.ᐨẏ(ˌț.ˍɫ, ʽ冫);
    } else {
      ˌț.ʽ = ٴᐤ.ᐨẏ(ˌț.ʽ, ʽ冫);
    } 
    return ʽ冫;
  }
  
  public final void ᐨẏ(String paramString1, String paramString2, String paramString3, ᔪ paramᔪ1, ᔪ paramᔪ2, int paramInt) {
    ᕻ ᕻ = new ᕻ(paramString1, paramString2, paramString3, ᐨẏ(paramᔪ1), ᐨẏ(paramᔪ2), paramInt);
    this.ˊᵃ = ٴᐤ.ᐨẏ(this.ˊᵃ, ᕻ);
  }
  
  public final ᐨẏ ᐨẏ(int paramInt, ˏɪ paramˏɪ, ᔪ[] paramArrayOfᔪ1, ᔪ[] paramArrayOfᔪ2, int[] paramArrayOfint, String paramString, boolean paramBoolean) {
    ˉḽ ˉḽ = new ˉḽ(paramInt, paramˏɪ, ᐨẏ(paramArrayOfᔪ1), ᐨẏ(paramArrayOfᔪ2), paramArrayOfint, paramString);
    if (paramBoolean) {
      this.ˌх = ٴᐤ.ᐨẏ(this.ˌх, ˉḽ);
    } else {
      this.ιﾌ = ٴᐤ.ᐨẏ(this.ιﾌ, ˉḽ);
    } 
    return ˉḽ;
  }
  
  public final void ˊ(int paramInt, ᔪ paramᔪ) {
    this.ˊ.ᐨẏ(new ˑᓶ(paramInt, ᐨẏ(paramᔪ)));
  }
  
  public final void ʿᵉ(int paramInt1, int paramInt2) {
    this.ˑỲ = paramInt1;
    this.ˌپ = paramInt2;
  }
  
  public void ᐨẏ() {}
  
  private static λ ᐨẏ(ᔪ paramᔪ) {
    if (!(paramᔪ.ᐨẏ instanceof λ))
      paramᔪ.ᐨẏ = (ٴᐤ)new λ(); 
    return (λ)paramᔪ.ᐨẏ;
  }
  
  private λ[] ᐨẏ(ᔪ[] paramArrayOfᔪ) {
    λ[] arrayOfΛ = new λ[paramArrayOfᔪ.length];
    byte b = 0;
    int i = paramArrayOfᔪ.length;
    while (b < i) {
      arrayOfΛ[b] = ᐨẏ(paramArrayOfᔪ[b]);
      b++;
    } 
    return arrayOfΛ;
  }
  
  private Object[] ᐨẏ(Object[] paramArrayOfObject) {
    Object[] arrayOfObject = new Object[paramArrayOfObject.length];
    byte b = 0;
    int i = paramArrayOfObject.length;
    while (b < i) {
      Object object;
      if (object = paramArrayOfObject[b] instanceof ᔪ)
        object = ᐨẏ((ᔪ)object); 
      arrayOfObject[b] = object;
      b++;
    } 
    return arrayOfObject;
  }
  
  public final void ͺо(int paramInt) {
    if (paramInt == 262144) {
      if (this.ʼᵖ != null && !this.ʼᵖ.isEmpty())
        throw new ˈח(); 
      if (this.ˍɫ != null && !this.ˍɫ.isEmpty())
        throw new ˈח(); 
      if (this.ʽ != null && !this.ʽ.isEmpty())
        throw new ˈח(); 
      if (this.ﾞǰ != null)
        for (int j = this.ﾞǰ.size() - 1; j >= 0; j--) {
          ˌț ˌț;
          if ((ˌț = this.ﾞǰ.get(j)).ˍɫ != null && !ˌț.ˍɫ.isEmpty())
            throw new ˈח(); 
          if (ˌț.ʽ != null && !ˌț.ʽ.isEmpty())
            throw new ˈח(); 
        }  
      ـс ـс1;
      for (int i = (ـс1 = this.ˊ).ʿᵉ - 1; i >= 0; i--) {
        Ӏ ӏ;
        if ((ӏ = this.ˊ.ᐨẏ(i)).ˍɫ != null && !ӏ.ˍɫ.isEmpty())
          throw new ˈח(); 
        if (ӏ.ʽ != null && !ӏ.ʽ.isEmpty())
          throw new ˈח(); 
        if (ӏ instanceof ʾᔂ) {
          boolean bool;
          if ((bool = ((ʾᔂ)ӏ).ʾ) != ((ӏ.ՙঘ == 185)))
            throw new ˈח(); 
        } else {
          Object object;
          if (ӏ instanceof ˏἴ && (object = ((ˏἴ)ӏ).ʿᵉ instanceof ʹō || (object instanceof ˑܘ && ((ˑܘ)object).ˉｓ() == 11)))
            throw new ˈח(); 
        } 
      } 
      if (this.ˌх != null && !this.ˌх.isEmpty())
        throw new ˈח(); 
      if (this.ιﾌ != null && !this.ιﾌ.isEmpty())
        throw new ˈח(); 
    } 
    if (paramInt < 458752) {
      ـс ـс1;
      for (int i = (ـс1 = this.ˊ).ʿᵉ - 1; i >= 0; i--) {
        Ӏ ӏ;
        Object object;
        if (ӏ = this.ˊ.ᐨẏ(i) instanceof ˏἴ && object = ((ˏἴ)ӏ).ʿᵉ instanceof ʾܪ)
          throw new ˈח(); 
      } 
    } 
  }
  
  public final void ᐨẏ(ˍɫ paramˍɫ) {
    String[] arrayOfString = (this.ـﭔ == null) ? null : this.ـﭔ.<String>toArray(new String[0]);
    ˉｓ ˉｓ1;
    if ((ˉｓ1 = paramˍɫ.ᐨẏ(this.ᒬ, this.name, this.ˎᴗ, this.ˊﮈ, arrayOfString)) != null)
      ᐨẏ(ˉｓ1); 
  }
  
  public final void ᐨẏ(ˉｓ paramˉｓ) {
    // Byte code:
    //   0: aload_0
    //   1: getfield ʼᵖ : Ljava/util/List;
    //   4: ifnull -> 47
    //   7: iconst_0
    //   8: istore_2
    //   9: aload_0
    //   10: getfield ʼᵖ : Ljava/util/List;
    //   13: invokeinterface size : ()I
    //   18: istore_3
    //   19: iload_2
    //   20: iload_3
    //   21: if_icmpge -> 47
    //   24: aload_0
    //   25: getfield ʼᵖ : Ljava/util/List;
    //   28: iload_2
    //   29: invokeinterface get : (I)Ljava/lang/Object;
    //   34: checkcast yyds/sniarbtej/ᐨп
    //   37: aload_1
    //   38: invokevirtual ᐨẏ : (Lyyds/sniarbtej/ˉｓ;)V
    //   41: iinc #2, 1
    //   44: goto -> 19
    //   47: aload_0
    //   48: getfield ʹﮃ : Ljava/lang/Object;
    //   51: ifnull -> 76
    //   54: aload_1
    //   55: invokevirtual ˊ : ()Lyyds/sniarbtej/ᐨẏ;
    //   58: dup
    //   59: astore_2
    //   60: aconst_null
    //   61: aload_0
    //   62: getfield ʹﮃ : Ljava/lang/Object;
    //   65: invokestatic ᐨẏ : (Lyyds/sniarbtej/ᐨẏ;Ljava/lang/String;Ljava/lang/Object;)V
    //   68: aload_2
    //   69: ifnull -> 76
    //   72: aload_2
    //   73: invokevirtual ᐨẏ : ()V
    //   76: aload_0
    //   77: getfield ʾ : Ljava/util/List;
    //   80: ifnull -> 135
    //   83: iconst_0
    //   84: istore_2
    //   85: aload_0
    //   86: getfield ʾ : Ljava/util/List;
    //   89: invokeinterface size : ()I
    //   94: istore_3
    //   95: iload_2
    //   96: iload_3
    //   97: if_icmpge -> 135
    //   100: aload_0
    //   101: getfield ʾ : Ljava/util/List;
    //   104: iload_2
    //   105: invokeinterface get : (I)Ljava/lang/Object;
    //   110: checkcast yyds/sniarbtej/ʾא
    //   113: dup
    //   114: astore #4
    //   116: aload_1
    //   117: aload #4
    //   119: getfield ˎᴗ : Ljava/lang/String;
    //   122: iconst_1
    //   123: invokevirtual ᐨẏ : (Ljava/lang/String;Z)Lyyds/sniarbtej/ᐨẏ;
    //   126: invokevirtual ᐨẏ : (Lyyds/sniarbtej/ᐨẏ;)V
    //   129: iinc #2, 1
    //   132: goto -> 95
    //   135: aload_0
    //   136: getfield ͺо : Ljava/util/List;
    //   139: ifnull -> 194
    //   142: iconst_0
    //   143: istore_2
    //   144: aload_0
    //   145: getfield ͺо : Ljava/util/List;
    //   148: invokeinterface size : ()I
    //   153: istore_3
    //   154: iload_2
    //   155: iload_3
    //   156: if_icmpge -> 194
    //   159: aload_0
    //   160: getfield ͺо : Ljava/util/List;
    //   163: iload_2
    //   164: invokeinterface get : (I)Ljava/lang/Object;
    //   169: checkcast yyds/sniarbtej/ʾא
    //   172: dup
    //   173: astore #4
    //   175: aload_1
    //   176: aload #4
    //   178: getfield ˎᴗ : Ljava/lang/String;
    //   181: iconst_0
    //   182: invokevirtual ᐨẏ : (Ljava/lang/String;Z)Lyyds/sniarbtej/ᐨẏ;
    //   185: invokevirtual ᐨẏ : (Lyyds/sniarbtej/ᐨẏ;)V
    //   188: iinc #2, 1
    //   191: goto -> 154
    //   194: aload_0
    //   195: getfield ˍɫ : Ljava/util/List;
    //   198: ifnull -> 263
    //   201: iconst_0
    //   202: istore_2
    //   203: aload_0
    //   204: getfield ˍɫ : Ljava/util/List;
    //   207: invokeinterface size : ()I
    //   212: istore_3
    //   213: iload_2
    //   214: iload_3
    //   215: if_icmpge -> 263
    //   218: aload_0
    //   219: getfield ˍɫ : Ljava/util/List;
    //   222: iload_2
    //   223: invokeinterface get : (I)Ljava/lang/Object;
    //   228: checkcast yyds/sniarbtej/ʽ冫
    //   231: dup
    //   232: astore #4
    //   234: aload_1
    //   235: aload #4
    //   237: getfield ٱ : I
    //   240: aload #4
    //   242: getfield ˊ : Lyyds/sniarbtej/ˏɪ;
    //   245: aload #4
    //   247: getfield ˎᴗ : Ljava/lang/String;
    //   250: iconst_1
    //   251: invokevirtual ᐨẏ : (ILyyds/sniarbtej/ˏɪ;Ljava/lang/String;Z)Lyyds/sniarbtej/ᐨẏ;
    //   254: invokevirtual ᐨẏ : (Lyyds/sniarbtej/ᐨẏ;)V
    //   257: iinc #2, 1
    //   260: goto -> 213
    //   263: aload_0
    //   264: getfield ʽ : Ljava/util/List;
    //   267: ifnull -> 332
    //   270: iconst_0
    //   271: istore_2
    //   272: aload_0
    //   273: getfield ʽ : Ljava/util/List;
    //   276: invokeinterface size : ()I
    //   281: istore_3
    //   282: iload_2
    //   283: iload_3
    //   284: if_icmpge -> 332
    //   287: aload_0
    //   288: getfield ʽ : Ljava/util/List;
    //   291: iload_2
    //   292: invokeinterface get : (I)Ljava/lang/Object;
    //   297: checkcast yyds/sniarbtej/ʽ冫
    //   300: dup
    //   301: astore #4
    //   303: aload_1
    //   304: aload #4
    //   306: getfield ٱ : I
    //   309: aload #4
    //   311: getfield ˊ : Lyyds/sniarbtej/ˏɪ;
    //   314: aload #4
    //   316: getfield ˎᴗ : Ljava/lang/String;
    //   319: iconst_0
    //   320: invokevirtual ᐨẏ : (ILyyds/sniarbtej/ˏɪ;Ljava/lang/String;Z)Lyyds/sniarbtej/ᐨẏ;
    //   323: invokevirtual ᐨẏ : (Lyyds/sniarbtej/ᐨẏ;)V
    //   326: iinc #2, 1
    //   329: goto -> 282
    //   332: aload_0
    //   333: getfield শ : I
    //   336: ifle -> 348
    //   339: aload_1
    //   340: aload_0
    //   341: getfield শ : I
    //   344: iconst_1
    //   345: invokevirtual ᐨẏ : (IZ)V
    //   348: aload_0
    //   349: getfield ᐨẏ : [Ljava/util/List;
    //   352: ifnull -> 440
    //   355: iconst_0
    //   356: istore_2
    //   357: aload_0
    //   358: getfield ᐨẏ : [Ljava/util/List;
    //   361: arraylength
    //   362: istore_3
    //   363: iload_2
    //   364: iload_3
    //   365: if_icmpge -> 440
    //   368: aload_0
    //   369: getfield ᐨẏ : [Ljava/util/List;
    //   372: iload_2
    //   373: aaload
    //   374: dup
    //   375: astore #4
    //   377: ifnull -> 434
    //   380: iconst_0
    //   381: istore #5
    //   383: aload #4
    //   385: invokeinterface size : ()I
    //   390: istore #6
    //   392: iload #5
    //   394: iload #6
    //   396: if_icmpge -> 434
    //   399: aload #4
    //   401: iload #5
    //   403: invokeinterface get : (I)Ljava/lang/Object;
    //   408: checkcast yyds/sniarbtej/ʾא
    //   411: dup
    //   412: astore #7
    //   414: aload_1
    //   415: iload_2
    //   416: aload #7
    //   418: getfield ˎᴗ : Ljava/lang/String;
    //   421: iconst_1
    //   422: invokevirtual ᐨẏ : (ILjava/lang/String;Z)Lyyds/sniarbtej/ᐨẏ;
    //   425: invokevirtual ᐨẏ : (Lyyds/sniarbtej/ᐨẏ;)V
    //   428: iinc #5, 1
    //   431: goto -> 392
    //   434: iinc #2, 1
    //   437: goto -> 363
    //   440: aload_0
    //   441: getfield ˋᴷ : I
    //   444: ifle -> 456
    //   447: aload_1
    //   448: aload_0
    //   449: getfield ˋᴷ : I
    //   452: iconst_0
    //   453: invokevirtual ᐨẏ : (IZ)V
    //   456: aload_0
    //   457: getfield ˊ : [Ljava/util/List;
    //   460: ifnull -> 548
    //   463: iconst_0
    //   464: istore_2
    //   465: aload_0
    //   466: getfield ˊ : [Ljava/util/List;
    //   469: arraylength
    //   470: istore_3
    //   471: iload_2
    //   472: iload_3
    //   473: if_icmpge -> 548
    //   476: aload_0
    //   477: getfield ˊ : [Ljava/util/List;
    //   480: iload_2
    //   481: aaload
    //   482: dup
    //   483: astore #4
    //   485: ifnull -> 542
    //   488: iconst_0
    //   489: istore #5
    //   491: aload #4
    //   493: invokeinterface size : ()I
    //   498: istore #6
    //   500: iload #5
    //   502: iload #6
    //   504: if_icmpge -> 542
    //   507: aload #4
    //   509: iload #5
    //   511: invokeinterface get : (I)Ljava/lang/Object;
    //   516: checkcast yyds/sniarbtej/ʾא
    //   519: dup
    //   520: astore #7
    //   522: aload_1
    //   523: iload_2
    //   524: aload #7
    //   526: getfield ˎᴗ : Ljava/lang/String;
    //   529: iconst_0
    //   530: invokevirtual ᐨẏ : (ILjava/lang/String;Z)Lyyds/sniarbtej/ᐨẏ;
    //   533: invokevirtual ᐨẏ : (Lyyds/sniarbtej/ᐨẏ;)V
    //   536: iinc #5, 1
    //   539: goto -> 500
    //   542: iinc #2, 1
    //   545: goto -> 471
    //   548: aload_0
    //   549: getfield ͺо : Z
    //   552: ifeq -> 562
    //   555: aload_0
    //   556: getfield ˊ : Lyyds/sniarbtej/ـс;
    //   559: invokevirtual ʻᒱ : ()V
    //   562: aload_0
    //   563: getfield ٴӵ : Ljava/util/List;
    //   566: ifnull -> 609
    //   569: iconst_0
    //   570: istore_2
    //   571: aload_0
    //   572: getfield ٴӵ : Ljava/util/List;
    //   575: invokeinterface size : ()I
    //   580: istore_3
    //   581: iload_2
    //   582: iload_3
    //   583: if_icmpge -> 609
    //   586: aload_1
    //   587: aload_0
    //   588: getfield ٴӵ : Ljava/util/List;
    //   591: iload_2
    //   592: invokeinterface get : (I)Ljava/lang/Object;
    //   597: checkcast yyds/sniarbtej/ᴵʖ
    //   600: invokevirtual ᴵʖ : (Lyyds/sniarbtej/ᴵʖ;)V
    //   603: iinc #2, 1
    //   606: goto -> 581
    //   609: aload_0
    //   610: getfield ˊ : Lyyds/sniarbtej/ـс;
    //   613: dup
    //   614: astore_2
    //   615: getfield ʿᵉ : I
    //   618: ifle -> 857
    //   621: aload_1
    //   622: invokevirtual ᴵʖ : ()V
    //   625: aload_0
    //   626: getfield ﾞǰ : Ljava/util/List;
    //   629: ifnull -> 689
    //   632: iconst_0
    //   633: istore_2
    //   634: aload_0
    //   635: getfield ﾞǰ : Ljava/util/List;
    //   638: invokeinterface size : ()I
    //   643: istore_3
    //   644: iload_2
    //   645: iload_3
    //   646: if_icmpge -> 689
    //   649: aload_0
    //   650: getfield ﾞǰ : Ljava/util/List;
    //   653: iload_2
    //   654: invokeinterface get : (I)Ljava/lang/Object;
    //   659: checkcast yyds/sniarbtej/ˌț
    //   662: iload_2
    //   663: invokevirtual ᴵƚ : (I)V
    //   666: aload_0
    //   667: getfield ﾞǰ : Ljava/util/List;
    //   670: iload_2
    //   671: invokeinterface get : (I)Ljava/lang/Object;
    //   676: checkcast yyds/sniarbtej/ˌț
    //   679: aload_1
    //   680: invokevirtual ᐨẏ : (Lyyds/sniarbtej/ˉｓ;)V
    //   683: iinc #2, 1
    //   686: goto -> 644
    //   689: aload_0
    //   690: getfield ˊ : Lyyds/sniarbtej/ـс;
    //   693: aload_1
    //   694: invokevirtual ᐨẏ : (Lyyds/sniarbtej/ˉｓ;)V
    //   697: aload_0
    //   698: getfield ˊᵃ : Ljava/util/List;
    //   701: ifnull -> 744
    //   704: iconst_0
    //   705: istore_2
    //   706: aload_0
    //   707: getfield ˊᵃ : Ljava/util/List;
    //   710: invokeinterface size : ()I
    //   715: istore_3
    //   716: iload_2
    //   717: iload_3
    //   718: if_icmpge -> 744
    //   721: aload_0
    //   722: getfield ˊᵃ : Ljava/util/List;
    //   725: iload_2
    //   726: invokeinterface get : (I)Ljava/lang/Object;
    //   731: checkcast yyds/sniarbtej/ᕻ
    //   734: aload_1
    //   735: invokevirtual ᐨẏ : (Lyyds/sniarbtej/ˉｓ;)V
    //   738: iinc #2, 1
    //   741: goto -> 716
    //   744: aload_0
    //   745: getfield ˌх : Ljava/util/List;
    //   748: ifnull -> 792
    //   751: iconst_0
    //   752: istore_2
    //   753: aload_0
    //   754: getfield ˌх : Ljava/util/List;
    //   757: invokeinterface size : ()I
    //   762: istore_3
    //   763: iload_2
    //   764: iload_3
    //   765: if_icmpge -> 792
    //   768: aload_0
    //   769: getfield ˌх : Ljava/util/List;
    //   772: iload_2
    //   773: invokeinterface get : (I)Ljava/lang/Object;
    //   778: checkcast yyds/sniarbtej/ˉḽ
    //   781: aload_1
    //   782: iconst_1
    //   783: invokevirtual ᐨẏ : (Lyyds/sniarbtej/ˉｓ;Z)V
    //   786: iinc #2, 1
    //   789: goto -> 763
    //   792: aload_0
    //   793: getfield ιﾌ : Ljava/util/List;
    //   796: ifnull -> 840
    //   799: iconst_0
    //   800: istore_2
    //   801: aload_0
    //   802: getfield ιﾌ : Ljava/util/List;
    //   805: invokeinterface size : ()I
    //   810: istore_3
    //   811: iload_2
    //   812: iload_3
    //   813: if_icmpge -> 840
    //   816: aload_0
    //   817: getfield ιﾌ : Ljava/util/List;
    //   820: iload_2
    //   821: invokeinterface get : (I)Ljava/lang/Object;
    //   826: checkcast yyds/sniarbtej/ˉḽ
    //   829: aload_1
    //   830: iconst_0
    //   831: invokevirtual ᐨẏ : (Lyyds/sniarbtej/ˉｓ;Z)V
    //   834: iinc #2, 1
    //   837: goto -> 811
    //   840: aload_1
    //   841: aload_0
    //   842: getfield ˑỲ : I
    //   845: aload_0
    //   846: getfield ˌپ : I
    //   849: invokevirtual ʿᵉ : (II)V
    //   852: aload_0
    //   853: iconst_1
    //   854: putfield ͺо : Z
    //   857: aload_1
    //   858: invokevirtual ᐨẏ : ()V
    //   861: return
  }
}


/* Location:              C:\Users\kb\Downloads\ja-netfilter.jar!\yyds\sniarbtej\ᐧє.class
 * Java compiler version: 8 (52.0)
 * JD-Core Version:       1.1.3
 */