package yyds.sniarbtej;

import java.io.ByteArrayOutputStream;
import java.io.DataInputStream;
import java.io.IOException;
import java.io.InputStream;
import java.util.regex.Pattern;

public class ᐨم {
  private static String ﾞл;
  
  private static String ʿᵉ;
  
  private static String ʹﮃ;
  
  private static String ՙᗮ;
  
  private static String ˍɫ;
  
  private static String ʽ;
  
  private static String ʾܪ;
  
  private static String ᐨم;
  
  private static String ʾ;
  
  private static String ͺо;
  
  private static String ٴӵ = ᐨẏ$ᐝт.W("ឩ?워媦篱婌ᒍ貨ꅣ藴腀◚萘暺艊悜".toCharArray(), (short)30411, (byte)0, (short)4).intern();
  
  private static String ᴵƚ;
  
  private static String ˌ;
  
  private static String ˍ;
  
  private static String ʹō;
  
  private static String ᐝᵣ;
  
  private static String ᔪ;
  
  private static String ʿλ;
  
  private static String ˉｓ;
  
  private static String ʿপ;
  
  private static String ʻล;
  
  private static String ˈے;
  
  private static String ـﭔ;
  
  private static String ʼᵖ;
  
  private static String ﾞǰ;
  
  private static String ˊᵃ;
  
  private static String ˌх;
  
  private static String ιﾌ;
  
  private static String ʻւ;
  
  private static String ˑܘ;
  
  private static int ᐧפ = 262144;
  
  private static int ιˠ = 256;
  
  private static int ˈהּ = 19;
  
  private static int ﹳיִ = 20;
  
  private static int ʴ = 26;
  
  private static int ˌᵋ = 27;
  
  private static int ʹл = 28;
  
  private static int ٴᖟ = 29;
  
  private static int ˊɼ = 30;
  
  private static int ۥ = 31;
  
  private static int ـไ = 32;
  
  private static int ˊᴬ = 33;
  
  private static int ʻᒱ = 34;
  
  private static int ﹳܕ = 35;
  
  private static int ˎאּ = 36;
  
  private static int ᵕ = 37;
  
  private static int ˌᔹ = 38;
  
  private static int ˎᴗ = 39;
  
  private static int ˊﮈ = 40;
  
  private static int ʼᐡ = 41;
  
  private static int ᴵઽ = 42;
  
  private static int ᐧṙ = 43;
  
  private static int ᐨר = 44;
  
  private static int ͺĹ = 45;
  
  private static int ᴵЃ = 59;
  
  private static int ᗮ = 60;
  
  private static int ᴶ = 61;
  
  private static int গ = 62;
  
  private static int ˏｳ = 63;
  
  private static int ˏﬤ = 64;
  
  private static int ـᘢ = 65;
  
  private static int ﾟ = 66;
  
  private static int Ӏ = 67;
  
  private static int ʾא = 68;
  
  private static int ᵘ = 69;
  
  private static int ˑܥ = 70;
  
  private static int ᐨ = 71;
  
  private static int ﾞঽ = 72;
  
  private static int ۦ = 73;
  
  private static int ˏⅭ = 74;
  
  private static int ـс = 75;
  
  private static int יς = 76;
  
  private static int ˏﾚ = 77;
  
  private static int ʿḶ = 78;
  
  private static int ʻᴷ = 196;
  
  private static int ʿশ = 200;
  
  private static int λ = 201;
  
  private static int ˏἴ = 33;
  
  private static int ˑᓶ = 49;
  
  private static int ˉḽ = 20;
  
  private static int ᘧ = 202;
  
  private static int ﹳڐ = 203;
  
  private static int ʾᔂ = 204;
  
  private static int ᐧє = 205;
  
  private static int ʹˉ = 206;
  
  private static int ٴḷ = 207;
  
  private static int ٴﾗ = 208;
  
  private static int ـɻ = 209;
  
  private static int ʻヽ = 210;
  
  private static int ʼˀ = 211;
  
  private static int ˍᒄ = 212;
  
  private static int ﹳᖩ = 213;
  
  private static int ˑゞ = 214;
  
  private static int יᔭ = 215;
  
  private static int ᒻ = 216;
  
  private static int ʽ冫 = 217;
  
  private static int ᔉ = 218;
  
  private static int ˈח = 219;
  
  private static int ٴᐤ = 220;
  
  private static int ՙᗮ = 1;
  
  private static int ˍɫ = 2;
  
  private static int ʽ = 4;
  
  private static int ʾܪ = 8;
  
  private static int ᐨم = 256;
  
  private static final int ʾ = 1048576;
  
  private static final int ͺо = 4096;
  
  @Deprecated
  private byte[] ᴵʖ;
  
  public final int ٴӵ;
  
  final byte[] ﾞл;
  
  private final int[] ᐨẏ;
  
  private final String[] ᐨẏ;
  
  private final ʾܪ[] ᐨẏ;
  
  private final int[] ˊ;
  
  private final int ᴵƚ;
  
  private ᐨم() {}
  
  static void ᐨẏ(Object<?> paramObject) {
    String str;
    if (!ᐨẏ(str = (paramObject = (Object<?>)paramObject.getClass()).getName().replace('.', '/'))) {
      "怢펶ᰇ⬀㢌튇थ".toCharArray()[4] = (char)("怢펶ᰇ⬀㢌튇थ".toCharArray()[4] ^ 0x2DAA);
      ᐨẏ(paramObject.getClassLoader().getResourceAsStream(str + ᐝᵣ$ﾞﾇ.j("怢펶ᰇ⬀㢌튇थ".toCharArray(), (short)25738, 2, (short)2)));
    } 
  }
  
  private static boolean ᐨẏ(String paramString) {
    "?⾪덠쨎幼⹧⇫䱤䐎负毹䁢Т嶹箈貾ㆁ?䴕".toCharArray()[3] = (char)("?⾪덠쨎幼⹧⇫䱤䐎负毹䁢Т嶹箈貾ㆁ?䴕".toCharArray()[3] ^ 0x1730);
    if (!paramString.startsWith(ᐝᵣ$ﾞﾇ.j("?⾪덠쨎幼⹧⇫䱤䐎负毹䁢Т嶹箈貾ㆁ?䴕".toCharArray(), (short)17197, 3, (short)0)))
      return false; 
    "婾啤எᓝ호岑잡ኢ?鿉掳푷⮙⊥೪һ蒋抛㴙᜻ꓒᷥ㨇绊p䕂?긴売ퟒꙚ鱛᱘韉⎵晊鎢驪襽ⵔ彠㬰琢쓧䴯卦牠镩⶯筶?谲읯懱?㷅䫠仞".toCharArray()[54] = (char)("婾啤எᓝ호岑잡ኢ?鿉掳푷⮙⊥೪һ蒋抛㴙᜻ꓒᷥ㨇绊p䕂?긴売ퟒꙚ鱛᱘韉⎵晊鎢驪襽ⵔ彠㬰琢쓧䴯卦牠镩⶯筶?谲읯懱?㷅䫠仞".toCharArray()[54] ^ 0x5153);
    String str = ᐝᵣ$ﾞﾇ.j("婾啤எᓝ호岑잡ኢ?鿉掳푷⮙⊥೪һ蒋抛㴙᜻ꓒᷥ㨇绊p䕂?긴売ퟒꙚ鱛᱘韉⎵晊鎢驪襽ⵔ彠㬰琢쓧䴯卦牠镩⶯筶?谲읯懱?㷅䫠仞".toCharArray(), (short)24897, 1, (short)4);
    "杸푸ಔ뭋丨ញ".toCharArray()[2] = (char)("杸푸ಔ뭋丨ញ".toCharArray()[2] ^ 0x5728);
    "듋䰱猵⳺䓞悞ꕂ䖷锏戨㽤㓇訳괦﹡꨺灞놢㺦贜긹⺼癠藽맣䌍".toCharArray()[20] = (char)("듋䰱猵⳺䓞悞ꕂ䖷锏戨㽤㓇訳괦﹡꨺灞놢㺦贜긹⺼癠藽맣䌍".toCharArray()[20] ^ 0x57D8);
    "챉䢘ꦛ䓕佤鎦왤풢ㄢૹቻꗄ퐐术".toCharArray()[5] = (char)("챉䢘ꦛ䓕佤鎦왤풢ㄢૹቻꗄ퐐术".toCharArray()[5] ^ 0x1406);
    "艣ꓳ豠薠ඃ㴄厼휅瓢굶쉜鸋ɽ⚊ﳺﳾ熡ꜵ嬦摔ⅱ≰ὴℭፍ㏟".toCharArray()[18] = (char)("艣ꓳ豠薠ඃ㴄厼휅瓢굶쉜鸋ɽ⚊ﳺﳾ熡ꜵ嬦摔ⅱ≰ὴℭፍ㏟".toCharArray()[18] ^ 0x7F11);
    "遦₅࠙밠鉶♪鯿ᇾശඇ텍罹襑⹟".toCharArray()[2] = (char)("遦₅࠙밠鉶♪鯿ᇾശඇ텍罹襑⹟".toCharArray()[2] ^ 0x4C5E);
    return (paramString.contains(ᐝᵣ$ﾞﾇ.j("杸푸ಔ뭋丨ញ".toCharArray(), (short)3622, 0, (short)5)) || Pattern.matches(ᐝᵣ$ﾞﾇ.j("듋䰱猵⳺䓞悞ꕂ䖷锏戨㽤㓇訳괦﹡꨺灞놢㺦贜긹⺼癠藽맣䌍".toCharArray(), (short)11787, 4, (short)0) + str + ᐝᵣ$ﾞﾇ.j("챉䢘ꦛ䓕佤鎦왤풢ㄢૹቻꗄ퐐术".toCharArray(), (short)4427, 0, (short)5), paramString) || Pattern.matches(ᐝᵣ$ﾞﾇ.j("艣ꓳ豠薠ඃ㴄厼휅瓢굶쉜鸋ɽ⚊ﳺﳾ熡ꜵ嬦摔ⅱ≰ὴℭፍ㏟".toCharArray(), (short)2566, 5, (short)3) + str + ᐝᵣ$ﾞﾇ.j("遦₅࠙밠鉶♪鯿ᇾശඇ텍罹襑⹟".toCharArray(), (short)22068, 3, (short)3), paramString));
  }
  
  private static void ᐨẏ(InputStream paramInputStream) {
    if (paramInputStream == null) {
      "ꭹꈄ掣愿缃ሧ眒褹딝ｰ锛?拰瑴ᱴ燣?⃏驭뽞㥾錺엾﶐䅪澡잴뉤戧氒蹒꾙杁愮敯硓ꎻ꧒赔漠崖얍ꥮ띰ꌫ礈?喈".toCharArray()[2] = (char)("ꭹꈄ掣愿缃ሧ眒褹딝ｰ锛?拰瑴ᱴ燣?⃏驭뽞㥾錺엾﶐䅪澡잴뉤戧氒蹒꾙杁愮敯硓ꎻ꧒赔漠崖얍ꥮ띰ꌫ礈?喈".toCharArray()[2] ^ 0x139B);
      throw new IllegalStateException(ˉﻤ$ͺſ.v("ꭹꈄ掣愿缃ሧ眒褹딝ｰ锛?拰瑴ᱴ燣?⃏驭뽞㥾錺엾﶐䅪澡잴뉤戧氒蹒꾙杁愮敯硓ꎻ꧒赔漠崖얍ꥮ띰ꌫ礈?喈".toCharArray(), (short)27174, 3, (short)3));
    } 
    try {
      DataInputStream dataInputStream = new DataInputStream(paramInputStream);
      try {
        dataInputStream.readInt();
        int i = dataInputStream.readUnsignedShort();
        dataInputStream.close();
      } catch (Throwable throwable) {
        try {
          dataInputStream.close();
        } catch (Throwable throwable1) {
          throwable.addSuppressed(throwable1);
        } 
        throw throwable;
      } 
    } catch (IOException iOException) {
      "岏⽾났颒?嗃姂ᨄ綎龔杷蛥뷼炪∊䷪굙⛤⏅䉍Ứ䐬፸䢺淢ॊ쓀㹪尮앥ᜦ脑啄㮔".toCharArray()[31] = (char)("岏⽾났颒?嗃姂ᨄ綎龔杷蛥뷼炪∊䷪굙⛤⏅䉍Ứ䐬፸䢺淢ॊ쓀㹪尮앥ᜦ脑啄㮔".toCharArray()[31] ^ 0x6F96);
      throw new IllegalStateException(ˉﻤ$ͺſ.v("岏⽾났颒?嗃姂ᨄ綎龔杷蛥뷼炪∊䷪굙⛤⏅䉍Ứ䐬፸䢺淢ॊ쓀㹪尮앥ᜦ脑啄㮔".toCharArray(), (short)16152, 5, (short)5), iOException);
    } 
    if (throwable != '￿') {
      "ᖑ᝺鲫峒㘍嶭?㙪쟘㳥⊜셆㉸쫁鴡袋?㓮鯉┦꣖⪾Ɉ玴刦ࡾ㧥अ쓄뉔謤狷鲪旇୳׏錻齑흮㯟㋘퇜ꚱꫳ㊟ʴ?ⓖ?瓫鶰ᚿ별ﾂ⑔퀤밂એ傰㶘ἠ䢔Ế໵堯렓ᑓ淍ﶿṁ".toCharArray()[58] = (char)("ᖑ᝺鲫峒㘍嶭?㙪쟘㳥⊜셆㉸쫁鴡袋?㓮鯉┦꣖⪾Ɉ玴刦ࡾ㧥अ쓄뉔謤狷鲪旇୳׏錻齑흮㯟㋘퇜ꚱꫳ㊟ʴ?ⓖ?瓫鶰ᚿ별ﾂ⑔퀤밂એ傰㶘ἠ䢔Ế໵堯렓ᑓ淍ﶿṁ".toCharArray()[58] ^ 0x3F9E);
      throw new IllegalStateException(ˉﻤ$ͺſ.v("ᖑ᝺鲫峒㘍嶭?㙪쟘㳥⊜셆㉸쫁鴡袋?㓮鯉┦꣖⪾Ɉ玴刦ࡾ㧥अ쓄뉔謤狷鲪旇୳׏錻齑흮㯟㋘퇜ꚱꫳ㊟ʴ?ⓖ?瓫鶰ᚿ별ﾂ⑔퀤밂એ傰㶘ἠ䢔Ế໵堯렓ᑓ淍ﶿṁ".toCharArray(), (short)28449, 2, (short)4));
    } 
  }
  
  public ᐨم(byte[] paramArrayOfbyte) {
    this(paramArrayOfbyte, 0);
  }
  
  private ᐨم(byte[] paramArrayOfbyte, int paramInt) {
    this(paramArrayOfbyte, 0, true);
  }
  
  ᐨم(byte[] paramArrayOfbyte, int paramInt, boolean paramBoolean) {
    this.ﾞл = paramArrayOfbyte;
    if (paramBoolean && ᐨẏ(paramInt + 6) > 67) {
      "曥웕嫨繫뽁ᩣ舦숐ꥸ겱穜ꢙ䉔ﷆ첲芗쨉앋㥈씈䶪ﲔ檖潔䆂买逵芩䵘ⲻ釤ᷪ⁫".toCharArray()[25] = (char)("曥웕嫨繫뽁ᩣ舦숐ꥸ겱穜ꢙ䉔ﷆ첲芗쨉앋㥈씈䶪ﲔ檖潔䆂买逵芩䵘ⲻ釤ᷪ⁫".toCharArray()[25] ^ 0x795);
      throw new IllegalArgumentException(ᐝᵣ$ﾞﾇ.j("曥웕嫨繫뽁ᩣ舦숐ꥸ겱穜ꢙ䉔ﷆ첲芗쨉앋㥈씈䶪ﲔ檖潔䆂买逵芩䵘ⲻ釤ᷪ⁫".toCharArray(), (short)25150, 3, (short)4) + ᐨẏ(paramInt + 6));
    } 
    int i = ᴵʖ(paramInt + 8);
    this.ᐨẏ = (ʾܪ[])new int[i];
    this.ᐨẏ = (ʾܪ[])new String[i];
    byte b = 1;
    paramInt += 10;
    int j = 0;
    boolean bool1 = false;
    boolean bool2 = false;
    while (b < i) {
      int k;
      this.ᐨẏ[b++] = paramInt + 1;
      switch (paramArrayOfbyte[paramInt]) {
        case 3:
        case 4:
        case 9:
        case 10:
        case 11:
        case 12:
          k = 5;
          break;
        case 17:
          k = 5;
          bool1 = true;
          bool2 = true;
          break;
        case 18:
          k = 5;
          bool1 = true;
          break;
        case 5:
        case 6:
          k = 9;
          b++;
          break;
        case 1:
          if ((k = 3 + ᴵʖ(paramInt + 1)) > j)
            j = k; 
          break;
        case 15:
          k = 4;
          break;
        case 7:
        case 8:
        case 16:
        case 19:
        case 20:
          k = 3;
          break;
        default:
          throw new IllegalArgumentException();
      } 
      paramInt += k;
    } 
    this.ᴵƚ = j;
    this.ٴӵ = paramInt;
    this.ᐨẏ = bool2 ? new ʾܪ[i] : null;
    this.ˊ = bool1 ? ᐨẏ(j) : null;
  }
  
  public ᐨم(InputStream paramInputStream) {
    this(ᐨẏ(paramInputStream, false));
  }
  
  public ᐨم(String paramString) {
    this(ᐨẏ(ClassLoader.getSystemResourceAsStream(paramString.replace('.', '/') + ˏȓ$ᴵЃ.E("쥫禌蒿诊᭞ᣄ".toCharArray(), (short)25909, (short)4, (short)2)), true));
  }
  
  private static byte[] ᐨẏ(InputStream paramInputStream, boolean paramBoolean) {
    if (paramInputStream == null) {
      "♵瞝ᚡ漎⽜쿭⯇얼柂甊鋦脓ᄆ暉灞".toCharArray()[5] = (char)("♵瞝ᚡ漎⽜쿭⯇얼柂甊鋦脓ᄆ暉灞".toCharArray()[5] ^ 0x475F);
      throw new IOException(ᐝᵣ$ﾞﾇ.j("♵瞝ᚡ漎⽜쿭⯇얼柂甊鋦脓ᄆ暉灞".toCharArray(), (short)3043, 4, (short)4));
    } 
    InputStream inputStream;
    int i = ((i = (inputStream = paramInputStream).available()) < 256) ? 4096 : Math.min(i, 1048576);
    try {
      ByteArrayOutputStream byteArrayOutputStream = new ByteArrayOutputStream();
    } finally {
      if (paramBoolean)
        paramInputStream.close(); 
    } 
  }
  
  private static int ᐨẏ(InputStream paramInputStream) {
    int i;
    return ((i = paramInputStream.available()) < 256) ? 4096 : Math.min(i, 1048576);
  }
  
  public int ˊ() {
    return ᴵʖ(this.ٴӵ);
  }
  
  public String ᐨẏ() {
    return ﾞл(this.ٴӵ + 2, new char[this.ᴵƚ]);
  }
  
  public String ˊ() {
    return ﾞл(this.ٴӵ + 4, new char[this.ᴵƚ]);
  }
  
  public String[] ᐨẏ() {
    int i = this.ٴӵ + 6;
    int j;
    String[] arrayOfString = new String[j = ᴵʖ(i)];
    if (j > 0) {
      char[] arrayOfChar = new char[this.ᴵƚ];
      for (byte b = 0; b < j; b++) {
        i += 2;
        arrayOfString[b] = ﾞл(i, arrayOfChar);
      } 
    } 
    return arrayOfString;
  }
  
  public void ᐨẏ(ˍɫ paramˍɫ, int paramInt) {
    ᐨẏ(paramˍɫ, new ᴵʖ[0], paramInt);
  }
  
  public void ᐨẏ(ˍɫ paramˍɫ, ᴵʖ[] paramArrayOfᴵʖ, int paramInt) {
    ʾ ʾ;
    (ʾ = new ʾ()).ˊ = (Object[])paramArrayOfᴵʖ;
    ʾ.ᕁ = paramInt;
    ʾ.ᐨẏ = (ˏɪ)new char[this.ᴵƚ];
    ˏɪ ˏɪ = ʾ.ᐨẏ;
    int i = this.ٴӵ;
    int j = ᴵʖ(i);
    String str1 = ﾞл(i + 2, (char[])ˏɪ);
    String str2 = ﾞл(i + 4, (char[])ˏɪ);
    String[] arrayOfString = new String[ᴵʖ(i + 6)];
    i += 8;
    int k;
    for (k = 0; k < arrayOfString.length; k++) {
      arrayOfString[k] = ﾞл(i, (char[])ˏɪ);
      i += 2;
    } 
    k = 0;
    int m = 0;
    String str3 = null;
    String str4 = null;
    String str5 = null;
    int n = 0;
    int i1 = 0;
    int i2 = 0;
    int i3 = 0;
    int i4 = 0;
    int i5 = 0;
    String str6 = null;
    String str7 = null;
    int i6 = 0;
    int i7 = 0;
    int i8 = 0;
    ᴵʖ ᴵʖ1 = null;
    int i9 = ᴵʖ();
    int i10;
    for (i10 = ᴵʖ(i9 - 2); i10 > 0; i10--) {
      String str = ᐨẏ(i9, (char[])ˏɪ);
      int i12 = ﾞл(i9 + 2);
      i9 += 6;
      "怖껽ꪐ葡狫뉸秾?䜛™".toCharArray()[1] = (char)("怖껽ꪐ葡狫뉸秾?䜛™".toCharArray()[1] ^ 0x2CD9);
      if (ˍɫ$יς.J("怖껽ꪐ葡狫뉸秾?䜛™".toCharArray(), (short)16518, (short)4, (byte)0).intern().equals(str)) {
        str4 = ᐨẏ(i9, (char[])ˏɪ);
      } else {
        "轗㒄漰랕㎡鍩뿞舘섧╁".toCharArray()[5] = (char)("轗㒄漰랕㎡鍩뿞舘섧╁".toCharArray()[5] ^ 0x27A4);
        if (ˍɫ$יς.J("轗㒄漰랕㎡鍩뿞舘섧╁".toCharArray(), (short)20449, (short)2, (byte)3).intern().equals(str)) {
          k = i9;
        } else {
          "默磊엶滏蔜軮H添❁ዛ偻鷱珺鱚࢐".toCharArray()[3] = (char)("默磊엶滏蔜軮H添❁ዛ偻鷱珺鱚࢐".toCharArray()[3] ^ 0xAF1);
          if (ˍɫ$יς.J("默磊엶滏蔜軮H添❁ዛ偻鷱珺鱚࢐".toCharArray(), (short)1846, (short)3, (byte)1).intern().equals(str)) {
            m = i9;
          } else {
            "咂퉟開䩈ᇦ樓┋㨗".toCharArray()[6] = (char)("咂퉟開䩈ᇦ樓┋㨗".toCharArray()[6] ^ 0x7FB5);
            if (ˍɫ$יς.J("咂퉟開䩈ᇦ樓┋㨗".toCharArray(), (short)30621, (short)0, (byte)1).intern().equals(str)) {
              str7 = ﾞл(i9, (char[])ˏɪ);
            } else {
              "껜끲輁；飼蜍꿌헤䞞".toCharArray()[5] = (char)("껜끲輁；飼蜍꿌헤䞞".toCharArray()[5] ^ 0x20C);
              if (ˍɫ$יς.J("껜끲輁；飼蜍꿌헤䞞".toCharArray(), (short)2989, (short)3, (byte)5).intern().equals(str)) {
                i6 = i9;
              } else {
                "䚬䄷튘ᨄ࿼늓὎귚化럒욹怵狔๲ᵳ?눙は墩".toCharArray()[0] = (char)("䚬䄷튘ᨄ࿼늓὎귚化럒욹怵狔๲ᵳ?눙は墩".toCharArray()[0] ^ 0x4543);
                if (ˍɫ$יς.J("䚬䄷튘ᨄ࿼늓὎귚化럒욹怵狔๲ᵳ?눙は墩".toCharArray(), (short)21149, (short)4, (byte)3).intern().equals(str)) {
                  i7 = i9;
                } else {
                  "키Ҩ鷷⺹䦘铚靲元搗炐".toCharArray()[1] = (char)("키Ҩ鷷⺹䦘铚靲元搗炐".toCharArray()[1] ^ 0x102D);
                  if (ˍɫ$יς.J("키Ҩ鷷⺹䦘铚靲元搗炐".toCharArray(), (short)27570, (short)4, (byte)0).intern().equals(str)) {
                    str3 = ᐨẏ(i9, (char[])ˏɪ);
                  } else {
                    "연ɔ湢౼世鬤髸ᝧ퉈楕騛喲⋎靵㭟襻㲳鬪讻Ỵ琳䊝Ꞗ৫湎".toCharArray()[16] = (char)("연ɔ湢౼世鬤髸ᝧ퉈楕騛喲⋎靵㭟襻㲳鬪讻Ỵ琳䊝Ꞗ৫湎".toCharArray()[16] ^ 0x5E4F);
                    if (ˍɫ$יς.J("연ɔ湢౼世鬤髸ᝧ퉈楕騛喲⋎靵㭟襻㲳鬪讻Ỵ琳䊝Ꞗ৫湎".toCharArray(), (short)31083, (short)2, (byte)3).intern().equals(str)) {
                      n = i9;
                    } else {
                      "쨠撌쳠툹监Ӡ絷湣ᣰ醮䩣鴦弰맾怡ㄐ쬬閸࢈ǌรg?ᆎ桜掲".toCharArray()[8] = (char)("쨠撌쳠툹监Ӡ絷湣ᣰ醮䩣鴦弰맾怡ㄐ쬬閸࢈ǌรg?ᆎ桜掲".toCharArray()[8] ^ 0x5E08);
                      if (ˍɫ$יς.J("쨠撌쳠툹监Ӡ絷湣ᣰ醮䩣鴦弰맾怡ㄐ쬬閸࢈ǌรg?ᆎ桜掲".toCharArray(), (short)31476, (short)0, (byte)4).intern().equals(str)) {
                        i2 = i9;
                      } else {
                        "쨻췦淗趧?✢ㄉ࣭亙䗧".toCharArray()[7] = (char)("쨻췦淗趧?✢ㄉ࣭亙䗧".toCharArray()[7] ^ 0x1B61);
                        if (ˍɫ$יς.J("쨻췦淗趧?✢ㄉ࣭亙䗧".toCharArray(), (short)30481, (short)5, (byte)5).intern().equals(str)) {
                          j |= 0x20000;
                        } else {
                          "뜺⋃Ⓤ꽼糺递핕ጉ誅浄".toCharArray()[1] = (char)("뜺⋃Ⓤ꽼糺递핕ጉ誅浄".toCharArray()[1] ^ 0xE01);
                          if (ˍɫ$יς.J("뜺⋃Ⓤ꽼糺递핕ጉ誅浄".toCharArray(), (short)3742, (short)1, (byte)4).intern().equals(str)) {
                            j |= 0x1000;
                          } else {
                            "뎂韙Ĉ࿪ᒯھ眴ꆮ鳠鶒법澴㧡뼦〼界⊃".toCharArray()[19] = (char)("뎂韙Ĉ࿪ᒯھ眴ꆮ鳠鶒법澴㧡뼦〼界⊃".toCharArray()[19] ^ 0x4EDA);
                            if (ˍɫ$יς.J("뎂韙Ĉ࿪ᒯھ眴ꆮ鳠鶒법澴㧡뼦〼界⊃".toCharArray(), (short)28632, (short)3, (byte)5).intern().equals(str)) {
                              if (i12 > this.ﾞл.length - i9)
                                throw new IllegalArgumentException(); 
                              str5 = ᐨẏ(i9, i12, new char[i12]);
                            } else {
                              "阖䪞낁툳㵎魱ᖿ⤕ᩡ沢溹玵᭏煏쒠偖똳集䯃孛鋥ㅉ瓾Ҕ建⣛".toCharArray()[7] = (char)("阖䪞낁툳㵎魱ᖿ⤕ᩡ沢溹玵᭏煏쒠偖똳集䯃孛鋥ㅉ瓾Ҕ建⣛".toCharArray()[7] ^ 0x4FA8);
                              if (ˍɫ$יς.J("阖䪞낁툳㵎魱ᖿ⤕ᩡ沢溹玵᭏煏쒠偖똳集䯃孛鋥ㅉ瓾Ҕ建⣛".toCharArray(), (short)18496, (short)2, (byte)4).intern().equals(str)) {
                                i1 = i9;
                              } else {
                                "䓳偻㍝隃᲍趍氞飹艔焛䖿භ플葿㍤锕뀬볛첄ℽ蠣姧烺㗍␱৐椗㬗ᒁ".toCharArray()[29] = (char)("䓳偻㍝隃᲍趍氞飹艔焛䖿භ플葿㍤锕뀬볛첄ℽ蠣姧烺㗍␱৐椗㬗ᒁ".toCharArray()[29] ^ 0x1B6A);
                                if (ˍɫ$יς.J("䓳偻㍝隃᲍趍氞飹艔焛䖿භ플葿㍤锕뀬볛첄ℽ蠣姧烺㗍␱৐椗㬗ᒁ".toCharArray(), (short)17449, (short)1, (byte)0).intern().equals(str)) {
                                  i3 = i9;
                                } else {
                                  "㌿ﰊ梳⽩㖬ሁ㊡".toCharArray()[3] = (char)("㌿ﰊ梳⽩㖬ሁ㊡".toCharArray()[3] ^ 0x32A7);
                                  if (ˍɫ$יς.J("㌿ﰊ梳⽩㖬ሁ㊡".toCharArray(), (short)29396, (short)0, (byte)1).intern().equals(str)) {
                                    i8 = i9;
                                    j |= 0x10000;
                                  } else {
                                    "羔䈷✳㝠鶣餻掸".toCharArray()[3] = (char)("羔䈷✳㝠鶣餻掸".toCharArray()[3] ^ 0x7492);
                                    if (ˍɫ$יς.J("羔䈷✳㝠鶣餻掸".toCharArray(), (short)10894, (short)3, (byte)4).intern().equals(str)) {
                                      i4 = i9;
                                    } else {
                                      "‡⹔艕型鲥䡆⎹?㛮뽞臰○ⁿ紘".toCharArray()[10] = (char)("‡⹔艕型鲥䡆⎹?㛮뽞臰○ⁿ紘".toCharArray()[10] ^ 0x70A9);
                                      if (ˍɫ$יς.J("‡⹔艕型鲥䡆⎹?㛮뽞臰○ⁿ紘".toCharArray(), (short)10787, (short)2, (byte)0).intern().equals(str)) {
                                        str6 = ﾞл(i9, (char[])ˏɪ);
                                      } else {
                                        "轵ሉ豪빆梒⠾殛᫵焷戔㊏垶洽".toCharArray()[1] = (char)("轵ሉ豪빆梒⠾殛᫵焷戔㊏垶洽".toCharArray()[1] ^ 0x5E60);
                                        if (ˍɫ$יς.J("轵ሉ豪빆梒⠾殛᫵焷戔㊏垶洽".toCharArray(), (short)27065, (short)2, (byte)3).intern().equals(str)) {
                                          i5 = i9;
                                        } else {
                                          "惱ʿ㾸㊻ἢ?⩰깖眷╤룈魦惛㩛岛".toCharArray()[15] = (char)("惱ʿ㾸㊻ἢ?⩰깖眷╤룈魦惛㩛岛".toCharArray()[15] ^ 0x6D9);
                                          if (!ˍɫ$יς.J("惱ʿ㾸㊻ἢ?⩰깖眷╤룈魦惛㩛岛".toCharArray(), (short)30271, (short)1, (byte)4).intern().equals(str)) {
                                            ᴵʖ ᴵʖ2;
                                            (ᴵʖ2 = ᐨẏ(paramArrayOfᴵʖ, str, i9, i12, (char[])ˏɪ, -1, null)).ᐨẏ = ᴵʖ1;
                                            ᴵʖ1 = ᴵʖ2;
                                          } 
                                        } 
                                      } 
                                    } 
                                  } 
                                } 
                              } 
                            } 
                          } 
                        } 
                      } 
                    } 
                  } 
                } 
              } 
            } 
          } 
        } 
      } 
      i9 += i12;
    } 
    paramˍɫ.ᐨẏ(ﾞл(this.ᐨẏ[1] - 7), j, str1, str3, str2, arrayOfString);
    if ((paramInt & 0x2) == 0 && (str4 != null || str5 != null))
      paramˍɫ.ᐨẏ(str4, str5); 
    if (i4 != 0)
      ᐨẏ(paramˍɫ, ʾ, i4, i5, str6); 
    if (str7 != null)
      paramˍɫ.ᐨẏ(str7); 
    if (m != 0) {
      String str8 = ﾞл(m, (char[])ˏɪ);
      int i12;
      String str10 = ((i12 = ᴵʖ(m + 2)) == 0) ? null : ᐨẏ(this.ᐨẏ[i12], (char[])ˏɪ);
      String str9 = (i12 == 0) ? null : ᐨẏ(this.ᐨẏ[i12] + 2, (char[])ˏɪ);
      paramˍɫ.ˊ(str8, str10, str9);
    } 
    if (n != 0) {
      i10 = ᴵʖ(n);
      int i12;
      for (i12 = n + 2; i10-- > 0; i12 = ᐨẏ(paramˍɫ.ᐨẏ(str, true), i12, true, (char[])ˏɪ)) {
        String str = ᐨẏ(i12, (char[])ˏɪ);
        i12 += 2;
      } 
    } 
    if (i1 != 0) {
      i10 = ᴵʖ(i1);
      int i12;
      for (i12 = i1 + 2; i10-- > 0; i12 = ᐨẏ(paramˍɫ.ᐨẏ(str, false), i12, true, (char[])ˏɪ)) {
        String str = ᐨẏ(i12, (char[])ˏɪ);
        i12 += 2;
      } 
    } 
    if (i2 != 0) {
      i10 = ᴵʖ(i2);
      int i12;
      for (i12 = i2 + 2; i10-- > 0; i12 = ᐨẏ(paramˍɫ.ᐨẏ(ʾ.ιƚ, ʾ.ᐨẏ, str, true), i12, true, (char[])ˏɪ)) {
        i12 = ᐨẏ(ʾ, i12);
        String str = ᐨẏ(i12, (char[])ˏɪ);
        i12 += 2;
      } 
    } 
    if (i3 != 0) {
      i10 = ᴵʖ(i3);
      int i12;
      for (i12 = i3 + 2; i10-- > 0; i12 = ᐨẏ(paramˍɫ.ᐨẏ(ʾ.ιƚ, ʾ.ᐨẏ, str, false), i12, true, (char[])ˏɪ)) {
        i12 = ᐨẏ(ʾ, i12);
        String str = ᐨẏ(i12, (char[])ˏɪ);
        i12 += 2;
      } 
    } 
    while (ᴵʖ1 != null) {
      ᴵʖ ᴵʖ2 = ᴵʖ1.ᐨẏ;
      ᴵʖ1.ᐨẏ = null;
      paramˍɫ.ᴵʖ(ᴵʖ1);
      ᴵʖ1 = ᴵʖ2;
    } 
    if (i6 != 0) {
      i10 = ᴵʖ(i6);
      for (int i12 = i6 + 2; i10-- > 0; i12 += 2)
        paramˍɫ.ˊ(ﾞл(i12, (char[])ˏɪ)); 
    } 
    if (i7 != 0) {
      i10 = ᴵʖ(i7);
      for (int i12 = i7 + 2; i10-- > 0; i12 += 2)
        paramˍɫ.ᴵʖ(ﾞл(i12, (char[])ˏɪ)); 
    } 
    if (k != 0) {
      i10 = ᴵʖ(k);
      for (int i12 = k + 2; i10-- > 0; i12 += 8)
        paramˍɫ.ᐨẏ(ﾞл(i12, (char[])ˏɪ), ﾞл(i12 + 2, (char[])ˏɪ), ᐨẏ(i12 + 4, (char[])ˏɪ), ᴵʖ(i12 + 6)); 
    } 
    if (i8 != 0) {
      i10 = ᴵʖ(i8);
      for (i8 += 2; i10-- > 0; i8 = ᐨẏ(paramˍɫ, ʾ, i8));
    } 
    i10 = ᴵʖ(i);
    for (i += 2; i10-- > 0; i = ˊ(paramˍɫ, ʾ, i));
    int i11 = ᴵʖ(i);
    for (i += 2; i11-- > 0; i = ᴵʖ(paramˍɫ, ʾ, i));
    paramˍɫ.ᐨẏ();
  }
  
  private void ᐨẏ(ˍɫ paramˍɫ, ʾ paramʾ, int paramInt1, int paramInt2, String paramString) {
    ˏɪ ˏɪ = paramʾ.ᐨẏ;
    paramInt1 = paramInt1;
    String str1 = ʿᵉ(paramInt1, (char[])ˏɪ);
    int k = ᴵʖ(paramInt1 + 2);
    String str2 = ᐨẏ(paramInt1 + 4, (char[])ˏɪ);
    paramInt1 += 6;
    ʻล ʻล;
    if ((ʻล = paramˍɫ.ᐨẏ(str1, k, str2)) == null)
      return; 
    if (paramString != null)
      ʻล.ʿᵉ(paramString); 
    if (paramInt2 != 0) {
      int m = ᴵʖ(paramInt2);
      for (paramInt2 += 2; m-- > 0; paramInt2 += 2)
        ʻล.ʹﮃ(ʹﮃ(paramInt2, (char[])ˏɪ)); 
    } 
    int i = ᴵʖ(paramInt1);
    paramInt1 += 2;
    while (i-- > 0) {
      String str3 = ʿᵉ(paramInt1, (char[])ˏɪ);
      int m = ᴵʖ(paramInt1 + 2);
      String str4 = ᐨẏ(paramInt1 + 4, (char[])ˏɪ);
      paramInt1 += 6;
      ʻล.ᐨẏ(str3, m, str4);
    } 
    paramInt2 = ᴵʖ(paramInt1);
    paramInt1 += 2;
    while (paramInt2-- > 0) {
      String[] arrayOfString;
      str1 = ʹﮃ(paramInt1, (char[])ˏɪ);
      k = ᴵʖ(paramInt1 + 2);
      i = ᴵʖ(paramInt1 + 4);
      paramInt1 += 6;
      str2 = null;
      if (i != 0) {
        arrayOfString = new String[i];
        for (byte b = 0; b < i; b++) {
          arrayOfString[b] = ʿᵉ(paramInt1, (char[])ˏɪ);
          paramInt1 += 2;
        } 
      } 
      ʻล.ᐨẏ(str1, k, arrayOfString);
    } 
    int j = ᴵʖ(paramInt1);
    paramInt1 += 2;
    while (j-- > 0) {
      String str = ʹﮃ(paramInt1, (char[])ˏɪ);
      i = ᴵʖ(paramInt1 + 2);
      int m = ᴵʖ(paramInt1 + 4);
      paramInt1 += 6;
      String[] arrayOfString = null;
      if (m != 0) {
        arrayOfString = new String[m];
        for (paramInt2 = 0; paramInt2 < m; paramInt2++) {
          arrayOfString[paramInt2] = ʿᵉ(paramInt1, (char[])ˏɪ);
          paramInt1 += 2;
        } 
      } 
      ʻล.ˊ(str, i, arrayOfString);
    } 
    k = ᴵʖ(paramInt1);
    for (paramInt1 += 2; k-- > 0; paramInt1 += 2)
      ʻล.ՙᗮ(ﾞл(paramInt1, (char[])ˏɪ)); 
    i = ᴵʖ(paramInt1);
    paramInt1 += 2;
    while (i-- > 0) {
      str2 = ﾞл(paramInt1, (char[])ˏɪ);
      int m = ᴵʖ(paramInt1 + 2);
      paramInt1 += 4;
      String[] arrayOfString = new String[m];
      for (j = 0; j < m; j++) {
        arrayOfString[j] = ﾞл(paramInt1, (char[])ˏɪ);
        paramInt1 += 2;
      } 
      ʻล.ᐨẏ(str2, arrayOfString);
    } 
    ʻล.ᐨẏ();
  }
  
  private int ᐨẏ(ˍɫ paramˍɫ, ʾ paramʾ, int paramInt) {
    ˏɪ ˏɪ = paramʾ.ᐨẏ;
    paramInt = paramInt;
    String str1 = ᐨẏ(paramInt, (char[])ˏɪ);
    String str2 = ᐨẏ(paramInt + 2, (char[])ˏɪ);
    paramInt += 4;
    String str3 = null;
    int i = 0;
    int j = 0;
    int k = 0;
    int m = 0;
    ᴵʖ ᴵʖ = null;
    int n = ᴵʖ(paramInt);
    for (paramInt += 2; n-- > 0; paramInt += i1) {
      String str = ᐨẏ(paramInt, (char[])ˏɪ);
      int i1 = ﾞл(paramInt + 2);
      paramInt += 6;
      "맗糷턤ꔺ౹䑏낆?ろ塇".toCharArray()[1] = (char)("맗糷턤ꔺ౹䑏낆?ろ塇".toCharArray()[1] ^ 0x7A31);
      if (ˉﻤ$ͺſ.v("맗糷턤ꔺ౹䑏낆?ろ塇".toCharArray(), (short)504, 5, (short)3).intern().equals(str)) {
        str3 = ᐨẏ(paramInt, (char[])ˏɪ);
      } else {
        "ាﯣ䦠躻幵ᔳ鉲繆弴㽨梳밲⫥졤К⿣箻䞈?鑼諅膳㝚斊".toCharArray()[0] = (char)("ាﯣ䦠躻幵ᔳ鉲繆弴㽨梳밲⫥졤К⿣箻䞈?鑼諅膳㝚斊".toCharArray()[0] ^ 0x1E17);
        if (ˉﻤ$ͺſ.v("ាﯣ䦠躻幵ᔳ鉲繆弴㽨梳밲⫥졤К⿣箻䞈?鑼諅膳㝚斊".toCharArray(), (short)5161, 5, (short)0).intern().equals(str)) {
          i = paramInt;
        } else {
          "懋㱂搮膷烍삑콪ࡐ㊲륰瞑薊᪆Ⲱ樱གྷळꮠ窊⪭難(ߠ兀憧".toCharArray()[12] = (char)("懋㱂搮膷烍삑콪ࡐ㊲륰瞑薊᪆Ⲱ樱གྷळꮠ窊⪭難(ߠ兀憧".toCharArray()[12] ^ 0x6CA0);
          if (ˉﻤ$ͺſ.v("懋㱂搮膷烍삑콪ࡐ㊲륰瞑薊᪆Ⲱ樱གྷळꮠ窊⪭難(ߠ兀憧".toCharArray(), (short)24897, 4, (short)3).intern().equals(str)) {
            k = paramInt;
          } else {
            "?Ꙣ랞麥᳣⪔ᾅ蓶?ịⲝ↭쩛녕뚝鰛艂堓Ɑ뗆૬㇢猆욥ꛂ淭".toCharArray()[2] = (char)("?Ꙣ랞麥᳣⪔ᾅ蓶?ịⲝ↭쩛녕뚝鰛艂堓Ɑ뗆૬㇢猆욥ꛂ淭".toCharArray()[2] ^ 0x570D);
            if (ˉﻤ$ͺſ.v("?Ꙣ랞麥᳣⪔ᾅ蓶?ịⲝ↭쩛녕뚝鰛艂堓Ɑ뗆૬㇢猆욥ꛂ淭".toCharArray(), (short)4980, 2, (short)0).intern().equals(str)) {
              j = paramInt;
            } else {
              "뛖≖㿠匁猦䏄機थ闣㺣伥๒?嵺⿌ʃΞ魏ማ䮉᫵㝬卿掻奇흟铯ỳ뽩➘".toCharArray()[7] = (char)("뛖≖㿠匁猦䏄機थ闣㺣伥๒?嵺⿌ʃΞ魏ማ䮉᫵㝬卿掻奇흟铯ỳ뽩➘".toCharArray()[7] ^ 0x5137);
              if (ˉﻤ$ͺſ.v("뛖≖㿠匁猦䏄機थ闣㺣伥๒?嵺⿌ʃΞ魏ማ䮉᫵㝬卿掻奇흟铯ỳ뽩➘".toCharArray(), (short)30760, 2, (short)4).intern().equals(str)) {
                m = paramInt;
              } else {
                ᴵʖ ᴵʖ1;
                (ᴵʖ1 = ᐨẏ((ᴵʖ[])paramʾ.ˊ, str, paramInt, i1, (char[])ˏɪ, -1, null)).ᐨẏ = ᴵʖ;
                ᴵʖ = ᴵʖ1;
              } 
            } 
          } 
        } 
      } 
    } 
    ʼᵖ ʼᵖ;
    if ((ʼᵖ = paramˍɫ.ᐨẏ(str1, str2, str3)) == null)
      return paramInt; 
    if (i != 0) {
      int i1 = ᴵʖ(i);
      int i2;
      for (i2 = i + 2; i1-- > 0; i2 = ᐨẏ(ʼᵖ.ᐨẏ(str, true), i2, true, (char[])ˏɪ)) {
        String str = ᐨẏ(i2, (char[])ˏɪ);
        i2 += 2;
      } 
    } 
    if (j != 0) {
      int i1 = ᴵʖ(j);
      int i2;
      for (i2 = j + 2; i1-- > 0; i2 = ᐨẏ(ʼᵖ.ᐨẏ(str, false), i2, true, (char[])ˏɪ)) {
        String str = ᐨẏ(i2, (char[])ˏɪ);
        i2 += 2;
      } 
    } 
    if (k != 0) {
      int i1 = ᴵʖ(k);
      int i2;
      for (i2 = k + 2; i1-- > 0; i2 = ᐨẏ(ʼᵖ.ᐨẏ(paramʾ.ιƚ, paramʾ.ᐨẏ, str, true), i2, true, (char[])ˏɪ)) {
        i2 = ᐨẏ(paramʾ, i2);
        String str = ᐨẏ(i2, (char[])ˏɪ);
        i2 += 2;
      } 
    } 
    if (m != 0) {
      int i1 = ᴵʖ(m);
      int i2;
      for (i2 = m + 2; i1-- > 0; i2 = ᐨẏ(ʼᵖ.ᐨẏ(paramʾ.ιƚ, paramʾ.ᐨẏ, str, false), i2, true, (char[])ˏɪ)) {
        i2 = ᐨẏ(paramʾ, i2);
        String str = ᐨẏ(i2, (char[])ˏɪ);
        i2 += 2;
      } 
    } 
    while (ᴵʖ != null) {
      ᴵʖ ᴵʖ1 = ᴵʖ.ᐨẏ;
      ᴵʖ.ᐨẏ = null;
      ʼᵖ.ᴵʖ(ᴵʖ);
      ᴵʖ = ᴵʖ1;
    } 
    ʼᵖ.ᐨẏ();
    return paramInt;
  }
  
  private int ˊ(ˍɫ paramˍɫ, ʾ paramʾ, int paramInt) {
    ˏɪ ˏɪ = paramʾ.ᐨẏ;
    paramInt = paramInt;
    int i = ᴵʖ(paramInt);
    String str1 = ᐨẏ(paramInt + 2, (char[])ˏɪ);
    String str2 = ᐨẏ(paramInt + 4, (char[])ˏɪ);
    paramInt += 6;
    Object object = null;
    String str3 = null;
    int j = 0;
    int k = 0;
    int m = 0;
    int n = 0;
    ᴵʖ ᴵʖ = null;
    int i1 = ᴵʖ(paramInt);
    for (paramInt += 2; i1-- > 0; paramInt += i2) {
      String str = ᐨẏ(paramInt, (char[])ˏɪ);
      int i2 = ﾞл(paramInt + 2);
      paramInt += 6;
      "峃댞㒧鞽龦勋⎏꬏뭟ⱌ㾗㚌ꄪ㹰".toCharArray()[3] = (char)("峃댞㒧鞽龦勋⎏꬏뭟ⱌ㾗㚌ꄪ㹰".toCharArray()[3] ^ 0x5175);
      if (ˉﻤ$ͺſ.v("峃댞㒧鞽龦勋⎏꬏뭟ⱌ㾗㚌ꄪ㹰".toCharArray(), (short)2423, 0, (short)3).intern().equals(str)) {
        int i3;
        object = ((i3 = ᴵʖ(paramInt)) == 0) ? null : ᐨẏ(i3, (char[])ˏɪ);
      } else {
        "丮껰轧䓷䀘뫷䒞羖ש".toCharArray()[8] = (char)("丮껰轧䓷䀘뫷䒞羖ש".toCharArray()[8] ^ 0x3F5);
        if (ˉﻤ$ͺſ.v("丮껰轧䓷䀘뫷䒞羖ש".toCharArray(), (short)782, 0, (short)5).intern().equals(str)) {
          str3 = ᐨẏ(paramInt, (char[])ˏɪ);
        } else {
          "猷瑀駘ᕱ䣕ꞜꝎ궊䪣".toCharArray()[2] = (char)("猷瑀駘ᕱ䣕ꞜꝎ궊䪣".toCharArray()[2] ^ 0x2B7F);
          if (ˉﻤ$ͺſ.v("猷瑀駘ᕱ䣕ꞜꝎ궊䪣".toCharArray(), (short)3175, 0, (short)0).intern().equals(str)) {
            i |= 0x20000;
          } else {
            "弽쀬꽤㭶߭ꓡ渱⯛䒓".toCharArray()[4] = (char)("弽쀬꽤㭶߭ꓡ渱⯛䒓".toCharArray()[4] ^ 0x7674);
            if (ˉﻤ$ͺſ.v("弽쀬꽤㭶߭ꓡ渱⯛䒓".toCharArray(), (short)30804, 4, (short)3).intern().equals(str)) {
              i |= 0x1000;
            } else {
              "叩빶튋翊ࢰづ농槄茺阶⯏ꇙ⡘ড়쾛⣛⤻靄쿆怈睊嗵㤘".toCharArray()[24] = (char)("叩빶튋翊ࢰづ농槄茺阶⯏ꇙ⡘ড়쾛⣛⤻靄쿆怈睊嗵㤘".toCharArray()[24] ^ 0x333);
              if (ˉﻤ$ͺſ.v("叩빶튋翊ࢰづ농槄茺阶⯏ꇙ⡘ড়쾛⣛⤻靄쿆怈睊嗵㤘".toCharArray(), (short)4323, 0, (short)4).intern().equals(str)) {
                j = paramInt;
              } else {
                "፹痞늷쐸㘂ǌᶎ啋踏燺욽꼶悃챜ꢑ軕跮긠⼎⫦㊳쉄방覨ꙛ❦ପ㼷ⓑ".toCharArray()[1] = (char)("፹痞늷쐸㘂ǌᶎ啋踏燺욽꼶悃챜ꢑ軕跮긠⼎⫦㊳쉄방覨ꙛ❦ପ㼷ⓑ".toCharArray()[1] ^ 0x423D);
                if (ˉﻤ$ͺſ.v("፹痞늷쐸㘂ǌᶎ啋踏燺욽꼶悃챜ꢑ軕跮긠⼎⫦㊳쉄방覨ꙛ❦ପ㼷ⓑ".toCharArray(), (short)32248, 1, (short)3).intern().equals(str)) {
                  m = paramInt;
                } else {
                  "퇐澏胯⋋⃡⿭褎᝾銦營᳡ɝ?묓错垢࿐⛊梅恄囌ؒ붵瑃㡢".toCharArray()[25] = (char)("퇐澏胯⋋⃡⿭褎᝾銦營᳡ɝ?묓错垢࿐⛊梅恄囌ؒ붵瑃㡢".toCharArray()[25] ^ 0x2EDC);
                  if (ˉﻤ$ͺſ.v("퇐澏胯⋋⃡⿭褎᝾銦營᳡ɝ?묓错垢࿐⛊梅恄囌ؒ붵瑃㡢".toCharArray(), (short)28530, 0, (short)5).intern().equals(str)) {
                    k = paramInt;
                  } else {
                    "켞喖㿄쟎ᰙꝍ擕亠⬮捵듘⻔莭⊿圐恳蔋퉳?䨞涭㞊ਧᒤᨫ낅즏礳".toCharArray()[19] = (char)("켞喖㿄쟎ᰙꝍ擕亠⬮捵듘⻔莭⊿圐恳蔋퉳?䨞涭㞊ਧᒤᨫ낅즏礳".toCharArray()[19] ^ 0x271E);
                    if (ˉﻤ$ͺſ.v("켞喖㿄쟎ᰙꝍ擕亠⬮捵듘⻔莭⊿圐恳蔋퉳?䨞涭㞊ਧᒤᨫ낅즏礳".toCharArray(), (short)27428, 1, (short)0).intern().equals(str)) {
                      n = paramInt;
                    } else {
                      ᴵʖ ᴵʖ1;
                      (ᴵʖ1 = ᐨẏ((ᴵʖ[])paramʾ.ˊ, str, paramInt, i2, (char[])ˏɪ, -1, null)).ᐨẏ = ᴵʖ;
                      ᴵʖ = ᴵʖ1;
                    } 
                  } 
                } 
              } 
            } 
          } 
        } 
      } 
    } 
    ᴵƚ ᴵƚ;
    if ((ᴵƚ = paramˍɫ.ᐨẏ(i, str1, str2, str3, object)) == null)
      return paramInt; 
    if (j != 0) {
      int i2 = ᴵʖ(j);
      int i3;
      for (i3 = j + 2; i2-- > 0; i3 = ᐨẏ(ᴵƚ.ᐨẏ(str, true), i3, true, (char[])ˏɪ)) {
        String str = ᐨẏ(i3, (char[])ˏɪ);
        i3 += 2;
      } 
    } 
    if (k != 0) {
      int i2 = ᴵʖ(k);
      int i3;
      for (i3 = k + 2; i2-- > 0; i3 = ᐨẏ(ᴵƚ.ᐨẏ(str, false), i3, true, (char[])ˏɪ)) {
        String str = ᐨẏ(i3, (char[])ˏɪ);
        i3 += 2;
      } 
    } 
    if (m != 0) {
      int i2 = ᴵʖ(m);
      int i3;
      for (i3 = m + 2; i2-- > 0; i3 = ᐨẏ(ᴵƚ.ᐨẏ(paramʾ.ιƚ, paramʾ.ᐨẏ, str, true), i3, true, (char[])ˏɪ)) {
        i3 = ᐨẏ(paramʾ, i3);
        String str = ᐨẏ(i3, (char[])ˏɪ);
        i3 += 2;
      } 
    } 
    if (n != 0) {
      int i2 = ᴵʖ(n);
      int i3;
      for (i3 = n + 2; i2-- > 0; i3 = ᐨẏ(ᴵƚ.ᐨẏ(paramʾ.ιƚ, paramʾ.ᐨẏ, str, false), i3, true, (char[])ˏɪ)) {
        i3 = ᐨẏ(paramʾ, i3);
        String str = ᐨẏ(i3, (char[])ˏɪ);
        i3 += 2;
      } 
    } 
    while (ᴵʖ != null) {
      ᴵʖ ᴵʖ1 = ᴵʖ.ᐨẏ;
      ᴵʖ.ᐨẏ = null;
      ᴵƚ.ᴵʖ(ᴵʖ);
      ᴵʖ = ᴵʖ1;
    } 
    ᴵƚ.ᐨẏ();
    return paramInt;
  }
  
  private int ᴵʖ(ˍɫ paramˍɫ, ʾ paramʾ, int paramInt) {
    // Byte code:
    //   0: aload_2
    //   1: getfield ᐨẏ : [C
    //   4: astore #4
    //   6: iload_3
    //   7: istore #5
    //   9: aload_2
    //   10: aload_0
    //   11: iload #5
    //   13: invokevirtual ᴵʖ : (I)I
    //   16: putfield ιᒶ : I
    //   19: aload_2
    //   20: aload_0
    //   21: iload #5
    //   23: iconst_2
    //   24: iadd
    //   25: aload #4
    //   27: invokevirtual ᐨẏ : (I[C)Ljava/lang/String;
    //   30: putfield ᐧפ : Ljava/lang/String;
    //   33: aload_2
    //   34: aload_0
    //   35: iload #5
    //   37: iconst_4
    //   38: iadd
    //   39: aload #4
    //   41: invokevirtual ᐨẏ : (I[C)Ljava/lang/String;
    //   44: putfield ιˠ : Ljava/lang/String;
    //   47: iinc #5, 6
    //   50: iconst_0
    //   51: istore #6
    //   53: iconst_0
    //   54: istore #7
    //   56: aconst_null
    //   57: astore #8
    //   59: iconst_0
    //   60: istore #9
    //   62: iconst_0
    //   63: istore #10
    //   65: iconst_0
    //   66: istore #11
    //   68: iconst_0
    //   69: istore #12
    //   71: iconst_0
    //   72: istore #13
    //   74: iconst_0
    //   75: istore #14
    //   77: iconst_0
    //   78: istore #15
    //   80: iconst_0
    //   81: istore #16
    //   83: iconst_0
    //   84: istore #17
    //   86: iconst_0
    //   87: istore #18
    //   89: aconst_null
    //   90: astore #19
    //   92: aload_0
    //   93: iload #5
    //   95: invokevirtual ᴵʖ : (I)I
    //   98: istore #20
    //   100: iinc #5, 2
    //   103: iload #20
    //   105: iinc #20, -1
    //   108: ifle -> 822
    //   111: aload_0
    //   112: iload #5
    //   114: aload #4
    //   116: invokevirtual ᐨẏ : (I[C)Ljava/lang/String;
    //   119: astore #21
    //   121: aload_0
    //   122: iload #5
    //   124: iconst_2
    //   125: iadd
    //   126: invokevirtual ﾞл : (I)I
    //   129: istore #22
    //   131: iinc #5, 6
    //   134: ldc_w '轈⌦෎뀷᷍'
    //   137: invokevirtual toCharArray : ()[C
    //   140: dup
    //   141: dup
    //   142: iconst_3
    //   143: dup_x1
    //   144: caload
    //   145: sipush #31089
    //   148: ixor
    //   149: i2c
    //   150: castore
    //   151: sipush #29968
    //   154: iconst_5
    //   155: iconst_1
    //   156: invokestatic W : (Ljava/lang/Object;SBS)Ljava/lang/String;
    //   159: invokevirtual intern : ()Ljava/lang/String;
    //   162: aload #21
    //   164: invokevirtual equals : (Ljava/lang/Object;)Z
    //   167: ifeq -> 186
    //   170: aload_2
    //   171: getfield ᕁ : I
    //   174: iconst_1
    //   175: iand
    //   176: ifne -> 812
    //   179: iload #5
    //   181: istore #6
    //   183: goto -> 812
    //   186: ldc_w '⏏멣壙晆᝙ꞯ攀傭'
    //   189: invokevirtual toCharArray : ()[C
    //   192: dup
    //   193: dup
    //   194: iconst_2
    //   195: dup_x1
    //   196: caload
    //   197: sipush #31736
    //   200: ixor
    //   201: i2c
    //   202: castore
    //   203: sipush #23228
    //   206: iconst_1
    //   207: iconst_5
    //   208: invokestatic W : (Ljava/lang/Object;SBS)Ljava/lang/String;
    //   211: invokevirtual intern : ()Ljava/lang/String;
    //   214: aload #21
    //   216: invokevirtual equals : (Ljava/lang/Object;)Z
    //   219: ifeq -> 279
    //   222: iload #5
    //   224: istore #7
    //   226: aload_0
    //   227: iload #7
    //   229: invokevirtual ᴵʖ : (I)I
    //   232: anewarray java/lang/String
    //   235: astore #8
    //   237: iload #7
    //   239: iconst_2
    //   240: iadd
    //   241: istore #23
    //   243: iconst_0
    //   244: istore #24
    //   246: iload #24
    //   248: aload #8
    //   250: arraylength
    //   251: if_icmpge -> 276
    //   254: aload #8
    //   256: iload #24
    //   258: aload_0
    //   259: iload #23
    //   261: aload #4
    //   263: invokevirtual ﾞл : (I[C)Ljava/lang/String;
    //   266: aastore
    //   267: iinc #23, 2
    //   270: iinc #24, 1
    //   273: goto -> 246
    //   276: goto -> 812
    //   279: ldc_w '׍άꖂ蘗㊵?ꂰ蟄厑Ṋ'
    //   282: invokevirtual toCharArray : ()[C
    //   285: dup
    //   286: dup
    //   287: iconst_2
    //   288: dup_x1
    //   289: caload
    //   290: sipush #30999
    //   293: ixor
    //   294: i2c
    //   295: castore
    //   296: sipush #8930
    //   299: iconst_5
    //   300: iconst_0
    //   301: invokestatic W : (Ljava/lang/Object;SBS)Ljava/lang/String;
    //   304: invokevirtual intern : ()Ljava/lang/String;
    //   307: aload #21
    //   309: invokevirtual equals : (Ljava/lang/Object;)Z
    //   312: ifeq -> 326
    //   315: aload_0
    //   316: iload #5
    //   318: invokevirtual ᴵʖ : (I)I
    //   321: istore #10
    //   323: goto -> 812
    //   326: ldc_w '樠讓?灝듕텲壿ᢺ'
    //   329: invokevirtual toCharArray : ()[C
    //   332: dup
    //   333: dup
    //   334: bipush #9
    //   336: dup_x1
    //   337: caload
    //   338: sipush #20828
    //   341: ixor
    //   342: i2c
    //   343: castore
    //   344: sipush #21460
    //   347: iconst_2
    //   348: iconst_4
    //   349: invokestatic W : (Ljava/lang/Object;SBS)Ljava/lang/String;
    //   352: invokevirtual intern : ()Ljava/lang/String;
    //   355: aload #21
    //   357: invokevirtual equals : (Ljava/lang/Object;)Z
    //   360: ifeq -> 378
    //   363: aload_2
    //   364: dup
    //   365: getfield ιᒶ : I
    //   368: ldc_w 131072
    //   371: ior
    //   372: putfield ιᒶ : I
    //   375: goto -> 812
    //   378: ldc_w '줃Ａ䵍ꃈݑ烺넇䜂伭暭෦韀?밇넼⊯耿犱?朳З縥瑝?㲑'
    //   381: invokevirtual toCharArray : ()[C
    //   384: dup
    //   385: dup
    //   386: bipush #12
    //   388: dup_x1
    //   389: caload
    //   390: sipush #1087
    //   393: ixor
    //   394: i2c
    //   395: castore
    //   396: sipush #8523
    //   399: iconst_2
    //   400: iconst_5
    //   401: invokestatic W : (Ljava/lang/Object;SBS)Ljava/lang/String;
    //   404: invokevirtual intern : ()Ljava/lang/String;
    //   407: aload #21
    //   409: invokevirtual equals : (Ljava/lang/Object;)Z
    //   412: ifeq -> 422
    //   415: iload #5
    //   417: istore #11
    //   419: goto -> 812
    //   422: ldc_w '磼큗퟿䯤ᓋꐯ堄쭜ᢘ惝⨐詸뜍鴐ᶠ筓ᜑ쐙渑쮆ㄽ〕幉紙쏭쬣溰撘'
    //   425: invokevirtual toCharArray : ()[C
    //   428: dup
    //   429: dup
    //   430: bipush #25
    //   432: dup_x1
    //   433: caload
    //   434: sipush #18349
    //   437: ixor
    //   438: i2c
    //   439: castore
    //   440: sipush #22146
    //   443: iconst_0
    //   444: iconst_4
    //   445: invokestatic W : (Ljava/lang/Object;SBS)Ljava/lang/String;
    //   448: invokevirtual intern : ()Ljava/lang/String;
    //   451: aload #21
    //   453: invokevirtual equals : (Ljava/lang/Object;)Z
    //   456: ifeq -> 466
    //   459: iload #5
    //   461: istore #15
    //   463: goto -> 812
    //   466: ldc_w '?इ秩쩬筂桇ꥶ⥈㦮疔＆㟟ᢛ귘ᓟṭ⡩'
    //   469: invokevirtual toCharArray : ()[C
    //   472: dup
    //   473: dup
    //   474: bipush #13
    //   476: dup_x1
    //   477: caload
    //   478: sipush #32119
    //   481: ixor
    //   482: i2c
    //   483: castore
    //   484: sipush #17580
    //   487: iconst_1
    //   488: iconst_1
    //   489: invokestatic W : (Ljava/lang/Object;SBS)Ljava/lang/String;
    //   492: invokevirtual intern : ()Ljava/lang/String;
    //   495: aload #21
    //   497: invokevirtual equals : (Ljava/lang/Object;)Z
    //   500: ifeq -> 510
    //   503: iload #5
    //   505: istore #17
    //   507: goto -> 812
    //   510: ldc_w '肞䒟娿컬癧?姏꜀ೠ'
    //   513: invokevirtual toCharArray : ()[C
    //   516: dup
    //   517: dup
    //   518: iconst_2
    //   519: dup_x1
    //   520: caload
    //   521: sipush #10953
    //   524: ixor
    //   525: i2c
    //   526: castore
    //   527: sipush #7610
    //   530: iconst_2
    //   531: iconst_3
    //   532: invokestatic W : (Ljava/lang/Object;SBS)Ljava/lang/String;
    //   535: invokevirtual intern : ()Ljava/lang/String;
    //   538: aload #21
    //   540: invokevirtual equals : (Ljava/lang/Object;)Z
    //   543: ifeq -> 564
    //   546: iconst_1
    //   547: istore #9
    //   549: aload_2
    //   550: dup
    //   551: getfield ιᒶ : I
    //   554: sipush #4096
    //   557: ior
    //   558: putfield ιᒶ : I
    //   561: goto -> 812
    //   564: ldc_w '扗䉖?שּׂⶬ汋ᝮ艊콇켡⒦谆傲鲜ﯢ骁䣽煮౵꯫旿폙ﺺጱ᱕'
    //   567: invokevirtual toCharArray : ()[C
    //   570: dup
    //   571: dup
    //   572: bipush #26
    //   574: dup_x1
    //   575: caload
    //   576: sipush #1557
    //   579: ixor
    //   580: i2c
    //   581: castore
    //   582: sipush #32010
    //   585: iconst_4
    //   586: iconst_0
    //   587: invokestatic W : (Ljava/lang/Object;SBS)Ljava/lang/String;
    //   590: invokevirtual intern : ()Ljava/lang/String;
    //   593: aload #21
    //   595: invokevirtual equals : (Ljava/lang/Object;)Z
    //   598: ifeq -> 608
    //   601: iload #5
    //   603: istore #12
    //   605: goto -> 812
    //   608: ldc_w '熈攀꼈䉜䠥?뙓✱ಇ㜱᝷簉⾷航刿΋뵷䰠ᵺ䂷?슄纶Ꟙ䮼旒댴窮檐㋣'
    //   611: invokevirtual toCharArray : ()[C
    //   614: dup
    //   615: dup
    //   616: iconst_3
    //   617: dup_x1
    //   618: caload
    //   619: sipush #4899
    //   622: ixor
    //   623: i2c
    //   624: castore
    //   625: sipush #11033
    //   628: iconst_2
    //   629: iconst_0
    //   630: invokestatic W : (Ljava/lang/Object;SBS)Ljava/lang/String;
    //   633: invokevirtual intern : ()Ljava/lang/String;
    //   636: aload #21
    //   638: invokevirtual equals : (Ljava/lang/Object;)Z
    //   641: ifeq -> 651
    //   644: iload #5
    //   646: istore #16
    //   648: goto -> 812
    //   651: ldc_w '䓋釟䩐՞ㄎ勍唰漣垥㦳↺毪⩖陽礸顬靮㳢ꗐꞭ跚ﺷﾟ퀽꬧鯞?配ˌ蘈鍢ꡝ㮳'
    //   654: invokevirtual toCharArray : ()[C
    //   657: dup
    //   658: dup
    //   659: bipush #30
    //   661: dup_x1
    //   662: caload
    //   663: sipush #25186
    //   666: ixor
    //   667: i2c
    //   668: castore
    //   669: sipush #27160
    //   672: iconst_2
    //   673: iconst_1
    //   674: invokestatic W : (Ljava/lang/Object;SBS)Ljava/lang/String;
    //   677: invokevirtual intern : ()Ljava/lang/String;
    //   680: aload #21
    //   682: invokevirtual equals : (Ljava/lang/Object;)Z
    //   685: ifeq -> 695
    //   688: iload #5
    //   690: istore #13
    //   692: goto -> 812
    //   695: ldc_w '娏⹫᢮ⴱ뛦巜檊ᛝ㫧?瓇ト虢尲瑛∆⚉寏ꖥố㐍ꄉ漬偎則詆糌࿎὾⠎֨'
    //   698: invokevirtual toCharArray : ()[C
    //   701: dup
    //   702: dup
    //   703: iconst_2
    //   704: dup_x1
    //   705: caload
    //   706: sipush #3087
    //   709: ixor
    //   710: i2c
    //   711: castore
    //   712: sipush #30344
    //   715: iconst_4
    //   716: iconst_2
    //   717: invokestatic W : (Ljava/lang/Object;SBS)Ljava/lang/String;
    //   720: invokevirtual intern : ()Ljava/lang/String;
    //   723: aload #21
    //   725: invokevirtual equals : (Ljava/lang/Object;)Z
    //   728: ifeq -> 738
    //   731: iload #5
    //   733: istore #14
    //   735: goto -> 812
    //   738: ldc_w '증쎶㢂ꐑ캀滕ჽѧ?뻺Ӣ嵆분ݓᐓ'
    //   741: invokevirtual toCharArray : ()[C
    //   744: dup
    //   745: dup
    //   746: bipush #8
    //   748: dup_x1
    //   749: caload
    //   750: sipush #1388
    //   753: ixor
    //   754: i2c
    //   755: castore
    //   756: sipush #8441
    //   759: iconst_3
    //   760: iconst_0
    //   761: invokestatic W : (Ljava/lang/Object;SBS)Ljava/lang/String;
    //   764: invokevirtual intern : ()Ljava/lang/String;
    //   767: aload #21
    //   769: invokevirtual equals : (Ljava/lang/Object;)Z
    //   772: ifeq -> 782
    //   775: iload #5
    //   777: istore #18
    //   779: goto -> 812
    //   782: aload_0
    //   783: aload_2
    //   784: getfield ˊ : [Lyyds/sniarbtej/ᴵʖ;
    //   787: aload #21
    //   789: iload #5
    //   791: iload #22
    //   793: aload #4
    //   795: iconst_m1
    //   796: aconst_null
    //   797: invokespecial ᐨẏ : ([Lyyds/sniarbtej/ᴵʖ;Ljava/lang/String;II[CI[Lyyds/sniarbtej/ᔪ;)Lyyds/sniarbtej/ᴵʖ;
    //   800: dup
    //   801: astore #23
    //   803: aload #19
    //   805: putfield ᐨẏ : Lyyds/sniarbtej/ᴵʖ;
    //   808: aload #23
    //   810: astore #19
    //   812: iload #5
    //   814: iload #22
    //   816: iadd
    //   817: istore #5
    //   819: goto -> 103
    //   822: aload_1
    //   823: aload_2
    //   824: getfield ιᒶ : I
    //   827: aload_2
    //   828: getfield ᐧפ : Ljava/lang/String;
    //   831: aload_2
    //   832: getfield ιˠ : Ljava/lang/String;
    //   835: iload #10
    //   837: ifne -> 844
    //   840: aconst_null
    //   841: goto -> 852
    //   844: aload_0
    //   845: iload #10
    //   847: aload #4
    //   849: invokevirtual ˊ : (I[C)Ljava/lang/String;
    //   852: aload #8
    //   854: invokevirtual ᐨẏ : (ILjava/lang/String;Ljava/lang/String;Ljava/lang/String;[Ljava/lang/String;)Lyyds/sniarbtej/ˉｓ;
    //   857: dup
    //   858: astore #21
    //   860: ifnonnull -> 866
    //   863: iload #5
    //   865: ireturn
    //   866: aload #21
    //   868: instanceof yyds/sniarbtej/ʿপ
    //   871: ifeq -> 1145
    //   874: aload #21
    //   876: checkcast yyds/sniarbtej/ʿপ
    //   879: dup
    //   880: astore #22
    //   882: aload_0
    //   883: iload #9
    //   885: aload_2
    //   886: getfield ιᒶ : I
    //   889: ldc_w 131072
    //   892: iand
    //   893: ifeq -> 900
    //   896: iconst_1
    //   897: goto -> 901
    //   900: iconst_0
    //   901: aload_0
    //   902: iload_3
    //   903: iconst_4
    //   904: iadd
    //   905: invokevirtual ᴵʖ : (I)I
    //   908: iload #10
    //   910: iload #7
    //   912: istore #23
    //   914: istore #20
    //   916: istore #10
    //   918: istore #9
    //   920: istore #8
    //   922: astore #7
    //   924: astore_1
    //   925: aload #7
    //   927: aload_1
    //   928: getfield ᐨẏ : Lyyds/sniarbtej/ˌх;
    //   931: dup
    //   932: astore #66
    //   934: getfield ᐨẏ : Lyyds/sniarbtej/ᐨم;
    //   937: invokestatic G : (Ljava/lang/Object;Ljava/lang/Object;)Z
    //   940: ifeq -> 982
    //   943: iload #10
    //   945: aload_1
    //   946: getfield ɟ : I
    //   949: if_icmpne -> 982
    //   952: iload #20
    //   954: aload_1
    //   955: getfield ﾞǰ : I
    //   958: if_icmpne -> 982
    //   961: iload #9
    //   963: aload_1
    //   964: getfield ʿλ : I
    //   967: ldc_w 131072
    //   970: iand
    //   971: ifeq -> 978
    //   974: iconst_1
    //   975: goto -> 979
    //   978: iconst_0
    //   979: if_icmpeq -> 986
    //   982: iconst_0
    //   983: goto -> 1109
    //   986: aload_1
    //   987: getfield ᐨẏ : Lyyds/sniarbtej/ˌх;
    //   990: dup
    //   991: astore #66
    //   993: getfield Ԇ : I
    //   996: bipush #49
    //   998: if_icmpge -> 1016
    //   1001: aload_1
    //   1002: getfield ʿλ : I
    //   1005: sipush #4096
    //   1008: iand
    //   1009: ifeq -> 1016
    //   1012: iconst_1
    //   1013: goto -> 1017
    //   1016: iconst_0
    //   1017: istore #24
    //   1019: iload #8
    //   1021: iload #24
    //   1023: if_icmpeq -> 1030
    //   1026: iconst_0
    //   1027: goto -> 1109
    //   1030: iload #23
    //   1032: ifne -> 1046
    //   1035: aload_1
    //   1036: getfield ٴῪ : I
    //   1039: ifeq -> 1108
    //   1042: iconst_0
    //   1043: goto -> 1109
    //   1046: aload #7
    //   1048: iload #23
    //   1050: invokevirtual ᴵʖ : (I)I
    //   1053: aload_1
    //   1054: getfield ٴῪ : I
    //   1057: if_icmpne -> 1108
    //   1060: iload #23
    //   1062: iconst_2
    //   1063: iadd
    //   1064: istore #25
    //   1066: iconst_0
    //   1067: istore #26
    //   1069: iload #26
    //   1071: aload_1
    //   1072: getfield ٴῪ : I
    //   1075: if_icmpge -> 1108
    //   1078: aload #7
    //   1080: iload #25
    //   1082: invokevirtual ᴵʖ : (I)I
    //   1085: aload_1
    //   1086: getfield ͺо : [I
    //   1089: iload #26
    //   1091: iaload
    //   1092: if_icmpeq -> 1099
    //   1095: iconst_0
    //   1096: goto -> 1109
    //   1099: iinc #25, 2
    //   1102: iinc #26, 1
    //   1105: goto -> 1069
    //   1108: iconst_1
    //   1109: ifeq -> 1145
    //   1112: aload #22
    //   1114: iload_3
    //   1115: iload #5
    //   1117: iload_3
    //   1118: isub
    //   1119: istore #8
    //   1121: istore #7
    //   1123: dup
    //   1124: astore_1
    //   1125: iload #7
    //   1127: bipush #6
    //   1129: iadd
    //   1130: putfield ᴵ氵 : I
    //   1133: aload_1
    //   1134: iload #8
    //   1136: bipush #6
    //   1138: isub
    //   1139: putfield ᵊ : I
    //   1142: iload #5
    //   1144: ireturn
    //   1145: iload #18
    //   1147: ifeq -> 1208
    //   1150: aload_2
    //   1151: getfield ᕁ : I
    //   1154: iconst_2
    //   1155: iand
    //   1156: ifne -> 1208
    //   1159: aload_0
    //   1160: iload #18
    //   1162: invokevirtual ˊ : (I)I
    //   1165: istore #22
    //   1167: iload #18
    //   1169: iconst_1
    //   1170: iadd
    //   1171: istore #23
    //   1173: iload #22
    //   1175: iinc #22, -1
    //   1178: ifle -> 1208
    //   1181: aload #21
    //   1183: aload_0
    //   1184: iload #23
    //   1186: aload #4
    //   1188: invokevirtual ᐨẏ : (I[C)Ljava/lang/String;
    //   1191: aload_0
    //   1192: iload #23
    //   1194: iconst_2
    //   1195: iadd
    //   1196: invokevirtual ᴵʖ : (I)I
    //   1199: invokevirtual ᐨẏ : (Ljava/lang/String;I)V
    //   1202: iinc #23, 4
    //   1205: goto -> 1173
    //   1208: iload #17
    //   1210: ifeq -> 1242
    //   1213: aload #21
    //   1215: invokevirtual ˊ : ()Lyyds/sniarbtej/ᐨẏ;
    //   1218: astore #22
    //   1220: aload_0
    //   1221: aload #22
    //   1223: iload #17
    //   1225: aconst_null
    //   1226: aload #4
    //   1228: invokespecial ᐨẏ : (Lyyds/sniarbtej/ᐨẏ;ILjava/lang/String;[C)I
    //   1231: pop
    //   1232: aload #22
    //   1234: ifnull -> 1242
    //   1237: aload #22
    //   1239: invokevirtual ᐨẏ : ()V
    //   1242: iload #11
    //   1244: ifeq -> 1304
    //   1247: aload_0
    //   1248: iload #11
    //   1250: invokevirtual ᴵʖ : (I)I
    //   1253: istore #22
    //   1255: iload #11
    //   1257: iconst_2
    //   1258: iadd
    //   1259: istore #23
    //   1261: iload #22
    //   1263: iinc #22, -1
    //   1266: ifle -> 1304
    //   1269: aload_0
    //   1270: iload #23
    //   1272: aload #4
    //   1274: invokevirtual ᐨẏ : (I[C)Ljava/lang/String;
    //   1277: astore #24
    //   1279: iinc #23, 2
    //   1282: aload_0
    //   1283: aload #21
    //   1285: aload #24
    //   1287: iconst_1
    //   1288: invokevirtual ᐨẏ : (Ljava/lang/String;Z)Lyyds/sniarbtej/ᐨẏ;
    //   1291: iload #23
    //   1293: iconst_1
    //   1294: aload #4
    //   1296: invokespecial ᐨẏ : (Lyyds/sniarbtej/ᐨẏ;IZ[C)I
    //   1299: istore #23
    //   1301: goto -> 1261
    //   1304: iload #12
    //   1306: ifeq -> 1366
    //   1309: aload_0
    //   1310: iload #12
    //   1312: invokevirtual ᴵʖ : (I)I
    //   1315: istore #22
    //   1317: iload #12
    //   1319: iconst_2
    //   1320: iadd
    //   1321: istore #23
    //   1323: iload #22
    //   1325: iinc #22, -1
    //   1328: ifle -> 1366
    //   1331: aload_0
    //   1332: iload #23
    //   1334: aload #4
    //   1336: invokevirtual ᐨẏ : (I[C)Ljava/lang/String;
    //   1339: astore #24
    //   1341: iinc #23, 2
    //   1344: aload_0
    //   1345: aload #21
    //   1347: aload #24
    //   1349: iconst_0
    //   1350: invokevirtual ᐨẏ : (Ljava/lang/String;Z)Lyyds/sniarbtej/ᐨẏ;
    //   1353: iload #23
    //   1355: iconst_1
    //   1356: aload #4
    //   1358: invokespecial ᐨẏ : (Lyyds/sniarbtej/ᐨẏ;IZ[C)I
    //   1361: istore #23
    //   1363: goto -> 1323
    //   1366: iload #15
    //   1368: ifeq -> 1445
    //   1371: aload_0
    //   1372: iload #15
    //   1374: invokevirtual ᴵʖ : (I)I
    //   1377: istore #22
    //   1379: iload #15
    //   1381: iconst_2
    //   1382: iadd
    //   1383: istore #23
    //   1385: iload #22
    //   1387: iinc #22, -1
    //   1390: ifle -> 1445
    //   1393: aload_0
    //   1394: aload_2
    //   1395: iload #23
    //   1397: invokespecial ᐨẏ : (Lyyds/sniarbtej/ʾ;I)I
    //   1400: istore #23
    //   1402: aload_0
    //   1403: iload #23
    //   1405: aload #4
    //   1407: invokevirtual ᐨẏ : (I[C)Ljava/lang/String;
    //   1410: astore #24
    //   1412: iinc #23, 2
    //   1415: aload_0
    //   1416: aload #21
    //   1418: aload_2
    //   1419: getfield ιƚ : I
    //   1422: aload_2
    //   1423: getfield ᐨẏ : Lyyds/sniarbtej/ˏɪ;
    //   1426: aload #24
    //   1428: iconst_1
    //   1429: invokevirtual ᐨẏ : (ILyyds/sniarbtej/ˏɪ;Ljava/lang/String;Z)Lyyds/sniarbtej/ᐨẏ;
    //   1432: iload #23
    //   1434: iconst_1
    //   1435: aload #4
    //   1437: invokespecial ᐨẏ : (Lyyds/sniarbtej/ᐨẏ;IZ[C)I
    //   1440: istore #23
    //   1442: goto -> 1385
    //   1445: iload #16
    //   1447: ifeq -> 1524
    //   1450: aload_0
    //   1451: iload #16
    //   1453: invokevirtual ᴵʖ : (I)I
    //   1456: istore #22
    //   1458: iload #16
    //   1460: iconst_2
    //   1461: iadd
    //   1462: istore #23
    //   1464: iload #22
    //   1466: iinc #22, -1
    //   1469: ifle -> 1524
    //   1472: aload_0
    //   1473: aload_2
    //   1474: iload #23
    //   1476: invokespecial ᐨẏ : (Lyyds/sniarbtej/ʾ;I)I
    //   1479: istore #23
    //   1481: aload_0
    //   1482: iload #23
    //   1484: aload #4
    //   1486: invokevirtual ᐨẏ : (I[C)Ljava/lang/String;
    //   1489: astore #24
    //   1491: iinc #23, 2
    //   1494: aload_0
    //   1495: aload #21
    //   1497: aload_2
    //   1498: getfield ιƚ : I
    //   1501: aload_2
    //   1502: getfield ᐨẏ : Lyyds/sniarbtej/ˏɪ;
    //   1505: aload #24
    //   1507: iconst_0
    //   1508: invokevirtual ᐨẏ : (ILyyds/sniarbtej/ˏɪ;Ljava/lang/String;Z)Lyyds/sniarbtej/ᐨẏ;
    //   1511: iload #23
    //   1513: iconst_1
    //   1514: aload #4
    //   1516: invokespecial ᐨẏ : (Lyyds/sniarbtej/ᐨẏ;IZ[C)I
    //   1519: istore #23
    //   1521: goto -> 1464
    //   1524: iload #13
    //   1526: ifeq -> 1539
    //   1529: aload_0
    //   1530: aload #21
    //   1532: aload_2
    //   1533: iload #13
    //   1535: iconst_1
    //   1536: invokespecial ᐨẏ : (Lyyds/sniarbtej/ˉｓ;Lyyds/sniarbtej/ʾ;IZ)V
    //   1539: iload #14
    //   1541: ifeq -> 1554
    //   1544: aload_0
    //   1545: aload #21
    //   1547: aload_2
    //   1548: iload #14
    //   1550: iconst_0
    //   1551: invokespecial ᐨẏ : (Lyyds/sniarbtej/ˉｓ;Lyyds/sniarbtej/ʾ;IZ)V
    //   1554: aload #19
    //   1556: ifnull -> 1586
    //   1559: aload #19
    //   1561: getfield ᐨẏ : Lyyds/sniarbtej/ᴵʖ;
    //   1564: astore #22
    //   1566: aload #19
    //   1568: aconst_null
    //   1569: putfield ᐨẏ : Lyyds/sniarbtej/ᴵʖ;
    //   1572: aload #21
    //   1574: aload #19
    //   1576: invokevirtual ᴵʖ : (Lyyds/sniarbtej/ᴵʖ;)V
    //   1579: aload #22
    //   1581: astore #19
    //   1583: goto -> 1554
    //   1586: iload #6
    //   1588: ifeq -> 6970
    //   1591: aload #21
    //   1593: invokevirtual ᴵʖ : ()V
    //   1596: aload_0
    //   1597: aload #21
    //   1599: aload_2
    //   1600: iload #6
    //   1602: istore #9
    //   1604: astore #8
    //   1606: astore #7
    //   1608: astore_1
    //   1609: iload #9
    //   1611: istore #10
    //   1613: aload_1
    //   1614: getfield ﾞл : [B
    //   1617: astore #20
    //   1619: aload #8
    //   1621: getfield ᐨẏ : [C
    //   1624: astore #23
    //   1626: aload_1
    //   1627: iload #10
    //   1629: invokevirtual ᴵʖ : (I)I
    //   1632: istore #24
    //   1634: aload_1
    //   1635: iload #10
    //   1637: iconst_2
    //   1638: iadd
    //   1639: invokevirtual ᴵʖ : (I)I
    //   1642: istore #25
    //   1644: aload_1
    //   1645: iload #10
    //   1647: iconst_4
    //   1648: iadd
    //   1649: invokevirtual ﾞл : (I)I
    //   1652: istore #26
    //   1654: iinc #10, 8
    //   1657: iload #26
    //   1659: aload_1
    //   1660: getfield ﾞл : [B
    //   1663: arraylength
    //   1664: iload #10
    //   1666: isub
    //   1667: if_icmple -> 1678
    //   1670: new java/lang/IllegalArgumentException
    //   1673: dup
    //   1674: invokespecial <init> : ()V
    //   1677: athrow
    //   1678: iload #10
    //   1680: istore_2
    //   1681: iload #10
    //   1683: iload #26
    //   1685: iadd
    //   1686: istore_3
    //   1687: aload #8
    //   1689: iload #26
    //   1691: iconst_1
    //   1692: iadd
    //   1693: anewarray yyds/sniarbtej/ᔪ
    //   1696: dup_x1
    //   1697: putfield ᐨẏ : [Lyyds/sniarbtej/ᔪ;
    //   1700: astore #4
    //   1702: iload #10
    //   1704: iload_3
    //   1705: if_icmpge -> 3029
    //   1708: iload #10
    //   1710: iload_2
    //   1711: isub
    //   1712: istore #6
    //   1714: aload #20
    //   1716: iload #10
    //   1718: baload
    //   1719: sipush #255
    //   1722: iand
    //   1723: dup
    //   1724: istore #11
    //   1726: tableswitch default -> 3018, 0 -> 2624, 1 -> 2624, 2 -> 2624, 3 -> 2624, 4 -> 2624, 5 -> 2624, 6 -> 2624, 7 -> 2624, 8 -> 2624, 9 -> 2624, 10 -> 2624, 11 -> 2624, 12 -> 2624, 13 -> 2624, 14 -> 2624, 15 -> 2624, 16 -> 2994, 17 -> 3000, 18 -> 2994, 19 -> 3000, 20 -> 3000, 21 -> 2994, 22 -> 2994, 23 -> 2994, 24 -> 2994, 25 -> 2994, 26 -> 2624, 27 -> 2624, 28 -> 2624, 29 -> 2624, 30 -> 2624, 31 -> 2624, 32 -> 2624, 33 -> 2624, 34 -> 2624, 35 -> 2624, 36 -> 2624, 37 -> 2624, 38 -> 2624, 39 -> 2624, 40 -> 2624, 41 -> 2624, 42 -> 2624, 43 -> 2624, 44 -> 2624, 45 -> 2624, 46 -> 2624, 47 -> 2624, 48 -> 2624, 49 -> 2624, 50 -> 2624, 51 -> 2624, 52 -> 2624, 53 -> 2624, 54 -> 2994, 55 -> 2994, 56 -> 2994, 57 -> 2994, 58 -> 2994, 59 -> 2624, 60 -> 2624, 61 -> 2624, 62 -> 2624, 63 -> 2624, 64 -> 2624, 65 -> 2624, 66 -> 2624, 67 -> 2624, 68 -> 2624, 69 -> 2624, 70 -> 2624, 71 -> 2624, 72 -> 2624, 73 -> 2624, 74 -> 2624, 75 -> 2624, 76 -> 2624, 77 -> 2624, 78 -> 2624, 79 -> 2624, 80 -> 2624, 81 -> 2624, 82 -> 2624, 83 -> 2624, 84 -> 2624, 85 -> 2624, 86 -> 2624, 87 -> 2624, 88 -> 2624, 89 -> 2624, 90 -> 2624, 91 -> 2624, 92 -> 2624, 93 -> 2624, 94 -> 2624, 95 -> 2624, 96 -> 2624, 97 -> 2624, 98 -> 2624, 99 -> 2624, 100 -> 2624, 101 -> 2624, 102 -> 2624, 103 -> 2624, 104 -> 2624, 105 -> 2624, 106 -> 2624, 107 -> 2624, 108 -> 2624, 109 -> 2624, 110 -> 2624, 111 -> 2624, 112 -> 2624, 113 -> 2624, 114 -> 2624, 115 -> 2624, 116 -> 2624, 117 -> 2624, 118 -> 2624, 119 -> 2624, 120 -> 2624, 121 -> 2624, 122 -> 2624, 123 -> 2624, 124 -> 2624, 125 -> 2624, 126 -> 2624, 127 -> 2624, 128 -> 2624, 129 -> 2624, 130 -> 2624, 131 -> 2624, 132 -> 3000, 133 -> 2624, 134 -> 2624, 135 -> 2624, 136 -> 2624, 137 -> 2624, 138 -> 2624, 139 -> 2624, 140 -> 2624, 141 -> 2624, 142 -> 2624, 143 -> 2624, 144 -> 2624, 145 -> 2624, 146 -> 2624, 147 -> 2624, 148 -> 2624, 149 -> 2624, 150 -> 2624, 151 -> 2624, 152 -> 2624, 153 -> 2630, 154 -> 2630, 155 -> 2630, 156 -> 2630, 157 -> 2630, 158 -> 2630, 159 -> 2630, 160 -> 2630, 161 -> 2630, 162 -> 2630, 163 -> 2630, 164 -> 2630, 165 -> 2630, 166 -> 2630, 167 -> 2630, 168 -> 2630, 169 -> 2994, 170 -> 2840, 171 -> 2922, 172 -> 2624, 173 -> 2624, 174 -> 2624, 175 -> 2624, 176 -> 2624, 177 -> 2624, 178 -> 3000, 179 -> 3000, 180 -> 3000, 181 -> 3000, 182 -> 3000, 183 -> 3000, 184 -> 3000, 185 -> 3006, 186 -> 3006, 187 -> 3000, 188 -> 2994, 189 -> 3000, 190 -> 2624, 191 -> 2624, 192 -> 3000, 193 -> 3000, 194 -> 2624, 195 -> 2624, 196 -> 2702, 197 -> 3012, 198 -> 2630, 199 -> 2630, 200 -> 2678, 201 -> 2678, 202 -> 2654, 203 -> 2654, 204 -> 2654, 205 -> 2654, 206 -> 2654, 207 -> 2654, 208 -> 2654, 209 -> 2654, 210 -> 2654, 211 -> 2654, 212 -> 2654, 213 -> 2654, 214 -> 2654, 215 -> 2654, 216 -> 2654, 217 -> 2654, 218 -> 2654, 219 -> 2654, 220 -> 2678
    //   2624: iinc #10, 1
    //   2627: goto -> 1702
    //   2630: aload_1
    //   2631: iload #6
    //   2633: aload_1
    //   2634: iload #10
    //   2636: iconst_1
    //   2637: iadd
    //   2638: invokevirtual ᐨẏ : (I)S
    //   2641: iadd
    //   2642: aload #4
    //   2644: invokespecial ˊ : (I[Lyyds/sniarbtej/ᔪ;)Lyyds/sniarbtej/ᔪ;
    //   2647: pop
    //   2648: iinc #10, 3
    //   2651: goto -> 1702
    //   2654: aload_1
    //   2655: iload #6
    //   2657: aload_1
    //   2658: iload #10
    //   2660: iconst_1
    //   2661: iadd
    //   2662: invokevirtual ᴵʖ : (I)I
    //   2665: iadd
    //   2666: aload #4
    //   2668: invokespecial ˊ : (I[Lyyds/sniarbtej/ᔪ;)Lyyds/sniarbtej/ᔪ;
    //   2671: pop
    //   2672: iinc #10, 3
    //   2675: goto -> 1702
    //   2678: aload_1
    //   2679: iload #6
    //   2681: aload_1
    //   2682: iload #10
    //   2684: iconst_1
    //   2685: iadd
    //   2686: invokevirtual ﾞл : (I)I
    //   2689: iadd
    //   2690: aload #4
    //   2692: invokespecial ˊ : (I[Lyyds/sniarbtej/ᔪ;)Lyyds/sniarbtej/ᔪ;
    //   2695: pop
    //   2696: iinc #10, 5
    //   2699: goto -> 1702
    //   2702: aload #20
    //   2704: iload #10
    //   2706: iconst_1
    //   2707: iadd
    //   2708: baload
    //   2709: sipush #255
    //   2712: iand
    //   2713: lookupswitch default -> 2832, 21 -> 2820, 22 -> 2820, 23 -> 2820, 24 -> 2820, 25 -> 2820, 54 -> 2820, 55 -> 2820, 56 -> 2820, 57 -> 2820, 58 -> 2820, 132 -> 2826, 169 -> 2820
    //   2820: iinc #10, 4
    //   2823: goto -> 1702
    //   2826: iinc #10, 6
    //   2829: goto -> 1702
    //   2832: new java/lang/IllegalArgumentException
    //   2835: dup
    //   2836: invokespecial <init> : ()V
    //   2839: athrow
    //   2840: iload #10
    //   2842: iconst_4
    //   2843: iload #6
    //   2845: iconst_3
    //   2846: iand
    //   2847: isub
    //   2848: iadd
    //   2849: istore #10
    //   2851: aload_1
    //   2852: iload #6
    //   2854: aload_1
    //   2855: iload #10
    //   2857: invokevirtual ﾞл : (I)I
    //   2860: iadd
    //   2861: aload #4
    //   2863: invokespecial ˊ : (I[Lyyds/sniarbtej/ᔪ;)Lyyds/sniarbtej/ᔪ;
    //   2866: pop
    //   2867: aload_1
    //   2868: iload #10
    //   2870: bipush #8
    //   2872: iadd
    //   2873: invokevirtual ﾞл : (I)I
    //   2876: aload_1
    //   2877: iload #10
    //   2879: iconst_4
    //   2880: iadd
    //   2881: invokevirtual ﾞл : (I)I
    //   2884: isub
    //   2885: iconst_1
    //   2886: iadd
    //   2887: istore #12
    //   2889: iinc #10, 12
    //   2892: iload #12
    //   2894: iinc #12, -1
    //   2897: ifle -> 3026
    //   2900: aload_1
    //   2901: iload #6
    //   2903: aload_1
    //   2904: iload #10
    //   2906: invokevirtual ﾞл : (I)I
    //   2909: iadd
    //   2910: aload #4
    //   2912: invokespecial ˊ : (I[Lyyds/sniarbtej/ᔪ;)Lyyds/sniarbtej/ᔪ;
    //   2915: pop
    //   2916: iinc #10, 4
    //   2919: goto -> 2892
    //   2922: iload #10
    //   2924: iconst_4
    //   2925: iload #6
    //   2927: iconst_3
    //   2928: iand
    //   2929: isub
    //   2930: iadd
    //   2931: istore #10
    //   2933: aload_1
    //   2934: iload #6
    //   2936: aload_1
    //   2937: iload #10
    //   2939: invokevirtual ﾞл : (I)I
    //   2942: iadd
    //   2943: aload #4
    //   2945: invokespecial ˊ : (I[Lyyds/sniarbtej/ᔪ;)Lyyds/sniarbtej/ᔪ;
    //   2948: pop
    //   2949: aload_1
    //   2950: iload #10
    //   2952: iconst_4
    //   2953: iadd
    //   2954: invokevirtual ﾞл : (I)I
    //   2957: istore #13
    //   2959: iinc #10, 8
    //   2962: iload #13
    //   2964: iinc #13, -1
    //   2967: ifle -> 3026
    //   2970: aload_1
    //   2971: iload #6
    //   2973: aload_1
    //   2974: iload #10
    //   2976: iconst_4
    //   2977: iadd
    //   2978: invokevirtual ﾞл : (I)I
    //   2981: iadd
    //   2982: aload #4
    //   2984: invokespecial ˊ : (I[Lyyds/sniarbtej/ᔪ;)Lyyds/sniarbtej/ᔪ;
    //   2987: pop
    //   2988: iinc #10, 8
    //   2991: goto -> 2962
    //   2994: iinc #10, 2
    //   2997: goto -> 1702
    //   3000: iinc #10, 3
    //   3003: goto -> 1702
    //   3006: iinc #10, 5
    //   3009: goto -> 1702
    //   3012: iinc #10, 4
    //   3015: goto -> 1702
    //   3018: new java/lang/IllegalArgumentException
    //   3021: dup
    //   3022: invokespecial <init> : ()V
    //   3025: athrow
    //   3026: goto -> 1702
    //   3029: aload_1
    //   3030: iload #10
    //   3032: invokevirtual ᴵʖ : (I)I
    //   3035: istore #6
    //   3037: iinc #10, 2
    //   3040: iload #6
    //   3042: iinc #6, -1
    //   3045: ifle -> 3135
    //   3048: aload_1
    //   3049: dup
    //   3050: iload #10
    //   3052: invokevirtual ᴵʖ : (I)I
    //   3055: aload #4
    //   3057: invokespecial ˊ : (I[Lyyds/sniarbtej/ᔪ;)Lyyds/sniarbtej/ᔪ;
    //   3060: astore #11
    //   3062: aload_1
    //   3063: dup
    //   3064: iload #10
    //   3066: iconst_2
    //   3067: iadd
    //   3068: invokevirtual ᴵʖ : (I)I
    //   3071: aload #4
    //   3073: invokespecial ˊ : (I[Lyyds/sniarbtej/ᔪ;)Lyyds/sniarbtej/ᔪ;
    //   3076: astore #12
    //   3078: aload_1
    //   3079: dup
    //   3080: iload #10
    //   3082: iconst_4
    //   3083: iadd
    //   3084: invokevirtual ᴵʖ : (I)I
    //   3087: aload #4
    //   3089: invokespecial ˊ : (I[Lyyds/sniarbtej/ᔪ;)Lyyds/sniarbtej/ᔪ;
    //   3092: astore #13
    //   3094: aload_1
    //   3095: dup
    //   3096: getfield ᐨẏ : [I
    //   3099: aload_1
    //   3100: iload #10
    //   3102: bipush #6
    //   3104: iadd
    //   3105: invokevirtual ᴵʖ : (I)I
    //   3108: iaload
    //   3109: aload #23
    //   3111: invokevirtual ᐨẏ : (I[C)Ljava/lang/String;
    //   3114: astore #14
    //   3116: iinc #10, 8
    //   3119: aload #7
    //   3121: aload #11
    //   3123: aload #12
    //   3125: aload #13
    //   3127: aload #14
    //   3129: invokevirtual ᐨẏ : (Lyyds/sniarbtej/ᔪ;Lyyds/sniarbtej/ᔪ;Lyyds/sniarbtej/ᔪ;Ljava/lang/String;)V
    //   3132: goto -> 3040
    //   3135: iconst_0
    //   3136: istore #11
    //   3138: iconst_0
    //   3139: istore #12
    //   3141: iconst_1
    //   3142: istore #13
    //   3144: iconst_0
    //   3145: istore #14
    //   3147: iconst_0
    //   3148: istore #6
    //   3150: aconst_null
    //   3151: astore #15
    //   3153: aconst_null
    //   3154: astore #16
    //   3156: aconst_null
    //   3157: astore #17
    //   3159: aload_1
    //   3160: iload #10
    //   3162: invokevirtual ᴵʖ : (I)I
    //   3165: istore #18
    //   3167: iinc #10, 2
    //   3170: iload #18
    //   3172: iinc #18, -1
    //   3175: ifle -> 3750
    //   3178: aload_1
    //   3179: iload #10
    //   3181: aload #23
    //   3183: invokevirtual ᐨẏ : (I[C)Ljava/lang/String;
    //   3186: astore #19
    //   3188: aload_1
    //   3189: iload #10
    //   3191: iconst_2
    //   3192: iadd
    //   3193: invokevirtual ﾞл : (I)I
    //   3196: istore #22
    //   3198: iinc #10, 6
    //   3201: ldc_w '绬?繾?ߓ팛롊๻ⱦﾊ⎶㊲Ⅴ㰃䌯苣匠'
    //   3204: invokevirtual toCharArray : ()[C
    //   3207: dup
    //   3208: dup
    //   3209: iconst_3
    //   3210: dup_x1
    //   3211: caload
    //   3212: sipush #4769
    //   3215: ixor
    //   3216: i2c
    //   3217: castore
    //   3218: sipush #8226
    //   3221: iconst_0
    //   3222: iconst_0
    //   3223: invokestatic W : (Ljava/lang/Object;SBS)Ljava/lang/String;
    //   3226: invokevirtual intern : ()Ljava/lang/String;
    //   3229: aload #19
    //   3231: invokevirtual equals : (Ljava/lang/Object;)Z
    //   3234: ifeq -> 3320
    //   3237: aload #8
    //   3239: getfield ᕁ : I
    //   3242: iconst_2
    //   3243: iand
    //   3244: ifne -> 3740
    //   3247: iload #10
    //   3249: istore #14
    //   3251: iload #10
    //   3253: istore #27
    //   3255: aload_1
    //   3256: iload #27
    //   3258: invokevirtual ᴵʖ : (I)I
    //   3261: istore #28
    //   3263: iinc #27, 2
    //   3266: iload #28
    //   3268: iinc #28, -1
    //   3271: ifle -> 3317
    //   3274: aload_1
    //   3275: iload #27
    //   3277: invokevirtual ᴵʖ : (I)I
    //   3280: istore #29
    //   3282: aload_1
    //   3283: iload #29
    //   3285: aload #4
    //   3287: invokespecial ᐨẏ : (I[Lyyds/sniarbtej/ᔪ;)V
    //   3290: aload_1
    //   3291: iload #27
    //   3293: iconst_2
    //   3294: iadd
    //   3295: invokevirtual ᴵʖ : (I)I
    //   3298: istore #30
    //   3300: aload_1
    //   3301: iload #29
    //   3303: iload #30
    //   3305: iadd
    //   3306: aload #4
    //   3308: invokespecial ᐨẏ : (I[Lyyds/sniarbtej/ᔪ;)V
    //   3311: iinc #27, 10
    //   3314: goto -> 3266
    //   3317: goto -> 3740
    //   3320: ldc_w '苃ॆ䔴⁜樄缲垇鿠蕩ﹲ횰쁟೹Ô蔅٭᷎軮蓼㫷'
    //   3323: invokevirtual toCharArray : ()[C
    //   3326: dup
    //   3327: dup
    //   3328: iconst_4
    //   3329: dup_x1
    //   3330: caload
    //   3331: sipush #13792
    //   3334: ixor
    //   3335: i2c
    //   3336: castore
    //   3337: sipush #8195
    //   3340: iconst_0
    //   3341: iconst_5
    //   3342: invokestatic W : (Ljava/lang/Object;SBS)Ljava/lang/String;
    //   3345: invokevirtual intern : ()Ljava/lang/String;
    //   3348: aload #19
    //   3350: invokevirtual equals : (Ljava/lang/Object;)Z
    //   3353: ifeq -> 3363
    //   3356: iload #10
    //   3358: istore #6
    //   3360: goto -> 3740
    //   3363: ldc_w '뿈Ｊ画艌ꦒ⾘瀅ﵿ쵨?儴ꉻ⩸'
    //   3366: invokevirtual toCharArray : ()[C
    //   3369: dup
    //   3370: dup
    //   3371: iconst_5
    //   3372: dup_x1
    //   3373: caload
    //   3374: sipush #13153
    //   3377: ixor
    //   3378: i2c
    //   3379: castore
    //   3380: sipush #29463
    //   3383: iconst_0
    //   3384: iconst_1
    //   3385: invokestatic W : (Ljava/lang/Object;SBS)Ljava/lang/String;
    //   3388: invokevirtual intern : ()Ljava/lang/String;
    //   3391: aload #19
    //   3393: invokevirtual equals : (Ljava/lang/Object;)Z
    //   3396: ifeq -> 3477
    //   3399: aload #8
    //   3401: getfield ᕁ : I
    //   3404: iconst_2
    //   3405: iand
    //   3406: ifne -> 3740
    //   3409: iload #10
    //   3411: istore #27
    //   3413: aload_1
    //   3414: iload #27
    //   3416: invokevirtual ᴵʖ : (I)I
    //   3419: istore #28
    //   3421: iinc #27, 2
    //   3424: iload #28
    //   3426: iinc #28, -1
    //   3429: ifle -> 3474
    //   3432: aload_1
    //   3433: iload #27
    //   3435: invokevirtual ᴵʖ : (I)I
    //   3438: istore #29
    //   3440: aload_1
    //   3441: iload #27
    //   3443: iconst_2
    //   3444: iadd
    //   3445: invokevirtual ᴵʖ : (I)I
    //   3448: istore #30
    //   3450: iinc #27, 4
    //   3453: aload_1
    //   3454: iload #29
    //   3456: aload #4
    //   3458: invokespecial ᐨẏ : (I[Lyyds/sniarbtej/ᔪ;)V
    //   3461: aload #4
    //   3463: iload #29
    //   3465: aaload
    //   3466: iload #30
    //   3468: invokevirtual ʿᵉ : (I)V
    //   3471: goto -> 3424
    //   3474: goto -> 3740
    //   3477: ldc_w '痞ជ쐻࿙웒ᒉ毓桜ꪓ휧貑㒚ꛈ㲲Ӧ㳴益딒吳鞶?精힠鈺⦅'
    //   3480: invokevirtual toCharArray : ()[C
    //   3483: dup
    //   3484: dup
    //   3485: bipush #25
    //   3487: dup_x1
    //   3488: caload
    //   3489: sipush #9807
    //   3492: ixor
    //   3493: i2c
    //   3494: castore
    //   3495: sipush #18832
    //   3498: iconst_4
    //   3499: iconst_0
    //   3500: invokestatic W : (Ljava/lang/Object;SBS)Ljava/lang/String;
    //   3503: invokevirtual intern : ()Ljava/lang/String;
    //   3506: aload #19
    //   3508: invokevirtual equals : (Ljava/lang/Object;)Z
    //   3511: ifeq -> 3530
    //   3514: aload_1
    //   3515: aload #7
    //   3517: aload #8
    //   3519: iload #10
    //   3521: iconst_1
    //   3522: invokespecial ᐨẏ : (Lyyds/sniarbtej/ˉｓ;Lyyds/sniarbtej/ʾ;IZ)[I
    //   3525: astore #15
    //   3527: goto -> 3740
    //   3530: ldc_w '映??윪階䒕㦋ꛃ앟Ɽ?䈱?깎񨿫ꄺ勽늬詪鐭⍕췰趝ѐ뗮뻁?ុ䴳'
    //   3533: invokevirtual toCharArray : ()[C
    //   3536: dup
    //   3537: dup
    //   3538: bipush #16
    //   3540: dup_x1
    //   3541: caload
    //   3542: sipush #26050
    //   3545: ixor
    //   3546: i2c
    //   3547: castore
    //   3548: sipush #466
    //   3551: iconst_1
    //   3552: iconst_0
    //   3553: invokestatic W : (Ljava/lang/Object;SBS)Ljava/lang/String;
    //   3556: invokevirtual intern : ()Ljava/lang/String;
    //   3559: aload #19
    //   3561: invokevirtual equals : (Ljava/lang/Object;)Z
    //   3564: ifeq -> 3583
    //   3567: aload_1
    //   3568: aload #7
    //   3570: aload #8
    //   3572: iload #10
    //   3574: iconst_0
    //   3575: invokespecial ᐨẏ : (Lyyds/sniarbtej/ˉｓ;Lyyds/sniarbtej/ʾ;IZ)[I
    //   3578: astore #16
    //   3580: goto -> 3740
    //   3583: ldc_w '꠭Ē臏⌲骃᱙륓댴௛Ų應땵綡'
    //   3586: invokevirtual toCharArray : ()[C
    //   3589: dup
    //   3590: dup
    //   3591: iconst_3
    //   3592: dup_x1
    //   3593: caload
    //   3594: sipush #20540
    //   3597: ixor
    //   3598: i2c
    //   3599: castore
    //   3600: sipush #16509
    //   3603: iconst_5
    //   3604: iconst_1
    //   3605: invokestatic W : (Ljava/lang/Object;SBS)Ljava/lang/String;
    //   3608: invokevirtual intern : ()Ljava/lang/String;
    //   3611: aload #19
    //   3613: invokevirtual equals : (Ljava/lang/Object;)Z
    //   3616: ifeq -> 3645
    //   3619: aload #8
    //   3621: getfield ᕁ : I
    //   3624: iconst_4
    //   3625: iand
    //   3626: ifne -> 3740
    //   3629: iload #10
    //   3631: iconst_2
    //   3632: iadd
    //   3633: istore #11
    //   3635: iload #10
    //   3637: iload #22
    //   3639: iadd
    //   3640: istore #12
    //   3642: goto -> 3740
    //   3645: ldc_w '쥛嬘؉ꓶ鐦牨覞䤆ⵃ'
    //   3648: invokevirtual toCharArray : ()[C
    //   3651: dup
    //   3652: dup
    //   3653: iconst_3
    //   3654: dup_x1
    //   3655: caload
    //   3656: sipush #3871
    //   3659: ixor
    //   3660: i2c
    //   3661: castore
    //   3662: sipush #28009
    //   3665: iconst_5
    //   3666: iconst_1
    //   3667: invokestatic W : (Ljava/lang/Object;SBS)Ljava/lang/String;
    //   3670: aload #19
    //   3672: invokevirtual equals : (Ljava/lang/Object;)Z
    //   3675: ifeq -> 3707
    //   3678: aload #8
    //   3680: getfield ᕁ : I
    //   3683: iconst_4
    //   3684: iand
    //   3685: ifne -> 3740
    //   3688: iload #10
    //   3690: iconst_2
    //   3691: iadd
    //   3692: istore #11
    //   3694: iload #10
    //   3696: iload #22
    //   3698: iadd
    //   3699: istore #12
    //   3701: iconst_0
    //   3702: istore #13
    //   3704: goto -> 3740
    //   3707: aload_1
    //   3708: aload #8
    //   3710: getfield ˊ : [Lyyds/sniarbtej/ᴵʖ;
    //   3713: aload #19
    //   3715: iload #10
    //   3717: iload #22
    //   3719: aload #23
    //   3721: iload #9
    //   3723: aload #4
    //   3725: invokespecial ᐨẏ : ([Lyyds/sniarbtej/ᴵʖ;Ljava/lang/String;II[CI[Lyyds/sniarbtej/ᔪ;)Lyyds/sniarbtej/ᴵʖ;
    //   3728: dup
    //   3729: astore #27
    //   3731: aload #17
    //   3733: putfield ᐨẏ : Lyyds/sniarbtej/ᴵʖ;
    //   3736: aload #27
    //   3738: astore #17
    //   3740: iload #10
    //   3742: iload #22
    //   3744: iadd
    //   3745: istore #10
    //   3747: goto -> 3170
    //   3750: aload #8
    //   3752: getfield ᕁ : I
    //   3755: bipush #8
    //   3757: iand
    //   3758: ifeq -> 3765
    //   3761: iconst_1
    //   3762: goto -> 3766
    //   3765: iconst_0
    //   3766: istore #19
    //   3768: iload #11
    //   3770: ifeq -> 3910
    //   3773: aload #8
    //   3775: iconst_m1
    //   3776: putfield ʽו : I
    //   3779: aload #8
    //   3781: iconst_0
    //   3782: putfield ﹳه : I
    //   3785: aload #8
    //   3787: iconst_0
    //   3788: putfield ᐧǏ : I
    //   3791: aload #8
    //   3793: iconst_0
    //   3794: putfield ιՆ : I
    //   3797: aload #8
    //   3799: iload #25
    //   3801: anewarray java/lang/Object
    //   3804: putfield ˊ : [Ljava/lang/Object;
    //   3807: aload #8
    //   3809: iconst_0
    //   3810: putfield וּ : I
    //   3813: aload #8
    //   3815: iload #24
    //   3817: anewarray java/lang/Object
    //   3820: putfield ᴵʖ : [Ljava/lang/Object;
    //   3823: iload #19
    //   3825: ifeq -> 3834
    //   3828: aload_1
    //   3829: aload #8
    //   3831: invokespecial ᐨẏ : (Lyyds/sniarbtej/ʾ;)V
    //   3834: iload #11
    //   3836: istore #22
    //   3838: iload #22
    //   3840: iload #12
    //   3842: iconst_2
    //   3843: isub
    //   3844: if_icmpge -> 3910
    //   3847: aload #20
    //   3849: iload #22
    //   3851: baload
    //   3852: bipush #8
    //   3854: if_icmpne -> 3904
    //   3857: aload_1
    //   3858: iload #22
    //   3860: iconst_1
    //   3861: iadd
    //   3862: invokevirtual ᴵʖ : (I)I
    //   3865: dup
    //   3866: istore #27
    //   3868: iflt -> 3904
    //   3871: iload #27
    //   3873: iload #26
    //   3875: if_icmpge -> 3904
    //   3878: aload #20
    //   3880: iload_2
    //   3881: iload #27
    //   3883: iadd
    //   3884: baload
    //   3885: sipush #255
    //   3888: iand
    //   3889: sipush #187
    //   3892: if_icmpne -> 3904
    //   3895: aload_1
    //   3896: iload #27
    //   3898: aload #4
    //   3900: invokespecial ˊ : (I[Lyyds/sniarbtej/ᔪ;)Lyyds/sniarbtej/ᔪ;
    //   3903: pop
    //   3904: iinc #22, 1
    //   3907: goto -> 3838
    //   3910: iload #19
    //   3912: ifeq -> 3938
    //   3915: aload #8
    //   3917: getfield ᕁ : I
    //   3920: sipush #256
    //   3923: iand
    //   3924: ifeq -> 3938
    //   3927: aload #7
    //   3929: iconst_m1
    //   3930: iload #25
    //   3932: aconst_null
    //   3933: iconst_0
    //   3934: aconst_null
    //   3935: invokevirtual ᐨẏ : (II[Ljava/lang/Object;I[Ljava/lang/Object;)V
    //   3938: iconst_0
    //   3939: istore #22
    //   3941: aload_1
    //   3942: aload #15
    //   3944: iconst_0
    //   3945: invokespecial ᐨẏ : ([II)I
    //   3948: istore #27
    //   3950: iconst_0
    //   3951: istore #28
    //   3953: aload_1
    //   3954: aload #16
    //   3956: iconst_0
    //   3957: invokespecial ᐨẏ : ([II)I
    //   3960: istore #29
    //   3962: iconst_0
    //   3963: istore #30
    //   3965: aload #8
    //   3967: getfield ᕁ : I
    //   3970: sipush #256
    //   3973: iand
    //   3974: ifne -> 3982
    //   3977: bipush #33
    //   3979: goto -> 3983
    //   3982: iconst_0
    //   3983: istore #9
    //   3985: iload_2
    //   3986: istore #10
    //   3988: iload #10
    //   3990: iload_3
    //   3991: if_icmpge -> 6391
    //   3994: iload #10
    //   3996: iload_2
    //   3997: isub
    //   3998: istore #18
    //   4000: aload #4
    //   4002: iload #18
    //   4004: aaload
    //   4005: dup
    //   4006: astore #31
    //   4008: ifnull -> 4033
    //   4011: aload #31
    //   4013: aload #7
    //   4015: aload #8
    //   4017: getfield ᕁ : I
    //   4020: iconst_2
    //   4021: iand
    //   4022: ifne -> 4029
    //   4025: iconst_1
    //   4026: goto -> 4030
    //   4029: iconst_0
    //   4030: invokevirtual ᐨẏ : (Lyyds/sniarbtej/ˉｓ;Z)V
    //   4033: iload #11
    //   4035: ifeq -> 4168
    //   4038: aload #8
    //   4040: getfield ʽו : I
    //   4043: iload #18
    //   4045: if_icmpeq -> 4057
    //   4048: aload #8
    //   4050: getfield ʽו : I
    //   4053: iconst_m1
    //   4054: if_icmpne -> 4168
    //   4057: aload #8
    //   4059: getfield ʽו : I
    //   4062: iconst_m1
    //   4063: if_icmpeq -> 4138
    //   4066: iload #13
    //   4068: ifeq -> 4076
    //   4071: iload #19
    //   4073: ifeq -> 4105
    //   4076: aload #7
    //   4078: iconst_m1
    //   4079: aload #8
    //   4081: getfield ᐧǏ : I
    //   4084: aload #8
    //   4086: getfield ˊ : [Ljava/lang/Object;
    //   4089: aload #8
    //   4091: getfield וּ : I
    //   4094: aload #8
    //   4096: getfield ᴵʖ : [Ljava/lang/Object;
    //   4099: invokevirtual ᐨẏ : (II[Ljava/lang/Object;I[Ljava/lang/Object;)V
    //   4102: goto -> 4135
    //   4105: aload #7
    //   4107: aload #8
    //   4109: getfield ﹳه : I
    //   4112: aload #8
    //   4114: getfield ιՆ : I
    //   4117: aload #8
    //   4119: getfield ˊ : [Ljava/lang/Object;
    //   4122: aload #8
    //   4124: getfield וּ : I
    //   4127: aload #8
    //   4129: getfield ᴵʖ : [Ljava/lang/Object;
    //   4132: invokevirtual ᐨẏ : (II[Ljava/lang/Object;I[Ljava/lang/Object;)V
    //   4135: iconst_0
    //   4136: istore #30
    //   4138: iload #11
    //   4140: iload #12
    //   4142: if_icmpge -> 4162
    //   4145: aload_1
    //   4146: iload #11
    //   4148: iload #13
    //   4150: iload #19
    //   4152: aload #8
    //   4154: invokespecial ᐨẏ : (IZZLyyds/sniarbtej/ʾ;)I
    //   4157: istore #11
    //   4159: goto -> 4033
    //   4162: iconst_0
    //   4163: istore #11
    //   4165: goto -> 4033
    //   4168: iload #30
    //   4170: ifeq -> 4199
    //   4173: aload #8
    //   4175: getfield ᕁ : I
    //   4178: bipush #8
    //   4180: iand
    //   4181: ifeq -> 4196
    //   4184: aload #7
    //   4186: sipush #256
    //   4189: iconst_0
    //   4190: aconst_null
    //   4191: iconst_0
    //   4192: aconst_null
    //   4193: invokevirtual ᐨẏ : (II[Ljava/lang/Object;I[Ljava/lang/Object;)V
    //   4196: iconst_0
    //   4197: istore #30
    //   4199: aload #20
    //   4201: iload #10
    //   4203: baload
    //   4204: sipush #255
    //   4207: iand
    //   4208: dup
    //   4209: istore #32
    //   4211: tableswitch default -> 6186, 0 -> 5108, 1 -> 5108, 2 -> 5108, 3 -> 5108, 4 -> 5108, 5 -> 5108, 6 -> 5108, 7 -> 5108, 8 -> 5108, 9 -> 5108, 10 -> 5108, 11 -> 5108, 12 -> 5108, 13 -> 5108, 14 -> 5108, 15 -> 5108, 16 -> 5714, 17 -> 5734, 18 -> 5755, 19 -> 5783, 20 -> 5783, 21 -> 5690, 22 -> 5690, 23 -> 5690, 24 -> 5690, 25 -> 5690, 26 -> 5121, 27 -> 5121, 28 -> 5121, 29 -> 5121, 30 -> 5121, 31 -> 5121, 32 -> 5121, 33 -> 5121, 34 -> 5121, 35 -> 5121, 36 -> 5121, 37 -> 5121, 38 -> 5121, 39 -> 5121, 40 -> 5121, 41 -> 5121, 42 -> 5121, 43 -> 5121, 44 -> 5121, 45 -> 5121, 46 -> 5108, 47 -> 5108, 48 -> 5108, 49 -> 5108, 50 -> 5108, 51 -> 5108, 52 -> 5108, 53 -> 5108, 54 -> 5690, 55 -> 5690, 56 -> 5690, 57 -> 5690, 58 -> 5690, 59 -> 5146, 60 -> 5146, 61 -> 5146, 62 -> 5146, 63 -> 5146, 64 -> 5146, 65 -> 5146, 66 -> 5146, 67 -> 5146, 68 -> 5146, 69 -> 5146, 70 -> 5146, 71 -> 5146, 72 -> 5146, 73 -> 5146, 74 -> 5146, 75 -> 5146, 76 -> 5146, 77 -> 5146, 78 -> 5146, 79 -> 5108, 80 -> 5108, 81 -> 5108, 82 -> 5108, 83 -> 5108, 84 -> 5108, 85 -> 5108, 86 -> 5108, 87 -> 5108, 88 -> 5108, 89 -> 5108, 90 -> 5108, 91 -> 5108, 92 -> 5108, 93 -> 5108, 94 -> 5108, 95 -> 5108, 96 -> 5108, 97 -> 5108, 98 -> 5108, 99 -> 5108, 100 -> 5108, 101 -> 5108, 102 -> 5108, 103 -> 5108, 104 -> 5108, 105 -> 5108, 106 -> 5108, 107 -> 5108, 108 -> 5108, 109 -> 5108, 110 -> 5108, 111 -> 5108, 112 -> 5108, 113 -> 5108, 114 -> 5108, 115 -> 5108, 116 -> 5108, 117 -> 5108, 118 -> 5108, 119 -> 5108, 120 -> 5108, 121 -> 5108, 122 -> 5108, 123 -> 5108, 124 -> 5108, 125 -> 5108, 126 -> 5108, 127 -> 5108, 128 -> 5108, 129 -> 5108, 130 -> 5108, 131 -> 5108, 132 -> 6125, 133 -> 5108, 134 -> 5108, 135 -> 5108, 136 -> 5108, 137 -> 5108, 138 -> 5108, 139 -> 5108, 140 -> 5108, 141 -> 5108, 142 -> 5108, 143 -> 5108, 144 -> 5108, 145 -> 5108, 146 -> 5108, 147 -> 5108, 148 -> 5108, 149 -> 5108, 150 -> 5108, 151 -> 5108, 152 -> 5108, 153 -> 5171, 154 -> 5171, 155 -> 5171, 156 -> 5171, 157 -> 5171, 158 -> 5171, 159 -> 5171, 160 -> 5171, 161 -> 5171, 162 -> 5171, 163 -> 5171, 164 -> 5171, 165 -> 5171, 166 -> 5171, 167 -> 5171, 168 -> 5171, 169 -> 5690, 170 -> 5462, 171 -> 5576, 172 -> 5108, 173 -> 5108, 174 -> 5108, 175 -> 5108, 176 -> 5108, 177 -> 5108, 178 -> 5808, 179 -> 5808, 180 -> 5808, 181 -> 5808, 182 -> 5808, 183 -> 5808, 184 -> 5808, 185 -> 5808, 186 -> 5948, 187 -> 6102, 188 -> 5714, 189 -> 6102, 190 -> 5108, 191 -> 5108, 192 -> 6102, 193 -> 6102, 194 -> 5108, 195 -> 5108, 196 -> 5394, 197 -> 6154, 198 -> 5171, 199 -> 5171, 200 -> 5198, 201 -> 5198, 202 -> 5228, 203 -> 5228, 204 -> 5228, 205 -> 5228, 206 -> 5228, 207 -> 5228, 208 -> 5228, 209 -> 5228, 210 -> 5228, 211 -> 5228, 212 -> 5228, 213 -> 5228, 214 -> 5228, 215 -> 5228, 216 -> 5228, 217 -> 5228, 218 -> 5228, 219 -> 5228, 220 -> 5363
    //   5108: aload #7
    //   5110: iload #32
    //   5112: invokevirtual ʹﮃ : (I)V
    //   5115: iinc #10, 1
    //   5118: goto -> 6194
    //   5121: iinc #32, -26
    //   5124: aload #7
    //   5126: bipush #21
    //   5128: iload #32
    //   5130: iconst_2
    //   5131: ishr
    //   5132: iadd
    //   5133: iload #32
    //   5135: iconst_3
    //   5136: iand
    //   5137: invokevirtual ᴵʖ : (II)V
    //   5140: iinc #10, 1
    //   5143: goto -> 6194
    //   5146: iinc #32, -59
    //   5149: aload #7
    //   5151: bipush #54
    //   5153: iload #32
    //   5155: iconst_2
    //   5156: ishr
    //   5157: iadd
    //   5158: iload #32
    //   5160: iconst_3
    //   5161: iand
    //   5162: invokevirtual ᴵʖ : (II)V
    //   5165: iinc #10, 1
    //   5168: goto -> 6194
    //   5171: aload #7
    //   5173: iload #32
    //   5175: aload #4
    //   5177: iload #18
    //   5179: aload_1
    //   5180: iload #10
    //   5182: iconst_1
    //   5183: iadd
    //   5184: invokevirtual ᐨẏ : (I)S
    //   5187: iadd
    //   5188: aaload
    //   5189: invokevirtual ᐨẏ : (ILyyds/sniarbtej/ᔪ;)V
    //   5192: iinc #10, 3
    //   5195: goto -> 6194
    //   5198: aload #7
    //   5200: iload #32
    //   5202: iload #9
    //   5204: isub
    //   5205: aload #4
    //   5207: iload #18
    //   5209: aload_1
    //   5210: iload #10
    //   5212: iconst_1
    //   5213: iadd
    //   5214: invokevirtual ﾞл : (I)I
    //   5217: iadd
    //   5218: aaload
    //   5219: invokevirtual ᐨẏ : (ILyyds/sniarbtej/ᔪ;)V
    //   5222: iinc #10, 5
    //   5225: goto -> 6194
    //   5228: iload #32
    //   5230: sipush #218
    //   5233: if_icmpge -> 5244
    //   5236: iload #32
    //   5238: bipush #49
    //   5240: isub
    //   5241: goto -> 5249
    //   5244: iload #32
    //   5246: bipush #20
    //   5248: isub
    //   5249: istore #32
    //   5251: aload #4
    //   5253: iload #18
    //   5255: aload_1
    //   5256: iload #10
    //   5258: iconst_1
    //   5259: iadd
    //   5260: invokevirtual ᴵʖ : (I)I
    //   5263: iadd
    //   5264: aaload
    //   5265: astore #33
    //   5267: iload #32
    //   5269: sipush #167
    //   5272: if_icmpeq -> 5283
    //   5275: iload #32
    //   5277: sipush #168
    //   5280: if_icmpne -> 5298
    //   5283: aload #7
    //   5285: iload #32
    //   5287: bipush #33
    //   5289: iadd
    //   5290: aload #33
    //   5292: invokevirtual ᐨẏ : (ILyyds/sniarbtej/ᔪ;)V
    //   5295: goto -> 5357
    //   5298: iload #32
    //   5300: sipush #167
    //   5303: if_icmpge -> 5317
    //   5306: iload #32
    //   5308: iconst_1
    //   5309: iadd
    //   5310: iconst_1
    //   5311: ixor
    //   5312: iconst_1
    //   5313: isub
    //   5314: goto -> 5321
    //   5317: iload #32
    //   5319: iconst_1
    //   5320: ixor
    //   5321: istore #32
    //   5323: aload_1
    //   5324: iload #18
    //   5326: iconst_3
    //   5327: iadd
    //   5328: aload #4
    //   5330: invokespecial ˊ : (I[Lyyds/sniarbtej/ᔪ;)Lyyds/sniarbtej/ᔪ;
    //   5333: astore #34
    //   5335: aload #7
    //   5337: iload #32
    //   5339: aload #34
    //   5341: invokevirtual ᐨẏ : (ILyyds/sniarbtej/ᔪ;)V
    //   5344: aload #7
    //   5346: sipush #200
    //   5349: aload #33
    //   5351: invokevirtual ᐨẏ : (ILyyds/sniarbtej/ᔪ;)V
    //   5354: iconst_1
    //   5355: istore #30
    //   5357: iinc #10, 3
    //   5360: goto -> 6194
    //   5363: aload #7
    //   5365: sipush #200
    //   5368: aload #4
    //   5370: iload #18
    //   5372: aload_1
    //   5373: iload #10
    //   5375: iconst_1
    //   5376: iadd
    //   5377: invokevirtual ﾞл : (I)I
    //   5380: iadd
    //   5381: aaload
    //   5382: invokevirtual ᐨẏ : (ILyyds/sniarbtej/ᔪ;)V
    //   5385: iconst_1
    //   5386: istore #30
    //   5388: iinc #10, 5
    //   5391: goto -> 6194
    //   5394: aload #20
    //   5396: iload #10
    //   5398: iconst_1
    //   5399: iadd
    //   5400: baload
    //   5401: sipush #255
    //   5404: iand
    //   5405: dup
    //   5406: istore #32
    //   5408: sipush #132
    //   5411: if_icmpne -> 5441
    //   5414: aload #7
    //   5416: aload_1
    //   5417: iload #10
    //   5419: iconst_2
    //   5420: iadd
    //   5421: invokevirtual ᴵʖ : (I)I
    //   5424: aload_1
    //   5425: iload #10
    //   5427: iconst_4
    //   5428: iadd
    //   5429: invokevirtual ᐨẏ : (I)S
    //   5432: invokevirtual ﾞл : (II)V
    //   5435: iinc #10, 6
    //   5438: goto -> 6194
    //   5441: aload #7
    //   5443: iload #32
    //   5445: aload_1
    //   5446: iload #10
    //   5448: iconst_2
    //   5449: iadd
    //   5450: invokevirtual ᴵʖ : (I)I
    //   5453: invokevirtual ᴵʖ : (II)V
    //   5456: iinc #10, 4
    //   5459: goto -> 6194
    //   5462: iload #10
    //   5464: iconst_4
    //   5465: iload #18
    //   5467: iconst_3
    //   5468: iand
    //   5469: isub
    //   5470: iadd
    //   5471: istore #10
    //   5473: aload #4
    //   5475: iload #18
    //   5477: aload_1
    //   5478: iload #10
    //   5480: invokevirtual ﾞл : (I)I
    //   5483: iadd
    //   5484: aaload
    //   5485: astore #33
    //   5487: aload_1
    //   5488: iload #10
    //   5490: iconst_4
    //   5491: iadd
    //   5492: invokevirtual ﾞл : (I)I
    //   5495: istore #34
    //   5497: aload_1
    //   5498: iload #10
    //   5500: bipush #8
    //   5502: iadd
    //   5503: invokevirtual ﾞл : (I)I
    //   5506: istore #35
    //   5508: iinc #10, 12
    //   5511: iload #35
    //   5513: iload #34
    //   5515: isub
    //   5516: iconst_1
    //   5517: iadd
    //   5518: anewarray yyds/sniarbtej/ᔪ
    //   5521: astore #36
    //   5523: iconst_0
    //   5524: istore #37
    //   5526: iload #37
    //   5528: aload #36
    //   5530: arraylength
    //   5531: if_icmpge -> 5560
    //   5534: aload #36
    //   5536: iload #37
    //   5538: aload #4
    //   5540: iload #18
    //   5542: aload_1
    //   5543: iload #10
    //   5545: invokevirtual ﾞл : (I)I
    //   5548: iadd
    //   5549: aaload
    //   5550: aastore
    //   5551: iinc #10, 4
    //   5554: iinc #37, 1
    //   5557: goto -> 5526
    //   5560: aload #7
    //   5562: iload #34
    //   5564: iload #35
    //   5566: aload #33
    //   5568: aload #36
    //   5570: invokevirtual ᐨẏ : (IILyyds/sniarbtej/ᔪ;[Lyyds/sniarbtej/ᔪ;)V
    //   5573: goto -> 6194
    //   5576: iload #10
    //   5578: iconst_4
    //   5579: iload #18
    //   5581: iconst_3
    //   5582: iand
    //   5583: isub
    //   5584: iadd
    //   5585: istore #10
    //   5587: aload #4
    //   5589: iload #18
    //   5591: aload_1
    //   5592: iload #10
    //   5594: invokevirtual ﾞл : (I)I
    //   5597: iadd
    //   5598: aaload
    //   5599: astore #33
    //   5601: aload_1
    //   5602: iload #10
    //   5604: iconst_4
    //   5605: iadd
    //   5606: invokevirtual ﾞл : (I)I
    //   5609: istore #34
    //   5611: iinc #10, 8
    //   5614: iload #34
    //   5616: newarray int
    //   5618: astore #35
    //   5620: iload #34
    //   5622: anewarray yyds/sniarbtej/ᔪ
    //   5625: astore #36
    //   5627: iconst_0
    //   5628: istore #37
    //   5630: iload #37
    //   5632: iload #34
    //   5634: if_icmpge -> 5676
    //   5637: aload #35
    //   5639: iload #37
    //   5641: aload_1
    //   5642: iload #10
    //   5644: invokevirtual ﾞл : (I)I
    //   5647: iastore
    //   5648: aload #36
    //   5650: iload #37
    //   5652: aload #4
    //   5654: iload #18
    //   5656: aload_1
    //   5657: iload #10
    //   5659: iconst_4
    //   5660: iadd
    //   5661: invokevirtual ﾞл : (I)I
    //   5664: iadd
    //   5665: aaload
    //   5666: aastore
    //   5667: iinc #10, 8
    //   5670: iinc #37, 1
    //   5673: goto -> 5630
    //   5676: aload #7
    //   5678: aload #33
    //   5680: aload #35
    //   5682: aload #36
    //   5684: invokevirtual ᐨẏ : (Lyyds/sniarbtej/ᔪ;[I[Lyyds/sniarbtej/ᔪ;)V
    //   5687: goto -> 6194
    //   5690: aload #7
    //   5692: iload #32
    //   5694: aload #20
    //   5696: iload #10
    //   5698: iconst_1
    //   5699: iadd
    //   5700: baload
    //   5701: sipush #255
    //   5704: iand
    //   5705: invokevirtual ᴵʖ : (II)V
    //   5708: iinc #10, 2
    //   5711: goto -> 6194
    //   5714: aload #7
    //   5716: iload #32
    //   5718: aload #20
    //   5720: iload #10
    //   5722: iconst_1
    //   5723: iadd
    //   5724: baload
    //   5725: invokevirtual ˊ : (II)V
    //   5728: iinc #10, 2
    //   5731: goto -> 6194
    //   5734: aload #7
    //   5736: iload #32
    //   5738: aload_1
    //   5739: iload #10
    //   5741: iconst_1
    //   5742: iadd
    //   5743: invokevirtual ᐨẏ : (I)S
    //   5746: invokevirtual ˊ : (II)V
    //   5749: iinc #10, 3
    //   5752: goto -> 6194
    //   5755: aload #7
    //   5757: aload_1
    //   5758: aload #20
    //   5760: iload #10
    //   5762: iconst_1
    //   5763: iadd
    //   5764: baload
    //   5765: sipush #255
    //   5768: iand
    //   5769: aload #23
    //   5771: invokevirtual ᐨẏ : (I[C)Ljava/lang/Object;
    //   5774: invokevirtual ˊ : (Ljava/lang/Object;)V
    //   5777: iinc #10, 2
    //   5780: goto -> 6194
    //   5783: aload #7
    //   5785: aload_1
    //   5786: dup
    //   5787: iload #10
    //   5789: iconst_1
    //   5790: iadd
    //   5791: invokevirtual ᴵʖ : (I)I
    //   5794: aload #23
    //   5796: invokevirtual ᐨẏ : (I[C)Ljava/lang/Object;
    //   5799: invokevirtual ˊ : (Ljava/lang/Object;)V
    //   5802: iinc #10, 3
    //   5805: goto -> 6194
    //   5808: aload_1
    //   5809: getfield ᐨẏ : [I
    //   5812: aload_1
    //   5813: iload #10
    //   5815: iconst_1
    //   5816: iadd
    //   5817: invokevirtual ᴵʖ : (I)I
    //   5820: iaload
    //   5821: istore #33
    //   5823: aload_1
    //   5824: getfield ᐨẏ : [I
    //   5827: aload_1
    //   5828: iload #33
    //   5830: iconst_2
    //   5831: iadd
    //   5832: invokevirtual ᴵʖ : (I)I
    //   5835: iaload
    //   5836: istore #34
    //   5838: aload_1
    //   5839: iload #33
    //   5841: aload #23
    //   5843: invokevirtual ﾞл : (I[C)Ljava/lang/String;
    //   5846: astore #35
    //   5848: aload_1
    //   5849: iload #34
    //   5851: aload #23
    //   5853: invokevirtual ᐨẏ : (I[C)Ljava/lang/String;
    //   5856: astore #36
    //   5858: aload_1
    //   5859: iload #34
    //   5861: iconst_2
    //   5862: iadd
    //   5863: aload #23
    //   5865: invokevirtual ᐨẏ : (I[C)Ljava/lang/String;
    //   5868: astore #37
    //   5870: iload #32
    //   5872: sipush #182
    //   5875: if_icmpge -> 5894
    //   5878: aload #7
    //   5880: iload #32
    //   5882: aload #35
    //   5884: aload #36
    //   5886: aload #37
    //   5888: invokevirtual ᐨẏ : (ILjava/lang/String;Ljava/lang/String;Ljava/lang/String;)V
    //   5891: goto -> 5928
    //   5894: aload #20
    //   5896: iload #33
    //   5898: iconst_1
    //   5899: isub
    //   5900: baload
    //   5901: bipush #11
    //   5903: if_icmpne -> 5910
    //   5906: iconst_1
    //   5907: goto -> 5911
    //   5910: iconst_0
    //   5911: istore #38
    //   5913: aload #7
    //   5915: iload #32
    //   5917: aload #35
    //   5919: aload #36
    //   5921: aload #37
    //   5923: iload #38
    //   5925: invokevirtual ᐨẏ : (ILjava/lang/String;Ljava/lang/String;Ljava/lang/String;Z)V
    //   5928: iload #32
    //   5930: sipush #185
    //   5933: if_icmpne -> 5942
    //   5936: iinc #10, 5
    //   5939: goto -> 6194
    //   5942: iinc #10, 3
    //   5945: goto -> 6194
    //   5948: aload_1
    //   5949: getfield ᐨẏ : [I
    //   5952: aload_1
    //   5953: iload #10
    //   5955: iconst_1
    //   5956: iadd
    //   5957: invokevirtual ᴵʖ : (I)I
    //   5960: iaload
    //   5961: istore #33
    //   5963: aload_1
    //   5964: getfield ᐨẏ : [I
    //   5967: aload_1
    //   5968: iload #33
    //   5970: iconst_2
    //   5971: iadd
    //   5972: invokevirtual ᴵʖ : (I)I
    //   5975: iaload
    //   5976: istore #34
    //   5978: aload_1
    //   5979: iload #34
    //   5981: aload #23
    //   5983: invokevirtual ᐨẏ : (I[C)Ljava/lang/String;
    //   5986: astore #35
    //   5988: aload_1
    //   5989: iload #34
    //   5991: iconst_2
    //   5992: iadd
    //   5993: aload #23
    //   5995: invokevirtual ᐨẏ : (I[C)Ljava/lang/String;
    //   5998: astore #36
    //   6000: aload_1
    //   6001: getfield ˊ : [I
    //   6004: aload_1
    //   6005: iload #33
    //   6007: invokevirtual ᴵʖ : (I)I
    //   6010: iaload
    //   6011: istore #37
    //   6013: aload_1
    //   6014: dup
    //   6015: iload #37
    //   6017: invokevirtual ᴵʖ : (I)I
    //   6020: aload #23
    //   6022: invokevirtual ᐨẏ : (I[C)Ljava/lang/Object;
    //   6025: checkcast yyds/sniarbtej/ʹō
    //   6028: astore #38
    //   6030: aload_1
    //   6031: iload #37
    //   6033: iconst_2
    //   6034: iadd
    //   6035: invokevirtual ᴵʖ : (I)I
    //   6038: anewarray java/lang/Object
    //   6041: astore #64
    //   6043: iinc #37, 4
    //   6046: iconst_0
    //   6047: istore #65
    //   6049: iload #65
    //   6051: aload #64
    //   6053: arraylength
    //   6054: if_icmpge -> 6083
    //   6057: aload #64
    //   6059: iload #65
    //   6061: aload_1
    //   6062: dup
    //   6063: iload #37
    //   6065: invokevirtual ᴵʖ : (I)I
    //   6068: aload #23
    //   6070: invokevirtual ᐨẏ : (I[C)Ljava/lang/Object;
    //   6073: aastore
    //   6074: iinc #37, 2
    //   6077: iinc #65, 1
    //   6080: goto -> 6049
    //   6083: aload #7
    //   6085: aload #35
    //   6087: aload #36
    //   6089: aload #38
    //   6091: aload #64
    //   6093: invokevirtual ᐨẏ : (Ljava/lang/String;Ljava/lang/String;Lyyds/sniarbtej/ʹō;[Ljava/lang/Object;)V
    //   6096: iinc #10, 5
    //   6099: goto -> 6194
    //   6102: aload #7
    //   6104: iload #32
    //   6106: aload_1
    //   6107: iload #10
    //   6109: iconst_1
    //   6110: iadd
    //   6111: aload #23
    //   6113: invokevirtual ﾞл : (I[C)Ljava/lang/String;
    //   6116: invokevirtual ᐨẏ : (ILjava/lang/String;)V
    //   6119: iinc #10, 3
    //   6122: goto -> 6194
    //   6125: aload #7
    //   6127: aload #20
    //   6129: iload #10
    //   6131: iconst_1
    //   6132: iadd
    //   6133: baload
    //   6134: sipush #255
    //   6137: iand
    //   6138: aload #20
    //   6140: iload #10
    //   6142: iconst_2
    //   6143: iadd
    //   6144: baload
    //   6145: invokevirtual ﾞл : (II)V
    //   6148: iinc #10, 3
    //   6151: goto -> 6194
    //   6154: aload #7
    //   6156: aload_1
    //   6157: iload #10
    //   6159: iconst_1
    //   6160: iadd
    //   6161: aload #23
    //   6163: invokevirtual ﾞл : (I[C)Ljava/lang/String;
    //   6166: aload #20
    //   6168: iload #10
    //   6170: iconst_3
    //   6171: iadd
    //   6172: baload
    //   6173: sipush #255
    //   6176: iand
    //   6177: invokevirtual ˊ : (Ljava/lang/String;I)V
    //   6180: iinc #10, 4
    //   6183: goto -> 6194
    //   6186: new java/lang/AssertionError
    //   6189: dup
    //   6190: invokespecial <init> : ()V
    //   6193: athrow
    //   6194: aload #15
    //   6196: ifnull -> 6291
    //   6199: iload #22
    //   6201: aload #15
    //   6203: arraylength
    //   6204: if_icmpge -> 6291
    //   6207: iload #27
    //   6209: iload #18
    //   6211: if_icmpgt -> 6291
    //   6214: iload #27
    //   6216: iload #18
    //   6218: if_icmpne -> 6275
    //   6221: aload_1
    //   6222: aload #8
    //   6224: aload #15
    //   6226: iload #22
    //   6228: iaload
    //   6229: invokespecial ᐨẏ : (Lyyds/sniarbtej/ʾ;I)I
    //   6232: istore #33
    //   6234: aload_1
    //   6235: iload #33
    //   6237: aload #23
    //   6239: invokevirtual ᐨẏ : (I[C)Ljava/lang/String;
    //   6242: astore #34
    //   6244: iinc #33, 2
    //   6247: aload_1
    //   6248: aload #7
    //   6250: aload #8
    //   6252: getfield ιƚ : I
    //   6255: aload #8
    //   6257: getfield ᐨẏ : Lyyds/sniarbtej/ˏɪ;
    //   6260: aload #34
    //   6262: iconst_1
    //   6263: invokevirtual ˊ : (ILyyds/sniarbtej/ˏɪ;Ljava/lang/String;Z)Lyyds/sniarbtej/ᐨẏ;
    //   6266: iload #33
    //   6268: iconst_1
    //   6269: aload #23
    //   6271: invokespecial ᐨẏ : (Lyyds/sniarbtej/ᐨẏ;IZ[C)I
    //   6274: pop
    //   6275: aload_1
    //   6276: aload #15
    //   6278: iinc #22, 1
    //   6281: iload #22
    //   6283: invokespecial ᐨẏ : ([II)I
    //   6286: istore #27
    //   6288: goto -> 6194
    //   6291: aload #16
    //   6293: ifnull -> 6388
    //   6296: iload #28
    //   6298: aload #16
    //   6300: arraylength
    //   6301: if_icmpge -> 6388
    //   6304: iload #29
    //   6306: iload #18
    //   6308: if_icmpgt -> 6388
    //   6311: iload #29
    //   6313: iload #18
    //   6315: if_icmpne -> 6372
    //   6318: aload_1
    //   6319: aload #8
    //   6321: aload #16
    //   6323: iload #28
    //   6325: iaload
    //   6326: invokespecial ᐨẏ : (Lyyds/sniarbtej/ʾ;I)I
    //   6329: istore #33
    //   6331: aload_1
    //   6332: iload #33
    //   6334: aload #23
    //   6336: invokevirtual ᐨẏ : (I[C)Ljava/lang/String;
    //   6339: astore #34
    //   6341: iinc #33, 2
    //   6344: aload_1
    //   6345: aload #7
    //   6347: aload #8
    //   6349: getfield ιƚ : I
    //   6352: aload #8
    //   6354: getfield ᐨẏ : Lyyds/sniarbtej/ˏɪ;
    //   6357: aload #34
    //   6359: iconst_0
    //   6360: invokevirtual ˊ : (ILyyds/sniarbtej/ˏɪ;Ljava/lang/String;Z)Lyyds/sniarbtej/ᐨẏ;
    //   6363: iload #33
    //   6365: iconst_1
    //   6366: aload #23
    //   6368: invokespecial ᐨẏ : (Lyyds/sniarbtej/ᐨẏ;IZ[C)I
    //   6371: pop
    //   6372: aload_1
    //   6373: aload #16
    //   6375: iinc #28, 1
    //   6378: iload #28
    //   6380: invokespecial ᐨẏ : ([II)I
    //   6383: istore #29
    //   6385: goto -> 6291
    //   6388: goto -> 3988
    //   6391: aload #4
    //   6393: iload #26
    //   6395: aaload
    //   6396: ifnull -> 6409
    //   6399: aload #7
    //   6401: aload #4
    //   6403: iload #26
    //   6405: aaload
    //   6406: invokevirtual ˊ : (Lyyds/sniarbtej/ᔪ;)V
    //   6409: iload #14
    //   6411: ifeq -> 6683
    //   6414: aload #8
    //   6416: getfield ᕁ : I
    //   6419: iconst_2
    //   6420: iand
    //   6421: ifne -> 6683
    //   6424: aconst_null
    //   6425: astore #18
    //   6427: iload #6
    //   6429: ifeq -> 6510
    //   6432: aload_1
    //   6433: iload #6
    //   6435: invokevirtual ᴵʖ : (I)I
    //   6438: iconst_3
    //   6439: imul
    //   6440: newarray int
    //   6442: astore #18
    //   6444: iload #6
    //   6446: iconst_2
    //   6447: iadd
    //   6448: istore #10
    //   6450: aload #18
    //   6452: arraylength
    //   6453: istore #31
    //   6455: iload #31
    //   6457: ifle -> 6510
    //   6460: aload #18
    //   6462: iinc #31, -1
    //   6465: iload #31
    //   6467: iload #10
    //   6469: bipush #6
    //   6471: iadd
    //   6472: iastore
    //   6473: aload #18
    //   6475: iinc #31, -1
    //   6478: iload #31
    //   6480: aload_1
    //   6481: iload #10
    //   6483: bipush #8
    //   6485: iadd
    //   6486: invokevirtual ᴵʖ : (I)I
    //   6489: iastore
    //   6490: aload #18
    //   6492: iinc #31, -1
    //   6495: iload #31
    //   6497: aload_1
    //   6498: iload #10
    //   6500: invokevirtual ᴵʖ : (I)I
    //   6503: iastore
    //   6504: iinc #10, 10
    //   6507: goto -> 6455
    //   6510: aload_1
    //   6511: iload #14
    //   6513: invokevirtual ᴵʖ : (I)I
    //   6516: istore #31
    //   6518: iload #14
    //   6520: iconst_2
    //   6521: iadd
    //   6522: istore #10
    //   6524: iload #31
    //   6526: iinc #31, -1
    //   6529: ifle -> 6683
    //   6532: aload_1
    //   6533: iload #10
    //   6535: invokevirtual ᴵʖ : (I)I
    //   6538: istore #32
    //   6540: aload_1
    //   6541: iload #10
    //   6543: iconst_2
    //   6544: iadd
    //   6545: invokevirtual ᴵʖ : (I)I
    //   6548: istore #33
    //   6550: aload_1
    //   6551: iload #10
    //   6553: iconst_4
    //   6554: iadd
    //   6555: aload #23
    //   6557: invokevirtual ᐨẏ : (I[C)Ljava/lang/String;
    //   6560: astore #34
    //   6562: aload_1
    //   6563: iload #10
    //   6565: bipush #6
    //   6567: iadd
    //   6568: aload #23
    //   6570: invokevirtual ᐨẏ : (I[C)Ljava/lang/String;
    //   6573: astore #35
    //   6575: aload_1
    //   6576: iload #10
    //   6578: bipush #8
    //   6580: iadd
    //   6581: invokevirtual ᴵʖ : (I)I
    //   6584: istore #36
    //   6586: iinc #10, 10
    //   6589: aconst_null
    //   6590: astore #37
    //   6592: aload #18
    //   6594: ifnull -> 6654
    //   6597: iconst_0
    //   6598: istore #38
    //   6600: iload #38
    //   6602: aload #18
    //   6604: arraylength
    //   6605: if_icmpge -> 6654
    //   6608: aload #18
    //   6610: iload #38
    //   6612: iaload
    //   6613: iload #32
    //   6615: if_icmpne -> 6648
    //   6618: aload #18
    //   6620: iload #38
    //   6622: iconst_1
    //   6623: iadd
    //   6624: iaload
    //   6625: iload #36
    //   6627: if_icmpne -> 6648
    //   6630: aload_1
    //   6631: aload #18
    //   6633: iload #38
    //   6635: iconst_2
    //   6636: iadd
    //   6637: iaload
    //   6638: aload #23
    //   6640: invokevirtual ᐨẏ : (I[C)Ljava/lang/String;
    //   6643: astore #37
    //   6645: goto -> 6654
    //   6648: iinc #38, 3
    //   6651: goto -> 6600
    //   6654: aload #7
    //   6656: aload #34
    //   6658: aload #35
    //   6660: aload #37
    //   6662: aload #4
    //   6664: iload #32
    //   6666: aaload
    //   6667: aload #4
    //   6669: iload #32
    //   6671: iload #33
    //   6673: iadd
    //   6674: aaload
    //   6675: iload #36
    //   6677: invokevirtual ᐨẏ : (Ljava/lang/String;Ljava/lang/String;Ljava/lang/String;Lyyds/sniarbtej/ᔪ;Lyyds/sniarbtej/ᔪ;I)V
    //   6680: goto -> 6524
    //   6683: aload #15
    //   6685: ifnull -> 6806
    //   6688: aload #15
    //   6690: dup
    //   6691: astore #18
    //   6693: arraylength
    //   6694: istore #31
    //   6696: iconst_0
    //   6697: istore #32
    //   6699: iload #32
    //   6701: iload #31
    //   6703: if_icmpge -> 6806
    //   6706: aload #18
    //   6708: iload #32
    //   6710: iaload
    //   6711: istore #33
    //   6713: aload_1
    //   6714: iload #33
    //   6716: invokevirtual ˊ : (I)I
    //   6719: dup
    //   6720: istore #34
    //   6722: bipush #64
    //   6724: if_icmpeq -> 6734
    //   6727: iload #34
    //   6729: bipush #65
    //   6731: if_icmpne -> 6800
    //   6734: aload_1
    //   6735: aload #8
    //   6737: iload #33
    //   6739: invokespecial ᐨẏ : (Lyyds/sniarbtej/ʾ;I)I
    //   6742: istore #10
    //   6744: aload_1
    //   6745: iload #10
    //   6747: aload #23
    //   6749: invokevirtual ᐨẏ : (I[C)Ljava/lang/String;
    //   6752: astore #35
    //   6754: iinc #10, 2
    //   6757: aload_1
    //   6758: aload #7
    //   6760: aload #8
    //   6762: getfield ιƚ : I
    //   6765: aload #8
    //   6767: getfield ᐨẏ : Lyyds/sniarbtej/ˏɪ;
    //   6770: aload #8
    //   6772: getfield ˊ : [Lyyds/sniarbtej/ᔪ;
    //   6775: aload #8
    //   6777: getfield ᴵʖ : [Lyyds/sniarbtej/ᔪ;
    //   6780: aload #8
    //   6782: getfield ﾞл : [I
    //   6785: aload #35
    //   6787: iconst_1
    //   6788: invokevirtual ᐨẏ : (ILyyds/sniarbtej/ˏɪ;[Lyyds/sniarbtej/ᔪ;[Lyyds/sniarbtej/ᔪ;[ILjava/lang/String;Z)Lyyds/sniarbtej/ᐨẏ;
    //   6791: iload #10
    //   6793: iconst_1
    //   6794: aload #23
    //   6796: invokespecial ᐨẏ : (Lyyds/sniarbtej/ᐨẏ;IZ[C)I
    //   6799: pop
    //   6800: iinc #32, 1
    //   6803: goto -> 6699
    //   6806: aload #16
    //   6808: ifnull -> 6929
    //   6811: aload #16
    //   6813: dup
    //   6814: astore #18
    //   6816: arraylength
    //   6817: istore #31
    //   6819: iconst_0
    //   6820: istore #32
    //   6822: iload #32
    //   6824: iload #31
    //   6826: if_icmpge -> 6929
    //   6829: aload #18
    //   6831: iload #32
    //   6833: iaload
    //   6834: istore #33
    //   6836: aload_1
    //   6837: iload #33
    //   6839: invokevirtual ˊ : (I)I
    //   6842: dup
    //   6843: istore #34
    //   6845: bipush #64
    //   6847: if_icmpeq -> 6857
    //   6850: iload #34
    //   6852: bipush #65
    //   6854: if_icmpne -> 6923
    //   6857: aload_1
    //   6858: aload #8
    //   6860: iload #33
    //   6862: invokespecial ᐨẏ : (Lyyds/sniarbtej/ʾ;I)I
    //   6865: istore #10
    //   6867: aload_1
    //   6868: iload #10
    //   6870: aload #23
    //   6872: invokevirtual ᐨẏ : (I[C)Ljava/lang/String;
    //   6875: astore #35
    //   6877: iinc #10, 2
    //   6880: aload_1
    //   6881: aload #7
    //   6883: aload #8
    //   6885: getfield ιƚ : I
    //   6888: aload #8
    //   6890: getfield ᐨẏ : Lyyds/sniarbtej/ˏɪ;
    //   6893: aload #8
    //   6895: getfield ˊ : [Lyyds/sniarbtej/ᔪ;
    //   6898: aload #8
    //   6900: getfield ᴵʖ : [Lyyds/sniarbtej/ᔪ;
    //   6903: aload #8
    //   6905: getfield ﾞл : [I
    //   6908: aload #35
    //   6910: iconst_0
    //   6911: invokevirtual ᐨẏ : (ILyyds/sniarbtej/ˏɪ;[Lyyds/sniarbtej/ᔪ;[Lyyds/sniarbtej/ᔪ;[ILjava/lang/String;Z)Lyyds/sniarbtej/ᐨẏ;
    //   6914: iload #10
    //   6916: iconst_1
    //   6917: aload #23
    //   6919: invokespecial ᐨẏ : (Lyyds/sniarbtej/ᐨẏ;IZ[C)I
    //   6922: pop
    //   6923: iinc #32, 1
    //   6926: goto -> 6822
    //   6929: aload #17
    //   6931: ifnull -> 6961
    //   6934: aload #17
    //   6936: getfield ᐨẏ : Lyyds/sniarbtej/ᴵʖ;
    //   6939: astore #18
    //   6941: aload #17
    //   6943: aconst_null
    //   6944: putfield ᐨẏ : Lyyds/sniarbtej/ᴵʖ;
    //   6947: aload #7
    //   6949: aload #17
    //   6951: invokevirtual ᴵʖ : (Lyyds/sniarbtej/ᴵʖ;)V
    //   6954: aload #18
    //   6956: astore #17
    //   6958: goto -> 6929
    //   6961: aload #7
    //   6963: iload #24
    //   6965: iload #25
    //   6967: invokevirtual ʿᵉ : (II)V
    //   6970: aload #21
    //   6972: invokevirtual ᐨẏ : ()V
    //   6975: iload #5
    //   6977: ireturn
  }
  
  private void ᐨẏ(ˉｓ paramˉｓ, ʾ paramʾ, int paramInt) {
    int i = paramInt;
    byte[] arrayOfByte = this.ﾞл;
    ˏɪ ˏɪ1 = paramʾ.ᐨẏ;
    int j = ᴵʖ(i);
    int k = ᴵʖ(i + 2);
    int m = ﾞл(i + 4);
    i += 8;
    if (m > this.ﾞл.length - i)
      throw new IllegalArgumentException(); 
    int n = i;
    int i1 = i + m;
    ˏɪ ˏɪ2 = paramʾ.ᐨẏ = (ˏɪ)new ᔪ[m + 1];
    while (i < i1) {
      int i11;
      int i12;
      int i9 = i - n;
      int i10;
      switch (i10 = arrayOfByte[i] & 0xFF) {
        case 0:
        case 1:
        case 2:
        case 3:
        case 4:
        case 5:
        case 6:
        case 7:
        case 8:
        case 9:
        case 10:
        case 11:
        case 12:
        case 13:
        case 14:
        case 15:
        case 26:
        case 27:
        case 28:
        case 29:
        case 30:
        case 31:
        case 32:
        case 33:
        case 34:
        case 35:
        case 36:
        case 37:
        case 38:
        case 39:
        case 40:
        case 41:
        case 42:
        case 43:
        case 44:
        case 45:
        case 46:
        case 47:
        case 48:
        case 49:
        case 50:
        case 51:
        case 52:
        case 53:
        case 59:
        case 60:
        case 61:
        case 62:
        case 63:
        case 64:
        case 65:
        case 66:
        case 67:
        case 68:
        case 69:
        case 70:
        case 71:
        case 72:
        case 73:
        case 74:
        case 75:
        case 76:
        case 77:
        case 78:
        case 79:
        case 80:
        case 81:
        case 82:
        case 83:
        case 84:
        case 85:
        case 86:
        case 87:
        case 88:
        case 89:
        case 90:
        case 91:
        case 92:
        case 93:
        case 94:
        case 95:
        case 96:
        case 97:
        case 98:
        case 99:
        case 100:
        case 101:
        case 102:
        case 103:
        case 104:
        case 105:
        case 106:
        case 107:
        case 108:
        case 109:
        case 110:
        case 111:
        case 112:
        case 113:
        case 114:
        case 115:
        case 116:
        case 117:
        case 118:
        case 119:
        case 120:
        case 121:
        case 122:
        case 123:
        case 124:
        case 125:
        case 126:
        case 127:
        case 128:
        case 129:
        case 130:
        case 131:
        case 133:
        case 134:
        case 135:
        case 136:
        case 137:
        case 138:
        case 139:
        case 140:
        case 141:
        case 142:
        case 143:
        case 144:
        case 145:
        case 146:
        case 147:
        case 148:
        case 149:
        case 150:
        case 151:
        case 152:
        case 172:
        case 173:
        case 174:
        case 175:
        case 176:
        case 177:
        case 190:
        case 191:
        case 194:
        case 195:
          i++;
          continue;
        case 153:
        case 154:
        case 155:
        case 156:
        case 157:
        case 158:
        case 159:
        case 160:
        case 161:
        case 162:
        case 163:
        case 164:
        case 165:
        case 166:
        case 167:
        case 168:
        case 198:
        case 199:
          ˊ(i9 + ᐨẏ(i + 1), (ᔪ[])ˏɪ2);
          i += 3;
          continue;
        case 202:
        case 203:
        case 204:
        case 205:
        case 206:
        case 207:
        case 208:
        case 209:
        case 210:
        case 211:
        case 212:
        case 213:
        case 214:
        case 215:
        case 216:
        case 217:
        case 218:
        case 219:
          ˊ(i9 + ᴵʖ(i + 1), (ᔪ[])ˏɪ2);
          i += 3;
          continue;
        case 200:
        case 201:
        case 220:
          ˊ(i9 + ﾞл(i + 1), (ᔪ[])ˏɪ2);
          i += 5;
          continue;
        case 196:
          switch (arrayOfByte[i + 1] & 0xFF) {
            case 21:
            case 22:
            case 23:
            case 24:
            case 25:
            case 54:
            case 55:
            case 56:
            case 57:
            case 58:
            case 169:
              i += 4;
              continue;
            case 132:
              i += 6;
              continue;
          } 
          throw new IllegalArgumentException();
        case 170:
          i += 4 - (i9 & 0x3);
          ˊ(i9 + ﾞл(i), (ᔪ[])ˏɪ2);
          i11 = ﾞл(i + 8) - ﾞл(i + 4) + 1;
          for (i += 12; i11-- > 0; i += 4)
            ˊ(i9 + ﾞл(i), (ᔪ[])ˏɪ2); 
          continue;
        case 171:
          i += 4 - (i9 & 0x3);
          ˊ(i9 + ﾞл(i), (ᔪ[])ˏɪ2);
          i12 = ﾞл(i + 4);
          for (i += 8; i12-- > 0; i += 8)
            ˊ(i9 + ﾞл(i + 4), (ᔪ[])ˏɪ2); 
          continue;
        case 16:
        case 18:
        case 21:
        case 22:
        case 23:
        case 24:
        case 25:
        case 54:
        case 55:
        case 56:
        case 57:
        case 58:
        case 169:
        case 188:
          i += 2;
          continue;
        case 17:
        case 19:
        case 20:
        case 132:
        case 178:
        case 179:
        case 180:
        case 181:
        case 182:
        case 183:
        case 184:
        case 187:
        case 189:
        case 192:
        case 193:
          i += 3;
          continue;
        case 185:
        case 186:
          i += 5;
          continue;
        case 197:
          i += 4;
          continue;
      } 
      throw new IllegalArgumentException();
    } 
    int i2 = ᴵʖ(i);
    i += 2;
    while (i2-- > 0) {
      ᔪ ᔪ1 = ˊ(ᴵʖ(i), (ᔪ[])ˏɪ2);
      ᔪ ᔪ2 = ˊ(ᴵʖ(i + 2), (ᔪ[])ˏɪ2);
      ᔪ ᔪ3 = ˊ(ᴵʖ(i + 4), (ᔪ[])ˏɪ2);
      String str = ᐨẏ(this.ᐨẏ[ᴵʖ(i + 6)], (char[])ˏɪ1);
      i += 8;
      paramˉｓ.ᐨẏ(ᔪ1, ᔪ2, ᔪ3, str);
    } 
    int i3 = 0;
    int i4 = 0;
    boolean bool1 = true;
    int i5 = 0;
    i2 = 0;
    int[] arrayOfInt1 = null;
    int[] arrayOfInt2 = null;
    ᴵʖ ᴵʖ = null;
    int i6 = ᴵʖ(i);
    for (i += 2; i6-- > 0; i += i9) {
      String str = ᐨẏ(i, (char[])ˏɪ1);
      int i9 = ﾞл(i + 2);
      i += 6;
      "毂렷屸㙭ᐸ鐭岪⢖밁䠮ᰏ訜疞菇䏞詁ḏ".toCharArray()[6] = (char)("毂렷屸㙭ᐸ鐭岪⢖밁䠮ᰏ訜疞菇䏞詁ḏ".toCharArray()[6] ^ 0x2FA);
      if (ˏȓ$ᴵЃ.E("毂렷屸㙭ᐸ鐭岪⢖밁䠮ᰏ訜疞菇䏞詁ḏ".toCharArray(), (short)21723, (short)4, (short)4).intern().equals(str)) {
        if ((paramʾ.ᕁ & 0x2) == 0) {
          i5 = i;
          int i10 = i;
          int i11 = ᴵʖ(i10);
          for (i10 += 2; i11-- > 0; i10 += 10) {
            int i12 = ᴵʖ(i10);
            ᐨẏ(i12, (ᔪ[])ˏɪ2);
            int i13 = ᴵʖ(i10 + 2);
            ᐨẏ(i12 + i13, (ᔪ[])ˏɪ2);
          } 
        } 
      } else {
        "ᝏꥳ塋ꮸ軜钿꼣Ў⁓꺁贽쥱뢙ꗋᴫ뜕맔綣ᓍ䦸Ⲩ".toCharArray()[16] = (char)("ᝏꥳ塋ꮸ軜钿꼣Ў⁓꺁贽쥱뢙ꗋᴫ뜕맔綣ᓍ䦸Ⲩ".toCharArray()[16] ^ 0x33ED);
        if (ˏȓ$ᴵЃ.E("ᝏꥳ塋ꮸ軜钿꼣Ў⁓꺁贽쥱뢙ꗋᴫ뜕맔綣ᓍ䦸Ⲩ".toCharArray(), (short)25595, (short)2, (short)1).intern().equals(str)) {
          i2 = i;
        } else {
          "簃쀺炥৵╄ﱊ疠ԅⰈ༪瑊ᬬ縌洃絳".toCharArray()[6] = (char)("簃쀺炥৵╄ﱊ疠ԅⰈ༪瑊ᬬ縌洃絳".toCharArray()[6] ^ 0x8E2);
          if (ˏȓ$ᴵЃ.E("簃쀺炥৵╄ﱊ疠ԅⰈ༪瑊ᬬ縌洃絳".toCharArray(), (short)18832, (short)3, (short)4).intern().equals(str)) {
            if ((paramʾ.ᕁ & 0x2) == 0) {
              int i10 = i;
              int i11 = ᴵʖ(i10);
              i10 += 2;
              while (i11-- > 0) {
                int i12 = ᴵʖ(i10);
                int i13 = ᴵʖ(i10 + 2);
                i10 += 4;
                ᐨẏ(i12, (ᔪ[])ˏɪ2);
                ˏɪ2[i12].ʿᵉ(i13);
              } 
            } 
          } else {
            "?迶⌈࣬㓥麑톃看賫㚴頋鞦̟ų람⌟連?ꙹᜥꛄ攟飓ᒛ泭䬀܌㼢".toCharArray()[28] = (char)("?迶⌈࣬㓥麑톃看賫㚴頋鞦̟ų람⌟連?ꙹᜥꛄ攟飓ᒛ泭䬀܌㼢".toCharArray()[28] ^ 0x41EE);
            if (ˏȓ$ᴵЃ.E("?迶⌈࣬㓥麑톃看賫㚴頋鞦̟ų람⌟連?ꙹᜥꛄ攟飓ᒛ泭䬀܌㼢".toCharArray(), (short)13420, (short)2, (short)0).intern().equals(str)) {
              arrayOfInt1 = ᐨẏ(paramˉｓ, paramʾ, i, true);
            } else {
              "꿒?禋ﮋ쮀毖艹?繪䷫톱ᥗꑁ썟⋷᷶浉拡湟䚕ۈ筹ꃗ⪬춠ꐢ秇".toCharArray()[9] = (char)("꿒?禋ﮋ쮀毖艹?繪䷫톱ᥗꑁ썟⋷᷶浉拡湟䚕ۈ筹ꃗ⪬춠ꐢ秇".toCharArray()[9] ^ 0x4B9C);
              if (ˏȓ$ᴵЃ.E("꿒?禋ﮋ쮀毖艹?繪䷫톱ᥗꑁ썟⋷᷶浉拡湟䚕ۈ筹ꃗ⪬춠ꐢ秇".toCharArray(), (short)21376, (short)0, (short)3).intern().equals(str)) {
                arrayOfInt2 = ᐨẏ(paramˉｓ, paramʾ, i, false);
              } else {
                "톛㗷쾌伳즴⾴磶暆쩽ຩꤺ뮳˚".toCharArray()[8] = (char)("톛㗷쾌伳즴⾴磶暆쩽ຩꤺ뮳˚".toCharArray()[8] ^ 0x40E4);
                if (ˏȓ$ᴵЃ.E("톛㗷쾌伳즴⾴磶暆쩽ຩꤺ뮳˚".toCharArray(), (short)24591, (short)0, (short)0).intern().equals(str)) {
                  if ((paramʾ.ᕁ & 0x4) == 0) {
                    i3 = i + 2;
                    i4 = i + i9;
                  } 
                } else {
                  "쬝ᦑಪꍿ媬钨峯㗜".toCharArray()[6] = (char)("쬝ᦑಪꍿ媬钨峯㗜".toCharArray()[6] ^ 0x185);
                  if (ˏȓ$ᴵЃ.E("쬝ᦑಪꍿ媬钨峯㗜".toCharArray(), (short)30012, (short)0, (short)1).equals(str)) {
                    if ((paramʾ.ᕁ & 0x4) == 0) {
                      i3 = i + 2;
                      i4 = i + i9;
                      bool1 = false;
                    } 
                  } else {
                    ᴵʖ ᴵʖ1;
                    (ᴵʖ1 = ᐨẏ((ᴵʖ[])paramʾ.ˊ, str, i, i9, (char[])ˏɪ1, paramInt, (ᔪ[])ˏɪ2)).ᐨẏ = ᴵʖ;
                    ᴵʖ = ᴵʖ1;
                  } 
                } 
              } 
            } 
          } 
        } 
      } 
    } 
    boolean bool2 = ((paramʾ.ᕁ & 0x8) != 0) ? true : false;
    if (i3 != 0) {
      paramʾ.ʽו = -1;
      paramʾ.ﹳه = 0;
      paramʾ.ᐧǏ = 0;
      paramʾ.ιՆ = 0;
      paramʾ.ˊ = new Object[k];
      paramʾ.וּ = 0;
      paramʾ.ᴵʖ = new Object[j];
      if (bool2)
        ᐨẏ(paramʾ); 
      for (int i9 = i3; i9 < i4 - 2; i9++) {
        int i10;
        if (arrayOfByte[i9] == 8 && (i10 = ᴵʖ(i9 + 1)) >= 0 && i10 < m && (arrayOfByte[n + i10] & 0xFF) == 187)
          ˊ(i10, (ᔪ[])ˏɪ2); 
      } 
    } 
    if (bool2 && (paramʾ.ᕁ & 0x100) != 0)
      paramˉｓ.ᐨẏ(-1, k, (Object[])null, 0, (Object[])null); 
    byte b1 = 0;
    int i7 = ᐨẏ(arrayOfInt1, 0);
    byte b2 = 0;
    int i8 = ᐨẏ(arrayOfInt2, 0);
    boolean bool3 = false;
    paramInt = ((paramʾ.ᕁ & 0x100) == 0) ? 33 : 0;
    i = n;
    while (i < i1) {
      Object[] arrayOfObject;
      ˏɪ ˏɪ4;
      ʾܪ ʾܪ1;
      int i10;
      ʾܪ ʾܪ2;
      int i11;
      int[] arrayOfInt;
      String str1;
      ᔪ[] arrayOfᔪ;
      String str2;
      byte b;
      String str3;
      int i12;
      ʹō ʹō;
      i6 = i - n;
      ˏɪ ˏɪ3;
      if ((ˏɪ3 = ˏɪ2[i6]) != null)
        ˏɪ3.ᐨẏ(paramˉｓ, ((paramʾ.ᕁ & 0x2) == 0)); 
      while (i3 != 0 && (paramʾ.ʽו == i6 || paramʾ.ʽו == -1)) {
        if (paramʾ.ʽו != -1) {
          if (!bool1 || bool2) {
            paramˉｓ.ᐨẏ(-1, paramʾ.ᐧǏ, paramʾ.ˊ, paramʾ.וּ, paramʾ.ᴵʖ);
          } else {
            paramˉｓ.ᐨẏ(paramʾ.ﹳه, paramʾ.ιՆ, paramʾ.ˊ, paramʾ.וּ, paramʾ.ᴵʖ);
          } 
          bool3 = false;
        } 
        if (i3 < i4) {
          i3 = ᐨẏ(i3, bool1, bool2, paramʾ);
          continue;
        } 
        i3 = 0;
      } 
      if (bool3) {
        if ((paramʾ.ᕁ & 0x8) != 0)
          paramˉｓ.ᐨẏ(256, 0, (Object[])null, 0, (Object[])null); 
        bool3 = false;
      } 
      int i9;
      switch (i9 = arrayOfByte[i] & 0xFF) {
        case 0:
        case 1:
        case 2:
        case 3:
        case 4:
        case 5:
        case 6:
        case 7:
        case 8:
        case 9:
        case 10:
        case 11:
        case 12:
        case 13:
        case 14:
        case 15:
        case 46:
        case 47:
        case 48:
        case 49:
        case 50:
        case 51:
        case 52:
        case 53:
        case 79:
        case 80:
        case 81:
        case 82:
        case 83:
        case 84:
        case 85:
        case 86:
        case 87:
        case 88:
        case 89:
        case 90:
        case 91:
        case 92:
        case 93:
        case 94:
        case 95:
        case 96:
        case 97:
        case 98:
        case 99:
        case 100:
        case 101:
        case 102:
        case 103:
        case 104:
        case 105:
        case 106:
        case 107:
        case 108:
        case 109:
        case 110:
        case 111:
        case 112:
        case 113:
        case 114:
        case 115:
        case 116:
        case 117:
        case 118:
        case 119:
        case 120:
        case 121:
        case 122:
        case 123:
        case 124:
        case 125:
        case 126:
        case 127:
        case 128:
        case 129:
        case 130:
        case 131:
        case 133:
        case 134:
        case 135:
        case 136:
        case 137:
        case 138:
        case 139:
        case 140:
        case 141:
        case 142:
        case 143:
        case 144:
        case 145:
        case 146:
        case 147:
        case 148:
        case 149:
        case 150:
        case 151:
        case 152:
        case 172:
        case 173:
        case 174:
        case 175:
        case 176:
        case 177:
        case 190:
        case 191:
        case 194:
        case 195:
          paramˉｓ.ʹﮃ(i9);
          i++;
          break;
        case 26:
        case 27:
        case 28:
        case 29:
        case 30:
        case 31:
        case 32:
        case 33:
        case 34:
        case 35:
        case 36:
        case 37:
        case 38:
        case 39:
        case 40:
        case 41:
        case 42:
        case 43:
        case 44:
        case 45:
          i9 -= 26;
          paramˉｓ.ᴵʖ(21 + (i9 >> 2), i9 & 0x3);
          i++;
          break;
        case 59:
        case 60:
        case 61:
        case 62:
        case 63:
        case 64:
        case 65:
        case 66:
        case 67:
        case 68:
        case 69:
        case 70:
        case 71:
        case 72:
        case 73:
        case 74:
        case 75:
        case 76:
        case 77:
        case 78:
          i9 -= 59;
          paramˉｓ.ᴵʖ(54 + (i9 >> 2), i9 & 0x3);
          i++;
          break;
        case 153:
        case 154:
        case 155:
        case 156:
        case 157:
        case 158:
        case 159:
        case 160:
        case 161:
        case 162:
        case 163:
        case 164:
        case 165:
        case 166:
        case 167:
        case 168:
        case 198:
        case 199:
          paramˉｓ.ᐨẏ(i9, (ᔪ)ˏɪ2[i6 + ᐨẏ(i + 1)]);
          i += 3;
          break;
        case 200:
        case 201:
          paramˉｓ.ᐨẏ(i9 - paramInt, (ᔪ)ˏɪ2[i6 + ﾞл(i + 1)]);
          i += 5;
          break;
        case 202:
        case 203:
        case 204:
        case 205:
        case 206:
        case 207:
        case 208:
        case 209:
        case 210:
        case 211:
        case 212:
        case 213:
        case 214:
        case 215:
        case 216:
        case 217:
        case 218:
        case 219:
          i9 = (i9 < 218) ? (i9 - 49) : (i9 - 20);
          ˏɪ4 = ˏɪ2[i6 + ᴵʖ(i + 1)];
          if (i9 == 167 || i9 == 168) {
            paramˉｓ.ᐨẏ(i9 + 33, (ᔪ)ˏɪ4);
          } else {
            i9 = (i9 < 167) ? ((i9 + 1 ^ 0x1) - 1) : (i9 ^ 0x1);
            ᔪ ᔪ = ˊ(i6 + 3, (ᔪ[])ˏɪ2);
            paramˉｓ.ᐨẏ(i9, ᔪ);
            paramˉｓ.ᐨẏ(200, (ᔪ)ˏɪ4);
            bool3 = true;
          } 
          i += 3;
          break;
        case 220:
          paramˉｓ.ᐨẏ(200, (ᔪ)ˏɪ2[i6 + ﾞл(i + 1)]);
          bool3 = true;
          i += 5;
          break;
        case 196:
          if ((i9 = arrayOfByte[i + 1] & 0xFF) == 132) {
            paramˉｓ.ﾞл(ᴵʖ(i + 2), ᐨẏ(i + 4));
            i += 6;
            break;
          } 
          paramˉｓ.ᴵʖ(i9, ᴵʖ(i + 2));
          i += 4;
          break;
        case 170:
          i += 4 - (i6 & 0x3);
          ˏɪ4 = ˏɪ2[i6 + ﾞл(i)];
          i10 = ﾞл(i + 4);
          i11 = ﾞл(i + 8);
          i += 12;
          arrayOfᔪ = new ᔪ[i11 - i10 + 1];
          for (b = 0; b < arrayOfᔪ.length; b++) {
            arrayOfᔪ[b] = (ᔪ)ˏɪ2[i6 + ﾞл(i)];
            i += 4;
          } 
          paramˉｓ.ᐨẏ(i10, i11, (ᔪ)ˏɪ4, arrayOfᔪ);
          break;
        case 171:
          i += 4 - (i6 & 0x3);
          ˏɪ4 = ˏɪ2[i6 + ﾞл(i)];
          i10 = ﾞл(i + 4);
          i += 8;
          arrayOfInt = new int[i10];
          arrayOfᔪ = new ᔪ[i10];
          for (b = 0; b < i10; b++) {
            arrayOfInt[b] = ﾞл(i);
            arrayOfᔪ[b] = (ᔪ)ˏɪ2[i6 + ﾞл(i + 4)];
            i += 8;
          } 
          paramˉｓ.ᐨẏ((ᔪ)ˏɪ4, arrayOfInt, arrayOfᔪ);
          break;
        case 21:
        case 22:
        case 23:
        case 24:
        case 25:
        case 54:
        case 55:
        case 56:
        case 57:
        case 58:
        case 169:
          paramˉｓ.ᴵʖ(i9, arrayOfByte[i + 1] & 0xFF);
          i += 2;
          break;
        case 16:
        case 188:
          paramˉｓ.ˊ(i9, arrayOfByte[i + 1]);
          i += 2;
          break;
        case 17:
          paramˉｓ.ˊ(i9, ᐨẏ(i + 1));
          i += 3;
          break;
        case 18:
          paramˉｓ.ˊ(ᐨẏ(arrayOfByte[i + 1] & 0xFF, (char[])ˏɪ1));
          i += 2;
          break;
        case 19:
        case 20:
          paramˉｓ.ˊ(ᐨẏ(ᴵʖ(i + 1), (char[])ˏɪ1));
          i += 3;
          break;
        case 178:
        case 179:
        case 180:
        case 181:
        case 182:
        case 183:
        case 184:
        case 185:
          ʾܪ1 = this.ᐨẏ[ᴵʖ(i + 1)];
          ʾܪ2 = this.ᐨẏ[ᴵʖ(ʾܪ1 + 2)];
          str1 = ﾞл(ʾܪ1, (char[])ˏɪ1);
          str2 = ᐨẏ(ʾܪ2, (char[])ˏɪ1);
          str3 = ᐨẏ(ʾܪ2 + 2, (char[])ˏɪ1);
          if (i9 < 182) {
            paramˉｓ.ᐨẏ(i9, str1, str2, str3);
          } else {
            boolean bool = (arrayOfByte[ʾܪ1 - 1] == 11) ? true : false;
            paramˉｓ.ᐨẏ(i9, str1, str2, str3, bool);
          } 
          if (i9 == 185) {
            i += 5;
            break;
          } 
          i += 3;
          break;
        case 186:
          ʾܪ1 = this.ᐨẏ[ᴵʖ(i + 1)];
          ʾܪ2 = this.ᐨẏ[ᴵʖ(ʾܪ1 + 2)];
          str1 = ᐨẏ(ʾܪ2, (char[])ˏɪ1);
          str2 = ᐨẏ(ʾܪ2 + 2, (char[])ˏɪ1);
          i12 = this.ˊ[ᴵʖ(ʾܪ1)];
          ʹō = (ʹō)ᐨẏ(ᴵʖ(i12), (char[])ˏɪ1);
          arrayOfObject = new Object[ᴵʖ(i12 + 2)];
          i12 += 4;
          for (i9 = 0; i9 < arrayOfObject.length; i9++) {
            arrayOfObject[i9] = ᐨẏ(ᴵʖ(i12), (char[])ˏɪ1);
            i12 += 2;
          } 
          paramˉｓ.ᐨẏ(str1, str2, ʹō, arrayOfObject);
          i += 5;
          break;
        case 187:
        case 189:
        case 192:
        case 193:
          paramˉｓ.ᐨẏ(i9, ﾞл(i + 1, (char[])ˏɪ1));
          i += 3;
          break;
        case 132:
          paramˉｓ.ﾞл(arrayOfByte[i + 1] & 0xFF, arrayOfByte[i + 2]);
          i += 3;
          break;
        case 197:
          paramˉｓ.ˊ(ﾞл(i + 1, (char[])ˏɪ1), arrayOfByte[i + 3] & 0xFF);
          i += 4;
          break;
        default:
          throw new AssertionError();
      } 
      while (arrayOfInt1 != null && b1 < arrayOfInt1.length && i7 <= i6) {
        if (i7 == i6) {
          int i13 = ᐨẏ(paramʾ, arrayOfInt1[b1]);
          String str = ᐨẏ(i13, (char[])ˏɪ1);
          i13 += 2;
          ᐨẏ(paramˉｓ.ˊ(paramʾ.ιƚ, paramʾ.ᐨẏ, str, true), i13, true, (char[])ˏɪ1);
        } 
        i7 = ᐨẏ(arrayOfInt1, ++b1);
      } 
      while (arrayOfInt2 != null && b2 < arrayOfInt2.length && i8 <= i6) {
        if (i8 == i6) {
          int i13 = ᐨẏ(paramʾ, arrayOfInt2[b2]);
          String str = ᐨẏ(i13, (char[])ˏɪ1);
          i13 += 2;
          ᐨẏ(paramˉｓ.ˊ(paramʾ.ιƚ, paramʾ.ᐨẏ, str, false), i13, true, (char[])ˏɪ1);
        } 
        i8 = ᐨẏ(arrayOfInt2, ++b2);
      } 
    } 
    if (ˏɪ2[m] != null)
      paramˉｓ.ˊ((ᔪ)ˏɪ2[m]); 
    if (i5 != 0 && (paramʾ.ᕁ & 0x2) == 0) {
      int[] arrayOfInt = null;
      if (i2 != 0) {
        arrayOfInt = new int[ᴵʖ(i2) * 3];
        i = i2 + 2;
        int i10 = arrayOfInt.length;
        while (i10 > 0) {
          arrayOfInt[--i10] = i + 6;
          arrayOfInt[--i10] = ᴵʖ(i + 8);
          arrayOfInt[--i10] = ᴵʖ(i);
          i += 10;
        } 
      } 
      int i9 = ᴵʖ(i5);
      i = i5 + 2;
      while (i9-- > 0) {
        int i10 = ᴵʖ(i);
        int i11 = ᴵʖ(i + 2);
        String str1 = ᐨẏ(i + 4, (char[])ˏɪ1);
        String str2 = ᐨẏ(i + 6, (char[])ˏɪ1);
        int i12 = ᴵʖ(i + 8);
        i += 10;
        String str3 = null;
        if (arrayOfInt != null)
          for (byte b = 0; b < arrayOfInt.length; b += 3) {
            if (arrayOfInt[b] == i10 && arrayOfInt[b + 1] == i12) {
              str3 = ᐨẏ(arrayOfInt[b + 2], (char[])ˏɪ1);
              break;
            } 
          }  
        paramˉｓ.ᐨẏ(str1, str2, str3, (ᔪ)ˏɪ2[i10], (ᔪ)ˏɪ2[i10 + i11], i12);
      } 
    } 
    if (arrayOfInt1 != null) {
      int[] arrayOfInt;
      int i9 = (arrayOfInt = arrayOfInt1).length;
      for (byte b = 0; b < i9; b++) {
        int i10 = arrayOfInt[b];
        int i11;
        if ((i11 = ˊ(i10)) == 64 || i11 == 65) {
          i = ᐨẏ(paramʾ, i10);
          String str = ᐨẏ(i, (char[])ˏɪ1);
          i += 2;
          ᐨẏ(paramˉｓ.ᐨẏ(paramʾ.ιƚ, paramʾ.ᐨẏ, (ᔪ[])paramʾ.ˊ, (ᔪ[])paramʾ.ᴵʖ, paramʾ.ﾞл, str, true), i, true, (char[])ˏɪ1);
        } 
      } 
    } 
    if (arrayOfInt2 != null) {
      int[] arrayOfInt;
      int i9 = (arrayOfInt = arrayOfInt2).length;
      for (byte b = 0; b < i9; b++) {
        int i10 = arrayOfInt[b];
        int i11;
        if ((i11 = ˊ(i10)) == 64 || i11 == 65) {
          i = ᐨẏ(paramʾ, i10);
          String str = ᐨẏ(i, (char[])ˏɪ1);
          i += 2;
          ᐨẏ(paramˉｓ.ᐨẏ(paramʾ.ιƚ, paramʾ.ᐨẏ, (ᔪ[])paramʾ.ˊ, (ᔪ[])paramʾ.ᴵʖ, paramʾ.ﾞл, str, false), i, true, (char[])ˏɪ1);
        } 
      } 
    } 
    while (ᴵʖ != null) {
      ᴵʖ ᴵʖ1 = ᴵʖ.ᐨẏ;
      ᴵʖ.ᐨẏ = null;
      paramˉｓ.ᴵʖ(ᴵʖ);
      ᴵʖ = ᴵʖ1;
    } 
    paramˉｓ.ʿᵉ(j, k);
  }
  
  private static void ˊ() {}
  
  private static ᔪ ᐨẏ(int paramInt, ᔪ[] paramArrayOfᔪ) {
    if (paramArrayOfᔪ[paramInt] == null)
      paramArrayOfᔪ[paramInt] = new ᔪ(); 
    return paramArrayOfᔪ[paramInt];
  }
  
  private ᔪ ˊ(int paramInt, ᔪ[] paramArrayOfᔪ) {
    ᔪ ᔪ1;
    (ᔪ1 = ᐨẏ(paramInt, paramArrayOfᔪ)).ᴵʖ = (short)((ᔪ1 = ᐨẏ(paramInt, paramArrayOfᔪ)).ᴵʖ & 0xFFFFFFFE);
    return ᔪ1;
  }
  
  private void ᐨẏ(int paramInt, ᔪ[] paramArrayOfᔪ) {
    if (paramArrayOfᔪ[paramInt] == null)
      (ᐨẏ(paramInt, paramArrayOfᔪ)).ᴵʖ = (short)((ᐨẏ(paramInt, paramArrayOfᔪ)).ᴵʖ | 0x1); 
  }
  
  private int[] ᐨẏ(ˉｓ paramˉｓ, ʾ paramʾ, int paramInt, boolean paramBoolean) {
    ˏɪ ˏɪ = paramʾ.ᐨẏ;
    paramInt = paramInt;
    int[] arrayOfInt = new int[ᴵʖ(paramInt)];
    paramInt += 2;
    for (byte b = 0; b < arrayOfInt.length; b++) {
      arrayOfInt[b] = paramInt;
      int i;
      switch ((i = ﾞл(paramInt)) >>> 24) {
        case 64:
        case 65:
          j = ᴵʖ(paramInt + 1);
          paramInt += 3;
          while (j-- > 0) {
            int k = ᴵʖ(paramInt);
            int m = ᴵʖ(paramInt + 2);
            paramInt += 6;
            ˊ(k, (ᔪ[])paramʾ.ᐨẏ);
            ˊ(k + m, (ᔪ[])paramʾ.ᐨẏ);
          } 
          break;
        case 71:
        case 72:
        case 73:
        case 74:
        case 75:
          paramInt += 4;
          break;
        case 16:
        case 17:
        case 18:
        case 23:
        case 66:
        case 67:
        case 68:
        case 69:
        case 70:
          paramInt += 3;
          break;
        default:
          throw new IllegalArgumentException();
      } 
      int j = ˊ(paramInt);
      if (i >>> 24 == 66) {
        ˏɪ ˏɪ1 = (j == 0) ? null : new ˏɪ(this.ﾞл, paramInt);
        paramInt += 1 + 2 * j;
        String str = ᐨẏ(paramInt, (char[])ˏɪ);
        paramInt += 2;
        paramInt = ᐨẏ(paramˉｓ.ᴵʖ(i & 0xFFFFFF00, ˏɪ1, str, paramBoolean), paramInt, true, (char[])ˏɪ);
      } else {
        paramInt += 3 + 2 * j;
        paramInt = ᐨẏ((ᐨẏ)null, paramInt, true, (char[])ˏɪ);
      } 
    } 
    return arrayOfInt;
  }
  
  private int ᐨẏ(int[] paramArrayOfint, int paramInt) {
    return (paramArrayOfint == null || paramInt >= paramArrayOfint.length || ˊ(paramArrayOfint[paramInt]) < 67) ? -1 : ᴵʖ(paramArrayOfint[paramInt] + 1);
  }
  
  private int ᐨẏ(ʾ paramʾ, int paramInt) {
    byte b;
    int i = paramInt;
    switch ((paramInt = ﾞл(paramInt)) >>> 24) {
      case 0:
      case 1:
      case 22:
        paramInt &= 0xFFFF0000;
        i += 2;
        break;
      case 19:
      case 20:
      case 21:
        paramInt &= 0xFF000000;
        i++;
        break;
      case 64:
      case 65:
        paramInt &= 0xFF000000;
        j = ᴵʖ(i + 1);
        i += 3;
        paramʾ.ˊ = (Object[])new ᔪ[j];
        paramʾ.ᴵʖ = (Object[])new ᔪ[j];
        paramʾ.ﾞл = new int[j];
        for (b = 0; b < j; b++) {
          int k = ᴵʖ(i);
          int m = ᴵʖ(i + 2);
          int n = ᴵʖ(i + 4);
          i += 6;
          paramʾ.ˊ[b] = ˊ(k, (ᔪ[])paramʾ.ᐨẏ);
          paramʾ.ᴵʖ[b] = ˊ(k + m, (ᔪ[])paramʾ.ᐨẏ);
          paramʾ.ﾞл[b] = n;
        } 
        break;
      case 71:
      case 72:
      case 73:
      case 74:
      case 75:
        paramInt &= 0xFF0000FF;
        i += 4;
        break;
      case 16:
      case 17:
      case 18:
      case 23:
      case 66:
        paramInt &= 0xFFFFFF00;
        i += 3;
        break;
      case 67:
      case 68:
      case 69:
      case 70:
        paramInt &= 0xFF000000;
        i += 3;
        break;
      default:
        throw new IllegalArgumentException();
    } 
    paramʾ.ιƚ = paramInt;
    int j = ˊ(i);
    paramʾ.ᐨẏ = (j == 0) ? null : new ˏɪ(this.ﾞл, i);
    return i + 1 + 2 * j;
  }
  
  private void ᐨẏ(ˉｓ paramˉｓ, ʾ paramʾ, int paramInt, boolean paramBoolean) {
    paramInt = paramInt;
    int i = this.ﾞл[paramInt++] & 0xFF;
    paramˉｓ.ᐨẏ(i, paramBoolean);
    ˏɪ ˏɪ = paramʾ.ᐨẏ;
    for (byte b = 0; b < i; b++) {
      int j = ᴵʖ(paramInt);
      for (paramInt += 2; j-- > 0; paramInt = ᐨẏ(paramˉｓ.ᐨẏ(b, str, paramBoolean), paramInt, true, (char[])ˏɪ)) {
        String str = ᐨẏ(paramInt, (char[])ˏɪ);
        paramInt += 2;
      } 
    } 
  }
  
  private int ᐨẏ(ᐨẏ paramᐨẏ, int paramInt, boolean paramBoolean, char[] paramArrayOfchar) {
    paramInt = paramInt;
    int i = ᴵʖ(paramInt);
    paramInt += 2;
    if (paramBoolean) {
      while (i-- > 0) {
        String str = ᐨẏ(paramInt, paramArrayOfchar);
        paramInt = ᐨẏ(paramᐨẏ, paramInt + 2, str, paramArrayOfchar);
      } 
    } else {
      while (i-- > 0)
        paramInt = ᐨẏ(paramᐨẏ, paramInt, (String)null, paramArrayOfchar); 
    } 
    if (paramᐨẏ != null)
      paramᐨẏ.ᐨẏ(); 
    return paramInt;
  }
  
  private int ᐨẏ(ᐨẏ paramᐨẏ, int paramInt, String paramString, char[] paramArrayOfchar) {
    byte[] arrayOfByte;
    byte b4;
    short[] arrayOfShort;
    byte b3;
    int[] arrayOfInt;
    byte b2;
    float[] arrayOfFloat;
    byte b1;
    int i;
    byte b8;
    boolean[] arrayOfBoolean;
    byte b7;
    char[] arrayOfChar;
    byte b6;
    long[] arrayOfLong;
    byte b5;
    double[] arrayOfDouble;
    paramInt = paramInt;
    if (paramᐨẏ == null) {
      switch (this.ﾞл[paramInt] & 0xFF) {
        case 101:
          return paramInt + 5;
        case 64:
          return ᐨẏ((ᐨẏ)null, paramInt + 3, true, paramArrayOfchar);
        case 91:
          return ᐨẏ((ᐨẏ)null, paramInt + 1, false, paramArrayOfchar);
      } 
      return paramInt + 3;
    } 
    switch (this.ﾞл[paramInt++] & 0xFF) {
      case 66:
        paramᐨẏ.ᐨẏ(paramString, Byte.valueOf((byte)ﾞл(this.ᐨẏ[ᴵʖ(paramInt)])));
        paramInt += 2;
        return paramInt;
      case 67:
        paramᐨẏ.ᐨẏ(paramString, Character.valueOf((char)ﾞл(this.ᐨẏ[ᴵʖ(paramInt)])));
        paramInt += 2;
        return paramInt;
      case 68:
      case 70:
      case 73:
      case 74:
        paramᐨẏ.ᐨẏ(paramString, ᐨẏ(ᴵʖ(paramInt), paramArrayOfchar));
        paramInt += 2;
        return paramInt;
      case 83:
        paramᐨẏ.ᐨẏ(paramString, Short.valueOf((short)ﾞл(this.ᐨẏ[ᴵʖ(paramInt)])));
        paramInt += 2;
        return paramInt;
      case 90:
        paramᐨẏ.ᐨẏ(paramString, (ﾞл(this.ᐨẏ[ᴵʖ(paramInt)]) == 0) ? Boolean.FALSE : Boolean.TRUE);
        paramInt += 2;
        return paramInt;
      case 115:
        paramᐨẏ.ᐨẏ(paramString, ᐨẏ(paramInt, paramArrayOfchar));
        paramInt += 2;
        return paramInt;
      case 101:
        paramᐨẏ.ᐨẏ(paramString, ᐨẏ(paramInt, paramArrayOfchar), ᐨẏ(paramInt + 2, paramArrayOfchar));
        paramInt += 4;
        return paramInt;
      case 99:
        paramᐨẏ.ᐨẏ(paramString, ˑܘ.ᐨẏ(ᐨẏ(paramInt, paramArrayOfchar)));
        paramInt += 2;
        return paramInt;
      case 64:
        return ᐨẏ(paramᐨẏ.ᐨẏ(paramString, ᐨẏ(paramInt, paramArrayOfchar)), paramInt + 2, true, paramArrayOfchar);
      case 91:
        i = ᴵʖ(paramInt);
        paramInt += 2;
        if (i == 0)
          return ᐨẏ(paramᐨẏ.ᐨẏ(paramString), paramInt - 2, false, paramArrayOfchar); 
        switch (this.ﾞл[paramInt] & 0xFF) {
          case 66:
            arrayOfByte = new byte[i];
            for (b8 = 0; b8 < i; b8++) {
              arrayOfByte[b8] = (byte)ﾞл(this.ᐨẏ[ᴵʖ(paramInt + 1)]);
              paramInt += 3;
            } 
            paramᐨẏ.ᐨẏ(paramString, arrayOfByte);
            return paramInt;
          case 90:
            arrayOfBoolean = new boolean[i];
            for (b4 = 0; b4 < i; b4++) {
              arrayOfBoolean[b4] = (ﾞл(this.ᐨẏ[ᴵʖ(paramInt + 1)]) != 0);
              paramInt += 3;
            } 
            paramᐨẏ.ᐨẏ(paramString, arrayOfBoolean);
            return paramInt;
          case 83:
            arrayOfShort = new short[i];
            for (b7 = 0; b7 < i; b7++) {
              arrayOfShort[b7] = (short)ﾞл(this.ᐨẏ[ᴵʖ(paramInt + 1)]);
              paramInt += 3;
            } 
            paramᐨẏ.ᐨẏ(paramString, arrayOfShort);
            return paramInt;
          case 67:
            arrayOfChar = new char[i];
            for (b3 = 0; b3 < i; b3++) {
              arrayOfChar[b3] = (char)ﾞл(this.ᐨẏ[ᴵʖ(paramInt + 1)]);
              paramInt += 3;
            } 
            paramᐨẏ.ᐨẏ(paramString, arrayOfChar);
            return paramInt;
          case 73:
            arrayOfInt = new int[i];
            for (b6 = 0; b6 < i; b6++) {
              arrayOfInt[b6] = ﾞл(this.ᐨẏ[ᴵʖ(paramInt + 1)]);
              paramInt += 3;
            } 
            paramᐨẏ.ᐨẏ(paramString, arrayOfInt);
            return paramInt;
          case 74:
            arrayOfLong = new long[i];
            for (b2 = 0; b2 < i; b2++) {
              arrayOfLong[b2] = ᐨẏ(this.ᐨẏ[ᴵʖ(paramInt + 1)]);
              paramInt += 3;
            } 
            paramᐨẏ.ᐨẏ(paramString, arrayOfLong);
            return paramInt;
          case 70:
            arrayOfFloat = new float[i];
            for (b5 = 0; b5 < i; b5++) {
              arrayOfFloat[b5] = Float.intBitsToFloat(ﾞл(this.ᐨẏ[ᴵʖ(paramInt + 1)]));
              paramInt += 3;
            } 
            paramᐨẏ.ᐨẏ(paramString, arrayOfFloat);
            return paramInt;
          case 68:
            arrayOfDouble = new double[i];
            for (b1 = 0; b1 < i; b1++) {
              arrayOfDouble[b1] = Double.longBitsToDouble(ᐨẏ(this.ᐨẏ[ᴵʖ(paramInt + 1)]));
              paramInt += 3;
            } 
            paramᐨẏ.ᐨẏ(paramString, arrayOfDouble);
            return paramInt;
        } 
        return ᐨẏ(paramᐨẏ.ᐨẏ(paramString), paramInt - 2, false, b1);
    } 
    throw new IllegalArgumentException();
  }
  
  private void ᐨẏ(ʾ paramʾ) {
    String str = paramʾ.ιˠ;
    Object[] arrayOfObject = paramʾ.ˊ;
    byte b1 = 0;
    if ((paramʾ.ιᒶ & 0x8) == 0) {
      "乾ꓣ㙣㉐?꘠桳".toCharArray()[5] = (char)("乾ꓣ㙣㉐?꘠桳".toCharArray()[5] ^ 0x1551);
      if (ᐝᵣ$ﾞﾇ.j("乾ꓣ㙣㉐?꘠桳".toCharArray(), (short)29647, 1, (short)3).equals(paramʾ.ᐧפ)) {
        b1++;
        arrayOfObject[0] = ـﭔ.ՙᗮ;
      } else {
        b1++;
        arrayOfObject[0] = ﾞл(this.ٴӵ + 2, (char[])paramʾ.ᐨẏ);
      } 
    } 
    byte b2 = 1;
    while (true) {
      byte b = b2;
      switch (str.charAt(b2++)) {
        case 'B':
        case 'C':
        case 'I':
        case 'S':
        case 'Z':
          arrayOfObject[b1++] = ـﭔ.ˊ;
          continue;
        case 'F':
          arrayOfObject[b1++] = ـﭔ.ᴵʖ;
          continue;
        case 'J':
          arrayOfObject[b1++] = ـﭔ.ʿᵉ;
          continue;
        case 'D':
          arrayOfObject[b1++] = ـﭔ.ﾞл;
          continue;
        case '[':
          while (str.charAt(b2) == '[')
            b2++; 
          if (str.charAt(b2) == 'L')
            while (str.charAt(++b2) != ';')
              b2++;  
          arrayOfObject[b1++] = str.substring(b, ++b2);
          continue;
        case 'L':
          while (str.charAt(b2) != ';')
            b2++; 
          arrayOfObject[b1++] = str.substring(b + 1, b2++);
          continue;
      } 
      paramʾ.ᐧǏ = b1;
      return;
    } 
  }
  
  private int ᐨẏ(int paramInt, boolean paramBoolean1, boolean paramBoolean2, ʾ paramʾ) {
    char c;
    int i;
    paramInt = paramInt;
    ˏɪ ˏɪ1 = paramʾ.ᐨẏ;
    ˏɪ ˏɪ2 = paramʾ.ᐨẏ;
    if (paramBoolean1) {
      c = this.ﾞл[paramInt++] & 0xFF;
    } else {
      c = 'ÿ';
      paramʾ.ʽו = -1;
    } 
    paramʾ.ιՆ = 0;
    if (c < '@') {
      i = c;
      paramʾ.ﹳه = 3;
      paramʾ.וּ = 0;
    } else if (c < '') {
      i = c - 64;
      paramInt = ᐨẏ(paramInt, paramʾ.ᴵʖ, 0, (char[])ˏɪ1, (ᔪ[])ˏɪ2);
      paramʾ.ﹳه = 4;
      paramʾ.וּ = 1;
    } else if (c >= '÷') {
      i = ᴵʖ(paramInt);
      paramInt += 2;
      if (c == '÷') {
        paramInt = ᐨẏ(paramInt, paramʾ.ᴵʖ, 0, (char[])ˏɪ1, (ᔪ[])ˏɪ2);
        paramʾ.ﹳه = 4;
        paramʾ.וּ = 1;
      } else if (c >= 'ø' && c < 'û') {
        paramʾ.ﹳه = 2;
        paramʾ.ιՆ = 251 - c;
        paramʾ.ᐧǏ -= paramʾ.ιՆ;
        paramʾ.וּ = 0;
      } else if (c == 'û') {
        paramʾ.ﹳه = 3;
        paramʾ.וּ = 0;
      } else if (c < 'ÿ') {
        paramBoolean2 = paramBoolean2 ? paramʾ.ᐧǏ : false;
        for (int j = c - 251; j > 0; j--)
          paramInt = ᐨẏ(paramInt, paramʾ.ˊ, paramBoolean2++, (char[])ˏɪ1, (ᔪ[])ˏɪ2); 
        paramʾ.ﹳه = 1;
        paramʾ.ιՆ = c - 251;
        paramʾ.ᐧǏ += paramʾ.ιՆ;
        paramʾ.וּ = 0;
      } else {
        int j = ᴵʖ(paramInt);
        paramInt += 2;
        paramʾ.ﹳه = 0;
        paramʾ.ιՆ = j;
        paramʾ.ᐧǏ = j;
        int k;
        for (k = 0; k < j; k++)
          paramInt = ᐨẏ(paramInt, paramʾ.ˊ, k, (char[])ˏɪ1, (ᔪ[])ˏɪ2); 
        k = ᴵʖ(paramInt);
        paramInt += 2;
        paramʾ.וּ = k;
        for (c = Character.MIN_VALUE; c < k; c++)
          paramInt = ᐨẏ(paramInt, paramʾ.ᴵʖ, c, (char[])ˏɪ1, (ᔪ[])ˏɪ2); 
      } 
    } else {
      throw new IllegalArgumentException();
    } 
    paramʾ.ʽו += i + 1;
    ˊ(paramʾ.ʽו, (ᔪ[])ˏɪ2);
    return paramInt;
  }
  
  private int ᐨẏ(int paramInt1, Object[] paramArrayOfObject, int paramInt2, char[] paramArrayOfchar, ᔪ[] paramArrayOfᔪ) {
    paramInt1 = paramInt1;
    int i;
    switch (i = this.ﾞл[paramInt1++] & 0xFF) {
      case 0:
        paramArrayOfObject[paramInt2] = ـﭔ.ᐨẏ;
        return paramInt1;
      case 1:
        paramArrayOfObject[paramInt2] = ـﭔ.ˊ;
        return paramInt1;
      case 2:
        paramArrayOfObject[paramInt2] = ـﭔ.ᴵʖ;
        return paramInt1;
      case 3:
        paramArrayOfObject[paramInt2] = ـﭔ.ﾞл;
        return paramInt1;
      case 4:
        paramArrayOfObject[paramInt2] = ـﭔ.ʿᵉ;
        return paramInt1;
      case 5:
        paramArrayOfObject[paramInt2] = ـﭔ.ʹﮃ;
        return paramInt1;
      case 6:
        paramArrayOfObject[paramInt2] = ـﭔ.ՙᗮ;
        return paramInt1;
      case 7:
        paramArrayOfObject[paramInt2] = ﾞл(paramInt1, paramArrayOfchar);
        paramInt1 += 2;
        return paramInt1;
      case 8:
        paramArrayOfObject[paramInt2] = ˊ(ᴵʖ(paramInt1), paramArrayOfᔪ);
        paramInt1 += 2;
        return paramInt1;
    } 
    throw new IllegalArgumentException();
  }
  
  int ᴵʖ() {
    int i = this.ٴӵ + 8 + (ᴵʖ(this.ٴӵ + 6) << 1);
    int j = ᴵʖ(i);
    i += 2;
    while (j-- > 0) {
      int m = ᴵʖ(i + 6);
      for (i += 8; m-- > 0; i += 6 + ﾞл(i + 2));
    } 
    int k = ᴵʖ(i);
    i += 2;
    while (k-- > 0) {
      j = ᴵʖ(i + 6);
      for (i += 8; j-- > 0; i += 6 + ﾞл(i + 2));
    } 
    return i + 2;
  }
  
  private int[] ᐨẏ(int paramInt) {
    char[] arrayOfChar = new char[paramInt];
    int i = ᴵʖ();
    for (int j = ᴵʖ(i - 2); j > 0; j--) {
      String str = ᐨẏ(i, arrayOfChar);
      int k = ﾞл(i + 2);
      i += 6;
      "㋑뿶䶆坐狂헐ᜐ䆒裟ⶥ㯒컫?▕".toCharArray()[2] = (char)("㋑뿶䶆坐狂헐ᜐ䆒裟ⶥ㯒컫?▕".toCharArray()[2] ^ 0x4FA5);
      if (ᐝᵣ$ﾞﾇ.j("㋑뿶䶆坐狂헐ᜐ䆒裟ⶥ㯒컫?▕".toCharArray(), (short)17614, 2, (short)4).intern().equals(str)) {
        int[] arrayOfInt = new int[ᴵʖ(i)];
        i += 2;
        for (j = 0; j < arrayOfInt.length; j++) {
          arrayOfInt[j] = i;
          i += 4 + (ᴵʖ(i + 2) << 1);
        } 
        return arrayOfInt;
      } 
      i += k;
    } 
    throw new IllegalArgumentException();
  }
  
  private ᴵʖ ᐨẏ(ᴵʖ[] paramArrayOfᴵʖ, String paramString, int paramInt1, int paramInt2, char[] paramArrayOfchar, int paramInt3, ᔪ[] paramArrayOfᔪ) {
    paramInt3 = (paramArrayOfᴵʖ = paramArrayOfᴵʖ).length;
    for (byte b = 0; b < paramInt3; b++) {
      ᴵʖ ᴵʖ1;
      if ((ᴵʖ1 = paramArrayOfᴵʖ[b]).ᐨẏ.equals(paramString))
        return ᴵʖ1.ᐨẏ(this, paramInt1, paramInt2, paramArrayOfchar); 
    } 
    return (new ᴵʖ(paramString)).ᐨẏ(this, paramInt1, paramInt2, (char[])null);
  }
  
  public int ﾞл() {
    return this.ᐨẏ.length;
  }
  
  public int ᐨẏ(int paramInt) {
    return this.ᐨẏ[paramInt];
  }
  
  public int ʿᵉ() {
    return this.ᴵƚ;
  }
  
  public int ˊ(int paramInt) {
    return this.ﾞл[paramInt] & 0xFF;
  }
  
  public int ᴵʖ(int paramInt) {
    byte[] arrayOfByte;
    return ((arrayOfByte = this.ﾞл)[paramInt] & 0xFF) << 8 | arrayOfByte[paramInt + 1] & 0xFF;
  }
  
  public short ᐨẏ(int paramInt) {
    byte[] arrayOfByte;
    return (short)(((arrayOfByte = this.ﾞл)[paramInt] & 0xFF) << 8 | arrayOfByte[paramInt + 1] & 0xFF);
  }
  
  public int ﾞл(int paramInt) {
    byte[] arrayOfByte;
    return ((arrayOfByte = this.ﾞл)[paramInt] & 0xFF) << 24 | (arrayOfByte[paramInt + 1] & 0xFF) << 16 | (arrayOfByte[paramInt + 2] & 0xFF) << 8 | arrayOfByte[paramInt + 3] & 0xFF;
  }
  
  public long ᐨẏ(int paramInt) {
    long l1 = ﾞл(paramInt);
    long l2 = ﾞл(paramInt + 4) & 0xFFFFFFFFL;
    return l1 << 32L | l2;
  }
  
  public String ᐨẏ(int paramInt, char[] paramArrayOfchar) {
    int i = ᴵʖ(paramInt);
    return (paramInt == 0 || i == 0) ? null : ˊ(i, paramArrayOfchar);
  }
  
  String ˊ(int paramInt, char[] paramArrayOfchar) {
    ʾܪ ʾܪ1;
    if ((ʾܪ1 = this.ᐨẏ[paramInt]) != null)
      return (String)ʾܪ1; 
    ʾܪ1 = this.ᐨẏ[paramInt];
    this.ᐨẏ[paramInt] = (ʾܪ)ᐨẏ(ʾܪ1 + 2, ᴵʖ(ʾܪ1), paramArrayOfchar);
    return ᐨẏ(ʾܪ1 + 2, ᴵʖ(ʾܪ1), paramArrayOfchar);
  }
  
  private String ᐨẏ(int paramInt1, int paramInt2, char[] paramArrayOfchar) {
    paramInt2 = (paramInt1 = paramInt1) + paramInt2;
    byte b = 0;
    byte[] arrayOfByte = this.ﾞл;
    while (paramInt1 < paramInt2) {
      byte b1;
      if (((b1 = arrayOfByte[paramInt1++]) & 0x80) == 0) {
        paramArrayOfchar[b++] = (char)(b1 & Byte.MAX_VALUE);
        continue;
      } 
      if ((b1 & 0xE0) == 192) {
        paramArrayOfchar[b++] = (char)(((b1 & 0x1F) << 6) + (arrayOfByte[paramInt1++] & 0x3F));
        continue;
      } 
      paramArrayOfchar[b++] = (char)(((b1 & 0xF) << 12) + ((arrayOfByte[paramInt1++] & 0x3F) << 6) + (arrayOfByte[paramInt1++] & 0x3F));
    } 
    return new String(paramArrayOfchar, 0, b);
  }
  
  private String ᴵʖ(int paramInt, char[] paramArrayOfchar) {
    return ᐨẏ(this.ᐨẏ[ᴵʖ(paramInt)], paramArrayOfchar);
  }
  
  public String ﾞл(int paramInt, char[] paramArrayOfchar) {
    return ᴵʖ(paramInt, paramArrayOfchar);
  }
  
  public String ʿᵉ(int paramInt, char[] paramArrayOfchar) {
    return ᴵʖ(paramInt, paramArrayOfchar);
  }
  
  public String ʹﮃ(int paramInt, char[] paramArrayOfchar) {
    return ᴵʖ(paramInt, paramArrayOfchar);
  }
  
  private ʾܪ ᐨẏ(int paramInt, char[] paramArrayOfchar) {
    ʾܪ ʾܪ1;
    if ((ʾܪ1 = this.ᐨẏ[paramInt]) != null)
      return ʾܪ1; 
    ʾܪ1 = this.ᐨẏ[paramInt];
    ʾܪ ʾܪ2 = this.ᐨẏ[ᴵʖ(ʾܪ1 + 2)];
    String str2 = ᐨẏ(ʾܪ2, paramArrayOfchar);
    String str1 = ᐨẏ(ʾܪ2 + 2, paramArrayOfchar);
    int i = this.ˊ[ᴵʖ(ʾܪ1)];
    ʹō ʹō = (ʹō)ᐨẏ(ᴵʖ(i), paramArrayOfchar);
    Object[] arrayOfObject = new Object[ᴵʖ(i + 2)];
    i += 4;
    for (byte b = 0; b < arrayOfObject.length; b++) {
      arrayOfObject[b] = ᐨẏ(ᴵʖ(i), paramArrayOfchar);
      i += 2;
    } 
    this.ᐨẏ[paramInt] = new ʾܪ(str2, str1, ʹō, arrayOfObject);
    return new ʾܪ(str2, str1, ʹō, arrayOfObject);
  }
  
  public Object ᐨẏ(int paramInt, char[] paramArrayOfchar) {
    String str1;
    boolean bool;
    ʾܪ ʾܪ2;
    String str2;
    String str3;
    ʾܪ ʾܪ1 = this.ᐨẏ[paramInt];
    switch (this.ﾞл[ʾܪ1 - 1]) {
      case 3:
        return Integer.valueOf(ﾞл(ʾܪ1));
      case 4:
        return Float.valueOf(Float.intBitsToFloat(ﾞл(ʾܪ1)));
      case 5:
        return Long.valueOf(ᐨẏ(ʾܪ1));
      case 6:
        return Double.valueOf(Double.longBitsToDouble(ᐨẏ(ʾܪ1)));
      case 7:
        return ˑܘ.ˊ(ᐨẏ(ʾܪ1, paramArrayOfchar));
      case 8:
        return ᐨẏ(ʾܪ1, paramArrayOfchar);
      case 16:
        return ˑܘ.ᴵʖ(ᐨẏ(ʾܪ1, paramArrayOfchar));
      case 15:
        paramInt = ˊ(ʾܪ1);
        ʾܪ1 = this.ᐨẏ[ᴵʖ(ʾܪ1 + 1)];
        ʾܪ2 = this.ᐨẏ[ᴵʖ(ʾܪ1 + 2)];
        str2 = ﾞл(ʾܪ1, paramArrayOfchar);
        str3 = ᐨẏ(ʾܪ2, paramArrayOfchar);
        str1 = ᐨẏ(ʾܪ2 + 2, paramArrayOfchar);
        bool = (this.ﾞл[ʾܪ1 - 1] == 11) ? true : false;
        return new ʹō(paramInt, str2, str3, str1, bool);
      case 17:
        return ᐨẏ(paramInt, (char[])str1);
    } 
    throw new IllegalArgumentException();
  }
  
  static {
    "㱪㏿㚙콡슌闪?龙좆玃痯顋᚟憕".toCharArray()[1] = (char)("㱪㏿㚙콡슌闪?龙좆玃痯顋᚟憕".toCharArray()[1] ^ 0x48F8);
    ﾞл = (byte[])ᐨẏ$ᐝт.W("㱪㏿㚙콡슌闪?龙좆玃痯顋᚟憕".toCharArray(), (short)10669, (byte)5, (short)3).intern();
    "㩾傺是㻓嗗婖俱餎䪱媪琬ᯬ⍳퓎芫犼暞熈骼㐽".toCharArray()[10] = (char)("㩾傺是㻓嗗婖俱餎䪱媪琬ᯬ⍳퓎芫犼暞熈骼㐽".toCharArray()[10] ^ 0x9FF);
    ͺо = ᐨẏ$ᐝт.W("㩾傺是㻓嗗婖俱餎䪱媪琬ᯬ⍳퓎芫犼暞熈骼㐽".toCharArray(), (short)2648, (byte)0, (short)2).intern();
    "ᅾ揍覸ಘ\021㓕蜳制⟰娔殞蘧쉟⥕㉜ࠓ蟬獎⠏".toCharArray()[8] = (char)("ᅾ揍覸ಘ\021㓕蜳制⟰娔殞蘧쉟⥕㉜ࠓ蟬獎⠏".toCharArray()[8] ^ 0x387A);
    ᴵƚ = ᐨẏ$ᐝт.W("ᅾ揍覸ಘ\021㓕蜳制⟰娔殞蘧쉟⥕㉜ࠓ蟬獎⠏".toCharArray(), (short)20361, (byte)4, (short)0).intern();
    "ظ媁묫켖ꍼᑗ?ֆꜵٸ놣栄块Ŧ얽箞⥫".toCharArray()[8] = (char)("ظ媁묫켖ꍼᑗ?ֆꜵٸ놣栄块Ŧ얽箞⥫".toCharArray()[8] ^ 0x606E);
    ʻล = ᐨẏ$ᐝт.W("ظ媁묫켖ꍼᑗ?ֆꜵٸ놣栄块Ŧ얽箞⥫".toCharArray(), (short)11430, (byte)3, (short)1).intern();
    "中熂฻⒑혩טּﯾസ畷춟̵嶻ే졩丏⯯".toCharArray()[15] = (char)("中熂฻⒑혩טּﯾസ畷춟̵嶻ే졩丏⯯".toCharArray()[15] ^ 0x5BEA);
    ˈے = ᐨẏ$ᐝт.W("中熂฻⒑혩טּﯾസ畷춟̵嶻ే졩丏⯯".toCharArray(), (short)11110, (byte)1, (short)1).intern();
    "?옧娄犕횫壘떢嶉姺琔呟⻂".toCharArray()[8] = (char)("?옧娄犕횫壘떢嶉姺琔呟⻂".toCharArray()[8] ^ 0x4FBB);
    ιﾌ = ᐨẏ$ᐝт.W("?옧娄犕횫壘떢嶉姺琔呟⻂".toCharArray(), (short)27584, (byte)0, (short)1).intern();
    "䈎⋏阯⦼䯁⫅䂬〤꒫ㄭ≼䐛ꐣ礩釔ᐈ쯦⚳ᢻ벷䍔塢繯慫蕹ኬ᳟扺௲毛".toCharArray()[13] = (char)("䈎⋏阯⦼䯁⫅䂬〤꒫ㄭ≼䐛ꐣ礩釔ᐈ쯦⚳ᢻ벷䍔塢繯慫蕹ኬ᳟扺௲毛".toCharArray()[13] ^ 0x7BD);
    ʿপ = ᐨẏ$ᐝт.W("䈎⋏阯⦼䯁⫅䂬〤꒫ㄭ≼䐛ꐣ礩釔ᐈ쯦⚳ᢻ벷䍔塢繯慫蕹ኬ᳟扺௲毛".toCharArray(), (short)6603, (byte)0, (short)5).intern();
    "漌櫢〧⛹췾䥣㗁?䌳襃鄣ʶ鐋ᑠ?ᓈḷｂ摹দ␐ⶡ".toCharArray()[2] = (char)("漌櫢〧⛹췾䥣㗁?䌳襃鄣ʶ鐋ᑠ?ᓈḷｂ摹দ␐ⶡ".toCharArray()[2] ^ 0x23F7);
    ˌ = ᐨẏ$ᐝт.W("漌櫢〧⛹췾䥣㗁?䌳襃鄣ʶ鐋ᑠ?ᓈḷｂ摹দ␐ⶡ".toCharArray(), (short)5314, (byte)4, (short)0).intern();
    "⟇Ứ嘾咆齟蘽累ꀊచ푭镄⏨ꏘ⍄".toCharArray()[4] = (char)("⟇Ứ嘾咆齟蘽累ꀊచ푭镄⏨ꏘ⍄".toCharArray()[4] ^ 0x30BD);
    ﾞǰ = ᐨẏ$ᐝт.W("⟇Ứ嘾咆齟蘽累ꀊచ푭镄⏨ꏘ⍄".toCharArray(), (short)27991, (byte)0, (short)3).intern();
    "瓚锉ბ鵏່噾伷퍏㠉?犥".toCharArray()[0] = (char)("瓚锉ბ鵏່噾伷퍏㠉?犥".toCharArray()[0] ^ 0x4C1A);
    ˍ = ᐨẏ$ᐝт.W("瓚锉ბ鵏່噾伷퍏㠉?犥".toCharArray(), (short)2538, (byte)4, (short)2).intern();
    "鎆곟蛏졊鱗쐹䟰璫荁﹏셒Ꞧﱨ㡵綂".toCharArray()[9] = (char)("鎆곟蛏졊鱗쐹䟰璫荁﹏셒Ꞧﱨ㡵綂".toCharArray()[9] ^ 0x440A);
    ـﭔ = ᐨẏ$ᐝт.W("鎆곟蛏졊鱗쐹䟰璫荁﹏셒Ꞧﱨ㡵綂".toCharArray(), (short)24141, (byte)4, (short)2).intern();
    "⏍쇯ს?䃹䷊䤼".toCharArray()[3] = (char)("⏍쇯ს?䃹䷊䤼".toCharArray()[3] ^ 0x7CEE);
    ʼᵖ = ᐨẏ$ᐝт.W("⏍쇯ს?䃹䷊䤼".toCharArray(), (short)25021, (byte)0, (short)0).intern();
    "㙾￼꣘뉪뀐ॐ靳㞠㶑髞⪈먹帨ﵭ岯ߊ❑䣼莫?쭐삅䳇?ᔝ퀚䊙鶀ữᛄ቉?农湤".toCharArray()[31] = (char)("㙾￼꣘뉪뀐ॐ靳㞠㶑髞⪈먹帨ﵭ岯ߊ❑䣼莫?쭐삅䳇?ᔝ퀚䊙鶀ữᛄ቉?农湤".toCharArray()[31] ^ 0xB9D);
    ʿλ = ᐨẏ$ᐝт.W("㙾￼꣘뉪뀐ॐ靳㞠㶑髞⪈먹帨ﵭ岯ߊ❑䣼莫?쭐삅䳇?ᔝ퀚䊙鶀ữᛄ቉?农湤".toCharArray(), (short)12792, (byte)4, (short)5).intern();
    "鸳ꦐꯓ䵵᳊쵀ᵉ줕Ⰷ".toCharArray()[6] = (char)("鸳ꦐꯓ䵵᳊쵀ᵉ줕Ⰷ".toCharArray()[6] ^ 0xBD7);
    ᐨم = ᐨẏ$ᐝт.W("鸳ꦐꯓ䵵᳊쵀ᵉ줕Ⰷ".toCharArray(), (short)19008, (byte)2, (short)0).intern();
    "䈐ꅿ鯜풢퉟?䎻˵愀偤즴厷郛⃶聆혟華장㋫ቖB㺓鏖Ꮛ".toCharArray()[11] = (char)("䈐ꅿ鯜풢퉟?䎻˵愀偤즴厷郛⃶聆혟華장㋫ቖB㺓鏖Ꮛ".toCharArray()[11] ^ 0x6814);
    ᐝᵣ = ᐨẏ$ᐝт.W("䈐ꅿ鯜풢퉟?䎻˵愀偤즴厷郛⃶聆혟華장㋫ቖB㺓鏖Ꮛ".toCharArray(), (short)6241, (byte)2, (short)3).intern();
    "뚤뾷핺⣤訡陥⁈₎굝涺Y갲놤곹ﲝ삕ၛ".toCharArray()[9] = (char)("뚤뾷핺⣤訡陥⁈₎굝涺Y갲놤곹ﲝ삕ၛ".toCharArray()[9] ^ 0x23F6);
    ʻւ = ᐨẏ$ᐝт.W("뚤뾷핺⣤訡陥⁈₎굝涺Y갲놤곹ﲝ삕ၛ".toCharArray(), (short)1039, (byte)4, (short)3).intern();
    "癠??쵃ꍷ覓縵".toCharArray()[3] = (char)("癠??쵃ꍷ覓縵".toCharArray()[3] ^ 0x5A76);
    ˑܘ = ᐨẏ$ᐝт.W("癠??쵃ꍷ覓縵".toCharArray(), (short)28134, (byte)4, (short)2).intern();
    "耗૚⣆Й⾞".toCharArray()[1] = (char)("耗૚⣆Й⾞".toCharArray()[1] ^ 0x18B3);
    ʿᵉ = ᐨẏ$ᐝт.W("耗૚⣆Й⾞".toCharArray(), (short)15289, (byte)5, (short)3).intern();
    "弡㴍ꌭ榥먮뇫쮺錞ಕ㤘韒멑ौ䚣襨⊲ᶾᚲŬ骰臱㏿䬍剔汈ᓙណ쌃闅䏭蓄䩖".toCharArray()[10] = (char)("弡㴍ꌭ榥먮뇫쮺錞ಕ㤘韒멑ौ䚣襨⊲ᶾᚲŬ骰臱㏿䬍剔汈ᓙណ쌃闅䏭蓄䩖".toCharArray()[10] ^ 0x1955);
    ᔪ = ᐨẏ$ᐝт.W("弡㴍ꌭ榥먮뇫쮺錞ಕ㤘韒멑ौ䚣襨⊲ᶾᚲŬ骰臱㏿䬍剔汈ᓙណ쌃闅䏭蓄䩖".toCharArray(), (short)12020, (byte)5, (short)3).intern();
    "ᶍ侽∟΋跂☁綑㢦파繎រﮝ豴Ɠ".toCharArray()[9] = (char)("ᶍ侽∟΋跂☁綑㢦파繎រﮝ豴Ɠ".toCharArray()[9] ^ 0x138B);
    ʹﮃ = ᐨẏ$ᐝт.W("ᶍ侽∟΋跂☁綑㢦파繎រﮝ豴Ɠ".toCharArray(), (short)15669, (byte)5, (short)1).intern();
    "⃒￥잮ፒ風憋뀾ᱢ蒒ꭧ沗⧽娮簃㟢폢弐퉵྿㹋慡龗酸磍?꒹噹⋋".toCharArray()[8] = (char)("⃒￥잮ፒ風憋뀾ᱢ蒒ꭧ沗⧽娮簃㟢폢弐퉵྿㹋慡龗酸磍?꒹噹⋋".toCharArray()[8] ^ 0x70CA);
    ˉｓ = ᐨẏ$ᐝт.W("⃒￥잮ፒ風憋뀾ᱢ蒒ꭧ沗⧽娮簃㟢폢弐퉵྿㹋慡龗酸磍?꒹噹⋋".toCharArray(), (short)23809, (byte)1, (short)4).intern();
    "鉬팎꫟퇉仅⽍虎풴㬁".toCharArray()[1] = (char)("鉬팎꫟퇉仅⽍虎풴㬁".toCharArray()[1] ^ 0x5C1F);
    ʾܪ = ᐨẏ$ᐝт.W("鉬팎꫟퇉仅⽍虎풴㬁".toCharArray(), (short)24239, (byte)5, (short)3).intern();
    "跡쳉괩駳깜⫥ﺝ드뿕혹ⱪ軴訩쐯碗ᗊ唦?匪⁉䒃".toCharArray()[18] = (char)("跡쳉괩駳깜⫥ﺝ드뿕혹ⱪ軴訩쐯碗ᗊ唦?匪⁉䒃".toCharArray()[18] ^ 0x46ED);
    ʹō = ᐨẏ$ᐝт.W("跡쳉괩駳깜⫥ﺝ드뿕혹ⱪ軴訩쐯碗ᗊ唦?匪⁉䒃".toCharArray(), (short)3444, (byte)0, (short)4).intern();
    "᠜貨긇譌蚭䲮㼊鷔す⬨".toCharArray()[9] = (char)("᠜貨긇譌蚭䲮㼊鷔す⬨".toCharArray()[9] ^ 0x2A2E);
    ՙᗮ = ᐨẏ$ᐝт.W("᠜貨긇譌蚭䲮㼊鷔す⬨".toCharArray(), (short)8603, (byte)3, (short)3).intern();
    "㩞矔룿쮘㵑℗Ꙋ푋쌧Ⴑそ䒬⃎".toCharArray()[13] = (char)("㩞矔룿쮘㵑℗Ꙋ푋쌧Ⴑそ䒬⃎".toCharArray()[13] ^ 0x4826);
    ˊᵃ = ᐨẏ$ᐝт.W("㩞矔룿쮘㵑℗Ꙋ푋쌧Ⴑそ䒬⃎".toCharArray(), (short)15184, (byte)0, (short)1).intern();
    "ࡀ澒哝㶏諾刞㲴뢊௄".toCharArray()[1] = (char)("ࡀ澒哝㶏諾刞㲴뢊௄".toCharArray()[1] ^ 0x1BBF);
    ˌх = ᐨẏ$ᐝт.W("ࡀ澒哝㶏諾刞㲴뢊௄".toCharArray(), (short)20487, (byte)1, (short)3).intern();
    "覍꺨볕靭㦩窭윐턼鸍咹龄秣䁂櫋".toCharArray()[6] = (char)("覍꺨볕靭㦩窭윐턼鸍咹龄秣䁂櫋".toCharArray()[6] ^ 0x73D0);
    ʽ = ᐨẏ$ᐝт.W("覍꺨볕靭㦩窭윐턼鸍咹龄秣䁂櫋".toCharArray(), (short)28339, (byte)2, (short)3).intern();
    "橆꿥螈ꨘᜀ鬏ꭵ㲨崙騝趜Ჵத".toCharArray()[3] = (char)("橆꿥螈ꨘᜀ鬏ꭵ㲨崙騝趜Ჵத".toCharArray()[3] ^ 0x4C25);
    ˍɫ = ᐨẏ$ᐝт.W("橆꿥螈ꨘᜀ鬏ꭵ㲨崙騝趜Ჵத".toCharArray(), (short)31475, (byte)4, (short)3).intern();
    "᪒엪쏡?櫘뎀⭜喣".toCharArray()[8] = (char)("᪒엪쏡?櫘뎀⭜喣".toCharArray()[8] ^ 0x70C1);
    ʾ = ᐨẏ$ᐝт.W("᪒엪쏡?櫘뎀⭜喣".toCharArray(), (short)6183, (byte)3, (short)4).intern();
  }
  
  static {
    "ឩ?워媦篱婌ᒍ貨ꅣ藴腀◚萘暺艊悜".toCharArray()[13] = (char)("ឩ?워媦篱婌ᒍ貨ꅣ藴腀◚萘暺艊悜".toCharArray()[13] ^ 0x455A);
  }
}


/* Location:              C:\Users\kb\Downloads\ja-netfilter.jar!\yyds\sniarbtej\ᐨم.class
 * Java compiler version: 8 (52.0)
 * JD-Core Version:       1.1.3
 */