package yyds.sniarbtej;

import java.util.ArrayList;
import ylt.pmn.zubdqvgt;

public final class ιՆ<V extends ן> {
  private static final int ᐨহ = 65536;
  
  V ᐨẏ;
  
  private V[] ᐨẏ;
  
  public int ﹳᖦ;
  
  public int ᐝᒰ;
  
  private int ˑỲ;
  
  public ιՆ(int paramInt1, int paramInt2) {
    this.ᐨẏ = (V[])new ן[paramInt1 + ((paramInt2 >= 0) ? paramInt2 : 4)];
    this.ﹳᖦ = paramInt1;
    this.ᐝᒰ = 0;
    this.ˑỲ = (paramInt2 >= 0) ? paramInt2 : 65536;
  }
  
  public ιՆ(ιՆ<? extends V> paramιՆ) {
    this(paramιՆ.ﹳᖦ, paramιՆ.ᐨẏ.length - paramιՆ.ﹳᖦ);
    ˊ(paramιՆ);
  }
  
  public final ιՆ<V> ˊ(ιՆ<? extends V> paramιՆ) {
    this.ᐨẏ = paramιՆ.ᐨẏ;
    if (this.ᐨẏ.length < paramιՆ.ᐨẏ.length) {
      this.ᐨẏ = (V[])paramιՆ.ᐨẏ.clone();
    } else {
      System.arraycopy(paramιՆ.ᐨẏ, 0, this.ᐨẏ, 0, paramιՆ.ᐨẏ.length);
    } 
    this.ﹳᖦ = paramιՆ.ﹳᖦ;
    this.ᐝᒰ = paramιՆ.ᐝᒰ;
    this.ˑỲ = paramιՆ.ˑỲ;
    return this;
  }
  
  public static void ᵕ() {}
  
  public final void ᐨẏ(V paramV) {
    this.ᐨẏ = (V[])paramV;
  }
  
  public final int ʴ() {
    return this.ﹳᖦ;
  }
  
  private int ˌᵋ() {
    return this.ˑỲ;
  }
  
  public final V ᐨẏ(int paramInt) {
    if (paramInt >= this.ﹳᖦ) {
      "ⲇዋᰄ㈊椓ヶ⫘痂᝜⧤튚蛔滅齃↡ꕌ爏?ᄊ컅곎拒䐀繢臫㵺?샷ؕ菶馸謪聉ト臄ࠄ꿺狣ῃ".toCharArray()[19] = (char)("ⲇዋᰄ㈊椓ヶ⫘痂᝜⧤튚蛔滅齃↡ꕌ爏?ᄊ컅곎拒䐀繢臫㵺?샷ؕ菶馸謪聉ト臄ࠄ꿺狣ῃ".toCharArray()[19] ^ 0x2FD3);
      throw new IndexOutOfBoundsException(ˉﻤ$ͺſ.v("ⲇዋᰄ㈊椓ヶ⫘痂᝜⧤튚蛔滅齃↡ꕌ爏?ᄊ컅곎拒䐀繢臫㵺?샷ؕ菶馸謪聉ト臄ࠄ꿺狣ῃ".toCharArray(), (short)24209, 4, (short)1) + paramInt);
    } 
    return this.ᐨẏ[paramInt];
  }
  
  public final void ᐨẏ(int paramInt, V paramV) {
    if (paramInt >= this.ﹳᖦ) {
      "㈋旙壜铗ểᡴ䶻ힺ謁䅮Œ䲱鈷낙뿞鯶煦⍤ଡ먖ㅓ஘䰑霦莸훊죌吓汤ﾩޗಇ??ἢ岃拽枘".toCharArray()[16] = (char)("㈋旙壜铗ểᡴ䶻ힺ謁䅮Œ䲱鈷낙뿞鯶煦⍤ଡ먖ㅓ஘䰑霦莸훊죌吓汤ﾩޗಇ??ἢ岃拽枘".toCharArray()[16] ^ 0x1417);
      throw new IndexOutOfBoundsException(ˍɫ$יς.J("㈋旙壜铗ểᡴ䶻ힺ謁䅮Œ䲱鈷낙뿞鯶煦⍤ଡ먖ㅓ஘䰑霦莸훊죌吓汤ﾩޗಇ??ἢ岃拽枘".toCharArray(), (short)27645, (short)2, (byte)5) + paramInt);
    } 
    this.ᐨẏ[paramInt] = paramV;
  }
  
  public final int ʹл() {
    return this.ᐝᒰ;
  }
  
  public final V ˊ(int paramInt) {
    return this.ᐨẏ[this.ﹳᖦ + paramInt];
  }
  
  private void ˊ(int paramInt, V paramV) {
    this.ᐨẏ[this.ﹳᖦ + paramInt] = paramV;
  }
  
  public final void ˌᔹ() {
    this.ᐝᒰ = 0;
  }
  
  private V ᐨẏ() {
    if (this.ᐝᒰ == 0) {
      "ꂻ⤗쁍磄䡠〈ຶ逿꨸枹惡ꢄ罸ﬓ흀됖刪鹩믓ᣑ둙ꁨ홢⣮䆒߹粈㹆⧴㹩ᠦ쓌燂啋猻".toCharArray()[9] = (char)("ꂻ⤗쁍磄䡠〈ຶ逿꨸枹惡ꢄ罸ﬓ흀됖刪鹩믓ᣑ둙ꁨ홢⣮䆒߹粈㹆⧴㹩ᠦ쓌燂啋猻".toCharArray()[9] ^ 0x4106);
      throw new IndexOutOfBoundsException(ᐨẏ$ᐝт.W("ꂻ⤗쁍磄䡠〈ຶ逿꨸枹惡ꢄ罸ﬓ흀됖刪鹩믓ᣑ둙ꁨ홢⣮䆒߹粈㹆⧴㹩ᠦ쓌燂啋猻".toCharArray(), (short)1170, (byte)3, (short)0));
    } 
    return this.ᐨẏ[this.ﹳᖦ + --this.ᐝᒰ];
  }
  
  public final void ˊ(V paramV) {
    if (this.ﹳᖦ + this.ᐝᒰ >= this.ᐨẏ.length) {
      if (this.ﹳᖦ + this.ᐝᒰ >= this.ˑỲ) {
        "⤗访錆섄ᛳ궾ㅘᮔ䚂ϒ锈놜槮싇ㅼ뺃蛺꛿眹δ牢?⨽銉ঝꍔ辉趡賜̘ᆃ".toCharArray()[23] = (char)("⤗访錆섄ᛳ궾ㅘᮔ䚂ϒ锈놜槮싇ㅼ뺃蛺꛿眹δ牢?⨽銉ঝꍔ辉趡賜̘ᆃ".toCharArray()[23] ^ 0x6ECE);
        throw new IndexOutOfBoundsException(ˉﻤ$ͺſ.v("⤗访錆섄ᛳ궾ㅘᮔ䚂ϒ锈놜槮싇ㅼ뺃蛺꛿眹δ牢?⨽銉ঝꍔ辉趡賜̘ᆃ".toCharArray(), (short)28834, 0, (short)4));
      } 
      V[] arrayOfV = this.ᐨẏ;
      this.ᐨẏ = (V[])new ן[2 * this.ᐨẏ.length];
      System.arraycopy(arrayOfV, 0, this.ᐨẏ, 0, arrayOfV.length);
    } 
    this.ᐨẏ[this.ﹳᖦ + this.ᐝᒰ++] = paramV;
  }
  
  public final void ᐨẏ(Ӏ paramӀ, וּ<V> paramוּ) {
    // Byte code:
    //   0: aload_1
    //   1: invokevirtual ˈהּ : ()I
    //   4: tableswitch default -> 2224, 0 -> 820, 1 -> 821, 2 -> 821, 3 -> 821, 4 -> 821, 5 -> 821, 6 -> 821, 7 -> 821, 8 -> 821, 9 -> 821, 10 -> 821, 11 -> 821, 12 -> 821, 13 -> 821, 14 -> 821, 15 -> 821, 16 -> 821, 17 -> 821, 18 -> 821, 19 -> 2224, 20 -> 2224, 21 -> 831, 22 -> 831, 23 -> 831, 24 -> 831, 25 -> 831, 26 -> 2224, 27 -> 2224, 28 -> 2224, 29 -> 2224, 30 -> 2224, 31 -> 2224, 32 -> 2224, 33 -> 2224, 34 -> 2224, 35 -> 2224, 36 -> 2224, 37 -> 2224, 38 -> 2224, 39 -> 2224, 40 -> 2224, 41 -> 2224, 42 -> 2224, 43 -> 2224, 44 -> 2224, 45 -> 2224, 46 -> 1842, 47 -> 1842, 48 -> 1842, 49 -> 1842, 50 -> 1842, 51 -> 1842, 52 -> 1842, 53 -> 1842, 54 -> 852, 55 -> 852, 56 -> 852, 57 -> 852, 58 -> 852, 59 -> 2224, 60 -> 2224, 61 -> 2224, 62 -> 2224, 63 -> 2224, 64 -> 2224, 65 -> 2224, 66 -> 2224, 67 -> 2224, 68 -> 2224, 69 -> 2224, 70 -> 2224, 71 -> 2224, 72 -> 2224, 73 -> 2224, 74 -> 2224, 75 -> 2224, 76 -> 2224, 77 -> 2224, 78 -> 2224, 79 -> 947, 80 -> 947, 81 -> 947, 82 -> 947, 83 -> 947, 84 -> 947, 85 -> 947, 86 -> 947, 87 -> 976, 88 -> 1022, 89 -> 1081, 90 -> 1146, 91 -> 1233, 92 -> 1292, 93 -> 1405, 94 -> 1563, 95 -> 1754, 96 -> 1842, 97 -> 1842, 98 -> 1842, 99 -> 1842, 100 -> 1842, 101 -> 1842, 102 -> 1842, 103 -> 1842, 104 -> 1842, 105 -> 1842, 106 -> 1842, 107 -> 1842, 108 -> 1842, 109 -> 1842, 110 -> 1842, 111 -> 1842, 112 -> 1842, 113 -> 1842, 114 -> 1842, 115 -> 1842, 116 -> 1866, 117 -> 1866, 118 -> 1866, 119 -> 1866, 120 -> 1842, 121 -> 1842, 122 -> 1842, 123 -> 1842, 124 -> 1842, 125 -> 1842, 126 -> 1842, 127 -> 1842, 128 -> 1842, 129 -> 1842, 130 -> 1842, 131 -> 1842, 132 -> 1880, 133 -> 1907, 134 -> 1907, 135 -> 1907, 136 -> 1907, 137 -> 1907, 138 -> 1907, 139 -> 1907, 140 -> 1907, 141 -> 1907, 142 -> 1907, 143 -> 1907, 144 -> 1907, 145 -> 1907, 146 -> 1907, 147 -> 1907, 148 -> 1842, 149 -> 1842, 150 -> 1842, 151 -> 1842, 152 -> 1842, 153 -> 1921, 154 -> 1921, 155 -> 1921, 156 -> 1921, 157 -> 1921, 158 -> 1921, 159 -> 1932, 160 -> 1932, 161 -> 1932, 162 -> 1932, 163 -> 1932, 164 -> 1932, 165 -> 1932, 166 -> 1932, 167 -> 1953, 168 -> 1954, 169 -> 1964, 170 -> 1965, 171 -> 1965, 172 -> 1976, 173 -> 1976, 174 -> 1976, 175 -> 1976, 176 -> 1976, 177 -> 1999, 178 -> 2040, 179 -> 2050, 180 -> 2061, 181 -> 1932, 182 -> 2075, 183 -> 2075, 184 -> 2075, 185 -> 2075, 186 -> 2089, 187 -> 2103, 188 -> 2113, 189 -> 2113, 190 -> 2113, 191 -> 2127, 192 -> 2138, 193 -> 2138, 194 -> 2152, 195 -> 2152, 196 -> 2224, 197 -> 2163, 198 -> 2213, 199 -> 2213
    //   820: return
    //   821: aload_0
    //   822: aload_2
    //   823: aload_1
    //   824: invokevirtual ᐨẏ : (Lyyds/sniarbtej/Ӏ;)Lyyds/sniarbtej/ן;
    //   827: invokevirtual ˊ : (Lyyds/sniarbtej/ן;)V
    //   830: return
    //   831: aload_0
    //   832: aload_2
    //   833: aload_1
    //   834: aload_0
    //   835: aload_1
    //   836: checkcast yyds/sniarbtej/ᕁ
    //   839: getfield ՙﺙ : I
    //   842: invokevirtual ᐨẏ : (I)Lyyds/sniarbtej/ן;
    //   845: invokevirtual ˊ : (Lyyds/sniarbtej/Ӏ;Lyyds/sniarbtej/ן;)Lyyds/sniarbtej/ן;
    //   848: invokevirtual ˊ : (Lyyds/sniarbtej/ן;)V
    //   851: return
    //   852: aload_2
    //   853: aload_1
    //   854: aload_0
    //   855: invokevirtual ᐨẏ : ()Lyyds/sniarbtej/ן;
    //   858: invokevirtual ˊ : (Lyyds/sniarbtej/Ӏ;Lyyds/sniarbtej/ן;)Lyyds/sniarbtej/ן;
    //   861: astore_3
    //   862: aload_1
    //   863: checkcast yyds/sniarbtej/ᕁ
    //   866: getfield ՙﺙ : I
    //   869: istore #4
    //   871: aload_0
    //   872: iload #4
    //   874: aload_3
    //   875: invokevirtual ᐨẏ : (ILyyds/sniarbtej/ן;)V
    //   878: aload_3
    //   879: invokeinterface ˍɫ : ()I
    //   884: iconst_2
    //   885: if_icmpne -> 903
    //   888: aload_0
    //   889: iload #4
    //   891: iconst_1
    //   892: iadd
    //   893: aload_2
    //   894: dup
    //   895: astore_1
    //   896: aconst_null
    //   897: invokevirtual ᐨẏ : (Lyyds/sniarbtej/ˑܘ;)Lyyds/sniarbtej/ן;
    //   900: invokevirtual ᐨẏ : (ILyyds/sniarbtej/ן;)V
    //   903: iload #4
    //   905: ifle -> 2274
    //   908: aload_0
    //   909: iload #4
    //   911: iconst_1
    //   912: isub
    //   913: invokevirtual ᐨẏ : (I)Lyyds/sniarbtej/ן;
    //   916: dup
    //   917: astore_3
    //   918: ifnull -> 946
    //   921: aload_3
    //   922: invokeinterface ˍɫ : ()I
    //   927: iconst_2
    //   928: if_icmpne -> 946
    //   931: aload_0
    //   932: iload #4
    //   934: iconst_1
    //   935: isub
    //   936: aload_2
    //   937: dup
    //   938: astore_1
    //   939: aconst_null
    //   940: invokevirtual ᐨẏ : (Lyyds/sniarbtej/ˑܘ;)Lyyds/sniarbtej/ן;
    //   943: invokevirtual ᐨẏ : (ILyyds/sniarbtej/ן;)V
    //   946: return
    //   947: aload_0
    //   948: invokevirtual ᐨẏ : ()Lyyds/sniarbtej/ן;
    //   951: astore #5
    //   953: aload_0
    //   954: invokevirtual ᐨẏ : ()Lyyds/sniarbtej/ן;
    //   957: astore #4
    //   959: aload_0
    //   960: invokevirtual ᐨẏ : ()Lyyds/sniarbtej/ן;
    //   963: astore_3
    //   964: aload_2
    //   965: aload_1
    //   966: aload_3
    //   967: aload #4
    //   969: aload #5
    //   971: invokevirtual ᐨẏ : (Lyyds/sniarbtej/Ӏ;Lyyds/sniarbtej/ן;Lyyds/sniarbtej/ן;Lyyds/sniarbtej/ן;)Lyyds/sniarbtej/ן;
    //   974: pop
    //   975: return
    //   976: aload_0
    //   977: invokevirtual ᐨẏ : ()Lyyds/sniarbtej/ן;
    //   980: invokeinterface ˍɫ : ()I
    //   985: iconst_2
    //   986: if_icmpne -> 2274
    //   989: new yyds/sniarbtej/ιƚ
    //   992: dup
    //   993: aload_1
    //   994: ldc '玝胙磤㣫꾂?沞팅ᙨꖧ᱘ഌ䅻习噭휺㗇団'
    //   996: invokevirtual toCharArray : ()[C
    //   999: dup
    //   1000: dup
    //   1001: iconst_3
    //   1002: dup_x1
    //   1003: caload
    //   1004: sipush #22743
    //   1007: ixor
    //   1008: i2c
    //   1009: castore
    //   1010: sipush #6317
    //   1013: iconst_1
    //   1014: iconst_4
    //   1015: invokestatic j : (Ljava/lang/Object;SIS)Ljava/lang/String;
    //   1018: invokespecial <init> : (Lyyds/sniarbtej/Ӏ;Ljava/lang/String;)V
    //   1021: athrow
    //   1022: aload_0
    //   1023: invokevirtual ᐨẏ : ()Lyyds/sniarbtej/ן;
    //   1026: invokeinterface ˍɫ : ()I
    //   1031: iconst_1
    //   1032: if_icmpne -> 2274
    //   1035: aload_0
    //   1036: invokevirtual ᐨẏ : ()Lyyds/sniarbtej/ן;
    //   1039: invokeinterface ˍɫ : ()I
    //   1044: iconst_1
    //   1045: if_icmpeq -> 2274
    //   1048: new yyds/sniarbtej/ιƚ
    //   1051: dup
    //   1052: aload_1
    //   1053: ldc '粈鎂邐틳ꤨ碁瞠⃜쭁栯杳㨎?⍯襵㗛㹰'
    //   1055: invokevirtual toCharArray : ()[C
    //   1058: dup
    //   1059: dup
    //   1060: iconst_3
    //   1061: dup_x1
    //   1062: caload
    //   1063: sipush #4743
    //   1066: ixor
    //   1067: i2c
    //   1068: castore
    //   1069: sipush #11275
    //   1072: iconst_1
    //   1073: iconst_5
    //   1074: invokestatic j : (Ljava/lang/Object;SIS)Ljava/lang/String;
    //   1077: invokespecial <init> : (Lyyds/sniarbtej/Ӏ;Ljava/lang/String;)V
    //   1080: athrow
    //   1081: aload_0
    //   1082: invokevirtual ᐨẏ : ()Lyyds/sniarbtej/ן;
    //   1085: dup
    //   1086: astore_3
    //   1087: invokeinterface ˍɫ : ()I
    //   1092: iconst_1
    //   1093: if_icmpeq -> 1130
    //   1096: new yyds/sniarbtej/ιƚ
    //   1099: dup
    //   1100: aload_1
    //   1101: ldc '뱃๧붺蝞嗣蝈㟼笡敎찄聉ꁻᚧ휆噱鿐ζ'
    //   1103: invokevirtual toCharArray : ()[C
    //   1106: dup
    //   1107: dup
    //   1108: bipush #11
    //   1110: dup_x1
    //   1111: caload
    //   1112: sipush #20627
    //   1115: ixor
    //   1116: i2c
    //   1117: castore
    //   1118: sipush #20806
    //   1121: iconst_3
    //   1122: iconst_4
    //   1123: invokestatic j : (Ljava/lang/Object;SIS)Ljava/lang/String;
    //   1126: invokespecial <init> : (Lyyds/sniarbtej/Ӏ;Ljava/lang/String;)V
    //   1129: athrow
    //   1130: aload_0
    //   1131: aload_3
    //   1132: invokevirtual ˊ : (Lyyds/sniarbtej/ן;)V
    //   1135: aload_0
    //   1136: aload_2
    //   1137: aload_1
    //   1138: aload_3
    //   1139: invokevirtual ˊ : (Lyyds/sniarbtej/Ӏ;Lyyds/sniarbtej/ן;)Lyyds/sniarbtej/ן;
    //   1142: invokevirtual ˊ : (Lyyds/sniarbtej/ן;)V
    //   1145: return
    //   1146: aload_0
    //   1147: invokevirtual ᐨẏ : ()Lyyds/sniarbtej/ן;
    //   1150: astore_3
    //   1151: aload_0
    //   1152: invokevirtual ᐨẏ : ()Lyyds/sniarbtej/ן;
    //   1155: astore #4
    //   1157: aload_3
    //   1158: invokeinterface ˍɫ : ()I
    //   1163: iconst_1
    //   1164: if_icmpne -> 1178
    //   1167: aload #4
    //   1169: invokeinterface ˍɫ : ()I
    //   1174: iconst_1
    //   1175: if_icmpeq -> 1211
    //   1178: new yyds/sniarbtej/ιƚ
    //   1181: dup
    //   1182: aload_1
    //   1183: ldc '⇇筍㽀躵ာ聦秸?埒츴蒯撫겶犋㽫ᶳഺ묱ꯕ齴䪜'
    //   1185: invokevirtual toCharArray : ()[C
    //   1188: dup
    //   1189: dup
    //   1190: iconst_3
    //   1191: dup_x1
    //   1192: caload
    //   1193: sipush #27327
    //   1196: ixor
    //   1197: i2c
    //   1198: castore
    //   1199: sipush #16049
    //   1202: iconst_5
    //   1203: iconst_5
    //   1204: invokestatic j : (Ljava/lang/Object;SIS)Ljava/lang/String;
    //   1207: invokespecial <init> : (Lyyds/sniarbtej/Ӏ;Ljava/lang/String;)V
    //   1210: athrow
    //   1211: aload_0
    //   1212: aload_2
    //   1213: aload_1
    //   1214: aload_3
    //   1215: invokevirtual ˊ : (Lyyds/sniarbtej/Ӏ;Lyyds/sniarbtej/ן;)Lyyds/sniarbtej/ן;
    //   1218: invokevirtual ˊ : (Lyyds/sniarbtej/ן;)V
    //   1221: aload_0
    //   1222: aload #4
    //   1224: invokevirtual ˊ : (Lyyds/sniarbtej/ן;)V
    //   1227: aload_0
    //   1228: aload_3
    //   1229: invokevirtual ˊ : (Lyyds/sniarbtej/ן;)V
    //   1232: return
    //   1233: aload_0
    //   1234: invokevirtual ᐨẏ : ()Lyyds/sniarbtej/ן;
    //   1237: dup
    //   1238: astore_3
    //   1239: invokeinterface ˍɫ : ()I
    //   1244: iconst_1
    //   1245: if_icmpne -> 1258
    //   1248: aload_0
    //   1249: aload_1
    //   1250: aload_3
    //   1251: aload_2
    //   1252: invokespecial ᐨẏ : (Lyyds/sniarbtej/Ӏ;Lyyds/sniarbtej/ן;Lyyds/sniarbtej/וּ;)Z
    //   1255: ifne -> 2274
    //   1258: new yyds/sniarbtej/ιƚ
    //   1261: dup
    //   1262: aload_1
    //   1263: ldc '⸉㓍냉죵垓??좶쨷䂨떋ꬑᇨꮢᒚ槼圍ﮣ룙㌙'
    //   1265: invokevirtual toCharArray : ()[C
    //   1268: dup
    //   1269: dup
    //   1270: bipush #11
    //   1272: dup_x1
    //   1273: caload
    //   1274: sipush #780
    //   1277: ixor
    //   1278: i2c
    //   1279: castore
    //   1280: sipush #26601
    //   1283: iconst_2
    //   1284: iconst_3
    //   1285: invokestatic j : (Ljava/lang/Object;SIS)Ljava/lang/String;
    //   1288: invokespecial <init> : (Lyyds/sniarbtej/Ӏ;Ljava/lang/String;)V
    //   1291: athrow
    //   1292: aload_0
    //   1293: invokevirtual ᐨẏ : ()Lyyds/sniarbtej/ן;
    //   1296: dup
    //   1297: astore_3
    //   1298: invokeinterface ˍɫ : ()I
    //   1303: iconst_1
    //   1304: if_icmpne -> 1356
    //   1307: aload_0
    //   1308: invokevirtual ᐨẏ : ()Lyyds/sniarbtej/ן;
    //   1311: dup
    //   1312: astore #4
    //   1314: invokeinterface ˍɫ : ()I
    //   1319: iconst_1
    //   1320: if_icmpne -> 1372
    //   1323: aload_0
    //   1324: aload #4
    //   1326: invokevirtual ˊ : (Lyyds/sniarbtej/ן;)V
    //   1329: aload_0
    //   1330: aload_3
    //   1331: invokevirtual ˊ : (Lyyds/sniarbtej/ן;)V
    //   1334: aload_0
    //   1335: aload_2
    //   1336: aload_1
    //   1337: aload #4
    //   1339: invokevirtual ˊ : (Lyyds/sniarbtej/Ӏ;Lyyds/sniarbtej/ן;)Lyyds/sniarbtej/ן;
    //   1342: invokevirtual ˊ : (Lyyds/sniarbtej/ן;)V
    //   1345: aload_0
    //   1346: aload_2
    //   1347: aload_1
    //   1348: aload_3
    //   1349: invokevirtual ˊ : (Lyyds/sniarbtej/Ӏ;Lyyds/sniarbtej/ן;)Lyyds/sniarbtej/ן;
    //   1352: invokevirtual ˊ : (Lyyds/sniarbtej/ן;)V
    //   1355: return
    //   1356: aload_0
    //   1357: aload_3
    //   1358: invokevirtual ˊ : (Lyyds/sniarbtej/ן;)V
    //   1361: aload_0
    //   1362: aload_2
    //   1363: aload_1
    //   1364: aload_3
    //   1365: invokevirtual ˊ : (Lyyds/sniarbtej/Ӏ;Lyyds/sniarbtej/ן;)Lyyds/sniarbtej/ן;
    //   1368: invokevirtual ˊ : (Lyyds/sniarbtej/ן;)V
    //   1371: return
    //   1372: new yyds/sniarbtej/ιƚ
    //   1375: dup
    //   1376: aload_1
    //   1377: ldc '㩃窱ĭꟚ杞姥皃?ጨ᫙뛒蹞聴䘙⃳'
    //   1379: invokevirtual toCharArray : ()[C
    //   1382: dup
    //   1383: dup
    //   1384: iconst_5
    //   1385: dup_x1
    //   1386: caload
    //   1387: sipush #1038
    //   1390: ixor
    //   1391: i2c
    //   1392: castore
    //   1393: sipush #8069
    //   1396: iconst_1
    //   1397: iconst_5
    //   1398: invokestatic j : (Ljava/lang/Object;SIS)Ljava/lang/String;
    //   1401: invokespecial <init> : (Lyyds/sniarbtej/Ӏ;Ljava/lang/String;)V
    //   1404: athrow
    //   1405: aload_0
    //   1406: invokevirtual ᐨẏ : ()Lyyds/sniarbtej/ן;
    //   1409: dup
    //   1410: astore_3
    //   1411: invokeinterface ˍɫ : ()I
    //   1416: iconst_1
    //   1417: if_icmpne -> 1491
    //   1420: aload_0
    //   1421: invokevirtual ᐨẏ : ()Lyyds/sniarbtej/ן;
    //   1424: dup
    //   1425: astore #4
    //   1427: invokeinterface ˍɫ : ()I
    //   1432: iconst_1
    //   1433: if_icmpne -> 1529
    //   1436: aload_0
    //   1437: invokevirtual ᐨẏ : ()Lyyds/sniarbtej/ן;
    //   1440: dup
    //   1441: astore #5
    //   1443: invokeinterface ˍɫ : ()I
    //   1448: iconst_1
    //   1449: if_icmpne -> 1529
    //   1452: aload_0
    //   1453: aload_2
    //   1454: aload_1
    //   1455: aload #4
    //   1457: invokevirtual ˊ : (Lyyds/sniarbtej/Ӏ;Lyyds/sniarbtej/ן;)Lyyds/sniarbtej/ן;
    //   1460: invokevirtual ˊ : (Lyyds/sniarbtej/ן;)V
    //   1463: aload_0
    //   1464: aload_2
    //   1465: aload_1
    //   1466: aload_3
    //   1467: invokevirtual ˊ : (Lyyds/sniarbtej/Ӏ;Lyyds/sniarbtej/ן;)Lyyds/sniarbtej/ן;
    //   1470: invokevirtual ˊ : (Lyyds/sniarbtej/ן;)V
    //   1473: aload_0
    //   1474: aload #5
    //   1476: invokevirtual ˊ : (Lyyds/sniarbtej/ן;)V
    //   1479: aload_0
    //   1480: aload #4
    //   1482: invokevirtual ˊ : (Lyyds/sniarbtej/ן;)V
    //   1485: aload_0
    //   1486: aload_3
    //   1487: invokevirtual ˊ : (Lyyds/sniarbtej/ן;)V
    //   1490: return
    //   1491: aload_0
    //   1492: invokevirtual ᐨẏ : ()Lyyds/sniarbtej/ן;
    //   1495: dup
    //   1496: astore #4
    //   1498: invokeinterface ˍɫ : ()I
    //   1503: iconst_1
    //   1504: if_icmpne -> 1529
    //   1507: aload_0
    //   1508: aload_2
    //   1509: aload_1
    //   1510: aload_3
    //   1511: invokevirtual ˊ : (Lyyds/sniarbtej/Ӏ;Lyyds/sniarbtej/ן;)Lyyds/sniarbtej/ן;
    //   1514: invokevirtual ˊ : (Lyyds/sniarbtej/ן;)V
    //   1517: aload_0
    //   1518: aload #4
    //   1520: invokevirtual ˊ : (Lyyds/sniarbtej/ן;)V
    //   1523: aload_0
    //   1524: aload_3
    //   1525: invokevirtual ˊ : (Lyyds/sniarbtej/ן;)V
    //   1528: return
    //   1529: new yyds/sniarbtej/ιƚ
    //   1532: dup
    //   1533: aload_1
    //   1534: ldc '龲稊ᣭ臭튇r慮頶鮺쒆뗦숭䭵㮓㇖黺⻝仃텁ꔉ帿当'
    //   1536: invokevirtual toCharArray : ()[C
    //   1539: dup
    //   1540: dup
    //   1541: bipush #20
    //   1543: dup_x1
    //   1544: caload
    //   1545: sipush #1421
    //   1548: ixor
    //   1549: i2c
    //   1550: castore
    //   1551: sipush #18457
    //   1554: iconst_4
    //   1555: iconst_3
    //   1556: invokestatic j : (Ljava/lang/Object;SIS)Ljava/lang/String;
    //   1559: invokespecial <init> : (Lyyds/sniarbtej/Ӏ;Ljava/lang/String;)V
    //   1562: athrow
    //   1563: aload_0
    //   1564: invokevirtual ᐨẏ : ()Lyyds/sniarbtej/ן;
    //   1567: dup
    //   1568: astore_3
    //   1569: invokeinterface ˍɫ : ()I
    //   1574: iconst_1
    //   1575: if_icmpne -> 1710
    //   1578: aload_0
    //   1579: invokevirtual ᐨẏ : ()Lyyds/sniarbtej/ן;
    //   1582: dup
    //   1583: astore #4
    //   1585: invokeinterface ˍɫ : ()I
    //   1590: iconst_1
    //   1591: if_icmpne -> 1720
    //   1594: aload_0
    //   1595: invokevirtual ᐨẏ : ()Lyyds/sniarbtej/ן;
    //   1598: dup
    //   1599: astore #5
    //   1601: invokeinterface ˍɫ : ()I
    //   1606: iconst_1
    //   1607: if_icmpne -> 1671
    //   1610: aload_0
    //   1611: invokevirtual ᐨẏ : ()Lyyds/sniarbtej/ן;
    //   1614: dup
    //   1615: astore #6
    //   1617: invokeinterface ˍɫ : ()I
    //   1622: iconst_1
    //   1623: if_icmpne -> 1720
    //   1626: aload_0
    //   1627: aload_2
    //   1628: aload_1
    //   1629: aload #4
    //   1631: invokevirtual ˊ : (Lyyds/sniarbtej/Ӏ;Lyyds/sniarbtej/ן;)Lyyds/sniarbtej/ן;
    //   1634: invokevirtual ˊ : (Lyyds/sniarbtej/ן;)V
    //   1637: aload_0
    //   1638: aload_2
    //   1639: aload_1
    //   1640: aload_3
    //   1641: invokevirtual ˊ : (Lyyds/sniarbtej/Ӏ;Lyyds/sniarbtej/ן;)Lyyds/sniarbtej/ן;
    //   1644: invokevirtual ˊ : (Lyyds/sniarbtej/ן;)V
    //   1647: aload_0
    //   1648: aload #6
    //   1650: invokevirtual ˊ : (Lyyds/sniarbtej/ן;)V
    //   1653: aload_0
    //   1654: aload #5
    //   1656: invokevirtual ˊ : (Lyyds/sniarbtej/ן;)V
    //   1659: aload_0
    //   1660: aload #4
    //   1662: invokevirtual ˊ : (Lyyds/sniarbtej/ן;)V
    //   1665: aload_0
    //   1666: aload_3
    //   1667: invokevirtual ˊ : (Lyyds/sniarbtej/ן;)V
    //   1670: return
    //   1671: aload_0
    //   1672: aload_2
    //   1673: aload_1
    //   1674: aload #4
    //   1676: invokevirtual ˊ : (Lyyds/sniarbtej/Ӏ;Lyyds/sniarbtej/ן;)Lyyds/sniarbtej/ן;
    //   1679: invokevirtual ˊ : (Lyyds/sniarbtej/ן;)V
    //   1682: aload_0
    //   1683: aload_2
    //   1684: aload_1
    //   1685: aload_3
    //   1686: invokevirtual ˊ : (Lyyds/sniarbtej/Ӏ;Lyyds/sniarbtej/ן;)Lyyds/sniarbtej/ן;
    //   1689: invokevirtual ˊ : (Lyyds/sniarbtej/ן;)V
    //   1692: aload_0
    //   1693: aload #5
    //   1695: invokevirtual ˊ : (Lyyds/sniarbtej/ן;)V
    //   1698: aload_0
    //   1699: aload #4
    //   1701: invokevirtual ˊ : (Lyyds/sniarbtej/ן;)V
    //   1704: aload_0
    //   1705: aload_3
    //   1706: invokevirtual ˊ : (Lyyds/sniarbtej/ן;)V
    //   1709: return
    //   1710: aload_0
    //   1711: aload_1
    //   1712: aload_3
    //   1713: aload_2
    //   1714: invokespecial ᐨẏ : (Lyyds/sniarbtej/Ӏ;Lyyds/sniarbtej/ן;Lyyds/sniarbtej/וּ;)Z
    //   1717: ifne -> 2274
    //   1720: new yyds/sniarbtej/ιƚ
    //   1723: dup
    //   1724: aload_1
    //   1725: ldc '䰺潋䄖츃炽奱܇킩婙ꀩⵖΑᖣ鿉ﯲ⬜㈺䉈⑳ʺ'
    //   1727: invokevirtual toCharArray : ()[C
    //   1730: dup
    //   1731: dup
    //   1732: bipush #11
    //   1734: dup_x1
    //   1735: caload
    //   1736: sipush #10495
    //   1739: ixor
    //   1740: i2c
    //   1741: castore
    //   1742: sipush #21804
    //   1745: iconst_5
    //   1746: iconst_3
    //   1747: invokestatic j : (Ljava/lang/Object;SIS)Ljava/lang/String;
    //   1750: invokespecial <init> : (Lyyds/sniarbtej/Ӏ;Ljava/lang/String;)V
    //   1753: athrow
    //   1754: aload_0
    //   1755: invokevirtual ᐨẏ : ()Lyyds/sniarbtej/ן;
    //   1758: astore #4
    //   1760: aload_0
    //   1761: invokevirtual ᐨẏ : ()Lyyds/sniarbtej/ן;
    //   1764: dup
    //   1765: astore_3
    //   1766: invokeinterface ˍɫ : ()I
    //   1771: iconst_1
    //   1772: if_icmpne -> 1786
    //   1775: aload #4
    //   1777: invokeinterface ˍɫ : ()I
    //   1782: iconst_1
    //   1783: if_icmpeq -> 1820
    //   1786: new yyds/sniarbtej/ιƚ
    //   1789: dup
    //   1790: aload_1
    //   1791: ldc '쬎鼤ꤎ䔺킃泄⃳፫?Ʇ獥셽堐️⭐蝓⹜ᒟ'
    //   1793: invokevirtual toCharArray : ()[C
    //   1796: dup
    //   1797: dup
    //   1798: bipush #16
    //   1800: dup_x1
    //   1801: caload
    //   1802: sipush #29073
    //   1805: ixor
    //   1806: i2c
    //   1807: castore
    //   1808: sipush #11685
    //   1811: iconst_0
    //   1812: iconst_4
    //   1813: invokestatic j : (Ljava/lang/Object;SIS)Ljava/lang/String;
    //   1816: invokespecial <init> : (Lyyds/sniarbtej/Ӏ;Ljava/lang/String;)V
    //   1819: athrow
    //   1820: aload_0
    //   1821: aload_2
    //   1822: aload_1
    //   1823: aload #4
    //   1825: invokevirtual ˊ : (Lyyds/sniarbtej/Ӏ;Lyyds/sniarbtej/ן;)Lyyds/sniarbtej/ן;
    //   1828: invokevirtual ˊ : (Lyyds/sniarbtej/ן;)V
    //   1831: aload_0
    //   1832: aload_2
    //   1833: aload_1
    //   1834: aload_3
    //   1835: invokevirtual ˊ : (Lyyds/sniarbtej/Ӏ;Lyyds/sniarbtej/ן;)Lyyds/sniarbtej/ן;
    //   1838: invokevirtual ˊ : (Lyyds/sniarbtej/ן;)V
    //   1841: return
    //   1842: aload_0
    //   1843: invokevirtual ᐨẏ : ()Lyyds/sniarbtej/ן;
    //   1846: astore #4
    //   1848: aload_0
    //   1849: invokevirtual ᐨẏ : ()Lyyds/sniarbtej/ן;
    //   1852: astore_3
    //   1853: aload_0
    //   1854: aload_2
    //   1855: aload_1
    //   1856: aload_3
    //   1857: aload #4
    //   1859: invokevirtual ᐨẏ : (Lyyds/sniarbtej/Ӏ;Lyyds/sniarbtej/ן;Lyyds/sniarbtej/ן;)Lyyds/sniarbtej/ן;
    //   1862: invokevirtual ˊ : (Lyyds/sniarbtej/ן;)V
    //   1865: return
    //   1866: aload_0
    //   1867: aload_2
    //   1868: aload_1
    //   1869: aload_0
    //   1870: invokevirtual ᐨẏ : ()Lyyds/sniarbtej/ן;
    //   1873: invokevirtual ᐨẏ : (Lyyds/sniarbtej/Ӏ;Lyyds/sniarbtej/ן;)Lyyds/sniarbtej/ן;
    //   1876: invokevirtual ˊ : (Lyyds/sniarbtej/ן;)V
    //   1879: return
    //   1880: aload_1
    //   1881: checkcast yyds/sniarbtej/ۦ
    //   1884: getfield ՙﺙ : I
    //   1887: istore #4
    //   1889: aload_0
    //   1890: iload #4
    //   1892: aload_2
    //   1893: aload_1
    //   1894: aload_0
    //   1895: iload #4
    //   1897: invokevirtual ᐨẏ : (I)Lyyds/sniarbtej/ן;
    //   1900: invokevirtual ᐨẏ : (Lyyds/sniarbtej/Ӏ;Lyyds/sniarbtej/ן;)Lyyds/sniarbtej/ן;
    //   1903: invokevirtual ᐨẏ : (ILyyds/sniarbtej/ן;)V
    //   1906: return
    //   1907: aload_0
    //   1908: aload_2
    //   1909: aload_1
    //   1910: aload_0
    //   1911: invokevirtual ᐨẏ : ()Lyyds/sniarbtej/ן;
    //   1914: invokevirtual ᐨẏ : (Lyyds/sniarbtej/Ӏ;Lyyds/sniarbtej/ן;)Lyyds/sniarbtej/ן;
    //   1917: invokevirtual ˊ : (Lyyds/sniarbtej/ן;)V
    //   1920: return
    //   1921: aload_2
    //   1922: aload_1
    //   1923: aload_0
    //   1924: invokevirtual ᐨẏ : ()Lyyds/sniarbtej/ן;
    //   1927: invokevirtual ᐨẏ : (Lyyds/sniarbtej/Ӏ;Lyyds/sniarbtej/ן;)Lyyds/sniarbtej/ן;
    //   1930: pop
    //   1931: return
    //   1932: aload_0
    //   1933: invokevirtual ᐨẏ : ()Lyyds/sniarbtej/ן;
    //   1936: astore #4
    //   1938: aload_0
    //   1939: invokevirtual ᐨẏ : ()Lyyds/sniarbtej/ן;
    //   1942: astore_3
    //   1943: aload_2
    //   1944: aload_1
    //   1945: aload_3
    //   1946: aload #4
    //   1948: invokevirtual ᐨẏ : (Lyyds/sniarbtej/Ӏ;Lyyds/sniarbtej/ן;Lyyds/sniarbtej/ן;)Lyyds/sniarbtej/ן;
    //   1951: pop
    //   1952: return
    //   1953: return
    //   1954: aload_0
    //   1955: aload_2
    //   1956: aload_1
    //   1957: invokevirtual ᐨẏ : (Lyyds/sniarbtej/Ӏ;)Lyyds/sniarbtej/ן;
    //   1960: invokevirtual ˊ : (Lyyds/sniarbtej/ן;)V
    //   1963: return
    //   1964: return
    //   1965: aload_2
    //   1966: aload_1
    //   1967: aload_0
    //   1968: invokevirtual ᐨẏ : ()Lyyds/sniarbtej/ן;
    //   1971: invokevirtual ᐨẏ : (Lyyds/sniarbtej/Ӏ;Lyyds/sniarbtej/ן;)Lyyds/sniarbtej/ן;
    //   1974: pop
    //   1975: return
    //   1976: aload_0
    //   1977: invokevirtual ᐨẏ : ()Lyyds/sniarbtej/ן;
    //   1980: astore_3
    //   1981: aload_2
    //   1982: aload_1
    //   1983: aload_3
    //   1984: invokevirtual ᐨẏ : (Lyyds/sniarbtej/Ӏ;Lyyds/sniarbtej/ן;)Lyyds/sniarbtej/ן;
    //   1987: pop
    //   1988: aload_2
    //   1989: aload_1
    //   1990: aload_3
    //   1991: aload_0
    //   1992: getfield ᐨẏ : Lyyds/sniarbtej/ן;
    //   1995: invokevirtual ᐨẏ : (Lyyds/sniarbtej/Ӏ;Lyyds/sniarbtej/ן;Lyyds/sniarbtej/ן;)V
    //   1998: return
    //   1999: aload_0
    //   2000: getfield ᐨẏ : Lyyds/sniarbtej/ן;
    //   2003: ifnull -> 2274
    //   2006: new yyds/sniarbtej/ιƚ
    //   2009: dup
    //   2010: aload_1
    //   2011: ldc 'ᦳ鋪੫ꤴ儐䥗䳧읜?䗦㇋蹉焜䅚賩樏?탛㍍鈓៍붰ヴ碚'
    //   2013: invokevirtual toCharArray : ()[C
    //   2016: dup
    //   2017: dup
    //   2018: bipush #12
    //   2020: dup_x1
    //   2021: caload
    //   2022: sipush #29563
    //   2025: ixor
    //   2026: i2c
    //   2027: castore
    //   2028: sipush #2363
    //   2031: iconst_0
    //   2032: iconst_5
    //   2033: invokestatic j : (Ljava/lang/Object;SIS)Ljava/lang/String;
    //   2036: invokespecial <init> : (Lyyds/sniarbtej/Ӏ;Ljava/lang/String;)V
    //   2039: athrow
    //   2040: aload_0
    //   2041: aload_2
    //   2042: aload_1
    //   2043: invokevirtual ᐨẏ : (Lyyds/sniarbtej/Ӏ;)Lyyds/sniarbtej/ן;
    //   2046: invokevirtual ˊ : (Lyyds/sniarbtej/ן;)V
    //   2049: return
    //   2050: aload_2
    //   2051: aload_1
    //   2052: aload_0
    //   2053: invokevirtual ᐨẏ : ()Lyyds/sniarbtej/ן;
    //   2056: invokevirtual ᐨẏ : (Lyyds/sniarbtej/Ӏ;Lyyds/sniarbtej/ן;)Lyyds/sniarbtej/ן;
    //   2059: pop
    //   2060: return
    //   2061: aload_0
    //   2062: aload_2
    //   2063: aload_1
    //   2064: aload_0
    //   2065: invokevirtual ᐨẏ : ()Lyyds/sniarbtej/ן;
    //   2068: invokevirtual ᐨẏ : (Lyyds/sniarbtej/Ӏ;Lyyds/sniarbtej/ן;)Lyyds/sniarbtej/ן;
    //   2071: invokevirtual ˊ : (Lyyds/sniarbtej/ן;)V
    //   2074: return
    //   2075: aload_0
    //   2076: aload_1
    //   2077: dup
    //   2078: checkcast yyds/sniarbtej/ʾᔂ
    //   2081: getfield ˎᴗ : Ljava/lang/String;
    //   2084: aload_2
    //   2085: invokespecial ᐨẏ : (Lyyds/sniarbtej/Ӏ;Ljava/lang/String;Lyyds/sniarbtej/וּ;)V
    //   2088: return
    //   2089: aload_0
    //   2090: aload_1
    //   2091: dup
    //   2092: checkcast yyds/sniarbtej/ʻᴷ
    //   2095: getfield ˎᴗ : Ljava/lang/String;
    //   2098: aload_2
    //   2099: invokespecial ᐨẏ : (Lyyds/sniarbtej/Ӏ;Ljava/lang/String;Lyyds/sniarbtej/וּ;)V
    //   2102: return
    //   2103: aload_0
    //   2104: aload_2
    //   2105: aload_1
    //   2106: invokevirtual ᐨẏ : (Lyyds/sniarbtej/Ӏ;)Lyyds/sniarbtej/ן;
    //   2109: invokevirtual ˊ : (Lyyds/sniarbtej/ן;)V
    //   2112: return
    //   2113: aload_0
    //   2114: aload_2
    //   2115: aload_1
    //   2116: aload_0
    //   2117: invokevirtual ᐨẏ : ()Lyyds/sniarbtej/ן;
    //   2120: invokevirtual ᐨẏ : (Lyyds/sniarbtej/Ӏ;Lyyds/sniarbtej/ן;)Lyyds/sniarbtej/ן;
    //   2123: invokevirtual ˊ : (Lyyds/sniarbtej/ן;)V
    //   2126: return
    //   2127: aload_2
    //   2128: aload_1
    //   2129: aload_0
    //   2130: invokevirtual ᐨẏ : ()Lyyds/sniarbtej/ן;
    //   2133: invokevirtual ᐨẏ : (Lyyds/sniarbtej/Ӏ;Lyyds/sniarbtej/ן;)Lyyds/sniarbtej/ן;
    //   2136: pop
    //   2137: return
    //   2138: aload_0
    //   2139: aload_2
    //   2140: aload_1
    //   2141: aload_0
    //   2142: invokevirtual ᐨẏ : ()Lyyds/sniarbtej/ן;
    //   2145: invokevirtual ᐨẏ : (Lyyds/sniarbtej/Ӏ;Lyyds/sniarbtej/ן;)Lyyds/sniarbtej/ן;
    //   2148: invokevirtual ˊ : (Lyyds/sniarbtej/ן;)V
    //   2151: return
    //   2152: aload_2
    //   2153: aload_1
    //   2154: aload_0
    //   2155: invokevirtual ᐨẏ : ()Lyyds/sniarbtej/ן;
    //   2158: invokevirtual ᐨẏ : (Lyyds/sniarbtej/Ӏ;Lyyds/sniarbtej/ן;)Lyyds/sniarbtej/ן;
    //   2161: pop
    //   2162: return
    //   2163: new java/util/ArrayList
    //   2166: dup
    //   2167: invokespecial <init> : ()V
    //   2170: astore_3
    //   2171: aload_1
    //   2172: checkcast yyds/sniarbtej/ˍᒄ
    //   2175: getfield ỵ : I
    //   2178: istore #4
    //   2180: iload #4
    //   2182: ifle -> 2202
    //   2185: aload_3
    //   2186: iconst_0
    //   2187: aload_0
    //   2188: invokevirtual ᐨẏ : ()Lyyds/sniarbtej/ן;
    //   2191: invokeinterface add : (ILjava/lang/Object;)V
    //   2196: iinc #4, -1
    //   2199: goto -> 2180
    //   2202: aload_0
    //   2203: aload_2
    //   2204: aload_1
    //   2205: aload_3
    //   2206: invokevirtual ᐨẏ : (Lyyds/sniarbtej/Ӏ;Ljava/util/List;)Lyyds/sniarbtej/ן;
    //   2209: invokevirtual ˊ : (Lyyds/sniarbtej/ן;)V
    //   2212: return
    //   2213: aload_2
    //   2214: aload_1
    //   2215: aload_0
    //   2216: invokevirtual ᐨẏ : ()Lyyds/sniarbtej/ן;
    //   2219: invokevirtual ᐨẏ : (Lyyds/sniarbtej/Ӏ;Lyyds/sniarbtej/ן;)Lyyds/sniarbtej/ן;
    //   2222: pop
    //   2223: return
    //   2224: new yyds/sniarbtej/ιƚ
    //   2227: dup
    //   2228: aload_1
    //   2229: new java/lang/StringBuilder
    //   2232: dup
    //   2233: ldc '댘뀌鴱뱸鱰褉Ḻ֣≣উ㹐粶棲濞'
    //   2235: invokevirtual toCharArray : ()[C
    //   2238: dup
    //   2239: dup
    //   2240: iconst_2
    //   2241: dup_x1
    //   2242: caload
    //   2243: sipush #27218
    //   2246: ixor
    //   2247: i2c
    //   2248: castore
    //   2249: sipush #29292
    //   2252: iconst_3
    //   2253: iconst_4
    //   2254: invokestatic j : (Ljava/lang/Object;SIS)Ljava/lang/String;
    //   2257: invokespecial <init> : (Ljava/lang/String;)V
    //   2260: aload_1
    //   2261: invokevirtual ˈהּ : ()I
    //   2264: invokevirtual append : (I)Ljava/lang/StringBuilder;
    //   2267: invokevirtual toString : ()Ljava/lang/String;
    //   2270: invokespecial <init> : (Lyyds/sniarbtej/Ӏ;Ljava/lang/String;)V
    //   2273: athrow
    //   2274: return
  }
  
  private boolean ᐨẏ(Ӏ paramӀ, V paramV, וּ<V> paramוּ) {
    V v;
    if ((v = ᐨẏ()).ˍɫ() == 1) {
      V v1;
      if ((v1 = ᐨẏ()).ˍɫ() == 1) {
        ˊ(paramוּ.ˊ(paramӀ, paramV));
        ˊ(v1);
        ˊ(v);
        ˊ(paramV);
        return true;
      } 
    } else {
      ˊ(paramוּ.ˊ(paramӀ, paramV));
      ˊ(v);
      ˊ(paramV);
      return true;
    } 
    return false;
  }
  
  private void ᐨẏ(Ӏ paramӀ, String paramString, וּ<V> paramוּ) {
    ArrayList<V> arrayList = new ArrayList();
    for (int i = ˑܘ.ʾܪ(paramString); i > 0; i--)
      arrayList.add(0, ᐨẏ()); 
    if (paramӀ.ˈהּ() != 184 && paramӀ.ˈהּ() != 186)
      arrayList.add(0, ᐨẏ()); 
    if (zubdqvgt.G(ˑܘ.ﾞл(paramString), ˑܘ.ᐨẏ)) {
      paramוּ.ᐨẏ(paramӀ, arrayList);
      return;
    } 
    ˊ(paramוּ.ᐨẏ(paramӀ, arrayList));
  }
  
  public final boolean ᐨẏ(ιՆ<? extends V> paramιՆ, וּ<V> paramוּ) {
    if (this.ᐝᒰ != paramιՆ.ᐝᒰ) {
      "?᰿퓬딄뫯䷨꽶鼸뼃䵷勯ശ謒勯乧쩐金鹘?龶䪌?暏景賊栻".toCharArray()[18] = (char)("?᰿퓬딄뫯䷨꽶鼸뼃䵷勯ശ謒勯乧쩐金鹘?龶䪌?暏景賊栻".toCharArray()[18] ^ 0x36D1);
      throw new ιƚ(null, ˍɫ$יς.J("?᰿퓬딄뫯䷨꽶鼸뼃䵷勯ശ謒勯乧쩐金鹘?龶䪌?暏景賊栻".toCharArray(), (short)25811, (short)3, (byte)4));
    } 
    boolean bool = false;
    for (byte b = 0; b < this.ﹳᖦ + this.ᐝᒰ; b++) {
      V v;
      if (!(v = paramוּ.ᐨẏ(this.ᐨẏ[b], paramιՆ.ᐨẏ[b])).equals(this.ᐨẏ[b])) {
        this.ᐨẏ[b] = v;
        bool = true;
      } 
    } 
    return bool;
  }
  
  public final boolean ᐨẏ(ιՆ<? extends V> paramιՆ, boolean[] paramArrayOfboolean) {
    boolean bool = false;
    for (byte b = 0; b < this.ﹳᖦ; b++) {
      if (!paramArrayOfboolean[b] && !this.ᐨẏ[b].equals(paramιՆ.ᐨẏ[b])) {
        this.ᐨẏ[b] = paramιՆ.ᐨẏ[b];
        bool = true;
      } 
    } 
    return bool;
  }
  
  public final String toString() {
    StringBuilder stringBuilder = new StringBuilder();
    byte b;
    ιՆ ιՆ1;
    for (b = 0; b < (ιՆ1 = this).ﹳᖦ; b++)
      stringBuilder.append(ᐨẏ(b)); 
    stringBuilder.append(' ');
    for (b = 0; b < (ιՆ1 = this).ᐝᒰ; b++)
      stringBuilder.append(ˊ(b).toString()); 
    return stringBuilder.toString();
  }
}


/* Location:              C:\Users\kb\Downloads\ja-netfilter.jar!\yyds\sniarbtej\ιՆ.class
 * Java compiler version: 8 (52.0)
 * JD-Core Version:       1.1.3
 */