package yyds.sniarbtej;

import java.util.ArrayList;
import java.util.HashMap;
import java.util.List;
import java.util.ListIterator;

public class ιᒶ<V extends ן> implements ـﭔ {
  private final וּ<V> ᐨẏ;
  
  private ـс ᴵʖ;
  
  private int ﾞڔ;
  
  private List<ˌț>[] ᴵʖ;
  
  public ιՆ<V>[] ᐨẏ;
  
  private ᐧᎰ[] ᐨẏ;
  
  private boolean[] ᐨẏ;
  
  private int[] ˍ;
  
  private int ʹᓱ;
  
  public ιᒶ(וּ<V> paramוּ) {
    this.ᐨẏ = (boolean[])paramוּ;
  }
  
  public final ιՆ<V>[] ᐨẏ(String paramString, ᐧє paramᐧє) {
    // Byte code:
    //   0: aload_2
    //   1: getfield ᒬ : I
    //   4: sipush #1280
    //   7: iand
    //   8: ifeq -> 24
    //   11: aload_0
    //   12: iconst_0
    //   13: anewarray yyds/sniarbtej/ιՆ
    //   16: putfield ᐨẏ : [Lyyds/sniarbtej/ιՆ;
    //   19: aload_0
    //   20: getfield ᐨẏ : [Lyyds/sniarbtej/ιՆ;
    //   23: areturn
    //   24: aload_0
    //   25: aload_2
    //   26: getfield ˊ : Lyyds/sniarbtej/ـс;
    //   29: putfield ᴵʖ : Lyyds/sniarbtej/ـс;
    //   32: aload_0
    //   33: dup
    //   34: getfield ᴵʖ : Lyyds/sniarbtej/ـс;
    //   37: dup
    //   38: astore #11
    //   40: getfield ʿᵉ : I
    //   43: putfield ﾞڔ : I
    //   46: aload_0
    //   47: dup
    //   48: getfield ﾞڔ : I
    //   51: anewarray java/util/List
    //   54: putfield ᴵʖ : [Ljava/util/List;
    //   57: aload_0
    //   58: dup
    //   59: getfield ﾞڔ : I
    //   62: anewarray yyds/sniarbtej/ιՆ
    //   65: putfield ᐨẏ : [Lyyds/sniarbtej/ιՆ;
    //   68: aload_0
    //   69: dup
    //   70: getfield ﾞڔ : I
    //   73: anewarray yyds/sniarbtej/ᐧᎰ
    //   76: putfield ᐨẏ : [Lyyds/sniarbtej/ᐧᎰ;
    //   79: aload_0
    //   80: dup
    //   81: getfield ﾞڔ : I
    //   84: newarray boolean
    //   86: putfield ᐨẏ : [Z
    //   89: aload_0
    //   90: dup
    //   91: getfield ﾞڔ : I
    //   94: newarray int
    //   96: putfield ˍ : [I
    //   99: aload_0
    //   100: iconst_0
    //   101: putfield ʹᓱ : I
    //   104: iconst_0
    //   105: istore_3
    //   106: iload_3
    //   107: aload_2
    //   108: getfield ﾞǰ : Ljava/util/List;
    //   111: invokeinterface size : ()I
    //   116: if_icmpge -> 226
    //   119: aload_2
    //   120: getfield ﾞǰ : Ljava/util/List;
    //   123: iload_3
    //   124: invokeinterface get : (I)Ljava/lang/Object;
    //   129: checkcast yyds/sniarbtej/ˌț
    //   132: astore #4
    //   134: aload_0
    //   135: getfield ᴵʖ : Lyyds/sniarbtej/ـс;
    //   138: aload #4
    //   140: getfield ᴵʖ : Lyyds/sniarbtej/λ;
    //   143: invokevirtual ᐨẏ : (Lyyds/sniarbtej/Ӏ;)I
    //   146: istore #5
    //   148: aload_0
    //   149: getfield ᴵʖ : Lyyds/sniarbtej/ـс;
    //   152: aload #4
    //   154: getfield ﾞл : Lyyds/sniarbtej/λ;
    //   157: invokevirtual ᐨẏ : (Lyyds/sniarbtej/Ӏ;)I
    //   160: istore #6
    //   162: iload #5
    //   164: istore #7
    //   166: iload #7
    //   168: iload #6
    //   170: if_icmpge -> 220
    //   173: aload_0
    //   174: getfield ᴵʖ : [Ljava/util/List;
    //   177: iload #7
    //   179: aaload
    //   180: dup
    //   181: astore #8
    //   183: ifnonnull -> 204
    //   186: new java/util/ArrayList
    //   189: dup
    //   190: invokespecial <init> : ()V
    //   193: astore #8
    //   195: aload_0
    //   196: getfield ᴵʖ : [Ljava/util/List;
    //   199: iload #7
    //   201: aload #8
    //   203: aastore
    //   204: aload #8
    //   206: aload #4
    //   208: invokeinterface add : (Ljava/lang/Object;)Z
    //   213: pop
    //   214: iinc #7, 1
    //   217: goto -> 166
    //   220: iinc #3, 1
    //   223: goto -> 106
    //   226: aload_0
    //   227: aload_2
    //   228: getfield ˌپ : I
    //   231: invokespecial ˌ : (I)V
    //   234: aload_0
    //   235: aload_1
    //   236: aload_2
    //   237: invokespecial ᐨẏ : (Ljava/lang/String;Lyyds/sniarbtej/ᐧє;)Lyyds/sniarbtej/ιՆ;
    //   240: astore_3
    //   241: aload_0
    //   242: iconst_0
    //   243: aload_3
    //   244: aconst_null
    //   245: invokespecial ᐨẏ : (ILyyds/sniarbtej/ιՆ;Lyyds/sniarbtej/ᐧᎰ;)V
    //   248: aload_0
    //   249: aload_1
    //   250: aload_2
    //   251: invokevirtual ᐨẏ : (Ljava/lang/String;Lyyds/sniarbtej/ᐧє;)V
    //   254: goto -> 319
    //   257: astore #4
    //   259: new yyds/sniarbtej/ιƚ
    //   262: dup
    //   263: aload_0
    //   264: getfield ᴵʖ : Lyyds/sniarbtej/ـс;
    //   267: iconst_0
    //   268: invokevirtual ᐨẏ : (I)Lyyds/sniarbtej/Ӏ;
    //   271: new java/lang/StringBuilder
    //   274: dup
    //   275: ldc '℀᳢៳䦗∱普쌖䀙宏⒒筣䔗琈者ꄵ滆Ǎꝫꋰᶴ즣Ȼ'
    //   277: invokevirtual toCharArray : ()[C
    //   280: dup
    //   281: dup
    //   282: iconst_4
    //   283: dup_x1
    //   284: caload
    //   285: sipush #10067
    //   288: ixor
    //   289: i2c
    //   290: castore
    //   291: sipush #20314
    //   294: iconst_5
    //   295: iconst_0
    //   296: invokestatic v : (Ljava/lang/Object;SIS)Ljava/lang/String;
    //   299: invokespecial <init> : (Ljava/lang/String;)V
    //   302: aload #4
    //   304: invokevirtual getMessage : ()Ljava/lang/String;
    //   307: invokevirtual append : (Ljava/lang/String;)Ljava/lang/StringBuilder;
    //   310: invokevirtual toString : ()Ljava/lang/String;
    //   313: aload #4
    //   315: invokespecial <init> : (Lyyds/sniarbtej/Ӏ;Ljava/lang/String;Ljava/lang/Throwable;)V
    //   318: athrow
    //   319: aload_0
    //   320: getfield ʹᓱ : I
    //   323: ifle -> 1570
    //   326: aload_0
    //   327: getfield ˍ : [I
    //   330: aload_0
    //   331: dup
    //   332: getfield ʹᓱ : I
    //   335: iconst_1
    //   336: isub
    //   337: dup_x1
    //   338: putfield ʹᓱ : I
    //   341: iaload
    //   342: istore #4
    //   344: aload_0
    //   345: getfield ᐨẏ : [Lyyds/sniarbtej/ιՆ;
    //   348: iload #4
    //   350: aaload
    //   351: astore #5
    //   353: aload_0
    //   354: getfield ᐨẏ : [Lyyds/sniarbtej/ᐧᎰ;
    //   357: iload #4
    //   359: aaload
    //   360: astore #6
    //   362: aload_0
    //   363: getfield ᐨẏ : [Z
    //   366: iload #4
    //   368: iconst_0
    //   369: bastore
    //   370: aconst_null
    //   371: astore #7
    //   373: aload_2
    //   374: getfield ˊ : Lyyds/sniarbtej/ـс;
    //   377: iload #4
    //   379: invokevirtual ᐨẏ : (I)Lyyds/sniarbtej/Ӏ;
    //   382: dup
    //   383: astore #7
    //   385: invokevirtual ˈהּ : ()I
    //   388: istore #8
    //   390: aload #7
    //   392: invokevirtual ﹳיִ : ()I
    //   395: dup
    //   396: istore_1
    //   397: bipush #8
    //   399: if_icmpeq -> 414
    //   402: iload_1
    //   403: bipush #15
    //   405: if_icmpeq -> 414
    //   408: iload_1
    //   409: bipush #14
    //   411: if_icmpne -> 429
    //   414: aload_0
    //   415: iload #4
    //   417: iconst_1
    //   418: iadd
    //   419: aload #5
    //   421: aload #6
    //   423: invokespecial ᐨẏ : (ILyyds/sniarbtej/ιՆ;Lyyds/sniarbtej/ᐧᎰ;)V
    //   426: goto -> 1170
    //   429: aload_3
    //   430: aload #5
    //   432: invokevirtual ˊ : (Lyyds/sniarbtej/ιՆ;)Lyyds/sniarbtej/ιՆ;
    //   435: aload #7
    //   437: aload_0
    //   438: getfield ᐨẏ : Lyyds/sniarbtej/וּ;
    //   441: invokevirtual ᐨẏ : (Lyyds/sniarbtej/Ӏ;Lyyds/sniarbtej/וּ;)V
    //   444: aload #6
    //   446: ifnonnull -> 453
    //   449: aconst_null
    //   450: goto -> 462
    //   453: new yyds/sniarbtej/ᐧᎰ
    //   456: dup
    //   457: aload #6
    //   459: invokespecial <init> : (Lyyds/sniarbtej/ᐧᎰ;)V
    //   462: astore #6
    //   464: aload #7
    //   466: instanceof yyds/sniarbtej/ʿশ
    //   469: ifeq -> 564
    //   472: aload #7
    //   474: checkcast yyds/sniarbtej/ʿশ
    //   477: astore_1
    //   478: iload #8
    //   480: sipush #167
    //   483: if_icmpeq -> 505
    //   486: iload #8
    //   488: sipush #168
    //   491: if_icmpeq -> 505
    //   494: aload_0
    //   495: iload #4
    //   497: iconst_1
    //   498: iadd
    //   499: aload_3
    //   500: aload #6
    //   502: invokespecial ᐨẏ : (ILyyds/sniarbtej/ιՆ;Lyyds/sniarbtej/ᐧᎰ;)V
    //   505: aload_0
    //   506: getfield ᴵʖ : Lyyds/sniarbtej/ـс;
    //   509: aload_1
    //   510: getfield ˊ : Lyyds/sniarbtej/λ;
    //   513: invokevirtual ᐨẏ : (Lyyds/sniarbtej/Ӏ;)I
    //   516: istore #9
    //   518: iload #8
    //   520: sipush #168
    //   523: if_icmpne -> 552
    //   526: aload_0
    //   527: iload #9
    //   529: aload_3
    //   530: new yyds/sniarbtej/ᐧᎰ
    //   533: dup
    //   534: aload_1
    //   535: getfield ˊ : Lyyds/sniarbtej/λ;
    //   538: aload_2
    //   539: getfield ˌپ : I
    //   542: aload_1
    //   543: invokespecial <init> : (Lyyds/sniarbtej/λ;ILyyds/sniarbtej/ʿশ;)V
    //   546: invokespecial ᐨẏ : (ILyyds/sniarbtej/ιՆ;Lyyds/sniarbtej/ᐧᎰ;)V
    //   549: goto -> 1170
    //   552: aload_0
    //   553: iload #9
    //   555: aload_3
    //   556: aload #6
    //   558: invokespecial ᐨẏ : (ILyyds/sniarbtej/ιՆ;Lyyds/sniarbtej/ᐧᎰ;)V
    //   561: goto -> 1170
    //   564: aload #7
    //   566: instanceof yyds/sniarbtej/ﹳڐ
    //   569: ifeq -> 662
    //   572: aload #7
    //   574: checkcast yyds/sniarbtej/ﹳڐ
    //   577: astore_1
    //   578: aload_0
    //   579: getfield ᴵʖ : Lyyds/sniarbtej/ـс;
    //   582: aload_1
    //   583: getfield ʿᵉ : Lyyds/sniarbtej/λ;
    //   586: invokevirtual ᐨẏ : (Lyyds/sniarbtej/Ӏ;)I
    //   589: istore #9
    //   591: aload_0
    //   592: iload #9
    //   594: aload_3
    //   595: aload #6
    //   597: invokespecial ᐨẏ : (ILyyds/sniarbtej/ιՆ;Lyyds/sniarbtej/ᐧᎰ;)V
    //   600: iconst_0
    //   601: istore #8
    //   603: iload #8
    //   605: aload_1
    //   606: getfield ﾞл : Ljava/util/List;
    //   609: invokeinterface size : ()I
    //   614: if_icmpge -> 659
    //   617: aload_1
    //   618: getfield ﾞл : Ljava/util/List;
    //   621: iload #8
    //   623: invokeinterface get : (I)Ljava/lang/Object;
    //   628: checkcast yyds/sniarbtej/λ
    //   631: astore #10
    //   633: aload_0
    //   634: getfield ᴵʖ : Lyyds/sniarbtej/ـс;
    //   637: aload #10
    //   639: invokevirtual ᐨẏ : (Lyyds/sniarbtej/Ӏ;)I
    //   642: istore #9
    //   644: aload_0
    //   645: iload #9
    //   647: aload_3
    //   648: aload #6
    //   650: invokespecial ᐨẏ : (ILyyds/sniarbtej/ιՆ;Lyyds/sniarbtej/ᐧᎰ;)V
    //   653: iinc #8, 1
    //   656: goto -> 603
    //   659: goto -> 1170
    //   662: aload #7
    //   664: instanceof yyds/sniarbtej/יᔭ
    //   667: ifeq -> 760
    //   670: aload #7
    //   672: checkcast yyds/sniarbtej/יᔭ
    //   675: astore_1
    //   676: aload_0
    //   677: getfield ᴵʖ : Lyyds/sniarbtej/ـс;
    //   680: aload_1
    //   681: getfield ʿᵉ : Lyyds/sniarbtej/λ;
    //   684: invokevirtual ᐨẏ : (Lyyds/sniarbtej/Ӏ;)I
    //   687: istore #9
    //   689: aload_0
    //   690: iload #9
    //   692: aload_3
    //   693: aload #6
    //   695: invokespecial ᐨẏ : (ILyyds/sniarbtej/ιՆ;Lyyds/sniarbtej/ᐧᎰ;)V
    //   698: iconst_0
    //   699: istore #8
    //   701: iload #8
    //   703: aload_1
    //   704: getfield ﾞл : Ljava/util/List;
    //   707: invokeinterface size : ()I
    //   712: if_icmpge -> 757
    //   715: aload_1
    //   716: getfield ﾞл : Ljava/util/List;
    //   719: iload #8
    //   721: invokeinterface get : (I)Ljava/lang/Object;
    //   726: checkcast yyds/sniarbtej/λ
    //   729: astore #10
    //   731: aload_0
    //   732: getfield ᴵʖ : Lyyds/sniarbtej/ـс;
    //   735: aload #10
    //   737: invokevirtual ᐨẏ : (Lyyds/sniarbtej/Ӏ;)I
    //   740: istore #9
    //   742: aload_0
    //   743: iload #9
    //   745: aload_3
    //   746: aload #6
    //   748: invokespecial ᐨẏ : (ILyyds/sniarbtej/ιՆ;Lyyds/sniarbtej/ᐧᎰ;)V
    //   751: iinc #8, 1
    //   754: goto -> 701
    //   757: goto -> 1170
    //   760: iload #8
    //   762: sipush #169
    //   765: if_icmpne -> 1039
    //   768: aload #6
    //   770: ifnonnull -> 807
    //   773: new yyds/sniarbtej/ιƚ
    //   776: dup
    //   777: aload #7
    //   779: ldc '쐍￰褦జ깑퀠䫾ꬑ咖僭ी临뎙雞?뱥⩞奈ᘛЖῷ珆?㜃┐мꬁ亝⣐ꦛﯣꁊၠ慺?惜쏎㯵'
    //   781: invokevirtual toCharArray : ()[C
    //   784: dup
    //   785: dup
    //   786: iconst_1
    //   787: dup_x1
    //   788: caload
    //   789: sipush #17618
    //   792: ixor
    //   793: i2c
    //   794: castore
    //   795: sipush #20944
    //   798: iconst_3
    //   799: iconst_1
    //   800: invokestatic v : (Ljava/lang/Object;SIS)Ljava/lang/String;
    //   803: invokespecial <init> : (Lyyds/sniarbtej/Ӏ;Ljava/lang/String;)V
    //   806: athrow
    //   807: iconst_0
    //   808: istore_1
    //   809: iload_1
    //   810: aload #6
    //   812: getfield ʹл : Ljava/util/List;
    //   815: invokeinterface size : ()I
    //   820: if_icmpge -> 1036
    //   823: aload #6
    //   825: getfield ʹл : Ljava/util/List;
    //   828: iload_1
    //   829: invokeinterface get : (I)Ljava/lang/Object;
    //   834: checkcast yyds/sniarbtej/ʿশ
    //   837: astore #9
    //   839: aload_0
    //   840: getfield ᴵʖ : Lyyds/sniarbtej/ـс;
    //   843: aload #9
    //   845: invokevirtual ᐨẏ : (Lyyds/sniarbtej/Ӏ;)I
    //   848: istore #8
    //   850: aload_0
    //   851: getfield ᐨẏ : [Lyyds/sniarbtej/ιՆ;
    //   854: iload #8
    //   856: aaload
    //   857: ifnull -> 1030
    //   860: aload_0
    //   861: iload #8
    //   863: iconst_1
    //   864: iadd
    //   865: aload_0
    //   866: getfield ᐨẏ : [Lyyds/sniarbtej/ιՆ;
    //   869: iload #8
    //   871: aaload
    //   872: aload_3
    //   873: aload_0
    //   874: getfield ᐨẏ : [Lyyds/sniarbtej/ᐧᎰ;
    //   877: iload #8
    //   879: aaload
    //   880: aload #6
    //   882: getfield ˊ : [Z
    //   885: astore #10
    //   887: astore #9
    //   889: astore #8
    //   891: astore #13
    //   893: istore #12
    //   895: astore #11
    //   897: aload #8
    //   899: aload #13
    //   901: aload #10
    //   903: invokevirtual ᐨẏ : (Lyyds/sniarbtej/ιՆ;[Z)Z
    //   906: pop
    //   907: aload #11
    //   909: getfield ᐨẏ : [Lyyds/sniarbtej/ιՆ;
    //   912: iload #12
    //   914: aaload
    //   915: dup
    //   916: astore #10
    //   918: ifnonnull -> 940
    //   921: aload #11
    //   923: getfield ᐨẏ : [Lyyds/sniarbtej/ιՆ;
    //   926: iload #12
    //   928: aload #8
    //   930: invokestatic ᐨẏ : (Lyyds/sniarbtej/ιՆ;)Lyyds/sniarbtej/ιՆ;
    //   933: aastore
    //   934: iconst_1
    //   935: istore #8
    //   937: goto -> 954
    //   940: aload #10
    //   942: aload #8
    //   944: aload #11
    //   946: getfield ᐨẏ : Lyyds/sniarbtej/וּ;
    //   949: invokevirtual ᐨẏ : (Lyyds/sniarbtej/ιՆ;Lyyds/sniarbtej/וּ;)Z
    //   952: istore #8
    //   954: aload #11
    //   956: getfield ᐨẏ : [Lyyds/sniarbtej/ᐧᎰ;
    //   959: iload #12
    //   961: aaload
    //   962: dup
    //   963: astore #10
    //   965: ifnull -> 985
    //   968: aload #9
    //   970: ifnull -> 985
    //   973: iload #8
    //   975: aload #10
    //   977: aload #9
    //   979: invokevirtual ᐨẏ : (Lyyds/sniarbtej/ᐧᎰ;)Z
    //   982: ior
    //   983: istore #8
    //   985: iload #8
    //   987: ifeq -> 1030
    //   990: aload #11
    //   992: getfield ᐨẏ : [Z
    //   995: iload #12
    //   997: baload
    //   998: ifne -> 1030
    //   1001: aload #11
    //   1003: getfield ᐨẏ : [Z
    //   1006: iload #12
    //   1008: iconst_1
    //   1009: bastore
    //   1010: aload #11
    //   1012: getfield ˍ : [I
    //   1015: aload #11
    //   1017: dup
    //   1018: getfield ʹᓱ : I
    //   1021: dup_x1
    //   1022: iconst_1
    //   1023: iadd
    //   1024: putfield ʹᓱ : I
    //   1027: iload #12
    //   1029: iastore
    //   1030: iinc #1, 1
    //   1033: goto -> 809
    //   1036: goto -> 1170
    //   1039: iload #8
    //   1041: sipush #191
    //   1044: if_icmpeq -> 1170
    //   1047: iload #8
    //   1049: sipush #172
    //   1052: if_icmplt -> 1063
    //   1055: iload #8
    //   1057: sipush #177
    //   1060: if_icmple -> 1170
    //   1063: aload #6
    //   1065: ifnull -> 1159
    //   1068: aload #7
    //   1070: instanceof yyds/sniarbtej/ᕁ
    //   1073: ifeq -> 1134
    //   1076: aload #7
    //   1078: checkcast yyds/sniarbtej/ᕁ
    //   1081: getfield ՙﺙ : I
    //   1084: istore_1
    //   1085: aload #6
    //   1087: getfield ˊ : [Z
    //   1090: iload_1
    //   1091: iconst_1
    //   1092: bastore
    //   1093: iload #8
    //   1095: bipush #22
    //   1097: if_icmpeq -> 1121
    //   1100: iload #8
    //   1102: bipush #24
    //   1104: if_icmpeq -> 1121
    //   1107: iload #8
    //   1109: bipush #55
    //   1111: if_icmpeq -> 1121
    //   1114: iload #8
    //   1116: bipush #57
    //   1118: if_icmpne -> 1131
    //   1121: aload #6
    //   1123: getfield ˊ : [Z
    //   1126: iload_1
    //   1127: iconst_1
    //   1128: iadd
    //   1129: iconst_1
    //   1130: bastore
    //   1131: goto -> 1159
    //   1134: aload #7
    //   1136: instanceof yyds/sniarbtej/ۦ
    //   1139: ifeq -> 1159
    //   1142: aload #7
    //   1144: checkcast yyds/sniarbtej/ۦ
    //   1147: getfield ՙﺙ : I
    //   1150: istore_1
    //   1151: aload #6
    //   1153: getfield ˊ : [Z
    //   1156: iload_1
    //   1157: iconst_1
    //   1158: bastore
    //   1159: aload_0
    //   1160: iload #4
    //   1162: iconst_1
    //   1163: iadd
    //   1164: aload_3
    //   1165: aload #6
    //   1167: invokespecial ᐨẏ : (ILyyds/sniarbtej/ιՆ;Lyyds/sniarbtej/ᐧᎰ;)V
    //   1170: aload_0
    //   1171: getfield ᴵʖ : [Ljava/util/List;
    //   1174: iload #4
    //   1176: aaload
    //   1177: dup
    //   1178: astore_1
    //   1179: ifnull -> 1383
    //   1182: aload_1
    //   1183: invokeinterface iterator : ()Ljava/util/Iterator;
    //   1188: astore #9
    //   1190: aload #9
    //   1192: invokeinterface hasNext : ()Z
    //   1197: ifeq -> 1383
    //   1200: aload #9
    //   1202: invokeinterface next : ()Ljava/lang/Object;
    //   1207: checkcast yyds/sniarbtej/ˌț
    //   1210: dup
    //   1211: astore #8
    //   1213: getfield ᐨẏ : Ljava/lang/String;
    //   1216: ifnonnull -> 1251
    //   1219: ldc '꜀蝫䑕혼丸䫁弢手䂳傉ᣇ贒꿲輪벮냖蟍䬝'
    //   1221: invokevirtual toCharArray : ()[C
    //   1224: dup
    //   1225: dup
    //   1226: iconst_1
    //   1227: dup_x1
    //   1228: caload
    //   1229: sipush #759
    //   1232: ixor
    //   1233: i2c
    //   1234: castore
    //   1235: sipush #16724
    //   1238: iconst_5
    //   1239: iconst_4
    //   1240: invokestatic v : (Ljava/lang/Object;SIS)Ljava/lang/String;
    //   1243: invokestatic ˊ : (Ljava/lang/String;)Lyyds/sniarbtej/ˑܘ;
    //   1246: astore #10
    //   1248: goto -> 1261
    //   1251: aload #8
    //   1253: getfield ᐨẏ : Ljava/lang/String;
    //   1256: invokestatic ˊ : (Ljava/lang/String;)Lyyds/sniarbtej/ˑܘ;
    //   1259: astore #10
    //   1261: aload_0
    //   1262: iload #4
    //   1264: aload #8
    //   1266: astore #13
    //   1268: istore #12
    //   1270: dup
    //   1271: astore #11
    //   1273: getfield ᴵʖ : Lyyds/sniarbtej/ـс;
    //   1276: aload #13
    //   1278: getfield ʹﮃ : Lyyds/sniarbtej/λ;
    //   1281: invokevirtual ᐨẏ : (Lyyds/sniarbtej/Ӏ;)I
    //   1284: pop
    //   1285: aload #5
    //   1287: invokestatic ᐨẏ : (Lyyds/sniarbtej/ιՆ;)Lyyds/sniarbtej/ιՆ;
    //   1290: astore_1
    //   1291: aload_0
    //   1292: getfield ᐨẏ : Lyyds/sniarbtej/וּ;
    //   1295: aload #10
    //   1297: astore #10
    //   1299: dup
    //   1300: astore #11
    //   1302: aload #10
    //   1304: invokevirtual ᐨẏ : (Lyyds/sniarbtej/ˑܘ;)Lyyds/sniarbtej/ן;
    //   1307: astore #10
    //   1309: aload_1
    //   1310: dup
    //   1311: astore #11
    //   1313: iconst_0
    //   1314: putfield ᐝᒰ : I
    //   1317: aload_1
    //   1318: aload #10
    //   1320: invokevirtual ˊ : (Lyyds/sniarbtej/ן;)V
    //   1323: aload_0
    //   1324: dup
    //   1325: getfield ᴵʖ : Lyyds/sniarbtej/ـс;
    //   1328: aload #8
    //   1330: getfield ʹﮃ : Lyyds/sniarbtej/λ;
    //   1333: invokevirtual ᐨẏ : (Lyyds/sniarbtej/Ӏ;)I
    //   1336: aload_1
    //   1337: aload #6
    //   1339: invokespecial ᐨẏ : (ILyyds/sniarbtej/ιՆ;Lyyds/sniarbtej/ᐧᎰ;)V
    //   1342: aload_3
    //   1343: invokestatic ᐨẏ : (Lyyds/sniarbtej/ιՆ;)Lyyds/sniarbtej/ιՆ;
    //   1346: dup
    //   1347: astore_1
    //   1348: dup
    //   1349: astore #11
    //   1351: iconst_0
    //   1352: putfield ᐝᒰ : I
    //   1355: aload_1
    //   1356: aload #10
    //   1358: invokevirtual ˊ : (Lyyds/sniarbtej/ן;)V
    //   1361: aload_0
    //   1362: dup
    //   1363: getfield ᴵʖ : Lyyds/sniarbtej/ـс;
    //   1366: aload #8
    //   1368: getfield ʹﮃ : Lyyds/sniarbtej/λ;
    //   1371: invokevirtual ᐨẏ : (Lyyds/sniarbtej/Ӏ;)I
    //   1374: aload_1
    //   1375: aload #6
    //   1377: invokespecial ᐨẏ : (ILyyds/sniarbtej/ιՆ;Lyyds/sniarbtej/ᐧᎰ;)V
    //   1380: goto -> 1190
    //   1383: goto -> 319
    //   1386: astore #8
    //   1388: new yyds/sniarbtej/ιƚ
    //   1391: dup
    //   1392: aload #8
    //   1394: getfield ʹﮃ : Lyyds/sniarbtej/Ӏ;
    //   1397: new java/lang/StringBuilder
    //   1400: dup
    //   1401: ldc_w '㮉ꈻ㽘偋饶ꔗ駛긕節Ӫ蒹ฮ税伩扳졚ᇻ朊쌻虴਋'
    //   1404: invokevirtual toCharArray : ()[C
    //   1407: dup
    //   1408: dup
    //   1409: bipush #11
    //   1411: dup_x1
    //   1412: caload
    //   1413: sipush #5232
    //   1416: ixor
    //   1417: i2c
    //   1418: castore
    //   1419: sipush #12100
    //   1422: iconst_0
    //   1423: iconst_4
    //   1424: invokestatic v : (Ljava/lang/Object;SIS)Ljava/lang/String;
    //   1427: invokespecial <init> : (Ljava/lang/String;)V
    //   1430: iload #4
    //   1432: invokevirtual append : (I)Ljava/lang/StringBuilder;
    //   1435: ldc_w 'ટ剀ቺ'
    //   1438: invokevirtual toCharArray : ()[C
    //   1441: dup
    //   1442: dup
    //   1443: iconst_1
    //   1444: dup_x1
    //   1445: caload
    //   1446: sipush #11315
    //   1449: ixor
    //   1450: i2c
    //   1451: castore
    //   1452: sipush #10203
    //   1455: iconst_2
    //   1456: iconst_2
    //   1457: invokestatic v : (Ljava/lang/Object;SIS)Ljava/lang/String;
    //   1460: invokevirtual append : (Ljava/lang/String;)Ljava/lang/StringBuilder;
    //   1463: aload #8
    //   1465: invokevirtual getMessage : ()Ljava/lang/String;
    //   1468: invokevirtual append : (Ljava/lang/String;)Ljava/lang/StringBuilder;
    //   1471: invokevirtual toString : ()Ljava/lang/String;
    //   1474: aload #8
    //   1476: invokespecial <init> : (Lyyds/sniarbtej/Ӏ;Ljava/lang/String;Ljava/lang/Throwable;)V
    //   1479: athrow
    //   1480: astore #8
    //   1482: new yyds/sniarbtej/ιƚ
    //   1485: dup
    //   1486: aload #7
    //   1488: new java/lang/StringBuilder
    //   1491: dup
    //   1492: ldc_w 'ᖒ野䁃强௝?䩃꯻藎ｐ飆舅̦଱묭ⷋ咱拭祉딫狔'
    //   1495: invokevirtual toCharArray : ()[C
    //   1498: dup
    //   1499: dup
    //   1500: iconst_3
    //   1501: dup_x1
    //   1502: caload
    //   1503: sipush #31218
    //   1506: ixor
    //   1507: i2c
    //   1508: castore
    //   1509: sipush #10863
    //   1512: iconst_5
    //   1513: iconst_5
    //   1514: invokestatic v : (Ljava/lang/Object;SIS)Ljava/lang/String;
    //   1517: invokespecial <init> : (Ljava/lang/String;)V
    //   1520: iload #4
    //   1522: invokevirtual append : (I)Ljava/lang/StringBuilder;
    //   1525: ldc_w '褬爷'
    //   1528: invokevirtual toCharArray : ()[C
    //   1531: dup
    //   1532: dup
    //   1533: iconst_1
    //   1534: dup_x1
    //   1535: caload
    //   1536: sipush #13548
    //   1539: ixor
    //   1540: i2c
    //   1541: castore
    //   1542: sipush #31879
    //   1545: iconst_4
    //   1546: iconst_1
    //   1547: invokestatic v : (Ljava/lang/Object;SIS)Ljava/lang/String;
    //   1550: invokevirtual append : (Ljava/lang/String;)Ljava/lang/StringBuilder;
    //   1553: aload #8
    //   1555: invokevirtual getMessage : ()Ljava/lang/String;
    //   1558: invokevirtual append : (Ljava/lang/String;)Ljava/lang/StringBuilder;
    //   1561: invokevirtual toString : ()Ljava/lang/String;
    //   1564: aload #8
    //   1566: invokespecial <init> : (Lyyds/sniarbtej/Ӏ;Ljava/lang/String;Ljava/lang/Throwable;)V
    //   1569: athrow
    //   1570: aload_0
    //   1571: getfield ᐨẏ : [Lyyds/sniarbtej/ιՆ;
    //   1574: areturn
    // Exception table:
    //   from	to	target	type
    //   234	254	257	java/lang/RuntimeException
    //   373	1383	1386	yyds/sniarbtej/ιƚ
    //   373	1383	1480	java/lang/RuntimeException
  }
  
  public final ιՆ<V>[] ˊ(String paramString, ᐧє paramᐧє) {
    // Byte code:
    //   0: aload_2
    //   1: dup
    //   2: dup
    //   3: astore_3
    //   4: getfield ˎᴗ : Ljava/lang/String;
    //   7: invokestatic ᐨم : (Ljava/lang/String;)I
    //   10: iconst_2
    //   11: ishr
    //   12: istore #4
    //   14: aload_3
    //   15: getfield ᒬ : I
    //   18: bipush #8
    //   20: iand
    //   21: ifeq -> 27
    //   24: iinc #4, -1
    //   27: aload_3
    //   28: getfield ˊ : Lyyds/sniarbtej/ـс;
    //   31: invokevirtual ᐨẏ : ()Ljava/util/ListIterator;
    //   34: astore_3
    //   35: aload_3
    //   36: invokeinterface hasNext : ()Z
    //   41: ifeq -> 166
    //   44: aload_3
    //   45: invokeinterface next : ()Ljava/lang/Object;
    //   50: checkcast yyds/sniarbtej/Ӏ
    //   53: dup
    //   54: astore #5
    //   56: instanceof yyds/sniarbtej/ᕁ
    //   59: ifeq -> 134
    //   62: aload #5
    //   64: checkcast yyds/sniarbtej/ᕁ
    //   67: getfield ՙﺙ : I
    //   70: istore #6
    //   72: aload #5
    //   74: invokevirtual ˈהּ : ()I
    //   77: bipush #22
    //   79: if_icmpeq -> 112
    //   82: aload #5
    //   84: invokevirtual ˈהּ : ()I
    //   87: bipush #24
    //   89: if_icmpeq -> 112
    //   92: aload #5
    //   94: invokevirtual ˈהּ : ()I
    //   97: bipush #55
    //   99: if_icmpeq -> 112
    //   102: aload #5
    //   104: invokevirtual ˈהּ : ()I
    //   107: bipush #57
    //   109: if_icmpne -> 116
    //   112: iconst_2
    //   113: goto -> 117
    //   116: iconst_1
    //   117: istore #7
    //   119: iload #4
    //   121: iload #6
    //   123: iload #7
    //   125: iadd
    //   126: invokestatic max : (II)I
    //   129: istore #4
    //   131: goto -> 35
    //   134: aload #5
    //   136: instanceof yyds/sniarbtej/ۦ
    //   139: ifeq -> 163
    //   142: aload #5
    //   144: checkcast yyds/sniarbtej/ۦ
    //   147: getfield ՙﺙ : I
    //   150: istore #6
    //   152: iload #4
    //   154: iload #6
    //   156: iconst_1
    //   157: iadd
    //   158: invokestatic max : (II)I
    //   161: istore #4
    //   163: goto -> 35
    //   166: iload #4
    //   168: putfield ˌپ : I
    //   171: aload_2
    //   172: iconst_m1
    //   173: putfield ˑỲ : I
    //   176: aload_0
    //   177: aload_1
    //   178: aload_2
    //   179: invokevirtual ᐨẏ : (Ljava/lang/String;Lyyds/sniarbtej/ᐧє;)[Lyyds/sniarbtej/ιՆ;
    //   182: pop
    //   183: aload_2
    //   184: aload_0
    //   185: getfield ᐨẏ : [Lyyds/sniarbtej/ιՆ;
    //   188: astore_3
    //   189: iconst_0
    //   190: istore #4
    //   192: aload_3
    //   193: dup
    //   194: astore_3
    //   195: arraylength
    //   196: istore #5
    //   198: iconst_0
    //   199: istore #6
    //   201: iload #6
    //   203: iload #5
    //   205: if_icmpge -> 268
    //   208: aload_3
    //   209: iload #6
    //   211: aaload
    //   212: dup
    //   213: astore #7
    //   215: ifnull -> 262
    //   218: iconst_0
    //   219: istore_1
    //   220: iconst_0
    //   221: istore_2
    //   222: iload_2
    //   223: aload #7
    //   225: dup
    //   226: astore #8
    //   228: getfield ᐝᒰ : I
    //   231: if_icmpge -> 254
    //   234: iload_1
    //   235: aload #7
    //   237: iload_2
    //   238: invokevirtual ˊ : (I)Lyyds/sniarbtej/ן;
    //   241: invokeinterface ˍɫ : ()I
    //   246: iadd
    //   247: istore_1
    //   248: iinc #2, 1
    //   251: goto -> 222
    //   254: iload #4
    //   256: iload_1
    //   257: invokestatic max : (II)I
    //   260: istore #4
    //   262: iinc #6, 1
    //   265: goto -> 201
    //   268: iload #4
    //   270: putfield ˑỲ : I
    //   273: aload_0
    //   274: getfield ᐨẏ : [Lyyds/sniarbtej/ιՆ;
    //   277: areturn
  }
  
  private static int ᐨẏ(ᐧє paramᐧє) {
    int i = ˑܘ.ᐨم(paramᐧє.ˎᴗ) >> 2;
    if ((paramᐧє.ᒬ & 0x8) != 0)
      i--; 
    ListIterator<Ӏ> listIterator = paramᐧє.ˊ.ᐨẏ();
    while (listIterator.hasNext()) {
      byte b;
      Ӏ ӏ;
      if (ӏ = listIterator.next() instanceof ᕁ) {
        int j = ((ᕁ)ӏ).ՙﺙ;
        b = (ӏ.ˈהּ() == 22 || ӏ.ˈהּ() == 24 || ӏ.ˈהּ() == 55 || ӏ.ˈהּ() == 57) ? 2 : 1;
        i = Math.max(i, j + b);
        continue;
      } 
      if (b instanceof ۦ) {
        int j = ((ۦ)b).ՙﺙ;
        i = Math.max(i, j + 1);
      } 
    } 
    return i;
  }
  
  private static int ᐨẏ(ιՆ<?>[] paramArrayOfιՆ) {
    int i = 0;
    int j = (paramArrayOfιՆ = paramArrayOfιՆ).length;
    for (byte b = 0; b < j; b++) {
      ιՆ<?> ιՆ1;
      if ((ιՆ1 = paramArrayOfιՆ[b]) != null) {
        int k = 0;
        ιՆ<?> ιՆ2;
        for (byte b1 = 0; b1 < (ιՆ2 = ιՆ1).ᐝᒰ; b1++)
          k += ιՆ1.ˊ(b1).ˍɫ(); 
        i = Math.max(i, k);
      } 
    } 
    return i;
  }
  
  private void ˌ(int paramInt) {
    ᐧᎰ ᐧᎰ1 = new ᐧᎰ(null, paramInt, null);
    ArrayList<Ӏ> arrayList = new ArrayList();
    ᐨẏ(0, ᐧᎰ1, arrayList);
    HashMap<Object, Object> hashMap = new HashMap<>();
    while (!arrayList.isEmpty()) {
      ʿশ ʿশ = (ʿশ)arrayList.remove(0);
      ᐧᎰ ᐧᎰ2;
      if ((ᐧᎰ2 = (ᐧᎰ)hashMap.get(ʿশ.ˊ)) == null) {
        ᐧᎰ2 = new ᐧᎰ(ʿশ.ˊ, paramInt, ʿশ);
        hashMap.put(ʿশ.ˊ, ᐧᎰ2);
        ᐨẏ(this.ᴵʖ.ᐨẏ(ʿশ.ˊ), ᐧᎰ2, arrayList);
        continue;
      } 
      ᐧᎰ2.ʹл.add(ʿশ);
    } 
    for (byte b = 0; b < this.ﾞڔ; b++) {
      if (this.ᐨẏ[b] != null && (this.ᐨẏ[b]).ᴵʖ == null)
        this.ᐨẏ[b] = null; 
    } 
  }
  
  private void ᐨẏ(int paramInt, ᐧᎰ paramᐧᎰ, List<Ӏ> paramList) {
    ArrayList<Integer> arrayList;
    (arrayList = new ArrayList<>()).add(Integer.valueOf(paramInt));
    while (!arrayList.isEmpty()) {
      if ((paramInt = ((Integer)arrayList.remove(arrayList.size() - 1)).intValue()) < 0 || paramInt >= this.ﾞڔ) {
        "섹쁢⚱矹—ಽ秼힭쪣䒈壱ᕴ⠍뿮?譿軲繪迅먜蛤괜᧔赶僐ﾼ㹰懘쓲ⴗ殼쾓鉵鏭꺞䖠뜵诧←".toCharArray()[9] = (char)("섹쁢⚱矹—ಽ秼힭쪣䒈壱ᕴ⠍뿮?譿軲繪迅먜蛤괜᧔赶僐ﾼ㹰懘쓲ⴗ殼쾓鉵鏭꺞䖠뜵诧←".toCharArray()[9] ^ 0x45BE);
        throw new ιƚ(null, ᐨẏ$ᐝт.W("섹쁢⚱矹—ಽ秼힭쪣䒈壱ᕴ⠍뿮?譿軲繪迅먜蛤괜᧔赶僐ﾼ㹰懘쓲ⴗ殼쾓鉵鏭꺞䖠뜵诧←".toCharArray(), (short)30821, (byte)1, (short)5));
      } 
      if (this.ᐨẏ[paramInt] == null) {
        this.ᐨẏ[paramInt] = new ᐧᎰ(paramᐧᎰ);
        Ӏ ӏ;
        if (ӏ = this.ᴵʖ.ᐨẏ(paramInt) instanceof ʿশ) {
          if (ӏ.ˈהּ() == 168) {
            paramList.add(ӏ);
          } else {
            ʿশ ʿশ = (ʿশ)ӏ;
            arrayList.add(Integer.valueOf(this.ᴵʖ.ᐨẏ(ʿশ.ˊ)));
          } 
        } else if (ӏ instanceof יᔭ) {
          יᔭ יᔭ = (יᔭ)ӏ;
          ᐨẏ(this.ᴵʖ.ᐨẏ(יᔭ.ʿᵉ), paramᐧᎰ, paramList);
          for (int i = יᔭ.ﾞл.size() - 1; i >= 0; i--) {
            λ λ = יᔭ.ﾞл.get(i);
            arrayList.add(Integer.valueOf(this.ᴵʖ.ᐨẏ(λ)));
          } 
        } else if (ӏ instanceof ﹳڐ) {
          ﹳڐ ﹳڐ = (ﹳڐ)ӏ;
          ᐨẏ(this.ᴵʖ.ᐨẏ(ﹳڐ.ʿᵉ), paramᐧᎰ, paramList);
          for (int i = ﹳڐ.ﾞл.size() - 1; i >= 0; i--) {
            λ λ = ﹳڐ.ﾞл.get(i);
            arrayList.add(Integer.valueOf(this.ᴵʖ.ᐨẏ(λ)));
          } 
        } 
        List<ˌț> list;
        if ((list = this.ᴵʖ[paramInt]) != null)
          for (ˌț ˌț : list)
            arrayList.add(Integer.valueOf(this.ᴵʖ.ᐨẏ(ˌț.ʹﮃ)));  
        switch (ӏ.ˈהּ()) {
          case 167:
          case 169:
          case 170:
          case 171:
          case 172:
          case 173:
          case 174:
          case 175:
          case 176:
          case 177:
          case 191:
            continue;
        } 
        arrayList.add(Integer.valueOf(paramInt + 1));
      } 
    } 
  }
  
  private ιՆ<V> ᐨẏ(String paramString, ᐧє paramᐧє) {
    int j = paramᐧє.ˑỲ;
    int i = paramᐧє.ˌپ;
    ιՆ<ן> ιՆ1 = new ιՆ<>(i, j);
    i = 0;
    if ((j = ((paramᐧє.ᒬ & 0x8) == 0) ? 1 : 0) != 0) {
      ˑܘ ˑܘ1 = ˑܘ.ˊ(paramString);
      ˑܘ ˑܘ2 = ˑܘ1;
      boolean[] arrayOfBoolean1;
      ιՆ1.ᐨẏ(0, (arrayOfBoolean1 = this.ᐨẏ).ᐨẏ(ˑܘ2));
      i++;
    } 
    ˑܘ[] arrayOfˑܘ;
    j = (arrayOfˑܘ = arrayOfˑܘ = ˑܘ.ᐨẏ(paramᐧє.ˎᴗ)).length;
    for (byte b = 0; b < j; b++) {
      ˑܘ ˑܘ1 = arrayOfˑܘ[b];
      ˑܘ ˑܘ2 = ˑܘ1;
      boolean[] arrayOfBoolean1;
      ιՆ1.ᐨẏ(i, (arrayOfBoolean1 = this.ᐨẏ).ᐨẏ(ˑܘ2));
      i++;
      if (ˑܘ1.ˍɫ() == 2) {
        ιՆ1.ᐨẏ(i, (arrayOfBoolean1 = this.ᐨẏ).ᐨẏ((ˑܘ)null));
        i++;
      } 
    } 
    while (i < paramᐧє.ˌپ) {
      boolean[] arrayOfBoolean1;
      ιՆ1.ᐨẏ(i, (arrayOfBoolean1 = this.ᐨẏ).ᐨẏ((ˑܘ)null));
      i++;
    } 
    ˑܘ ˑܘ = ˑܘ.ﾞл(paramᐧє.ˎᴗ);
    boolean[] arrayOfBoolean;
    ˑܘ = (arrayOfBoolean = this.ᐨẏ).ᐨẏ(ˑܘ);
    ιՆ<ן> ιՆ2;
    (ιՆ2 = ιՆ1).ᐨẏ = (V[])ˑܘ;
    return (ιՆ)ιՆ1;
  }
  
  public final ιՆ<V>[] ᐨẏ() {
    return (ιՆ<V>[])this.ᐨẏ;
  }
  
  public final List<ˌț> ˊ(int paramInt) {
    return this.ᴵʖ[paramInt];
  }
  
  protected void ᐨẏ(String paramString, ᐧє paramᐧє) {}
  
  private static ιՆ<V> ᐨẏ(int paramInt1, int paramInt2) {
    return (ιՆ)new ιՆ<>(paramInt1, paramInt2);
  }
  
  protected static ιՆ<V> ᐨẏ(ιՆ<? extends V> paramιՆ) {
    return (ιՆ)new ιՆ<>((ιՆ)paramιՆ);
  }
  
  protected static void ˎאּ() {}
  
  private static boolean ʽ() {
    return true;
  }
  
  private boolean ᐨẏ(int paramInt, ˌț paramˌț) {
    this.ᴵʖ.ᐨẏ(paramˌț.ʹﮃ);
    return true;
  }
  
  private void ᐨẏ(int paramInt, ιՆ<V> paramιՆ, ᐧᎰ paramᐧᎰ) {
    // Byte code:
    //   0: aload_0
    //   1: getfield ᐨẏ : [Lyyds/sniarbtej/ιՆ;
    //   4: iload_1
    //   5: aaload
    //   6: dup
    //   7: astore #4
    //   9: ifnonnull -> 27
    //   12: aload_0
    //   13: getfield ᐨẏ : [Lyyds/sniarbtej/ιՆ;
    //   16: iload_1
    //   17: aload_2
    //   18: invokestatic ᐨẏ : (Lyyds/sniarbtej/ιՆ;)Lyyds/sniarbtej/ιՆ;
    //   21: aastore
    //   22: iconst_1
    //   23: istore_2
    //   24: goto -> 38
    //   27: aload #4
    //   29: aload_2
    //   30: aload_0
    //   31: getfield ᐨẏ : Lyyds/sniarbtej/וּ;
    //   34: invokevirtual ᐨẏ : (Lyyds/sniarbtej/ιՆ;Lyyds/sniarbtej/וּ;)Z
    //   37: istore_2
    //   38: aload_0
    //   39: getfield ᐨẏ : [Lyyds/sniarbtej/ᐧᎰ;
    //   42: iload_1
    //   43: aaload
    //   44: dup
    //   45: astore #4
    //   47: ifnonnull -> 73
    //   50: aload_3
    //   51: ifnull -> 86
    //   54: aload_0
    //   55: getfield ᐨẏ : [Lyyds/sniarbtej/ᐧᎰ;
    //   58: iload_1
    //   59: new yyds/sniarbtej/ᐧᎰ
    //   62: dup
    //   63: aload_3
    //   64: invokespecial <init> : (Lyyds/sniarbtej/ᐧᎰ;)V
    //   67: aastore
    //   68: iconst_1
    //   69: istore_2
    //   70: goto -> 86
    //   73: aload_3
    //   74: ifnull -> 86
    //   77: iload_2
    //   78: aload #4
    //   80: aload_3
    //   81: invokevirtual ᐨẏ : (Lyyds/sniarbtej/ᐧᎰ;)Z
    //   84: ior
    //   85: istore_2
    //   86: iload_2
    //   87: ifeq -> 123
    //   90: aload_0
    //   91: getfield ᐨẏ : [Z
    //   94: iload_1
    //   95: baload
    //   96: ifne -> 123
    //   99: aload_0
    //   100: getfield ᐨẏ : [Z
    //   103: iload_1
    //   104: iconst_1
    //   105: bastore
    //   106: aload_0
    //   107: getfield ˍ : [I
    //   110: aload_0
    //   111: dup
    //   112: getfield ʹᓱ : I
    //   115: dup_x1
    //   116: iconst_1
    //   117: iadd
    //   118: putfield ʹᓱ : I
    //   121: iload_1
    //   122: iastore
    //   123: return
  }
  
  private void ᐨẏ(int paramInt, ιՆ<V> paramιՆ1, ιՆ<V> paramιՆ2, ᐧᎰ paramᐧᎰ, boolean[] paramArrayOfboolean) {
    // Byte code:
    //   0: aload_3
    //   1: aload_2
    //   2: aload #5
    //   4: invokevirtual ᐨẏ : (Lyyds/sniarbtej/ιՆ;[Z)Z
    //   7: pop
    //   8: aload_0
    //   9: getfield ᐨẏ : [Lyyds/sniarbtej/ιՆ;
    //   12: iload_1
    //   13: aaload
    //   14: dup
    //   15: astore_2
    //   16: ifnonnull -> 34
    //   19: aload_0
    //   20: getfield ᐨẏ : [Lyyds/sniarbtej/ιՆ;
    //   23: iload_1
    //   24: aload_3
    //   25: invokestatic ᐨẏ : (Lyyds/sniarbtej/ιՆ;)Lyyds/sniarbtej/ιՆ;
    //   28: aastore
    //   29: iconst_1
    //   30: istore_2
    //   31: goto -> 44
    //   34: aload_2
    //   35: aload_3
    //   36: aload_0
    //   37: getfield ᐨẏ : Lyyds/sniarbtej/וּ;
    //   40: invokevirtual ᐨẏ : (Lyyds/sniarbtej/ιՆ;Lyyds/sniarbtej/וּ;)Z
    //   43: istore_2
    //   44: aload_0
    //   45: getfield ᐨẏ : [Lyyds/sniarbtej/ᐧᎰ;
    //   48: iload_1
    //   49: aaload
    //   50: dup
    //   51: astore_3
    //   52: ifnull -> 69
    //   55: aload #4
    //   57: ifnull -> 69
    //   60: iload_2
    //   61: aload_3
    //   62: aload #4
    //   64: invokevirtual ᐨẏ : (Lyyds/sniarbtej/ᐧᎰ;)Z
    //   67: ior
    //   68: istore_2
    //   69: iload_2
    //   70: ifeq -> 106
    //   73: aload_0
    //   74: getfield ᐨẏ : [Z
    //   77: iload_1
    //   78: baload
    //   79: ifne -> 106
    //   82: aload_0
    //   83: getfield ᐨẏ : [Z
    //   86: iload_1
    //   87: iconst_1
    //   88: bastore
    //   89: aload_0
    //   90: getfield ˍ : [I
    //   93: aload_0
    //   94: dup
    //   95: getfield ʹᓱ : I
    //   98: dup_x1
    //   99: iconst_1
    //   100: iadd
    //   101: putfield ʹᓱ : I
    //   104: iload_1
    //   105: iastore
    //   106: return
  }
}


/* Location:              C:\Users\kb\Downloads\ja-netfilter.jar!\yyds\sniarbtej\ιᒶ.class
 * Java compiler version: 8 (52.0)
 * JD-Core Version:       1.1.3
 */